Workbook

Sheet Cover
A1: 02 — Market Sizing: U.S. Vertical Opportunity for Clay
A2: Independent portfolio case study by Zhuoran (Zora) Wang · Not commissioned by or affiliated with Clay Labs Inc. · Research reference date: 2026-10-18
A4: Purpose | B4: Size and compare three candidate U.S. verticals bottom-up (unique firms × annual contract value), with explicit TAM / SAM / SOM definitions and sensitivity ranges.
A5: TAM | B5: Annual revenue if every in-scope firm (20+ employees, segment NAICS) bought Clay at the size-band ACV. A theoretical ceiling, not a forecast.
A6: SAM | B6: TAM firms filtered to those with (1) an active B2B outbound / territory sales motion and (2) a CRM/data stack Clay can integrate with today (Growth tier and above).
A7: SOM | B7: Year-3 ARR potential from SAM firms at a uniform 'fair-share' penetration rate. Phase 1 deliberately applies the SAME penetration to every segment; segment-specific right-to-win is assessed in Phases 2–3.
A8: Unit of analysis | B8: Unique FIRMS (enterprises), never establishments. Firm counts are de-duplicated across sub-industries using Census-measured overlap (see Firm_Counts).
A9: Primary data | B9: 2022 Economic Census — Establishment & Firm Size Statistics, Employment Size of Firms (EC2200SIZEEMPFIRM); BLS OEWS May 2025 industry-specific estimates. See Sources.
A10: Not a forecast | B10: Nothing here is a Clay forecast or uses Clay internal data. ACV, readiness and penetration inputs are labeled benchmarks [B] or scenario assumptions [D].
A11: Color legend | B11: Blue text = hardcoded input · Black = formula · Green = formula linking another tab · Yellow fill = key judgment-based assumption.
A12: Evidence classes | B12: A = verified public fact · B = external benchmark / third-party estimate · C = analyst estimate (derived) · D = scenario assumption · E = recommendation.
A13: Tabs | B13: Executive_Summary → Assumptions → Firm_Counts → Segment_Profile → TAM_SAM_SOM → Sensitivity → Hypothesis_Tests → Segment_Defs → Raw_Census → Raw_OEWS → Sources

Sheet Executive_Summary
A1: Executive summary — Phase 1 market sizing (Base case unless noted)
A2: All $ are annual. SOM = year-3 ARR potential at uniform fair-share penetration (scenario output, not a forecast). Segments are alternatives; do not add them.
A4: Metric | B4: A. Industrial Distribution | C4: B. Industrial Manufacturing | D4: C. B2B Professional Services | E4: Unit / class
A5: Unique firms, 20+ employees | B5: =Firm_Counts!D61 -> 11493.544 | C5: =Firm_Counts!E61 -> 23784.588 | D5: =Firm_Counts!F61 -> 33035.014 | E5: firms · [C] from [A]
A6: of which SMB (20–99) | B6: =Firm_Counts!D58 -> 9106.2022 | C6: =Firm_Counts!E58 -> 18442.232 | D6: =Firm_Counts!F58 -> 26020.542 | E6: firms
A7: of which Mid-Market (100–499) | B7: =Firm_Counts!D59 -> 2011.3421 | C7: =Firm_Counts!E59 -> 4448.9884 | D7: =Firm_Counts!F59 -> 5775.4045 | E7: firms
A8: of which Enterprise (500+) | B8: =Firm_Counts!D60 -> 376 | C8: =Firm_Counts!E60 -> 893.36787 | D8: =Firm_Counts!F60 -> 1239.0676 | E8: firms
A9: TAM (Base) | B9: =TAM_SAM_SOM!E9 -> 1.3108336e+08 | C9: =TAM_SAM_SOM!E13 -> 2.8089858e+08 | D9: =TAM_SAM_SOM!E17 -> 3.8500621e+08 | E9: $/yr · [C]/[D]
A10: SAM (Base) | B10: =TAM_SAM_SOM!I9 -> 68163347 | C10: =TAM_SAM_SOM!I13 -> 75842617 | D10: =TAM_SAM_SOM!I17 -> 1.4822739e+08 | E10: $/yr · [C]/[D]
A11: SOM — year-3 ARR potential (Base) | B11: =TAM_SAM_SOM!L9 -> 1864123.6 | C11: =TAM_SAM_SOM!L13 -> 2149272.5 | D11: =TAM_SAM_SOM!L17 -> 4178480.9 | E11: $/yr · [D]
A12: SOM range — compounded Low | B12: =TAM_SAM_SOM!L26 -> 240197.34 | C12: =TAM_SAM_SOM!L30 -> 211060.82 | D12: =TAM_SAM_SOM!L34 -> 469215.74 | E12: $/yr · outer bound
A13: SOM range — compounded High | B13: =TAM_SAM_SOM!L43 -> 8834852.7 | C13: =TAM_SAM_SOM!L47 -> 12980959 | D13: =TAM_SAM_SOM!L51 -> 23406300 | E13: $/yr · outer bound
A14: SOM customers, year 3 (Base) | B14: =TAM_SAM_SOM!K9 -> 114.13651 | C14: =TAM_SAM_SOM!K13 -> 125.20041 | D14: =TAM_SAM_SOM!K17 -> 245.59701 | E14: customers · [D]
A15: SAM as % of TAM | B15: =B10/B9 -> 0.52 | C15: =C10/C9 -> 0.27 | D15: =D10/D9 -> 0.385 | E15: % · [D]
A17: Structural profile
A18: Sales occupations share of employment (all industries ≈ 8.6%) | B18: =Segment_Profile!B13 -> 0.2195913 | C18: =Segment_Profile!C13 -> 0.027389137 | D18: =Segment_Profile!D13 -> 0.061716312 | E18: % · [C] from OEWS
A19: Computer & math occupations share (all industries ≈ 3.4%) | B19: =Segment_Profile!B18 -> 0.023270103 | C19: =Segment_Profile!C18 -> 0.015371036 | D19: =Segment_Profile!D18 -> 0.24190733 | E19: % · [C] from OEWS
A20: Implied sales staff per 20+ firm | B20: =Segment_Profile!B19 -> 27.700087 | C20: =Segment_Profile!C19 -> 3.6494993 | D20: =Segment_Profile!D19 -> 9.3223336 | E20: people · [C]
A22: Sanity checks
A23: Clay customers reported (Sep 2026, S03) — for scale | B23: 17000 | E23: customers · [A*]
A24: Base SOM customers as % of Clay's total customer count | B24: =B14/$B$23 -> 0.0067139126 | C24: =C14/$B$23 -> 0.0073647297 | D24: =D14/$B$23 -> 0.014446883 | E24: % · [C]
A25: Clay ARR, third-party estimate (Sep 2026, S23; was ~$150M in May 2026, S04) — for scale | B25: 200000000 | E25: $/yr · [B] estimate
A26: Base SOM ARR as % of Clay's estimated ARR | B26: =B11/$B$25 -> 0.0093206179 | C26: =C11/$B$25 -> 0.010746362 | D26: =D11/$B$25 -> 0.020892405 | E26: % · [C] (H8 context)
A28: Key takeaways (Phase 1)
A29: 1. Industrial distribution is the smallest segment by firm count (H2 rejected): professional services offers nearly 3× the 20+ firm universe and the largest TAM, SAM and SOM at equal ACV and penetration.
A30: 2. Distribution is the most sales-intensive vertical in scope — sales occupations are ~22% of employment (~2.5× the economy-wide share) and an in-scope firm employs ~28 sales staff on average. Because so many distributors run active sales motions, distribution's SAM is roughly equal to manufacturing's despite having half the firms.
A31: 3. Manufacturing is large in firm count but has the weakest direct-sales motion (~2.7% sales occupations); much of its selling is outsourced to distributors and reps — a reason to reach manufacturers through the distribution channel rather than as a stand-alone vertical.
A32: 4. Builder capacity is the mirror image of need: professional services has near-software levels of technical staff; distribution and manufacturing are below the economy-wide average (preliminary support for H4).
A33: 5. At uniform fair-share penetration, every segment's 3-year SOM is ~1–2% of Clay's estimated ARR — any vertical program is an incremental growth option, not a pivot (context for H8).

Sheet Assumptions
A1: Assumptions — every judgment-based input in one place (Low / Base / High)
A2: Low and High are compounded in the scenario outer bounds on TAM_SAM_SOM; one-at-a-time swings are on Sensitivity. Edit blue cells only.
A4: ID | B4: Parameter | C4: Applies to | D4: Low | E4: Base | F4: High | G4: Unit | H4: Class | I4: Source / rationale
A5: A1 | B5: Annual contract value (ACV) | C5: SMB (20–99) | D5: 5352 | E5: 7500 | F5: 12000 | G5: $/yr | H5: B/D | I5: Low = Growth-tier entry at list, annual billing ($446/mo × 12; S01 [A]). CRM sync, webhooks and HTTP API require Growth or above. Base/High allow for additional Actions / Data-Credit tiers. Vendr reports mid-market buyers at ~$10K–$30K (S16 [B]).
A6: A2 | B6: Annual contract value (ACV) | C6: Mid-Market (100–499) | D6: 12000 | E6: 20000 | F6: 35000 | G6: $/yr | H6: B/D | I6: Anchored on Vendr's reported mid-market range of ~$10K–$30K/yr (S16 [B], updated Feb 2026; vendor-reported, small sample).
A7: A3 | B7: Annual contract value (ACV) | C7: Enterprise (500+) | D7: 30000 | E7: 60000 | F7: 120000 | G7: $/yr | H7: B/D | I7: Base = Vendr median $59,996/yr across 96 purchases; observed range $16,500–$170,000 (S16 [B]). Negotiated, sales-led deals; skews larger than self-serve.
A8: A4 | B8: SAM filter 1 — active B2B outbound / territory sales motion | C8: A. Industrial Distribution | D8: 0.65 | E8: 0.8 | F8: 0.9 | G8: % firms | H8: D | I8: Distribution is the most sales-intensive segment: sales occupations = ~22% of employment vs ~8.6% economy-wide (≈2.5×) (OEWS May 2025, S15 [A]; see Segment_Profile).
A9: A5 | B9: SAM filter 1 — active B2B outbound / territory sales motion | C9: B. Industrial Manufacturing | D9: 0.3 | E9: 0.45 | F9: 0.6 | G9: % firms | H9: D | I9: Sales occupations only ~2.7% of manufacturing employment (S15 [A]) — consistent with many manufacturers selling through distributors and independent reps rather than direct outbound teams.
A10: A6 | B10: SAM filter 1 — active B2B outbound / territory sales motion | C10: C. B2B Professional Services | D10: 0.4 | E10: 0.55 | F10: 0.7 | G10: % firms | H10: D | I10: Sales occupations ~6.2% of employment (S15 [A]), but BD is often done by billable 'seller-doers' (partners/principals) not counted as sales staff; A&E skews RFP-driven.
A11: A7 | B11: SAM filter 2 — CRM / data stack Clay can integrate with | C11: A. Industrial Distribution | D11: 0.52 | E11: 0.65 | F11: 0.76 | G11: % firms | H11: B/D | I11: Distribution Strategy Group 2022 survey of distributors ($10M–$500M revenue; n=96 respondents, 66 distributors): 52% general-purpose CRM, 15% purpose-built, 9% custom, 9% ERP-provided, 15% none (S17 [B]). Low = general-purpose only; High = any non-ERP CRM.
A12: A8 | B12: SAM filter 2 — CRM / data stack Clay can integrate with | C12: B. Industrial Manufacturing | D12: 0.45 | E12: 0.6 | F12: 0.75 | G12: % firms | H12: D | I12: No reliable public adoption rate found (a 2023 vendor-sponsored survey reported usage frequency, not adoption — not used). Set slightly below distribution given lower sales-function density. KEY DATA GAP.
A13: A9 | B13: SAM filter 2 — CRM / data stack Clay can integrate with | C13: C. B2B Professional Services | D13: 0.55 | E13: 0.7 | F13: 0.85 | G13: % firms | H13: D | I13: No reliable public adoption rate found. Set above distribution given far higher technical workforce share (computer occupations ~24% of employment vs ~2% in distribution; S15 [A]). KEY DATA GAP.
A14: A10 | B14: 3-year penetration of SAM firms (uniform across segments) | C14: SMB (20–99) | D14: 0.005 | E14: 0.015 | F14: 0.03 | G14: % SAM firms | H14: D | I14: Fair-share assumption for a focused vertical program over three years. Deliberately identical across segments in Phase 1. Sanity check vs Clay's 17,000+ total customers on Executive_Summary.
A15: A11 | B15: 3-year penetration of SAM firms (uniform across segments) | C15: Mid-Market (100–499) | D15: 0.01 | E15: 0.03 | F15: 0.06 | G15: % SAM firms | H15: D | I15: Higher than SMB: sales-assisted motion concentrates effort on fewer, larger accounts.
A16: A12 | B16: 3-year penetration of SAM firms (uniform across segments) | C16: Enterprise (500+) | D16: 0.02 | E16: 0.06 | F16: 0.12 | G16: % SAM firms | H16: D | I16: Highest: named-account coverage; Clay reports >200% enterprise NRR (S02 [A]) indicating strong land-and-expand once in.
A18: Note: there is no segment-specific ACV multiplier and no segment-specific penetration in Phase 1 by design — Phase 1 isolates market size and reachability. Competitive position and right-to-win enter in Phases 2–3; any segment-specific ACV evidence (e.g., seller headcount driving usage) is tested in Phase 4.

Sheet Firm_Counts
A1: Firm counts — unique U.S. firms by segment and firm size (2022)
A2: Firms operated for the entire year. Suppressed cells imputed (block 2). Sub-industry totals de-duplicated with Census-measured overlap (block 3). Establishments shown for contrast only — never used as the counting unit.
A4: Segment | B4: NAICS | C4: Industry | D4: 20-49 | E4: 50-99 | F4: 100-249 | G4: 250-499 | H4: 500+ | I4: Firms 20+ | J4: Firms <20 | K4: All FY firms | L4: FY establishments | M4: Estab. per firm
A5: A. Industrial Distribution | B5: 4235 | C5: Metal & Mineral (except Petroleum) Merchant Wholesalers | D5: =SUMIFS(Raw_Census!$D$5:$D$379,Raw_Census!$A$5:$A$379,$B5&"|"&D$4) -> 771 | E5: =E28 -> 262.65787 | F5: =F28 -> 161.32381 | G5: =G28 -> 51.018318 | H5: =SUMIFS(Raw_Census!$D$5:$D$379,Raw_Census!$A$5:$A$379,$B5&"|"&H$4) -> 22 | I5: =SUM(D5:H5) -> 1268 | J5: =SUMIFS(Raw_Census!$D$5:$D$379,Raw_Census!$A$5:$A$379,$B5&"|0-4")+SUMIFS(Raw_Census!$D$5:$D$379,Raw_Census!$A$5:$A$379,$B5&"|5-9")+SUMIFS(Raw_Census!$D$5:$D$379,Raw_Census!$A$5:$A$379,$B5&"|10-19") -> 4559 | K5: =SUMIFS(Raw_Census!$D$5:$D$379,Raw_Census!$A$5:$A$379,$B5&"|FY") -> 5827 | L5: =SUMIFS(Raw_Census!$F$5:$F$379,Raw_Census!$A$5:$A$379,$B5&"|FY") -> 8293 | M5: =IFERROR(L5/K5,0) -> 1.4232023
A6: A. Industrial Distribution | B6: 4236 | C6: Household Appliances & Electrical/Electronic Goods Merchant Wholesalers | D6: =SUMIFS(Raw_Census!$D$5:$D$379,Raw_Census!$A$5:$A$379,$B6&"|"&D$4) -> 1408 | E6: =SUMIFS(Raw_Census!$D$5:$D$379,Raw_Census!$A$5:$A$379,$B6&"|"&E$4) -> 570 | F6: =SUMIFS(Raw_Census!$D$5:$D$379,Raw_Census!$A$5:$A$379,$B6&"|"&F$4) -> 350 | G6: =SUMIFS(Raw_Census!$D$5:$D$379,Raw_Census!$A$5:$A$379,$B6&"|"&G$4) -> 136 | H6: =SUMIFS(Raw_Census!$D$5:$D$379,Raw_Census!$A$5:$A$379,$B6&"|"&H$4) -> 114 | I6: =SUM(D6:H6) -> 2578 | J6: =SUMIFS(Raw_Census!$D$5:$D$379,Raw_Census!$A$5:$A$379,$B6&"|0-4")+SUMIFS(Raw_Census!$D$5:$D$379,Raw_Census!$A$5:$A$379,$B6&"|5-9")+SUMIFS(Raw_Census!$D$5:$D$379,Raw_Census!$A$5:$A$379,$B6&"|10-19") -> 11708 | K6: =SUMIFS(Raw_Census!$D$5:$D$379,Raw_Census!$A$5:$A$379,$B6&"|FY") -> 14286 | L6: =SUMIFS(Raw_Census!$F$5:$F$379,Raw_Census!$A$5:$A$379,$B6&"|FY") -> 23428 | M6: =IFERROR(L6/K6,0) -> 1.6399272
A7: A. Industrial Distribution | B7: 4237 | C7: Hardware, Plumbing & Heating Equipment Merchant Wholesalers | D7: =SUMIFS(Raw_Census!$D$5:$D$379,Raw_Census!$A$5:$A$379,$B7&"|"&D$4) -> 1013 | E7: =SUMIFS(Raw_Census!$D$5:$D$379,Raw_Census!$A$5:$A$379,$B7&"|"&E$4) -> 424 | F7: =SUMIFS(Raw_Census!$D$5:$D$379,Raw_Census!$A$5:$A$379,$B7&"|"&F$4) -> 242 | G7: =SUMIFS(Raw_Census!$D$5:$D$379,Raw_Census!$A$5:$A$379,$B7&"|"&G$4) -> 85 | H7: =SUMIFS(Raw_Census!$D$5:$D$379,Raw_Census!$A$5:$A$379,$B7&"|"&H$4) -> 57 | I7: =SUM(D7:H7) -> 1821 | J7: =SUMIFS(Raw_Census!$D$5:$D$379,Raw_Census!$A$5:$A$379,$B7&"|0-4")+SUMIFS(Raw_Census!$D$5:$D$379,Raw_Census!$A$5:$A$379,$B7&"|5-9")+SUMIFS(Raw_Census!$D$5:$D$379,Raw_Census!$A$5:$A$379,$B7&"|10-19") -> 6792 | K7: =SUMIFS(Raw_Census!$D$5:$D$379,Raw_Census!$A$5:$A$379,$B7&"|FY") -> 8613 | L7: =SUMIFS(Raw_Census!$F$5:$F$379,Raw_Census!$A$5:$A$379,$B7&"|FY") -> 19057 | M7: =IFERROR(L7/K7,0) -> 2.2125856
A8: A. Industrial Distribution | B8: 4238 | C8: Machinery, Equipment & Supplies Merchant Wholesalers | D8: =SUMIFS(Raw_Census!$D$5:$D$379,Raw_Census!$A$5:$A$379,$B8&"|"&D$4) -> 3622 | E8: =SUMIFS(Raw_Census!$D$5:$D$379,Raw_Census!$A$5:$A$379,$B8&"|"&E$4) -> 1218 | F8: =SUMIFS(Raw_Census!$D$5:$D$379,Raw_Census!$A$5:$A$379,$B8&"|"&F$4) -> 746 | G8: =SUMIFS(Raw_Census!$D$5:$D$379,Raw_Census!$A$5:$A$379,$B8&"|"&G$4) -> 240 | H8: =SUMIFS(Raw_Census!$D$5:$D$379,Raw_Census!$A$5:$A$379,$B8&"|"&H$4) -> 183 | I8: =SUM(D8:H8) -> 6009 | J8: =SUMIFS(Raw_Census!$D$5:$D$379,Raw_Census!$A$5:$A$379,$B8&"|0-4")+SUMIFS(Raw_Census!$D$5:$D$379,Raw_Census!$A$5:$A$379,$B8&"|5-9")+SUMIFS(Raw_Census!$D$5:$D$379,Raw_Census!$A$5:$A$379,$B8&"|10-19") -> 27128 | K8: =SUMIFS(Raw_Census!$D$5:$D$379,Raw_Census!$A$5:$A$379,$B8&"|FY") -> 33137 | L8: =SUMIFS(Raw_Census!$F$5:$F$379,Raw_Census!$A$5:$A$379,$B8&"|FY") -> 52144 | M8: =IFERROR(L8/K8,0) -> 1.5735884
A9: A. Industrial Distribution — subtotal (before de-dup) | D9: =SUM(D5:D8) -> 6814 | E9: =SUM(E5:E8) -> 2474.6579 | F9: =SUM(F5:F8) -> 1499.3238 | G9: =SUM(G5:G8) -> 512.01832 | H9: =SUM(H5:H8) -> 376 | I9: =SUM(I5:I8) -> 11676 | J9: =SUM(J5:J8) -> 50187 | K9: =SUM(K5:K8) -> 61863 | L9: =SUM(L5:L8) -> 102922 | M9: =IFERROR(L9/K9,0) -> 1.6637085
A11: B. Industrial Manufacturing | B11: 326 | C11: Plastics & Rubber Products Manufacturing | D11: =SUMIFS(Raw_Census!$D$5:$D$379,Raw_Census!$A$5:$A$379,$B11&"|"&D$4) -> 1505 | E11: =SUMIFS(Raw_Census!$D$5:$D$379,Raw_Census!$A$5:$A$379,$B11&"|"&E$4) -> 935 | F11: =SUMIFS(Raw_Census!$D$5:$D$379,Raw_Census!$A$5:$A$379,$B11&"|"&F$4) -> 760 | G11: =SUMIFS(Raw_Census!$D$5:$D$379,Raw_Census!$A$5:$A$379,$B11&"|"&G$4) -> 313 | H11: =SUMIFS(Raw_Census!$D$5:$D$379,Raw_Census!$A$5:$A$379,$B11&"|"&H$4) -> 277 | I11: =SUM(D11:H11) -> 3790 | J11: =SUMIFS(Raw_Census!$D$5:$D$379,Raw_Census!$A$5:$A$379,$B11&"|0-4")+SUMIFS(Raw_Census!$D$5:$D$379,Raw_Census!$A$5:$A$379,$B11&"|5-9")+SUMIFS(Raw_Census!$D$5:$D$379,Raw_Census!$A$5:$A$379,$B11&"|10-19") -> 4626 | K11: =SUMIFS(Raw_Census!$D$5:$D$379,Raw_Census!$A$5:$A$379,$B11&"|FY") -> 8416 | L11: =SUMIFS(Raw_Census!$F$5:$F$379,Raw_Census!$A$5:$A$379,$B11&"|FY") -> 11550 | M11: =IFERROR(L11/K11,0) -> 1.3723859
A12: B. Industrial Manufacturing | B12: 332 | C12: Fabricated Metal Product Manufacturing | D12: =SUMIFS(Raw_Census!$D$5:$D$379,Raw_Census!$A$5:$A$379,$B12&"|"&D$4) -> 7758 | E12: =SUMIFS(Raw_Census!$D$5:$D$379,Raw_Census!$A$5:$A$379,$B12&"|"&E$4) -> 3050 | F12: =SUMIFS(Raw_Census!$D$5:$D$379,Raw_Census!$A$5:$A$379,$B12&"|"&F$4) -> 1685 | G12: =SUMIFS(Raw_Census!$D$5:$D$379,Raw_Census!$A$5:$A$379,$B12&"|"&G$4) -> 423 | H12: =SUMIFS(Raw_Census!$D$5:$D$379,Raw_Census!$A$5:$A$379,$B12&"|"&H$4) -> 278 | I12: =SUM(D12:H12) -> 13194 | J12: =SUMIFS(Raw_Census!$D$5:$D$379,Raw_Census!$A$5:$A$379,$B12&"|0-4")+SUMIFS(Raw_Census!$D$5:$D$379,Raw_Census!$A$5:$A$379,$B12&"|5-9")+SUMIFS(Raw_Census!$D$5:$D$379,Raw_Census!$A$5:$A$379,$B12&"|10-19") -> 36021 | K12: =SUMIFS(Raw_Census!$D$5:$D$379,Raw_Census!$A$5:$A$379,$B12&"|FY") -> 49215 | L12: =SUMIFS(Raw_Census!$F$5:$F$379,Raw_Census!$A$5:$A$379,$B12&"|FY") -> 53708 | M12: =IFERROR(L12/K12,0) -> 1.0912933
A13: B. Industrial Manufacturing | B13: 333 | C13: Machinery Manufacturing | D13: =SUMIFS(Raw_Census!$D$5:$D$379,Raw_Census!$A$5:$A$379,$B13&"|"&D$4) -> 3291 | E13: =SUMIFS(Raw_Census!$D$5:$D$379,Raw_Census!$A$5:$A$379,$B13&"|"&E$4) -> 1484 | F13: =SUMIFS(Raw_Census!$D$5:$D$379,Raw_Census!$A$5:$A$379,$B13&"|"&F$4) -> 997 | G13: =SUMIFS(Raw_Census!$D$5:$D$379,Raw_Census!$A$5:$A$379,$B13&"|"&G$4) -> 358 | H13: =SUMIFS(Raw_Census!$D$5:$D$379,Raw_Census!$A$5:$A$379,$B13&"|"&H$4) -> 295 | I13: =SUM(D13:H13) -> 6425 | J13: =SUMIFS(Raw_Census!$D$5:$D$379,Raw_Census!$A$5:$A$379,$B13&"|0-4")+SUMIFS(Raw_Census!$D$5:$D$379,Raw_Census!$A$5:$A$379,$B13&"|5-9")+SUMIFS(Raw_Census!$D$5:$D$379,Raw_Census!$A$5:$A$379,$B13&"|10-19") -> 12231 | K13: =SUMIFS(Raw_Census!$D$5:$D$379,Raw_Census!$A$5:$A$379,$B13&"|FY") -> 18656 | L13: =SUMIFS(Raw_Census!$F$5:$F$379,Raw_Census!$A$5:$A$379,$B13&"|FY") -> 21352 | M13: =IFERROR(L13/K13,0) -> 1.1445111
A14: B. Industrial Manufacturing | B14: 335 | C14: Electrical Equipment, Appliance & Component Manufacturing | D14: =SUMIFS(Raw_Census!$D$5:$D$379,Raw_Census!$A$5:$A$379,$B14&"|"&D$4) -> 775 | E14: =SUMIFS(Raw_Census!$D$5:$D$379,Raw_Census!$A$5:$A$379,$B14&"|"&E$4) -> 422 | F14: =SUMIFS(Raw_Census!$D$5:$D$379,Raw_Census!$A$5:$A$379,$B14&"|"&F$4) -> 288 | G14: =SUMIFS(Raw_Census!$D$5:$D$379,Raw_Census!$A$5:$A$379,$B14&"|"&G$4) -> 108 | H14: =SUMIFS(Raw_Census!$D$5:$D$379,Raw_Census!$A$5:$A$379,$B14&"|"&H$4) -> 129 | I14: =SUM(D14:H14) -> 1722 | J14: =SUMIFS(Raw_Census!$D$5:$D$379,Raw_Census!$A$5:$A$379,$B14&"|0-4")+SUMIFS(Raw_Census!$D$5:$D$379,Raw_Census!$A$5:$A$379,$B14&"|5-9")+SUMIFS(Raw_Census!$D$5:$D$379,Raw_Census!$A$5:$A$379,$B14&"|10-19") -> 2792 | K14: =SUMIFS(Raw_Census!$D$5:$D$379,Raw_Census!$A$5:$A$379,$B14&"|FY") -> 4514 | L14: =SUMIFS(Raw_Census!$F$5:$F$379,Raw_Census!$A$5:$A$379,$B14&"|FY") -> 5270 | M14: =IFERROR(L14/K14,0) -> 1.167479
A15: B. Industrial Manufacturing — subtotal (before de-dup) | D15: =SUM(D11:D14) -> 13329 | E15: =SUM(E11:E14) -> 5891 | F15: =SUM(F11:F14) -> 3730 | G15: =SUM(G11:G14) -> 1202 | H15: =SUM(H11:H14) -> 979 | I15: =SUM(I11:I14) -> 25131 | J15: =SUM(J11:J14) -> 55670 | K15: =SUM(K11:K14) -> 80801 | L15: =SUM(L11:L14) -> 91880 | M15: =IFERROR(L15/K15,0) -> 1.1371146
A17: C. B2B Professional Services | B17: 5413 | C17: Architectural, Engineering & Related Services | D17: =SUMIFS(Raw_Census!$D$5:$D$379,Raw_Census!$A$5:$A$379,$B17&"|"&D$4) -> 5930 | E17: =SUMIFS(Raw_Census!$D$5:$D$379,Raw_Census!$A$5:$A$379,$B17&"|"&E$4) -> 2104 | F17: =SUMIFS(Raw_Census!$D$5:$D$379,Raw_Census!$A$5:$A$379,$B17&"|"&F$4) -> 1251 | G17: =SUMIFS(Raw_Census!$D$5:$D$379,Raw_Census!$A$5:$A$379,$B17&"|"&G$4) -> 429 | H17: =SUMIFS(Raw_Census!$D$5:$D$379,Raw_Census!$A$5:$A$379,$B17&"|"&H$4) -> 387 | I17: =SUM(D17:H17) -> 10101 | J17: =SUMIFS(Raw_Census!$D$5:$D$379,Raw_Census!$A$5:$A$379,$B17&"|0-4")+SUMIFS(Raw_Census!$D$5:$D$379,Raw_Census!$A$5:$A$379,$B17&"|5-9")+SUMIFS(Raw_Census!$D$5:$D$379,Raw_Census!$A$5:$A$379,$B17&"|10-19") -> 70489 | K17: =SUMIFS(Raw_Census!$D$5:$D$379,Raw_Census!$A$5:$A$379,$B17&"|FY") -> 80590 | L17: =SUMIFS(Raw_Census!$F$5:$F$379,Raw_Census!$A$5:$A$379,$B17&"|FY") -> 102514 | M17: =IFERROR(L17/K17,0) -> 1.2720437
A18: C. B2B Professional Services | B18: 5415 | C18: Computer Systems Design & Related Services | D18: =SUMIFS(Raw_Census!$D$5:$D$379,Raw_Census!$A$5:$A$379,$B18&"|"&D$4) -> 5831 | E18: =SUMIFS(Raw_Census!$D$5:$D$379,Raw_Census!$A$5:$A$379,$B18&"|"&E$4) -> 2359 | F18: =SUMIFS(Raw_Census!$D$5:$D$379,Raw_Census!$A$5:$A$379,$B18&"|"&F$4) -> 1581 | G18: =SUMIFS(Raw_Census!$D$5:$D$379,Raw_Census!$A$5:$A$379,$B18&"|"&G$4) -> 561 | H18: =SUMIFS(Raw_Census!$D$5:$D$379,Raw_Census!$A$5:$A$379,$B18&"|"&H$4) -> 447 | I18: =SUM(D18:H18) -> 10779 | J18: =SUMIFS(Raw_Census!$D$5:$D$379,Raw_Census!$A$5:$A$379,$B18&"|0-4")+SUMIFS(Raw_Census!$D$5:$D$379,Raw_Census!$A$5:$A$379,$B18&"|5-9")+SUMIFS(Raw_Census!$D$5:$D$379,Raw_Census!$A$5:$A$379,$B18&"|10-19") -> 83509 | K18: =SUMIFS(Raw_Census!$D$5:$D$379,Raw_Census!$A$5:$A$379,$B18&"|FY") -> 94288 | L18: =SUMIFS(Raw_Census!$F$5:$F$379,Raw_Census!$A$5:$A$379,$B18&"|FY") -> 110473 | M18: =IFERROR(L18/K18,0) -> 1.1716549
A19: C. B2B Professional Services | B19: 5416 | C19: Management, Scientific & Technical Consulting | D19: =SUMIFS(Raw_Census!$D$5:$D$379,Raw_Census!$A$5:$A$379,$B19&"|"&D$4) -> 5789 | E19: =SUMIFS(Raw_Census!$D$5:$D$379,Raw_Census!$A$5:$A$379,$B19&"|"&E$4) -> 2151 | F19: =SUMIFS(Raw_Census!$D$5:$D$379,Raw_Census!$A$5:$A$379,$B19&"|"&F$4) -> 1244 | G19: =SUMIFS(Raw_Census!$D$5:$D$379,Raw_Census!$A$5:$A$379,$B19&"|"&G$4) -> 430 | H19: =SUMIFS(Raw_Census!$D$5:$D$379,Raw_Census!$A$5:$A$379,$B19&"|"&H$4) -> 339 | I19: =SUM(D19:H19) -> 9953 | J19: =SUMIFS(Raw_Census!$D$5:$D$379,Raw_Census!$A$5:$A$379,$B19&"|0-4")+SUMIFS(Raw_Census!$D$5:$D$379,Raw_Census!$A$5:$A$379,$B19&"|5-9")+SUMIFS(Raw_Census!$D$5:$D$379,Raw_Census!$A$5:$A$379,$B19&"|10-19") -> 139134 | K19: =SUMIFS(Raw_Census!$D$5:$D$379,Raw_Census!$A$5:$A$379,$B19&"|FY") -> 149087 | L19: =SUMIFS(Raw_Census!$F$5:$F$379,Raw_Census!$A$5:$A$379,$B19&"|FY") -> 160268 | M19: =IFERROR(L19/K19,0) -> 1.0749965
A20: C. B2B Professional Services | B20: 5418 | C20: Advertising, PR & Related Services | D20: =SUMIFS(Raw_Census!$D$5:$D$379,Raw_Census!$A$5:$A$379,$B20&"|"&D$4) -> 1655 | E20: =SUMIFS(Raw_Census!$D$5:$D$379,Raw_Census!$A$5:$A$379,$B20&"|"&E$4) -> 584 | F20: =SUMIFS(Raw_Census!$D$5:$D$379,Raw_Census!$A$5:$A$379,$B20&"|"&F$4) -> 371 | G20: =SUMIFS(Raw_Census!$D$5:$D$379,Raw_Census!$A$5:$A$379,$B20&"|"&G$4) -> 132 | H20: =SUMIFS(Raw_Census!$D$5:$D$379,Raw_Census!$A$5:$A$379,$B20&"|"&H$4) -> 102 | I20: =SUM(D20:H20) -> 2844 | J20: =SUMIFS(Raw_Census!$D$5:$D$379,Raw_Census!$A$5:$A$379,$B20&"|0-4")+SUMIFS(Raw_Census!$D$5:$D$379,Raw_Census!$A$5:$A$379,$B20&"|5-9")+SUMIFS(Raw_Census!$D$5:$D$379,Raw_Census!$A$5:$A$379,$B20&"|10-19") -> 24892 | K20: =SUMIFS(Raw_Census!$D$5:$D$379,Raw_Census!$A$5:$A$379,$B20&"|FY") -> 27736 | L20: =SUMIFS(Raw_Census!$F$5:$F$379,Raw_Census!$A$5:$A$379,$B20&"|FY") -> 31557 | M20: =IFERROR(L20/K20,0) -> 1.1377632
A21: C. B2B Professional Services — subtotal (before de-dup) | D21: =SUM(D17:D20) -> 19205 | E21: =SUM(E17:E20) -> 7198 | F21: =SUM(F17:F20) -> 4447 | G21: =SUM(G17:G20) -> 1552 | H21: =SUM(H17:H20) -> 1275 | I21: =SUM(I17:I20) -> 33677 | J21: =SUM(J17:J20) -> 318024 | K21: =SUM(K17:K20) -> 351701 | L21: =SUM(L17:L20) -> 404812 | M21: =IFERROR(L21/K21,0) -> 1.1510118
A23: Block 2 — Imputation of Census-suppressed cells (NAICS 4235, firms with 50–499 employees)
A24: 4235 firms operated full year (FY) | D24: =SUMIFS(Raw_Census!$D$5:$D$379,Raw_Census!$A$5:$A$379,"4235|FY") -> 5827
A25: less: reported bands (0–4, 5–9, 10–19, 20–49, 500+) | D25: =SUMIFS(Raw_Census!$D$5:$D$379,Raw_Census!$A$5:$A$379,"4235|0-4")+SUMIFS(Raw_Census!$D$5:$D$379,Raw_Census!$A$5:$A$379,"4235|5-9")+SUMIFS(Raw_Census!$D$5:$D$379,Raw_Census!$A$5:$A$379,"4235|10-19")+SUMIFS(Raw_Census!$D$5:$D$379,Raw_Census!$A$5:$A$379,"4235|20-49")+SUMIFS(Raw_Census!$D$5:$D$379,Raw_Census!$A$5:$A$379,"4235|500+") -> 5352
A26: Suppressed residual (firms with 50–499 employees) [C] | D26: =D24-D25 -> 475 | E26: 50-99 | F26: 100-249 | G26: 250-499
A27: Allocation key: parent NAICS 423 firm mix across 50–99 / 100–249 / 250–499 | E27: =SUMIFS(Raw_Census!$D$5:$D$379,Raw_Census!$A$5:$A$379,"423|50-99")/(SUMIFS(Raw_Census!$D$5:$D$379,Raw_Census!$A$5:$A$379,"423|50-99")+SUMIFS(Raw_Census!$D$5:$D$379,Raw_Census!$A$5:$A$379,"423|100-249")+SUMIFS(Raw_Census!$D$5:$D$379,Raw_Census!$A$5:$A$379,"423|250-499")) -> 0.55296393 | F27: =SUMIFS(Raw_Census!$D$5:$D$379,Raw_Census!$A$5:$A$379,"423|100-249")/(SUMIFS(Raw_Census!$D$5:$D$379,Raw_Census!$A$5:$A$379,"423|50-99")+SUMIFS(Raw_Census!$D$5:$D$379,Raw_Census!$A$5:$A$379,"423|100-249")+SUMIFS(Raw_Census!$D$5:$D$379,Raw_Census!$A$5:$A$379,"423|250-499")) -> 0.33962908 | G27: =SUMIFS(Raw_Census!$D$5:$D$379,Raw_Census!$A$5:$A$379,"423|250-499")/(SUMIFS(Raw_Census!$D$5:$D$379,Raw_Census!$A$5:$A$379,"423|50-99")+SUMIFS(Raw_Census!$D$5:$D$379,Raw_Census!$A$5:$A$379,"423|100-249")+SUMIFS(Raw_Census!$D$5:$D$379,Raw_Census!$A$5:$A$379,"423|250-499")) -> 0.10740699
A28: Imputed 4235 firms by band (feeds yellow cells above) | E28: =$D$26*E27 -> 262.65787 | F28: =$D$26*F27 -> 161.32381 | G28: =$D$26*G27 -> 51.018318
A31: Block 3 — De-duplication: a firm with establishments in several sub-industries is counted in each. Factor = MIN(1, sector firms ÷ Σ reported sub-industry firms), per band.
A32: Parent sector | C32: Measure | D32: 20-49 | E32: 50-99 | F32: 100-249 | G32: 250-499 | H32: 500+
A33: 423 | C33: Sector firms (parent) | D33: =SUMIFS(Raw_Census!$D$5:$D$379,Raw_Census!$A$5:$A$379,$A33&"|"&D$32) -> 13339 | E33: =SUMIFS(Raw_Census!$D$5:$D$379,Raw_Census!$A$5:$A$379,$A33&"|"&E$32) -> 4860 | F33: =SUMIFS(Raw_Census!$D$5:$D$379,Raw_Census!$A$5:$A$379,$A33&"|"&F$32) -> 2985 | G33: =SUMIFS(Raw_Census!$D$5:$D$379,Raw_Census!$A$5:$A$379,$A33&"|"&G$32) -> 944 | H33: =SUMIFS(Raw_Census!$D$5:$D$379,Raw_Census!$A$5:$A$379,$A33&"|"&H$32) -> 802
A34: 423 | C34: Σ reported sub-industry firms | D34: =SUMIFS(Raw_Census!$D$5:$D$379,Raw_Census!$I$5:$I$379,$A34,Raw_Census!$C$5:$C$379,D$32) -> 13706 | E34: =SUMIFS(Raw_Census!$D$5:$D$379,Raw_Census!$I$5:$I$379,$A34,Raw_Census!$C$5:$C$379,E$32) -> 4212 | F34: =SUMIFS(Raw_Census!$D$5:$D$379,Raw_Census!$I$5:$I$379,$A34,Raw_Census!$C$5:$C$379,F$32) -> 2574 | G34: =SUMIFS(Raw_Census!$D$5:$D$379,Raw_Census!$I$5:$I$379,$A34,Raw_Census!$C$5:$C$379,G$32) -> 858 | H34: =SUMIFS(Raw_Census!$D$5:$D$379,Raw_Census!$I$5:$I$379,$A34,Raw_Census!$C$5:$C$379,H$32) -> 798
A35: 423 | C35: Implied overlap | D35: =IFERROR(D34/D33-1,0) -> 0.027513307 | E35: =IFERROR(E34/E33-1,0) -> -0.13333333 | F35: =IFERROR(F34/F33-1,0) -> -0.13768844 | G35: =IFERROR(G34/G33-1,0) -> -0.091101695 | H35: =IFERROR(H34/H33-1,0) -> -0.0049875312
A36: 423 | C36: De-dup factor applied [C] | D36: =IFERROR(MIN(1,D33/D34),1) -> 0.97322341 | E36: =IFERROR(MIN(1,E33/E34),1) -> 1 | F36: =IFERROR(MIN(1,F33/F34),1) -> 1 | G36: =IFERROR(MIN(1,G33/G34),1) -> 1 | H36: =IFERROR(MIN(1,H33/H34),1) -> 1
A38: 31-33 | C38: Sector firms (parent) | D38: =SUMIFS(Raw_Census!$D$5:$D$379,Raw_Census!$A$5:$A$379,$A38&"|"&D$32) -> 32323 | E38: =SUMIFS(Raw_Census!$D$5:$D$379,Raw_Census!$A$5:$A$379,$A38&"|"&E$32) -> 13573 | F38: =SUMIFS(Raw_Census!$D$5:$D$379,Raw_Census!$A$5:$A$379,$A38&"|"&F$32) -> 8859 | G38: =SUMIFS(Raw_Census!$D$5:$D$379,Raw_Census!$A$5:$A$379,$A38&"|"&G$32) -> 3013 | H38: =SUMIFS(Raw_Census!$D$5:$D$379,Raw_Census!$A$5:$A$379,$A38&"|"&H$32) -> 2942
A39: 31-33 | C39: Σ reported sub-industry firms | D39: =SUMIFS(Raw_Census!$D$5:$D$379,Raw_Census!$I$5:$I$379,$A39,Raw_Census!$C$5:$C$379,D$32) -> 33325 | E39: =SUMIFS(Raw_Census!$D$5:$D$379,Raw_Census!$I$5:$I$379,$A39,Raw_Census!$C$5:$C$379,E$32) -> 14501 | F39: =SUMIFS(Raw_Census!$D$5:$D$379,Raw_Census!$I$5:$I$379,$A39,Raw_Census!$C$5:$C$379,F$32) -> 9840 | G39: =SUMIFS(Raw_Census!$D$5:$D$379,Raw_Census!$I$5:$I$379,$A39,Raw_Census!$C$5:$C$379,G$32) -> 3320 | H39: =SUMIFS(Raw_Census!$D$5:$D$379,Raw_Census!$I$5:$I$379,$A39,Raw_Census!$C$5:$C$379,H$32) -> 3224
A40: 31-33 | C40: Implied overlap | D40: =IFERROR(D39/D38-1,0) -> 0.030999598 | E40: =IFERROR(E39/E38-1,0) -> 0.068371031 | F40: =IFERROR(F39/F38-1,0) -> 0.11073485 | G40: =IFERROR(G39/G38-1,0) -> 0.1018918 | H40: =IFERROR(H39/H38-1,0) -> 0.095853161
A41: 31-33 | C41: De-dup factor applied [C] | D41: =IFERROR(MIN(1,D38/D39),1) -> 0.96993248 | E41: =IFERROR(MIN(1,E38/E39),1) -> 0.93600441 | F41: =IFERROR(MIN(1,F38/F39),1) -> 0.90030488 | G41: =IFERROR(MIN(1,G38/G39),1) -> 0.90753012 | H41: =IFERROR(MIN(1,H38/H39),1) -> 0.91253102
A43: 54 | C43: Sector firms (parent) | D43: =SUMIFS(Raw_Census!$D$5:$D$379,Raw_Census!$A$5:$A$379,$A43&"|"&D$32) -> 35049 | E43: =SUMIFS(Raw_Census!$D$5:$D$379,Raw_Census!$A$5:$A$379,$A43&"|"&E$32) -> 11416 | F43: =SUMIFS(Raw_Census!$D$5:$D$379,Raw_Census!$A$5:$A$379,$A43&"|"&F$32) -> 6827 | G43: =SUMIFS(Raw_Census!$D$5:$D$379,Raw_Census!$A$5:$A$379,$A43&"|"&G$32) -> 2304 | H43: =SUMIFS(Raw_Census!$D$5:$D$379,Raw_Census!$A$5:$A$379,$A43&"|"&H$32) -> 2069
A44: 54 | C44: Σ reported sub-industry firms | D44: =SUMIFS(Raw_Census!$D$5:$D$379,Raw_Census!$I$5:$I$379,$A44,Raw_Census!$C$5:$C$379,D$32) -> 35475 | E44: =SUMIFS(Raw_Census!$D$5:$D$379,Raw_Census!$I$5:$I$379,$A44,Raw_Census!$C$5:$C$379,E$32) -> 11662 | F44: =SUMIFS(Raw_Census!$D$5:$D$379,Raw_Census!$I$5:$I$379,$A44,Raw_Census!$C$5:$C$379,F$32) -> 7061 | G44: =SUMIFS(Raw_Census!$D$5:$D$379,Raw_Census!$I$5:$I$379,$A44,Raw_Census!$C$5:$C$379,G$32) -> 2423 | H44: =SUMIFS(Raw_Census!$D$5:$D$379,Raw_Census!$I$5:$I$379,$A44,Raw_Census!$C$5:$C$379,H$32) -> 2129
A45: 54 | C45: Implied overlap | D45: =IFERROR(D44/D43-1,0) -> 0.012154412 | E45: =IFERROR(E44/E43-1,0) -> 0.021548704 | F45: =IFERROR(F44/F43-1,0) -> 0.03427567 | G45: =IFERROR(G44/G43-1,0) -> 0.051649306 | H45: =IFERROR(H44/H43-1,0) -> 0.028999517
A46: 54 | C46: De-dup factor applied [C] | D46: =IFERROR(MIN(1,D43/D44),1) -> 0.98799154 | E46: =IFERROR(MIN(1,E43/E44),1) -> 0.97890585 | F46: =IFERROR(MIN(1,F43/F44),1) -> 0.96686022 | G46: =IFERROR(MIN(1,G43/G44),1) -> 0.95088733 | H46: =IFERROR(MIN(1,H43/H44),1) -> 0.97181775
A48: Reading: overlap is small in distribution (~1–3%) and professional services (~1–5%) but material in mid-size/large manufacturing (~7–11%), where multi-plant firms span subsectors. Where some sub-industry cells are suppressed, the reported sum is a lower bound, so the factor is conservative (removes less overlap than exists).
A50: Block 4 — Unique firms by segment (de-duplicated) [C]
A51: Segment | D51: 20-49 | E51: 50-99 | F51: 100-249 | G51: 250-499 | H51: 500+ | I51: Firms 20+
A52: A. Industrial Distribution | D52: =D9*D$36 -> 6631.5443 | E52: =E9*E$36 -> 2474.6579 | F52: =F9*F$36 -> 1499.3238 | G52: =G9*G$36 -> 512.01832 | H52: =H9*H$36 -> 376 | I52: =SUM(D52:H52) -> 11493.544
A53: B. Industrial Manufacturing | D53: =D15*D$41 -> 12928.23 | E53: =E15*E$41 -> 5514.002 | F53: =F15*F$41 -> 3358.1372 | G53: =G15*G$41 -> 1090.8512 | H53: =H15*H$41 -> 893.36787 | I53: =SUM(D53:H53) -> 23784.588
A54: C. B2B Professional Services | D54: =D21*D$46 -> 18974.378 | E54: =E21*E$46 -> 7046.1643 | F54: =F21*F$46 -> 4299.6274 | G54: =G21*G$46 -> 1475.7771 | H54: =H21*H$46 -> 1239.0676 | I54: =SUM(D54:H54) -> 33035.014
A56: Block 5 — Unique firms by size group (feeds TAM_SAM_SOM and Sensitivity)
A57: Size group | C57: Bands | D57: A. Industrial Distribution | E57: B. Industrial Manufacturing | F57: C. B2B Professional Services
A58: SMB | C58: 20–99 | D58: =D52+E52 -> 9106.2022 | E58: =D53+E53 -> 18442.232 | F58: =D54+E54 -> 26020.542
A59: Mid-Market | C59: 100–499 | D59: =F52+G52 -> 2011.3421 | E59: =F53+G53 -> 4448.9884 | F59: =F54+G54 -> 5775.4045
A60: Enterprise | C60: 500+ | D60: =H52 -> 376 | E60: =H53 -> 893.36787 | F60: =H54 -> 1239.0676
A61: Total firms 20+ | D61: =SUM(D58:D60) -> 11493.544 | E61: =SUM(E58:E60) -> 23784.588 | F61: =SUM(F58:F60) -> 33035.014

Sheet Segment_Profile
A1: Segment profile — structure, sales intensity and 'builder capacity'
A2: Census metrics use the core NAICS codes; OEWS metrics use the closest BLS industry groupings (distribution proxy 4230A1 also includes 4232/4233/4239). Ratios are [C] derived from [A] data.
A4: Metric | B4: A. Industrial Distribution | C4: B. Industrial Manufacturing | D4: C. B2B Professional Services | E4: Ref: Software Publishers (Clay core proxy) | F4: Ref: All industries | G4: Unit / source | H4: What it indicates
A5: Structure (2022 Economic Census, S14)
A6: Unique firms, 20+ employees | B6: =Firm_Counts!D61 -> 11493.544 | C6: =Firm_Counts!E61 -> 23784.588 | D6: =Firm_Counts!F61 -> 33035.014 | E6: =SUMIFS(Raw_Census!$D$5:$D$379,Raw_Census!$A$5:$A$379,"5132|20-49")+SUMIFS(Raw_Census!$D$5:$D$379,Raw_Census!$A$5:$A$379,"5132|50-99")+SUMIFS(Raw_Census!$D$5:$D$379,Raw_Census!$A$5:$A$379,"5132|100-249")+SUMIFS(Raw_Census!$D$5:$D$379,Raw_Census!$A$5:$A$379,"5132|250-499")+SUMIFS(Raw_Census!$D$5:$D$379,Raw_Census!$A$5:$A$379,"5132|500+") -> 3274 | G6: firms [C] | H6: Size of the reachable firm universe (de-duplicated).
A7: Establishments per firm (all FY firms) | B7: =(SUMIFS(Raw_Census!$F$5:$F$379,Raw_Census!$A$5:$A$379,"4235|FY")+SUMIFS(Raw_Census!$F$5:$F$379,Raw_Census!$A$5:$A$379,"4236|FY")+SUMIFS(Raw_Census!$F$5:$F$379,Raw_Census!$A$5:$A$379,"4237|FY")+SUMIFS(Raw_Census!$F$5:$F$379,Raw_Census!$A$5:$A$379,"4238|FY"))/(SUMIFS(Raw_Census!$D$5:$D$379,Raw_Census!$A$5:$A$379,"4235|FY")+SUMIFS(Raw_Census!$D$5:$D$379,Raw_Census!$A$5:$A$379,"4236|FY")+SUMIFS(Raw_Census!$D$5:$D$379,Raw_Census!$A$5:$A$379,"4237|FY")+SUMIFS(Raw_Census!$D$5:$D$379,Raw_Census!$A$5:$A$379,"4238|FY")) -> 1.6637085 | C7: =(SUMIFS(Raw_Census!$F$5:$F$379,Raw_Census!$A$5:$A$379,"326|FY")+SUMIFS(Raw_Census!$F$5:$F$379,Raw_Census!$A$5:$A$379,"332|FY")+SUMIFS(Raw_Census!$F$5:$F$379,Raw_Census!$A$5:$A$379,"333|FY")+SUMIFS(Raw_Census!$F$5:$F$379,Raw_Census!$A$5:$A$379,"335|FY"))/(SUMIFS(Raw_Census!$D$5:$D$379,Raw_Census!$A$5:$A$379,"326|FY")+SUMIFS(Raw_Census!$D$5:$D$379,Raw_Census!$A$5:$A$379,"332|FY")+SUMIFS(Raw_Census!$D$5:$D$379,Raw_Census!$A$5:$A$379,"333|FY")+SUMIFS(Raw_Census!$D$5:$D$379,Raw_Census!$A$5:$A$379,"335|FY")) -> 1.1371146 | D7: =(SUMIFS(Raw_Census!$F$5:$F$379,Raw_Census!$A$5:$A$379,"5413|FY")+SUMIFS(Raw_Census!$F$5:$F$379,Raw_Census!$A$5:$A$379,"5415|FY")+SUMIFS(Raw_Census!$F$5:$F$379,Raw_Census!$A$5:$A$379,"5416|FY")+SUMIFS(Raw_Census!$F$5:$F$379,Raw_Census!$A$5:$A$379,"5418|FY"))/(SUMIFS(Raw_Census!$D$5:$D$379,Raw_Census!$A$5:$A$379,"5413|FY")+SUMIFS(Raw_Census!$D$5:$D$379,Raw_Census!$A$5:$A$379,"5415|FY")+SUMIFS(Raw_Census!$D$5:$D$379,Raw_Census!$A$5:$A$379,"5416|FY")+SUMIFS(Raw_Census!$D$5:$D$379,Raw_Census!$A$5:$A$379,"5418|FY")) -> 1.1510118 | E7: =(SUMIFS(Raw_Census!$F$5:$F$379,Raw_Census!$A$5:$A$379,"5132|FY"))/(SUMIFS(Raw_Census!$D$5:$D$379,Raw_Census!$A$5:$A$379,"5132|FY")) -> 1.3082948 | G7: ratio [C] | H7: Branch intensity. >1.5 means multi-branch networks → territory planning and branch-level account mapping matter.
A8: Avg receipts per firm, 20+ firms ($M) | B8: =(SUMIFS(Raw_Census!$H$5:$H$379,Raw_Census!$A$5:$A$379,"4235|20-49")+SUMIFS(Raw_Census!$H$5:$H$379,Raw_Census!$A$5:$A$379,"4235|50-99")+SUMIFS(Raw_Census!$H$5:$H$379,Raw_Census!$A$5:$A$379,"4235|100-249")+SUMIFS(Raw_Census!$H$5:$H$379,Raw_Census!$A$5:$A$379,"4235|250-499")+SUMIFS(Raw_Census!$H$5:$H$379,Raw_Census!$A$5:$A$379,"4235|500+")+SUMIFS(Raw_Census!$H$5:$H$379,Raw_Census!$A$5:$A$379,"4236|20-49")+SUMIFS(Raw_Census!$H$5:$H$379,Raw_Census!$A$5:$A$379,"4236|50-99")+SUMIFS(Raw_Census!$H$5:$H$379,Raw_Census!$A$5:$A$379,"4236|100-249")+SUMIFS(Raw_Census!$H$5:$H$379,Raw_Census!$A$5:$A$379,"4236|250-499")+SUMIFS(Raw_Census!$H$5:$H$379,Raw_Census!$A$5:$A$379,"4236|500+")+SUMIFS(Raw_Census!$H$5:$H$379,Raw_Census!$A$5:$A$379,"4237|20-49")+SUMIFS(Raw_Census!$H$5:$H$379,Raw_Census!$A$5:$A$379,"4237|50-99")+SUMIFS(Raw_Census!$H$5:$H$379,Raw_Census!$A$5:$A$379,"4237|100-249")+SUMIFS(Raw_Census!$H$5:$H$379,Raw_Census!$A$5:$A$379,"4237|250-499")+SUMIFS(Raw_Census!$H$5:$H$379,Raw_Census!$A$5:$A$379,"4237|500+")+SUMIFS(Raw_Census!$H$5:$H$379,Raw_Census!$A$5:$A$379,"4238|20-49")+SUMIFS(Raw_Census!$H$5:$H$379,Raw_Census!$A$5:$A$379,"4238|50-99")+SUMIFS(Raw_Census!$H$5:$H$379,Raw_Census!$A$5:$A$379,"4238|100-249")+SUMIFS(Raw_Census!$H$5:$H$379,Raw_Census!$A$5:$A$379,"4238|250-499")+SUMIFS(Raw_Census!$H$5:$H$379,Raw_Census!$A$5:$A$379,"4238|500+"))/(IF(SUMIFS(Raw_Census!$H$5:$H$379,Raw_Census!$A$5:$A$379,"4235|20-49")>0,SUMIFS(Raw_Census!$D$5:$D$379,Raw_Census!$A$5:$A$379,"4235|20-49"),0)+IF(SUMIFS(Raw_Census!$H$5:$H$379,Raw_Census!$A$5:$A$379,"4235|50-99")>0,SUMIFS(Raw_Census!$D$5:$D$379,Raw_Census!$A$5:$A$379,"4235|50-99"),0)+IF(SUMIFS(Raw_Census!$H$5:$H$379,Raw_Census!$A$5:$A$379,"4235|100-249")>0,SUMIFS(Raw_Census!$D$5:$D$379,Raw_Census!$A$5:$A$379,"4235|100-249"),0)+IF(SUMIFS(Raw_Census!$H$5:$H$379,Raw_Census!$A$5:$A$379,"4235|250-499")>0,SUMIFS(Raw_Census!$D$5:$D$379,Raw_Census!$A$5:$A$379,"4235|250-499"),0)+IF(SUMIFS(Raw_Census!$H$5:$H$379,Raw_Census!$A$5:$A$379,"4235|500+")>0,SUMIFS(Raw_Census!$D$5:$D$379,Raw_Census!$A$5:$A$379,"4235|500+"),0)+IF(SUMIFS(Raw_Census!$H$5:$H$379,Raw_Census!$A$5:$A$379,"4236|20-49")>0,SUMIFS(Raw_Census!$D$5:$D$379,Raw_Census!$A$5:$A$379,"4236|20-49"),0)+IF(SUMIFS(Raw_Census!$H$5:$H$379,Raw_Census!$A$5:$A$379,"4236|50-99")>0,SUMIFS(Raw_Census!$D$5:$D$379,Raw_Census!$A$5:$A$379,"4236|50-99"),0)+IF(SUMIFS(Raw_Census!$H$5:$H$379,Raw_Census!$A$5:$A$379,"4236|100-249")>0,SUMIFS(Raw_Census!$D$5:$D$379,Raw_Census!$A$5:$A$379,"4236|100-249"),0)+IF(SUMIFS(Raw_Census!$H$5:$H$379,Raw_Census!$A$5:$A$379,"4236|250-499")>0,SUMIFS(Raw_Census!$D$5:$D$379,Raw_Census!$A$5:$A$379,"4236|250-499"),0)+IF(SUMIFS(Raw_Census!$H$5:$H$379,Raw_Census!$A$5:$A$379,"4236|500+")>0,SUMIFS(Raw_Census!$D$5:$D$379,Raw_Census!$A$5:$A$379,"4236|500+"),0)+IF(SUMIFS(Raw_Census!$H$5:$H$379,Raw_Census!$A$5:$A$379,"4237|20-49")>0,SUMIFS(Raw_Census!$D$5:$D$379,Raw_Census!$A$5:$A$379,"4237|20-49"),0)+IF(SUMIFS(Raw_Census!$H$5:$H$379,Raw_Census!$A$5:$A$379,"4237|50-99")>0,SUMIFS(Raw_Census!$D$5:$D$379,Raw_Census!$A$5:$A$379,"4237|50-99"),0)+IF(SUMIFS(Raw_Census!$H$5:$H$379,Raw_Census!$A$5:$A$379,"4237|100-249")>0,SUMIFS(Raw_Census!$D$5:$D$379,Raw_Census!$A$5:$A$379,"4237|100-249"),0)+IF(SUMIFS(Raw_Census!$H$5:$H$379,Raw_Census!$A$5:$A$379,"4237|250-499")>0,SUMIFS(Raw_Census!$D$5:$D$379,Raw_Census!$A$5:$A$379,"4237|250-499"),0)+IF(SUMIFS(Raw_Census!$H$5:$H$379,Raw_Census!$A$5:$A$379,"4237|500+")>0,SUMIFS(Raw_Census!$D$5:$D$379,Raw_Census!$A$5:$A$379,"4237|500+"),0)+IF(SUMIFS(Raw_Census!$H$5:$H$379,Raw_Census!$A$5:$A$379,"4238|20-49")>0,SUMIFS(Raw_Census!$D$5:$D$379,Raw_Census!$A$5:$A$379,"4238|20-49"),0)+IF(SUMIFS(Raw_Census!$H$5:$H$379,Raw_Census!$A$5:$A$379,"4238|50-99")>0,SUMIFS(Raw_Census!$D$5:$D$379,Raw_Census!$A$5:$A$379,"4238|50-99"),0)+IF(SUMIFS(Raw_Census!$H$5:$H$379,Raw_Census!$A$5:$A$379,"4238|100-249")>0,SUMIFS(Raw_Census!$D$5:$D$379,Raw_Census!$A$5:$A$379,"4238|100-249"),0)+IF(SUMIFS(Raw_Census!$H$5:$H$379,Raw_Census!$A$5:$A$379,"4238|250-499")>0,SUMIFS(Raw_Census!$D$5:$D$379,Raw_Census!$A$5:$A$379,"4238|250-499"),0)+IF(SUMIFS(Raw_Census!$H$5:$H$379,Raw_Census!$A$5:$A$379,"4238|500+")>0,SUMIFS(Raw_Census!$D$5:$D$379,Raw_Census!$A$5:$A$379,"4238|500+"),0))/1000 -> 166.04619 | C8: =(SUMIFS(Raw_Census!$H$5:$H$379,Raw_Census!$A$5:$A$379,"326|20-49")+SUMIFS(Raw_Census!$H$5:$H$379,Raw_Census!$A$5:$A$379,"326|50-99")+SUMIFS(Raw_Census!$H$5:$H$379,Raw_Census!$A$5:$A$379,"326|100-249")+SUMIFS(Raw_Census!$H$5:$H$379,Raw_Census!$A$5:$A$379,"326|250-499")+SUMIFS(Raw_Census!$H$5:$H$379,Raw_Census!$A$5:$A$379,"326|500+")+SUMIFS(Raw_Census!$H$5:$H$379,Raw_Census!$A$5:$A$379,"332|20-49")+SUMIFS(Raw_Census!$H$5:$H$379,Raw_Census!$A$5:$A$379,"332|50-99")+SUMIFS(Raw_Census!$H$5:$H$379,Raw_Census!$A$5:$A$379,"332|100-249")+SUMIFS(Raw_Census!$H$5:$H$379,Raw_Census!$A$5:$A$379,"332|250-499")+SUMIFS(Raw_Census!$H$5:$H$379,Raw_Census!$A$5:$A$379,"332|500+")+SUMIFS(Raw_Census!$H$5:$H$379,Raw_Census!$A$5:$A$379,"333|20-49")+SUMIFS(Raw_Census!$H$5:$H$379,Raw_Census!$A$5:$A$379,"333|50-99")+SUMIFS(Raw_Census!$H$5:$H$379,Raw_Census!$A$5:$A$379,"333|100-249")+SUMIFS(Raw_Census!$H$5:$H$379,Raw_Census!$A$5:$A$379,"333|250-499")+SUMIFS(Raw_Census!$H$5:$H$379,Raw_Census!$A$5:$A$379,"333|500+")+SUMIFS(Raw_Census!$H$5:$H$379,Raw_Census!$A$5:$A$379,"335|20-49")+SUMIFS(Raw_Census!$H$5:$H$379,Raw_Census!$A$5:$A$379,"335|50-99")+SUMIFS(Raw_Census!$H$5:$H$379,Raw_Census!$A$5:$A$379,"335|100-249")+SUMIFS(Raw_Census!$H$5:$H$379,Raw_Census!$A$5:$A$379,"335|250-499")+SUMIFS(Raw_Census!$H$5:$H$379,Raw_Census!$A$5:$A$379,"335|500+"))/(IF(SUMIFS(Raw_Census!$H$5:$H$379,Raw_Census!$A$5:$A$379,"326|20-49")>0,SUMIFS(Raw_Census!$D$5:$D$379,Raw_Census!$A$5:$A$379,"326|20-49"),0)+IF(SUMIFS(Raw_Census!$H$5:$H$379,Raw_Census!$A$5:$A$379,"326|50-99")>0,SUMIFS(Raw_Census!$D$5:$D$379,Raw_Census!$A$5:$A$379,"326|50-99"),0)+IF(SUMIFS(Raw_Census!$H$5:$H$379,Raw_Census!$A$5:$A$379,"326|100-249")>0,SUMIFS(Raw_Census!$D$5:$D$379,Raw_Census!$A$5:$A$379,"326|100-249"),0)+IF(SUMIFS(Raw_Census!$H$5:$H$379,Raw_Census!$A$5:$A$379,"326|250-499")>0,SUMIFS(Raw_Census!$D$5:$D$379,Raw_Census!$A$5:$A$379,"326|250-499"),0)+IF(SUMIFS(Raw_Census!$H$5:$H$379,Raw_Census!$A$5:$A$379,"326|500+")>0,SUMIFS(Raw_Census!$D$5:$D$379,Raw_Census!$A$5:$A$379,"326|500+"),0)+IF(SUMIFS(Raw_Census!$H$5:$H$379,Raw_Census!$A$5:$A$379,"332|20-49")>0,SUMIFS(Raw_Census!$D$5:$D$379,Raw_Census!$A$5:$A$379,"332|20-49"),0)+IF(SUMIFS(Raw_Census!$H$5:$H$379,Raw_Census!$A$5:$A$379,"332|50-99")>0,SUMIFS(Raw_Census!$D$5:$D$379,Raw_Census!$A$5:$A$379,"332|50-99"),0)+IF(SUMIFS(Raw_Census!$H$5:$H$379,Raw_Census!$A$5:$A$379,"332|100-249")>0,SUMIFS(Raw_Census!$D$5:$D$379,Raw_Census!$A$5:$A$379,"332|100-249"),0)+IF(SUMIFS(Raw_Census!$H$5:$H$379,Raw_Census!$A$5:$A$379,"332|250-499")>0,SUMIFS(Raw_Census!$D$5:$D$379,Raw_Census!$A$5:$A$379,"332|250-499"),0)+IF(SUMIFS(Raw_Census!$H$5:$H$379,Raw_Census!$A$5:$A$379,"332|500+")>0,SUMIFS(Raw_Census!$D$5:$D$379,Raw_Census!$A$5:$A$379,"332|500+"),0)+IF(SUMIFS(Raw_Census!$H$5:$H$379,Raw_Census!$A$5:$A$379,"333|20-49")>0,SUMIFS(Raw_Census!$D$5:$D$379,Raw_Census!$A$5:$A$379,"333|20-49"),0)+IF(SUMIFS(Raw_Census!$H$5:$H$379,Raw_Census!$A$5:$A$379,"333|50-99")>0,SUMIFS(Raw_Census!$D$5:$D$379,Raw_Census!$A$5:$A$379,"333|50-99"),0)+IF(SUMIFS(Raw_Census!$H$5:$H$379,Raw_Census!$A$5:$A$379,"333|100-249")>0,SUMIFS(Raw_Census!$D$5:$D$379,Raw_Census!$A$5:$A$379,"333|100-249"),0)+IF(SUMIFS(Raw_Census!$H$5:$H$379,Raw_Census!$A$5:$A$379,"333|250-499")>0,SUMIFS(Raw_Census!$D$5:$D$379,Raw_Census!$A$5:$A$379,"333|250-499"),0)+IF(SUMIFS(Raw_Census!$H$5:$H$379,Raw_Census!$A$5:$A$379,"333|500+")>0,SUMIFS(Raw_Census!$D$5:$D$379,Raw_Census!$A$5:$A$379,"333|500+"),0)+IF(SUMIFS(Raw_Census!$H$5:$H$379,Raw_Census!$A$5:$A$379,"335|20-49")>0,SUMIFS(Raw_Census!$D$5:$D$379,Raw_Census!$A$5:$A$379,"335|20-49"),0)+IF(SUMIFS(Raw_Census!$H$5:$H$379,Raw_Census!$A$5:$A$379,"335|50-99")>0,SUMIFS(Raw_Census!$D$5:$D$379,Raw_Census!$A$5:$A$379,"335|50-99"),0)+IF(SUMIFS(Raw_Census!$H$5:$H$379,Raw_Census!$A$5:$A$379,"335|100-249")>0,SUMIFS(Raw_Census!$D$5:$D$379,Raw_Census!$A$5:$A$379,"335|100-249"),0)+IF(SUMIFS(Raw_Census!$H$5:$H$379,Raw_Census!$A$5:$A$379,"335|250-499")>0,SUMIFS(Raw_Census!$D$5:$D$379,Raw_Census!$A$5:$A$379,"335|250-499"),0)+IF(SUMIFS(Raw_Census!$H$5:$H$379,Raw_Census!$A$5:$A$379,"335|500+")>0,SUMIFS(Raw_Census!$D$5:$D$379,Raw_Census!$A$5:$A$379,"335|500+"),0))/1000 -> 51.937391 | D8: =(SUMIFS(Raw_Census!$H$5:$H$379,Raw_Census!$A$5:$A$379,"5413|20-49")+SUMIFS(Raw_Census!$H$5:$H$379,Raw_Census!$A$5:$A$379,"5413|50-99")+SUMIFS(Raw_Census!$H$5:$H$379,Raw_Census!$A$5:$A$379,"5413|100-249")+SUMIFS(Raw_Census!$H$5:$H$379,Raw_Census!$A$5:$A$379,"5413|250-499")+SUMIFS(Raw_Census!$H$5:$H$379,Raw_Census!$A$5:$A$379,"5413|500+")+SUMIFS(Raw_Census!$H$5:$H$379,Raw_Census!$A$5:$A$379,"5415|20-49")+SUMIFS(Raw_Census!$H$5:$H$379,Raw_Census!$A$5:$A$379,"5415|50-99")+SUMIFS(Raw_Census!$H$5:$H$379,Raw_Census!$A$5:$A$379,"5415|100-249")+SUMIFS(Raw_Census!$H$5:$H$379,Raw_Census!$A$5:$A$379,"5415|250-499")+SUMIFS(Raw_Census!$H$5:$H$379,Raw_Census!$A$5:$A$379,"5415|500+")+SUMIFS(Raw_Census!$H$5:$H$379,Raw_Census!$A$5:$A$379,"5416|20-49")+SUMIFS(Raw_Census!$H$5:$H$379,Raw_Census!$A$5:$A$379,"5416|50-99")+SUMIFS(Raw_Census!$H$5:$H$379,Raw_Census!$A$5:$A$379,"5416|100-249")+SUMIFS(Raw_Census!$H$5:$H$379,Raw_Census!$A$5:$A$379,"5416|250-499")+SUMIFS(Raw_Census!$H$5:$H$379,Raw_Census!$A$5:$A$379,"5416|500+")+SUMIFS(Raw_Census!$H$5:$H$379,Raw_Census!$A$5:$A$379,"5418|20-49")+SUMIFS(Raw_Census!$H$5:$H$379,Raw_Census!$A$5:$A$379,"5418|50-99")+SUMIFS(Raw_Census!$H$5:$H$379,Raw_Census!$A$5:$A$379,"5418|100-249")+SUMIFS(Raw_Census!$H$5:$H$379,Raw_Census!$A$5:$A$379,"5418|250-499")+SUMIFS(Raw_Census!$H$5:$H$379,Raw_Census!$A$5:$A$379,"5418|500+"))/(IF(SUMIFS(Raw_Census!$H$5:$H$379,Raw_Census!$A$5:$A$379,"5413|20-49")>0,SUMIFS(Raw_Census!$D$5:$D$379,Raw_Census!$A$5:$A$379,"5413|20-49"),0)+IF(SUMIFS(Raw_Census!$H$5:$H$379,Raw_Census!$A$5:$A$379,"5413|50-99")>0,SUMIFS(Raw_Census!$D$5:$D$379,Raw_Census!$A$5:$A$379,"5413|50-99"),0)+IF(SUMIFS(Raw_Census!$H$5:$H$379,Raw_Census!$A$5:$A$379,"5413|100-249")>0,SUMIFS(Raw_Census!$D$5:$D$379,Raw_Census!$A$5:$A$379,"5413|100-249"),0)+IF(SUMIFS(Raw_Census!$H$5:$H$379,Raw_Census!$A$5:$A$379,"5413|250-499")>0,SUMIFS(Raw_Census!$D$5:$D$379,Raw_Census!$A$5:$A$379,"5413|250-499"),0)+IF(SUMIFS(Raw_Census!$H$5:$H$379,Raw_Census!$A$5:$A$379,"5413|500+")>0,SUMIFS(Raw_Census!$D$5:$D$379,Raw_Census!$A$5:$A$379,"5413|500+"),0)+IF(SUMIFS(Raw_Census!$H$5:$H$379,Raw_Census!$A$5:$A$379,"5415|20-49")>0,SUMIFS(Raw_Census!$D$5:$D$379,Raw_Census!$A$5:$A$379,"5415|20-49"),0)+IF(SUMIFS(Raw_Census!$H$5:$H$379,Raw_Census!$A$5:$A$379,"5415|50-99")>0,SUMIFS(Raw_Census!$D$5:$D$379,Raw_Census!$A$5:$A$379,"5415|50-99"),0)+IF(SUMIFS(Raw_Census!$H$5:$H$379,Raw_Census!$A$5:$A$379,"5415|100-249")>0,SUMIFS(Raw_Census!$D$5:$D$379,Raw_Census!$A$5:$A$379,"5415|100-249"),0)+IF(SUMIFS(Raw_Census!$H$5:$H$379,Raw_Census!$A$5:$A$379,"5415|250-499")>0,SUMIFS(Raw_Census!$D$5:$D$379,Raw_Census!$A$5:$A$379,"5415|250-499"),0)+IF(SUMIFS(Raw_Census!$H$5:$H$379,Raw_Census!$A$5:$A$379,"5415|500+")>0,SUMIFS(Raw_Census!$D$5:$D$379,Raw_Census!$A$5:$A$379,"5415|500+"),0)+IF(SUMIFS(Raw_Census!$H$5:$H$379,Raw_Census!$A$5:$A$379,"5416|20-49")>0,SUMIFS(Raw_Census!$D$5:$D$379,Raw_Census!$A$5:$A$379,"5416|20-49"),0)+IF(SUMIFS(Raw_Census!$H$5:$H$379,Raw_Census!$A$5:$A$379,"5416|50-99")>0,SUMIFS(Raw_Census!$D$5:$D$379,Raw_Census!$A$5:$A$379,"5416|50-99"),0)+IF(SUMIFS(Raw_Census!$H$5:$H$379,Raw_Census!$A$5:$A$379,"5416|100-249")>0,SUMIFS(Raw_Census!$D$5:$D$379,Raw_Census!$A$5:$A$379,"5416|100-249"),0)+IF(SUMIFS(Raw_Census!$H$5:$H$379,Raw_Census!$A$5:$A$379,"5416|250-499")>0,SUMIFS(Raw_Census!$D$5:$D$379,Raw_Census!$A$5:$A$379,"5416|250-499"),0)+IF(SUMIFS(Raw_Census!$H$5:$H$379,Raw_Census!$A$5:$A$379,"5416|500+")>0,SUMIFS(Raw_Census!$D$5:$D$379,Raw_Census!$A$5:$A$379,"5416|500+"),0)+IF(SUMIFS(Raw_Census!$H$5:$H$379,Raw_Census!$A$5:$A$379,"5418|20-49")>0,SUMIFS(Raw_Census!$D$5:$D$379,Raw_Census!$A$5:$A$379,"5418|20-49"),0)+IF(SUMIFS(Raw_Census!$H$5:$H$379,Raw_Census!$A$5:$A$379,"5418|50-99")>0,SUMIFS(Raw_Census!$D$5:$D$379,Raw_Census!$A$5:$A$379,"5418|50-99"),0)+IF(SUMIFS(Raw_Census!$H$5:$H$379,Raw_Census!$A$5:$A$379,"5418|100-249")>0,SUMIFS(Raw_Census!$D$5:$D$379,Raw_Census!$A$5:$A$379,"5418|100-249"),0)+IF(SUMIFS(Raw_Census!$H$5:$H$379,Raw_Census!$A$5:$A$379,"5418|250-499")>0,SUMIFS(Raw_Census!$D$5:$D$379,Raw_Census!$A$5:$A$379,"5418|250-499"),0)+IF(SUMIFS(Raw_Census!$H$5:$H$379,Raw_Census!$A$5:$A$379,"5418|500+")>0,SUMIFS(Raw_Census!$D$5:$D$379,Raw_Census!$A$5:$A$379,"5418|500+"),0))/1000 -> 38.089748 | E8: =(SUMIFS(Raw_Census!$H$5:$H$379,Raw_Census!$A$5:$A$379,"5132|20-49")+SUMIFS(Raw_Census!$H$5:$H$379,Raw_Census!$A$5:$A$379,"5132|50-99")+SUMIFS(Raw_Census!$H$5:$H$379,Raw_Census!$A$5:$A$379,"5132|100-249")+SUMIFS(Raw_Census!$H$5:$H$379,Raw_Census!$A$5:$A$379,"5132|250-499")+SUMIFS(Raw_Census!$H$5:$H$379,Raw_Census!$A$5:$A$379,"5132|500+"))/(IF(SUMIFS(Raw_Census!$H$5:$H$379,Raw_Census!$A$5:$A$379,"5132|20-49")>0,SUMIFS(Raw_Census!$D$5:$D$379,Raw_Census!$A$5:$A$379,"5132|20-49"),0)+IF(SUMIFS(Raw_Census!$H$5:$H$379,Raw_Census!$A$5:$A$379,"5132|50-99")>0,SUMIFS(Raw_Census!$D$5:$D$379,Raw_Census!$A$5:$A$379,"5132|50-99"),0)+IF(SUMIFS(Raw_Census!$H$5:$H$379,Raw_Census!$A$5:$A$379,"5132|100-249")>0,SUMIFS(Raw_Census!$D$5:$D$379,Raw_Census!$A$5:$A$379,"5132|100-249"),0)+IF(SUMIFS(Raw_Census!$H$5:$H$379,Raw_Census!$A$5:$A$379,"5132|250-499")>0,SUMIFS(Raw_Census!$D$5:$D$379,Raw_Census!$A$5:$A$379,"5132|250-499"),0)+IF(SUMIFS(Raw_Census!$H$5:$H$379,Raw_Census!$A$5:$A$379,"5132|500+")>0,SUMIFS(Raw_Census!$D$5:$D$379,Raw_Census!$A$5:$A$379,"5132|500+"),0))/1000 -> 144.17364 | G8: $M per firm [C] | H8: Ability to pay. Denominator excludes cells whose receipts are suppressed.
A9: Avg receipts per firm, 20–99 employees ($M) | B9: =(SUMIFS(Raw_Census!$H$5:$H$379,Raw_Census!$A$5:$A$379,"4235|20-49")+SUMIFS(Raw_Census!$H$5:$H$379,Raw_Census!$A$5:$A$379,"4235|50-99")+SUMIFS(Raw_Census!$H$5:$H$379,Raw_Census!$A$5:$A$379,"4236|20-49")+SUMIFS(Raw_Census!$H$5:$H$379,Raw_Census!$A$5:$A$379,"4236|50-99")+SUMIFS(Raw_Census!$H$5:$H$379,Raw_Census!$A$5:$A$379,"4237|20-49")+SUMIFS(Raw_Census!$H$5:$H$379,Raw_Census!$A$5:$A$379,"4237|50-99")+SUMIFS(Raw_Census!$H$5:$H$379,Raw_Census!$A$5:$A$379,"4238|20-49")+SUMIFS(Raw_Census!$H$5:$H$379,Raw_Census!$A$5:$A$379,"4238|50-99"))/(IF(SUMIFS(Raw_Census!$H$5:$H$379,Raw_Census!$A$5:$A$379,"4235|20-49")>0,SUMIFS(Raw_Census!$D$5:$D$379,Raw_Census!$A$5:$A$379,"4235|20-49"),0)+IF(SUMIFS(Raw_Census!$H$5:$H$379,Raw_Census!$A$5:$A$379,"4235|50-99")>0,SUMIFS(Raw_Census!$D$5:$D$379,Raw_Census!$A$5:$A$379,"4235|50-99"),0)+IF(SUMIFS(Raw_Census!$H$5:$H$379,Raw_Census!$A$5:$A$379,"4236|20-49")>0,SUMIFS(Raw_Census!$D$5:$D$379,Raw_Census!$A$5:$A$379,"4236|20-49"),0)+IF(SUMIFS(Raw_Census!$H$5:$H$379,Raw_Census!$A$5:$A$379,"4236|50-99")>0,SUMIFS(Raw_Census!$D$5:$D$379,Raw_Census!$A$5:$A$379,"4236|50-99"),0)+IF(SUMIFS(Raw_Census!$H$5:$H$379,Raw_Census!$A$5:$A$379,"4237|20-49")>0,SUMIFS(Raw_Census!$D$5:$D$379,Raw_Census!$A$5:$A$379,"4237|20-49"),0)+IF(SUMIFS(Raw_Census!$H$5:$H$379,Raw_Census!$A$5:$A$379,"4237|50-99")>0,SUMIFS(Raw_Census!$D$5:$D$379,Raw_Census!$A$5:$A$379,"4237|50-99"),0)+IF(SUMIFS(Raw_Census!$H$5:$H$379,Raw_Census!$A$5:$A$379,"4238|20-49")>0,SUMIFS(Raw_Census!$D$5:$D$379,Raw_Census!$A$5:$A$379,"4238|20-49"),0)+IF(SUMIFS(Raw_Census!$H$5:$H$379,Raw_Census!$A$5:$A$379,"4238|50-99")>0,SUMIFS(Raw_Census!$D$5:$D$379,Raw_Census!$A$5:$A$379,"4238|50-99"),0))/1000 -> 40.572669 | C9: =(SUMIFS(Raw_Census!$H$5:$H$379,Raw_Census!$A$5:$A$379,"326|20-49")+SUMIFS(Raw_Census!$H$5:$H$379,Raw_Census!$A$5:$A$379,"326|50-99")+SUMIFS(Raw_Census!$H$5:$H$379,Raw_Census!$A$5:$A$379,"332|20-49")+SUMIFS(Raw_Census!$H$5:$H$379,Raw_Census!$A$5:$A$379,"332|50-99")+SUMIFS(Raw_Census!$H$5:$H$379,Raw_Census!$A$5:$A$379,"333|20-49")+SUMIFS(Raw_Census!$H$5:$H$379,Raw_Census!$A$5:$A$379,"333|50-99")+SUMIFS(Raw_Census!$H$5:$H$379,Raw_Census!$A$5:$A$379,"335|20-49")+SUMIFS(Raw_Census!$H$5:$H$379,Raw_Census!$A$5:$A$379,"335|50-99"))/(IF(SUMIFS(Raw_Census!$H$5:$H$379,Raw_Census!$A$5:$A$379,"326|20-49")>0,SUMIFS(Raw_Census!$D$5:$D$379,Raw_Census!$A$5:$A$379,"326|20-49"),0)+IF(SUMIFS(Raw_Census!$H$5:$H$379,Raw_Census!$A$5:$A$379,"326|50-99")>0,SUMIFS(Raw_Census!$D$5:$D$379,Raw_Census!$A$5:$A$379,"326|50-99"),0)+IF(SUMIFS(Raw_Census!$H$5:$H$379,Raw_Census!$A$5:$A$379,"332|20-49")>0,SUMIFS(Raw_Census!$D$5:$D$379,Raw_Census!$A$5:$A$379,"332|20-49"),0)+IF(SUMIFS(Raw_Census!$H$5:$H$379,Raw_Census!$A$5:$A$379,"332|50-99")>0,SUMIFS(Raw_Census!$D$5:$D$379,Raw_Census!$A$5:$A$379,"332|50-99"),0)+IF(SUMIFS(Raw_Census!$H$5:$H$379,Raw_Census!$A$5:$A$379,"333|20-49")>0,SUMIFS(Raw_Census!$D$5:$D$379,Raw_Census!$A$5:$A$379,"333|20-49"),0)+IF(SUMIFS(Raw_Census!$H$5:$H$379,Raw_Census!$A$5:$A$379,"333|50-99")>0,SUMIFS(Raw_Census!$D$5:$D$379,Raw_Census!$A$5:$A$379,"333|50-99"),0)+IF(SUMIFS(Raw_Census!$H$5:$H$379,Raw_Census!$A$5:$A$379,"335|20-49")>0,SUMIFS(Raw_Census!$D$5:$D$379,Raw_Census!$A$5:$A$379,"335|20-49"),0)+IF(SUMIFS(Raw_Census!$H$5:$H$379,Raw_Census!$A$5:$A$379,"335|50-99")>0,SUMIFS(Raw_Census!$D$5:$D$379,Raw_Census!$A$5:$A$379,"335|50-99"),0))/1000 -> 11.748174 | D9: =(SUMIFS(Raw_Census!$H$5:$H$379,Raw_Census!$A$5:$A$379,"5413|20-49")+SUMIFS(Raw_Census!$H$5:$H$379,Raw_Census!$A$5:$A$379,"5413|50-99")+SUMIFS(Raw_Census!$H$5:$H$379,Raw_Census!$A$5:$A$379,"5415|20-49")+SUMIFS(Raw_Census!$H$5:$H$379,Raw_Census!$A$5:$A$379,"5415|50-99")+SUMIFS(Raw_Census!$H$5:$H$379,Raw_Census!$A$5:$A$379,"5416|20-49")+SUMIFS(Raw_Census!$H$5:$H$379,Raw_Census!$A$5:$A$379,"5416|50-99")+SUMIFS(Raw_Census!$H$5:$H$379,Raw_Census!$A$5:$A$379,"5418|20-49")+SUMIFS(Raw_Census!$H$5:$H$379,Raw_Census!$A$5:$A$379,"5418|50-99"))/(IF(SUMIFS(Raw_Census!$H$5:$H$379,Raw_Census!$A$5:$A$379,"5413|20-49")>0,SUMIFS(Raw_Census!$D$5:$D$379,Raw_Census!$A$5:$A$379,"5413|20-49"),0)+IF(SUMIFS(Raw_Census!$H$5:$H$379,Raw_Census!$A$5:$A$379,"5413|50-99")>0,SUMIFS(Raw_Census!$D$5:$D$379,Raw_Census!$A$5:$A$379,"5413|50-99"),0)+IF(SUMIFS(Raw_Census!$H$5:$H$379,Raw_Census!$A$5:$A$379,"5415|20-49")>0,SUMIFS(Raw_Census!$D$5:$D$379,Raw_Census!$A$5:$A$379,"5415|20-49"),0)+IF(SUMIFS(Raw_Census!$H$5:$H$379,Raw_Census!$A$5:$A$379,"5415|50-99")>0,SUMIFS(Raw_Census!$D$5:$D$379,Raw_Census!$A$5:$A$379,"5415|50-99"),0)+IF(SUMIFS(Raw_Census!$H$5:$H$379,Raw_Census!$A$5:$A$379,"5416|20-49")>0,SUMIFS(Raw_Census!$D$5:$D$379,Raw_Census!$A$5:$A$379,"5416|20-49"),0)+IF(SUMIFS(Raw_Census!$H$5:$H$379,Raw_Census!$A$5:$A$379,"5416|50-99")>0,SUMIFS(Raw_Census!$D$5:$D$379,Raw_Census!$A$5:$A$379,"5416|50-99"),0)+IF(SUMIFS(Raw_Census!$H$5:$H$379,Raw_Census!$A$5:$A$379,"5418|20-49")>0,SUMIFS(Raw_Census!$D$5:$D$379,Raw_Census!$A$5:$A$379,"5418|20-49"),0)+IF(SUMIFS(Raw_Census!$H$5:$H$379,Raw_Census!$A$5:$A$379,"5418|50-99")>0,SUMIFS(Raw_Census!$D$5:$D$379,Raw_Census!$A$5:$A$379,"5418|50-99"),0))/1000 -> 10.091837 | E9: =(SUMIFS(Raw_Census!$H$5:$H$379,Raw_Census!$A$5:$A$379,"5132|20-49")+SUMIFS(Raw_Census!$H$5:$H$379,Raw_Census!$A$5:$A$379,"5132|50-99"))/(IF(SUMIFS(Raw_Census!$H$5:$H$379,Raw_Census!$A$5:$A$379,"5132|20-49")>0,SUMIFS(Raw_Census!$D$5:$D$379,Raw_Census!$A$5:$A$379,"5132|20-49"),0)+IF(SUMIFS(Raw_Census!$H$5:$H$379,Raw_Census!$A$5:$A$379,"5132|50-99")>0,SUMIFS(Raw_Census!$D$5:$D$379,Raw_Census!$A$5:$A$379,"5132|50-99"),0))/1000 -> 13.638612 | G9: $M per firm [C] | H9: Same metric for the SMB band only — removes the skew from very large firms.
A10: Avg employees per firm, 20+ firms | B10: =(SUMIFS(Raw_Census!$G$5:$G$379,Raw_Census!$A$5:$A$379,"4235|20-49")+SUMIFS(Raw_Census!$G$5:$G$379,Raw_Census!$A$5:$A$379,"4235|50-99")+SUMIFS(Raw_Census!$G$5:$G$379,Raw_Census!$A$5:$A$379,"4235|100-249")+SUMIFS(Raw_Census!$G$5:$G$379,Raw_Census!$A$5:$A$379,"4235|250-499")+SUMIFS(Raw_Census!$G$5:$G$379,Raw_Census!$A$5:$A$379,"4235|500+")+SUMIFS(Raw_Census!$G$5:$G$379,Raw_Census!$A$5:$A$379,"4236|20-49")+SUMIFS(Raw_Census!$G$5:$G$379,Raw_Census!$A$5:$A$379,"4236|50-99")+SUMIFS(Raw_Census!$G$5:$G$379,Raw_Census!$A$5:$A$379,"4236|100-249")+SUMIFS(Raw_Census!$G$5:$G$379,Raw_Census!$A$5:$A$379,"4236|250-499")+SUMIFS(Raw_Census!$G$5:$G$379,Raw_Census!$A$5:$A$379,"4236|500+")+SUMIFS(Raw_Census!$G$5:$G$379,Raw_Census!$A$5:$A$379,"4237|20-49")+SUMIFS(Raw_Census!$G$5:$G$379,Raw_Census!$A$5:$A$379,"4237|50-99")+SUMIFS(Raw_Census!$G$5:$G$379,Raw_Census!$A$5:$A$379,"4237|100-249")+SUMIFS(Raw_Census!$G$5:$G$379,Raw_Census!$A$5:$A$379,"4237|250-499")+SUMIFS(Raw_Census!$G$5:$G$379,Raw_Census!$A$5:$A$379,"4237|500+")+SUMIFS(Raw_Census!$G$5:$G$379,Raw_Census!$A$5:$A$379,"4238|20-49")+SUMIFS(Raw_Census!$G$5:$G$379,Raw_Census!$A$5:$A$379,"4238|50-99")+SUMIFS(Raw_Census!$G$5:$G$379,Raw_Census!$A$5:$A$379,"4238|100-249")+SUMIFS(Raw_Census!$G$5:$G$379,Raw_Census!$A$5:$A$379,"4238|250-499")+SUMIFS(Raw_Census!$G$5:$G$379,Raw_Census!$A$5:$A$379,"4238|500+"))/(IF(SUMIFS(Raw_Census!$G$5:$G$379,Raw_Census!$A$5:$A$379,"4235|20-49")>0,SUMIFS(Raw_Census!$D$5:$D$379,Raw_Census!$A$5:$A$379,"4235|20-49"),0)+IF(SUMIFS(Raw_Census!$G$5:$G$379,Raw_Census!$A$5:$A$379,"4235|50-99")>0,SUMIFS(Raw_Census!$D$5:$D$379,Raw_Census!$A$5:$A$379,"4235|50-99"),0)+IF(SUMIFS(Raw_Census!$G$5:$G$379,Raw_Census!$A$5:$A$379,"4235|100-249")>0,SUMIFS(Raw_Census!$D$5:$D$379,Raw_Census!$A$5:$A$379,"4235|100-249"),0)+IF(SUMIFS(Raw_Census!$G$5:$G$379,Raw_Census!$A$5:$A$379,"4235|250-499")>0,SUMIFS(Raw_Census!$D$5:$D$379,Raw_Census!$A$5:$A$379,"4235|250-499"),0)+IF(SUMIFS(Raw_Census!$G$5:$G$379,Raw_Census!$A$5:$A$379,"4235|500+")>0,SUMIFS(Raw_Census!$D$5:$D$379,Raw_Census!$A$5:$A$379,"4235|500+"),0)+IF(SUMIFS(Raw_Census!$G$5:$G$379,Raw_Census!$A$5:$A$379,"4236|20-49")>0,SUMIFS(Raw_Census!$D$5:$D$379,Raw_Census!$A$5:$A$379,"4236|20-49"),0)+IF(SUMIFS(Raw_Census!$G$5:$G$379,Raw_Census!$A$5:$A$379,"4236|50-99")>0,SUMIFS(Raw_Census!$D$5:$D$379,Raw_Census!$A$5:$A$379,"4236|50-99"),0)+IF(SUMIFS(Raw_Census!$G$5:$G$379,Raw_Census!$A$5:$A$379,"4236|100-249")>0,SUMIFS(Raw_Census!$D$5:$D$379,Raw_Census!$A$5:$A$379,"4236|100-249"),0)+IF(SUMIFS(Raw_Census!$G$5:$G$379,Raw_Census!$A$5:$A$379,"4236|250-499")>0,SUMIFS(Raw_Census!$D$5:$D$379,Raw_Census!$A$5:$A$379,"4236|250-499"),0)+IF(SUMIFS(Raw_Census!$G$5:$G$379,Raw_Census!$A$5:$A$379,"4236|500+")>0,SUMIFS(Raw_Census!$D$5:$D$379,Raw_Census!$A$5:$A$379,"4236|500+"),0)+IF(SUMIFS(Raw_Census!$G$5:$G$379,Raw_Census!$A$5:$A$379,"4237|20-49")>0,SUMIFS(Raw_Census!$D$5:$D$379,Raw_Census!$A$5:$A$379,"4237|20-49"),0)+IF(SUMIFS(Raw_Census!$G$5:$G$379,Raw_Census!$A$5:$A$379,"4237|50-99")>0,SUMIFS(Raw_Census!$D$5:$D$379,Raw_Census!$A$5:$A$379,"4237|50-99"),0)+IF(SUMIFS(Raw_Census!$G$5:$G$379,Raw_Census!$A$5:$A$379,"4237|100-249")>0,SUMIFS(Raw_Census!$D$5:$D$379,Raw_Census!$A$5:$A$379,"4237|100-249"),0)+IF(SUMIFS(Raw_Census!$G$5:$G$379,Raw_Census!$A$5:$A$379,"4237|250-499")>0,SUMIFS(Raw_Census!$D$5:$D$379,Raw_Census!$A$5:$A$379,"4237|250-499"),0)+IF(SUMIFS(Raw_Census!$G$5:$G$379,Raw_Census!$A$5:$A$379,"4237|500+")>0,SUMIFS(Raw_Census!$D$5:$D$379,Raw_Census!$A$5:$A$379,"4237|500+"),0)+IF(SUMIFS(Raw_Census!$G$5:$G$379,Raw_Census!$A$5:$A$379,"4238|20-49")>0,SUMIFS(Raw_Census!$D$5:$D$379,Raw_Census!$A$5:$A$379,"4238|20-49"),0)+IF(SUMIFS(Raw_Census!$G$5:$G$379,Raw_Census!$A$5:$A$379,"4238|50-99")>0,SUMIFS(Raw_Census!$D$5:$D$379,Raw_Census!$A$5:$A$379,"4238|50-99"),0)+IF(SUMIFS(Raw_Census!$G$5:$G$379,Raw_Census!$A$5:$A$379,"4238|100-249")>0,SUMIFS(Raw_Census!$D$5:$D$379,Raw_Census!$A$5:$A$379,"4238|100-249"),0)+IF(SUMIFS(Raw_Census!$G$5:$G$379,Raw_Census!$A$5:$A$379,"4238|250-499")>0,SUMIFS(Raw_Census!$D$5:$D$379,Raw_Census!$A$5:$A$379,"4238|250-499"),0)+IF(SUMIFS(Raw_Census!$G$5:$G$379,Raw_Census!$A$5:$A$379,"4238|500+")>0,SUMIFS(Raw_Census!$D$5:$D$379,Raw_Census!$A$5:$A$379,"4238|500+"),0)) -> 126.14383 | C10: =(SUMIFS(Raw_Census!$G$5:$G$379,Raw_Census!$A$5:$A$379,"326|20-49")+SUMIFS(Raw_Census!$G$5:$G$379,Raw_Census!$A$5:$A$379,"326|50-99")+SUMIFS(Raw_Census!$G$5:$G$379,Raw_Census!$A$5:$A$379,"326|100-249")+SUMIFS(Raw_Census!$G$5:$G$379,Raw_Census!$A$5:$A$379,"326|250-499")+SUMIFS(Raw_Census!$G$5:$G$379,Raw_Census!$A$5:$A$379,"326|500+")+SUMIFS(Raw_Census!$G$5:$G$379,Raw_Census!$A$5:$A$379,"332|20-49")+SUMIFS(Raw_Census!$G$5:$G$379,Raw_Census!$A$5:$A$379,"332|50-99")+SUMIFS(Raw_Census!$G$5:$G$379,Raw_Census!$A$5:$A$379,"332|100-249")+SUMIFS(Raw_Census!$G$5:$G$379,Raw_Census!$A$5:$A$379,"332|250-499")+SUMIFS(Raw_Census!$G$5:$G$379,Raw_Census!$A$5:$A$379,"332|500+")+SUMIFS(Raw_Census!$G$5:$G$379,Raw_Census!$A$5:$A$379,"333|20-49")+SUMIFS(Raw_Census!$G$5:$G$379,Raw_Census!$A$5:$A$379,"333|50-99")+SUMIFS(Raw_Census!$G$5:$G$379,Raw_Census!$A$5:$A$379,"333|100-249")+SUMIFS(Raw_Census!$G$5:$G$379,Raw_Census!$A$5:$A$379,"333|250-499")+SUMIFS(Raw_Census!$G$5:$G$379,Raw_Census!$A$5:$A$379,"333|500+")+SUMIFS(Raw_Census!$G$5:$G$379,Raw_Census!$A$5:$A$379,"335|20-49")+SUMIFS(Raw_Census!$G$5:$G$379,Raw_Census!$A$5:$A$379,"335|50-99")+SUMIFS(Raw_Census!$G$5:$G$379,Raw_Census!$A$5:$A$379,"335|100-249")+SUMIFS(Raw_Census!$G$5:$G$379,Raw_Census!$A$5:$A$379,"335|250-499")+SUMIFS(Raw_Census!$G$5:$G$379,Raw_Census!$A$5:$A$379,"335|500+"))/(IF(SUMIFS(Raw_Census!$G$5:$G$379,Raw_Census!$A$5:$A$379,"326|20-49")>0,SUMIFS(Raw_Census!$D$5:$D$379,Raw_Census!$A$5:$A$379,"326|20-49"),0)+IF(SUMIFS(Raw_Census!$G$5:$G$379,Raw_Census!$A$5:$A$379,"326|50-99")>0,SUMIFS(Raw_Census!$D$5:$D$379,Raw_Census!$A$5:$A$379,"326|50-99"),0)+IF(SUMIFS(Raw_Census!$G$5:$G$379,Raw_Census!$A$5:$A$379,"326|100-249")>0,SUMIFS(Raw_Census!$D$5:$D$379,Raw_Census!$A$5:$A$379,"326|100-249"),0)+IF(SUMIFS(Raw_Census!$G$5:$G$379,Raw_Census!$A$5:$A$379,"326|250-499")>0,SUMIFS(Raw_Census!$D$5:$D$379,Raw_Census!$A$5:$A$379,"326|250-499"),0)+IF(SUMIFS(Raw_Census!$G$5:$G$379,Raw_Census!$A$5:$A$379,"326|500+")>0,SUMIFS(Raw_Census!$D$5:$D$379,Raw_Census!$A$5:$A$379,"326|500+"),0)+IF(SUMIFS(Raw_Census!$G$5:$G$379,Raw_Census!$A$5:$A$379,"332|20-49")>0,SUMIFS(Raw_Census!$D$5:$D$379,Raw_Census!$A$5:$A$379,"332|20-49"),0)+IF(SUMIFS(Raw_Census!$G$5:$G$379,Raw_Census!$A$5:$A$379,"332|50-99")>0,SUMIFS(Raw_Census!$D$5:$D$379,Raw_Census!$A$5:$A$379,"332|50-99"),0)+IF(SUMIFS(Raw_Census!$G$5:$G$379,Raw_Census!$A$5:$A$379,"332|100-249")>0,SUMIFS(Raw_Census!$D$5:$D$379,Raw_Census!$A$5:$A$379,"332|100-249"),0)+IF(SUMIFS(Raw_Census!$G$5:$G$379,Raw_Census!$A$5:$A$379,"332|250-499")>0,SUMIFS(Raw_Census!$D$5:$D$379,Raw_Census!$A$5:$A$379,"332|250-499"),0)+IF(SUMIFS(Raw_Census!$G$5:$G$379,Raw_Census!$A$5:$A$379,"332|500+")>0,SUMIFS(Raw_Census!$D$5:$D$379,Raw_Census!$A$5:$A$379,"332|500+"),0)+IF(SUMIFS(Raw_Census!$G$5:$G$379,Raw_Census!$A$5:$A$379,"333|20-49")>0,SUMIFS(Raw_Census!$D$5:$D$379,Raw_Census!$A$5:$A$379,"333|20-49"),0)+IF(SUMIFS(Raw_Census!$G$5:$G$379,Raw_Census!$A$5:$A$379,"333|50-99")>0,SUMIFS(Raw_Census!$D$5:$D$379,Raw_Census!$A$5:$A$379,"333|50-99"),0)+IF(SUMIFS(Raw_Census!$G$5:$G$379,Raw_Census!$A$5:$A$379,"333|100-249")>0,SUMIFS(Raw_Census!$D$5:$D$379,Raw_Census!$A$5:$A$379,"333|100-249"),0)+IF(SUMIFS(Raw_Census!$G$5:$G$379,Raw_Census!$A$5:$A$379,"333|250-499")>0,SUMIFS(Raw_Census!$D$5:$D$379,Raw_Census!$A$5:$A$379,"333|250-499"),0)+IF(SUMIFS(Raw_Census!$G$5:$G$379,Raw_Census!$A$5:$A$379,"333|500+")>0,SUMIFS(Raw_Census!$D$5:$D$379,Raw_Census!$A$5:$A$379,"333|500+"),0)+IF(SUMIFS(Raw_Census!$G$5:$G$379,Raw_Census!$A$5:$A$379,"335|20-49")>0,SUMIFS(Raw_Census!$D$5:$D$379,Raw_Census!$A$5:$A$379,"335|20-49"),0)+IF(SUMIFS(Raw_Census!$G$5:$G$379,Raw_Census!$A$5:$A$379,"335|50-99")>0,SUMIFS(Raw_Census!$D$5:$D$379,Raw_Census!$A$5:$A$379,"335|50-99"),0)+IF(SUMIFS(Raw_Census!$G$5:$G$379,Raw_Census!$A$5:$A$379,"335|100-249")>0,SUMIFS(Raw_Census!$D$5:$D$379,Raw_Census!$A$5:$A$379,"335|100-249"),0)+IF(SUMIFS(Raw_Census!$G$5:$G$379,Raw_Census!$A$5:$A$379,"335|250-499")>0,SUMIFS(Raw_Census!$D$5:$D$379,Raw_Census!$A$5:$A$379,"335|250-499"),0)+IF(SUMIFS(Raw_Census!$G$5:$G$379,Raw_Census!$A$5:$A$379,"335|500+")>0,SUMIFS(Raw_Census!$D$5:$D$379,Raw_Census!$A$5:$A$379,"335|500+"),0)) -> 133.24623 | D10: =(SUMIFS(Raw_Census!$G$5:$G$379,Raw_Census!$A$5:$A$379,"5413|20-49")+SUMIFS(Raw_Census!$G$5:$G$379,Raw_Census!$A$5:$A$379,"5413|50-99")+SUMIFS(Raw_Census!$G$5:$G$379,Raw_Census!$A$5:$A$379,"5413|100-249")+SUMIFS(Raw_Census!$G$5:$G$379,Raw_Census!$A$5:$A$379,"5413|250-499")+SUMIFS(Raw_Census!$G$5:$G$379,Raw_Census!$A$5:$A$379,"5413|500+")+SUMIFS(Raw_Census!$G$5:$G$379,Raw_Census!$A$5:$A$379,"5415|20-49")+SUMIFS(Raw_Census!$G$5:$G$379,Raw_Census!$A$5:$A$379,"5415|50-99")+SUMIFS(Raw_Census!$G$5:$G$379,Raw_Census!$A$5:$A$379,"5415|100-249")+SUMIFS(Raw_Census!$G$5:$G$379,Raw_Census!$A$5:$A$379,"5415|250-499")+SUMIFS(Raw_Census!$G$5:$G$379,Raw_Census!$A$5:$A$379,"5415|500+")+SUMIFS(Raw_Census!$G$5:$G$379,Raw_Census!$A$5:$A$379,"5416|20-49")+SUMIFS(Raw_Census!$G$5:$G$379,Raw_Census!$A$5:$A$379,"5416|50-99")+SUMIFS(Raw_Census!$G$5:$G$379,Raw_Census!$A$5:$A$379,"5416|100-249")+SUMIFS(Raw_Census!$G$5:$G$379,Raw_Census!$A$5:$A$379,"5416|250-499")+SUMIFS(Raw_Census!$G$5:$G$379,Raw_Census!$A$5:$A$379,"5416|500+")+SUMIFS(Raw_Census!$G$5:$G$379,Raw_Census!$A$5:$A$379,"5418|20-49")+SUMIFS(Raw_Census!$G$5:$G$379,Raw_Census!$A$5:$A$379,"5418|50-99")+SUMIFS(Raw_Census!$G$5:$G$379,Raw_Census!$A$5:$A$379,"5418|100-249")+SUMIFS(Raw_Census!$G$5:$G$379,Raw_Census!$A$5:$A$379,"5418|250-499")+SUMIFS(Raw_Census!$G$5:$G$379,Raw_Census!$A$5:$A$379,"5418|500+"))/(IF(SUMIFS(Raw_Census!$G$5:$G$379,Raw_Census!$A$5:$A$379,"5413|20-49")>0,SUMIFS(Raw_Census!$D$5:$D$379,Raw_Census!$A$5:$A$379,"5413|20-49"),0)+IF(SUMIFS(Raw_Census!$G$5:$G$379,Raw_Census!$A$5:$A$379,"5413|50-99")>0,SUMIFS(Raw_Census!$D$5:$D$379,Raw_Census!$A$5:$A$379,"5413|50-99"),0)+IF(SUMIFS(Raw_Census!$G$5:$G$379,Raw_Census!$A$5:$A$379,"5413|100-249")>0,SUMIFS(Raw_Census!$D$5:$D$379,Raw_Census!$A$5:$A$379,"5413|100-249"),0)+IF(SUMIFS(Raw_Census!$G$5:$G$379,Raw_Census!$A$5:$A$379,"5413|250-499")>0,SUMIFS(Raw_Census!$D$5:$D$379,Raw_Census!$A$5:$A$379,"5413|250-499"),0)+IF(SUMIFS(Raw_Census!$G$5:$G$379,Raw_Census!$A$5:$A$379,"5413|500+")>0,SUMIFS(Raw_Census!$D$5:$D$379,Raw_Census!$A$5:$A$379,"5413|500+"),0)+IF(SUMIFS(Raw_Census!$G$5:$G$379,Raw_Census!$A$5:$A$379,"5415|20-49")>0,SUMIFS(Raw_Census!$D$5:$D$379,Raw_Census!$A$5:$A$379,"5415|20-49"),0)+IF(SUMIFS(Raw_Census!$G$5:$G$379,Raw_Census!$A$5:$A$379,"5415|50-99")>0,SUMIFS(Raw_Census!$D$5:$D$379,Raw_Census!$A$5:$A$379,"5415|50-99"),0)+IF(SUMIFS(Raw_Census!$G$5:$G$379,Raw_Census!$A$5:$A$379,"5415|100-249")>0,SUMIFS(Raw_Census!$D$5:$D$379,Raw_Census!$A$5:$A$379,"5415|100-249"),0)+IF(SUMIFS(Raw_Census!$G$5:$G$379,Raw_Census!$A$5:$A$379,"5415|250-499")>0,SUMIFS(Raw_Census!$D$5:$D$379,Raw_Census!$A$5:$A$379,"5415|250-499"),0)+IF(SUMIFS(Raw_Census!$G$5:$G$379,Raw_Census!$A$5:$A$379,"5415|500+")>0,SUMIFS(Raw_Census!$D$5:$D$379,Raw_Census!$A$5:$A$379,"5415|500+"),0)+IF(SUMIFS(Raw_Census!$G$5:$G$379,Raw_Census!$A$5:$A$379,"5416|20-49")>0,SUMIFS(Raw_Census!$D$5:$D$379,Raw_Census!$A$5:$A$379,"5416|20-49"),0)+IF(SUMIFS(Raw_Census!$G$5:$G$379,Raw_Census!$A$5:$A$379,"5416|50-99")>0,SUMIFS(Raw_Census!$D$5:$D$379,Raw_Census!$A$5:$A$379,"5416|50-99"),0)+IF(SUMIFS(Raw_Census!$G$5:$G$379,Raw_Census!$A$5:$A$379,"5416|100-249")>0,SUMIFS(Raw_Census!$D$5:$D$379,Raw_Census!$A$5:$A$379,"5416|100-249"),0)+IF(SUMIFS(Raw_Census!$G$5:$G$379,Raw_Census!$A$5:$A$379,"5416|250-499")>0,SUMIFS(Raw_Census!$D$5:$D$379,Raw_Census!$A$5:$A$379,"5416|250-499"),0)+IF(SUMIFS(Raw_Census!$G$5:$G$379,Raw_Census!$A$5:$A$379,"5416|500+")>0,SUMIFS(Raw_Census!$D$5:$D$379,Raw_Census!$A$5:$A$379,"5416|500+"),0)+IF(SUMIFS(Raw_Census!$G$5:$G$379,Raw_Census!$A$5:$A$379,"5418|20-49")>0,SUMIFS(Raw_Census!$D$5:$D$379,Raw_Census!$A$5:$A$379,"5418|20-49"),0)+IF(SUMIFS(Raw_Census!$G$5:$G$379,Raw_Census!$A$5:$A$379,"5418|50-99")>0,SUMIFS(Raw_Census!$D$5:$D$379,Raw_Census!$A$5:$A$379,"5418|50-99"),0)+IF(SUMIFS(Raw_Census!$G$5:$G$379,Raw_Census!$A$5:$A$379,"5418|100-249")>0,SUMIFS(Raw_Census!$D$5:$D$379,Raw_Census!$A$5:$A$379,"5418|100-249"),0)+IF(SUMIFS(Raw_Census!$G$5:$G$379,Raw_Census!$A$5:$A$379,"5418|250-499")>0,SUMIFS(Raw_Census!$D$5:$D$379,Raw_Census!$A$5:$A$379,"5418|250-499"),0)+IF(SUMIFS(Raw_Census!$G$5:$G$379,Raw_Census!$A$5:$A$379,"5418|500+")>0,SUMIFS(Raw_Census!$D$5:$D$379,Raw_Census!$A$5:$A$379,"5418|500+"),0)) -> 151.05137 | E10: =(SUMIFS(Raw_Census!$G$5:$G$379,Raw_Census!$A$5:$A$379,"5132|20-49")+SUMIFS(Raw_Census!$G$5:$G$379,Raw_Census!$A$5:$A$379,"5132|50-99")+SUMIFS(Raw_Census!$G$5:$G$379,Raw_Census!$A$5:$A$379,"5132|100-249")+SUMIFS(Raw_Census!$G$5:$G$379,Raw_Census!$A$5:$A$379,"5132|250-499")+SUMIFS(Raw_Census!$G$5:$G$379,Raw_Census!$A$5:$A$379,"5132|500+"))/(IF(SUMIFS(Raw_Census!$G$5:$G$379,Raw_Census!$A$5:$A$379,"5132|20-49")>0,SUMIFS(Raw_Census!$D$5:$D$379,Raw_Census!$A$5:$A$379,"5132|20-49"),0)+IF(SUMIFS(Raw_Census!$G$5:$G$379,Raw_Census!$A$5:$A$379,"5132|50-99")>0,SUMIFS(Raw_Census!$D$5:$D$379,Raw_Census!$A$5:$A$379,"5132|50-99"),0)+IF(SUMIFS(Raw_Census!$G$5:$G$379,Raw_Census!$A$5:$A$379,"5132|100-249")>0,SUMIFS(Raw_Census!$D$5:$D$379,Raw_Census!$A$5:$A$379,"5132|100-249"),0)+IF(SUMIFS(Raw_Census!$G$5:$G$379,Raw_Census!$A$5:$A$379,"5132|250-499")>0,SUMIFS(Raw_Census!$D$5:$D$379,Raw_Census!$A$5:$A$379,"5132|250-499"),0)+IF(SUMIFS(Raw_Census!$G$5:$G$379,Raw_Census!$A$5:$A$379,"5132|500+")>0,SUMIFS(Raw_Census!$D$5:$D$379,Raw_Census!$A$5:$A$379,"5132|500+"),0)) -> 296.0956 | G10: employees [C] | H10: Average firm scale within the in-scope universe.
A12: Sales intensity & builder capacity (BLS OEWS May 2025, S15)
A13: Sales occupations (SOC 41) share of employment | B13: =(SUMIFS(Raw_OEWS!$G$5:$G$147,Raw_OEWS!$D$5:$D$147,"Distribution",Raw_OEWS!$E$5:$E$147,"41-0000"))/(SUMIFS(Raw_OEWS!$G$5:$G$147,Raw_OEWS!$D$5:$D$147,"Distribution",Raw_OEWS!$E$5:$E$147,"00-0000")) -> 0.2195913 | C13: =(SUMIFS(Raw_OEWS!$G$5:$G$147,Raw_OEWS!$D$5:$D$147,"Manufacturing",Raw_OEWS!$E$5:$E$147,"41-0000"))/(SUMIFS(Raw_OEWS!$G$5:$G$147,Raw_OEWS!$D$5:$D$147,"Manufacturing",Raw_OEWS!$E$5:$E$147,"00-0000")) -> 0.027389137 | D13: =(SUMIFS(Raw_OEWS!$G$5:$G$147,Raw_OEWS!$D$5:$D$147,"ProfServices",Raw_OEWS!$E$5:$E$147,"41-0000"))/(SUMIFS(Raw_OEWS!$G$5:$G$147,Raw_OEWS!$D$5:$D$147,"ProfServices",Raw_OEWS!$E$5:$E$147,"00-0000")) -> 0.061716312 | E13: =(SUMIFS(Raw_OEWS!$G$5:$G$147,Raw_OEWS!$D$5:$D$147,"Software",Raw_OEWS!$E$5:$E$147,"41-0000"))/(SUMIFS(Raw_OEWS!$G$5:$G$147,Raw_OEWS!$D$5:$D$147,"Software",Raw_OEWS!$E$5:$E$147,"00-0000")) -> 0.10817982 | F13: =(SUMIFS(Raw_OEWS!$G$5:$G$147,Raw_OEWS!$D$5:$D$147,"AllIndustries",Raw_OEWS!$E$5:$E$147,"41-0000"))/(SUMIFS(Raw_OEWS!$G$5:$G$147,Raw_OEWS!$D$5:$D$147,"AllIndustries",Raw_OEWS!$E$5:$E$147,"00-0000")) -> 0.086332274 | G13: % of employment [C] | H13: Need proxy: how much of the workforce sells. Distribution ≈ 2.5× the economy-wide share.
A14: Wholesale & mfg sales reps per 1,000 employees (41-4011 + 41-4012) | B14: =(SUMIFS(Raw_OEWS!$G$5:$G$147,Raw_OEWS!$D$5:$D$147,"Distribution",Raw_OEWS!$E$5:$E$147,"41-4011")+SUMIFS(Raw_OEWS!$G$5:$G$147,Raw_OEWS!$D$5:$D$147,"Distribution",Raw_OEWS!$E$5:$E$147,"41-4012"))/(SUMIFS(Raw_OEWS!$G$5:$G$147,Raw_OEWS!$D$5:$D$147,"Distribution",Raw_OEWS!$E$5:$E$147,"00-0000"))*1000 -> 156.41705 | C14: =(SUMIFS(Raw_OEWS!$G$5:$G$147,Raw_OEWS!$D$5:$D$147,"Manufacturing",Raw_OEWS!$E$5:$E$147,"41-4011")+SUMIFS(Raw_OEWS!$G$5:$G$147,Raw_OEWS!$D$5:$D$147,"Manufacturing",Raw_OEWS!$E$5:$E$147,"41-4012"))/(SUMIFS(Raw_OEWS!$G$5:$G$147,Raw_OEWS!$D$5:$D$147,"Manufacturing",Raw_OEWS!$E$5:$E$147,"00-0000"))*1000 -> 22.937685 | D14: =(SUMIFS(Raw_OEWS!$G$5:$G$147,Raw_OEWS!$D$5:$D$147,"ProfServices",Raw_OEWS!$E$5:$E$147,"41-4011")+SUMIFS(Raw_OEWS!$G$5:$G$147,Raw_OEWS!$D$5:$D$147,"ProfServices",Raw_OEWS!$E$5:$E$147,"41-4012"))/(SUMIFS(Raw_OEWS!$G$5:$G$147,Raw_OEWS!$D$5:$D$147,"ProfServices",Raw_OEWS!$E$5:$E$147,"00-0000"))*1000 -> 6.3032493 | E14: =(SUMIFS(Raw_OEWS!$G$5:$G$147,Raw_OEWS!$D$5:$D$147,"Software",Raw_OEWS!$E$5:$E$147,"41-4011")+SUMIFS(Raw_OEWS!$G$5:$G$147,Raw_OEWS!$D$5:$D$147,"Software",Raw_OEWS!$E$5:$E$147,"41-4012"))/(SUMIFS(Raw_OEWS!$G$5:$G$147,Raw_OEWS!$D$5:$D$147,"Software",Raw_OEWS!$E$5:$E$147,"00-0000"))*1000 -> 27.746191 | F14: =(SUMIFS(Raw_OEWS!$G$5:$G$147,Raw_OEWS!$D$5:$D$147,"AllIndustries",Raw_OEWS!$E$5:$E$147,"41-4011")+SUMIFS(Raw_OEWS!$G$5:$G$147,Raw_OEWS!$D$5:$D$147,"AllIndustries",Raw_OEWS!$E$5:$E$147,"41-4012"))/(SUMIFS(Raw_OEWS!$G$5:$G$147,Raw_OEWS!$D$5:$D$147,"AllIndustries",Raw_OEWS!$E$5:$E$147,"00-0000"))*1000 -> 9.7944169 | G14: per 1,000 [C] | H14: Field/inside B2B reps — the users of prospecting, territory and enrichment workflows.
A15: Sales managers per 1,000 employees (11-2022) | B15: =(SUMIFS(Raw_OEWS!$G$5:$G$147,Raw_OEWS!$D$5:$D$147,"Distribution",Raw_OEWS!$E$5:$E$147,"11-2022"))/(SUMIFS(Raw_OEWS!$G$5:$G$147,Raw_OEWS!$D$5:$D$147,"Distribution",Raw_OEWS!$E$5:$E$147,"00-0000"))*1000 -> 18.859229 | C15: =(SUMIFS(Raw_OEWS!$G$5:$G$147,Raw_OEWS!$D$5:$D$147,"Manufacturing",Raw_OEWS!$E$5:$E$147,"11-2022"))/(SUMIFS(Raw_OEWS!$G$5:$G$147,Raw_OEWS!$D$5:$D$147,"Manufacturing",Raw_OEWS!$E$5:$E$147,"00-0000"))*1000 -> 6.0391094 | D15: =(SUMIFS(Raw_OEWS!$G$5:$G$147,Raw_OEWS!$D$5:$D$147,"ProfServices",Raw_OEWS!$E$5:$E$147,"11-2022"))/(SUMIFS(Raw_OEWS!$G$5:$G$147,Raw_OEWS!$D$5:$D$147,"ProfServices",Raw_OEWS!$E$5:$E$147,"00-0000"))*1000 -> 10.54172 | E15: =(SUMIFS(Raw_OEWS!$G$5:$G$147,Raw_OEWS!$D$5:$D$147,"Software",Raw_OEWS!$E$5:$E$147,"11-2022"))/(SUMIFS(Raw_OEWS!$G$5:$G$147,Raw_OEWS!$D$5:$D$147,"Software",Raw_OEWS!$E$5:$E$147,"00-0000"))*1000 -> 24.759306 | F15: =(SUMIFS(Raw_OEWS!$G$5:$G$147,Raw_OEWS!$D$5:$D$147,"AllIndustries",Raw_OEWS!$E$5:$E$147,"11-2022"))/(SUMIFS(Raw_OEWS!$G$5:$G$147,Raw_OEWS!$D$5:$D$147,"AllIndustries",Raw_OEWS!$E$5:$E$147,"00-0000"))*1000 -> 4.09709 | G15: per 1,000 [C] | H15: Likely economic buyers / champions for sales tooling.
A16: Marketing managers per 1,000 employees (11-2021) | B16: =(SUMIFS(Raw_OEWS!$G$5:$G$147,Raw_OEWS!$D$5:$D$147,"Distribution",Raw_OEWS!$E$5:$E$147,"11-2021"))/(SUMIFS(Raw_OEWS!$G$5:$G$147,Raw_OEWS!$D$5:$D$147,"Distribution",Raw_OEWS!$E$5:$E$147,"00-0000"))*1000 -> 4.3669847 | C16: =(SUMIFS(Raw_OEWS!$G$5:$G$147,Raw_OEWS!$D$5:$D$147,"Manufacturing",Raw_OEWS!$E$5:$E$147,"11-2021"))/(SUMIFS(Raw_OEWS!$G$5:$G$147,Raw_OEWS!$D$5:$D$147,"Manufacturing",Raw_OEWS!$E$5:$E$147,"00-0000"))*1000 -> 1.8226633 | D16: =(SUMIFS(Raw_OEWS!$G$5:$G$147,Raw_OEWS!$D$5:$D$147,"ProfServices",Raw_OEWS!$E$5:$E$147,"11-2021"))/(SUMIFS(Raw_OEWS!$G$5:$G$147,Raw_OEWS!$D$5:$D$147,"ProfServices",Raw_OEWS!$E$5:$E$147,"00-0000"))*1000 -> 11.567974 | E16: =(SUMIFS(Raw_OEWS!$G$5:$G$147,Raw_OEWS!$D$5:$D$147,"Software",Raw_OEWS!$E$5:$E$147,"11-2021"))/(SUMIFS(Raw_OEWS!$G$5:$G$147,Raw_OEWS!$D$5:$D$147,"Software",Raw_OEWS!$E$5:$E$147,"00-0000"))*1000 -> 19.695247 | F16: =(SUMIFS(Raw_OEWS!$G$5:$G$147,Raw_OEWS!$D$5:$D$147,"AllIndustries",Raw_OEWS!$E$5:$E$147,"11-2021"))/(SUMIFS(Raw_OEWS!$G$5:$G$147,Raw_OEWS!$D$5:$D$147,"AllIndustries",Raw_OEWS!$E$5:$E$147,"00-0000"))*1000 -> 2.5418061 | G16: per 1,000 [C] | H16: Marketing-led demand generation capacity.
A17: Market research analysts & marketing specialists per 1,000 (13-1161) | B17: =(SUMIFS(Raw_OEWS!$G$5:$G$147,Raw_OEWS!$D$5:$D$147,"Distribution",Raw_OEWS!$E$5:$E$147,"13-1161"))/(SUMIFS(Raw_OEWS!$G$5:$G$147,Raw_OEWS!$D$5:$D$147,"Distribution",Raw_OEWS!$E$5:$E$147,"00-0000"))*1000 -> 8.4267444 | C17: =(SUMIFS(Raw_OEWS!$G$5:$G$147,Raw_OEWS!$D$5:$D$147,"Manufacturing",Raw_OEWS!$E$5:$E$147,"13-1161"))/(SUMIFS(Raw_OEWS!$G$5:$G$147,Raw_OEWS!$D$5:$D$147,"Manufacturing",Raw_OEWS!$E$5:$E$147,"00-0000"))*1000 -> 3.6070699 | D17: =(SUMIFS(Raw_OEWS!$G$5:$G$147,Raw_OEWS!$D$5:$D$147,"ProfServices",Raw_OEWS!$E$5:$E$147,"13-1161"))/(SUMIFS(Raw_OEWS!$G$5:$G$147,Raw_OEWS!$D$5:$D$147,"ProfServices",Raw_OEWS!$E$5:$E$147,"00-0000"))*1000 -> 31.680386 | E17: =(SUMIFS(Raw_OEWS!$G$5:$G$147,Raw_OEWS!$D$5:$D$147,"Software",Raw_OEWS!$E$5:$E$147,"13-1161"))/(SUMIFS(Raw_OEWS!$G$5:$G$147,Raw_OEWS!$D$5:$D$147,"Software",Raw_OEWS!$E$5:$E$147,"00-0000"))*1000 -> 35.615192 | F17: =(SUMIFS(Raw_OEWS!$G$5:$G$147,Raw_OEWS!$D$5:$D$147,"AllIndustries",Raw_OEWS!$E$5:$E$147,"13-1161"))/(SUMIFS(Raw_OEWS!$G$5:$G$147,Raw_OEWS!$D$5:$D$147,"AllIndustries",Raw_OEWS!$E$5:$E$147,"00-0000"))*1000 -> 5.7852392 | G17: per 1,000 [C] | H17: Closest occupational proxy for marketing-ops / data-savvy GTM staff who build Clay workflows.
A18: Computer & mathematical occupations share of employment (SOC 15) | B18: =(SUMIFS(Raw_OEWS!$G$5:$G$147,Raw_OEWS!$D$5:$D$147,"Distribution",Raw_OEWS!$E$5:$E$147,"15-0000"))/(SUMIFS(Raw_OEWS!$G$5:$G$147,Raw_OEWS!$D$5:$D$147,"Distribution",Raw_OEWS!$E$5:$E$147,"00-0000")) -> 0.023270103 | C18: =(SUMIFS(Raw_OEWS!$G$5:$G$147,Raw_OEWS!$D$5:$D$147,"Manufacturing",Raw_OEWS!$E$5:$E$147,"15-0000"))/(SUMIFS(Raw_OEWS!$G$5:$G$147,Raw_OEWS!$D$5:$D$147,"Manufacturing",Raw_OEWS!$E$5:$E$147,"00-0000")) -> 0.015371036 | D18: =(SUMIFS(Raw_OEWS!$G$5:$G$147,Raw_OEWS!$D$5:$D$147,"ProfServices",Raw_OEWS!$E$5:$E$147,"15-0000"))/(SUMIFS(Raw_OEWS!$G$5:$G$147,Raw_OEWS!$D$5:$D$147,"ProfServices",Raw_OEWS!$E$5:$E$147,"00-0000")) -> 0.24190733 | E18: =(SUMIFS(Raw_OEWS!$G$5:$G$147,Raw_OEWS!$D$5:$D$147,"Software",Raw_OEWS!$E$5:$E$147,"15-0000"))/(SUMIFS(Raw_OEWS!$G$5:$G$147,Raw_OEWS!$D$5:$D$147,"Software",Raw_OEWS!$E$5:$E$147,"00-0000")) -> 0.4674096 | F18: =(SUMIFS(Raw_OEWS!$G$5:$G$147,Raw_OEWS!$D$5:$D$147,"AllIndustries",Raw_OEWS!$E$5:$E$147,"15-0000"))/(SUMIFS(Raw_OEWS!$G$5:$G$147,Raw_OEWS!$D$5:$D$147,"AllIndustries",Raw_OEWS!$E$5:$E$147,"00-0000")) -> 0.033828003 | G18: % of employment [C] | H18: 'Builder capacity' proxy (tests H4): technical talent available to configure and maintain workflows.
A19: Implied sales staff per 20+ firm | B19: =B10*B13 -> 27.700087 | C19: =C10*C13 -> 3.6494993 | D19: =D10*D13 -> 9.3223336 | E19: =E10*E13 -> 32.031569 | G19: people [C] | H19: Avg employees per 20+ firm × sales-occupation share. Clay usage (records, signals, sequences) scales with seller count — relevant to ACV in Phase 4.
A21: Indices vs all industries (=1.00)
A22: Sales intensity index | B22: =B13/$F13 -> 2.5435598 | C22: =C13/$F13 -> 0.31725259 | D22: =D13/$F13 -> 0.71486953 | E22: =E13/$F13 -> 1.2530635 | F22: 1 | G22: index [C]
A23: Builder capacity index (computer occupations) | B23: =B18/$F18 -> 0.68789469 | C23: =C18/$F18 -> 0.45438793 | D23: =D18/$F18 -> 7.1510969 | E23: =E18/$F18 -> 13.817239 | F23: 1 | G23: index [C]
A24: Marketing-ops talent index (13-1161) | B24: =B17/$F17 -> 1.4565939 | C24: =C17/$F17 -> 0.62349537 | D24: =D17/$F17 -> 5.4760719 | E24: =E17/$F17 -> 6.1562177 | F24: 1 | G24: index [C]
A26: Caveat: OEWS counts employees in establishments classified to the industry; manufacturers' sales are partly done by independent reps (NAICS 4251) and distributors, which this metric correctly shows as low direct-sales intensity. Professional-services BD by billable staff is not captured in SOC 41.

Sheet TAM_SAM_SOM
A1: TAM / SAM / SOM by segment — three scenarios shown side by side
A2: Low and High compound every input at its low/high value (outer bounds, not likely cases). SOM = year-3 ARR potential at uniform fair-share penetration — not a Clay forecast. [C]/[D]
A4: Scenario: Base
A5: Segment | B5: Size group | C5: Unique firms | D5: ACV ($) | E5: TAM ($) | F5: SAM filter 1: outbound motion | G5: SAM filter 2: CRM-ready | H5: SAM firms | I5: SAM ($) | J5: 3-yr penetration | K5: SOM customers | L5: SOM ARR ($)
A6: A. Industrial Distribution | B6: SMB | C6: =Firm_Counts!D58 -> 9106.2022 | D6: =Assumptions!$E$5 -> 7500 | E6: =C6*D6 -> 68296516 | F6: =Assumptions!$E$8 -> 0.8 | G6: =Assumptions!$E$11 -> 0.65 | H6: =C6*F6*G6 -> 4735.2251 | I6: =H6*D6 -> 35514188 | J6: =Assumptions!$E$14 -> 0.015 | K6: =H6*J6 -> 71.028377 | L6: =K6*D6 -> 532712.83
A7: A. Industrial Distribution | B7: Mid-Market | C7: =Firm_Counts!D59 -> 2011.3421 | D7: =Assumptions!$E$6 -> 20000 | E7: =C7*D7 -> 40226843 | F7: =Assumptions!$E$8 -> 0.8 | G7: =Assumptions!$E$11 -> 0.65 | H7: =C7*F7*G7 -> 1045.8979 | I7: =H7*D7 -> 20917958 | J7: =Assumptions!$E$15 -> 0.03 | K7: =H7*J7 -> 31.376937 | L7: =K7*D7 -> 627538.75
A8: A. Industrial Distribution | B8: Enterprise | C8: =Firm_Counts!D60 -> 376 | D8: =Assumptions!$E$7 -> 60000 | E8: =C8*D8 -> 22560000 | F8: =Assumptions!$E$8 -> 0.8 | G8: =Assumptions!$E$11 -> 0.65 | H8: =C8*F8*G8 -> 195.52 | I8: =H8*D8 -> 11731200 | J8: =Assumptions!$E$16 -> 0.06 | K8: =H8*J8 -> 11.7312 | L8: =K8*D8 -> 703872
A9: A. Industrial Distribution — total | C9: =SUM(C6:C8) -> 11493.544 | E9: =SUM(E6:E8) -> 1.3108336e+08 | H9: =SUM(H6:H8) -> 5976.643 | I9: =SUM(I6:I8) -> 68163347 | K9: =SUM(K6:K8) -> 114.13651 | L9: =SUM(L6:L8) -> 1864123.6
A10: B. Industrial Manufacturing | B10: SMB | C10: =Firm_Counts!E58 -> 18442.232 | D10: =Assumptions!$E$5 -> 7500 | E10: =C10*D10 -> 1.3831674e+08 | F10: =Assumptions!$E$9 -> 0.45 | G10: =Assumptions!$E$12 -> 0.6 | H10: =C10*F10*G10 -> 4979.4027 | I10: =H10*D10 -> 37345520 | J10: =Assumptions!$E$14 -> 0.015 | K10: =H10*J10 -> 74.69104 | L10: =K10*D10 -> 560182.8
A11: B. Industrial Manufacturing | B11: Mid-Market | C11: =Firm_Counts!E59 -> 4448.9884 | D11: =Assumptions!$E$6 -> 20000 | E11: =C11*D11 -> 88979768 | F11: =Assumptions!$E$9 -> 0.45 | G11: =Assumptions!$E$12 -> 0.6 | H11: =C11*F11*G11 -> 1201.2269 | I11: =H11*D11 -> 24024537 | J11: =Assumptions!$E$15 -> 0.03 | K11: =H11*J11 -> 36.036806 | L11: =K11*D11 -> 720736.12
A12: B. Industrial Manufacturing | B12: Enterprise | C12: =Firm_Counts!E60 -> 893.36787 | D12: =Assumptions!$E$7 -> 60000 | E12: =C12*D12 -> 53602072 | F12: =Assumptions!$E$9 -> 0.45 | G12: =Assumptions!$E$12 -> 0.6 | H12: =C12*F12*G12 -> 241.20932 | I12: =H12*D12 -> 14472559 | J12: =Assumptions!$E$16 -> 0.06 | K12: =H12*J12 -> 14.472559 | L12: =K12*D12 -> 868353.57
A13: B. Industrial Manufacturing — total | C13: =SUM(C10:C12) -> 23784.588 | E13: =SUM(E10:E12) -> 2.8089858e+08 | H13: =SUM(H10:H12) -> 6421.8388 | I13: =SUM(I10:I12) -> 75842617 | K13: =SUM(K10:K12) -> 125.20041 | L13: =SUM(L10:L12) -> 2149272.5
A14: C. B2B Professional Services | B14: SMB | C14: =Firm_Counts!F58 -> 26020.542 | D14: =Assumptions!$E$5 -> 7500 | E14: =C14*D14 -> 1.9515406e+08 | F14: =Assumptions!$E$10 -> 0.55 | G14: =Assumptions!$E$13 -> 0.7 | H14: =C14*F14*G14 -> 10017.909 | I14: =H14*D14 -> 75134315 | J14: =Assumptions!$E$14 -> 0.015 | K14: =H14*J14 -> 150.26863 | L14: =K14*D14 -> 1127014.7
A15: C. B2B Professional Services | B15: Mid-Market | C15: =Firm_Counts!F59 -> 5775.4045 | D15: =Assumptions!$E$6 -> 20000 | E15: =C15*D15 -> 1.1550809e+08 | F15: =Assumptions!$E$10 -> 0.55 | G15: =Assumptions!$E$13 -> 0.7 | H15: =C15*F15*G15 -> 2223.5307 | I15: =H15*D15 -> 44470615 | J15: =Assumptions!$E$15 -> 0.03 | K15: =H15*J15 -> 66.705922 | L15: =K15*D15 -> 1334118.4
A16: C. B2B Professional Services | B16: Enterprise | C16: =Firm_Counts!F60 -> 1239.0676 | D16: =Assumptions!$E$7 -> 60000 | E16: =C16*D16 -> 74344058 | F16: =Assumptions!$E$10 -> 0.55 | G16: =Assumptions!$E$13 -> 0.7 | H16: =C16*F16*G16 -> 477.04104 | I16: =H16*D16 -> 28622462 | J16: =Assumptions!$E$16 -> 0.06 | K16: =H16*J16 -> 28.622462 | L16: =K16*D16 -> 1717347.7
A17: C. B2B Professional Services — total | C17: =SUM(C14:C16) -> 33035.014 | E17: =SUM(E14:E16) -> 3.8500621e+08 | H17: =SUM(H14:H16) -> 12718.48 | I17: =SUM(I14:I16) -> 1.4822739e+08 | K17: =SUM(K14:K16) -> 245.59701 | L17: =SUM(L14:L16) -> 4178480.9
A18: All three segments (comparison only — segments are alternatives, not additive bets) | C18: =C9+C13+C17 -> 68313.147 | E18: =E9+E13+E17 -> 7.9698815e+08 | H18: =H9+H13+H17 -> 25116.962 | I18: =I9+I13+I17 -> 2.9223336e+08 | K18: =K9+K13+K17 -> 484.93393 | L18: =L9+L13+L17 -> 8191877
A21: Scenario: Low
A22: Segment | B22: Size group | C22: Unique firms | D22: ACV ($) | E22: TAM ($) | F22: SAM filter 1: outbound motion | G22: SAM filter 2: CRM-ready | H22: SAM firms | I22: SAM ($) | J22: 3-yr penetration | K22: SOM customers | L22: SOM ARR ($)
A23: A. Industrial Distribution | B23: SMB | C23: =Firm_Counts!D58 -> 9106.2022 | D23: =Assumptions!$D$5 -> 5352 | E23: =C23*D23 -> 48736394 | F23: =Assumptions!$D$8 -> 0.65 | G23: =Assumptions!$D$11 -> 0.52 | H23: =C23*F23*G23 -> 3077.8963 | I23: =H23*D23 -> 16472901 | J23: =Assumptions!$D$14 -> 0.005 | K23: =H23*J23 -> 15.389482 | L23: =K23*D23 -> 82364.506
A24: A. Industrial Distribution | B24: Mid-Market | C24: =Firm_Counts!D59 -> 2011.3421 | D24: =Assumptions!$D$6 -> 12000 | E24: =C24*D24 -> 24136106 | F24: =Assumptions!$D$8 -> 0.65 | G24: =Assumptions!$D$11 -> 0.52 | H24: =C24*F24*G24 -> 679.83364 | I24: =H24*D24 -> 8158003.7 | J24: =Assumptions!$D$15 -> 0.01 | K24: =H24*J24 -> 6.7983364 | L24: =K24*D24 -> 81580.037
A25: A. Industrial Distribution | B25: Enterprise | C25: =Firm_Counts!D60 -> 376 | D25: =Assumptions!$D$7 -> 30000 | E25: =C25*D25 -> 11280000 | F25: =Assumptions!$D$8 -> 0.65 | G25: =Assumptions!$D$11 -> 0.52 | H25: =C25*F25*G25 -> 127.088 | I25: =H25*D25 -> 3812640 | J25: =Assumptions!$D$16 -> 0.02 | K25: =H25*J25 -> 2.54176 | L25: =K25*D25 -> 76252.8
A26: A. Industrial Distribution — total | C26: =SUM(C23:C25) -> 11493.544 | E26: =SUM(E23:E25) -> 84152500 | H26: =SUM(H23:H25) -> 3884.818 | I26: =SUM(I23:I25) -> 28443545 | K26: =SUM(K23:K25) -> 24.729578 | L26: =SUM(L23:L25) -> 240197.34
A27: B. Industrial Manufacturing | B27: SMB | C27: =Firm_Counts!E58 -> 18442.232 | D27: =Assumptions!$D$5 -> 5352 | E27: =C27*D27 -> 98702826 | F27: =Assumptions!$D$9 -> 0.3 | G27: =Assumptions!$D$12 -> 0.45 | H27: =C27*F27*G27 -> 2489.7013 | I27: =H27*D27 -> 13324882 | J27: =Assumptions!$D$14 -> 0.005 | K27: =H27*J27 -> 12.448507 | L27: =K27*D27 -> 66624.408
A28: B. Industrial Manufacturing | B28: Mid-Market | C28: =Firm_Counts!E59 -> 4448.9884 | D28: =Assumptions!$D$6 -> 12000 | E28: =C28*D28 -> 53387861 | F28: =Assumptions!$D$9 -> 0.3 | G28: =Assumptions!$D$12 -> 0.45 | H28: =C28*F28*G28 -> 600.61343 | I28: =H28*D28 -> 7207361.2 | J28: =Assumptions!$D$15 -> 0.01 | K28: =H28*J28 -> 6.0061343 | L28: =K28*D28 -> 72073.612
A29: B. Industrial Manufacturing | B29: Enterprise | C29: =Firm_Counts!E60 -> 893.36787 | D29: =Assumptions!$D$7 -> 30000 | E29: =C29*D29 -> 26801036 | F29: =Assumptions!$D$9 -> 0.3 | G29: =Assumptions!$D$12 -> 0.45 | H29: =C29*F29*G29 -> 120.60466 | I29: =H29*D29 -> 3618139.9 | J29: =Assumptions!$D$16 -> 0.02 | K29: =H29*J29 -> 2.4120932 | L29: =K29*D29 -> 72362.797
A30: B. Industrial Manufacturing — total | C30: =SUM(C27:C29) -> 23784.588 | E30: =SUM(E27:E29) -> 1.7889172e+08 | H30: =SUM(H27:H29) -> 3210.9194 | I30: =SUM(I27:I29) -> 24150383 | K30: =SUM(K27:K29) -> 20.866734 | L30: =SUM(L27:L29) -> 211060.82
A31: C. B2B Professional Services | B31: SMB | C31: =Firm_Counts!F58 -> 26020.542 | D31: =Assumptions!$D$5 -> 5352 | E31: =C31*D31 -> 1.3926194e+08 | F31: =Assumptions!$D$10 -> 0.4 | G31: =Assumptions!$D$13 -> 0.55 | H31: =C31*F31*G31 -> 5724.5192 | I31: =H31*D31 -> 30637627 | J31: =Assumptions!$D$14 -> 0.005 | K31: =H31*J31 -> 28.622596 | L31: =K31*D31 -> 153188.13
A32: C. B2B Professional Services | B32: Mid-Market | C32: =Firm_Counts!F59 -> 5775.4045 | D32: =Assumptions!$D$6 -> 12000 | E32: =C32*D32 -> 69304854 | F32: =Assumptions!$D$10 -> 0.4 | G32: =Assumptions!$D$13 -> 0.55 | H32: =C32*F32*G32 -> 1270.589 | I32: =H32*D32 -> 15247068 | J32: =Assumptions!$D$15 -> 0.01 | K32: =H32*J32 -> 12.70589 | L32: =K32*D32 -> 152470.68
A33: C. B2B Professional Services | B33: Enterprise | C33: =Firm_Counts!F60 -> 1239.0676 | D33: =Assumptions!$D$7 -> 30000 | E33: =C33*D33 -> 37172029 | F33: =Assumptions!$D$10 -> 0.4 | G33: =Assumptions!$D$13 -> 0.55 | H33: =C33*F33*G33 -> 272.59488 | I33: =H33*D33 -> 8177846.4 | J33: =Assumptions!$D$16 -> 0.02 | K33: =H33*J33 -> 5.4518976 | L33: =K33*D33 -> 163556.93
A34: C. B2B Professional Services — total | C34: =SUM(C31:C33) -> 33035.014 | E34: =SUM(E31:E33) -> 2.4573882e+08 | H34: =SUM(H31:H33) -> 7267.7031 | I34: =SUM(I31:I33) -> 54062541 | K34: =SUM(K31:K33) -> 46.780384 | L34: =SUM(L31:L33) -> 469215.74
A35: All three segments (comparison only — segments are alternatives, not additive bets) | C35: =C26+C30+C34 -> 68313.147 | E35: =E26+E30+E34 -> 5.0878305e+08 | H35: =H26+H30+H34 -> 14363.44 | I35: =I26+I30+I34 -> 1.0665647e+08 | K35: =K26+K30+K34 -> 92.376696 | L35: =L26+L30+L34 -> 920473.9
A38: Scenario: High
A39: Segment | B39: Size group | C39: Unique firms | D39: ACV ($) | E39: TAM ($) | F39: SAM filter 1: outbound motion | G39: SAM filter 2: CRM-ready | H39: SAM firms | I39: SAM ($) | J39: 3-yr penetration | K39: SOM customers | L39: SOM ARR ($)
A40: A. Industrial Distribution | B40: SMB | C40: =Firm_Counts!D58 -> 9106.2022 | D40: =Assumptions!$F$5 -> 12000 | E40: =C40*D40 -> 1.0927443e+08 | F40: =Assumptions!$F$8 -> 0.9 | G40: =Assumptions!$F$11 -> 0.76 | H40: =C40*F40*G40 -> 6228.6423 | I40: =H40*D40 -> 74743707 | J40: =Assumptions!$F$14 -> 0.03 | K40: =H40*J40 -> 186.85927 | L40: =K40*D40 -> 2242311.2
A41: A. Industrial Distribution | B41: Mid-Market | C41: =Firm_Counts!D59 -> 2011.3421 | D41: =Assumptions!$F$6 -> 35000 | E41: =C41*D41 -> 70396975 | F41: =Assumptions!$F$8 -> 0.9 | G41: =Assumptions!$F$11 -> 0.76 | H41: =C41*F41*G41 -> 1375.758 | I41: =H41*D41 -> 48151531 | J41: =Assumptions!$F$15 -> 0.06 | K41: =H41*J41 -> 82.545481 | L41: =K41*D41 -> 2889091.8
A42: A. Industrial Distribution | B42: Enterprise | C42: =Firm_Counts!D60 -> 376 | D42: =Assumptions!$F$7 -> 120000 | E42: =C42*D42 -> 45120000 | F42: =Assumptions!$F$8 -> 0.9 | G42: =Assumptions!$F$11 -> 0.76 | H42: =C42*F42*G42 -> 257.184 | I42: =H42*D42 -> 30862080 | J42: =Assumptions!$F$16 -> 0.12 | K42: =H42*J42 -> 30.86208 | L42: =K42*D42 -> 3703449.6
A43: A. Industrial Distribution — total | C43: =SUM(C40:C42) -> 11493.544 | E43: =SUM(E40:E42) -> 2.247914e+08 | H43: =SUM(H40:H42) -> 7861.5843 | I43: =SUM(I40:I42) -> 1.5375732e+08 | K43: =SUM(K40:K42) -> 300.26683 | L43: =SUM(L40:L42) -> 8834852.7
A44: B. Industrial Manufacturing | B44: SMB | C44: =Firm_Counts!E58 -> 18442.232 | D44: =Assumptions!$F$5 -> 12000 | E44: =C44*D44 -> 2.2130678e+08 | F44: =Assumptions!$F$9 -> 0.6 | G44: =Assumptions!$F$12 -> 0.75 | H44: =C44*F44*G44 -> 8299.0044 | I44: =H44*D44 -> 99588053 | J44: =Assumptions!$F$14 -> 0.03 | K44: =H44*J44 -> 248.97013 | L44: =K44*D44 -> 2987641.6
A45: B. Industrial Manufacturing | B45: Mid-Market | C45: =Firm_Counts!E59 -> 4448.9884 | D45: =Assumptions!$F$6 -> 35000 | E45: =C45*D45 -> 1.5571459e+08 | F45: =Assumptions!$F$9 -> 0.6 | G45: =Assumptions!$F$12 -> 0.75 | H45: =C45*F45*G45 -> 2002.0448 | I45: =H45*D45 -> 70071567 | J45: =Assumptions!$F$15 -> 0.06 | K45: =H45*J45 -> 120.12269 | L45: =K45*D45 -> 4204294
A46: B. Industrial Manufacturing | B46: Enterprise | C46: =Firm_Counts!E60 -> 893.36787 | D46: =Assumptions!$F$7 -> 120000 | E46: =C46*D46 -> 1.0720414e+08 | F46: =Assumptions!$F$9 -> 0.6 | G46: =Assumptions!$F$12 -> 0.75 | H46: =C46*F46*G46 -> 402.01554 | I46: =H46*D46 -> 48241865 | J46: =Assumptions!$F$16 -> 0.12 | K46: =H46*J46 -> 48.241865 | L46: =K46*D46 -> 5789023.8
A47: B. Industrial Manufacturing — total | C47: =SUM(C44:C46) -> 23784.588 | E47: =SUM(E44:E46) -> 4.8422552e+08 | H47: =SUM(H44:H46) -> 10703.065 | I47: =SUM(I44:I46) -> 2.1790149e+08 | K47: =SUM(K44:K46) -> 417.33468 | L47: =SUM(L44:L46) -> 12980959
A48: C. B2B Professional Services | B48: SMB | C48: =Firm_Counts!F58 -> 26020.542 | D48: =Assumptions!$F$5 -> 12000 | E48: =C48*D48 -> 3.122465e+08 | F48: =Assumptions!$F$10 -> 0.7 | G48: =Assumptions!$F$13 -> 0.85 | H48: =C48*F48*G48 -> 15482.222 | I48: =H48*D48 -> 1.8578667e+08 | J48: =Assumptions!$F$14 -> 0.03 | K48: =H48*J48 -> 464.46667 | L48: =K48*D48 -> 5573600.1
A49: C. B2B Professional Services | B49: Mid-Market | C49: =Firm_Counts!F59 -> 5775.4045 | D49: =Assumptions!$F$6 -> 35000 | E49: =C49*D49 -> 2.0213916e+08 | F49: =Assumptions!$F$10 -> 0.7 | G49: =Assumptions!$F$13 -> 0.85 | H49: =C49*F49*G49 -> 3436.3657 | I49: =H49*D49 -> 1.202728e+08 | J49: =Assumptions!$F$15 -> 0.06 | K49: =H49*J49 -> 206.18194 | L49: =K49*D49 -> 7216368
A50: C. B2B Professional Services | B50: Enterprise | C50: =Firm_Counts!F60 -> 1239.0676 | D50: =Assumptions!$F$7 -> 120000 | E50: =C50*D50 -> 1.4868812e+08 | F50: =Assumptions!$F$10 -> 0.7 | G50: =Assumptions!$F$13 -> 0.85 | H50: =C50*F50*G50 -> 737.24524 | I50: =H50*D50 -> 88469429 | J50: =Assumptions!$F$16 -> 0.12 | K50: =H50*J50 -> 88.469429 | L50: =K50*D50 -> 10616332
A51: C. B2B Professional Services — total | C51: =SUM(C48:C50) -> 33035.014 | E51: =SUM(E48:E50) -> 6.6307378e+08 | H51: =SUM(H48:H50) -> 19655.833 | I51: =SUM(I48:I50) -> 3.945289e+08 | K51: =SUM(K48:K50) -> 759.11804 | L51: =SUM(L48:L50) -> 23406300
A52: All three segments (comparison only — segments are alternatives, not additive bets) | C52: =C43+C47+C51 -> 68313.147 | E52: =E43+E47+E51 -> 1.3720907e+09 | H52: =H43+H47+H51 -> 38220.482 | I52: =I43+I47+I51 -> 7.661877e+08 | K52: =K43+K47+K51 -> 1476.7196 | L52: =L43+L47+L51 -> 45222112

Sheet Sensitivity
A1: Sensitivity — what moves SOM, and what would have to be true for the ranking to change
A2: Block A: one-at-a-time swings on Base SOM ARR. Block B: Distribution SOM grid vs Prof. Services base. Block C: segment-definition sensitivity (tests H1).
A4: Block A — One-at-a-time sensitivity of Base SOM ARR ($), other inputs held at Base
A5: Input swung | B5: Segment | C5: SOM @ Low input | D5: SOM @ Base | E5: SOM @ High input | F5: Swing (High − Low)
A6: ACV (all size bands) | B6: A. Industrial Distribution | C6: =SUMPRODUCT(Firm_Counts!D58:D60,Assumptions!E14:E16,Assumptions!D5:D7)*Assumptions!$E$8*Assumptions!$E$11 -> 1108603.1 | D6: =SUMPRODUCT(Firm_Counts!D58:D60,Assumptions!E14:E16,Assumptions!E5:E7)*Assumptions!$E$8*Assumptions!$E$11 -> 1864123.6 | E6: =SUMPRODUCT(Firm_Counts!D58:D60,Assumptions!E14:E16,Assumptions!F5:F7)*Assumptions!$E$8*Assumptions!$E$11 -> 3358277.3 | F6: =E6-C6 -> 2249674.2
A7: 3-yr penetration (all size bands) | B7: A. Industrial Distribution | C7: =SUMPRODUCT(Firm_Counts!D58:D60,Assumptions!D14:D16,Assumptions!E5:E7)*Assumptions!$E$8*Assumptions!$E$11 -> 621374.52 | D7: =SUMPRODUCT(Firm_Counts!D58:D60,Assumptions!E14:E16,Assumptions!E5:E7)*Assumptions!$E$8*Assumptions!$E$11 -> 1864123.6 | E7: =SUMPRODUCT(Firm_Counts!D58:D60,Assumptions!F14:F16,Assumptions!E5:E7)*Assumptions!$E$8*Assumptions!$E$11 -> 3728247.1 | F7: =E7-C7 -> 3106872.6
A8: SAM filter 1 — outbound motion | B8: A. Industrial Distribution | C8: =SUMPRODUCT(Firm_Counts!D58:D60,Assumptions!E14:E16,Assumptions!E5:E7)*Assumptions!$D$8*Assumptions!$E$11 -> 1514600.4 | D8: =SUMPRODUCT(Firm_Counts!D58:D60,Assumptions!E14:E16,Assumptions!E5:E7)*Assumptions!$E$8*Assumptions!$E$11 -> 1864123.6 | E8: =SUMPRODUCT(Firm_Counts!D58:D60,Assumptions!E14:E16,Assumptions!E5:E7)*Assumptions!$F$8*Assumptions!$E$11 -> 2097139 | F8: =E8-C8 -> 582538.62
A9: SAM filter 2 — CRM readiness | B9: A. Industrial Distribution | C9: =SUMPRODUCT(Firm_Counts!D58:D60,Assumptions!E14:E16,Assumptions!E5:E7)*Assumptions!$E$8*Assumptions!$D$11 -> 1491298.9 | D9: =SUMPRODUCT(Firm_Counts!D58:D60,Assumptions!E14:E16,Assumptions!E5:E7)*Assumptions!$E$8*Assumptions!$E$11 -> 1864123.6 | E9: =SUMPRODUCT(Firm_Counts!D58:D60,Assumptions!E14:E16,Assumptions!E5:E7)*Assumptions!$E$8*Assumptions!$F$11 -> 2179590.6 | F9: =E9-C9 -> 688291.78
A11: ACV (all size bands) | B11: B. Industrial Manufacturing | C11: =SUMPRODUCT(Firm_Counts!E58:E60,Assumptions!E14:E16,Assumptions!D5:D7)*Assumptions!$E$9*Assumptions!$E$12 -> 1266364.9 | D11: =SUMPRODUCT(Firm_Counts!E58:E60,Assumptions!E14:E16,Assumptions!E5:E7)*Assumptions!$E$9*Assumptions!$E$12 -> 2149272.5 | E11: =SUMPRODUCT(Firm_Counts!E58:E60,Assumptions!E14:E16,Assumptions!F5:F7)*Assumptions!$E$9*Assumptions!$E$12 -> 3894287.8 | F11: =E11-C11 -> 2627922.9
A12: 3-yr penetration (all size bands) | B12: B. Industrial Manufacturing | C12: =SUMPRODUCT(Firm_Counts!E58:E60,Assumptions!D14:D16,Assumptions!E5:E7)*Assumptions!$E$9*Assumptions!$E$12 -> 716424.16 | D12: =SUMPRODUCT(Firm_Counts!E58:E60,Assumptions!E14:E16,Assumptions!E5:E7)*Assumptions!$E$9*Assumptions!$E$12 -> 2149272.5 | E12: =SUMPRODUCT(Firm_Counts!E58:E60,Assumptions!F14:F16,Assumptions!E5:E7)*Assumptions!$E$9*Assumptions!$E$12 -> 4298545 | F12: =E12-C12 -> 3582120.8
A13: SAM filter 1 — outbound motion | B13: B. Industrial Manufacturing | C13: =SUMPRODUCT(Firm_Counts!E58:E60,Assumptions!E14:E16,Assumptions!E5:E7)*Assumptions!$D$9*Assumptions!$E$12 -> 1432848.3 | D13: =SUMPRODUCT(Firm_Counts!E58:E60,Assumptions!E14:E16,Assumptions!E5:E7)*Assumptions!$E$9*Assumptions!$E$12 -> 2149272.5 | E13: =SUMPRODUCT(Firm_Counts!E58:E60,Assumptions!E14:E16,Assumptions!E5:E7)*Assumptions!$F$9*Assumptions!$E$12 -> 2865696.6 | F13: =E13-C13 -> 1432848.3
A14: SAM filter 2 — CRM readiness | B14: B. Industrial Manufacturing | C14: =SUMPRODUCT(Firm_Counts!E58:E60,Assumptions!E14:E16,Assumptions!E5:E7)*Assumptions!$E$9*Assumptions!$D$12 -> 1611954.4 | D14: =SUMPRODUCT(Firm_Counts!E58:E60,Assumptions!E14:E16,Assumptions!E5:E7)*Assumptions!$E$9*Assumptions!$E$12 -> 2149272.5 | E14: =SUMPRODUCT(Firm_Counts!E58:E60,Assumptions!E14:E16,Assumptions!E5:E7)*Assumptions!$E$9*Assumptions!$F$12 -> 2686590.6 | F14: =E14-C14 -> 1074636.2
A16: ACV (all size bands) | B16: C. B2B Professional Services | C16: =SUMPRODUCT(Firm_Counts!F58:F60,Assumptions!E14:E16,Assumptions!D5:D7)*Assumptions!$E$10*Assumptions!$E$13 -> 2463382.6 | D16: =SUMPRODUCT(Firm_Counts!F58:F60,Assumptions!E14:E16,Assumptions!E5:E7)*Assumptions!$E$10*Assumptions!$E$13 -> 4178480.9 | E16: =SUMPRODUCT(Firm_Counts!F58:F60,Assumptions!E14:E16,Assumptions!F5:F7)*Assumptions!$E$10*Assumptions!$E$13 -> 7572626.3 | F16: =E16-C16 -> 5109243.7
A17: 3-yr penetration (all size bands) | B17: C. B2B Professional Services | C17: =SUMPRODUCT(Firm_Counts!F58:F60,Assumptions!D14:D16,Assumptions!E5:E7)*Assumptions!$E$10*Assumptions!$E$13 -> 1392827 | D17: =SUMPRODUCT(Firm_Counts!F58:F60,Assumptions!E14:E16,Assumptions!E5:E7)*Assumptions!$E$10*Assumptions!$E$13 -> 4178480.9 | E17: =SUMPRODUCT(Firm_Counts!F58:F60,Assumptions!F14:F16,Assumptions!E5:E7)*Assumptions!$E$10*Assumptions!$E$13 -> 8356961.8 | F17: =E17-C17 -> 6964134.9
A18: SAM filter 1 — outbound motion | B18: C. B2B Professional Services | C18: =SUMPRODUCT(Firm_Counts!F58:F60,Assumptions!E14:E16,Assumptions!E5:E7)*Assumptions!$D$10*Assumptions!$E$13 -> 3038895.2 | D18: =SUMPRODUCT(Firm_Counts!F58:F60,Assumptions!E14:E16,Assumptions!E5:E7)*Assumptions!$E$10*Assumptions!$E$13 -> 4178480.9 | E18: =SUMPRODUCT(Firm_Counts!F58:F60,Assumptions!E14:E16,Assumptions!E5:E7)*Assumptions!$F$10*Assumptions!$E$13 -> 5318066.6 | F18: =E18-C18 -> 2279171.4
A19: SAM filter 2 — CRM readiness | B19: C. B2B Professional Services | C19: =SUMPRODUCT(Firm_Counts!F58:F60,Assumptions!E14:E16,Assumptions!E5:E7)*Assumptions!$E$10*Assumptions!$D$13 -> 3283092.1 | D19: =SUMPRODUCT(Firm_Counts!F58:F60,Assumptions!E14:E16,Assumptions!E5:E7)*Assumptions!$E$10*Assumptions!$E$13 -> 4178480.9 | E19: =SUMPRODUCT(Firm_Counts!F58:F60,Assumptions!E14:E16,Assumptions!E5:E7)*Assumptions!$E$10*Assumptions!$F$13 -> 5073869.7 | F19: =E19-C19 -> 1790777.5
A21: Check: Block A base equals TAM_SAM_SOM base SOM (should be 0) | B21: =ROUND(D6-TAM_SAM_SOM!L9,2)+ROUND(D11-TAM_SAM_SOM!L13,2)+ROUND(D16-TAM_SAM_SOM!L17,2) -> 0
A24: Block B — Distribution Base SOM ARR under multipliers on penetration (rows) × ACV (columns). Shaded = matches or exceeds Prof. Services Base SOM.
A25: Prof. Services Base SOM ARR (benchmark) | B25: =TAM_SAM_SOM!L17 -> 4178480.9
A26: Distribution Base SOM ARR | B26: =TAM_SAM_SOM!L9 -> 1864123.6
A28: Penetration multiplier ↓ / ACV multiplier → | B28: 0.5 | C28: 0.75 | D28: 1 | E28: 1.5 | F28: 2 | G28: 3
A29: 0.5 | B29: =$B$26*$A29*B$28 -> 466030.89 | C29: =$B$26*$A29*C$28 -> 699046.34 | D29: =$B$26*$A29*D$28 -> 932061.79 | E29: =$B$26*$A29*E$28 -> 1398092.7 | F29: =$B$26*$A29*F$28 -> 1864123.6 | G29: =$B$26*$A29*G$28 -> 2796185.4
A30: 0.75 | B30: =$B$26*$A30*B$28 -> 699046.34 | C30: =$B$26*$A30*C$28 -> 1048569.5 | D30: =$B$26*$A30*D$28 -> 1398092.7 | E30: =$B$26*$A30*E$28 -> 2097139 | F30: =$B$26*$A30*F$28 -> 2796185.4 | G30: =$B$26*$A30*G$28 -> 4194278
A31: 1 | B31: =$B$26*$A31*B$28 -> 932061.79 | C31: =$B$26*$A31*C$28 -> 1398092.7 | D31: =$B$26*$A31*D$28 -> 1864123.6 | E31: =$B$26*$A31*E$28 -> 2796185.4 | F31: =$B$26*$A31*F$28 -> 3728247.1 | G31: =$B$26*$A31*G$28 -> 5592370.7
A32: 1.5 | B32: =$B$26*$A32*B$28 -> 1398092.7 | C32: =$B$26*$A32*C$28 -> 2097139 | D32: =$B$26*$A32*D$28 -> 2796185.4 | E32: =$B$26*$A32*E$28 -> 4194278 | F32: =$B$26*$A32*F$28 -> 5592370.7 | G32: =$B$26*$A32*G$28 -> 8388556.1
A33: 2 | B33: =$B$26*$A33*B$28 -> 1864123.6 | C33: =$B$26*$A33*C$28 -> 2796185.4 | D33: =$B$26*$A33*D$28 -> 3728247.1 | E33: =$B$26*$A33*E$28 -> 5592370.7 | F33: =$B$26*$A33*F$28 -> 7456494.3 | G33: =$B$26*$A33*G$28 -> 11184741
A34: 3 | B34: =$B$26*$A34*B$28 -> 2796185.4 | C34: =$B$26*$A34*C$28 -> 4194278 | D34: =$B$26*$A34*D$28 -> 5592370.7 | E34: =$B$26*$A34*E$28 -> 8388556.1 | F34: =$B$26*$A34*F$28 -> 11184741 | G34: =$B$26*$A34*G$28 -> 16777112
A36: Break-even combined multiplier for Distribution to match Prof. Services (penetration × ACV) | B36: =B25/B26 -> 2.2415257
A39: Block C — Segment-definition sensitivity: unique-ish firms with 20+ employees (core definition vs broader alternatives)
A40: Definition | B40: Segment | C40: Firms 20+ | D40: vs core | E40: Note
A41: Core (model) | B41: A. Industrial Distribution | C41: =Firm_Counts!D61 -> 11493.544 | D41: =C41/C41 -> 1 | E41: De-duplicated core NAICS 4235–4238.
A42: Broad: + 4233 lumber/construction materials + 4234 prof. & commercial equipment | B42: A. Industrial Distribution | C42: =Firm_Counts!D61+SUMIFS(Raw_Census!$D$5:$D$379,Raw_Census!$A$5:$A$379,"4233|20-49")+SUMIFS(Raw_Census!$D$5:$D$379,Raw_Census!$A$5:$A$379,"4233|50-99")+SUMIFS(Raw_Census!$D$5:$D$379,Raw_Census!$A$5:$A$379,"4233|100-249")+SUMIFS(Raw_Census!$D$5:$D$379,Raw_Census!$A$5:$A$379,"4233|250-499")+SUMIFS(Raw_Census!$D$5:$D$379,Raw_Census!$A$5:$A$379,"4233|500+")+SUMIFS(Raw_Census!$D$5:$D$379,Raw_Census!$A$5:$A$379,"4234|20-49")+SUMIFS(Raw_Census!$D$5:$D$379,Raw_Census!$A$5:$A$379,"4234|50-99")+SUMIFS(Raw_Census!$D$5:$D$379,Raw_Census!$A$5:$A$379,"4234|100-249")+SUMIFS(Raw_Census!$D$5:$D$379,Raw_Census!$A$5:$A$379,"4234|250-499")+SUMIFS(Raw_Census!$D$5:$D$379,Raw_Census!$A$5:$A$379,"4234|500+")*1 -> 16431.544 | D42: =C42/C41 -> 1.4296325 | E42: Not de-duplicated (adds ≤3% overlap).
A43: Core (model) | B43: B. Industrial Manufacturing | C43: =Firm_Counts!E61 -> 23784.588 | D43: =C43/C43 -> 1 | E43: De-duplicated core NAICS 326/332/333/335.
A44: Broad: all manufacturing (sector 31-33, original brief) | B44: B. Industrial Manufacturing | C44: =SUMIFS(Raw_Census!$D$5:$D$379,Raw_Census!$A$5:$A$379,"31-33|20-49")+SUMIFS(Raw_Census!$D$5:$D$379,Raw_Census!$A$5:$A$379,"31-33|50-99")+SUMIFS(Raw_Census!$D$5:$D$379,Raw_Census!$A$5:$A$379,"31-33|100-249")+SUMIFS(Raw_Census!$D$5:$D$379,Raw_Census!$A$5:$A$379,"31-33|250-499")+SUMIFS(Raw_Census!$D$5:$D$379,Raw_Census!$A$5:$A$379,"31-33|500+") -> 60710 | D44: =C44/C43 -> 2.5524932 | E44: Sector total is already unique firms.
A45: Core (model) | B45: C. B2B Professional Services | C45: =Firm_Counts!F61 -> 33035.014 | D45: =C45/C45 -> 1 | E45: De-duplicated core NAICS 5413/5415/5416/5418.
A46: Broad: all professional, scientific & technical services (sector 54) | B46: C. B2B Professional Services | C46: =SUMIFS(Raw_Census!$D$5:$D$379,Raw_Census!$A$5:$A$379,"54|20-49")+SUMIFS(Raw_Census!$D$5:$D$379,Raw_Census!$A$5:$A$379,"54|50-99")+SUMIFS(Raw_Census!$D$5:$D$379,Raw_Census!$A$5:$A$379,"54|100-249")+SUMIFS(Raw_Census!$D$5:$D$379,Raw_Census!$A$5:$A$379,"54|250-499")+SUMIFS(Raw_Census!$D$5:$D$379,Raw_Census!$A$5:$A$379,"54|500+") -> 57665 | D46: =C46/C45 -> 1.7455721 | E46: Adds legal, accounting, R&D, design, other.

Sheet Hypothesis_Tests
A1: Hypothesis tests addressed in Phase 1
A2: Hypotheses from 01_Project_Charter.md §8. Verdicts are formula-driven where the test is quantitative.
A4: ID | B4: Hypothesis (abridged) | C4: Test metric | D4: Value | E4: Threshold | F4: Verdict | G4: Comment
A5: H1 | B5: 'B2B manufacturing suppliers' as written (all of 31-33) is too broad; a narrower industrial subset is more appropriate. | C5: Share of all-manufacturing 20+ firms captured by the core industrial subsectors | D5: =Firm_Counts!E61/Sensitivity!C44 -> 0.39177382 | E5: n/a (qualitative) | F5: Supported (qualitative) | G5: Core subsectors are only about two-fifths of manufacturing firms with 20+ employees; the remainder includes food, beverage, apparel, printing, furniture and wood — retail/CPG or local-market go-to-market, not engineered B2B selling. Industry heterogeneity is also visible in receipts per firm across core subsectors ($9M fabricated metal vs $38M electrical equipment).
A6: H2 | B6: Distribution's mid-market pool (20–499) is ≥ manufacturing's and ≥ 50% of professional services'. | C6: Distribution 20–499 firms ÷ Prof. Services 20–499 firms | D6: =(Firm_Counts!D58+Firm_Counts!D59)/(Firm_Counts!F58+Firm_Counts!F59) -> 0.34965288 | E6: 0.5 | F6: =IF(AND(D6>=E6,D7>=1),"Supported","Rejected") -> Rejected | G6: Distribution is the SMALLEST segment by firm count. The case for distribution, if any, must rest on need intensity and per-firm value, not market breadth.
C7: Distribution 20–499 firms ÷ Manufacturing 20–499 firms | D7: =(Firm_Counts!D58+Firm_Counts!D59)/(Firm_Counts!E58+Firm_Counts!E59) -> 0.48566848 | E7: 1
A8: H4 | B8: Binding constraint in industrial segments is builder capacity, not need. | C8: Builder-capacity index (computer occupations share vs all industries): Distribution / Manufacturing / Prof. Services | D8: =TEXT(Segment_Profile!B18/Segment_Profile!F18,"0.00")&" / "&TEXT(Segment_Profile!C18/Segment_Profile!F18,"0.00")&" / "&TEXT(Segment_Profile!D18/Segment_Profile!F18,"0.00") -> 0.69 / 0.45 / 7.15 | E8: <1.0 = below avg | F8: =IF(AND(Segment_Profile!B18<Segment_Profile!F18,Segment_Profile!B13>Segment_Profile!F13),"Preliminary support (distribution)","Not supported") -> Preliminary support (distribution) | G8: Distribution combines the highest sales intensity with below-average technical talent — the 'high need, low builder capacity' profile. Manufacturing is low on both (weak need AND weak capacity). Professional services is the mirror image of distribution. Occupational proxies only; confirm with job-posting / partner evidence in Phase 2.
A9: H6 | B9: Industrial mid-market ACV sits in the Growth-tier range (~$5K–$25K). | C9: Base ACV for SMB / Mid-Market (Assumptions A1–A2) | D9: =TEXT(Assumptions!$E$5,"$#,##0")&" / "&TEXT(Assumptions!$E$6,"$#,##0") -> $7,500 / $20,000 | E9: $5K–$25K | F9: Untested (assumption) | G9: Phase 1 can only bound ACV from list pricing and a vendor benchmark; no segment-specific contract data is public. Note: average distributor revenue per 20+ firm is several times that of professional-services firms (Segment_Profile), so ability to pay is not the constraint for distribution.

Sheet Segment_Defs
A1: Segment definitions (refined in Phase 1)
A2: NAICS 2022 codes · 'Core' codes drive the model; 'Broad' codes are used only in the definition sensitivity (Sensitivity tab, block C)
A4: Segment | B4: NAICS | C4: Industry | D4: Scope | E4: Rationale
A5: A. Industrial Distribution | B5: 4235 | C5: Metal & Mineral (except Petroleum) Merchant Wholesalers | D5: Core | E5: Industrial MRO / metals service centers; outside-sales-led; serve manufacturers and contractors.
A6: A. Industrial Distribution | B6: 4236 | C6: Household Appliances & Electrical/Electronic Goods Merchant Wholesalers | D6: Core | E6: Electrical distributors (e.g., the Regency Supply case, S07); contractor-facing territory sales.
A7: A. Industrial Distribution | B7: 4237 | C7: Hardware, Plumbing & Heating Equipment Merchant Wholesalers | D7: Core | E7: PHVAC / hardware distributors; branch-heavy networks serving contractors.
A8: A. Industrial Distribution | B8: 4238 | C8: Machinery, Equipment & Supplies Merchant Wholesalers | D8: Core | E8: Industrial machinery, equipment and supplies distributors; largest core sub-segment.
A9: A. Industrial Distribution | B9: 4233 | C9: Lumber & Other Construction Materials Merchant Wholesalers | D9: Broad | E9: Building-materials distribution; adjacent but more residential/contractor commodity-driven.
A10: A. Industrial Distribution | B10: 4234 | C10: Professional & Commercial Equipment Merchant Wholesalers | D10: Broad | E10: Includes computers, medical and office equipment — mixed, partly tech-channel; excluded from core.
A11: B. Industrial Manufacturing | B11: 326 | C11: Plastics & Rubber Products Manufacturing | D11: Core | E11: Component suppliers selling B2B to OEMs; engineered-to-order sales.
A12: B. Industrial Manufacturing | B12: 332 | C12: Fabricated Metal Product Manufacturing | D12: Core | E12: Job shops and fabricators; largest firm count; many small, owner-led firms.
A13: B. Industrial Manufacturing | B13: 333 | C13: Machinery Manufacturing | D13: Core | E13: Capital equipment OEMs; direct + dealer/distributor channels.
A14: B. Industrial Manufacturing | B14: 335 | C14: Electrical Equipment, Appliance & Component Manufacturing | D14: Core | E14: Electrical equipment/components; often sell through electrical distributors (link to Segment A).
A15: B. Industrial Manufacturing | B15: 31-33 | C15: All Manufacturing (sector) | D15: Broad | E15: Original brief scope. Rejected as core: includes food, beverage, apparel, printing etc. with retail/CPG go-to-market (tests H1).
... A23: Adjacency (not scored) | B23: 5613 | C23: Employment Services (staffing) | D23: Adjacency | E23: Outbound-heavy B2B service; noted for future screening, outside the brief's three segments.
A25: Size bands (firm employment, all U.S. establishments of the firm): SMB = 20–99 · Mid-Market = 100–499 · Enterprise = 500+. Firms with <20 employees are excluded from TAM (rarely staff a dedicated sales/RevOps function; Clay CRM sync requires the Growth tier).

Sheet Raw_Census
A1: Raw data — 2022 Economic Census, Employment Size of Firms (EC2200SIZEEMPFIRM), United States
A2: Source S14 · Reference year 2022 · Firms 'operated for the entire year' (FY) by firm employment size · Receipts in $ thousands · D = suppressed by Census (disclosure) · blank = not published
A4: Key | B4: NAICS 2022 | C4: Size band | D4: Firms | E4: Firm flag | F4: Establishments | G4: Employees | H4: Receipts ($000) | I4: Parent sector (for de-dup) | J4: File
A5: =B5&"|"&C5 -> 42|ALL | B5: 42 | C5: ALL | D5: 265472 | F5: 373446 | G5: 6219107 | H5: 11870055103 | J5: raw_census_ecnsize_2022_firm_size.csv
A6: =B6&"|"&C6 -> 42|FY | B6: 42 | C6: FY | D6: 236838 | F6: 344624 | G6: 6157364 | H6: 11818905379 | J6: raw_census_ecnsize_2022_firm_size.csv
A7: =B7&"|"&C7 -> 42|0-4 | B7: 42 | C7: 0-4 | D7: 126013 | F7: 127035 | G7: 251862 | H7: 316488154 | J7: raw_census_ecnsize_2022_firm_size.csv
A8: =B8&"|"&C8 -> 42|5-9 | B8: 42 | C8: 5-9 | D8: 43311 | F8: 44561 | G8: 285881 | H8: 318961246 | J8: raw_census_ecnsize_2022_firm_size.csv
A9: =B9&"|"&C9 -> 42|10-19 | B9: 42 | C9: 10-19 | D9: 30140 | F9: 33227 | G9: 406023 | H9: 474833888 | J9: raw_census_ecnsize_2022_firm_size.csv
A10: =B10&"|"&C10 -> 42|20-49 | B10: 42 | C10: 20-49 | D10: 21752 | F10: 29364 | G10: 661264 | H10: 854118039 | J10: raw_census_ecnsize_2022_firm_size.csv
A11: =B11&"|"&C11 -> 42|50-99 | B11: 42 | C11: 50-99 | D11: 7842 | F11: 16195 | G11: 541263 | H11: 724261166 | J11: raw_census_ecnsize_2022_firm_size.csv
A12: =B12&"|"&C12 -> 42|100-249 | B12: 42 | C12: 100-249 | D12: 4884 | F12: 18625 | G12: 745783 | H12: 1139812378 | J12: raw_census_ecnsize_2022_firm_size.csv
A13: =B13&"|"&C13 -> 42|250-499 | B13: 42 | C13: 250-499 | D13: 1591 | F13: 12879 | G13: 552047 | H13: 1431482338 | J13: raw_census_ecnsize_2022_firm_size.csv
A14: =B14&"|"&C14 -> 42|500+ | B14: 42 | C14: 500+ | D14: 1305 | F14: 62738 | G14: 2713241 | H14: 6558948170 | J14: raw_census_ecnsize_2022_firm_size.csv
A15: =B15&"|"&C15 -> 42|NFY | B15: 42 | C15: NFY | D15: 28634 | F15: 28822 | G15: 61743 | H15: 51149724 | J15: raw_census_ecnsize_2022_firm_size.csv
A16: =B16&"|"&C16 -> 423|ALL | B16: 423 | C16: ALL | D16: 144016 | F16: 218013 | G16: 3631054 | H16: 4917521572 | J16: raw_census_ecnsize_2022_firm_size.csv
... A26: =B26&"|"&C26 -> 423|NFY | B26: 423 | C26: NFY | D26: 13744 | F26: 13871 | G26: 34924 | H26: 22361743 | J26: raw_census_ecnsize_2022_firm_size.csv
A27: =B27&"|"&C27 -> 4235|ALL | B27: 4235 | C27: ALL | D27: 6239 | F27: 8705 | G27: 141633 | H27: 329309175 | I27: 423 | J27: raw_census_ecnsize_2022_firm_size.csv
A28: =B28&"|"&C28 -> 4235|FY | B28: 4235 | C28: FY | D28: 5827 | F28: 8293 | G28: 140747 | H28: 328151501 | I28: 423 | J28: raw_census_ecnsize_2022_firm_size.csv
A29: =B29&"|"&C29 -> 4235|0-4 | B29: 4235 | C29: 0-4 | D29: 2440 | F29: 2468 | I29: 423 | J29: raw_census_ecnsize_2022_firm_size.csv
A30: =B30&"|"&C30 -> 4235|5-9 | B30: 4235 | C30: 5-9 | D30: 1155 | F30: 1188 | G30: 7733 | H30: 20414280 | I30: 423 | J30: raw_census_ecnsize_2022_firm_size.csv
A31: =B31&"|"&C31 -> 4235|10-19 | B31: 4235 | C31: 10-19 | D31: 964 | F31: 1070 | G31: 13143 | H31: 23110739 | I31: 423 | J31: raw_census_ecnsize_2022_firm_size.csv
A32: =B32&"|"&C32 -> 4235|20-49 | B32: 4235 | C32: 20-49 | D32: 771 | F32: 1069 | G32: 23666 | H32: 67537558 | I32: 423 | J32: raw_census_ecnsize_2022_firm_size.csv
A33: =B33&"|"&C33 -> 4235|50-99 | B33: 4235 | C33: 50-99 | E33: D | I33: 423 | J33: raw_census_ecnsize_2022_firm_size.csv
A34: =B34&"|"&C34 -> 4235|100-249 | B34: 4235 | C34: 100-249 | E34: D | I34: 423 | J34: raw_census_ecnsize_2022_firm_size.csv
A35: =B35&"|"&C35 -> 4235|250-499 | B35: 4235 | C35: 250-499 | E35: D | I35: 423 | J35: raw_census_ecnsize_2022_firm_size.csv
A36: =B36&"|"&C36 -> 4235|500+ | B36: 4235 | C36: 500+ | D36: 22 | F36: 952 | G36: 33421 | H36: 55907376 | I36: 423 | J36: raw_census_ecnsize_2022_firm_size.csv
A37: =B37&"|"&C37 -> 4235|NFY | B37: 4235 | C37: NFY | D37: 412 | F37: 412 | G37: 886 | H37: 1157674 | I37: 423 | J37: raw_census_ecnsize_2022_firm_size.csv
A38: =B38&"|"&C38 -> 4236|ALL | B38: 4236 | C38: ALL | D38: 15781 | F38: 24933 | G38: 563675 | H38: 895229207 | I38: 423 | J38: raw_census_ecnsize_2022_firm_size.csv
A39: =B39&"|"&C39 -> 4236|FY | B39: 4236 | C39: FY | D39: 14286 | F39: 23428 | G39: 558076 | H39: 892018171 | I39: 423 | J39: raw_census_ecnsize_2022_firm_size.csv
A40: =B40&"|"&C40 -> 4236|0-4 | B40: 4236 | C40: 0-4 | D40: 6944 | F40: 7014 | G40: 14375 | H40: 12828028 | I40: 423 | J40: raw_census_ecnsize_2022_firm_size.csv
A41: =B41&"|"&C41 -> 4236|5-9 | B41: 4236 | C41: 5-9 | D41: 2810 | F41: 2910 | G41: 18634 | H41: 13883407 | I41: 423 | J41: raw_census_ecnsize_2022_firm_size.csv
A42: =B42&"|"&C42 -> 4236|10-19 | B42: 4236 | C42: 10-19 | D42: 1954 | F42: 2166 | G42: 26304 | H42: 24330556 | I42: 423 | J42: raw_census_ecnsize_2022_firm_size.csv
A43: =B43&"|"&C43 -> 4236|20-49 | B43: 4236 | C43: 20-49 | D43: 1408 | F43: 1868 | G43: 42698 | H43: 41687752 | I43: 423 | J43: raw_census_ecnsize_2022_firm_size.csv
A44: =B44&"|"&C44 -> 4236|50-99 | B44: 4236 | C44: 50-99 | D44: 570 | F44: 1260 | G44: 39297 | H44: 45903055 | I44: 423 | J44: raw_census_ecnsize_2022_firm_size.csv
A45: =B45&"|"&C45 -> 4236|100-249 | B45: 4236 | C45: 100-249 | D45: 350 | F45: 1159 | G45: 54183 | H45: 83021837 | I45: 423 | J45: raw_census_ecnsize_2022_firm_size.csv
A46: =B46&"|"&C46 -> 4236|250-499 | B46: 4236 | C46: 250-499 | D46: 136 | F46: 909 | G46: 47492 | H46: 153644795 | I46: 423 | J46: raw_census_ecnsize_2022_firm_size.csv
A47: =B47&"|"&C47 -> 4236|500+ | B47: 4236 | C47: 500+ | D47: 114 | F47: 6142 | G47: 315093 | H47: 516718741 | I47: 423 | J47: raw_census_ecnsize_2022_firm_size.csv
... A70: =B70&"|"&C70 -> 4238|NFY | B70: 4238 | C70: NFY | D70: 2665 | F70: 2693 | G70: 7465 | H70: 4252334 | I70: 423 | J70: raw_census_ecnsize_2022_firm_size.csv
A71: =B71&"|"&C71 -> 31-33|ALL | B71: 31-33 | C71: ALL | D71: 240644 | F71: 286626 | G71: 12171365 | H71: 7048663670 | J71: raw_census_ecnsize_2022_firm_size.csv
A72: =B72&"|"&C72 -> 31-33|FY | B72: 31-33 | C72: FY | D72: 238346 | F72: 284257 | G72: 12132125 | H72: 7040422502 | J72: raw_census_ecnsize_2022_firm_size.csv
A73: =B73&"|"&C73 -> 31-33|0-4 | B73: 31-33 | C73: 0-4 | D73: 103968 | F73: 104168 | G73: 203315 | H73: 50821615 | J73: raw_census_ecnsize_2022_firm_size.csv
A74: =B74&"|"&C74 -> 31-33|5-9 | B74: 31-33 | C74: 5-9 | D74: 39293 | F74: 39630 | G74: 262177 | H74: 65055412 | J74: raw_census_ecnsize_2022_firm_size.csv
A75: =B75&"|"&C75 -> 31-33|10-19 | B75: 31-33 | C75: 10-19 | D75: 34375 | F75: 35156 | G75: 473065 | H75: 113477378 | J75: raw_census_ecnsize_2022_firm_size.csv
A76: =B76&"|"&C76 -> 31-33|20-49 | B76: 31-33 | C76: 20-49 | D76: 32323 | F76: 34726 | G76: 998735 | H76: 278225654 | J76: raw_census_ecnsize_2022_firm_size.csv
A77: =B77&"|"&C77 -> 31-33|50-99 | B77: 31-33 | C77: 50-99 | D77: 13573 | F77: 16643 | G77: 943335 | H77: 312776290 | J77: raw_census_ecnsize_2022_firm_size.csv
A78: =B78&"|"&C78 -> 31-33|100-249 | B78: 31-33 | C78: 100-249 | D78: 8859 | F78: 14517 | G78: 1352115 | H78: 523251882 | J78: raw_census_ecnsize_2022_firm_size.csv
A79: =B79&"|"&C79 -> 31-33|250-499 | B79: 31-33 | C79: 250-499 | D79: 3013 | F79: 7770 | G79: 1046637 | H79: 507167665 | J79: raw_census_ecnsize_2022_firm_size.csv
A80: =B80&"|"&C80 -> 31-33|500+ | B80: 31-33 | C80: 500+ | D80: 2942 | F80: 31647 | G80: 6852746 | H80: 5189646606 | J80: raw_census_ecnsize_2022_firm_size.csv
A81: =B81&"|"&C81 -> 31-33|NFY | B81: 31-33 | C81: NFY | D81: 2298 | F81: 2369 | G81: 39240 | H81: 8241168 | J81: raw_census_ecnsize_2022_firm_size.csv
A82: =B82&"|"&C82 -> 326|ALL | B82: 326 | C82: ALL | D82: 8491 | F82: 11630 | G82: 825424 | H82: 303212658 | I82: 31-33 | J82: raw_census_ecnsize_2022_firm_size.csv
A83: =B83&"|"&C83 -> 326|FY | B83: 326 | C83: FY | D83: 8416 | F83: 11550 | G83: 821991 | H83: 302634977 | I83: 31-33 | J83: raw_census_ecnsize_2022_firm_size.csv
A84: =B84&"|"&C84 -> 326|0-4 | B84: 326 | C84: 0-4 | D84: 2181 | F84: 2185 | G84: 4686 | H84: 1572735 | I84: 31-33 | J84: raw_census_ecnsize_2022_firm_size.csv
A85: =B85&"|"&C85 -> 326|5-9 | B85: 326 | C85: 5-9 | D85: 1300 | F85: 1307 | G85: 8517 | H85: 2776701 | I85: 31-33 | J85: raw_census_ecnsize_2022_firm_size.csv
A86: =B86&"|"&C86 -> 326|10-19 | B86: 326 | C86: 10-19 | D86: 1145 | F86: 1157 | G86: 16304 | H86: 4483702 | I86: 31-33 | J86: raw_census_ecnsize_2022_firm_size.csv
A87: =B87&"|"&C87 -> 326|20-49 | B87: 326 | C87: 20-49 | D87: 1505 | F87: 1589 | G87: 48064 | H87: 13513333 | I87: 31-33 | J87: raw_census_ecnsize_2022_firm_size.csv
A88: =B88&"|"&C88 -> 326|50-99 | B88: 326 | C88: 50-99 | D88: 935 | F88: 1097 | G88: 66254 | H88: 19959650 | I88: 31-33 | J88: raw_census_ecnsize_2022_firm_size.csv
A89: =B89&"|"&C89 -> 326|100-249 | B89: 326 | C89: 100-249 | D89: 760 | F89: 1165 | G89: 119875 | H89: 40003013 | I89: 31-33 | J89: raw_census_ecnsize_2022_firm_size.csv
A90: =B90&"|"&C90 -> 326|250-499 | B90: 326 | C90: 250-499 | D90: 313 | F90: 815 | G90: 108128 | H90: 38397550 | I90: 31-33 | J90: raw_census_ecnsize_2022_firm_size.csv
A91: =B91&"|"&C91 -> 326|500+ | B91: 326 | C91: 500+ | D91: 277 | F91: 2235 | G91: 450163 | H91: 181928293 | I91: 31-33 | J91: raw_census_ecnsize_2022_firm_size.csv
A92: =B92&"|"&C92 -> 326|NFY | B92: 326 | C92: NFY | D92: 75 | F92: 80 | G92: 3433 | H92: 577681 | I92: 31-33 | J92: raw_census_ecnsize_2022_firm_size.csv
A93: =B93&"|"&C93 -> 332|ALL | B93: 332 | C93: ALL | D93: 49631 | F93: 54131 | G93: 1424399 | H93: 465673224 | I93: 31-33 | J93: raw_census_ecnsize_2022_firm_size.csv
... A136: =B136&"|"&C136 -> 335|NFY | B136: 335 | C136: NFY | D136: 38 | F136: 38 | G136: 1149 | H136: 155716 | I136: 31-33 | J136: raw_census_ecnsize_2022_firm_size.csv
A137: =B137&"|"&C137 -> 54|ALL | B137: 54 | C137: ALL | D137: 876176 | F137: 977257 | G137: 11185562 | H137: 2667262040 | J137: raw_census_ecnsize_2022_firm_size.csv
A138: =B138&"|"&C138 -> 54|FY | B138: 54 | C138: FY | D138: 682701 | F138: 783523 | G138: 10987793 | H138: 2616384416 | J138: raw_census_ecnsize_2022_firm_size.csv
A139: =B139&"|"&C139 -> 54|0-4 | B139: 54 | C139: 0-4 | D139: 462549 | F139: 463440 | G139: 837416 | H139: 183164148 | J139: raw_census_ecnsize_2022_firm_size.csv
A140: =B140&"|"&C140 -> 54|5-9 | B140: 54 | C140: 5-9 | D140: 103685 | F140: 104573 | G140: 677076 | H140: 136081252 | J140: raw_census_ecnsize_2022_firm_size.csv
A141: =B141&"|"&C141 -> 54|10-19 | B141: 54 | C141: 10-19 | D141: 58802 | F141: 61518 | G141: 785210 | H141: 163612699 | J141: raw_census_ecnsize_2022_firm_size.csv
A142: =B142&"|"&C142 -> 54|20-49 | B142: 54 | C142: 20-49 | D142: 35049 | F142: 41789 | G142: 1048008 | H142: 229495147 | J142: raw_census_ecnsize_2022_firm_size.csv
A143: =B143&"|"&C143 -> 54|50-99 | B143: 54 | C143: 50-99 | D143: 11416 | F143: 18272 | G143: 787141 | H143: 184107812 | J143: raw_census_ecnsize_2022_firm_size.csv
A144: =B144&"|"&C144 -> 54|100-249 | B144: 54 | C144: 100-249 | D144: 6827 | F144: 17145 | G144: 1036485 | H144: 252583359 | J144: raw_census_ecnsize_2022_firm_size.csv
A145: =B145&"|"&C145 -> 54|250-499 | B145: 54 | C145: 250-499 | D145: 2304 | F145: 9861 | G145: 799542 | H145: 199848710 | J145: raw_census_ecnsize_2022_firm_size.csv
A146: =B146&"|"&C146 -> 54|500+ | B146: 54 | C146: 500+ | D146: 2069 | F146: 66925 | G146: 5016915 | H146: 1267491289 | J146: raw_census_ecnsize_2022_firm_size.csv
A147: =B147&"|"&C147 -> 54|NFY | B147: 54 | C147: NFY | D147: 193475 | F147: 193734 | G147: 197769 | H147: 50877624 | J147: raw_census_ecnsize_2022_firm_size.csv
A148: =B148&"|"&C148 -> 5411|ALL | B148: 5411 | C148: ALL | D148: 168337 | F148: 182081 | G148: 1395948 | H148: 374572500 | I148: 54 | J148: raw_census_ecnsize_2022_firm_size.csv
A149: =B149&"|"&C149 -> 5411|FY | B149: 5411 | C149: FY | D149: 142068 | F149: 155771 | G149: 1374144 | H149: 367665906 | I149: 54 | J149: raw_census_ecnsize_2022_firm_size.csv
A150: =B150&"|"&C150 -> 5411|0-4 | B150: 5411 | C150: 0-4 | D150: 98148 | F150: 98339 | G150: 192332 | H150: 41701767 | I150: 54 | J150: raw_census_ecnsize_2022_firm_size.csv
A151: =B151&"|"&C151 -> 5411|5-9 | B151: 5411 | C151: 5-9 | D151: 24205 | F151: 24408 | G151: 156477 | H151: 32972474 | I151: 54 | J151: raw_census_ecnsize_2022_firm_size.csv
A152: =B152&"|"&C152 -> 5411|10-19 | B152: 5411 | C152: 10-19 | D152: 11097 | F152: 11921 | G152: 146340 | H152: 33044856 | I152: 54 | J152: raw_census_ecnsize_2022_firm_size.csv
A153: =B153&"|"&C153 -> 5411|20-49 | B153: 5411 | C153: 20-49 | D153: 5672 | F153: 7678 | G153: 168562 | H153: 39417935 | I153: 54 | J153: raw_census_ecnsize_2022_firm_size.csv
A154: =B154&"|"&C154 -> 5411|50-99 | B154: 5411 | C154: 50-99 | D154: 1573 | F154: 3457 | G154: 107806 | H154: 26151760 | I154: 54 | J154: raw_census_ecnsize_2022_firm_size.csv
A155: =B155&"|"&C155 -> 5411|100-249 | B155: 5411 | C155: 100-249 | D155: 900 | F155: 3761 | G155: 133248 | H155: 33969786 | I155: 54 | J155: raw_census_ecnsize_2022_firm_size.csv
A156: =B156&"|"&C156 -> 5411|250-499 | B156: 5411 | C156: 250-499 | D156: 251 | F156: 2239 | G156: 86614 | H156: 23462215 | I156: 54 | J156: raw_census_ecnsize_2022_firm_size.csv
A157: =B157&"|"&C157 -> 5411|500+ | B157: 5411 | C157: 500+ | D157: 222 | F157: 3968 | G157: 382765 | H157: 136945113 | I157: 54 | J157: raw_census_ecnsize_2022_firm_size.csv
A158: =B158&"|"&C158 -> 5411|NFY | B158: 5411 | C158: NFY | D158: 26269 | F158: 26310 | G158: 21804 | H158: 6906594 | I158: 54 | J158: raw_census_ecnsize_2022_firm_size.csv
A159: =B159&"|"&C159 -> 5412|ALL | B159: 5412 | C159: ALL | D159: 120889 | F159: 136861 | G159: 1313416 | H159: 208847722 | I159: 54 | J159: raw_census_ecnsize_2022_firm_size.csv
... A213: =B213&"|"&C213 -> 5418|NFY | B213: 5418 | C213: NFY | D213: 6958 | F213: 6985 | G213: 9919 | H213: 2816543 | I213: 54 | J213: raw_census_ecnsize_2022_firm_size.csv
A214: =B214&"|"&C214 -> 5132|ALL | B214: 5132 | C214: ALL | D214: 16824 | F214: 20976 | G214: 1033305 | H214: 492929994 | J214: raw_census_ecnsize_2022_firm_size.csv
A215: =B215&"|"&C215 -> 5132|FY | B215: 5132 | C215: FY | D215: 13406 | F215: 17539 | G215: 1024177 | H215: 489677276 | J215: raw_census_ecnsize_2022_firm_size.csv
A216: =B216&"|"&C216 -> 5132|0-4 | B216: 5132 | C216: 0-4 | D216: 5759 | F216: 5791 | G216: 11662 | H216: 4193224 | J216: raw_census_ecnsize_2022_firm_size.csv
A217: =B217&"|"&C217 -> 5132|5-9 | B217: 5132 | C217: 5-9 | D217: 2363 | F217: 2395 | G217: 15727 | H217: 4958049 | J217: raw_census_ecnsize_2022_firm_size.csv
A218: =B218&"|"&C218 -> 5132|10-19 | B218: 5132 | C218: 10-19 | D218: 2010 | F218: 2048 | G218: 27371 | H218: 8501498 | J218: raw_census_ecnsize_2022_firm_size.csv
A219: =B219&"|"&C219 -> 5132|20-49 | B219: 5132 | C219: 20-49 | D219: 1557 | F219: 1645 | G219: 47948 | H219: 15211659 | J219: raw_census_ecnsize_2022_firm_size.csv
A220: =B220&"|"&C220 -> 5132|50-99 | B220: 5132 | C220: 50-99 | D220: 638 | F220: 753 | G220: 44250 | H220: 14725095 | J220: raw_census_ecnsize_2022_firm_size.csv
A221: =B221&"|"&C221 -> 5132|100-249 | B221: 5132 | C221: 100-249 | D221: 575 | F221: 797 | G221: 89863 | H221: 40293112 | J221: raw_census_ecnsize_2022_firm_size.csv
A222: =B222&"|"&C222 -> 5132|250-499 | B222: 5132 | C222: 250-499 | D222: 209 | F222: 416 | G222: 73378 | H222: 26998461 | J222: raw_census_ecnsize_2022_firm_size.csv
A223: =B223&"|"&C223 -> 5132|500+ | B223: 5132 | C223: 500+ | D223: 295 | F223: 3694 | G223: 713978 | H223: 374796178 | J223: raw_census_ecnsize_2022_firm_size.csv
A224: =B224&"|"&C224 -> 5132|NFY | B224: 5132 | C224: NFY | D224: 3418 | F224: 3437 | G224: 9128 | H224: 3252718 | J224: raw_census_ecnsize_2022_firm_size.csv
A225: =B225&"|"&C225 -> 5613|ALL | B225: 5613 | C225: ALL | D225: 31331 | F225: 56763 | G225: 7770894 | H225: 557867373 | J225: raw_census_ecnsize_2022_firm_size.csv
... A235: =B235&"|"&C235 -> 5613|NFY | B235: 5613 | C235: NFY | D235: 6636 | F235: 6658 | G235: 45216 | H235: 3909319 | J235: raw_census_ecnsize_2022_firm_size.csv
A236: =B236&"|"&C236 -> 4231|FY | B236: 4231 | C236: FY | D236: 12540 | F236: 21606 | I236: 423 | J236: overlap_raw.csv
...

Sheet Raw_OEWS
A1: Raw data — BLS Occupational Employment and Wage Statistics (OEWS), May 2025, national industry-specific estimates
A2: Source S15 · Employment counts by occupation within industry · RSE = relative standard error (%) · suppressed estimates left blank
A4: Key | B4: BLS industry code | C4: Industry | D4: Segment proxy | E4: SOC code | F4: Occupation | G4: Employment | H4: Emp. RSE (%)
A5: =B5&"|"&E5 -> 000000|00-0000 | B5: 000000 | C5: Cross-industry (all) | D5: AllIndustries | E5: 00-0000 | F5: All occupations | G5: 155495730 | H5: 0
A6: =B6&"|"&E6 -> 000000|11-2021 | B6: 000000 | C6: Cross-industry (all) | D6: AllIndustries | E6: 11-2021 | F6: Marketing managers | G6: 395240 | H6: 0.8
A7: =B7&"|"&E7 -> 000000|11-2022 | B7: 000000 | C7: Cross-industry (all) | D7: AllIndustries | E7: 11-2022 | F7: Sales managers | G7: 637080 | H7: 1.1
A8: =B8&"|"&E8 -> 000000|13-1161 | B8: 000000 | C8: Cross-industry (all) | D8: AllIndustries | E8: 13-1161 | F8: Market research analysts & marketing specialists | G8: 899580 | H8: 0.8
A9: =B9&"|"&E9 -> 000000|15-0000 | B9: 000000 | C9: Cross-industry (all) | D9: AllIndustries | E9: 15-0000 | F9: Computer & mathematical occupations (major group) | G9: 5260110 | H9: 0.3
A10: =B10&"|"&E10 -> 000000|41-0000 | B10: 000000 | C10: Cross-industry (all) | D10: AllIndustries | E10: 41-0000 | F10: Sales & related occupations (major group) | G10: 13424300 | H10: 0.3
A11: =B11&"|"&E11 -> 000000|41-4011 | B11: 000000 | C11: Cross-industry (all) | D11: AllIndustries | E11: 41-4011 | F11: Sales reps, wholesale & mfg — technical & scientific products | G11: 284800 | H11: 1.8
A12: =B12&"|"&E12 -> 000000|41-4012 | B12: 000000 | C12: Cross-industry (all) | D12: AllIndustries | E12: 41-4012 | F12: Sales reps, wholesale & mfg — except technical & scientific | G12: 1238190 | H12: 0.6
A13: =B13&"|"&E13 -> 000000|43-4051 | B13: 000000 | C13: Cross-industry (all) | D13: AllIndustries | E13: 43-4051 | F13: Customer service representatives | G13: 2595750 | H13: 0.4
A14: =B14&"|"&E14 -> 4230A1|00-0000 | B14: 4230A1 | C14: Merchant Wholesalers, Durable Goods (4232/3/5/6/7/9 only) | D14: Distribution | E14: 00-0000 | F14: All occupations | G14: 1503920 | H14: 0
A15: =B15&"|"&E15 -> 4230A1|11-2021 | B15: 4230A1 | C15: Merchant Wholesalers, Durable Goods (4232/3/5/6/7/9 only) | D15: Distribution | E15: 11-2021 | F15: Marketing managers | G15: 7620 | H15: 6.3
A16: =B16&"|"&E16 -> 4230A1|11-2022 | B16: 4230A1 | C16: Merchant Wholesalers, Durable Goods (4232/3/5/6/7/9 only) | D16: Distribution | E16: 11-2022 | F16: Sales managers | G16: 28580 | H16: 3.3
... A82: =B82&"|"&E82 -> 541100|41-0000 | B82: 541100 | C82: Legal Services | D82: (not used) | E82: 41-0000 | F82: Sales & related occupations (major group) | G82: 3380 | H82: 14.2
A83: =B83&"|"&E83 -> 541100|41-4012 | B83: 541100 | C83: Legal Services | D83: (not used) | E83: 41-4012 | F83: Sales reps, wholesale & mfg — except technical & scientific
A84: =B84&"|"&E84 -> 541100|43-4051 | B84: 541100 | C84: Legal Services | D84: (not used) | E84: 43-4051 | F84: Customer service representatives | G84: 7170 | H84: 10
A85: =B85&"|"&E85 -> 541200|00-0000 | B85: 541200 | C85: Accounting, Tax Prep, Bookkeeping & Payroll | D85: (not used) | E85: 00-0000 | F85: All occupations | G85: 1091370 | H85: 0
A86: =B86&"|"&E86 -> 541200|11-2021 | B86: 541200 | C86: Accounting, Tax Prep, Bookkeeping & Payroll | D86: (not used) | E86: 11-2021 | F86: Marketing managers | G86: 4160 | H86: 7.4
A87: =B87&"|"&E87 -> 541200|11-2022 | B87: 541200 | C87: Accounting, Tax Prep, Bookkeeping & Payroll | D87: (not used) | E87: 11-2022 | F87: Sales managers | G87: 5360 | H87: 6.7
A88: =B88&"|"&E88 -> 541200|13-1161 | B88: 541200 | C88: Accounting, Tax Prep, Bookkeeping & Payroll | D88: (not used) | E88: 13-1161 | F88: Market research analysts & marketing specialists | G88: 6430 | H88: 5.4
A89: =B89&"|"&E89 -> 541200|15-0000 | B89: 541200 | C89: Accounting, Tax Prep, Bookkeeping & Payroll | D89: (not used) | E89: 15-0000 | F89: Computer & mathematical occupations (major group) | G89: 53990 | H89: 2.8
A90: =B90&"|"&E90 -> 541200|41-0000 | B90: 541200 | C90: Accounting, Tax Prep, Bookkeeping & Payroll | D90: (not used) | E90: 41-0000 | F90: Sales & related occupations (major group) | G90: 37640 | H90: 7.3
A91: =B91&"|"&E91 -> 541200|41-4011 | B91: 541200 | C91: Accounting, Tax Prep, Bookkeeping & Payroll | D91: (not used) | E91: 41-4011 | F91: Sales reps, wholesale & mfg — technical & scientific products | G91: 320 | H91: 37.2
A92: =B92&"|"&E92 -> 541200|41-4012 | B92: 541200 | C92: Accounting, Tax Prep, Bookkeeping & Payroll | D92: (not used) | E92: 41-4012 | F92: Sales reps, wholesale & mfg — except technical & scientific
A93: =B93&"|"&E93 -> 541200|43-4051 | B93: 541200 | C93: Accounting, Tax Prep, Bookkeeping & Payroll | D93: (not used) | E93: 43-4051 | F93: Customer service representatives | G93: 18920 | H93: 4.8
A94: =B94&"|"&E94 -> 541300|00-0000 | B94: 541300 | C94: Architectural, Engineering & Related | D94: ProfServices | E94: 00-0000 | F94: All occupations | G94: 1719390 | H94: 0
A95: =B95&"|"&E95 -> 541300|11-2021 | B95: 541300 | C95: Architectural, Engineering & Related | D95: ProfServices | E95: 11-2021 | F95: Marketing managers | G95: 6380 | H95: 8.9
A96: =B96&"|"&E96 -> 541300|11-2022 | B96: 541300 | C96: Architectural, Engineering & Related | D96: ProfServices | E96: 11-2022 | F96: Sales managers | G96: 5230 | H96: 5.9
A97: =B97&"|"&E97 -> 541300|13-1161 | B97: 541300 | C97: Architectural, Engineering & Related | D97: ProfServices | E97: 13-1161 | F97: Market research analysts & marketing specialists | G97: 14890 | H97: 5.4
A98: =B98&"|"&E98 -> 541300|15-0000 | B98: 541300 | C98: Architectural, Engineering & Related | D98: ProfServices | E98: 15-0000 | F98: Computer & mathematical occupations (major group) | G98: 117050 | H98: 2.3
A99: =B99&"|"&E99 -> 541300|41-0000 | B99: 541300 | C99: Architectural, Engineering & Related | D99: ProfServices | E99: 41-0000 | F99: Sales & related occupations (major group) | G99: 19650 | H99: 5.9
A100: =B100&"|"&E100 -> 541300|41-4011 | B100: 541300 | C100: Architectural, Engineering & Related | D100: ProfServices | E100: 41-4011 | F100: Sales reps, wholesale & mfg — technical & scientific products | G100: 1830 | H100: 16.6
A101: =B101&"|"&E101 -> 541300|41-4012 | B101: 541300 | C101: Architectural, Engineering & Related | D101: ProfServices | E101: 41-4012 | F101: Sales reps, wholesale & mfg — except technical & scientific | G101: 1170 | H101: 16.7
A102: =B102&"|"&E102 -> 541300|43-4051 | B102: 541300 | C102: Architectural, Engineering & Related | D102: ProfServices | E102: 43-4051 | F102: Customer service representatives | G102: 4710 | H102: 4.8
A103: =B103&"|"&E103 -> 541500|00-0000 | B103: 541500 | C103: Computer Systems Design & Related | D103: ProfServices | E103: 00-0000 | F103: All occupations | G103: 2445140 | H103: 0
A104: =B104&"|"&E104 -> 541500|11-2021 | B104: 541500 | C104: Computer Systems Design & Related | D104: ProfServices | E104: 11-2021 | F104: Marketing managers | G104: 25860 | H104: 4
... A126: =B126&"|"&E126 -> 541800|41-0000 | B126: 541800 | C126: Advertising, PR & Related | D126: ProfServices | E126: 41-0000 | F126: Sales & related occupations (major group) | G126: 94260 | H126: 2.4
A127: =B127&"|"&E127 -> 541800|41-4011 | B127: 541800 | C127: Advertising, PR & Related | D127: ProfServices | E127: 41-4011 | F127: Sales reps, wholesale & mfg — technical & scientific products
A128: =B128&"|"&E128 -> 541800|41-4012 | B128: 541800 | C128: Advertising, PR & Related | D128: ProfServices | E128: 41-4012 | F128: Sales reps, wholesale & mfg — except technical & scientific | G128: 2830 | H128: 11
A129: =B129&"|"&E129 -> 541800|43-4051 | B129: 541800 | C129: Advertising, PR & Related | D129: ProfServices | E129: 43-4051 | F129: Customer service representatives | G129: 8440 | H129: 10.6
A130: =B130&"|"&E130 -> 513200|00-0000 | B130: 513200 | C130: Software Publishers | D130: Software | E130: 00-0000 | F130: All occupations | G130: 659550 | H130: 0
A131: =B131&"|"&E131 -> 513200|11-2021 | B131: 513200 | C131: Software Publishers | D131: Software | E131: 11-2021 | F131: Marketing managers | G131: 12990 | H131: 8.4
A132: =B132&"|"&E132 -> 513200|11-2022 | B132: 513200 | C132: Software Publishers | D132: Software | E132: 11-2022 | F132: Sales managers | G132: 16330 | H132: 4.1
A133: =B133&"|"&E133 -> 513200|13-1161 | B133: 513200 | C133: Software Publishers | D133: Software | E133: 13-1161 | F133: Market research analysts & marketing specialists | G133: 23490 | H133: 4.7
A134: =B134&"|"&E134 -> 513200|15-0000 | B134: 513200 | C134: Software Publishers | D134: Software | E134: 15-0000 | F134: Computer & mathematical occupations (major group) | G134: 308280 | H134: 1.1
A135: =B135&"|"&E135 -> 513200|41-0000 | B135: 513200 | C135: Software Publishers | D135: Software | E135: 41-0000 | F135: Sales & related occupations (major group) | G135: 71350 | H135: 3
A136: =B136&"|"&E136 -> 513200|41-4011 | B136: 513200 | C136: Software Publishers | D136: Software | E136: 41-4011 | F136: Sales reps, wholesale & mfg — technical & scientific products | G136: 12800 | H136: 4.5
A137: =B137&"|"&E137 -> 513200|41-4012 | B137: 513200 | C137: Software Publishers | D137: Software | E137: 41-4012 | F137: Sales reps, wholesale & mfg — except technical & scientific | G137: 5500 | H137: 11.5
A138: =B138&"|"&E138 -> 513200|43-4051 | B138: 513200 | C138: Software Publishers | D138: Software | E138: 43-4051 | F138: Customer service representatives | G138: 16710 | H138: 5.9
A139: =B139&"|"&E139 -> 561300|00-0000 | B139: 561300 | C139: Employment Services | D139: (not used) | E139: 00-0000 | F139: All occupations | G139: 3301980 | H139: 0
... A147: =B147&"|"&E147 -> 561300|43-4051 | B147: 561300 | C147: Employment Services | D147: (not used) | E147: 43-4051 | F147: Customer service representatives | G147: 69550 | H147: 3.2

Sheet Sources
A1: Sources used in this workbook
A2: Full register: Research_Sources.csv. Access date for all: 2026-10-18/19.
A4: ID | B4: Source | C4: Publisher | D4: Reference period | E4: URL | F4: Used for
A5: S01 | B5: Clay pricing page | C5: Clay Labs Inc. | D5: Live, Oct 2026 | E5: https://www.clay.com/pricing | F5: ACV floor (Growth tier list price)
A6: S02 | B6: Clay second employee tender offer press release | C6: Business Wire | D6: Dec 2025–Jan 2026 | E6: https://www.businesswire.com/news/home/20260128514638/en | F6: Enterprise NRR >200% (penetration rationale)
A7: S03 | B7: Clay Series D coverage (17,000+ customers) | C7: Autobound / mrweb (secondary) | D7: Sep 2026 | E7: https://mrweb.com/drno/news40306.htm | F7: Sanity check: customer count
A8: S04 | B8: Clay crosses $150M/year (estimate) | C8: Sacra | D8: May 2026 | E8: https://sacra.com/research/clay-crosses-150m-year/ | F8: Superseded ARR estimate [B]
A9: S23 | B9: Apollo.io at $265M ARR (incl. Clay ~$200M ARR estimate, Sep 2026) | C9: Sacra | D9: 2026-10-14 | E9: https://sacra.com/research/apollo-at-265m-arr/ | F9: Sanity check: ARR scale [B]
A10: S14 | B10: 2022 Economic Census — Employment Size of Firms (EC2200SIZEEMPFIRM) | C10: U.S. Census Bureau | D10: 2022 | E10: https://data.census.gov/table/ECNSIZE2022.EC2200SIZEEMPFIRM | F10: All firm, establishment, employment and receipts counts
A11: S15 | B11: OEWS May 2025 national industry-specific estimates | C11: U.S. Bureau of Labor Statistics | D11: May 2025 | E11: https://data.bls.gov/oes/#/industry/423800/2025 | F11: Sales intensity and builder-capacity proxies
A12: S16 | B12: Clay pricing benchmarks (Vendr marketplace) | C12: Vendr | D12: Updated Feb 2026 | E12: https://www.vendr.com/marketplace/clay | F12: ACV benchmarks: median $59,996; range $16.5K–$170K; n=96
A13: S17 | B13: The State of CRM in Distribution (2022) | C13: Distribution Strategy Group | D13: 2022 | E13: https://archive.distributionstrategy.com/wp-content/uploads/2022/10/DSG-The-State-of-CRM-in-Distribution-Making-the-Software-Work-for-You.pdf | F13: Distributor CRM adoption mix (SAM filter 2)
