Workbook

Sheet Cover
A1: 07 — Financial Model: three-year business case for a U.S. industrial-distribution pilot
A2: Independent portfolio case study by Zhuoran (Zora) Wang · Not commissioned by or affiliated with Clay Labs Inc. · Research reference date: 2026-10-18
A4: Question | B4: Does the Phase 3 recommendation (enter industrial distribution through a staged, partner-led pilot) create value over 2027–2029, and how should it be sized and gated?
A5: Structure | B5: Assumptions → Market Sizing → ACV Build → GTM Funnel → Revenue Model → Unit Economics (live model, selectors on Assumptions D4:D5) → Scenarios and Sensitivity (full model copies on Engine Runs) → Executive Output.
A6: Time and units | B6: Quarterly, Q1 2027–Q4 2029; annual totals in columns P–R and 2027–29 in S. US$ nominal. ARR is end-of-quarter run-rate; recognized revenue = average ARR ÷ 4 (kept separate).
A7: Scope of costs | B7: Incremental to Clay only: vertical team, variable sales cost, programs, partner fees, enablement, onboarding subsidies, template/connector build, customer success. COGS via gross margin. No allocation of Clay's existing overhead.
A8: Evidence classes | B8: A = verified public fact · B = external benchmark · C = analyst estimate · D = scenario assumption · E = recommendation. Every input row on Assumptions carries its class and source.
A9: Color legend | B9: Blue = input · black = formula · green = link to another tab · yellow fill = judgment assumption · green fill = key output.
A10: Not a forecast | B10: Outputs are scenario-based estimates. They are not Clay forecasts and imply no access to Clay internal financials. Probability weights in the decision analysis are explicit judgments.

Sheet Executive Output
A1: Executive Output — three-year business case for the distribution pilot (2027–2029)
A2: Scenario outputs are illustrative estimates built from public data and labeled assumptions. They are not Clay forecasts and do not use Clay internal data.
A3: ="Live model currently set to: "&Assumptions!$E$4&" · "&Assumptions!$E$5&" (change on Assumptions D4:D5)" -> Live model currently set to: Base · Partner-led pilot (change on Assumptions D4:D5)
A5: Metric | B5: Partner-led: Downside | C5: Partner-led: Downside, gated | D5: Partner-led: Base | E5: Partner-led: Upside | F5: Partner-led: Upside + scale-up | G5: Sales-led team: Base | H5: Note
A6: Exit ARR, Q4 2029 | B6: =Scenarios!D5 -> 60533.792 | C6: =Scenarios!E5 -> 6382.4703 | D6: =Scenarios!F5 -> 861203.84 | E6: =Scenarios!G5 -> 4372033.9 | F6: =Scenarios!H5 -> 6013068.7 | G6: =Scenarios!I5 -> 861203.84
A7: New customers 2027–29 | B7: =Scenarios!D7 -> 5.4867647 | C7: =Scenarios!E7 -> 0.61705718 | D7: =Scenarios!F7 -> 57.63577 | E7: =Scenarios!G7 -> 193.95499 | F7: =Scenarios!H7 -> 257.63071 | G7: =Scenarios!I7 -> 57.63577
A8: Average first-year ACV | B8: =Scenarios!D9 -> 11019.558 | C8: =Scenarios!E9 -> 10372.816 | D8: =Scenarios!F9 -> 13800.744 | E8: =Scenarios!G9 -> 18213.149 | F8: =Scenarios!H9 -> 19363.117 | G8: =Scenarios!I9 -> 13800.744 | H8: Usage-based build
A9: CAC | B9: =Scenarios!D10 -> 331930.67 | C9: =Scenarios!E10 -> 819865.25 | D9: =Scenarios!F10 -> 41115.536 | E9: =Scenarios!G10 -> 18950.649 | F9: =Scenarios!H10 -> 17982.905 | G9: =Scenarios!I10 -> 119895.93 | H9: Sales & marketing ÷ new customers
A10: CAC payback, 2027–29 average (months) | B10: =Scenarios!D11 -> 657.20636 | C10: =Scenarios!E11 -> 1724.5046 | D10: =Scenarios!F11 -> 55.001095 | E10: =Scenarios!G11 -> 17.341545 | F10: =Scenarios!H11 -> 15.478659 | G10: =Scenarios!I11 -> 160.38725 | H10: Benchmark median: SMB 8–12, MM 14–18 (S47)
A11: CAC payback, 2029 cohort (months) | B11: =Scenarios!D12 -> 444.95536 | C11: =Scenarios!E12 -> 0 | D11: =Scenarios!F12 -> 36.566752 | E11: =Scenarios!G12 -> 14.839987 | F11: =Scenarios!H12 -> 12.321919 | G11: =Scenarios!I12 -> 108.09951 | H11: Steady-state view after launch costs
A12: LTV : CAC | B12: =Scenarios!D13 -> 0.091295526 | C12: =Scenarios!E13 -> 0.0347926 | D12: =Scenarios!F13 -> 1.0908874 | E12: =Scenarios!G13 -> 3.4598993 | F12: =Scenarios!H13 -> 3.8763047 | G12: =Scenarios!I13 -> 0.37409458 | H12: >3x is the usual bar [K]
A13: Total incremental cost 2027–29 | B13: =Scenarios!D14 -> 2537039 | C13: =Scenarios!E14 -> 984681.44 | D13: =Scenarios!F14 -> 3208602.2 | E13: =Scenarios!G14 -> 4886302 | F13: =Scenarios!H14 -> 5981245.9 | G13: =Scenarios!I14 -> 7749171.1
A14: Cumulative program P&L 2027–29 | B14: =Scenarios!D15 -> -2502632.2 | C14: =Scenarios!E15 -> -977016.28 | D14: =Scenarios!F15 -> -2684074.4 | E14: =Scenarios!G15 -> -1575275 | F14: =Scenarios!H15 -> -1902658.5 | G14: =Scenarios!I15 -> -7224643.2
A15: Peak investment required | B15: =Scenarios!D16 -> -2502632.2 | C15: =Scenarios!E16 -> -981728.03 | D15: =Scenarios!F16 -> -2684074.4 | E15: =Scenarios!G16 -> -2016342.7 | F15: =Scenarios!H16 -> -2446003.1 | G15: =Scenarios!I16 -> -7224643.2 | H15: Lowest cumulative P&L
A16: Q4 2029 program P&L, annualized | B16: =Scenarios!D18 -> -734894.69 | C16: =Scenarios!E18 -> 2538.4117 | D16: =Scenarios!F18 -> -670395.19 | E16: =Scenarios!G18 -> 962564.01 | F16: =Scenarios!H18 -> 1302973.5 | G16: =Scenarios!I18 -> -2520754.9 | H16: Exit run-rate
A17: Total value incl. embedded value of ARR base | B17: =Scenarios!D20 -> -2429124 | C17: =Scenarios!E20 -> -968557.16 | D17: =Scenarios!F20 -> -1041530 | E17: =Scenarios!G20 -> 9851170.9 | F17: =Scenarios!H20 -> 13729819 | G17: =Scenarios!I20 -> -5582098.9 | H17: Cumulative P&L + 5-yr GP of 2029 base
A19: Decision metrics
A20: Expected total value — staged pilot (probability-weighted) | B20: =Scenarios!G30 -> 1938280.2 | H20: Weights 35/45/20 (Assumptions, judgment)
A21: Expected total value — ungated | B21: =Scenarios!G29 -> 651352.27
A22: Expected cumulative P&L 2027–29 — staged (no post-2029 value) | B22: =Scenarios!G31 -> -1930320.9 | H22: Every scenario is cash-negative through 2029; value depends on the ARR base after 2029
A23: Break-even probability of Upside (staged EV = 0) | B23: =Scenarios!G33 -> 0.068496873 | H23: Pilot is worth running if P(Upside) exceeds this
A24: Sales-led team minus partner-led, Base cumulative P&L | B24: =Scenarios!G34 -> -4540568.9 | H24: Same ARR; extra cost only
A25: Lowest tested win rate for ≤ 24-month payback (2029 cohort, Base usage) | B25: =Sensitivity!E31 -> none tested | H25: Benchmarks: 21% avg; 31–39% opp→won
A26: Lowest tested win rate for total value ≥ 0 | B26: =Sensitivity!E32 -> 0.5
A27: Model checks (0 = pass) | B27: =ABS(Scenarios!D23)+ABS(Scenarios!D24) -> 0 | H27: Live model reconciles to engine runs
A29: What the model shows
A30: 1. The distribution vertical is demand-limited, not capacity-limited. A dedicated sales team produces the same ARR as the partner-led pilot in Base, at materially higher cost, so Option 1 is rejected on economics (H7 supported).
A31: 2. In the Base case the partner-led pilot does not pay back within 2027–29. The serviceable market is ~5,200 firms, and list-price ACVs are ~$5K (SMB), ~$10K (Mid-Market) and ~$62K (Enterprise).
A32: 3. The Upside case (higher win rates, usage and retention) pays back and is profitable at its 2029 exit run-rate; there, borrowed AE capacity binds from Q3 2028, which is the evidence-based trigger to hire two dedicated AEs. The pilot is therefore an option: a capped, gateable investment with an asymmetric payoff.
A33: 4. A Q4 2027 Go/No-Go gate cuts the Downside loss by more than half. The sensitivity is led by usage intensity (ACV), then funnel conversion (win rate, SQL→opportunity, qualification), gross margin and partner productivity; these become the gate metrics.
A34: 5. Implication for strategy: run the pilot lean (≈1 lead + 1 engineer + shared AEs + partners), focus on 100+ employee distributors, and do not hire a vertical sales team unless the gate metrics are met.

Sheet Assumptions
A1: Assumptions — every input in one place (Downside / Base / Upside)
A2: Change blue cells only. 'Live' feeds the main model (GTM Funnel → Revenue Model → Unit Economics) via the two selectors below. Scenarios/Sensitivity run their own copies of the model.
A4: Scenario selector (1 = Downside, 2 = Base, 3 = Upside) | D4: 2 | E4: =CHOOSE($D$4,"Downside","Base","Upside") -> Base
A5: Motion selector (1 = Partner-led pilot [Option 4], 2 = Sales-led vertical team [Option 1]) | D5: 1 | E5: =CHOOSE($D$5,"Partner-led pilot","Sales-led vertical team") -> Partner-led pilot
A7: ID | B7: Input | C7: Unit | D7: Downside | E7: Base | F7: Upside | G7: Live | H7: Class | I7: Source / rationale
A8: MARKET
A9: A1 | B9: SAM filter 1: share of firms with active outbound/territory motion | C9: % | D9: 0.65 | E9: 0.8 | F9: 0.9 | G9: =INDEX(D9:F9,1,Assumptions!$D$4) -> 0.8 | H9: D | I9: Phase 1 (02_Market_Sizing, Assumptions A4); sales occupations 22% of distribution employment (S15)
A10: A2 | B10: SAM filter 2: share CRM-ready (integrable today) | C10: % | D10: 0.52 | E10: 0.65 | F10: 0.76 | G10: =INDEX(D10:F10,1,Assumptions!$D$4) -> 0.65 | H10: B/D | I10: Phase 1 A7; DSG 2022 distributor CRM survey (S17)
A11: A3 | B11: Share of SAM already Clay customers (excluded) | C11: % | D11: 0.03 | E11: 0.03 | F11: 0.03 | G11: =INDEX(D11:F11,1,Assumptions!$D$4) -> 0.03 | H11: D | I11: No public data; small given ~40% software mix of detected Clay users (S32)
A12: A4 | B12: Wave 1 launch quarter — 4236 electrical distributors (1 = Q1 2027) | C12: quarter | D12: 1 | E12: 1 | F12: 1 | G12: =INDEX(D12:F12,1,Assumptions!$D$4) -> 1 | H12: E | I12: Beachhead from 06_Segment_Prioritization (Subsegment_Drilldown)
A13: A5 | B13: Wave 2 launch quarter — 4237 hardware, plumbing & HVAC | C13: quarter | D13: 7 | E13: 5 | F13: 4 | G13: =INDEX(D13:F13,1,Assumptions!$D$4) -> 5 | H13: D | I13: After first Go/No-Go gate; Downside delays
A14: A6 | B14: Wave 3 launch quarter — 4238 machinery & MRO (99 = never) | C14: quarter | D14: 99 | E14: 7 | F14: 6 | G14: =INDEX(D14:F14,1,Assumptions!$D$4) -> 7 | H14: D | I14: Downside never launches wave 3
A16: GTM FUNNEL
A17: A7 | B17: Outbound coverage: share of active SAM accounts sequenced per quarter | C17: % | D17: 0.3 | E17: 0.4 | F17: 0.5 | G17: =INDEX(D17:F17,1,Assumptions!$D$4) -> 0.4 | H17: D | I17: Clay-run outbound (Clay's own product); rotating coverage
A18: A8 | B18: Outbound meeting rate per account sequenced | C18: % | D18: 0.02 | E18: 0.03 | F18: 0.045 | G18: =INDEX(D18:F18,1,Assumptions!$D$4) -> 0.03 | H18: D | I18: Typical cold outbound meeting rates 1–5% [K]; 'lead lists/email' MQL→SQL are among the weakest sources (S49)
A19: A9 | B19: Inbound / template-led leads per quarter (% of active SAM) | C19: % | D19: 0.005 | E19: 0.01 | F19: 0.015 | G19: =INDEX(D19:F19,1,Assumptions!$D$4) -> 0.01 | H19: D | I19: Templates, trade associations, events, Clay community
A20: A10 | B20: Partners active at launch | C20: # | D20: 1 | E20: 2 | F20: 3 | G20: =INDEX(D20:F20,1,Assumptions!$D$4) -> 2 | H20: D | I20: No distribution-focused Clay partners visible today (S35) → recruitment is a pilot task
A21: A11 | B21: Partners added per quarter | C21: # | D21: 1 | E21: 1 | F21: 2 | G21: =INDEX(D21:F21,1,Assumptions!$D$4) -> 1 | H21: D
A22: A12 | B22: Partner network cap | C22: # | D22: 5 | E22: 10 | F22: 15 | G22: =INDEX(D22:F22,1,Assumptions!$D$4) -> 10 | H22: D
A23: A13 | B23: Leads per active partner per quarter | C23: # | D23: 2 | E23: 3 | F23: 4 | G23: =INDEX(D23:F23,1,Assumptions!$D$4) -> 3 | H23: D | I23: Warm introductions from implementers / distribution consultancies
A24: A14 | B24: Qualification rate — outbound & inbound leads → SQL | C24: % | D24: 0.35 | E24: 0.45 | F24: 0.55 | G24: =INDEX(D24:F24,1,Assumptions!$D$4) -> 0.45 | H24: B | I24: Norwest 2025 ~36% MQL→SQL; SMB/MM average 39% (S48, S49)
A25: A15 | B25: Qualification rate — partner leads → SQL | C25: % | D25: 0.5 | E25: 0.6 | F25: 0.7 | G25: =INDEX(D25:F25,1,Assumptions!$D$4) -> 0.6 | H25: D | I25: Warm, pre-vetted introductions
A26: A16 | B26: SQL → opportunity conversion | C26: % | D26: 0.35 | E26: 0.45 | F26: 0.55 | G26: =INDEX(D26:F26,1,Assumptions!$D$4) -> 0.45 | H26: B | I26: SMB/MM average 42% (S49)
A27: A17 | B27: Win rate (opportunity → closed-won) | C27: % | D27: 0.2 | E27: 0.28 | F27: 0.35 | G27: =INDEX(D27:F27,1,Assumptions!$D$4) -> 0.28 | H27: B | I27: HubSpot 2024 average 21%; opportunity→won 31–39% (S48, S49); ICP-matched deals win ~3.1× more (Ebsta, S48)
A28: A18 | B28: Sales cycle: quarters from opportunity to close (1 or 2) | C28: qtrs | D28: 2 | E28: 1 | F28: 1 | G28: =INDEX(D28:F28,1,Assumptions!$D$4) -> 1 | H28: B | I28: Deals < $25K: 2–3 months (Norwest 2025, S48)
A29: A19 | B29: Win mix — SMB (20–99 employees) | C29: % | D29: 0.5 | E29: 0.5 | F29: 0.5 | G29: =INDEX(D29:F29,1,Assumptions!$D$4) -> 0.5 | H29: E | I29: ICP prioritizes 100+ employee distributors where ACV is above the Growth floor (ACV Build)
A30: A20 | B30: Win mix — Mid-Market (100–499) | C30: % | D30: 0.38 | E30: 0.38 | F30: 0.38 | G30: =INDEX(D30:F30,1,Assumptions!$D$4) -> 0.38 | H30: E
A31: A21 | B31: Win mix — Enterprise (500+) | C31: % | D31: 0.12 | E31: 0.12 | F31: 0.12 | G31: =INDEX(D31:F31,1,Assumptions!$D$4) -> 0.12 | H31: E
A32: A22 | B32: Self-serve share of SMB wins (templates; no AE) | C32: % | D32: 0.15 | E32: 0.3 | F32: 0.4 | G32: =INDEX(D32:F32,1,Assumptions!$D$4) -> 0.3 | H32: D | I32: Low builder capacity limits self-serve (H4); templates raise it
A34: ACV BUILD (usage-based pricing)
A35: A23 | B35: Sales occupations share of employment (distribution) | C35: % | D35: 0.22 | E35: 0.22 | F35: 0.22 | G35: =INDEX(D35:F35,1,Assumptions!$D$4) -> 0.22 | H35: C | I35: OEWS May 2025 (S15) via 02_Market_Sizing Segment_Profile
A36: A24 | B36: Accounts tracked per seller | C36: # | D36: 150 | E36: 150 | F36: 150 | G36: =INDEX(D36:F36,1,Assumptions!$D$4) -> 150 | H36: D | I36: Territory book of business; outside reps cover contractor and plant accounts
A37: A25 | B37: Usage intensity factor (multiplies accounts tracked) | C37: x | D37: 0.75 | E37: 1 | F37: 1.5 | G37: =INDEX(D37:F37,1,Assumptions!$D$4) -> 1 | H37: D | I37: Range for workflow depth (signals, research, sourcing)
A38: A26 | B38: Contacts per account | C38: # | D38: 2 | E38: 2 | F38: 2 | G38: =INDEX(D38:F38,1,Assumptions!$D$4) -> 2 | H38: D
A39: A27 | B39: Contact refreshes per year | C39: # | D39: 2 | E39: 2 | F39: 2 | G39: =INDEX(D39:F39,1,Assumptions!$D$4) -> 2 | H39: D
A40: A28 | B40: Data credits per contact refresh (email + phone waterfall) | C40: credits | D40: 6 | E40: 6 | F40: 6 | G40: =INDEX(D40:F40,1,Assumptions!$D$4) -> 6 | H40: B/D | I40: Third-party: email lookups 1–5 credits per record depending on provider (S51)
A41: A29 | B41: AI research credits per account per year | C41: credits | D41: 4 | E41: 4 | F41: 4 | G41: =INDEX(D41:F41,1,Assumptions!$D$4) -> 4 | H41: D | I41: Fixed-price Claygent models (S01)
A42: A30 | B42: New accounts sourced per year (% of tracked) | C42: % | D42: 0.25 | E42: 0.25 | F42: 0.25 | G42: =INDEX(D42:F42,1,Assumptions!$D$4) -> 0.25 | H42: D | I42: Google Maps / permits sourcing of new contractors (S37, S26)
A43: A31 | B43: Data credits per new account sourced | C43: credits | D43: 8 | E43: 8 | F43: 8 | G43: =INDEX(D43:F43,1,Assumptions!$D$4) -> 8 | H43: D
A44: A32 | B44: Actions per row operation | C44: actions | D44: 6 | E44: 6 | F44: 6 | G44: =INDEX(D44:F44,1,Assumptions!$D$4) -> 6 | H44: D | I44: Actions 'cost less than a cent each' (S01)
A45: A33 | B45: Data-credit pack price ($/month, Growth 72K credits/yr) | C45: $/mo | D45: 261 | E45: 261 | F45: 261 | G45: =INDEX(D45:F45,1,Assumptions!$D$4) -> 261 | H45: A | I45: Clay pricing page (S01)
A46: A34 | B46: Data-credit pack size (credits/yr) | C46: credits | D46: 72000 | E46: 72000 | F46: 72000 | G46: =INDEX(D46:F46,1,Assumptions!$D$4) -> 72000 | H46: A | I46: S01
A47: A35 | B47: Actions pack price ($/month, Growth 480K actions/yr) | C47: $/mo | D47: 185 | E47: 185 | F47: 185 | G47: =INDEX(D47:F47,1,Assumptions!$D$4) -> 185 | H47: A | I47: S01
A48: A36 | B48: Actions pack size (actions/yr) | C48: actions | D48: 480000 | E48: 480000 | F48: 480000 | G48: =INDEX(D48:F48,1,Assumptions!$D$4) -> 480000 | H48: A | I48: S01
A49: A37 | B49: Enterprise minimum data credits per year | C49: credits | D49: 1200000 | E49: 1200000 | F49: 1200000 | G49: =INDEX(D49:F49,1,Assumptions!$D$4) -> 1200000 | H49: A | I49: Enterprise includes 100,000+ data credits per month (S01 FAQ)
A50: A38 | B50: Enterprise minimum actions per year | C50: actions | D50: 2400000 | E50: 2400000 | F50: 2400000 | G50: =INDEX(D50:F50,1,Assumptions!$D$4) -> 2400000 | H50: A | I50: Enterprise includes 200,000+ actions per month (S01 FAQ)
A51: A39 | B51: Enterprise discount vs list | C51: % | D51: 0.3 | E51: 0.3 | F51: 0.3 | G51: =INDEX(D51:F51,1,Assumptions!$D$4) -> 0.3 | H51: B | I51: Vendr: Enterprise 25–35% below initial quotes (S16)
A53: RETENTION & EXPANSION (annual)
A54: A40 | B54: Gross revenue retention — SMB | C54: % | D54: 0.85 | E54: 0.88 | F54: 0.91 | G54: =INDEX(D54:F54,1,Assumptions!$D$4) -> 0.88 | H54: B | I54: SaaS Capital 2025 median GRR 90% for ACV < $12K (S43); low builder capacity → base below median
A55: A41 | B55: Gross revenue retention — Mid-Market | C55: % | D55: 0.86 | E55: 0.9 | F55: 0.93 | G55: =INDEX(D55:F55,1,Assumptions!$D$4) -> 0.9 | H55: B | I55: SaaS Capital: 91% ($12–25K) (S43)
A56: A42 | B56: Gross revenue retention — Enterprise | C56: % | D56: 0.88 | E56: 0.92 | F56: 0.95 | G56: =INDEX(D56:F56,1,Assumptions!$D$4) -> 0.92 | H56: B | I56: SaaS Capital: 90–91% ($50–250K), 95% (> $250K) (S43)
A57: A43 | B57: Net revenue retention — SMB | C57: % | D57: 0.92 | E57: 1 | F57: 1.06 | G57: =INDEX(D57:F57,1,Assumptions!$D$4) -> 1 | H57: B | I57: SaaS Capital median NRR 98% (< $12K) (S43)
A58: A44 | B58: Net revenue retention — Mid-Market | C58: % | D58: 0.98 | E58: 1.06 | F58: 1.15 | G58: =INDEX(D58:F58,1,Assumptions!$D$4) -> 1.06 | H58: B | I58: SaaS Capital 103% ($12–25K) (S43)
A59: A45 | B59: Net revenue retention — Enterprise | C59: % | D59: 1.05 | E59: 1.15 | F59: 1.3 | G59: =INDEX(D59:F59,1,Assumptions!$D$4) -> 1.15 | H59: B | I59: SaaS Capital 104% ($50–100K); Clay reports enterprise NRR > 200% overall (S02), not assumed for this segment
A61: SALES CAPACITY & COST RATES
A62: A46 | B62: AE annual quota (new ARR) | C62: $ | D62: 875000 | E62: 875000 | F62: 875000 | G62: =INDEX(D62:F62,1,Assumptions!$D$4) -> 875000 | H62: B | I62: Bridge Group 2026: SaaS median quota $875K (n=158) (S44)
A63: A47 | B63: AE productivity (average attainment of quota) | C63: % | D63: 0.55 | E63: 0.7 | F63: 0.85 | G63: =INDEX(D63:F63,1,Assumptions!$D$4) -> 0.7 | H63: B | I63: Bridge Group 2026: 48% of reps at quota (S44)
A64: A48 | B64: AE on-target earnings (cash) | C64: $ | D64: 200000 | E64: 200000 | F64: 200000 | G64: =INDEX(D64:F64,1,Assumptions!$D$4) -> 200000 | H64: B | I64: Bridge Group 2026 median OTE $200K (S44)
A65: A49 | B65: Wages as share of total compensation (loading) | C65: % | D65: 0.7 | E65: 0.7 | F65: 0.7 | G65: =INDEX(D65:F65,1,Assumptions!$D$4) -> 0.7 | H65: A | I65: BLS ECEC, private industry, June 2026: wages 70.0% (S45)
A66: A50 | B66: Sales manager wage (vertical lead, partner manager) | C66: $ | D66: 186910 | E66: 186910 | F66: 186910 | G66: =INDEX(D66:F66,1,Assumptions!$D$4) -> 186910 | H66: A | I66: OEWS May 2025, software publishers 11-2022 mean (S46)
A67: A51 | B67: Marketing manager wage (product marketing) | C67: $ | D67: 206930 | E67: 206930 | F67: 206930 | G67: =INDEX(D67:F67,1,Assumptions!$D$4) -> 206930 | H67: A | I67: OEWS May 2025, software publishers 11-2021 mean (S46)
A68: A52 | B68: Software developer wage (GTM / solutions engineer) | C68: $ | D68: 158300 | E68: 158300 | F68: 158300 | G68: =INDEX(D68:F68,1,Assumptions!$D$4) -> 158300 | H68: A | I68: OEWS May 2025, software publishers 15-1252 mean (S46)
A69: A53 | B69: Business operations specialist wage (customer success) | C69: $ | D69: 112510 | E69: 112510 | F69: 112510 | G69: =INDEX(D69:F69,1,Assumptions!$D$4) -> 112510 | H69: A | I69: OEWS May 2025, software publishers 13-1199 mean (S46)
A70: A54 | B70: Mid-Market + Enterprise accounts per CSM | C70: # | D70: 40 | E70: 40 | F70: 40 | G70: =INDEX(D70:F70,1,Assumptions!$D$4) -> 40 | H70: D
A71: A55 | B71: SMB accounts per CSM (pooled / digital) | C71: # | D71: 250 | E71: 250 | F71: 250 | G71: =INDEX(D71:F71,1,Assumptions!$D$4) -> 250 | H71: D
A72: A56 | B72: Gross margin on Clay revenue (data pass-through, AI, hosting) | C72: % | D72: 0.55 | E72: 0.65 | F72: 0.72 | G72: =INDEX(D72:F72,1,Assumptions!$D$4) -> 0.65 | H72: D | I72: Sacra: Clay margins resemble data-heavy SaaS, below 80%+ pure software (S52); no reported figure
A73: A57 | B73: Launch marketing spend per wave | C73: $ | D73: 40000 | E73: 40000 | F73: 40000 | G73: =INDEX(D73:F73,1,Assumptions!$D$4) -> 40000 | H73: D | I73: Trade shows, content, association sponsorships
A74: A58 | B74: Partner fee on partner-sourced first-year ACV | C74: % | D74: 0.25 | E74: 0.2 | F74: 0.15 | G74: =INDEX(D74:F74,1,Assumptions!$D$4) -> 0.2 | H74: B | I74: Referral 10–15%; VAR 20–30% (Freshworks, Bessemer via S50)
A75: A59 | B75: Partner enablement per active partner per quarter | C75: $ | D75: 2000 | E75: 2000 | F75: 2000 | G75: =INDEX(D75:F75,1,Assumptions!$D$4) -> 2000 | H75: D | I75: Training, certification, co-marketing
A76: A60 | B76: Onboarding / co-build subsidy, Mid-Market & Enterprise (% of first-year ACV) | C76: % | D76: 0.2 | E76: 0.15 | F76: 0.1 | G76: =INDEX(D76:F76,1,Assumptions!$D$4) -> 0.15 | H76: B | I76: Bessemer: budget 10–20% of purchase price for partner-delivered services (S50)
A77: A61 | B77: Template & ERP-connector build (one-time) | C77: $ | D77: 250000 | E77: 250000 | F77: 250000 | G77: =INDEX(D77:F77,1,Assumptions!$D$4) -> 250000 | H77: D | I77: Distribution templates (contractor sourcing, branch scoring, e-commerce vetting) + ERP connector gap (05 §3)
A78: A62 | B78: Quarters over which build is spent | C78: qtrs | D78: 4 | E78: 4 | F78: 4 | G78: =INDEX(D78:F78,1,Assumptions!$D$4) -> 4 | H78: D
A79: A63 | B79: Program stop quarter (99 = runs all 12 quarters; used for gated cases) | C79: quarter | D79: 99 | E79: 99 | F79: 99 | G79: =INDEX(D79:F79,1,Assumptions!$D$4) -> 99 | H79: D | I79: Scenarios tab overrides to 4 for 'Downside, stopped at Q4 2027 gate'
A80: A64 | B80: Embedded-value horizon after 2029 (years) | C80: yrs | D80: 5 | E80: 5 | F80: 5 | G80: =INDEX(D80:F80,1,Assumptions!$D$4) -> 5 | H80: D | I80: Gross profit of the 2029 customer base over 5 more years, decaying at GRR, net of CS cost
A82: DECISION ANALYSIS
A83: A65 | B83: Probability weight — Downside | C83: % | D83: 0.35 | E83: 0.35 | F83: 0.35 | G83: =INDEX(D83:F83,1,Assumptions!$D$4) -> 0.35 | H83: D | I83: Judgment; break-even probability shown on Scenarios
A84: A66 | B84: Probability weight — Base | C84: % | D84: 0.45 | E84: 0.45 | F84: 0.45 | G84: =INDEX(D84:F84,1,Assumptions!$D$4) -> 0.45 | H84: D
A85: A67 | B85: Probability weight — Upside | C85: % | D85: 0.2 | E85: 0.2 | F85: 0.2 | G85: =INDEX(D85:F85,1,Assumptions!$D$4) -> 0.2 | H85: D
A87: Check: win mix sums to 100% (each scenario) | D87: =D29+D30+D31 -> 1 | E87: =E29+E30+E31 -> 1 | F87: =F29+F30+F31 -> 1
A88: Check: probabilities sum to 100% | E88: =E83+E84+E85 -> 1
A90: MOTION DESIGN (team and cost structure)
A91: ID | B91: Input | C91: Unit | D91: Partner-led pilot | E91: Sales-led team | G91: Live | H91: Class | I91: Rationale
A92: M1 | B92: Vertical lead (player-coach; owns partners in year 1) | C92: FTE | D92: 1 | E92: 1 | G92: =INDEX(D92:E92,1,Assumptions!$D$5) -> 1 | H92: D | I92: Single owner for the vertical P&L
A93: M2 | B93: Partner managers — 2027 | C93: FTE | D93: 0 | E93: 1 | G93: =INDEX(D93:E93,1,Assumptions!$D$5) -> 0 | H93: D | I93: Partner-led: vertical lead covers partners in year 1
A94: M3 | B94: Partner managers — 2028 onward | C94: FTE | D94: 0.5 | E94: 1 | G94: =INDEX(D94:E94,1,Assumptions!$D$5) -> 0.5 | H94: D
A95: M4 | B95: GTM / solutions engineers — 2027 | C95: FTE | D95: 1 | E95: 1 | G95: =INDEX(D95:E95,1,Assumptions!$D$5) -> 1 | H95: D | I95: Builds templates and connector; pilot support
A96: M5 | B96: GTM / solutions engineers — 2028 onward | C96: FTE | D96: 0.5 | E96: 0.5 | G96: =INDEX(D96:E96,1,Assumptions!$D$5) -> 0.5 | H96: D
A97: M6 | B97: Product marketing | C97: FTE | D97: 0.25 | E97: 0.5 | G97: =INDEX(D97:E97,1,Assumptions!$D$5) -> 0.25 | H97: D
A98: M7 | B98: Program marketing per quarter | C98: $ | D98: 25000 | E98: 60000 | G98: =INDEX(D98:E98,1,Assumptions!$D$5) -> 25000 | H98: D | I98: Events, content, paid; sales-led needs more top-of-funnel
A99: M8 | B99: Shared AE capacity borrowed from Clay's existing commercial team | C99: AE-eq. | D99: 2 | E99: 0 | G99: =INDEX(D99:E99,1,Assumptions!$D$5) -> 2 | H99: D | I99: Partner-led closes deals with existing AEs, paying a variable cost per deal
A100: M9 | B100: Charge variable AE cost per deal closed with shared capacity (1 = yes) | C100: flag | D100: 1 | E100: 0 | G100: =INDEX(D100:E100,1,Assumptions!$D$5) -> 1 | H100: D
A102: Dedicated AE headcount by quarter (FTE, end of quarter)
D103: Q1 2027 | E103: Q2 2027 | F103: Q3 2027 | G103: Q4 2027 | H103: Q1 2028 | I103: Q2 2028 | J103: Q3 2028 | K103: Q4 2028 | L103: Q1 2029 | M103: Q2 2029 | N103: Q3 2029 | O103: Q4 2029
B104: Partner-led pilot | D104: 0 | E104: 0 | F104: 0 | G104: 0 | H104: 0 | I104: 0 | J104: 0 | K104: 0 | L104: 0 | M104: 0 | N104: 0 | O104: 0
B105: Sales-led team | D105: 2 | E105: 2 | F105: 3 | G105: 3 | H105: 4 | I105: 4 | J105: 5 | K105: 5 | L105: 6 | M105: 6 | N105: 6 | O105: 6
B106: Live | D106: =INDEX(D104:D105,Assumptions!$D$5,1) -> 0 | E106: =INDEX(E104:E105,Assumptions!$D$5,1) -> 0 | F106: =INDEX(F104:F105,Assumptions!$D$5,1) -> 0 | G106: =INDEX(G104:G105,Assumptions!$D$5,1) -> 0 | H106: =INDEX(H104:H105,Assumptions!$D$5,1) -> 0 | I106: =INDEX(I104:I105,Assumptions!$D$5,1) -> 0 | J106: =INDEX(J104:J105,Assumptions!$D$5,1) -> 0 | K106: =INDEX(K104:K105,Assumptions!$D$5,1) -> 0 | ... O106: =INDEX(O104:O105,Assumptions!$D$5,1) -> 0
B107: Partner-led + scale-up hires (used only in the Upside scale-up run) | D107: 0 | E107: 0 | F107: 0 | G107: 0 | H107: 1 | I107: 2 | J107: 2 | K107: 2 | L107: 2 | M107: 2 | N107: 2 | O107: 2
B108: Trigger: in Upside, shared AE capacity binds from Q3 2028 (see 'Wins lost to capacity'); two dedicated AEs hired in Q1–Q2 2028 after the gate clear it.
A110: COMPUTED FROM ACV BUILD (do not edit)
B111: First-year ACV — SMB | C111: $ | D111: ='ACV Build'!D40 -> 5352 | E111: ='ACV Build'!E40 -> 5352 | F111: ='ACV Build'!F40 -> 5352 | G111: =INDEX(D111:F111,1,Assumptions!$D$4) -> 5352 | H111: C | I111: Usage-based build on 'ACV Build' tab
...

Sheet Market Sizing
A1: Market Sizing — the addressable opportunity for the distribution pilot
A2: Unique firms with 20+ employees, 2022 Economic Census (S14). Wave 1 = electrical (4236), wave 2 = PHVAC (4237), wave 3 = machinery/MRO (4238). Metals (4235) excluded per Phase 3.
A4: NAICS | B4: Sub-industry | C4: Firms 20–49 | D4: Firms 50–99 | E4: Firms 100–249 | F4: Firms 250–499 | G4: Firms 500+ | H4: Emp. 20–49 | I4: Emp. 50–99 | J4: Emp. 100–249 | K4: Emp. 250–499 | L4: Emp. 500+
A5: 4236 | B5: Electrical & electronic goods (wave 1) | C5: 1408 | D5: 570 | E5: 350 | F5: 136 | G5: 114 | H5: 42698 | I5: 39297 | J5: 54183 | K5: 47492 | L5: 315093
A6: 4237 | B6: Hardware, plumbing & HVAC (wave 2) | C6: 1013 | D6: 424 | E6: 242 | F6: 85 | G6: 57 | H6: 31260 | I6: 29270 | J6: 36995 | K6: 29008 | L6: 116895
A7: 4238 | B7: Machinery, equipment & supplies (wave 3) | C7: 3622 | D7: 1218 | E7: 746 | F7: 240 | G7: 183 | H7: 110129 | I7: 83565 | J7: 115979 | K7: 83365 | L7: 220621
A9: De-duplication factor for 20–49 band (sector 423) | C9: 0.973 | D9: 02_Market_Sizing › Firm_Counts Block 3 (larger bands: no measurable overlap)
A11: Wave | B11: Sub-industry | C11: SMB 20–99 | D11: Mid-Market 100–499 | E11: Enterprise 500+ | F11: Firms 20+ total | G11: SAM firms (Live) | H11: SAM share
A12: W1 | B12: =B5 -> Electrical & electronic goods (wave 1) | C12: =C5*$C$9+D5 -> 1939.984 | D12: =E5+F5 -> 486 | E12: =G5 -> 114 | F12: =SUM(C12:E12) -> 2539.984 | G12: =F12*Assumptions!$G$9*Assumptions!$G$10*(1-Assumptions!$G$11) -> 1281.1679 | H12: =G12/F12 -> 0.5044
A13: W2 | B13: =B6 -> Hardware, plumbing & HVAC (wave 2) | C13: =C6*$C$9+D6 -> 1409.649 | D13: =E6+F6 -> 327 | E13: =G6 -> 57 | F13: =SUM(C13:E13) -> 1793.649 | G13: =F13*Assumptions!$G$9*Assumptions!$G$10*(1-Assumptions!$G$11) -> 904.71656 | H13: =G13/F13 -> 0.5044
A14: W3 | B14: =B7 -> Machinery, equipment & supplies (wave 3) | C14: =C7*$C$9+D7 -> 4742.206 | D14: =E7+F7 -> 986 | E14: =G7 -> 183 | F14: =SUM(C14:E14) -> 5911.206 | G14: =F14*Assumptions!$G$9*Assumptions!$G$10*(1-Assumptions!$G$11) -> 2981.6123 | H14: =G14/F14 -> 0.5044
A15: Total | C15: =SUM(C12:C14) -> 8091.839 | D15: =SUM(D12:D14) -> 1799 | E15: =SUM(E12:E14) -> 354 | F15: =SUM(F12:F14) -> 10244.839 | G15: =SUM(G12:G14) -> 5167.4968 | H15: =G15/F15 -> 0.5044
A17: Band | C17: Firms (3 waves) | D17: Employees | E17: Avg employees per firm
A18: SMB 20–99 | C18: =SUM(C5:C7)+SUM(D5:D7) -> 8255 | D18: =SUM(H5:H7)+SUM(I5:I7) -> 336219 | E18: =D18/C18 -> 40.729134
A19: Mid-Market 100–499 | C19: =SUM(E5:E7)+SUM(F5:F7) -> 1799 | D19: =SUM(J5:J7)+SUM(K5:K7) -> 367022 | E19: =D19/C19 -> 204.01445
A20: Enterprise 500+ | C20: =SUM(G5:G7) -> 354 | D20: =SUM(L5:L7) -> 652609 | E20: =D20/C20 -> 1843.5282
A22: Average employees per firm feed the ACV Build (sellers per firm = employees × sales share). The 20–49 band is not de-duplicated here because this is an average, not a count.
A24: Reconciliation to Phase 1 | C24: Phase 1 (02) | D24: Phase 4 (this model) | E24: Difference / reason
A25: Distribution SAM firms | C25: 5976.6 | D25: =G15 -> 5167.4968 | E25: Phase 4 excludes 4235 metals (Phase 3) and Clay's existing customers
A26: Base ACV — SMB | C26: 7500 | D26: =Assumptions!$E$111 -> 5352 | E26: Usage build: SMB usage sits below the Growth floor, so ACV = $5,352 list
A27: Base ACV — Mid-Market | C27: 20000 | D27: =Assumptions!$E$112 -> 9766.7201 | E27: Usage build: ~45 sellers × 150 accounts → ~$9.8K at list
A28: Base ACV — Enterprise | C28: 60000 | D28: =Assumptions!$E$113 -> 61778.256 | E28: Usage build after 30% discount ≈ Vendr median ($59,996)
A29: Year-3 ARR (Base, Phase 1 SOM vs Phase 4 exit ARR) | C29: 1864124 | D29: =Scenarios!$F$5 -> 861203.84 | E29: Funnel- and wave-based build with lower SMB/MM ACV

Sheet ACV Build
A1: ACV Build — what would a distributor actually spend on Clay?
A2: Bottom-up from sellers per firm × accounts tracked × Clay's usage meters (Data Credits and Actions) at published Growth-tier rates. SMB and Mid-Market are floored at the Growth plan (CRM sync requires Growth). Enterprise is floored at the Enterprise minimum, less discount.
A4: Step | B4: Formula | D4: Downside | E4: Base | F4: Upside | G4: Live
A5: Unit prices (from published plans)
A6: Price per data credit | D6: =Assumptions!$D$45*12/Assumptions!$D$46 -> 0.0435 | E6: =Assumptions!$E$45*12/Assumptions!$E$46 -> 0.0435 | F6: =Assumptions!$F$45*12/Assumptions!$F$46 -> 0.0435 | G6: =Assumptions!$G$45*12/Assumptions!$G$46 -> 0.0435
A7: Price per action | D7: =Assumptions!$D$47*12/Assumptions!$D$48 -> 0.004625 | E7: =Assumptions!$E$47*12/Assumptions!$E$48 -> 0.004625 | F7: =Assumptions!$F$47*12/Assumptions!$F$48 -> 0.004625 | G7: =Assumptions!$G$47*12/Assumptions!$G$48 -> 0.004625
A8: Growth plan floor (annual) | D8: =(Assumptions!$D$45+Assumptions!$D$47)*12 -> 5352 | E8: =(Assumptions!$E$45+Assumptions!$E$47)*12 -> 5352 | F8: =(Assumptions!$F$45+Assumptions!$F$47)*12 -> 5352 | G8: =(Assumptions!$G$45+Assumptions!$G$47)*12 -> 5352
A9: Enterprise minimum at list (annual) | D9: =Assumptions!$D$49*Assumptions!$D$45*12/Assumptions!$D$46+Assumptions!$D$50*Assumptions!$D$47*12/Assumptions!$D$48 -> 63300 | E9: =Assumptions!$E$49*Assumptions!$E$45*12/Assumptions!$E$46+Assumptions!$E$50*Assumptions!$E$47*12/Assumptions!$E$48 -> 63300 | F9: =Assumptions!$F$49*Assumptions!$F$45*12/Assumptions!$F$46+Assumptions!$F$50*Assumptions!$F$47*12/Assumptions!$F$48 -> 63300 | G9: =Assumptions!$G$49*Assumptions!$G$45*12/Assumptions!$G$46+Assumptions!$G$50*Assumptions!$G$47*12/Assumptions!$G$48 -> 63300
A11: SMB (20–99)
A12: Avg employees per firm | B12: Market Sizing | D12: ='Market Sizing'!$E$18 -> 40.729134 | E12: ='Market Sizing'!$E$18 -> 40.729134 | F12: ='Market Sizing'!$E$18 -> 40.729134 | G12: ='Market Sizing'!$E$18 -> 40.729134
A13: Sellers per firm | B13: employees × sales share | D13: =D12*Assumptions!$D$35 -> 8.9604094 | E13: =E12*Assumptions!$E$35 -> 8.9604094 | F13: =F12*Assumptions!$F$35 -> 8.9604094 | G13: =G12*Assumptions!$G$35 -> 8.9604094
A14: Accounts tracked | B14: sellers × accounts/seller × usage factor | D14: =D13*Assumptions!$D$36*Assumptions!$D$37 -> 1008.0461 | E14: =E13*Assumptions!$E$36*Assumptions!$E$37 -> 1344.0614 | F14: =F13*Assumptions!$F$36*Assumptions!$F$37 -> 2016.0921 | G14: =G13*Assumptions!$G$36*Assumptions!$G$37 -> 1344.0614
A15: Contacts tracked | B15: accounts × contacts/account | D15: =D14*Assumptions!$D$38 -> 2016.0921 | E15: =E14*Assumptions!$E$38 -> 2688.1228 | F15: =F14*Assumptions!$F$38 -> 4032.1843 | G15: =G14*Assumptions!$G$38 -> 2688.1228
A16: Data credits per year | B16: refreshes + AI research + new-account sourcing | D16: =D15*Assumptions!$D$39*Assumptions!$D$40+D14*Assumptions!$D$41+D14*Assumptions!$D$42*Assumptions!$D$43 -> 30241.382 | E16: =E15*Assumptions!$E$39*Assumptions!$E$40+E14*Assumptions!$E$41+E14*Assumptions!$E$42*Assumptions!$E$43 -> 40321.843 | F16: =F15*Assumptions!$F$39*Assumptions!$F$40+F14*Assumptions!$F$41+F14*Assumptions!$F$42*Assumptions!$F$43 -> 60482.764 | G16: =G15*Assumptions!$G$39*Assumptions!$G$40+G14*Assumptions!$G$41+G14*Assumptions!$G$42*Assumptions!$G$43 -> 40321.843
A17: Actions per year | B17: row operations × actions/op | D17: =(D15*Assumptions!$D$39+D14+D14*Assumptions!$D$42)*Assumptions!$D$44 -> 31753.451 | E17: =(E15*Assumptions!$E$39+E14+E14*Assumptions!$E$42)*Assumptions!$E$44 -> 42337.935 | F17: =(F15*Assumptions!$F$39+F14+F14*Assumptions!$F$42)*Assumptions!$F$44 -> 63506.902 | G17: =(G15*Assumptions!$G$39+G14+G14*Assumptions!$G$42)*Assumptions!$G$44 -> 42337.935
A18: Usage cost at list | B18: credits × price + actions × price | D18: =D16*Assumptions!$D$45*12/Assumptions!$D$46+D17*Assumptions!$D$47*12/Assumptions!$D$48 -> 1462.3598 | E18: =E16*Assumptions!$E$45*12/Assumptions!$E$46+E17*Assumptions!$E$47*12/Assumptions!$E$48 -> 1949.8131 | F18: =F16*Assumptions!$F$45*12/Assumptions!$F$46+F17*Assumptions!$F$47*12/Assumptions!$F$48 -> 2924.7196 | G18: =G16*Assumptions!$G$45*12/Assumptions!$G$46+G17*Assumptions!$G$47*12/Assumptions!$G$48 -> 1949.8131
A20: Mid-Market (100–499)
A21: Avg employees per firm | B21: Market Sizing | D21: ='Market Sizing'!$E$19 -> 204.01445 | E21: ='Market Sizing'!$E$19 -> 204.01445 | F21: ='Market Sizing'!$E$19 -> 204.01445 | G21: ='Market Sizing'!$E$19 -> 204.01445
A22: Sellers per firm | B22: employees × sales share | D22: =D21*Assumptions!$D$35 -> 44.88318 | E22: =E21*Assumptions!$E$35 -> 44.88318 | F22: =F21*Assumptions!$F$35 -> 44.88318 | G22: =G21*Assumptions!$G$35 -> 44.88318
A23: Accounts tracked | B23: sellers × accounts/seller × usage factor | D23: =D22*Assumptions!$D$36*Assumptions!$D$37 -> 5049.3577 | E23: =E22*Assumptions!$E$36*Assumptions!$E$37 -> 6732.4769 | F23: =F22*Assumptions!$F$36*Assumptions!$F$37 -> 10098.715 | G23: =G22*Assumptions!$G$36*Assumptions!$G$37 -> 6732.4769
A24: Contacts tracked | B24: accounts × contacts/account | D24: =D23*Assumptions!$D$38 -> 10098.715 | E24: =E23*Assumptions!$E$38 -> 13464.954 | F24: =F23*Assumptions!$F$38 -> 20197.431 | G24: =G23*Assumptions!$G$38 -> 13464.954
A25: Data credits per year | B25: refreshes + AI research + new-account sourcing | D25: =D24*Assumptions!$D$39*Assumptions!$D$40+D23*Assumptions!$D$41+D23*Assumptions!$D$42*Assumptions!$D$43 -> 151480.73 | E25: =E24*Assumptions!$E$39*Assumptions!$E$40+E23*Assumptions!$E$41+E23*Assumptions!$E$42*Assumptions!$E$43 -> 201974.31 | F25: =F24*Assumptions!$F$39*Assumptions!$F$40+F23*Assumptions!$F$41+F23*Assumptions!$F$42*Assumptions!$F$43 -> 302961.46 | G25: =G24*Assumptions!$G$39*Assumptions!$G$40+G23*Assumptions!$G$41+G23*Assumptions!$G$42*Assumptions!$G$43 -> 201974.31
A26: Actions per year | B26: row operations × actions/op | D26: =(D24*Assumptions!$D$39+D23+D23*Assumptions!$D$42)*Assumptions!$D$44 -> 159054.77 | E26: =(E24*Assumptions!$E$39+E23+E23*Assumptions!$E$42)*Assumptions!$E$44 -> 212073.02 | F26: =(F24*Assumptions!$F$39+F23+F23*Assumptions!$F$42)*Assumptions!$F$44 -> 318109.54 | G26: =(G24*Assumptions!$G$39+G23+G23*Assumptions!$G$42)*Assumptions!$G$44 -> 212073.02
A27: Usage cost at list | B27: credits × price + actions × price | D27: =D25*Assumptions!$D$45*12/Assumptions!$D$46+D26*Assumptions!$D$47*12/Assumptions!$D$48 -> 7325.0401 | E27: =E25*Assumptions!$E$45*12/Assumptions!$E$46+E26*Assumptions!$E$47*12/Assumptions!$E$48 -> 9766.7201 | F27: =F25*Assumptions!$F$45*12/Assumptions!$F$46+F26*Assumptions!$F$47*12/Assumptions!$F$48 -> 14650.08 | G27: =G25*Assumptions!$G$45*12/Assumptions!$G$46+G26*Assumptions!$G$47*12/Assumptions!$G$48 -> 9766.7201
A29: Enterprise (500+)
A30: Avg employees per firm | B30: Market Sizing | D30: ='Market Sizing'!$E$20 -> 1843.5282 | E30: ='Market Sizing'!$E$20 -> 1843.5282 | F30: ='Market Sizing'!$E$20 -> 1843.5282 | G30: ='Market Sizing'!$E$20 -> 1843.5282
A31: Sellers per firm | B31: employees × sales share | D31: =D30*Assumptions!$D$35 -> 405.57621 | E31: =E30*Assumptions!$E$35 -> 405.57621 | F31: =F30*Assumptions!$F$35 -> 405.57621 | G31: =G30*Assumptions!$G$35 -> 405.57621
A32: Accounts tracked | B32: sellers × accounts/seller × usage factor | D32: =D31*Assumptions!$D$36*Assumptions!$D$37 -> 45627.324 | E32: =E31*Assumptions!$E$36*Assumptions!$E$37 -> 60836.432 | F32: =F31*Assumptions!$F$36*Assumptions!$F$37 -> 91254.648 | G32: =G31*Assumptions!$G$36*Assumptions!$G$37 -> 60836.432
A33: Contacts tracked | B33: accounts × contacts/account | D33: =D32*Assumptions!$D$38 -> 91254.648 | E33: =E32*Assumptions!$E$38 -> 121672.86 | F33: =F32*Assumptions!$F$38 -> 182509.3 | G33: =G32*Assumptions!$G$38 -> 121672.86
A34: Data credits per year | B34: refreshes + AI research + new-account sourcing | D34: =D33*Assumptions!$D$39*Assumptions!$D$40+D32*Assumptions!$D$41+D32*Assumptions!$D$42*Assumptions!$D$43 -> 1368819.7 | E34: =E33*Assumptions!$E$39*Assumptions!$E$40+E32*Assumptions!$E$41+E32*Assumptions!$E$42*Assumptions!$E$43 -> 1825093 | F34: =F33*Assumptions!$F$39*Assumptions!$F$40+F32*Assumptions!$F$41+F32*Assumptions!$F$42*Assumptions!$F$43 -> 2737639.4 | G34: =G33*Assumptions!$G$39*Assumptions!$G$40+G32*Assumptions!$G$41+G32*Assumptions!$G$42*Assumptions!$G$43 -> 1825093
A35: Actions per year | B35: row operations × actions/op | D35: =(D33*Assumptions!$D$39+D32+D32*Assumptions!$D$42)*Assumptions!$D$44 -> 1437260.7 | E35: =(E33*Assumptions!$E$39+E32+E32*Assumptions!$E$42)*Assumptions!$E$44 -> 1916347.6 | F35: =(F33*Assumptions!$F$39+F32+F32*Assumptions!$F$42)*Assumptions!$F$44 -> 2874521.4 | G35: =(G33*Assumptions!$G$39+G32+G32*Assumptions!$G$42)*Assumptions!$G$44 -> 1916347.6
A36: Usage cost at list | B36: credits × price + actions × price | D36: =D34*Assumptions!$D$45*12/Assumptions!$D$46+D35*Assumptions!$D$47*12/Assumptions!$D$48 -> 66190.989 | E36: =E34*Assumptions!$E$45*12/Assumptions!$E$46+E35*Assumptions!$E$47*12/Assumptions!$E$48 -> 88254.652 | F36: =F34*Assumptions!$F$45*12/Assumptions!$F$46+F35*Assumptions!$F$47*12/Assumptions!$F$48 -> 132381.98 | G36: =G34*Assumptions!$G$45*12/Assumptions!$G$46+G35*Assumptions!$G$47*12/Assumptions!$G$48 -> 88254.652
A39: First-year ACV (feeds Assumptions)
A40: ACV — SMB (20–99) | B40: MAX(floor, usage) | D40: =MAX(((Assumptions!$D$45+Assumptions!$D$47)*12),(((('Market Sizing'!$E$18*Assumptions!$D$35*Assumptions!$D$36*Assumptions!$D$37)*Assumptions!$D$38)*Assumptions!$D$39*Assumptions!$D$40+('Market Sizing'!$E$18*Assumptions!$D$35*Assumptions!$D$36*Assumptions!$D$37)*Assumptions!$D$41+('Market Sizing'!$E$18*Assumptions!$D$35*Assumptions!$D$36*Assumptions!$D$37)*Assumptions!$D$42*Assumptions!$D$43)*(Assumptions!$D$45*12/Assumptions!$D$46)+((('Market Sizing'!$E$18*Assumptions!$D$35*Assumptions!$D$36*Assumptions!$D$37)*Assumptions!$D$38)*Assumptions!$D$39+('Market Sizing'!$E$18*Assumptions!$D$35*Assumptions!$D$36*Assumptions!$D$37)+('Market Sizing'!$E$18*Assumptions!$D$35*Assumptions!$D$36*Assumptions!$D$37)*Assumptions!$D$42)*Assumptions!$D$44*(Assumptions!$D$47*12/Assumptions!$D$48))) -> 5352 | E40: =MAX(((Assumptions!$E$45+Assumptions!$E$47)*12),(((('Market Sizing'!$E$18*Assumptions!$E$35*Assumptions!$E$36*Assumptions!$E$37)*Assumptions!$E$38)*Assumptions!$E$39*Assumptions!$E$40+('Market Sizing'!$E$18*Assumptions!$E$35*Assumptions!$E$36*Assumptions!$E$37)*Assumptions!$E$41+('Market Sizing'!$E$18*Assumptions!$E$35*Assumptions!$E$36*Assumptions!$E$37)*Assumptions!$E$42*Assumptions!$E$43)*(Assumptions!$E$45*12/Assumptions!$E$46)+((('Market Sizing'!$E$18*Assumptions!$E$35*Assumptions!$E$36*Assumptions!$E$37)*Assumptions!$E$38)*Assumptions!$E$39+('Market Sizing'!$E$18*Assumptions!$E$35*Assumptions!$E$36*Assumptions!$E$37)+('Market Sizing'!$E$18*Assumptions!$E$35*Assumptions!$E$36*Assumptions!$E$37)*Assumptions!$E$42)*Assumptions!$E$44*(Assumptions!$E$47*12/Assumptions!$E$48))) -> 5352 | F40: =MAX(((Assumptions!$F$45+Assumptions!$F$47)*12),(((('Market Sizing'!$E$18*Assumptions!$F$35*Assumptions!$F$36*Assumptions!$F$37)*Assumptions!$F$38)*Assumptions!$F$39*Assumptions!$F$40+('Market Sizing'!$E$18*Assumptions!$F$35*Assumptions!$F$36*Assumptions!$F$37)*Assumptions!$F$41+('Market Sizing'!$E$18*Assumptions!$F$35*Assumptions!$F$36*Assumptions!$F$37)*Assumptions!$F$42*Assumptions!$F$43)*(Assumptions!$F$45*12/Assumptions!$F$46)+((('Market Sizing'!$E$18*Assumptions!$F$35*Assumptions!$F$36*Assumptions!$F$37)*Assumptions!$F$38)*Assumptions!$F$39+('Market Sizing'!$E$18*Assumptions!$F$35*Assumptions!$F$36*Assumptions!$F$37)+('Market Sizing'!$E$18*Assumptions!$F$35*Assumptions!$F$36*Assumptions!$F$37)*Assumptions!$F$42)*Assumptions!$F$44*(Assumptions!$F$47*12/Assumptions!$F$48))) -> 5352 | G40: =MAX(((Assumptions!$G$45+Assumptions!$G$47)*12),(((('Market Sizing'!$E$18*Assumptions!$G$35*Assumptions!$G$36*Assumptions!$G$37)*Assumptions!$G$38)*Assumptions!$G$39*Assumptions!$G$40+('Market Sizing'!$E$18*Assumptions!$G$35*Assumptions!$G$36*Assumptions!$G$37)*Assumptions!$G$41+('Market Sizing'!$E$18*Assumptions!$G$35*Assumptions!$G$36*Assumptions!$G$37)*Assumptions!$G$42*Assumptions!$G$43)*(Assumptions!$G$45*12/Assumptions!$G$46)+((('Market Sizing'!$E$18*Assumptions!$G$35*Assumptions!$G$36*Assumptions!$G$37)*Assumptions!$G$38)*Assumptions!$G$39+('Market Sizing'!$E$18*Assumptions!$G$35*Assumptions!$G$36*Assumptions!$G$37)+('Market Sizing'!$E$18*Assumptions!$G$35*Assumptions!$G$36*Assumptions!$G$37)*Assumptions!$G$42)*Assumptions!$G$44*(Assumptions!$G$47*12/Assumptions!$G$48))) -> 5352
A41: ACV — Mid-Market (100–499) | B41: MAX(floor, usage) | D41: =MAX(((Assumptions!$D$45+Assumptions!$D$47)*12),(((('Market Sizing'!$E$19*Assumptions!$D$35*Assumptions!$D$36*Assumptions!$D$37)*Assumptions!$D$38)*Assumptions!$D$39*Assumptions!$D$40+('Market Sizing'!$E$19*Assumptions!$D$35*Assumptions!$D$36*Assumptions!$D$37)*Assumptions!$D$41+('Market Sizing'!$E$19*Assumptions!$D$35*Assumptions!$D$36*Assumptions!$D$37)*Assumptions!$D$42*Assumptions!$D$43)*(Assumptions!$D$45*12/Assumptions!$D$46)+((('Market Sizing'!$E$19*Assumptions!$D$35*Assumptions!$D$36*Assumptions!$D$37)*Assumptions!$D$38)*Assumptions!$D$39+('Market Sizing'!$E$19*Assumptions!$D$35*Assumptions!$D$36*Assumptions!$D$37)+('Market Sizing'!$E$19*Assumptions!$D$35*Assumptions!$D$36*Assumptions!$D$37)*Assumptions!$D$42)*Assumptions!$D$44*(Assumptions!$D$47*12/Assumptions!$D$48))) -> 7325.0401 | E41: =MAX(((Assumptions!$E$45+Assumptions!$E$47)*12),(((('Market Sizing'!$E$19*Assumptions!$E$35*Assumptions!$E$36*Assumptions!$E$37)*Assumptions!$E$38)*Assumptions!$E$39*Assumptions!$E$40+('Market Sizing'!$E$19*Assumptions!$E$35*Assumptions!$E$36*Assumptions!$E$37)*Assumptions!$E$41+('Market Sizing'!$E$19*Assumptions!$E$35*Assumptions!$E$36*Assumptions!$E$37)*Assumptions!$E$42*Assumptions!$E$43)*(Assumptions!$E$45*12/Assumptions!$E$46)+((('Market Sizing'!$E$19*Assumptions!$E$35*Assumptions!$E$36*Assumptions!$E$37)*Assumptions!$E$38)*Assumptions!$E$39+('Market Sizing'!$E$19*Assumptions!$E$35*Assumptions!$E$36*Assumptions!$E$37)+('Market Sizing'!$E$19*Assumptions!$E$35*Assumptions!$E$36*Assumptions!$E$37)*Assumptions!$E$42)*Assumptions!$E$44*(Assumptions!$E$47*12/Assumptions!$E$48))) -> 9766.7201 | F41: =MAX(((Assumptions!$F$45+Assumptions!$F$47)*12),(((('Market Sizing'!$E$19*Assumptions!$F$35*Assumptions!$F$36*Assumptions!$F$37)*Assumptions!$F$38)*Assumptions!$F$39*Assumptions!$F$40+('Market Sizing'!$E$19*Assumptions!$F$35*Assumptions!$F$36*Assumptions!$F$37)*Assumptions!$F$41+('Market Sizing'!$E$19*Assumptions!$F$35*Assumptions!$F$36*Assumptions!$F$37)*Assumptions!$F$42*Assumptions!$F$43)*(Assumptions!$F$45*12/Assumptions!$F$46)+((('Market Sizing'!$E$19*Assumptions!$F$35*Assumptions!$F$36*Assumptions!$F$37)*Assumptions!$F$38)*Assumptions!$F$39+('Market Sizing'!$E$19*Assumptions!$F$35*Assumptions!$F$36*Assumptions!$F$37)+('Market Sizing'!$E$19*Assumptions!$F$35*Assumptions!$F$36*Assumptions!$F$37)*Assumptions!$F$42)*Assumptions!$F$44*(Assumptions!$F$47*12/Assumptions!$F$48))) -> 14650.08 | G41: =MAX(((Assumptions!$G$45+Assumptions!$G$47)*12),(((('Market Sizing'!$E$19*Assumptions!$G$35*Assumptions!$G$36*Assumptions!$G$37)*Assumptions!$G$38)*Assumptions!$G$39*Assumptions!$G$40+('Market Sizing'!$E$19*Assumptions!$G$35*Assumptions!$G$36*Assumptions!$G$37)*Assumptions!$G$41+('Market Sizing'!$E$19*Assumptions!$G$35*Assumptions!$G$36*Assumptions!$G$37)*Assumptions!$G$42*Assumptions!$G$43)*(Assumptions!$G$45*12/Assumptions!$G$46)+((('Market Sizing'!$E$19*Assumptions!$G$35*Assumptions!$G$36*Assumptions!$G$37)*Assumptions!$G$38)*Assumptions!$G$39+('Market Sizing'!$E$19*Assumptions!$G$35*Assumptions!$G$36*Assumptions!$G$37)+('Market Sizing'!$E$19*Assumptions!$G$35*Assumptions!$G$36*Assumptions!$G$37)*Assumptions!$G$42)*Assumptions!$G$44*(Assumptions!$G$47*12/Assumptions!$G$48))) -> 9766.7201
A42: ACV — Enterprise (500+) | B42: MAX(Enterprise minimum, usage) × (1 − discount) | D42: =MAX((Assumptions!$D$49*(Assumptions!$D$45*12/Assumptions!$D$46)+Assumptions!$D$50*(Assumptions!$D$47*12/Assumptions!$D$48)),(((('Market Sizing'!$E$20*Assumptions!$D$35*Assumptions!$D$36*Assumptions!$D$37)*Assumptions!$D$38)*Assumptions!$D$39*Assumptions!$D$40+('Market Sizing'!$E$20*Assumptions!$D$35*Assumptions!$D$36*Assumptions!$D$37)*Assumptions!$D$41+('Market Sizing'!$E$20*Assumptions!$D$35*Assumptions!$D$36*Assumptions!$D$37)*Assumptions!$D$42*Assumptions!$D$43)*(Assumptions!$D$45*12/Assumptions!$D$46)+((('Market Sizing'!$E$20*Assumptions!$D$35*Assumptions!$D$36*Assumptions!$D$37)*Assumptions!$D$38)*Assumptions!$D$39+('Market Sizing'!$E$20*Assumptions!$D$35*Assumptions!$D$36*Assumptions!$D$37)+('Market Sizing'!$E$20*Assumptions!$D$35*Assumptions!$D$36*Assumptions!$D$37)*Assumptions!$D$42)*Assumptions!$D$44*(Assumptions!$D$47*12/Assumptions!$D$48)))*(1-Assumptions!$D$51) -> 46333.692 | E42: =MAX((Assumptions!$E$49*(Assumptions!$E$45*12/Assumptions!$E$46)+Assumptions!$E$50*(Assumptions!$E$47*12/Assumptions!$E$48)),(((('Market Sizing'!$E$20*Assumptions!$E$35*Assumptions!$E$36*Assumptions!$E$37)*Assumptions!$E$38)*Assumptions!$E$39*Assumptions!$E$40+('Market Sizing'!$E$20*Assumptions!$E$35*Assumptions!$E$36*Assumptions!$E$37)*Assumptions!$E$41+('Market Sizing'!$E$20*Assumptions!$E$35*Assumptions!$E$36*Assumptions!$E$37)*Assumptions!$E$42*Assumptions!$E$43)*(Assumptions!$E$45*12/Assumptions!$E$46)+((('Market Sizing'!$E$20*Assumptions!$E$35*Assumptions!$E$36*Assumptions!$E$37)*Assumptions!$E$38)*Assumptions!$E$39+('Market Sizing'!$E$20*Assumptions!$E$35*Assumptions!$E$36*Assumptions!$E$37)+('Market Sizing'!$E$20*Assumptions!$E$35*Assumptions!$E$36*Assumptions!$E$37)*Assumptions!$E$42)*Assumptions!$E$44*(Assumptions!$E$47*12/Assumptions!$E$48)))*(1-Assumptions!$E$51) -> 61778.256 | F42: =MAX((Assumptions!$F$49*(Assumptions!$F$45*12/Assumptions!$F$46)+Assumptions!$F$50*(Assumptions!$F$47*12/Assumptions!$F$48)),(((('Market Sizing'!$E$20*Assumptions!$F$35*Assumptions!$F$36*Assumptions!$F$37)*Assumptions!$F$38)*Assumptions!$F$39*Assumptions!$F$40+('Market Sizing'!$E$20*Assumptions!$F$35*Assumptions!$F$36*Assumptions!$F$37)*Assumptions!$F$41+('Market Sizing'!$E$20*Assumptions!$F$35*Assumptions!$F$36*Assumptions!$F$37)*Assumptions!$F$42*Assumptions!$F$43)*(Assumptions!$F$45*12/Assumptions!$F$46)+((('Market Sizing'!$E$20*Assumptions!$F$35*Assumptions!$F$36*Assumptions!$F$37)*Assumptions!$F$38)*Assumptions!$F$39+('Market Sizing'!$E$20*Assumptions!$F$35*Assumptions!$F$36*Assumptions!$F$37)+('Market Sizing'!$E$20*Assumptions!$F$35*Assumptions!$F$36*Assumptions!$F$37)*Assumptions!$F$42)*Assumptions!$F$44*(Assumptions!$F$47*12/Assumptions!$F$48)))*(1-Assumptions!$F$51) -> 92667.384 | G42: =MAX((Assumptions!$G$49*(Assumptions!$G$45*12/Assumptions!$G$46)+Assumptions!$G$50*(Assumptions!$G$47*12/Assumptions!$G$48)),(((('Market Sizing'!$E$20*Assumptions!$G$35*Assumptions!$G$36*Assumptions!$G$37)*Assumptions!$G$38)*Assumptions!$G$39*Assumptions!$G$40+('Market Sizing'!$E$20*Assumptions!$G$35*Assumptions!$G$36*Assumptions!$G$37)*Assumptions!$G$41+('Market Sizing'!$E$20*Assumptions!$G$35*Assumptions!$G$36*Assumptions!$G$37)*Assumptions!$G$42*Assumptions!$G$43)*(Assumptions!$G$45*12/Assumptions!$G$46)+((('Market Sizing'!$E$20*Assumptions!$G$35*Assumptions!$G$36*Assumptions!$G$37)*Assumptions!$G$38)*Assumptions!$G$39+('Market Sizing'!$E$20*Assumptions!$G$35*Assumptions!$G$36*Assumptions!$G$37)+('Market Sizing'!$E$20*Assumptions!$G$35*Assumptions!$G$36*Assumptions!$G$37)*Assumptions!$G$42)*Assumptions!$G$44*(Assumptions!$G$47*12/Assumptions!$G$48)))*(1-Assumptions!$G$51) -> 61778.256
A44: Check: Base Enterprise ACV vs Vendr median buyer ($59,996, S16) | E44: =E42/59996 -> 1.0297063
A46: Finding: at published rates, an SMB distributor's usage (~$2K/yr) sits well below the Growth floor, so seller density does NOT lift SMB ACV. It matters only from mid-market upward. This tempers Phase 3's revenue-potential argument (stress test T4 there) and is why the pilot's ICP leans to 100+ employee distributors.

Sheet GTM Funnel
A1: GTM Funnel — live model (selected scenario and motion)
A2: Lead generation → qualification → opportunities → wins, with a sales-capacity constraint. Quarters Q1 2027–Q4 2029; annual columns P–R; total S.
A3: ="Live run: "&Assumptions!$E$4&" scenario · "&Assumptions!$E$5 -> Live run: Base scenario · Partner-led pilot
A5: Live model — inputs carried into this run | B5: Unit / note | C5: Q1 2027 | D5: Q2 2027 | E5: Q3 2027 | F5: Q4 2027 | G5: Q1 2028 | H5: Q2 2028 | I5: Q3 2028 | J5: Q4 2028 | K5: Q1 2029 | L5: Q2 2029 | M5: Q3 2029 | N5: Q4 2029 | P5: 2027 | Q5: 2028 | R5: 2029 | S5: 2027–29
A6: SAM accounts — wave 1 (4236 electrical) | B6: firms × filters × (1 − existing) | C6: ='Market Sizing'!$F$12*Assumptions!$G$9*Assumptions!$G$10*(1-Assumptions!$G$11) -> 1281.1679
A7: SAM accounts — wave 2 (4237 PHVAC) | C7: ='Market Sizing'!$F$13*Assumptions!$G$9*Assumptions!$G$10*(1-Assumptions!$G$11) -> 904.71656
A8: SAM accounts — wave 3 (4238 machinery/MRO) | C8: ='Market Sizing'!$F$14*Assumptions!$G$9*Assumptions!$G$10*(1-Assumptions!$G$11) -> 2981.6123
A9: First-year ACV — SMB | B9: usage build (ACV Build) | C9: =MAX(((Assumptions!$G$45+Assumptions!$G$47)*12),(((('Market Sizing'!$E$18*Assumptions!$G$35*Assumptions!$G$36*Assumptions!$G$37)*Assumptions!$G$38)*Assumptions!$G$39*Assumptions!$G$40+('Market Sizing'!$E$18*Assumptions!$G$35*Assumptions!$G$36*Assumptions!$G$37)*Assumptions!$G$41+('Market Sizing'!$E$18*Assumptions!$G$35*Assumptions!$G$36*Assumptions!$G$37)*Assumptions!$G$42*Assumptions!$G$43)*(Assumptions!$G$45*12/Assumptions!$G$46)+((('Market Sizing'!$E$18*Assumptions!$G$35*Assumptions!$G$36*Assumptions!$G$37)*Assumptions!$G$38)*Assumptions!$G$39+('Market Sizing'!$E$18*Assumptions!$G$35*Assumptions!$G$36*Assumptions!$G$37)+('Market Sizing'!$E$18*Assumptions!$G$35*Assumptions!$G$36*Assumptions!$G$37)*Assumptions!$G$42)*Assumptions!$G$44*(Assumptions!$G$47*12/Assumptions!$G$48))) -> 5352
A10: First-year ACV — Mid-Market | C10: =MAX(((Assumptions!$G$45+Assumptions!$G$47)*12),(((('Market Sizing'!$E$19*Assumptions!$G$35*Assumptions!$G$36*Assumptions!$G$37)*Assumptions!$G$38)*Assumptions!$G$39*Assumptions!$G$40+('Market Sizing'!$E$19*Assumptions!$G$35*Assumptions!$G$36*Assumptions!$G$37)*Assumptions!$G$41+('Market Sizing'!$E$19*Assumptions!$G$35*Assumptions!$G$36*Assumptions!$G$37)*Assumptions!$G$42*Assumptions!$G$43)*(Assumptions!$G$45*12/Assumptions!$G$46)+((('Market Sizing'!$E$19*Assumptions!$G$35*Assumptions!$G$36*Assumptions!$G$37)*Assumptions!$G$38)*Assumptions!$G$39+('Market Sizing'!$E$19*Assumptions!$G$35*Assumptions!$G$36*Assumptions!$G$37)+('Market Sizing'!$E$19*Assumptions!$G$35*Assumptions!$G$36*Assumptions!$G$37)*Assumptions!$G$42)*Assumptions!$G$44*(Assumptions!$G$47*12/Assumptions!$G$48))) -> 9766.7201
A11: First-year ACV — Enterprise | C11: =MAX((Assumptions!$G$49*(Assumptions!$G$45*12/Assumptions!$G$46)+Assumptions!$G$50*(Assumptions!$G$47*12/Assumptions!$G$48)),(((('Market Sizing'!$E$20*Assumptions!$G$35*Assumptions!$G$36*Assumptions!$G$37)*Assumptions!$G$38)*Assumptions!$G$39*Assumptions!$G$40+('Market Sizing'!$E$20*Assumptions!$G$35*Assumptions!$G$36*Assumptions!$G$37)*Assumptions!$G$41+('Market Sizing'!$E$20*Assumptions!$G$35*Assumptions!$G$36*Assumptions!$G$37)*Assumptions!$G$42*Assumptions!$G$43)*(Assumptions!$G$45*12/Assumptions!$G$46)+((('Market Sizing'!$E$20*Assumptions!$G$35*Assumptions!$G$36*Assumptions!$G$37)*Assumptions!$G$38)*Assumptions!$G$39+('Market Sizing'!$E$20*Assumptions!$G$35*Assumptions!$G$36*Assumptions!$G$37)+('Market Sizing'!$E$20*Assumptions!$G$35*Assumptions!$G$36*Assumptions!$G$37)*Assumptions!$G$42)*Assumptions!$G$44*(Assumptions!$G$47*12/Assumptions!$G$48)))*(1-Assumptions!$G$51) -> 61778.256
A12: Sales-assisted mix denominator | B12: mixS(1−ss)+mixM+mixE | C12: =Assumptions!$G$29*(1-Assumptions!$G$32)+Assumptions!$G$30+Assumptions!$G$31 -> 0.85
A13: Blended ACV of sales-assisted wins | C13: =(Assumptions!$G$29*(1-Assumptions!$G$32)*$C$9+Assumptions!$G$30*$C$10+Assumptions!$G$31*$C$11)/$C$12 -> 15291.699
A14: AE fully loaded annual cost | B14: OTE ÷ wage share | C14: =Assumptions!$G$64/Assumptions!$G$65 -> 285714.29
A15: Deals per ramped AE per quarter | B15: quota × productivity ÷ 4 ÷ ACV | C15: =Assumptions!$G$62*Assumptions!$G$63/4/$C$13 -> 10.013603
A16: Variable AE cost per deal (shared capacity) | C16: =$C$14/4/$C$15 -> 7133.1542
A17: GTM funnel | B17: Unit / note | C17: Q1 2027 | D17: Q2 2027 | E17: Q3 2027 | F17: Q4 2027 | G17: Q1 2028 | H17: Q2 2028 | I17: Q3 2028 | J17: Q4 2028 | K17: Q1 2029 | L17: Q2 2029 | M17: Q3 2029 | N17: Q4 2029 | P17: 2027 | Q17: 2028 | R17: 2029 | S17: 2027–29
A18: Quarter number | B18: # | C18: 1 | D18: 2 | E18: 3 | F18: 4 | G18: 5 | H18: 6 | I18: 7 | J18: 8 | K18: 9 | L18: 10 | M18: 11 | N18: 12
A19: Program running (1) / stopped (0) | B19: flag | C19: =IF(C18<=Assumptions!$G$79,1,0) -> 1 | D19: =IF(D18<=Assumptions!$G$79,1,0) -> 1 | E19: =IF(E18<=Assumptions!$G$79,1,0) -> 1 | F19: =IF(F18<=Assumptions!$G$79,1,0) -> 1 | G19: =IF(G18<=Assumptions!$G$79,1,0) -> 1 | H19: =IF(H18<=Assumptions!$G$79,1,0) -> 1 | I19: =IF(I18<=Assumptions!$G$79,1,0) -> 1 | J19: =IF(J18<=Assumptions!$G$79,1,0) -> 1 | ... N19: =IF(N18<=Assumptions!$G$79,1,0) -> 1
A20: Wave 1 active (0.5 in launch quarter) | B20: factor | C20: =IF(C18=Assumptions!$G$12,0.5,IF(C18>Assumptions!$G$12,1,0)) -> 0.5 | D20: =IF(D18=Assumptions!$G$12,0.5,IF(D18>Assumptions!$G$12,1,0)) -> 1 | E20: =IF(E18=Assumptions!$G$12,0.5,IF(E18>Assumptions!$G$12,1,0)) -> 1 | F20: =IF(F18=Assumptions!$G$12,0.5,IF(F18>Assumptions!$G$12,1,0)) -> 1 | G20: =IF(G18=Assumptions!$G$12,0.5,IF(G18>Assumptions!$G$12,1,0)) -> 1 | H20: =IF(H18=Assumptions!$G$12,0.5,IF(H18>Assumptions!$G$12,1,0)) -> 1 | I20: =IF(I18=Assumptions!$G$12,0.5,IF(I18>Assumptions!$G$12,1,0)) -> 1 | J20: =IF(J18=Assumptions!$G$12,0.5,IF(J18>Assumptions!$G$12,1,0)) -> 1 | ... N20: =IF(N18=Assumptions!$G$12,0.5,IF(N18>Assumptions!$G$12,1,0)) -> 1
A21: Wave 2 active (0.5 in launch quarter) | B21: factor | C21: =IF(C18=Assumptions!$G$13,0.5,IF(C18>Assumptions!$G$13,1,0)) -> 0 | D21: =IF(D18=Assumptions!$G$13,0.5,IF(D18>Assumptions!$G$13,1,0)) -> 0 | E21: =IF(E18=Assumptions!$G$13,0.5,IF(E18>Assumptions!$G$13,1,0)) -> 0 | F21: =IF(F18=Assumptions!$G$13,0.5,IF(F18>Assumptions!$G$13,1,0)) -> 0 | G21: =IF(G18=Assumptions!$G$13,0.5,IF(G18>Assumptions!$G$13,1,0)) -> 0.5 | H21: =IF(H18=Assumptions!$G$13,0.5,IF(H18>Assumptions!$G$13,1,0)) -> 1 | I21: =IF(I18=Assumptions!$G$13,0.5,IF(I18>Assumptions!$G$13,1,0)) -> 1 | J21: =IF(J18=Assumptions!$G$13,0.5,IF(J18>Assumptions!$G$13,1,0)) -> 1 | ... N21: =IF(N18=Assumptions!$G$13,0.5,IF(N18>Assumptions!$G$13,1,0)) -> 1
A22: Wave 3 active (0.5 in launch quarter) | B22: factor | C22: =IF(C18=Assumptions!$G$14,0.5,IF(C18>Assumptions!$G$14,1,0)) -> 0 | D22: =IF(D18=Assumptions!$G$14,0.5,IF(D18>Assumptions!$G$14,1,0)) -> 0 | E22: =IF(E18=Assumptions!$G$14,0.5,IF(E18>Assumptions!$G$14,1,0)) -> 0 | F22: =IF(F18=Assumptions!$G$14,0.5,IF(F18>Assumptions!$G$14,1,0)) -> 0 | G22: =IF(G18=Assumptions!$G$14,0.5,IF(G18>Assumptions!$G$14,1,0)) -> 0 | H22: =IF(H18=Assumptions!$G$14,0.5,IF(H18>Assumptions!$G$14,1,0)) -> 0 | I22: =IF(I18=Assumptions!$G$14,0.5,IF(I18>Assumptions!$G$14,1,0)) -> 0.5 | J22: =IF(J18=Assumptions!$G$14,0.5,IF(J18>Assumptions!$G$14,1,0)) -> 1 | ... N22: =IF(N18=Assumptions!$G$14,0.5,IF(N18>Assumptions!$G$14,1,0)) -> 1
A23: Active SAM accounts in launched waves | B23: accounts | C23: =$C$6*C20+$C$7*C21+$C$8*C22 -> 640.58396 | D23: =$C$6*D20+$C$7*D21+$C$8*D22 -> 1281.1679 | E23: =$C$6*E20+$C$7*E21+$C$8*E22 -> 1281.1679 | F23: =$C$6*F20+$C$7*F21+$C$8*F22 -> 1281.1679 | G23: =$C$6*G20+$C$7*G21+$C$8*G22 -> 1733.5262 | H23: =$C$6*H20+$C$7*H21+$C$8*H22 -> 2185.8845 | I23: =$C$6*I20+$C$7*I21+$C$8*I22 -> 3676.6906 | J23: =$C$6*J20+$C$7*J21+$C$8*J22 -> 5167.4968 | ... N23: =$C$6*N20+$C$7*N21+$C$8*N22 -> 5167.4968 | P23: =F23 -> 1281.1679 | Q23: =J23 -> 5167.4968 | R23: =N23 -> 5167.4968 | S23: =R23 -> 5167.4968
A24: Accounts sequenced by Clay-run outbound | B24: accounts | C24: =C23*Assumptions!$G$17*C19 -> 256.23359 | D24: =D23*Assumptions!$G$17*D19 -> 512.46717 | E24: =E23*Assumptions!$G$17*E19 -> 512.46717 | F24: =F23*Assumptions!$G$17*F19 -> 512.46717 | G24: =G23*Assumptions!$G$17*G19 -> 693.41048 | H24: =H23*Assumptions!$G$17*H19 -> 874.35379 | I24: =I23*Assumptions!$G$17*I19 -> 1470.6763 | J24: =J23*Assumptions!$G$17*J19 -> 2066.9987 | ... N24: =N23*Assumptions!$G$17*N19 -> 2066.9987 | P24: =SUM(C24:F24) -> 1793.6351 | Q24: =SUM(G24:J24) -> 5105.4392 | R24: =SUM(K24:N24) -> 8267.9949 | S24: =SUM(P24:R24) -> 15167.069
A25: Leads — outbound meetings | B25: leads | C25: =C24*Assumptions!$G$18 -> 7.6870076 | D25: =D24*Assumptions!$G$18 -> 15.374015 | E25: =E24*Assumptions!$G$18 -> 15.374015 | F25: =F24*Assumptions!$G$18 -> 15.374015 | G25: =G24*Assumptions!$G$18 -> 20.802314 | H25: =H24*Assumptions!$G$18 -> 26.230614 | I25: =I24*Assumptions!$G$18 -> 44.120288 | J25: =J24*Assumptions!$G$18 -> 62.009961 | ... N25: =N24*Assumptions!$G$18 -> 62.009961 | P25: =SUM(C25:F25) -> 53.809053 | Q25: =SUM(G25:J25) -> 153.16318 | R25: =SUM(K25:N25) -> 248.03985 | S25: =SUM(P25:R25) -> 455.01208
A26: Leads — inbound / template-led | B26: leads | C26: =C23*Assumptions!$G$19*C19 -> 6.4058396 | D26: =D23*Assumptions!$G$19*D19 -> 12.811679 | E26: =E23*Assumptions!$G$19*E19 -> 12.811679 | F26: =F23*Assumptions!$G$19*F19 -> 12.811679 | G26: =G23*Assumptions!$G$19*G19 -> 17.335262 | H26: =H23*Assumptions!$G$19*H19 -> 21.858845 | I26: =I23*Assumptions!$G$19*I19 -> 36.766906 | J26: =J23*Assumptions!$G$19*J19 -> 51.674968 | ... N26: =N23*Assumptions!$G$19*N19 -> 51.674968 | P26: =SUM(C26:F26) -> 44.840878 | Q26: =SUM(G26:J26) -> 127.63598 | R26: =SUM(K26:N26) -> 206.69987 | S26: =SUM(P26:R26) -> 379.17673
A27: Active partners | B27: partners | C27: =IF(C19=1,MIN(Assumptions!$G$22,Assumptions!$G$20+Assumptions!$G$21*(C18-1)),0) -> 2 | D27: =IF(D19=1,MIN(Assumptions!$G$22,Assumptions!$G$20+Assumptions!$G$21*(D18-1)),0) -> 3 | E27: =IF(E19=1,MIN(Assumptions!$G$22,Assumptions!$G$20+Assumptions!$G$21*(E18-1)),0) -> 4 | F27: =IF(F19=1,MIN(Assumptions!$G$22,Assumptions!$G$20+Assumptions!$G$21*(F18-1)),0) -> 5 | G27: =IF(G19=1,MIN(Assumptions!$G$22,Assumptions!$G$20+Assumptions!$G$21*(G18-1)),0) -> 6 | H27: =IF(H19=1,MIN(Assumptions!$G$22,Assumptions!$G$20+Assumptions!$G$21*(H18-1)),0) -> 7 | I27: =IF(I19=1,MIN(Assumptions!$G$22,Assumptions!$G$20+Assumptions!$G$21*(I18-1)),0) -> 8 | J27: =IF(J19=1,MIN(Assumptions!$G$22,Assumptions!$G$20+Assumptions!$G$21*(J18-1)),0) -> 9 | ... N27: =IF(N19=1,MIN(Assumptions!$G$22,Assumptions!$G$20+Assumptions!$G$21*(N18-1)),0) -> 10 | P27: =F27 -> 5 | Q27: =J27 -> 9 | R27: =N27 -> 10 | S27: =R27 -> 10
A28: Leads — partner-sourced | B28: leads | C28: =C27*Assumptions!$G$23 -> 6 | D28: =D27*Assumptions!$G$23 -> 9 | E28: =E27*Assumptions!$G$23 -> 12 | F28: =F27*Assumptions!$G$23 -> 15 | G28: =G27*Assumptions!$G$23 -> 18 | H28: =H27*Assumptions!$G$23 -> 21 | I28: =I27*Assumptions!$G$23 -> 24 | J28: =J27*Assumptions!$G$23 -> 27 | ... N28: =N27*Assumptions!$G$23 -> 30 | P28: =SUM(C28:F28) -> 42 | Q28: =SUM(G28:J28) -> 90 | R28: =SUM(K28:N28) -> 120 | S28: =SUM(P28:R28) -> 252
A29: Total leads | B29: leads | C29: =C25+C26+C28 -> 20.092847 | D29: =D25+D26+D28 -> 37.185694 | E29: =E25+E26+E28 -> 40.185694 | F29: =F25+F26+F28 -> 43.185694 | G29: =G25+G26+G28 -> 56.137577 | H29: =H25+H26+H28 -> 69.089459 | I29: =I25+I26+I28 -> 104.88719 | J29: =J25+J26+J28 -> 140.68493 | ... N29: =N25+N26+N28 -> 143.68493 | P29: =SUM(C29:F29) -> 140.64993 | Q29: =SUM(G29:J29) -> 370.79916 | R29: =SUM(K29:N29) -> 574.73972 | S29: =SUM(P29:R29) -> 1086.1888
A30: Qualified (SQL) — outbound + inbound | B30: SQLs | C30: =(C25+C26)*Assumptions!$G$24 -> 6.3417813 | D30: =(D25+D26)*Assumptions!$G$24 -> 12.683563 | E30: =(E25+E26)*Assumptions!$G$24 -> 12.683563 | F30: =(F25+F26)*Assumptions!$G$24 -> 12.683563 | G30: =(G25+G26)*Assumptions!$G$24 -> 17.161909 | H30: =(H25+H26)*Assumptions!$G$24 -> 21.640256 | I30: =(I25+I26)*Assumptions!$G$24 -> 36.399237 | J30: =(J25+J26)*Assumptions!$G$24 -> 51.158218 | ... N30: =(N25+N26)*Assumptions!$G$24 -> 51.158218 | P30: =SUM(C30:F30) -> 44.392469 | Q30: =SUM(G30:J30) -> 126.35962 | R30: =SUM(K30:N30) -> 204.63287 | S30: =SUM(P30:R30) -> 375.38496
A31: Qualified (SQL) — partner | B31: SQLs | C31: =C28*Assumptions!$G$25 -> 3.6 | D31: =D28*Assumptions!$G$25 -> 5.4 | E31: =E28*Assumptions!$G$25 -> 7.2 | F31: =F28*Assumptions!$G$25 -> 9 | G31: =G28*Assumptions!$G$25 -> 10.8 | H31: =H28*Assumptions!$G$25 -> 12.6 | I31: =I28*Assumptions!$G$25 -> 14.4 | J31: =J28*Assumptions!$G$25 -> 16.2 | ... N31: =N28*Assumptions!$G$25 -> 18 | P31: =SUM(C31:F31) -> 25.2 | Q31: =SUM(G31:J31) -> 54 | R31: =SUM(K31:N31) -> 72 | S31: =SUM(P31:R31) -> 151.2
A32: Opportunities created | B32: opps | C32: =(C30+C31)*Assumptions!$G$26 -> 4.4738016 | D32: =(D30+D31)*Assumptions!$G$26 -> 8.1376031 | E32: =(E30+E31)*Assumptions!$G$26 -> 8.9476031 | F32: =(F30+F31)*Assumptions!$G$26 -> 9.7576031 | G32: =(G30+G31)*Assumptions!$G$26 -> 12.582859 | H32: =(H30+H31)*Assumptions!$G$26 -> 15.408115 | I32: =(I30+I31)*Assumptions!$G$26 -> 22.859657 | J32: =(J30+J31)*Assumptions!$G$26 -> 30.311198 | ... N32: =(N30+N31)*Assumptions!$G$26 -> 31.121198 | P32: =SUM(C32:F32) -> 31.316611 | Q32: =SUM(G32:J32) -> 81.16183 | R32: =SUM(K32:N32) -> 124.48479 | S32: =SUM(P32:R32) -> 236.96323
A33: of which partner-sourced | B33: opps | C33: =C31*Assumptions!$G$26 -> 1.62 | D33: =D31*Assumptions!$G$26 -> 2.43 | E33: =E31*Assumptions!$G$26 -> 3.24 | F33: =F31*Assumptions!$G$26 -> 4.05 | G33: =G31*Assumptions!$G$26 -> 4.86 | H33: =H31*Assumptions!$G$26 -> 5.67 | I33: =I31*Assumptions!$G$26 -> 6.48 | J33: =J31*Assumptions!$G$26 -> 7.29 | ... N33: =N31*Assumptions!$G$26 -> 8.1 | P33: =SUM(C33:F33) -> 11.34 | Q33: =SUM(G33:J33) -> 24.3 | R33: =SUM(K33:N33) -> 32.4 | S33: =SUM(P33:R33) -> 68.04
A34: Demand-limited wins (opps from 1–2 quarters earlier × win rate) | B34: wins | C34: =0*Assumptions!$G$27 -> 0 | D34: =IF(Assumptions!$G$28=1,C32,0)*Assumptions!$G$27 -> 1.2526644 | E34: =IF(Assumptions!$G$28=1,D32,C32)*Assumptions!$G$27 -> 2.2785289 | F34: =IF(Assumptions!$G$28=1,E32,D32)*Assumptions!$G$27 -> 2.5053289 | G34: =IF(Assumptions!$G$28=1,F32,E32)*Assumptions!$G$27 -> 2.7321289 | H34: =IF(Assumptions!$G$28=1,G32,F32)*Assumptions!$G$27 -> 3.5232006 | I34: =IF(Assumptions!$G$28=1,H32,G32)*Assumptions!$G$27 -> 4.3142723 | J34: =IF(Assumptions!$G$28=1,I32,H32)*Assumptions!$G$27 -> 6.4007039 | K34: =IF(Assumptions!$G$28=1,J32,I32)*Assumptions!$G$27 -> 8.4871355 | L34: =IF(Assumptions!$G$28=1,K32,J32)*Assumptions!$G$27 -> 8.7139355 | ... N34: =IF(Assumptions!$G$28=1,M32,L32)*Assumptions!$G$27 -> 8.7139355 | P34: =SUM(C34:F34) -> 6.0365222 | Q34: =SUM(G34:J34) -> 16.970306 | R34: =SUM(K34:N34) -> 34.628942 | S34: =SUM(P34:R34) -> 57.63577
A35: Partner-sourced share of wins | B35: % | C35: =IFERROR(0/0,0) -> 0 | D35: =IFERROR(IF(Assumptions!$G$28=1,C33,0)/IF(Assumptions!$G$28=1,C32,0),0) -> 0.36210815 | E35: =IFERROR(IF(Assumptions!$G$28=1,D33,C33)/IF(Assumptions!$G$28=1,D32,C32),0) -> 0.29861373 | F35: =IFERROR(IF(Assumptions!$G$28=1,E33,D33)/IF(Assumptions!$G$28=1,E32,D32),0) -> 0.36210815 | G35: =IFERROR(IF(Assumptions!$G$28=1,F33,E33)/IF(Assumptions!$G$28=1,F32,E32),0) -> 0.41506095 | H35: =IFERROR(IF(Assumptions!$G$28=1,G33,F33)/IF(Assumptions!$G$28=1,G32,F32),0) -> 0.38623972 | I35: =IFERROR(IF(Assumptions!$G$28=1,H33,G33)/IF(Assumptions!$G$28=1,H32,G32),0) -> 0.3679879 | J35: =IFERROR(IF(Assumptions!$G$28=1,I33,H33)/IF(Assumptions!$G$28=1,I32,H32),0) -> 0.28346882 | K35: =IFERROR(IF(Assumptions!$G$28=1,J33,I33)/IF(Assumptions!$G$28=1,J32,I32),0) -> 0.24050517 | L35: =IFERROR(IF(Assumptions!$G$28=1,K33,J33)/IF(Assumptions!$G$28=1,K32,J32),0) -> 0.26027276 | ... N35: =IFERROR(IF(Assumptions!$G$28=1,M33,L33)/IF(Assumptions!$G$28=1,M32,L32),0) -> 0.26027276
A36: Self-serve SMB wins (no AE) | B36: wins | C36: =C34*Assumptions!$G$29*Assumptions!$G$32 -> 0 | D36: =D34*Assumptions!$G$29*Assumptions!$G$32 -> 0.18789967 | E36: =E34*Assumptions!$G$29*Assumptions!$G$32 -> 0.34177933 | F36: =F34*Assumptions!$G$29*Assumptions!$G$32 -> 0.37579933 | G36: =G34*Assumptions!$G$29*Assumptions!$G$32 -> 0.40981933 | H36: =H34*Assumptions!$G$29*Assumptions!$G$32 -> 0.52848009 | I36: =I34*Assumptions!$G$29*Assumptions!$G$32 -> 0.64714085 | J36: =J34*Assumptions!$G$29*Assumptions!$G$32 -> 0.96010559 | ... N36: =N34*Assumptions!$G$29*Assumptions!$G$32 -> 1.3070903 | P36: =SUM(C36:F36) -> 0.90547833 | Q36: =SUM(G36:J36) -> 2.5455459 | R36: =SUM(K36:N36) -> 5.1943413 | S36: =SUM(P36:R36) -> 8.6453655
A37: Sales-assisted demand | B37: wins | C37: =C34-C36 -> 0 | D37: =D34-D36 -> 1.0647648 | E37: =E34-E36 -> 1.9367495 | F37: =F34-F36 -> 2.1295295 | G37: =G34-G36 -> 2.3223095 | H37: =H34-H36 -> 2.9947205 | I37: =I34-I36 -> 3.6671315 | J37: =J34-J36 -> 5.4405983 | ... N37: =N34-N36 -> 7.4068452 | P37: =SUM(C37:F37) -> 5.1310439 | Q37: =SUM(G37:J37) -> 14.42476 | R37: =SUM(K37:N37) -> 29.434601 | S37: =SUM(P37:R37) -> 48.990404
A38: Dedicated AEs (headcount) | B38: FTE | C38: =Assumptions!$D$106 -> 0 | D38: =Assumptions!$E$106 -> 0 | E38: =Assumptions!$F$106 -> 0 | F38: =Assumptions!$G$106 -> 0 | G38: =Assumptions!$H$106 -> 0 | H38: =Assumptions!$I$106 -> 0 | I38: =Assumptions!$J$106 -> 0 | J38: =Assumptions!$K$106 -> 0 | K38: =Assumptions!$L$106 -> 0 | L38: =Assumptions!$M$106 -> 0 | M38: =Assumptions!$N$106 -> 0 | N38: =Assumptions!$O$106 -> 0 | P38: =F38 -> 0 | Q38: =J38 -> 0 | R38: =N38 -> 0 | S38: =R38 -> 0
A39: Ramped dedicated AEs (≈6-month ramp) | B39: FTE | C39: =0 -> 0 | D39: =0.5*C38 -> 0 | E39: =C38+0.5*(D38-C38) -> 0 | F39: =D38+0.5*(E38-D38) -> 0 | G39: =E38+0.5*(F38-E38) -> 0 | H39: =F38+0.5*(G38-F38) -> 0 | I39: =G38+0.5*(H38-G38) -> 0 | J39: =H38+0.5*(I38-H38) -> 0 | K39: =I38+0.5*(J38-I38) -> 0 | L39: =J38+0.5*(K38-J38) -> 0 | ... N39: =L38+0.5*(M38-L38) -> 0 | P39: =F39 -> 0 | Q39: =J39 -> 0 | R39: =N39 -> 0 | S39: =R39 -> 0
A40: Sales capacity (dedicated + shared AEs) | B40: deals | C40: =(C39+Assumptions!$G$99*C19)*$C$15 -> 20.027205 | D40: =(D39+Assumptions!$G$99*D19)*$C$15 -> 20.027205 | E40: =(E39+Assumptions!$G$99*E19)*$C$15 -> 20.027205 | F40: =(F39+Assumptions!$G$99*F19)*$C$15 -> 20.027205 | G40: =(G39+Assumptions!$G$99*G19)*$C$15 -> 20.027205 | H40: =(H39+Assumptions!$G$99*H19)*$C$15 -> 20.027205 | I40: =(I39+Assumptions!$G$99*I19)*$C$15 -> 20.027205 | J40: =(J39+Assumptions!$G$99*J19)*$C$15 -> 20.027205 | ... N40: =(N39+Assumptions!$G$99*N19)*$C$15 -> 20.027205 | P40: =SUM(C40:F40) -> 80.108821 | Q40: =SUM(G40:J40) -> 80.108821 | R40: =SUM(K40:N40) -> 80.108821 | S40: =SUM(P40:R40) -> 240.32646
A41: Sales-assisted wins = MIN(demand, capacity) | B41: wins | C41: =MIN(C37,C40) -> 0 | D41: =MIN(D37,D40) -> 1.0647648 | E41: =MIN(E37,E40) -> 1.9367495 | F41: =MIN(F37,F40) -> 2.1295295 | G41: =MIN(G37,G40) -> 2.3223095 | H41: =MIN(H37,H40) -> 2.9947205 | I41: =MIN(I37,I40) -> 3.6671315 | J41: =MIN(J37,J40) -> 5.4405983 | ... N41: =MIN(N37,N40) -> 7.4068452 | P41: =SUM(C41:F41) -> 5.1310439 | Q41: =SUM(G41:J41) -> 14.42476 | R41: =SUM(K41:N41) -> 29.434601 | S41: =SUM(P41:R41) -> 48.990404
A42: Wins lost to capacity constraint | B42: wins | C42: =C37-C41 -> 0 | D42: =D37-D41 -> 0 | E42: =E37-E41 -> 0 | F42: =F37-F41 -> 0 | G42: =G37-G41 -> 0 | H42: =H37-H41 -> 0 | I42: =I37-I41 -> 0 | J42: =J37-J41 -> 0 | ... N42: =N37-N41 -> 0 | P42: =SUM(C42:F42) -> 0 | Q42: =SUM(G42:J42) -> 0 | R42: =SUM(K42:N42) -> 0 | S42: =SUM(P42:R42) -> 0
A43: New customers | B43: customers | C43: =C36+C41 -> 0 | D43: =D36+D41 -> 1.2526644 | E43: =E36+E41 -> 2.2785289 | F43: =F36+F41 -> 2.5053289 | G43: =G36+G41 -> 2.7321289 | H43: =H36+H41 -> 3.5232006 | I43: =I36+I41 -> 4.3142723 | J43: =J36+J41 -> 6.4007039 | ... N43: =N36+N41 -> 8.7139355 | P43: =SUM(C43:F43) -> 6.0365222 | Q43: =SUM(G43:J43) -> 16.970306 | R43: =SUM(K43:N43) -> 34.628942 | S43: =SUM(P43:R43) -> 57.63577
A44: New SMB | B44: customers | C44: =C36+C41*Assumptions!$G$29*(1-Assumptions!$G$32)/$C$12 -> 0 | D44: =D36+D41*Assumptions!$G$29*(1-Assumptions!$G$32)/$C$12 -> 0.62633222 | E44: =E36+E41*Assumptions!$G$29*(1-Assumptions!$G$32)/$C$12 -> 1.1392644 | F44: =F36+F41*Assumptions!$G$29*(1-Assumptions!$G$32)/$C$12 -> 1.2526644 | G44: =G36+G41*Assumptions!$G$29*(1-Assumptions!$G$32)/$C$12 -> 1.3660644 | H44: =H36+H41*Assumptions!$G$29*(1-Assumptions!$G$32)/$C$12 -> 1.7616003 | I44: =I36+I41*Assumptions!$G$29*(1-Assumptions!$G$32)/$C$12 -> 2.1571362 | J44: =J36+J41*Assumptions!$G$29*(1-Assumptions!$G$32)/$C$12 -> 3.200352 | ... N44: =N36+N41*Assumptions!$G$29*(1-Assumptions!$G$32)/$C$12 -> 4.3569677 | P44: =SUM(C44:F44) -> 3.0182611 | Q44: =SUM(G44:J44) -> 8.4851528 | R44: =SUM(K44:N44) -> 17.314471 | S44: =SUM(P44:R44) -> 28.817885
A45: New Mid-Market | B45: customers | C45: =C41*Assumptions!$G$30/$C$12 -> 0 | D45: =D41*Assumptions!$G$30/$C$12 -> 0.47601249 | E45: =E41*Assumptions!$G$30/$C$12 -> 0.86584097 | F45: =F41*Assumptions!$G$30/$C$12 -> 0.95202497 | G45: =G41*Assumptions!$G$30/$C$12 -> 1.038209 | H45: =H41*Assumptions!$G$30/$C$12 -> 1.3388162 | I45: =I41*Assumptions!$G$30/$C$12 -> 1.6394235 | J45: =J41*Assumptions!$G$30/$C$12 -> 2.4322675 | ... N45: =N41*Assumptions!$G$30/$C$12 -> 3.3112955 | P45: =SUM(C45:F45) -> 2.2938784 | Q45: =SUM(G45:J45) -> 6.4487162 | R45: =SUM(K45:N45) -> 13.158998 | S45: =SUM(P45:R45) -> 21.901593
A46: New Enterprise | B46: customers | C46: =C41*Assumptions!$G$31/$C$12 -> 0 | D46: =D41*Assumptions!$G$31/$C$12 -> 0.15031973 | E46: =E41*Assumptions!$G$31/$C$12 -> 0.27342347 | F46: =F41*Assumptions!$G$31/$C$12 -> 0.30063947 | G46: =G41*Assumptions!$G$31/$C$12 -> 0.32785547 | H46: =H41*Assumptions!$G$31/$C$12 -> 0.42278407 | I46: =I41*Assumptions!$G$31/$C$12 -> 0.51771268 | J46: =J41*Assumptions!$G$31/$C$12 -> 0.76808447 | ... N46: =N41*Assumptions!$G$31/$C$12 -> 1.0456723 | P46: =SUM(C46:F46) -> 0.72438266 | Q46: =SUM(G46:J46) -> 2.0364367 | R46: =SUM(K46:N46) -> 4.155473 | S46: =SUM(P46:R46) -> 6.9162924
A47: Lead-to-win conversion (lagged) | B47: % | C47: =0 -> 0 | D47: =IFERROR(D43/C29,0) -> 0.062343799 | E47: =IFERROR(E43/D29,0) -> 0.06127434 | F47: =IFERROR(F43/E29,0) -> 0.062343799 | G47: =IFERROR(G43/F29,0) -> 0.063264674 | H47: =IFERROR(H43/G29,0) -> 0.062760112 | I47: =IFERROR(I43/H29,0) -> 0.062444726 | J47: =IFERROR(J43/I29,0) -> 0.061024646 | K47: =IFERROR(K43/J29,0) -> 0.060327254 | ... N47: =IFERROR(N43/M29,0) -> 0.060646134

Sheet Revenue Model
A1: Revenue Model — customers, ARR and recognized revenue
A2: ARR = prior ARR × NRR^(1/4) + new customers × ACV. Recognized revenue = average ARR ÷ 4 (kept separate from ARR). Customers decay at GRR^(1/4).
A3: ="Live run: "&Assumptions!$E$4&" scenario · "&Assumptions!$E$5 -> Live run: Base scenario · Partner-led pilot
A5: Customers, ARR and revenue | B5: Unit / note | C5: Q1 2027 | D5: Q2 2027 | E5: Q3 2027 | F5: Q4 2027 | G5: Q1 2028 | H5: Q2 2028 | I5: Q3 2028 | J5: Q4 2028 | K5: Q1 2029 | L5: Q2 2029 | M5: Q3 2029 | N5: Q4 2029 | P5: 2027 | Q5: 2028 | R5: 2029 | S5: 2027–29
A6: Customers — SMB | B6: customers | C6: =0*Assumptions!$G$54^(1/4)+'GTM Funnel'!C44 -> 0 | D6: =C6*Assumptions!$G$54^(1/4)+'GTM Funnel'!D44 -> 0.62633222 | E6: =D6*Assumptions!$G$54^(1/4)+'GTM Funnel'!E44 -> 1.7458966 | F6: =E6*Assumptions!$G$54^(1/4)+'GTM Funnel'!F44 -> 2.9436472 | G6: =F6*Assumptions!$G$54^(1/4)+'GTM Funnel'!G44 -> 4.2171249 | H6: =G6*Assumptions!$G$54^(1/4)+'GTM Funnel'!H44 -> 5.8460837 | I6: =H6*Assumptions!$G$54^(1/4)+'GTM Funnel'!I44 -> 7.8193425 | J6: =I6*Assumptions!$G$54^(1/4)+'GTM Funnel'!J44 -> 10.773752 | K6: =J6*Assumptions!$G$54^(1/4)+'GTM Funnel'!K44 -> 14.678452 | ... N6: =M6*Assumptions!$G$54^(1/4)+'GTM Funnel'!N44 -> 26.000606 | P6: =F6 -> 2.9436472 | Q6: =J6 -> 10.773752 | R6: =N6 -> 26.000606 | S6: =R6 -> 26.000606
A7: Customers — Mid-Market | B7: customers | C7: =0*Assumptions!$G$55^(1/4)+'GTM Funnel'!C45 -> 0 | D7: =C7*Assumptions!$G$55^(1/4)+'GTM Funnel'!D45 -> 0.47601249 | E7: =D7*Assumptions!$G$55^(1/4)+'GTM Funnel'!E45 -> 1.3294789 | F7: =E7*Assumptions!$G$55^(1/4)+'GTM Funnel'!F45 -> 2.2469424 | G7: =F7*Assumptions!$G$55^(1/4)+'GTM Funnel'!G45 -> 3.2267393 | H7: =G7*Assumptions!$G$55^(1/4)+'GTM Funnel'!H45 -> 4.4816724 | I7: =H7*Assumptions!$G$55^(1/4)+'GTM Funnel'!I45 -> 6.0045892 | J7: =I7*Assumptions!$G$55^(1/4)+'GTM Funnel'!J45 -> 8.2807598 | K7: =J7*Assumptions!$G$55^(1/4)+'GTM Funnel'!K45 -> 11.290603 | ... N7: =M7*Assumptions!$G$55^(1/4)+'GTM Funnel'!N45 -> 20.110635 | P7: =F7 -> 2.2469424 | Q7: =J7 -> 8.2807598 | R7: =N7 -> 20.110635 | S7: =R7 -> 20.110635
A8: Customers — Enterprise | B8: customers | C8: =0*Assumptions!$G$56^(1/4)+'GTM Funnel'!C46 -> 0 | D8: =C8*Assumptions!$G$56^(1/4)+'GTM Funnel'!D46 -> 0.15031973 | E8: =D8*Assumptions!$G$56^(1/4)+'GTM Funnel'!E46 -> 0.42064216 | F8: =E8*Assumptions!$G$56^(1/4)+'GTM Funnel'!F46 -> 0.71260393 | G8: =F8*Assumptions!$G$56^(1/4)+'GTM Funnel'!G46 -> 1.0257586 | H8: =G8*Assumptions!$G$56^(1/4)+'GTM Funnel'!H46 -> 1.4273817 | I8: =H8*Assumptions!$G$56^(1/4)+'GTM Funnel'!I46 -> 1.915648 | J8: =I8*Assumptions!$G$56^(1/4)+'GTM Funnel'!J46 -> 2.6442133 | K8: =J8*Assumptions!$G$56^(1/4)+'GTM Funnel'!K46 -> 3.6081204 | ... N8: =M8*Assumptions!$G$56^(1/4)+'GTM Funnel'!N46 -> 6.462139 | P8: =F8 -> 0.71260393 | Q8: =J8 -> 2.6442133 | R8: =N8 -> 6.462139 | S8: =R8 -> 6.462139
A9: Customers — total | B9: customers | C9: =C6+C7+C8 -> 0 | D9: =D6+D7+D8 -> 1.2526644 | E9: =E6+E7+E8 -> 3.4960177 | F9: =F6+F7+F8 -> 5.9031936 | G9: =G6+G7+G8 -> 8.4696228 | H9: =H6+H7+H8 -> 11.755138 | I9: =I6+I7+I8 -> 15.73958 | J9: =J6+J7+J8 -> 21.698725 | ... N9: =N6+N7+N8 -> 52.57338 | P9: =F9 -> 5.9031936 | Q9: =J9 -> 21.698725 | R9: =N9 -> 52.57338 | S9: =R9 -> 52.57338
A10: ARR — SMB (end of quarter) | B10: $ | C10: =0*Assumptions!$G$57^(1/4)+'GTM Funnel'!C44*'GTM Funnel'!$C$9 -> 0 | D10: =C10*Assumptions!$G$57^(1/4)+'GTM Funnel'!D44*'GTM Funnel'!$C$9 -> 3352.13 | E10: =D10*Assumptions!$G$57^(1/4)+'GTM Funnel'!E44*'GTM Funnel'!$C$9 -> 9449.4733 | F10: =E10*Assumptions!$G$57^(1/4)+'GTM Funnel'!F44*'GTM Funnel'!$C$9 -> 16153.733 | G10: =F10*Assumptions!$G$57^(1/4)+'GTM Funnel'!G44*'GTM Funnel'!$C$9 -> 23464.91 | H10: =G10*Assumptions!$G$57^(1/4)+'GTM Funnel'!H44*'GTM Funnel'!$C$9 -> 32892.995 | I10: =H10*Assumptions!$G$57^(1/4)+'GTM Funnel'!I44*'GTM Funnel'!$C$9 -> 44437.988 | J10: =I10*Assumptions!$G$57^(1/4)+'GTM Funnel'!J44*'GTM Funnel'!$C$9 -> 61566.271 | K10: =J10*Assumptions!$G$57^(1/4)+'GTM Funnel'!K44*'GTM Funnel'!$C$9 -> 84277.846 | ... N10: =M10*Assumptions!$G$57^(1/4)+'GTM Funnel'!N44*'GTM Funnel'!$C$9 -> 154233.32 | P10: =F10 -> 16153.733 | Q10: =J10 -> 61566.271 | R10: =N10 -> 154233.32 | S10: =R10 -> 154233.32
A11: ARR — Mid-Market (end of quarter) | B11: $ | C11: =0*Assumptions!$G$58^(1/4)+'GTM Funnel'!C45*'GTM Funnel'!$C$10 -> 0 | D11: =C11*Assumptions!$G$58^(1/4)+'GTM Funnel'!D45*'GTM Funnel'!$C$10 -> 4649.0807 | E11: =D11*Assumptions!$G$58^(1/4)+'GTM Funnel'!E45*'GTM Funnel'!$C$10 -> 13173.727 | F11: =E11*Assumptions!$G$58^(1/4)+'GTM Funnel'!F45*'GTM Funnel'!$C$10 -> 22665.198 | G11: =F11*Assumptions!$G$58^(1/4)+'GTM Funnel'!G45*'GTM Funnel'!$C$10 -> 33137.68 | H11: =G11*Assumptions!$G$58^(1/4)+'GTM Funnel'!H45*'GTM Funnel'!$C$10 -> 46699.78 | I11: =H11*Assumptions!$G$58^(1/4)+'GTM Funnel'!I45*'GTM Funnel'!$C$10 -> 63396.836 | J11: =I11*Assumptions!$G$58^(1/4)+'GTM Funnel'!J45*'GTM Funnel'!$C$10 -> 88082.387 | K11: =J11*Assumptions!$G$58^(1/4)+'GTM Funnel'!K45*'GTM Funnel'!$C$10 -> 120873.66 | ... N11: =M11*Assumptions!$G$58^(1/4)+'GTM Funnel'!N45*'GTM Funnel'!$C$10 -> 224725.29 | P11: =F11 -> 22665.198 | Q11: =J11 -> 88082.387 | R11: =N11 -> 224725.29 | S11: =R11 -> 224725.29
A12: ARR — Enterprise (end of quarter) | B12: $ | C12: =0*Assumptions!$G$59^(1/4)+'GTM Funnel'!C46*'GTM Funnel'!$C$11 -> 0 | D12: =C12*Assumptions!$G$59^(1/4)+'GTM Funnel'!D46*'GTM Funnel'!$C$11 -> 9286.491 | E12: =D12*Assumptions!$G$59^(1/4)+'GTM Funnel'!E46*'GTM Funnel'!$C$11 -> 26508.326 | F12: =E12*Assumptions!$G$59^(1/4)+'GTM Funnel'!F46*'GTM Funnel'!$C$11 -> 46023.893 | G12: =F12*Assumptions!$G$59^(1/4)+'GTM Funnel'!G46*'GTM Funnel'!$C$11 -> 67914.753 | H12: =G12*Assumptions!$G$59^(1/4)+'GTM Funnel'!H46*'GTM Funnel'!$C$11 -> 96448.533 | I12: =H12*Assumptions!$G$59^(1/4)+'GTM Funnel'!I46*'GTM Funnel'!$C$11 -> 131861.44 | J12: =I12*Assumptions!$G$59^(1/4)+'GTM Funnel'!J46*'GTM Funnel'!$C$11 -> 184001.1 | K12: =J12*Assumptions!$G$59^(1/4)+'GTM Funnel'!K46*'GTM Funnel'!$C$11 -> 253462.28 | ... N12: =M12*Assumptions!$G$59^(1/4)+'GTM Funnel'!N46*'GTM Funnel'!$C$11 -> 482245.22 | P12: =F12 -> 46023.893 | Q12: =J12 -> 184001.1 | R12: =N12 -> 482245.22 | S12: =R12 -> 482245.22
A13: ARR — total (end of quarter) | B13: $ | C13: =C10+C11+C12 -> 0 | D13: =D10+D11+D12 -> 17287.702 | E13: =E10+E11+E12 -> 49131.526 | F13: =F10+F11+F12 -> 84842.824 | G13: =G10+G11+G12 -> 124517.34 | H13: =H10+H11+H12 -> 176041.31 | I13: =I10+I11+I12 -> 239696.27 | J13: =J10+J11+J12 -> 333649.76 | ... N13: =N10+N11+N12 -> 861203.84 | P13: =F13 -> 84842.824 | Q13: =J13 -> 333649.76 | R13: =N13 -> 861203.84 | S13: =R13 -> 861203.84
A14: New ARR booked (first-year ACV) | B14: $ | C14: ='GTM Funnel'!C44*'GTM Funnel'!$C$9+'GTM Funnel'!C45*'GTM Funnel'!$C$10+'GTM Funnel'!C46*'GTM Funnel'!$C$11 -> 0 | D14: ='GTM Funnel'!D44*'GTM Funnel'!$C$9+'GTM Funnel'!D45*'GTM Funnel'!$C$10+'GTM Funnel'!D46*'GTM Funnel'!$C$11 -> 17287.702 | E14: ='GTM Funnel'!E44*'GTM Funnel'!$C$9+'GTM Funnel'!E45*'GTM Funnel'!$C$10+'GTM Funnel'!E46*'GTM Funnel'!$C$11 -> 31445.395 | F14: ='GTM Funnel'!F44*'GTM Funnel'!$C$9+'GTM Funnel'!F45*'GTM Funnel'!$C$10+'GTM Funnel'!F46*'GTM Funnel'!$C$11 -> 34575.403 | G14: ='GTM Funnel'!G44*'GTM Funnel'!$C$9+'GTM Funnel'!G45*'GTM Funnel'!$C$10+'GTM Funnel'!G46*'GTM Funnel'!$C$11 -> 37705.412 | H14: ='GTM Funnel'!H44*'GTM Funnel'!$C$9+'GTM Funnel'!H45*'GTM Funnel'!$C$10+'GTM Funnel'!H46*'GTM Funnel'!$C$11 -> 48622.791 | I14: ='GTM Funnel'!I44*'GTM Funnel'!$C$9+'GTM Funnel'!I45*'GTM Funnel'!$C$10+'GTM Funnel'!I46*'GTM Funnel'!$C$11 -> 59540.169 | J14: ='GTM Funnel'!J44*'GTM Funnel'!$C$9+'GTM Funnel'!J45*'GTM Funnel'!$C$10+'GTM Funnel'!J46*'GTM Funnel'!$C$11 -> 88334.479 | ... N14: ='GTM Funnel'!N44*'GTM Funnel'!$C$9+'GTM Funnel'!N45*'GTM Funnel'!$C$10+'GTM Funnel'!N46*'GTM Funnel'!$C$11 -> 120258.8 | P14: =SUM(C14:F14) -> 83308.5 | Q14: =SUM(G14:J14) -> 234202.85 | R14: =SUM(K14:N14) -> 477905.18 | S14: =SUM(P14:R14) -> 795416.53
A15: Net expansion / (contraction) of existing ARR | B15: $ | C15: =C13-0-C14 -> 0 | D15: =D13-C13-D14 -> 0 | E15: =E13-D13-E14 -> 398.42965 | F15: =F13-E13-F14 -> 1135.8943 | G15: =G13-F13-G14 -> 1969.1067 | H15: =H13-G13-H14 -> 2901.1752 | I15: =I13-H13-I14 -> 4114.7897 | J15: =J13-I13-J14 -> 5619.0147 | K15: =K13-J13-K14 -> 7835.2326 | ... N15: =N13-M13-N14 -> 17122.938 | P15: =SUM(C15:F15) -> 1534.324 | Q15: =SUM(G15:J15) -> 14604.086 | R15: =SUM(K15:N15) -> 49648.898 | S15: =SUM(P15:R15) -> 65787.309
A16: Recognized revenue (average ARR ÷ 4) | B16: $ | C16: =(0+C13)/8 -> 0 | D16: =(C13+D13)/8 -> 2160.9627 | E16: =(D13+E13)/8 -> 8302.4035 | F16: =(E13+F13)/8 -> 16746.794 | G16: =(F13+G13)/8 -> 26170.021 | H16: =(G13+H13)/8 -> 37569.831 | I16: =(H13+I13)/8 -> 51967.197 | J16: =(I13+J13)/8 -> 71668.254 | K16: =(J13+K13)/8 -> 99032.943 | ... N16: =(M13+N13)/8 -> 198128.24 | P16: =SUM(C16:F16) -> 27210.16 | Q16: =SUM(G16:J16) -> 187375.3 | R16: =SUM(K16:N16) -> 592380.39 | S16: =SUM(P16:R16) -> 806965.86
A17: Gross profit | B17: $ | C17: =C16*Assumptions!$G$72 -> 0 | D17: =D16*Assumptions!$G$72 -> 1404.6258 | E17: =E16*Assumptions!$G$72 -> 5396.5622 | F17: =F16*Assumptions!$G$72 -> 10885.416 | G17: =G16*Assumptions!$G$72 -> 17010.514 | H17: =H16*Assumptions!$G$72 -> 24420.39 | I17: =I16*Assumptions!$G$72 -> 33778.678 | J17: =J16*Assumptions!$G$72 -> 46584.365 | ... N17: =N16*Assumptions!$G$72 -> 128783.36 | P17: =SUM(C17:F17) -> 17686.604 | Q17: =SUM(G17:J17) -> 121793.95 | R17: =SUM(K17:N17) -> 385047.26 | S17: =SUM(P17:R17) -> 524527.81

Sheet Unit Economics
A1: Unit Economics — incremental cost, program P&L, CAC and payback
A2: Incremental to Clay's existing business: only costs created by the vertical program. CAC basis = sales & marketing; engineering and CS shown separately.
A3: ="Live run: "&Assumptions!$E$4&" scenario · "&Assumptions!$E$5 -> Live run: Base scenario · Partner-led pilot
A5: Incremental cost of the vertical program | B5: Unit / note | C5: Q1 2027 | D5: Q2 2027 | E5: Q3 2027 | F5: Q4 2027 | G5: Q1 2028 | H5: Q2 2028 | I5: Q3 2028 | J5: Q4 2028 | K5: Q1 2029 | L5: Q2 2029 | M5: Q3 2029 | N5: Q4 2029 | P5: 2027 | Q5: 2028 | R5: 2029 | S5: 2027–29
A6: FTE — vertical lead | B6: FTE | C6: =Assumptions!$G$92*'GTM Funnel'!C19 -> 1 | D6: =Assumptions!$G$92*'GTM Funnel'!D19 -> 1 | E6: =Assumptions!$G$92*'GTM Funnel'!E19 -> 1 | F6: =Assumptions!$G$92*'GTM Funnel'!F19 -> 1 | G6: =Assumptions!$G$92*'GTM Funnel'!G19 -> 1 | H6: =Assumptions!$G$92*'GTM Funnel'!H19 -> 1 | I6: =Assumptions!$G$92*'GTM Funnel'!I19 -> 1 | J6: =Assumptions!$G$92*'GTM Funnel'!J19 -> 1 | ... N6: =Assumptions!$G$92*'GTM Funnel'!N19 -> 1 | P6: =AVERAGE(C6:F6) -> 1 | Q6: =AVERAGE(G6:J6) -> 1 | R6: =AVERAGE(K6:N6) -> 1
A7: FTE — dedicated AEs | B7: FTE | C7: ='GTM Funnel'!C38*'GTM Funnel'!C19 -> 0 | D7: ='GTM Funnel'!D38*'GTM Funnel'!D19 -> 0 | E7: ='GTM Funnel'!E38*'GTM Funnel'!E19 -> 0 | F7: ='GTM Funnel'!F38*'GTM Funnel'!F19 -> 0 | G7: ='GTM Funnel'!G38*'GTM Funnel'!G19 -> 0 | H7: ='GTM Funnel'!H38*'GTM Funnel'!H19 -> 0 | I7: ='GTM Funnel'!I38*'GTM Funnel'!I19 -> 0 | J7: ='GTM Funnel'!J38*'GTM Funnel'!J19 -> 0 | ... N7: ='GTM Funnel'!N38*'GTM Funnel'!N19 -> 0 | P7: =AVERAGE(C7:F7) -> 0 | Q7: =AVERAGE(G7:J7) -> 0 | R7: =AVERAGE(K7:N7) -> 0
A8: FTE — partner managers | B8: FTE | C8: =IF('GTM Funnel'!C18<=4,Assumptions!$G$93,Assumptions!$G$94)*'GTM Funnel'!C19 -> 0 | D8: =IF('GTM Funnel'!D18<=4,Assumptions!$G$93,Assumptions!$G$94)*'GTM Funnel'!D19 -> 0 | E8: =IF('GTM Funnel'!E18<=4,Assumptions!$G$93,Assumptions!$G$94)*'GTM Funnel'!E19 -> 0 | F8: =IF('GTM Funnel'!F18<=4,Assumptions!$G$93,Assumptions!$G$94)*'GTM Funnel'!F19 -> 0 | G8: =IF('GTM Funnel'!G18<=4,Assumptions!$G$93,Assumptions!$G$94)*'GTM Funnel'!G19 -> 0.5 | H8: =IF('GTM Funnel'!H18<=4,Assumptions!$G$93,Assumptions!$G$94)*'GTM Funnel'!H19 -> 0.5 | I8: =IF('GTM Funnel'!I18<=4,Assumptions!$G$93,Assumptions!$G$94)*'GTM Funnel'!I19 -> 0.5 | J8: =IF('GTM Funnel'!J18<=4,Assumptions!$G$93,Assumptions!$G$94)*'GTM Funnel'!J19 -> 0.5 | ... N8: =IF('GTM Funnel'!N18<=4,Assumptions!$G$93,Assumptions!$G$94)*'GTM Funnel'!N19 -> 0.5 | P8: =AVERAGE(C8:F8) -> 0 | Q8: =AVERAGE(G8:J8) -> 0.5 | R8: =AVERAGE(K8:N8) -> 0.5
A9: FTE — GTM / solutions engineers | B9: FTE | C9: =IF('GTM Funnel'!C18<=4,Assumptions!$G$95,Assumptions!$G$96)*'GTM Funnel'!C19 -> 1 | D9: =IF('GTM Funnel'!D18<=4,Assumptions!$G$95,Assumptions!$G$96)*'GTM Funnel'!D19 -> 1 | E9: =IF('GTM Funnel'!E18<=4,Assumptions!$G$95,Assumptions!$G$96)*'GTM Funnel'!E19 -> 1 | F9: =IF('GTM Funnel'!F18<=4,Assumptions!$G$95,Assumptions!$G$96)*'GTM Funnel'!F19 -> 1 | G9: =IF('GTM Funnel'!G18<=4,Assumptions!$G$95,Assumptions!$G$96)*'GTM Funnel'!G19 -> 0.5 | H9: =IF('GTM Funnel'!H18<=4,Assumptions!$G$95,Assumptions!$G$96)*'GTM Funnel'!H19 -> 0.5 | I9: =IF('GTM Funnel'!I18<=4,Assumptions!$G$95,Assumptions!$G$96)*'GTM Funnel'!I19 -> 0.5 | J9: =IF('GTM Funnel'!J18<=4,Assumptions!$G$95,Assumptions!$G$96)*'GTM Funnel'!J19 -> 0.5 | ... N9: =IF('GTM Funnel'!N18<=4,Assumptions!$G$95,Assumptions!$G$96)*'GTM Funnel'!N19 -> 0.5 | P9: =AVERAGE(C9:F9) -> 1 | Q9: =AVERAGE(G9:J9) -> 0.5 | R9: =AVERAGE(K9:N9) -> 0.5
A10: FTE — product marketing | B10: FTE | C10: =Assumptions!$G$97*'GTM Funnel'!C19 -> 0.25 | D10: =Assumptions!$G$97*'GTM Funnel'!D19 -> 0.25 | E10: =Assumptions!$G$97*'GTM Funnel'!E19 -> 0.25 | F10: =Assumptions!$G$97*'GTM Funnel'!F19 -> 0.25 | G10: =Assumptions!$G$97*'GTM Funnel'!G19 -> 0.25 | H10: =Assumptions!$G$97*'GTM Funnel'!H19 -> 0.25 | I10: =Assumptions!$G$97*'GTM Funnel'!I19 -> 0.25 | J10: =Assumptions!$G$97*'GTM Funnel'!J19 -> 0.25 | ... N10: =Assumptions!$G$97*'GTM Funnel'!N19 -> 0.25 | P10: =AVERAGE(C10:F10) -> 0.25 | Q10: =AVERAGE(G10:J10) -> 0.25 | R10: =AVERAGE(K10:N10) -> 0.25
A11: FTE — customer success (coverage ratios) | B11: FTE | C11: =('Revenue Model'!C7+'Revenue Model'!C8)/Assumptions!$G$70+'Revenue Model'!C6/Assumptions!$G$71 -> 0 | D11: =('Revenue Model'!D7+'Revenue Model'!D8)/Assumptions!$G$70+'Revenue Model'!D6/Assumptions!$G$71 -> 0.018163634 | E11: =('Revenue Model'!E7+'Revenue Model'!E8)/Assumptions!$G$70+'Revenue Model'!E6/Assumptions!$G$71 -> 0.050736613 | F11: =('Revenue Model'!F7+'Revenue Model'!F8)/Assumptions!$G$70+'Revenue Model'!F6/Assumptions!$G$71 -> 0.085763247 | G11: =('Revenue Model'!G7+'Revenue Model'!G8)/Assumptions!$G$70+'Revenue Model'!G6/Assumptions!$G$71 -> 0.12318095 | H11: =('Revenue Model'!H7+'Revenue Model'!H8)/Assumptions!$G$70+'Revenue Model'!H6/Assumptions!$G$71 -> 0.17111069 | I11: =('Revenue Model'!I7+'Revenue Model'!I8)/Assumptions!$G$70+'Revenue Model'!I6/Assumptions!$G$71 -> 0.2292833 | J11: =('Revenue Model'!J7+'Revenue Model'!J8)/Assumptions!$G$70+'Revenue Model'!J6/Assumptions!$G$71 -> 0.31621934 | ... N11: =('Revenue Model'!N7+'Revenue Model'!N8)/Assumptions!$G$70+'Revenue Model'!N6/Assumptions!$G$71 -> 0.76832178 | P11: =AVERAGE(C11:F11) -> 0.038665874 | Q11: =AVERAGE(G11:J11) -> 0.20994857 | R11: =AVERAGE(K11:N11) -> 0.60120878
A12: Cost — vertical lead + partner managers | B12: $ | C12: =(C6+C8)*Assumptions!$G$66/Assumptions!$G$65/4 -> 66753.571 | D12: =(D6+D8)*Assumptions!$G$66/Assumptions!$G$65/4 -> 66753.571 | E12: =(E6+E8)*Assumptions!$G$66/Assumptions!$G$65/4 -> 66753.571 | F12: =(F6+F8)*Assumptions!$G$66/Assumptions!$G$65/4 -> 66753.571 | G12: =(G6+G8)*Assumptions!$G$66/Assumptions!$G$65/4 -> 100130.36 | H12: =(H6+H8)*Assumptions!$G$66/Assumptions!$G$65/4 -> 100130.36 | I12: =(I6+I8)*Assumptions!$G$66/Assumptions!$G$65/4 -> 100130.36 | J12: =(J6+J8)*Assumptions!$G$66/Assumptions!$G$65/4 -> 100130.36 | ... N12: =(N6+N8)*Assumptions!$G$66/Assumptions!$G$65/4 -> 100130.36 | P12: =SUM(C12:F12) -> 267014.29 | Q12: =SUM(G12:J12) -> 400521.43 | R12: =SUM(K12:N12) -> 400521.43 | S12: =SUM(P12:R12) -> 1068057.1
A13: Cost — dedicated AEs | B13: $ | C13: =C7*'GTM Funnel'!$C$14/4 -> 0 | D13: =D7*'GTM Funnel'!$C$14/4 -> 0 | E13: =E7*'GTM Funnel'!$C$14/4 -> 0 | F13: =F7*'GTM Funnel'!$C$14/4 -> 0 | G13: =G7*'GTM Funnel'!$C$14/4 -> 0 | H13: =H7*'GTM Funnel'!$C$14/4 -> 0 | I13: =I7*'GTM Funnel'!$C$14/4 -> 0 | J13: =J7*'GTM Funnel'!$C$14/4 -> 0 | ... N13: =N7*'GTM Funnel'!$C$14/4 -> 0 | P13: =SUM(C13:F13) -> 0 | Q13: =SUM(G13:J13) -> 0 | R13: =SUM(K13:N13) -> 0 | S13: =SUM(P13:R13) -> 0
A14: Cost — variable AE cost (shared capacity deals) | B14: $ | C14: =MAX(0,'GTM Funnel'!C41-'GTM Funnel'!C39*'GTM Funnel'!$C$15)*'GTM Funnel'!$C$16*Assumptions!$G$100 -> 0 | D14: =MAX(0,'GTM Funnel'!D41-'GTM Funnel'!D39*'GTM Funnel'!$C$15)*'GTM Funnel'!$C$16*Assumptions!$G$100 -> 7595.1313 | E14: =MAX(0,'GTM Funnel'!E41-'GTM Funnel'!E39*'GTM Funnel'!$C$15)*'GTM Funnel'!$C$16*Assumptions!$G$100 -> 13815.133 | F14: =MAX(0,'GTM Funnel'!F41-'GTM Funnel'!F39*'GTM Funnel'!$C$15)*'GTM Funnel'!$C$16*Assumptions!$G$100 -> 15190.263 | G14: =MAX(0,'GTM Funnel'!G41-'GTM Funnel'!G39*'GTM Funnel'!$C$15)*'GTM Funnel'!$C$16*Assumptions!$G$100 -> 16565.392 | H14: =MAX(0,'GTM Funnel'!H41-'GTM Funnel'!H39*'GTM Funnel'!$C$15)*'GTM Funnel'!$C$16*Assumptions!$G$100 -> 21361.803 | I14: =MAX(0,'GTM Funnel'!I41-'GTM Funnel'!I39*'GTM Funnel'!$C$15)*'GTM Funnel'!$C$16*Assumptions!$G$100 -> 26158.214 | J14: =MAX(0,'GTM Funnel'!J41-'GTM Funnel'!J39*'GTM Funnel'!$C$15)*'GTM Funnel'!$C$16*Assumptions!$G$100 -> 38808.627 | ... N14: =MAX(0,'GTM Funnel'!N41-'GTM Funnel'!N39*'GTM Funnel'!$C$15)*'GTM Funnel'!$C$16*Assumptions!$G$100 -> 52834.169 | P14: =SUM(C14:F14) -> 36600.527 | Q14: =SUM(G14:J14) -> 102894.04 | R14: =SUM(K14:N14) -> 209961.55 | S14: =SUM(P14:R14) -> 349456.11
A15: Cost — product marketing | B15: $ | C15: =C10*Assumptions!$G$67/Assumptions!$G$65/4 -> 18475.893 | D15: =D10*Assumptions!$G$67/Assumptions!$G$65/4 -> 18475.893 | E15: =E10*Assumptions!$G$67/Assumptions!$G$65/4 -> 18475.893 | F15: =F10*Assumptions!$G$67/Assumptions!$G$65/4 -> 18475.893 | G15: =G10*Assumptions!$G$67/Assumptions!$G$65/4 -> 18475.893 | H15: =H10*Assumptions!$G$67/Assumptions!$G$65/4 -> 18475.893 | I15: =I10*Assumptions!$G$67/Assumptions!$G$65/4 -> 18475.893 | J15: =J10*Assumptions!$G$67/Assumptions!$G$65/4 -> 18475.893 | ... N15: =N10*Assumptions!$G$67/Assumptions!$G$65/4 -> 18475.893 | P15: =SUM(C15:F15) -> 73903.571 | Q15: =SUM(G15:J15) -> 73903.571 | R15: =SUM(K15:N15) -> 73903.571 | S15: =SUM(P15:R15) -> 221710.71
A16: Cost — program and launch marketing | B16: $ | C16: =(Assumptions!$G$98+Assumptions!$G$73*(('GTM Funnel'!C18=Assumptions!$G$12)+('GTM Funnel'!C18=Assumptions!$G$13)+('GTM Funnel'!C18=Assumptions!$G$14)))*'GTM Funnel'!C19 -> 65000 | D16: =(Assumptions!$G$98+Assumptions!$G$73*(('GTM Funnel'!D18=Assumptions!$G$12)+('GTM Funnel'!D18=Assumptions!$G$13)+('GTM Funnel'!D18=Assumptions!$G$14)))*'GTM Funnel'!D19 -> 25000 | E16: =(Assumptions!$G$98+Assumptions!$G$73*(('GTM Funnel'!E18=Assumptions!$G$12)+('GTM Funnel'!E18=Assumptions!$G$13)+('GTM Funnel'!E18=Assumptions!$G$14)))*'GTM Funnel'!E19 -> 25000 | F16: =(Assumptions!$G$98+Assumptions!$G$73*(('GTM Funnel'!F18=Assumptions!$G$12)+('GTM Funnel'!F18=Assumptions!$G$13)+('GTM Funnel'!F18=Assumptions!$G$14)))*'GTM Funnel'!F19 -> 25000 | G16: =(Assumptions!$G$98+Assumptions!$G$73*(('GTM Funnel'!G18=Assumptions!$G$12)+('GTM Funnel'!G18=Assumptions!$G$13)+('GTM Funnel'!G18=Assumptions!$G$14)))*'GTM Funnel'!G19 -> 65000 | H16: =(Assumptions!$G$98+Assumptions!$G$73*(('GTM Funnel'!H18=Assumptions!$G$12)+('GTM Funnel'!H18=Assumptions!$G$13)+('GTM Funnel'!H18=Assumptions!$G$14)))*'GTM Funnel'!H19 -> 25000 | I16: =(Assumptions!$G$98+Assumptions!$G$73*(('GTM Funnel'!I18=Assumptions!$G$12)+('GTM Funnel'!I18=Assumptions!$G$13)+('GTM Funnel'!I18=Assumptions!$G$14)))*'GTM Funnel'!I19 -> 65000 | J16: =(Assumptions!$G$98+Assumptions!$G$73*(('GTM Funnel'!J18=Assumptions!$G$12)+('GTM Funnel'!J18=Assumptions!$G$13)+('GTM Funnel'!J18=Assumptions!$G$14)))*'GTM Funnel'!J19 -> 25000 | ... N16: =(Assumptions!$G$98+Assumptions!$G$73*(('GTM Funnel'!N18=Assumptions!$G$12)+('GTM Funnel'!N18=Assumptions!$G$13)+('GTM Funnel'!N18=Assumptions!$G$14)))*'GTM Funnel'!N19 -> 25000 | P16: =SUM(C16:F16) -> 140000 | Q16: =SUM(G16:J16) -> 180000 | R16: =SUM(K16:N16) -> 100000 | S16: =SUM(P16:R16) -> 420000
A17: Cost — partner fees on partner-sourced ACV | B17: $ | C17: ='Revenue Model'!C14*'GTM Funnel'!C35*Assumptions!$G$74 -> 0 | D17: ='Revenue Model'!D14*'GTM Funnel'!D35*Assumptions!$G$74 -> 1252.0035 | E17: ='Revenue Model'!E14*'GTM Funnel'!E35*Assumptions!$G$74 -> 1878.0053 | F17: ='Revenue Model'!F14*'GTM Funnel'!F35*Assumptions!$G$74 -> 2504.0071 | G17: ='Revenue Model'!G14*'GTM Funnel'!G35*Assumptions!$G$74 -> 3130.0088 | H17: ='Revenue Model'!H14*'GTM Funnel'!H35*Assumptions!$G$74 -> 3756.0106 | I17: ='Revenue Model'!I14*'GTM Funnel'!I35*Assumptions!$G$74 -> 4382.0124 | J17: ='Revenue Model'!J14*'GTM Funnel'!J35*Assumptions!$G$74 -> 5008.0141 | ... N17: ='Revenue Model'!N14*'GTM Funnel'!N35*Assumptions!$G$74 -> 6260.0177 | P17: =SUM(C17:F17) -> 5634.0159 | Q17: =SUM(G17:J17) -> 16276.046 | R17: =SUM(K17:N17) -> 24414.069 | S17: =SUM(P17:R17) -> 46324.131
A18: Cost — partner enablement | B18: $ | C18: ='GTM Funnel'!C27*Assumptions!$G$75 -> 4000 | D18: ='GTM Funnel'!D27*Assumptions!$G$75 -> 6000 | E18: ='GTM Funnel'!E27*Assumptions!$G$75 -> 8000 | F18: ='GTM Funnel'!F27*Assumptions!$G$75 -> 10000 | G18: ='GTM Funnel'!G27*Assumptions!$G$75 -> 12000 | H18: ='GTM Funnel'!H27*Assumptions!$G$75 -> 14000 | I18: ='GTM Funnel'!I27*Assumptions!$G$75 -> 16000 | J18: ='GTM Funnel'!J27*Assumptions!$G$75 -> 18000 | ... N18: ='GTM Funnel'!N27*Assumptions!$G$75 -> 20000 | P18: =SUM(C18:F18) -> 28000 | Q18: =SUM(G18:J18) -> 60000 | R18: =SUM(K18:N18) -> 80000 | S18: =SUM(P18:R18) -> 168000
A19: Cost — onboarding / co-build subsidy (MM & Ent) | B19: $ | C19: =('GTM Funnel'!C45*'GTM Funnel'!$C$10+'GTM Funnel'!C46*'GTM Funnel'!$C$11)*Assumptions!$G$76 -> 0 | D19: =('GTM Funnel'!D45*'GTM Funnel'!$C$10+'GTM Funnel'!D46*'GTM Funnel'!$C$11)*Assumptions!$G$76 -> 2090.3358 | E19: =('GTM Funnel'!E45*'GTM Funnel'!$C$10+'GTM Funnel'!E46*'GTM Funnel'!$C$11)*Assumptions!$G$76 -> 3802.2077 | F19: =('GTM Funnel'!F45*'GTM Funnel'!$C$10+'GTM Funnel'!F46*'GTM Funnel'!$C$11)*Assumptions!$G$76 -> 4180.6715 | G19: =('GTM Funnel'!G45*'GTM Funnel'!$C$10+'GTM Funnel'!G46*'GTM Funnel'!$C$11)*Assumptions!$G$76 -> 4559.1353 | H19: =('GTM Funnel'!H45*'GTM Funnel'!$C$10+'GTM Funnel'!H46*'GTM Funnel'!$C$11)*Assumptions!$G$76 -> 5879.2059 | I19: =('GTM Funnel'!I45*'GTM Funnel'!$C$10+'GTM Funnel'!I46*'GTM Funnel'!$C$11)*Assumptions!$G$76 -> 7199.2765 | J19: =('GTM Funnel'!J45*'GTM Funnel'!$C$10+'GTM Funnel'!J46*'GTM Funnel'!$C$11)*Assumptions!$G$76 -> 10680.929 | ... N19: =('GTM Funnel'!N45*'GTM Funnel'!$C$10+'GTM Funnel'!N46*'GTM Funnel'!$C$11)*Assumptions!$G$76 -> 14541.046 | P19: =SUM(C19:F19) -> 10073.215 | Q19: =SUM(G19:J19) -> 28318.547 | R19: =SUM(K19:N19) -> 57785.719 | S19: =SUM(P19:R19) -> 96177.481
A20: Sales & marketing cost (CAC basis) | B20: $ | C20: =C12+C13+C14+C15+C16+C17+C18+C19 -> 154229.46 | D20: =D12+D13+D14+D15+D16+D17+D18+D19 -> 127166.93 | E20: =E12+E13+E14+E15+E16+E17+E18+E19 -> 137724.81 | F20: =F12+F13+F14+F15+F16+F17+F18+F19 -> 142104.41 | G20: =G12+G13+G14+G15+G16+G17+G18+G19 -> 219860.79 | H20: =H12+H13+H14+H15+H16+H17+H18+H19 -> 188603.27 | I20: =I12+I13+I14+I15+I16+I17+I18+I19 -> 237345.75 | J20: =J12+J13+J14+J15+J16+J17+J18+J19 -> 216103.82 | ... N20: =N12+N13+N14+N15+N16+N17+N18+N19 -> 237241.48 | P20: =SUM(C20:F20) -> 561225.61 | Q20: =SUM(G20:J20) -> 861913.63 | R20: =SUM(K20:N20) -> 946586.33 | S20: =SUM(P20:R20) -> 2369725.6
A21: Cost — GTM / solutions engineers | B21: $ | C21: =C9*Assumptions!$G$68/Assumptions!$G$65/4 -> 56535.714 | D21: =D9*Assumptions!$G$68/Assumptions!$G$65/4 -> 56535.714 | E21: =E9*Assumptions!$G$68/Assumptions!$G$65/4 -> 56535.714 | F21: =F9*Assumptions!$G$68/Assumptions!$G$65/4 -> 56535.714 | G21: =G9*Assumptions!$G$68/Assumptions!$G$65/4 -> 28267.857 | H21: =H9*Assumptions!$G$68/Assumptions!$G$65/4 -> 28267.857 | I21: =I9*Assumptions!$G$68/Assumptions!$G$65/4 -> 28267.857 | J21: =J9*Assumptions!$G$68/Assumptions!$G$65/4 -> 28267.857 | ... N21: =N9*Assumptions!$G$68/Assumptions!$G$65/4 -> 28267.857 | P21: =SUM(C21:F21) -> 226142.86 | Q21: =SUM(G21:J21) -> 113071.43 | R21: =SUM(K21:N21) -> 113071.43 | S21: =SUM(P21:R21) -> 452285.71
A22: Cost — template & ERP-connector build (one-time) | B22: $ | C22: =IF('GTM Funnel'!C18<=Assumptions!$G$78,Assumptions!$G$77/Assumptions!$G$78,0) -> 62500 | D22: =IF('GTM Funnel'!D18<=Assumptions!$G$78,Assumptions!$G$77/Assumptions!$G$78,0) -> 62500 | E22: =IF('GTM Funnel'!E18<=Assumptions!$G$78,Assumptions!$G$77/Assumptions!$G$78,0) -> 62500 | F22: =IF('GTM Funnel'!F18<=Assumptions!$G$78,Assumptions!$G$77/Assumptions!$G$78,0) -> 62500 | G22: =IF('GTM Funnel'!G18<=Assumptions!$G$78,Assumptions!$G$77/Assumptions!$G$78,0) -> 0 | H22: =IF('GTM Funnel'!H18<=Assumptions!$G$78,Assumptions!$G$77/Assumptions!$G$78,0) -> 0 | I22: =IF('GTM Funnel'!I18<=Assumptions!$G$78,Assumptions!$G$77/Assumptions!$G$78,0) -> 0 | J22: =IF('GTM Funnel'!J18<=Assumptions!$G$78,Assumptions!$G$77/Assumptions!$G$78,0) -> 0 | ... N22: =IF('GTM Funnel'!N18<=Assumptions!$G$78,Assumptions!$G$77/Assumptions!$G$78,0) -> 0 | P22: =SUM(C22:F22) -> 250000 | Q22: =SUM(G22:J22) -> 0 | R22: =SUM(K22:N22) -> 0 | S22: =SUM(P22:R22) -> 250000
A23: Cost — customer success | B23: $ | C23: =C11*Assumptions!$G$69/Assumptions!$G$65/4 -> 0 | D23: =D11*Assumptions!$G$69/Assumptions!$G$65/4 -> 729.85375 | E23: =E11*Assumptions!$G$69/Assumptions!$G$65/4 -> 2038.7058 | F23: =F11*Assumptions!$G$69/Assumptions!$G$65/4 -> 3446.1511 | G23: =G11*Assumptions!$G$69/Assumptions!$G$65/4 -> 4949.6744 | H23: =H11*Assumptions!$G$69/Assumptions!$G$65/4 -> 6875.594 | I23: =I11*Assumptions!$G$69/Assumptions!$G$65/4 -> 9213.0943 | J23: =J11*Assumptions!$G$69/Assumptions!$G$65/4 -> 12706.371 | ... N23: =N11*Assumptions!$G$69/Assumptions!$G$65/4 -> 30872.816 | P23: =SUM(C23:F23) -> 6214.7106 | Q23: =SUM(G23:J23) -> 33744.733 | R23: =SUM(K23:N23) -> 96631.428 | S23: =SUM(P23:R23) -> 136590.87
A24: Total incremental program cost (excl. COGS) | B24: $ | C24: =C20+C21+C22+C23 -> 273265.18 | D24: =D20+D21+D22+D23 -> 246932.5 | E24: =E20+E21+E22+E23 -> 258799.23 | F24: =F20+F21+F22+F23 -> 264586.27 | G24: =G20+G21+G22+G23 -> 253078.32 | H24: =H20+H21+H22+H23 -> 223746.72 | I24: =I20+I21+I22+I23 -> 274826.7 | J24: =J20+J21+J22+J23 -> 257078.05 | ... N24: =N20+N21+N22+N23 -> 296382.15 | P24: =SUM(C24:F24) -> 1043583.2 | Q24: =SUM(G24:J24) -> 1008729.8 | R24: =SUM(K24:N24) -> 1156289.2 | S24: =SUM(P24:R24) -> 3208602.2
A25: Program P&L and unit economics | B25: Unit / note | C25: Q1 2027 | D25: Q2 2027 | E25: Q3 2027 | F25: Q4 2027 | G25: Q1 2028 | H25: Q2 2028 | I25: Q3 2028 | J25: Q4 2028 | K25: Q1 2029 | L25: Q2 2029 | M25: Q3 2029 | N25: Q4 2029 | P25: 2027 | Q25: 2028 | R25: 2029 | S25: 2027–29
A26: Gross profit (from Revenue Model) | B26: $ | C26: ='Revenue Model'!C17 -> 0 | D26: ='Revenue Model'!D17 -> 1404.6258 | E26: ='Revenue Model'!E17 -> 5396.5622 | F26: ='Revenue Model'!F17 -> 10885.416 | G26: ='Revenue Model'!G17 -> 17010.514 | H26: ='Revenue Model'!H17 -> 24420.39 | I26: ='Revenue Model'!I17 -> 33778.678 | J26: ='Revenue Model'!J17 -> 46584.365 | ... N26: ='Revenue Model'!N17 -> 128783.36 | P26: =SUM(C26:F26) -> 17686.604 | Q26: =SUM(G26:J26) -> 121793.95 | R26: =SUM(K26:N26) -> 385047.26 | S26: =SUM(P26:R26) -> 524527.81
A27: Contribution after customer success | B27: $ | C27: ='Revenue Model'!C17-C23 -> 0 | D27: ='Revenue Model'!D17-D23 -> 674.77201 | E27: ='Revenue Model'!E17-E23 -> 3357.8564 | F27: ='Revenue Model'!F17-F23 -> 7439.2649 | G27: ='Revenue Model'!G17-G23 -> 12060.839 | H27: ='Revenue Model'!H17-H23 -> 17544.796 | I27: ='Revenue Model'!I17-I23 -> 24565.584 | J27: ='Revenue Model'!J17-J23 -> 33877.994 | ... N27: ='Revenue Model'!N17-N23 -> 97910.542 | P27: =SUM(C27:F27) -> 11471.893 | Q27: =SUM(G27:J27) -> 88049.213 | R27: =SUM(K27:N27) -> 288415.83 | S27: =SUM(P27:R27) -> 387936.93
A28: Program P&L (gross profit − all incremental cost) | B28: $ | C28: ='Revenue Model'!C17-C24 -> -273265.18 | D28: ='Revenue Model'!D17-D24 -> -245527.88 | E28: ='Revenue Model'!E17-E24 -> -253402.67 | F28: ='Revenue Model'!F17-F24 -> -253700.85 | G28: ='Revenue Model'!G17-G24 -> -236067.8 | H28: ='Revenue Model'!H17-H24 -> -199326.33 | I28: ='Revenue Model'!I17-I24 -> -241048.03 | J28: ='Revenue Model'!J17-J24 -> -210493.68 | ... N28: ='Revenue Model'!N17-N24 -> -167598.8 | P28: =SUM(C28:F28) -> -1025896.6 | Q28: =SUM(G28:J28) -> -886935.84 | R28: =SUM(K28:N28) -> -771241.93 | S28: =SUM(P28:R28) -> -2684074.4
A29: Cumulative program P&L (investment position) | B29: $ | C29: =0+C28 -> -273265.18 | D29: =C29+D28 -> -518793.06 | E29: =D29+E28 -> -772195.72 | F29: =E29+F28 -> -1025896.6 | G29: =F29+G28 -> -1261964.4 | H29: =G29+H28 -> -1461290.7 | I29: =H29+I28 -> -1702338.7 | J29: =I29+J28 -> -1912832.4 | K29: =J29+K28 -> -2128916.6 | ... N29: =M29+N28 -> -2684074.4 | P29: =F29 -> -1025896.6 | Q29: =J29 -> -1912832.4 | R29: =N29 -> -2684074.4 | S29: =R29 -> -2684074.4
A30: Helper: quarter number if P&L > 0, else 99 | B30: # | C30: =IF(AND(C28>0,'GTM Funnel'!C19=1),'GTM Funnel'!C18,99) -> 99 | D30: =IF(AND(D28>0,'GTM Funnel'!D19=1),'GTM Funnel'!D18,99) -> 99 | E30: =IF(AND(E28>0,'GTM Funnel'!E19=1),'GTM Funnel'!E18,99) -> 99 | F30: =IF(AND(F28>0,'GTM Funnel'!F19=1),'GTM Funnel'!F18,99) -> 99 | G30: =IF(AND(G28>0,'GTM Funnel'!G19=1),'GTM Funnel'!G18,99) -> 99 | H30: =IF(AND(H28>0,'GTM Funnel'!H19=1),'GTM Funnel'!H18,99) -> 99 | I30: =IF(AND(I28>0,'GTM Funnel'!I19=1),'GTM Funnel'!I18,99) -> 99 | J30: =IF(AND(J28>0,'GTM Funnel'!J19=1),'GTM Funnel'!J18,99) -> 99 | ... N30: =IF(AND(N28>0,'GTM Funnel'!N19=1),'GTM Funnel'!N18,99) -> 99
A31: CAC (S&M ÷ new customers) | B31: $ | C31: =IFERROR(C20/'GTM Funnel'!C43,0) -> 0 | D31: =IFERROR(D20/'GTM Funnel'!D43,0) -> 101517.16 | E31: =IFERROR(E20/'GTM Funnel'!E43,0) -> 60444.619 | F31: =IFERROR(F20/'GTM Funnel'!F43,0) -> 56720.859 | G31: =IFERROR(G20/'GTM Funnel'!G43,0) -> 80472.334 | H31: =IFERROR(H20/'GTM Funnel'!H43,0) -> 53531.8 | I31: =IFERROR(I20/'GTM Funnel'!I43,0) -> 55014.087 | J31: =IFERROR(J20/'GTM Funnel'!J43,0) -> 33762.509 | ... N31: =IFERROR(N20/'GTM Funnel'!N43,0) -> 27225.527 | P31: =IFERROR(P20/'GTM Funnel'!P43*1,0) -> 92971.681 | Q31: =IFERROR(Q20/'GTM Funnel'!Q43*1,0) -> 50789.517 | R31: =IFERROR(R20/'GTM Funnel'!R43*1,0) -> 27335.121 | S31: =IFERROR(S20/'GTM Funnel'!S43*1,0) -> 41115.536
A32: Average first-year ACV of new customers | B32: $ | C32: =IFERROR('Revenue Model'!C14/'GTM Funnel'!C43,0) -> 0 | D32: =IFERROR('Revenue Model'!D14/'GTM Funnel'!D43,0) -> 13800.744 | E32: =IFERROR('Revenue Model'!E14/'GTM Funnel'!E43,0) -> 13800.744 | F32: =IFERROR('Revenue Model'!F14/'GTM Funnel'!F43,0) -> 13800.744 | G32: =IFERROR('Revenue Model'!G14/'GTM Funnel'!G43,0) -> 13800.744 | H32: =IFERROR('Revenue Model'!H14/'GTM Funnel'!H43,0) -> 13800.744 | I32: =IFERROR('Revenue Model'!I14/'GTM Funnel'!I43,0) -> 13800.744 | J32: =IFERROR('Revenue Model'!J14/'GTM Funnel'!J43,0) -> 13800.744 | ... N32: =IFERROR('Revenue Model'!N14/'GTM Funnel'!N43,0) -> 13800.744 | P32: =IFERROR('Revenue Model'!P14/'GTM Funnel'!P43*1,0) -> 13800.744 | Q32: =IFERROR('Revenue Model'!Q14/'GTM Funnel'!Q43*1,0) -> 13800.744 | R32: =IFERROR('Revenue Model'!R14/'GTM Funnel'!R43*1,0) -> 13800.744 | S32: =IFERROR('Revenue Model'!S14/'GTM Funnel'!S43*1,0) -> 13800.744
A33: CAC payback (months of gross profit) | B33: months | C33: =IFERROR(C31/(C32*Assumptions!$G$72/12),0) -> 0 | D33: =IFERROR(D31/(D32*Assumptions!$G$72/12),0) -> 135.80158 | E33: =IFERROR(E31/(E32*Assumptions!$G$72/12),0) -> 80.858005 | F33: =IFERROR(F31/(F32*Assumptions!$G$72/12),0) -> 75.876655 | G33: =IFERROR(G31/(G32*Assumptions!$G$72/12),0) -> 107.64949 | H33: =IFERROR(H31/(H32*Assumptions!$G$72/12),0) -> 71.610585 | I33: =IFERROR(I31/(I32*Assumptions!$G$72/12),0) -> 73.593471 | J33: =IFERROR(J31/(J32*Assumptions!$G$72/12),0) -> 45.164799 | ... N33: =IFERROR(N31/(N32*Assumptions!$G$72/12),0) -> 36.420145 | P33: =IFERROR(P31/(P32*Assumptions!$G$72/12),0) -> 124.37012 | Q33: =IFERROR(Q31/(Q32*Assumptions!$G$72/12),0) -> 67.942177 | R33: =IFERROR(R31/(R32*Assumptions!$G$72/12),0) -> 36.566752 | S33: =IFERROR(S31/(S32*Assumptions!$G$72/12),0) -> 55.001095
A34: ARR-weighted blended GRR (new-customer mix) | C34: =(Assumptions!$G$29*'GTM Funnel'!$C$9*Assumptions!$G$54+Assumptions!$G$30*'GTM Funnel'!$C$10*Assumptions!$G$55+Assumptions!$G$31*'GTM Funnel'!$C$11*Assumptions!$G$56)/(Assumptions!$G$29*'GTM Funnel'!$C$9+Assumptions!$G$30*'GTM Funnel'!$C$10+Assumptions!$G$31*'GTM Funnel'!$C$11) -> 0.90686541
A35: Key outputs of this run | B35: Unit / note | C35: Q1 2027 | D35: Q2 2027 | E35: Q3 2027 | F35: Q4 2027 | G35: Q1 2028 | H35: Q2 2028 | I35: Q3 2028 | J35: Q4 2028 | K35: Q1 2029 | L35: Q2 2029 | M35: Q3 2029 | N35: Q4 2029 | P35: 2027 | Q35: 2028 | R35: 2029 | S35: 2027–29
A36: Exit ARR, Q4 2029 | C36: ='Revenue Model'!N13 -> 861203.84
A37: Customers, Q4 2029 | C37: ='Revenue Model'!N9 -> 52.57338
A38: New customers 2027–29 | C38: ='GTM Funnel'!S43 -> 57.63577
A39: Recognized revenue 2027–29 | C39: ='Revenue Model'!S16 -> 806965.86
A40: S&M cost 2027–29 | C40: =S20 -> 2369725.6
A41: Total incremental cost 2027–29 | C41: =S24 -> 3208602.2
A42: Average first-year ACV | C42: =S32 -> 13800.744
A43: CAC (2027–29) | C43: =S31 -> 41115.536
A44: CAC payback, months (2027–29) | C44: =S33 -> 55.001095
A45: CAC payback, months (2029 cohort) | C45: =R33 -> 36.566752
A46: LTV : CAC (lifetime capped at 5 years) | C46: =IFERROR(S32*Assumptions!$G$72*MIN(1/(1-$C$34),5)/S31,0) -> 1.0908874
A47: Cumulative program P&L 2027–29 | C47: =N29 -> -2684074.4
A48: Peak investment (lowest cumulative P&L) | C48: =MIN(C29:N29) -> -2684074.4
A49: First quarter with positive program P&L (99 = not by Q4 2029) | C49: =MIN(C30:N30) -> 99
A50: Q4 2029 program P&L, annualized | C50: =N28*4 -> -670395.19
A51: Embedded value of 2029 ARR base (5 yrs, net of CS, no new spend) | C51: ='Revenue Model'!N13*(Assumptions!$G$72-IFERROR(N23*4/'Revenue Model'!N13,0))*$C$34*(1-$C$34^Assumptions!$G$80)/(1-$C$34) -> 1642544.4
A52: Total value = cumulative P&L + embedded value | C52: ='Unit Economics'!$C$47+'Unit Economics'!$C$51 -> -1041530

Sheet Scenarios
A1: Scenarios — partner-led pilot (Downside / Base / Upside), gated downside, and the sales-led alternative
A2: Every figure links to a full model run on 'Engine Runs'. Scenario outputs are illustrative, not Clay forecasts.
A4: Output | B4: Unit | D4: Partner-led: Downside | E4: Partner-led: Downside, gated at Q4 2027 | F4: Partner-led: Base | G4: Partner-led: Upside (shared AEs only) | H4: Partner-led: Upside + 2 AEs hired after gate | I4: Sales-led team: Base | J4: Sales-led team: Upside
A5: Exit ARR, Q4 2029 | B5: $ | D5: ='Engine Runs'!$C$92 -> 60533.792 | E5: ='Engine Runs'!$C$414 -> 6382.4703 | F5: ='Engine Runs'!$C$199 -> 861203.84 | G5: ='Engine Runs'!$C$306 -> 4372033.9 | H5: ='Engine Runs'!$C$521 -> 6013068.7 | I5: ='Engine Runs'!$C$628 -> 861203.84 | J5: ='Engine Runs'!$C$735 -> 6013068.7
A6: Customers, Q4 2029 | B6: # | D6: ='Engine Runs'!$C$93 -> 4.7949449 | E6: ='Engine Runs'!$C$415 -> 0.45102196 | F6: ='Engine Runs'!$C$200 -> 52.57338 | G6: ='Engine Runs'!$C$307 -> 179.38503 | H6: ='Engine Runs'!$C$522 -> 240.40829 | I6: ='Engine Runs'!$C$629 -> 52.57338 | J6: ='Engine Runs'!$C$736 -> 240.40829
A7: New customers 2027–29 | B7: # | D7: ='Engine Runs'!$C$94 -> 5.4867647 | E7: ='Engine Runs'!$C$416 -> 0.61705718 | F7: ='Engine Runs'!$C$201 -> 57.63577 | G7: ='Engine Runs'!$C$308 -> 193.95499 | H7: ='Engine Runs'!$C$523 -> 257.63071 | I7: ='Engine Runs'!$C$630 -> 57.63577 | J7: ='Engine Runs'!$C$737 -> 257.63071
A8: Recognized revenue 2027–29 | B8: $ | D8: ='Engine Runs'!$C$95 -> 62557.912 | E8: ='Engine Runs'!$C$417 -> 13936.659 | F8: ='Engine Runs'!$C$202 -> 806965.86 | G8: ='Engine Runs'!$C$309 -> 4598648.6 | H8: ='Engine Runs'!$C$524 -> 5664704.7 | I8: ='Engine Runs'!$C$631 -> 806965.86 | J8: ='Engine Runs'!$C$738 -> 5664704.7
A9: Average first-year ACV | B9: $ | D9: ='Engine Runs'!$C$98 -> 11019.558 | E9: ='Engine Runs'!$C$420 -> 10372.816 | F9: ='Engine Runs'!$C$205 -> 13800.744 | G9: ='Engine Runs'!$C$312 -> 18213.149 | H9: ='Engine Runs'!$C$527 -> 19363.117 | I9: ='Engine Runs'!$C$634 -> 13800.744 | J9: ='Engine Runs'!$C$741 -> 19363.117
A10: CAC | B10: $ | D10: ='Engine Runs'!$C$99 -> 331930.67 | E10: ='Engine Runs'!$C$421 -> 819865.25 | F10: ='Engine Runs'!$C$206 -> 41115.536 | G10: ='Engine Runs'!$C$313 -> 18950.649 | H10: ='Engine Runs'!$C$528 -> 17982.905 | I10: ='Engine Runs'!$C$635 -> 119895.93 | J10: ='Engine Runs'!$C$742 -> 29104.689
A11: CAC payback (2027–29 average) | B11: months | D11: ='Engine Runs'!$C$100 -> 657.20636 | E11: ='Engine Runs'!$C$422 -> 1724.5046 | F11: ='Engine Runs'!$C$207 -> 55.001095 | G11: ='Engine Runs'!$C$314 -> 17.341545 | H11: ='Engine Runs'!$C$529 -> 15.478659 | I11: ='Engine Runs'!$C$636 -> 160.38725 | J11: ='Engine Runs'!$C$743 -> 25.051657
A12: CAC payback (2029 cohort) | B12: months | D12: ='Engine Runs'!$C$101 -> 444.95536 | E12: ='Engine Runs'!$C$423 -> 0 | F12: ='Engine Runs'!$C$208 -> 36.566752 | G12: ='Engine Runs'!$C$315 -> 14.839987 | H12: ='Engine Runs'!$C$530 -> 12.321919 | I12: ='Engine Runs'!$C$637 -> 108.09951 | J12: ='Engine Runs'!$C$744 -> 18.922852
A13: LTV : CAC | B13: x | D13: ='Engine Runs'!$C$102 -> 0.091295526 | E13: ='Engine Runs'!$C$424 -> 0.0347926 | F13: ='Engine Runs'!$C$209 -> 1.0908874 | G13: ='Engine Runs'!$C$316 -> 3.4598993 | H13: ='Engine Runs'!$C$531 -> 3.8763047 | I13: ='Engine Runs'!$C$638 -> 0.37409458 | J13: ='Engine Runs'!$C$745 -> 2.3950512
A14: Total incremental cost 2027–29 | B14: $ | D14: ='Engine Runs'!$C$97 -> 2537039 | E14: ='Engine Runs'!$C$419 -> 984681.44 | F14: ='Engine Runs'!$C$204 -> 3208602.2 | G14: ='Engine Runs'!$C$311 -> 4886302 | H14: ='Engine Runs'!$C$526 -> 5981245.9 | I14: ='Engine Runs'!$C$633 -> 7749171.1 | J14: ='Engine Runs'!$C$740 -> 8846559
A15: Cumulative program P&L 2027–29 | B15: $ | D15: ='Engine Runs'!$C$103 -> -2502632.2 | E15: ='Engine Runs'!$C$425 -> -977016.28 | F15: ='Engine Runs'!$C$210 -> -2684074.4 | G15: ='Engine Runs'!$C$317 -> -1575275 | H15: ='Engine Runs'!$C$532 -> -1902658.5 | I15: ='Engine Runs'!$C$639 -> -7224643.2 | J15: ='Engine Runs'!$C$746 -> -4767971.6
A16: Peak investment (lowest cumulative P&L) | B16: $ | D16: ='Engine Runs'!$C$104 -> -2502632.2 | E16: ='Engine Runs'!$C$426 -> -981728.03 | F16: ='Engine Runs'!$C$211 -> -2684074.4 | G16: ='Engine Runs'!$C$318 -> -2016342.7 | H16: ='Engine Runs'!$C$533 -> -2446003.1 | I16: ='Engine Runs'!$C$640 -> -7224643.2 | J16: ='Engine Runs'!$C$747 -> -4824750.7
A17: First quarter with positive program P&L (99 = none) | B17: # | D17: ='Engine Runs'!$C$105 -> 99 | E17: ='Engine Runs'!$C$427 -> 99 | F17: ='Engine Runs'!$C$212 -> 99 | G17: ='Engine Runs'!$C$319 -> 10 | H17: ='Engine Runs'!$C$534 -> 10 | I17: ='Engine Runs'!$C$641 -> 99 | J17: ='Engine Runs'!$C$748 -> 12
A18: Q4 2029 program P&L, annualized | B18: $ | D18: ='Engine Runs'!$C$106 -> -734894.69 | E18: ='Engine Runs'!$C$428 -> 2538.4117 | F18: ='Engine Runs'!$C$213 -> -670395.19 | G18: ='Engine Runs'!$C$320 -> 962564.01 | H18: ='Engine Runs'!$C$535 -> 1302973.5 | I18: ='Engine Runs'!$C$642 -> -2520754.9 | J18: ='Engine Runs'!$C$749 -> 227116.17
A19: Embedded value of 2029 ARR base | B19: $ | D19: ='Engine Runs'!$C$107 -> 73508.168 | E19: ='Engine Runs'!$C$429 -> 8459.1143 | F19: ='Engine Runs'!$C$214 -> 1642544.4 | G19: ='Engine Runs'!$C$321 -> 11426446 | H19: ='Engine Runs'!$C$536 -> 15632477 | I19: ='Engine Runs'!$C$643 -> 1642544.4 | J19: ='Engine Runs'!$C$750 -> 15632477
A20: Total value (cumulative P&L + embedded value) | B20: $ | D20: ='Engine Runs'!$C$108 -> -2429124 | E20: ='Engine Runs'!$C$430 -> -968557.16 | F20: ='Engine Runs'!$C$215 -> -1041530 | G20: ='Engine Runs'!$C$322 -> 9851170.9 | H20: ='Engine Runs'!$C$537 -> 13729819 | I20: ='Engine Runs'!$C$644 -> -5582098.9 | J20: ='Engine Runs'!$C$751 -> 10864505
A22: Reconciliation: live model vs matching engine run (should be 0)
A23: Exit ARR difference | D23: =IF(Assumptions!$D$5=1,'Unit Economics'!$C$36-INDEX(D5:G5,1,CHOOSE(Assumptions!$D$4,1,3,4)),IF(Assumptions!$D$4=2,'Unit Economics'!$C$36-I5,IF(Assumptions!$D$4=3,'Unit Economics'!$C$36-J5,"n/a"))) -> 0
A24: Cumulative P&L difference | D24: =IF(Assumptions!$D$5=1,'Unit Economics'!$C$47-INDEX(D15:G15,1,CHOOSE(Assumptions!$D$4,1,3,4)),IF(Assumptions!$D$4=2,'Unit Economics'!$C$47-I15,IF(Assumptions!$D$4=3,'Unit Economics'!$C$47-J15,"n/a"))) -> 0
A26: Decision analysis — is the pilot worth running? (probabilities are judgment [D])
A27: Item | D27: Downside | E27: Base | F27: Upside | G27: Expected value
A28: Probability weight | D28: =Assumptions!$E$83 -> 0.35 | E28: =Assumptions!$E$84 -> 0.45 | F28: =Assumptions!$E$85 -> 0.2
A29: Total value — ungated (run all 12 quarters) | D29: =D20 -> -2429124 | E29: =F20 -> -1041530 | F29: =G20 -> 9851170.9 | G29: =SUMPRODUCT(D28:F28,D29:F29) -> 651352.27
A30: Total value — staged (Downside stopped at Q4 2027 gate; Upside adds 2 AEs) | D30: =E20 -> -968557.16 | E30: =F20 -> -1041530 | F30: =H20 -> 13729819 | G30: =SUMPRODUCT(D28:F28,D30:F30) -> 1938280.2
A31: Cumulative P&L 2027–29 only — staged (excludes post-2029 value) | D31: =E15 -> -977016.28 | E31: =F15 -> -2684074.4 | F31: =H15 -> -1902658.5 | G31: =SUMPRODUCT(D28:F28,D31:F31) -> -1930320.9
A32: Value of staging (staged EV − ungated EV) | G32: =G30-G29 -> 1286927.9
A33: Break-even probability of Upside for staged EV = 0 (Downside:Base ratio held) | G33: =IF(AND(((D28*D30+E28*E30)/(D28+E28))<0,F30>0),-((D28*D30+E28*E30)/(D28+E28))/(F30-((D28*D30+E28*E30)/(D28+E28))),IF(((D28*D30+E28*E30)/(D28+E28))>=0,0,"never")) -> 0.068496873
A34: Sales-led team vs partner-led: difference in Base cumulative P&L | G34: =I15-F15 -> -4540568.9
A36: Reading: in Base the binding constraint is demand (pipeline), not sales capacity, so a dedicated sales team produces the same ARR as the partner-led pilot at much higher cost. Only in Upside does the borrowed AE capacity bind (from Q3 2028), so dedicated AEs should be hired on that evidence, after the gate, not up front. The gate assumes Downside is distinguishable from Base by Q4 2027 on leading indicators (win rate, ACV, partner leads); if it is not, use the ungated row.
A38: ARR trajectory by quarter (for charts) | D38: Q1 2027 | E38: Q2 2027 | F38: Q3 2027 | G38: Q4 2027 | H38: Q1 2028 | I38: Q2 2028 | J38: Q3 2028 | K38: Q4 2028 | L38: Q1 2029 | M38: Q2 2029 | N38: Q3 2029 | O38: Q4 2029
A39: Partner-led: Downside | D39: ='Engine Runs'!C56 -> 0 | E39: ='Engine Runs'!D56 -> 0 | F39: ='Engine Runs'!E56 -> 2007.9211 | G39: ='Engine Runs'!F56 -> 6023.5821 | H39: ='Engine Runs'!G56 -> 10810.623 | I39: ='Engine Runs'!H56 -> 16369.717 | J39: ='Engine Runs'!I56 -> 22701.678 | K39: ='Engine Runs'!J56 -> 29036.086 | ... O39: ='Engine Runs'!N56 -> 60533.792
A40: Partner-led: Base | D40: ='Engine Runs'!C163 -> 0 | E40: ='Engine Runs'!D163 -> 17287.702 | F40: ='Engine Runs'!E163 -> 49131.526 | G40: ='Engine Runs'!F163 -> 84842.824 | H40: ='Engine Runs'!G163 -> 124517.34 | I40: ='Engine Runs'!H163 -> 176041.31 | J40: ='Engine Runs'!I163 -> 239696.27 | K40: ='Engine Runs'!J163 -> 333649.76 | ... O40: ='Engine Runs'!N163 -> 861203.84
A41: Partner-led: Upside | D41: ='Engine Runs'!C270 -> 0 | E41: ='Engine Runs'!D270 -> 96088.344 | F41: ='Engine Runs'!E270 -> 282746.34 | G41: ='Engine Runs'!F270 -> 499871.05 | H41: ='Engine Runs'!G270 -> 794844.51 | I41: ='Engine Runs'!H270 -> 1171745.4 | J41: ='Engine Runs'!I270 -> 1632359.5 | K41: ='Engine Runs'!J270 -> 2126318.1 | ... O41: ='Engine Runs'!N270 -> 4372033.9
A42: Partner-led: Upside + scale-up | D42: ='Engine Runs'!C485 -> 0 | E42: ='Engine Runs'!D485 -> 96088.344 | F42: ='Engine Runs'!E485 -> 282746.34 | G42: ='Engine Runs'!F485 -> 499871.05 | H42: ='Engine Runs'!G485 -> 794844.51 | I42: ='Engine Runs'!H485 -> 1171745.4 | J42: ='Engine Runs'!I485 -> 1739908.6 | K42: ='Engine Runs'!J485 -> 2509292.3 | ... O42: ='Engine Runs'!N485 -> 6013068.7
A43: Sales-led: Base | D43: ='Engine Runs'!C592 -> 0 | E43: ='Engine Runs'!D592 -> 17287.702 | F43: ='Engine Runs'!E592 -> 49131.526 | G43: ='Engine Runs'!F592 -> 84842.824 | H43: ='Engine Runs'!G592 -> 124517.34 | I43: ='Engine Runs'!H592 -> 176041.31 | J43: ='Engine Runs'!I592 -> 239696.27 | K43: ='Engine Runs'!J592 -> 333649.76 | ... O43: ='Engine Runs'!N592 -> 861203.84
A45: Cumulative program P&L by quarter (for charts) | D45: Q1 2027 | E45: Q2 2027 | F45: Q3 2027 | G45: Q4 2027 | H45: Q1 2028 | I45: Q2 2028 | J45: Q3 2028 | K45: Q4 2028 | L45: Q1 2029 | M45: Q2 2029 | N45: Q3 2029 | O45: Q4 2029
A46: Partner-led: Downside | D46: ='Engine Runs'!C85 -> -271265.18 | E46: ='Engine Runs'!D85 -> -504530.36 | F46: ='Engine Runs'!E85 -> -741409.23 | G46: ='Engine Runs'!F85 -> -981728.03 | H46: ='Engine Runs'!G85 -> -1167043.2 | I46: ='Engine Runs'!H85 -> -1352671.8 | J46: ='Engine Runs'!I85 -> -1578538.3 | K46: ='Engine Runs'!J85 -> -1763827.7 | ... O46: ='Engine Runs'!N85 -> -2502632.2
A47: Partner-led: Downside, gated | D47: ='Engine Runs'!C407 -> -271265.18 | E47: ='Engine Runs'!D407 -> -504530.36 | F47: ='Engine Runs'!E407 -> -741409.23 | G47: ='Engine Runs'!F407 -> -981728.03 | H47: ='Engine Runs'!G407 -> -981217.36 | I47: ='Engine Runs'!H407 -> -980682.89 | J47: ='Engine Runs'!I407 -> -980095.95 | K47: ='Engine Runs'!J407 -> -979499.06 | ... O47: ='Engine Runs'!N407 -> -977016.28
A48: Partner-led: Base | D48: ='Engine Runs'!C192 -> -273265.18 | E48: ='Engine Runs'!D192 -> -518793.06 | F48: ='Engine Runs'!E192 -> -772195.72 | G48: ='Engine Runs'!F192 -> -1025896.6 | H48: ='Engine Runs'!G192 -> -1261964.4 | I48: ='Engine Runs'!H192 -> -1461290.7 | J48: ='Engine Runs'!I192 -> -1702338.7 | K48: ='Engine Runs'!J192 -> -1912832.4 | ... O48: ='Engine Runs'!N192 -> -2684074.4
A49: Partner-led: Upside + scale-up | D49: ='Engine Runs'!C514 -> -275265.18 | E49: ='Engine Runs'!D514 -> -556623.28 | F49: ='Engine Runs'!E514 -> -863548.78 | G49: ='Engine Runs'!F514 -> -1196589.3 | H49: ='Engine Runs'!G514 -> -1502477.2 | I49: ='Engine Runs'!H514 -> -1870375.7 | J49: ='Engine Runs'!I514 -> -2140708.7 | K49: ='Engine Runs'!J514 -> -2354772.2 | ... O49: ='Engine Runs'!N514 -> -1902658.5
A50: Sales-led: Base | D50: ='Engine Runs'!C621 -> -536351.79 | E50: ='Engine Runs'!D621 -> -1037371.1 | F50: ='Engine Runs'!E621 -> -1611473.9 | G50: ='Engine Runs'!F621 -> -2184499.6 | H50: ='Engine Runs'!G621 -> -2776569 | I50: ='Engine Runs'!H621 -> -3327100.5 | J50: ='Engine Runs'!I621 -> -3985985.8 | K50: ='Engine Runs'!J621 -> -4601666.4 | ... O50: ='Engine Runs'!N621 -> -7224643.2

Sheet Sensitivity
A1: Sensitivity — which assumptions matter, and what has to be true
A2: Base scenario, partner-led pilot. Block A: one-at-a-time swings using each input's Downside / Upside value. Block B: minimum win rate. Block C: win rate × usage intensity grid.
A4: Input swung (one at a time) | B4: Downside value | C4: Upside value | D4: Total value @ Downside | E4: Total value @ Upside | F4: Swing (total value) | G4: Exit ARR @ Downside | H4: Exit ARR @ Upside | I4: Payback @ Downside | J4: Payback @ Upside
A5: Outbound meeting rate | B5: =Assumptions!$D$18 -> 0.02 | C5: =Assumptions!$F$18 -> 0.045 | D5: ='Engine Runs'!$C$859 -> -1242345.6 | E5: ='Engine Runs'!$C$967 -> -740306.58 | F5: =ABS(E5-D5) -> 502039.02 | G5: ='Engine Runs'!$C$843 -> 750621.44 | H5: ='Engine Runs'!$C$951 -> 1027077.4 | I5: ='Engine Runs'!$C$851 -> 61.607765 | J5: ='Engine Runs'!$C$959 -> 47.766713
A6: Inbound / template lead rate | B6: =Assumptions!$D$19 -> 0.005 | C6: =Assumptions!$F$19 -> 0.015 | D6: ='Engine Runs'!$C$1075 -> -1292549.5 | E6: ='Engine Runs'!$C$1183 -> -790510.49 | F6: =ABS(E6-D6) -> 502039.02 | G6: ='Engine Runs'!$C$1059 -> 722975.84 | H6: ='Engine Runs'!$C$1167 -> 999431.83 | I6: ='Engine Runs'!$C$1067 -> 63.576596 | J6: ='Engine Runs'!$C$1175 -> 48.805158
A7: Partner network (start, adds, cap, leads/partner) | B7: =Assumptions!$D$20 -> 1 | C7: =Assumptions!$F$20 -> 3 | D7: ='Engine Runs'!$C$1291 -> -1223297 | E7: ='Engine Runs'!$C$1399 -> -604363.8 | F7: =ABS(E7-D7) -> 618933.2 | G7: ='Engine Runs'!$C$1275 -> 711749.82 | H7: ='Engine Runs'!$C$1383 -> 1170941.9 | I7: ='Engine Runs'!$C$1283 -> 61.670473 | J7: ='Engine Runs'!$C$1391 -> 46.138349
A8: Qualification rates | B8: =Assumptions!$D$24 -> 0.35 | C8: =Assumptions!$F$24 -> 0.55 | D8: ='Engine Runs'!$C$1507 -> -1359310.9 | E8: ='Engine Runs'!$C$1615 -> -723749.08 | F8: =ABS(E8-D8) -> 635561.84 | G8: ='Engine Runs'!$C$1491 -> 683880.8 | H8: ='Engine Runs'!$C$1599 -> 1038526.9 | I8: ='Engine Runs'!$C$1499 -> 66.364894 | J8: ='Engine Runs'!$C$1607 -> 47.520156
A9: SQL → opportunity | B9: =Assumptions!$D$26 -> 0.35 | C9: =Assumptions!$F$26 -> 0.55 | D9: ='Engine Runs'!$C$1723 -> -1383424.1 | E9: ='Engine Runs'!$C$1831 -> -699635.87 | F9: =ABS(E9-D9) -> 683788.25 | G9: ='Engine Runs'!$C$1707 -> 669825.21 | H9: ='Engine Runs'!$C$1815 -> 1052582.5 | I9: ='Engine Runs'!$C$1715 -> 67.453325 | J9: ='Engine Runs'!$C$1823 -> 47.076948
A10: Win rate | B10: =Assumptions!$D$27 -> 0.2 | C10: =Assumptions!$F$27 -> 0.35 | D10: ='Engine Runs'!$C$1939 -> -1481108.2 | E10: ='Engine Runs'!$C$2047 -> -656899.1 | F10: =ABS(E10-D10) -> 824209.06 | G10: ='Engine Runs'!$C$1923 -> 615145.6 | H10: ='Engine Runs'!$C$2031 -> 1076504.8 | I10: ='Engine Runs'!$C$1931 -> 72.434217 | J10: ='Engine Runs'!$C$2039 -> 46.284534
A11: Usage intensity (ACV) | B11: =Assumptions!$D$37 -> 0.75 | C11: =Assumptions!$F$37 -> 1.5 | D11: ='Engine Runs'!$C$2155 -> -1479090.5 | E11: ='Engine Runs'!$C$2263 -> -164154.47 | F11: =ABS(E11-D11) -> 1314936.1 | G11: ='Engine Runs'!$C$2139 -> 684461.21 | H11: ='Engine Runs'!$C$2247 -> 1214689.1 | I11: ='Engine Runs'!$C$2147 -> 65.738844 | J11: ='Engine Runs'!$C$2255 -> 42.779379
A12: Gross revenue retention | B12: =Assumptions!$D$54 -> 0.85 | C12: =Assumptions!$F$54 -> 0.91 | D12: ='Engine Runs'!$C$2371 -> -1207749.2 | E12: ='Engine Runs'!$C$2479 -> -898753 | F12: =ABS(E12-D12) -> 308996.25 | G12: ='Engine Runs'!$C$2355 -> 861203.84 | H12: ='Engine Runs'!$C$2463 -> 861203.84 | I12: ='Engine Runs'!$C$2363 -> 55.001095 | J12: ='Engine Runs'!$C$2471 -> 55.001095
A13: Net revenue retention | B13: =Assumptions!$D$57 -> 0.92 | C13: =Assumptions!$F$57 -> 1.06 | D13: ='Engine Runs'!$C$2587 -> -1219232.7 | E13: ='Engine Runs'!$C$2695 -> -803522.82 | F13: =ABS(E13-D13) -> 415709.87 | G13: ='Engine Runs'!$C$2571 -> 799711.2 | H13: ='Engine Runs'!$C$2679 -> 943913.12 | I13: ='Engine Runs'!$C$2579 -> 55.001095 | J13: ='Engine Runs'!$C$2687 -> 55.001095
A14: Gross margin | B14: =Assumptions!$D$72 -> 0.55 | C14: =Assumptions!$F$72 -> 0.72 | D14: ='Engine Runs'!$C$2803 -> -1446451.6 | E14: ='Engine Runs'!$C$2911 -> -758084.85 | F14: =ABS(E14-D14) -> 688366.8 | G14: ='Engine Runs'!$C$2787 -> 861203.84 | H14: ='Engine Runs'!$C$2895 -> 861203.84 | I14: ='Engine Runs'!$C$2795 -> 65.001294 | J14: ='Engine Runs'!$C$2903 -> 49.653766
A15: Wave timing (waves 2 and 3) | B15: =Assumptions!$D$13 -> 7 | C15: =Assumptions!$F$13 -> 4 | D15: ='Engine Runs'!$C$3019 -> -1454999.1 | E15: ='Engine Runs'!$C$3127 -> -885677.84 | F15: =ABS(E15-D15) -> 569321.23 | G15: ='Engine Runs'!$C$3003 -> 585509.59 | H15: ='Engine Runs'!$C$3111 -> 936293.21 | I15: ='Engine Runs'!$C$3011 -> 75.567182 | J15: ='Engine Runs'!$C$3119 -> 51.536292
A16: Partner fee and onboarding subsidy | B16: =Assumptions!$D$74 -> 0.25 | C16: =Assumptions!$F$74 -> 0.15 | D16: ='Engine Runs'!$C$3235 -> -1085170.2 | E16: ='Engine Runs'!$C$3343 -> -997889.81 | F16: =ABS(E16-D16) -> 87280.386 | G16: ='Engine Runs'!$C$3219 -> 861203.84 | H16: ='Engine Runs'!$C$3327 -> 861203.84 | I16: ='Engine Runs'!$C$3227 -> 56.013979 | J16: ='Engine Runs'!$C$3335 -> 53.98821
A17: Self-serve share of SMB | B17: =Assumptions!$D$32 -> 0.15 | C17: =Assumptions!$F$32 -> 0.4 | D17: ='Engine Runs'!$C$3451 -> -1052321.8 | E17: ='Engine Runs'!$C$3559 -> -1034335.4 | F17: =ABS(E17-D17) -> 17986.393 | G17: ='Engine Runs'!$C$3435 -> 861203.84 | H17: ='Engine Runs'!$C$3543 -> 861203.84 | I17: ='Engine Runs'!$C$3443 -> 55.251572 | J17: ='Engine Runs'!$C$3551 -> 54.83411
A18: Base case (for reference) | D18: ='Engine Runs'!$C$215 -> -1041530 | E18: ='Engine Runs'!$C$215 -> -1041530 | G18: ='Engine Runs'!$C$199 -> 861203.84 | I18: ='Engine Runs'!$C$207 -> 55.001095
A19: Note: the rank of each input = its swing; the bar chart below plots the swing.
A21: Block B — What win rate does the pilot need? (all else Base)
A22: Win rate | B22: New customers | C22: Exit ARR | D22: CAC payback (2027–29) | E22: CAC payback (2029 cohort) | F22: Cumulative P&L | G22: Total value | H22: Payback ≤ 24 mo (2029 cohort)? | I22: Total value ≥ 0?
A23: 0.15 | B23: ='Engine Runs'!$C$3653 -> 30.876305 | C23: ='Engine Runs'!$C$3651 -> 461359.2 | D23: ='Engine Runs'!$C$3659 -> 92.772859 | E23: ='Engine Runs'!$C$3660 -> 58.476537 | F23: ='Engine Runs'!$C$3662 -> -2635779 | G23: ='Engine Runs'!$C$3667 -> -1755844.5 | H23: =IF(AND(E23>0,E23<=24),"Yes","No") -> No | I23: =IF(G23>=0,"Yes","No") -> No
A24: 0.2 | B24: ='Engine Runs'!$C$3761 -> 41.168407 | C24: ='Engine Runs'!$C$3759 -> 615145.6 | D24: ='Engine Runs'!$C$3767 -> 72.434217 | E24: ='Engine Runs'!$C$3768 -> 46.678961 | F24: ='Engine Runs'!$C$3770 -> -2654354.1 | G24: ='Engine Runs'!$C$3775 -> -1481108.2 | H24: =IF(AND(E24>0,E24<=24),"Yes","No") -> No | I24: =IF(G24>=0,"Yes","No") -> No
A25: 0.25 | B25: ='Engine Runs'!$C$3869 -> 51.460509 | C25: ='Engine Runs'!$C$3867 -> 768932 | D25: ='Engine Runs'!$C$3875 -> 60.231031 | E25: ='Engine Runs'!$C$3876 -> 39.600414 | F25: ='Engine Runs'!$C$3878 -> -2672929.3 | G25: ='Engine Runs'!$C$3883 -> -1206371.8 | H25: =IF(AND(E25>0,E25<=24),"Yes","No") -> No | I25: =IF(G25>=0,"Yes","No") -> No
A26: 0.28 | B26: ='Engine Runs'!$C$3977 -> 57.63577 | C26: ='Engine Runs'!$C$3975 -> 861203.84 | D26: ='Engine Runs'!$C$3983 -> 55.001095 | E26: ='Engine Runs'!$C$3984 -> 36.566752 | F26: ='Engine Runs'!$C$3986 -> -2684074.4 | G26: ='Engine Runs'!$C$3991 -> -1041530 | H26: =IF(AND(E26>0,E26<=24),"Yes","No") -> No | I26: =IF(G26>=0,"Yes","No") -> No
A27: 0.3 | B27: ='Engine Runs'!$C$4085 -> 61.752611 | C27: ='Engine Runs'!$C$4083 -> 922718.4 | D27: ='Engine Runs'!$C$4091 -> 52.095575 | E27: ='Engine Runs'!$C$4092 -> 34.881384 | F27: ='Engine Runs'!$C$4094 -> -2691504.4 | G27: ='Engine Runs'!$C$4099 -> -931635.46 | H27: =IF(AND(E27>0,E27<=24),"Yes","No") -> No | I27: =IF(G27>=0,"Yes","No") -> No
A28: 0.35 | B28: ='Engine Runs'!$C$4193 -> 72.044712 | C28: ='Engine Runs'!$C$4191 -> 1076504.8 | D28: ='Engine Runs'!$C$4199 -> 46.284534 | E28: ='Engine Runs'!$C$4200 -> 31.510647 | F28: ='Engine Runs'!$C$4202 -> -2710079.6 | G28: ='Engine Runs'!$C$4207 -> -656899.1 | H28: =IF(AND(E28>0,E28<=24),"Yes","No") -> No | I28: =IF(G28>=0,"Yes","No") -> No
A29: 0.4 | B29: ='Engine Runs'!$C$4301 -> 82.336814 | C29: ='Engine Runs'!$C$4299 -> 1230291.2 | D29: ='Engine Runs'!$C$4307 -> 41.926253 | E29: ='Engine Runs'!$C$4308 -> 28.982595 | F29: ='Engine Runs'!$C$4310 -> -2728654.7 | G29: ='Engine Runs'!$C$4315 -> -382162.75 | H29: =IF(AND(E29>0,E29<=24),"Yes","No") -> No | I29: =IF(G29>=0,"Yes","No") -> No
A30: 0.5 | B30: ='Engine Runs'!$C$4409 -> 102.92102 | C30: ='Engine Runs'!$C$4407 -> 1537864 | D30: ='Engine Runs'!$C$4415 -> 35.824661 | E30: ='Engine Runs'!$C$4416 -> 25.443322 | F30: ='Engine Runs'!$C$4418 -> -2765805 | G30: ='Engine Runs'!$C$4423 -> 167309.95 | H30: =IF(AND(E30>0,E30<=24),"Yes","No") -> No | I30: =IF(G30>=0,"Yes","No") -> Yes
A31: Lowest tested win rate with 2029-cohort payback ≤ 24 months | E31: =IFERROR(INDEX(A23:A30,MATCH("Yes",H23:H30,0)),"none tested") -> none tested
A32: Lowest tested win rate with total value ≥ 0 | E32: =IFERROR(INDEX(A23:A30,MATCH("Yes",I23:I30,0)),"none tested") -> 0.5
A35: Block C — CAC payback, 2029 cohort (months): win rate (rows) × usage intensity (columns)
A36: Win rate ↓ / usage → | B36: 0.75 | C36: 1 | D36: 1.5 | E36: 2
A37: 0.2 | B37: ='Engine Runs'!$C$4524 -> 55.349647 | C37: ='Engine Runs'!$C$4632 -> 46.678961 | D37: ='Engine Runs'!$C$4740 -> 36.809978 | E37: ='Engine Runs'!$C$4848 -> 31.345719
A38: 0.28 | B38: ='Engine Runs'!$C$4956 -> 42.685255 | C38: ='Engine Runs'!$C$5064 -> 36.566752 | D38: ='Engine Runs'!$C$5172 -> 29.602666 | E38: ='Engine Runs'!$C$5280 -> 25.746792
A39: 0.35 | B39: ='Engine Runs'!$C$5388 -> 36.353059 | C39: ='Engine Runs'!$C$5496 -> 31.510647 | D39: ='Engine Runs'!$C$5604 -> 25.999011 | E39: ='Engine Runs'!$C$5712 -> 22.947328
A40: 0.45 | B40: ='Engine Runs'!$C$5820 -> 30.72444 | C40: ='Engine Runs'!$C$5928 -> 27.016332 | D40: ='Engine Runs'!$C$6036 -> 22.795761 | E40: ='Engine Runs'!$C$6144 -> 21.231391
A43: Block C2 — Total value ($): same grid
A44: Win rate ↓ / usage → | B44: 0.75 | C44: 1 | D44: 1.5 | E44: 2
A45: 0.2 | B45: ='Engine Runs'!$C$4531 -> -1793651.4 | C45: ='Engine Runs'!$C$4639 -> -1481108.2 | D45: ='Engine Runs'!$C$4747 -> -854411.35 | E45: ='Engine Runs'!$C$4855 -> -226759.45
A46: 0.28 | B46: ='Engine Runs'!$C$4963 -> -1479090.5 | C46: ='Engine Runs'!$C$5071 -> -1041530 | D46: ='Engine Runs'!$C$5179 -> -164154.47 | E46: ='Engine Runs'!$C$5287 -> 714558.2
A47: 0.35 | B47: ='Engine Runs'!$C$5395 -> -1203849.8 | C47: ='Engine Runs'!$C$5503 -> -656899.1 | D47: ='Engine Runs'!$C$5611 -> 439820.31 | E47: ='Engine Runs'!$C$5719 -> 1538211.1
A48: 0.45 | B48: ='Engine Runs'!$C$5827 -> -810648.71 | C48: ='Engine Runs'!$C$5935 -> -107426.4 | D48: ='Engine Runs'!$C$6043 -> 1302641.4 | E48: ='Engine Runs'!$C$6151 -> 2500398.5
A50: Reading: win rate alone cannot rescue the economics — at Base usage, even a 50% win rate leaves 2029-cohort payback above 24 months (Block B). Payback ≤ 24 months and positive total value appear only toward the bottom-right of the grid: win rates of 35%+ combined with usage ~1.5–2× the base build (i.e. mid-market ACVs of ~$15–20K). ACV per account is therefore the first thing the pilot must prove.

Sheet Engine Runs
A1: Engine Runs — full copies of the model for each scenario and sensitivity case
A2: Generated by the same code as the live model (identical row logic). Each block lists its inputs at the top; yellow = input changed for that run.
A4: RUN: Partner-led pilot — Downside
A5: Partner-led pilot — Downside — inputs carried into this run | B5: Unit / note | C5: Q1 2027 | D5: Q2 2027 | E5: Q3 2027 | F5: Q4 2027 | G5: Q1 2028 | H5: Q2 2028 | I5: Q3 2028 | J5: Q4 2028 | K5: Q1 2029 | L5: Q2 2029 | M5: Q3 2029 | N5: Q4 2029 | P5: 2027 | Q5: 2028 | R5: 2029 | S5: 2027–29
A6: SAM accounts — wave 1 (4236 electrical) | B6: firms × filters × (1 − existing) | C6: ='Market Sizing'!$F$12*Assumptions!$D$9*Assumptions!$D$10*(1-Assumptions!$D$11) -> 832.75915
A7: SAM accounts — wave 2 (4237 PHVAC) | C7: ='Market Sizing'!$F$13*Assumptions!$D$9*Assumptions!$D$10*(1-Assumptions!$D$11) -> 588.06576
A8: SAM accounts — wave 3 (4238 machinery/MRO) | C8: ='Market Sizing'!$F$14*Assumptions!$D$9*Assumptions!$D$10*(1-Assumptions!$D$11) -> 1938.048
A9: First-year ACV — SMB | B9: usage build (ACV Build) | C9: =MAX(((Assumptions!$D$45+Assumptions!$D$47)*12),(((('Market Sizing'!$E$18*Assumptions!$D$35*Assumptions!$D$36*Assumptions!$D$37)*Assumptions!$D$38)*Assumptions!$D$39*Assumptions!$D$40+('Market Sizing'!$E$18*Assumptions!$D$35*Assumptions!$D$36*Assumptions!$D$37)*Assumptions!$D$41+('Market Sizing'!$E$18*Assumptions!$D$35*Assumptions!$D$36*Assumptions!$D$37)*Assumptions!$D$42*Assumptions!$D$43)*(Assumptions!$D$45*12/Assumptions!$D$46)+((('Market Sizing'!$E$18*Assumptions!$D$35*Assumptions!$D$36*Assumptions!$D$37)*Assumptions!$D$38)*Assumptions!$D$39+('Market Sizing'!$E$18*Assumptions!$D$35*Assumptions!$D$36*Assumptions!$D$37)+('Market Sizing'!$E$18*Assumptions!$D$35*Assumptions!$D$36*Assumptions!$D$37)*Assumptions!$D$42)*Assumptions!$D$44*(Assumptions!$D$47*12/Assumptions!$D$48))) -> 5352
A10: First-year ACV — Mid-Market | C10: =MAX(((Assumptions!$D$45+Assumptions!$D$47)*12),(((('Market Sizing'!$E$19*Assumptions!$D$35*Assumptions!$D$36*Assumptions!$D$37)*Assumptions!$D$38)*Assumptions!$D$39*Assumptions!$D$40+('Market Sizing'!$E$19*Assumptions!$D$35*Assumptions!$D$36*Assumptions!$D$37)*Assumptions!$D$41+('Market Sizing'!$E$19*Assumptions!$D$35*Assumptions!$D$36*Assumptions!$D$37)*Assumptions!$D$42*Assumptions!$D$43)*(Assumptions!$D$45*12/Assumptions!$D$46)+((('Market Sizing'!$E$19*Assumptions!$D$35*Assumptions!$D$36*Assumptions!$D$37)*Assumptions!$D$38)*Assumptions!$D$39+('Market Sizing'!$E$19*Assumptions!$D$35*Assumptions!$D$36*Assumptions!$D$37)+('Market Sizing'!$E$19*Assumptions!$D$35*Assumptions!$D$36*Assumptions!$D$37)*Assumptions!$D$42)*Assumptions!$D$44*(Assumptions!$D$47*12/Assumptions!$D$48))) -> 7325.0401
A11: First-year ACV — Enterprise | C11: =MAX((Assumptions!$D$49*(Assumptions!$D$45*12/Assumptions!$D$46)+Assumptions!$D$50*(Assumptions!$D$47*12/Assumptions!$D$48)),(((('Market Sizing'!$E$20*Assumptions!$D$35*Assumptions!$D$36*Assumptions!$D$37)*Assumptions!$D$38)*Assumptions!$D$39*Assumptions!$D$40+('Market Sizing'!$E$20*Assumptions!$D$35*Assumptions!$D$36*Assumptions!$D$37)*Assumptions!$D$41+('Market Sizing'!$E$20*Assumptions!$D$35*Assumptions!$D$36*Assumptions!$D$37)*Assumptions!$D$42*Assumptions!$D$43)*(Assumptions!$D$45*12/Assumptions!$D$46)+((('Market Sizing'!$E$20*Assumptions!$D$35*Assumptions!$D$36*Assumptions!$D$37)*Assumptions!$D$38)*Assumptions!$D$39+('Market Sizing'!$E$20*Assumptions!$D$35*Assumptions!$D$36*Assumptions!$D$37)+('Market Sizing'!$E$20*Assumptions!$D$35*Assumptions!$D$36*Assumptions!$D$37)*Assumptions!$D$42)*Assumptions!$D$44*(Assumptions!$D$47*12/Assumptions!$D$48)))*(1-Assumptions!$D$51) -> 46333.692
A12: Sales-assisted mix denominator | B12: mixS(1−ss)+mixM+mixE | C12: =Assumptions!$D$29*(1-Assumptions!$D$32)+Assumptions!$D$30+Assumptions!$D$31 -> 0.925
A13: Blended ACV of sales-assisted wins | C13: =(Assumptions!$D$29*(1-Assumptions!$D$32)*$C$9+Assumptions!$D$30*$C$10+Assumptions!$D$31*$C$11)/$C$12 -> 11479.09
A14: AE fully loaded annual cost | B14: OTE ÷ wage share | C14: =Assumptions!$D$64/Assumptions!$D$65 -> 285714.29
A15: Deals per ramped AE per quarter | B15: quota × productivity ÷ 4 ÷ ACV | C15: =Assumptions!$D$62*Assumptions!$D$63/4/$C$13 -> 10.481014
A16: Variable AE cost per deal (shared capacity) | C16: =$C$14/4/$C$15 -> 6815.0442
A17: GTM funnel | B17: Unit / note | C17: Q1 2027 | D17: Q2 2027 | E17: Q3 2027 | F17: Q4 2027 | G17: Q1 2028 | H17: Q2 2028 | I17: Q3 2028 | J17: Q4 2028 | K17: Q1 2029 | L17: Q2 2029 | M17: Q3 2029 | N17: Q4 2029 | P17: 2027 | Q17: 2028 | R17: 2029 | S17: 2027–29
A18: Quarter number | B18: # | C18: 1 | D18: 2 | E18: 3 | F18: 4 | G18: 5 | H18: 6 | I18: 7 | J18: 8 | K18: 9 | L18: 10 | M18: 11 | N18: 12
A19: Program running (1) / stopped (0) | B19: flag | C19: =IF(C18<=Assumptions!$D$79,1,0) -> 1 | D19: =IF(D18<=Assumptions!$D$79,1,0) -> 1 | E19: =IF(E18<=Assumptions!$D$79,1,0) -> 1 | F19: =IF(F18<=Assumptions!$D$79,1,0) -> 1 | G19: =IF(G18<=Assumptions!$D$79,1,0) -> 1 | H19: =IF(H18<=Assumptions!$D$79,1,0) -> 1 | I19: =IF(I18<=Assumptions!$D$79,1,0) -> 1 | J19: =IF(J18<=Assumptions!$D$79,1,0) -> 1 | ... N19: =IF(N18<=Assumptions!$D$79,1,0) -> 1
A20: Wave 1 active (0.5 in launch quarter) | B20: factor | C20: =IF(C18=Assumptions!$D$12,0.5,IF(C18>Assumptions!$D$12,1,0)) -> 0.5 | D20: =IF(D18=Assumptions!$D$12,0.5,IF(D18>Assumptions!$D$12,1,0)) -> 1 | E20: =IF(E18=Assumptions!$D$12,0.5,IF(E18>Assumptions!$D$12,1,0)) -> 1 | F20: =IF(F18=Assumptions!$D$12,0.5,IF(F18>Assumptions!$D$12,1,0)) -> 1 | G20: =IF(G18=Assumptions!$D$12,0.5,IF(G18>Assumptions!$D$12,1,0)) -> 1 | H20: =IF(H18=Assumptions!$D$12,0.5,IF(H18>Assumptions!$D$12,1,0)) -> 1 | I20: =IF(I18=Assumptions!$D$12,0.5,IF(I18>Assumptions!$D$12,1,0)) -> 1 | J20: =IF(J18=Assumptions!$D$12,0.5,IF(J18>Assumptions!$D$12,1,0)) -> 1 | ... N20: =IF(N18=Assumptions!$D$12,0.5,IF(N18>Assumptions!$D$12,1,0)) -> 1
A21: Wave 2 active (0.5 in launch quarter) | B21: factor | C21: =IF(C18=Assumptions!$D$13,0.5,IF(C18>Assumptions!$D$13,1,0)) -> 0 | D21: =IF(D18=Assumptions!$D$13,0.5,IF(D18>Assumptions!$D$13,1,0)) -> 0 | E21: =IF(E18=Assumptions!$D$13,0.5,IF(E18>Assumptions!$D$13,1,0)) -> 0 | F21: =IF(F18=Assumptions!$D$13,0.5,IF(F18>Assumptions!$D$13,1,0)) -> 0 | G21: =IF(G18=Assumptions!$D$13,0.5,IF(G18>Assumptions!$D$13,1,0)) -> 0 | H21: =IF(H18=Assumptions!$D$13,0.5,IF(H18>Assumptions!$D$13,1,0)) -> 0 | I21: =IF(I18=Assumptions!$D$13,0.5,IF(I18>Assumptions!$D$13,1,0)) -> 0.5 | J21: =IF(J18=Assumptions!$D$13,0.5,IF(J18>Assumptions!$D$13,1,0)) -> 1 | ... N21: =IF(N18=Assumptions!$D$13,0.5,IF(N18>Assumptions!$D$13,1,0)) -> 1
A22: Wave 3 active (0.5 in launch quarter) | B22: factor | C22: =IF(C18=Assumptions!$D$14,0.5,IF(C18>Assumptions!$D$14,1,0)) -> 0 | D22: =IF(D18=Assumptions!$D$14,0.5,IF(D18>Assumptions!$D$14,1,0)) -> 0 | E22: =IF(E18=Assumptions!$D$14,0.5,IF(E18>Assumptions!$D$14,1,0)) -> 0 | F22: =IF(F18=Assumptions!$D$14,0.5,IF(F18>Assumptions!$D$14,1,0)) -> 0 | G22: =IF(G18=Assumptions!$D$14,0.5,IF(G18>Assumptions!$D$14,1,0)) -> 0 | H22: =IF(H18=Assumptions!$D$14,0.5,IF(H18>Assumptions!$D$14,1,0)) -> 0 | I22: =IF(I18=Assumptions!$D$14,0.5,IF(I18>Assumptions!$D$14,1,0)) -> 0 | J22: =IF(J18=Assumptions!$D$14,0.5,IF(J18>Assumptions!$D$14,1,0)) -> 0 | ... N22: =IF(N18=Assumptions!$D$14,0.5,IF(N18>Assumptions!$D$14,1,0)) -> 0
A23: Active SAM accounts in launched waves | B23: accounts | C23: =$C$6*C20+$C$7*C21+$C$8*C22 -> 416.37958 | D23: =$C$6*D20+$C$7*D21+$C$8*D22 -> 832.75915 | E23: =$C$6*E20+$C$7*E21+$C$8*E22 -> 832.75915 | F23: =$C$6*F20+$C$7*F21+$C$8*F22 -> 832.75915 | G23: =$C$6*G20+$C$7*G21+$C$8*G22 -> 832.75915 | H23: =$C$6*H20+$C$7*H21+$C$8*H22 -> 832.75915 | I23: =$C$6*I20+$C$7*I21+$C$8*I22 -> 1126.792 | J23: =$C$6*J20+$C$7*J21+$C$8*J22 -> 1420.8249 | ... N23: =$C$6*N20+$C$7*N21+$C$8*N22 -> 1420.8249 | P23: =F23 -> 832.75915 | Q23: =J23 -> 1420.8249 | R23: =N23 -> 1420.8249 | S23: =R23 -> 1420.8249
A24: Accounts sequenced by Clay-run outbound | B24: accounts | C24: =C23*Assumptions!$D$17*C19 -> 124.91387 | D24: =D23*Assumptions!$D$17*D19 -> 249.82775 | E24: =E23*Assumptions!$D$17*E19 -> 249.82775 | F24: =F23*Assumptions!$D$17*F19 -> 249.82775 | G24: =G23*Assumptions!$D$17*G19 -> 249.82775 | H24: =H23*Assumptions!$D$17*H19 -> 249.82775 | I24: =I23*Assumptions!$D$17*I19 -> 338.03761 | J24: =J23*Assumptions!$D$17*J19 -> 426.24747 | ... N24: =N23*Assumptions!$D$17*N19 -> 426.24747 | P24: =SUM(C24:F24) -> 874.39711 | Q24: =SUM(G24:J24) -> 1263.9406 | R24: =SUM(K24:N24) -> 1704.9899 | S24: =SUM(P24:R24) -> 3843.3276
A25: Leads — outbound meetings | B25: leads | C25: =C24*Assumptions!$D$18 -> 2.4982775 | D25: =D24*Assumptions!$D$18 -> 4.9965549 | E25: =E24*Assumptions!$D$18 -> 4.9965549 | F25: =F24*Assumptions!$D$18 -> 4.9965549 | G25: =G24*Assumptions!$D$18 -> 4.9965549 | H25: =H24*Assumptions!$D$18 -> 4.9965549 | I25: =I24*Assumptions!$D$18 -> 6.7607522 | J25: =J24*Assumptions!$D$18 -> 8.5249495 | ... N25: =N24*Assumptions!$D$18 -> 8.5249495 | P25: =SUM(C25:F25) -> 17.487942 | Q25: =SUM(G25:J25) -> 25.278812 | R25: =SUM(K25:N25) -> 34.099798 | S25: =SUM(P25:R25) -> 76.866552
A26: Leads — inbound / template-led | B26: leads | C26: =C23*Assumptions!$D$19*C19 -> 2.0818979 | D26: =D23*Assumptions!$D$19*D19 -> 4.1637958 | E26: =E23*Assumptions!$D$19*E19 -> 4.1637958 | F26: =F23*Assumptions!$D$19*F19 -> 4.1637958 | G26: =G23*Assumptions!$D$19*G19 -> 4.1637958 | H26: =H23*Assumptions!$D$19*H19 -> 4.1637958 | I26: =I23*Assumptions!$D$19*I19 -> 5.6339602 | J26: =J23*Assumptions!$D$19*J19 -> 7.1041246 | ... N26: =N23*Assumptions!$D$19*N19 -> 7.1041246 | P26: =SUM(C26:F26) -> 14.573285 | Q26: =SUM(G26:J26) -> 21.065676 | R26: =SUM(K26:N26) -> 28.416498 | S26: =SUM(P26:R26) -> 64.05546
A27: Active partners | B27: partners | C27: =IF(C19=1,MIN(Assumptions!$D$22,Assumptions!$D$20+Assumptions!$D$21*(C18-1)),0) -> 1 | D27: =IF(D19=1,MIN(Assumptions!$D$22,Assumptions!$D$20+Assumptions!$D$21*(D18-1)),0) -> 2 | E27: =IF(E19=1,MIN(Assumptions!$D$22,Assumptions!$D$20+Assumptions!$D$21*(E18-1)),0) -> 3 | F27: =IF(F19=1,MIN(Assumptions!$D$22,Assumptions!$D$20+Assumptions!$D$21*(F18-1)),0) -> 4 | G27: =IF(G19=1,MIN(Assumptions!$D$22,Assumptions!$D$20+Assumptions!$D$21*(G18-1)),0) -> 5 | H27: =IF(H19=1,MIN(Assumptions!$D$22,Assumptions!$D$20+Assumptions!$D$21*(H18-1)),0) -> 5 | I27: =IF(I19=1,MIN(Assumptions!$D$22,Assumptions!$D$20+Assumptions!$D$21*(I18-1)),0) -> 5 | J27: =IF(J19=1,MIN(Assumptions!$D$22,Assumptions!$D$20+Assumptions!$D$21*(J18-1)),0) -> 5 | ... N27: =IF(N19=1,MIN(Assumptions!$D$22,Assumptions!$D$20+Assumptions!$D$21*(N18-1)),0) -> 5 | P27: =F27 -> 4 | Q27: =J27 -> 5 | R27: =N27 -> 5 | S27: =R27 -> 5
A28: Leads — partner-sourced | B28: leads | C28: =C27*Assumptions!$D$23 -> 2 | D28: =D27*Assumptions!$D$23 -> 4 | E28: =E27*Assumptions!$D$23 -> 6 | F28: =F27*Assumptions!$D$23 -> 8 | G28: =G27*Assumptions!$D$23 -> 10 | H28: =H27*Assumptions!$D$23 -> 10 | I28: =I27*Assumptions!$D$23 -> 10 | J28: =J27*Assumptions!$D$23 -> 10 | ... N28: =N27*Assumptions!$D$23 -> 10 | P28: =SUM(C28:F28) -> 20 | Q28: =SUM(G28:J28) -> 40 | R28: =SUM(K28:N28) -> 40 | S28: =SUM(P28:R28) -> 100
A29: Total leads | B29: leads | C29: =C25+C26+C28 -> 6.5801753 | D29: =D25+D26+D28 -> 13.160351 | E29: =E25+E26+E28 -> 15.160351 | F29: =F25+F26+F28 -> 17.160351 | G29: =G25+G26+G28 -> 19.160351 | H29: =H25+H26+H28 -> 19.160351 | I29: =I25+I26+I28 -> 22.394712 | J29: =J25+J26+J28 -> 25.629074 | ... N29: =N25+N26+N28 -> 25.629074 | P29: =SUM(C29:F29) -> 52.061227 | Q29: =SUM(G29:J29) -> 86.344488 | R29: =SUM(K29:N29) -> 102.5163 | S29: =SUM(P29:R29) -> 240.92201
A30: Qualified (SQL) — outbound + inbound | B30: SQLs | C30: =(C25+C26)*Assumptions!$D$24 -> 1.6030614 | D30: =(D25+D26)*Assumptions!$D$24 -> 3.2061227 | E30: =(E25+E26)*Assumptions!$D$24 -> 3.2061227 | F30: =(F25+F26)*Assumptions!$D$24 -> 3.2061227 | G30: =(G25+G26)*Assumptions!$D$24 -> 3.2061227 | H30: =(H25+H26)*Assumptions!$D$24 -> 3.2061227 | I30: =(I25+I26)*Assumptions!$D$24 -> 4.3381493 | J30: =(J25+J26)*Assumptions!$D$24 -> 5.4701759 | ... N30: =(N25+N26)*Assumptions!$D$24 -> 5.4701759 | P30: =SUM(C30:F30) -> 11.22143 | Q30: =SUM(G30:J30) -> 16.220571 | R30: =SUM(K30:N30) -> 21.880704 | S30: =SUM(P30:R30) -> 49.322704
A31: Qualified (SQL) — partner | B31: SQLs | C31: =C28*Assumptions!$D$25 -> 1 | D31: =D28*Assumptions!$D$25 -> 2 | E31: =E28*Assumptions!$D$25 -> 3 | F31: =F28*Assumptions!$D$25 -> 4 | G31: =G28*Assumptions!$D$25 -> 5 | H31: =H28*Assumptions!$D$25 -> 5 | I31: =I28*Assumptions!$D$25 -> 5 | J31: =J28*Assumptions!$D$25 -> 5 | ... N31: =N28*Assumptions!$D$25 -> 5 | P31: =SUM(C31:F31) -> 10 | Q31: =SUM(G31:J31) -> 20 | R31: =SUM(K31:N31) -> 20 | S31: =SUM(P31:R31) -> 50
A32: Opportunities created | B32: opps | C32: =(C30+C31)*Assumptions!$D$26 -> 0.91107148 | D32: =(D30+D31)*Assumptions!$D$26 -> 1.822143 | E32: =(E30+E31)*Assumptions!$D$26 -> 2.172143 | F32: =(F30+F31)*Assumptions!$D$26 -> 2.522143 | G32: =(G30+G31)*Assumptions!$D$26 -> 2.872143 | H32: =(H30+H31)*Assumptions!$D$26 -> 2.872143 | I32: =(I30+I31)*Assumptions!$D$26 -> 3.2683523 | J32: =(J30+J31)*Assumptions!$D$26 -> 3.6645616 | ... N32: =(N30+N31)*Assumptions!$D$26 -> 3.6645616 | P32: =SUM(C32:F32) -> 7.4275004 | Q32: =SUM(G32:J32) -> 12.6772 | R32: =SUM(K32:N32) -> 14.658246 | S32: =SUM(P32:R32) -> 34.762946
A33: of which partner-sourced | B33: opps | C33: =C31*Assumptions!$D$26 -> 0.35 | D33: =D31*Assumptions!$D$26 -> 0.7 | E33: =E31*Assumptions!$D$26 -> 1.05 | F33: =F31*Assumptions!$D$26 -> 1.4 | G33: =G31*Assumptions!$D$26 -> 1.75 | H33: =H31*Assumptions!$D$26 -> 1.75 | I33: =I31*Assumptions!$D$26 -> 1.75 | J33: =J31*Assumptions!$D$26 -> 1.75 | ... N33: =N31*Assumptions!$D$26 -> 1.75 | P33: =SUM(C33:F33) -> 3.5 | Q33: =SUM(G33:J33) -> 7 | R33: =SUM(K33:N33) -> 7 | S33: =SUM(P33:R33) -> 17.5
A34: Demand-limited wins (opps from 1–2 quarters earlier × win rate) | B34: wins | C34: =0*Assumptions!$D$27 -> 0 | D34: =IF(Assumptions!$D$28=1,C32,0)*Assumptions!$D$27 -> 0 | E34: =IF(Assumptions!$D$28=1,D32,C32)*Assumptions!$D$27 -> 0.1822143 | F34: =IF(Assumptions!$D$28=1,E32,D32)*Assumptions!$D$27 -> 0.36442859 | G34: =IF(Assumptions!$D$28=1,F32,E32)*Assumptions!$D$27 -> 0.43442859 | H34: =IF(Assumptions!$D$28=1,G32,F32)*Assumptions!$D$27 -> 0.50442859 | I34: =IF(Assumptions!$D$28=1,H32,G32)*Assumptions!$D$27 -> 0.57442859 | J34: =IF(Assumptions!$D$28=1,I32,H32)*Assumptions!$D$27 -> 0.57442859 | K34: =IF(Assumptions!$D$28=1,J32,I32)*Assumptions!$D$27 -> 0.65367045 | L34: =IF(Assumptions!$D$28=1,K32,J32)*Assumptions!$D$27 -> 0.73291231 | ... N34: =IF(Assumptions!$D$28=1,M32,L32)*Assumptions!$D$27 -> 0.73291231 | P34: =SUM(C34:F34) -> 0.54664289 | Q34: =SUM(G34:J34) -> 2.0877144 | R34: =SUM(K34:N34) -> 2.8524074 | S34: =SUM(P34:R34) -> 5.4867647
A35: Partner-sourced share of wins | B35: % | C35: =IFERROR(0/0,0) -> 0 | D35: =IFERROR(IF(Assumptions!$D$28=1,C33,0)/IF(Assumptions!$D$28=1,C32,0),0) -> 0 | E35: =IFERROR(IF(Assumptions!$D$28=1,D33,C33)/IF(Assumptions!$D$28=1,D32,C32),0) -> 0.38416305 | F35: =IFERROR(IF(Assumptions!$D$28=1,E33,D33)/IF(Assumptions!$D$28=1,E32,D32),0) -> 0.38416305 | G35: =IFERROR(IF(Assumptions!$D$28=1,F33,E33)/IF(Assumptions!$D$28=1,F32,E32),0) -> 0.4833936 | H35: =IFERROR(IF(Assumptions!$D$28=1,G33,F33)/IF(Assumptions!$D$28=1,G32,F32),0) -> 0.55508352 | I35: =IFERROR(IF(Assumptions!$D$28=1,H33,G33)/IF(Assumptions!$D$28=1,H32,G32),0) -> 0.60930115 | J35: =IFERROR(IF(Assumptions!$D$28=1,I33,H33)/IF(Assumptions!$D$28=1,I32,H32),0) -> 0.60930115 | K35: =IFERROR(IF(Assumptions!$D$28=1,J33,I33)/IF(Assumptions!$D$28=1,J32,I32),0) -> 0.535438 | L35: =IFERROR(IF(Assumptions!$D$28=1,K33,J33)/IF(Assumptions!$D$28=1,K32,J32),0) -> 0.47754689 | ... N35: =IFERROR(IF(Assumptions!$D$28=1,M33,L33)/IF(Assumptions!$D$28=1,M32,L32),0) -> 0.47754689
A36: Self-serve SMB wins (no AE) | B36: wins | C36: =C34*Assumptions!$D$29*Assumptions!$D$32 -> 0 | D36: =D34*Assumptions!$D$29*Assumptions!$D$32 -> 0 | E36: =E34*Assumptions!$D$29*Assumptions!$D$32 -> 0.013666072 | F36: =F34*Assumptions!$D$29*Assumptions!$D$32 -> 0.027332144 | G36: =G34*Assumptions!$D$29*Assumptions!$D$32 -> 0.032582144 | H36: =H34*Assumptions!$D$29*Assumptions!$D$32 -> 0.037832144 | I36: =I34*Assumptions!$D$29*Assumptions!$D$32 -> 0.043082144 | J36: =J34*Assumptions!$D$29*Assumptions!$D$32 -> 0.043082144 | ... N36: =N34*Assumptions!$D$29*Assumptions!$D$32 -> 0.054968424 | P36: =SUM(C36:F36) -> 0.040998217 | Q36: =SUM(G36:J36) -> 0.15657858 | R36: =SUM(K36:N36) -> 0.21393055 | S36: =SUM(P36:R36) -> 0.41150735
A37: Sales-assisted demand | B37: wins | C37: =C34-C36 -> 0 | D37: =D34-D36 -> 0 | E37: =E34-E36 -> 0.16854822 | F37: =F34-F36 -> 0.33709645 | G37: =G34-G36 -> 0.40184645 | H37: =H34-H36 -> 0.46659645 | I37: =I34-I36 -> 0.53134645 | J37: =J34-J36 -> 0.53134645 | ... N37: =N34-N36 -> 0.67794389 | P37: =SUM(C37:F37) -> 0.50564467 | Q37: =SUM(G37:J37) -> 1.9311358 | R37: =SUM(K37:N37) -> 2.6384768 | S37: =SUM(P37:R37) -> 5.0752573
A38: Dedicated AEs (headcount) | B38: FTE | C38: =Assumptions!$D$104 -> 0 | D38: =Assumptions!$E$104 -> 0 | E38: =Assumptions!$F$104 -> 0 | F38: =Assumptions!$G$104 -> 0 | G38: =Assumptions!$H$104 -> 0 | H38: =Assumptions!$I$104 -> 0 | I38: =Assumptions!$J$104 -> 0 | J38: =Assumptions!$K$104 -> 0 | K38: =Assumptions!$L$104 -> 0 | L38: =Assumptions!$M$104 -> 0 | M38: =Assumptions!$N$104 -> 0 | N38: =Assumptions!$O$104 -> 0 | P38: =F38 -> 0 | Q38: =J38 -> 0 | R38: =N38 -> 0 | S38: =R38 -> 0
A39: Ramped dedicated AEs (≈6-month ramp) | B39: FTE | C39: =0 -> 0 | D39: =0.5*C38 -> 0 | E39: =C38+0.5*(D38-C38) -> 0 | F39: =D38+0.5*(E38-D38) -> 0 | G39: =E38+0.5*(F38-E38) -> 0 | H39: =F38+0.5*(G38-F38) -> 0 | I39: =G38+0.5*(H38-G38) -> 0 | J39: =H38+0.5*(I38-H38) -> 0 | K39: =I38+0.5*(J38-I38) -> 0 | L39: =J38+0.5*(K38-J38) -> 0 | ... N39: =L38+0.5*(M38-L38) -> 0 | P39: =F39 -> 0 | Q39: =J39 -> 0 | R39: =N39 -> 0 | S39: =R39 -> 0
A40: Sales capacity (dedicated + shared AEs) | B40: deals | C40: =(C39+Assumptions!$D$99*C19)*$C$15 -> 20.962027 | D40: =(D39+Assumptions!$D$99*D19)*$C$15 -> 20.962027 | E40: =(E39+Assumptions!$D$99*E19)*$C$15 -> 20.962027 | F40: =(F39+Assumptions!$D$99*F19)*$C$15 -> 20.962027 | G40: =(G39+Assumptions!$D$99*G19)*$C$15 -> 20.962027 | H40: =(H39+Assumptions!$D$99*H19)*$C$15 -> 20.962027 | I40: =(I39+Assumptions!$D$99*I19)*$C$15 -> 20.962027 | J40: =(J39+Assumptions!$D$99*J19)*$C$15 -> 20.962027 | ... N40: =(N39+Assumptions!$D$99*N19)*$C$15 -> 20.962027 | P40: =SUM(C40:F40) -> 83.84811 | Q40: =SUM(G40:J40) -> 83.84811 | R40: =SUM(K40:N40) -> 83.84811 | S40: =SUM(P40:R40) -> 251.54433
A41: Sales-assisted wins = MIN(demand, capacity) | B41: wins | C41: =MIN(C37,C40) -> 0 | D41: =MIN(D37,D40) -> 0 | E41: =MIN(E37,E40) -> 0.16854822 | F41: =MIN(F37,F40) -> 0.33709645 | G41: =MIN(G37,G40) -> 0.40184645 | H41: =MIN(H37,H40) -> 0.46659645 | I41: =MIN(I37,I40) -> 0.53134645 | J41: =MIN(J37,J40) -> 0.53134645 | ... N41: =MIN(N37,N40) -> 0.67794389 | P41: =SUM(C41:F41) -> 0.50564467 | Q41: =SUM(G41:J41) -> 1.9311358 | R41: =SUM(K41:N41) -> 2.6384768 | S41: =SUM(P41:R41) -> 5.0752573
A42: Wins lost to capacity constraint | B42: wins | C42: =C37-C41 -> 0 | D42: =D37-D41 -> 0 | E42: =E37-E41 -> 0 | F42: =F37-F41 -> 0 | G42: =G37-G41 -> 0 | H42: =H37-H41 -> 0 | I42: =I37-I41 -> 0 | J42: =J37-J41 -> 0 | ... N42: =N37-N41 -> 0 | P42: =SUM(C42:F42) -> 0 | Q42: =SUM(G42:J42) -> 0 | R42: =SUM(K42:N42) -> 0 | S42: =SUM(P42:R42) -> 0
A43: New customers | B43: customers | C43: =C36+C41 -> 0 | D43: =D36+D41 -> 0 | E43: =E36+E41 -> 0.1822143 | F43: =F36+F41 -> 0.36442859 | G43: =G36+G41 -> 0.43442859 | H43: =H36+H41 -> 0.50442859 | I43: =I36+I41 -> 0.57442859 | J43: =J36+J41 -> 0.57442859 | ... N43: =N36+N41 -> 0.73291231 | P43: =SUM(C43:F43) -> 0.54664289 | Q43: =SUM(G43:J43) -> 2.0877144 | R43: =SUM(K43:N43) -> 2.8524074 | S43: =SUM(P43:R43) -> 5.4867647
A44: New SMB | B44: customers | C44: =C36+C41*Assumptions!$D$29*(1-Assumptions!$D$32)/$C$12 -> 0 | D44: =D36+D41*Assumptions!$D$29*(1-Assumptions!$D$32)/$C$12 -> 0 | E44: =E36+E41*Assumptions!$D$29*(1-Assumptions!$D$32)/$C$12 -> 0.091107148 | F44: =F36+F41*Assumptions!$D$29*(1-Assumptions!$D$32)/$C$12 -> 0.1822143 | G44: =G36+G41*Assumptions!$D$29*(1-Assumptions!$D$32)/$C$12 -> 0.2172143 | H44: =H36+H41*Assumptions!$D$29*(1-Assumptions!$D$32)/$C$12 -> 0.2522143 | I44: =I36+I41*Assumptions!$D$29*(1-Assumptions!$D$32)/$C$12 -> 0.2872143 | J44: =J36+J41*Assumptions!$D$29*(1-Assumptions!$D$32)/$C$12 -> 0.2872143 | ... N44: =N36+N41*Assumptions!$D$29*(1-Assumptions!$D$32)/$C$12 -> 0.36645616 | P44: =SUM(C44:F44) -> 0.27332144 | Q44: =SUM(G44:J44) -> 1.0438572 | R44: =SUM(K44:N44) -> 1.4262037 | S44: =SUM(P44:R44) -> 2.7433823
A45: New Mid-Market | B45: customers | C45: =C41*Assumptions!$D$30/$C$12 -> 0 | D45: =D41*Assumptions!$D$30/$C$12 -> 0 | E45: =E41*Assumptions!$D$30/$C$12 -> 0.069241432 | F45: =F41*Assumptions!$D$30/$C$12 -> 0.13848286 | G45: =G41*Assumptions!$D$30/$C$12 -> 0.16508286 | H45: =H41*Assumptions!$D$30/$C$12 -> 0.19168286 | I45: =I41*Assumptions!$D$30/$C$12 -> 0.21828286 | J45: =J41*Assumptions!$D$30/$C$12 -> 0.21828286 | ... N45: =N41*Assumptions!$D$30/$C$12 -> 0.27850668 | P45: =SUM(C45:F45) -> 0.2077243 | Q45: =SUM(G45:J45) -> 0.79333146 | R45: =SUM(K45:N45) -> 1.0839148 | S45: =SUM(P45:R45) -> 2.0849706
A46: New Enterprise | B46: customers | C46: =C41*Assumptions!$D$31/$C$12 -> 0 | D46: =D41*Assumptions!$D$31/$C$12 -> 0 | E46: =E41*Assumptions!$D$31/$C$12 -> 0.021865716 | F46: =F41*Assumptions!$D$31/$C$12 -> 0.043731431 | G46: =G41*Assumptions!$D$31/$C$12 -> 0.052131431 | H46: =H41*Assumptions!$D$31/$C$12 -> 0.060531431 | I46: =I41*Assumptions!$D$31/$C$12 -> 0.068931431 | J46: =J41*Assumptions!$D$31/$C$12 -> 0.068931431 | ... N46: =N41*Assumptions!$D$31/$C$12 -> 0.087949478 | P46: =SUM(C46:F46) -> 0.065597147 | Q46: =SUM(G46:J46) -> 0.25052572 | R46: =SUM(K46:N46) -> 0.34228889 | S46: =SUM(P46:R46) -> 0.65841176
A47: Lead-to-win conversion (lagged) | B47: % | C47: =0 -> 0 | D47: =IFERROR(D43/C29,0) -> 0 | E47: =IFERROR(E43/D29,0) -> 0.013845702 | F47: =IFERROR(F43/E29,0) -> 0.024038269 | G47: =IFERROR(G43/F29,0) -> 0.025315834 | H47: =IFERROR(H43/G29,0) -> 0.026326689 | I47: =IFERROR(I43/H29,0) -> 0.029980067 | J47: =IFERROR(J43/I29,0) -> 0.025650188 | K47: =IFERROR(K43/J29,0) -> 0.025505036 | ... N47: =IFERROR(N43/M29,0) -> 0.02859691
A48: Customers, ARR and revenue | B48: Unit / note | C48: Q1 2027 | D48: Q2 2027 | E48: Q3 2027 | F48: Q4 2027 | G48: Q1 2028 | H48: Q2 2028 | I48: Q3 2028 | J48: Q4 2028 | K48: Q1 2029 | L48: Q2 2029 | M48: Q3 2029 | N48: Q4 2029 | P48: 2027 | Q48: 2028 | R48: 2029 | S48: 2027–29
A49: Customers — SMB | B49: customers | C49: =0*Assumptions!$D$54^(1/4)+C44 -> 0 | D49: =C49*Assumptions!$D$54^(1/4)+D44 -> 0 | E49: =D49*Assumptions!$D$54^(1/4)+E44 -> 0.091107148 | F49: =E49*Assumptions!$D$54^(1/4)+F44 -> 0.26969398 | G49: =F49*Assumptions!$D$54^(1/4)+G44 -> 0.4761703 | H49: =G49*Assumptions!$D$54^(1/4)+H44 -> 0.70942568 | I49: =H49*Assumptions!$D$54^(1/4)+I44 -> 0.9683939 | J49: =I49*Assumptions!$D$54^(1/4)+J44 -> 1.2170512 | K49: =J49*Assumptions!$D$54^(1/4)+K44 -> 1.495429 | ... N49: =M49*Assumptions!$D$54^(1/4)+N44 -> 2.3800008 | P49: =F49 -> 0.26969398 | Q49: =J49 -> 1.2170512 | R49: =N49 -> 2.3800008 | S49: =R49 -> 2.3800008
A50: Customers — Mid-Market | B50: customers | C50: =0*Assumptions!$D$55^(1/4)+C45 -> 0 | D50: =C50*Assumptions!$D$55^(1/4)+D45 -> 0 | E50: =D50*Assumptions!$D$55^(1/4)+E45 -> 0.069241432 | F50: =E50*Assumptions!$D$55^(1/4)+F45 -> 0.20516211 | G50: =F50*Assumptions!$D$55^(1/4)+G45 -> 0.36265321 | H50: =G50*Assumptions!$D$55^(1/4)+H45 -> 0.54091656 | I50: =H50*Assumptions!$D$55^(1/4)+I45 -> 0.73918351 | J50: =I50*Assumptions!$D$55^(1/4)+J45 -> 0.93011384 | K50: =J50*Assumptions!$D$55^(1/4)+K45 -> 1.1440909 | ... N50: =M50*Assumptions!$D$55^(1/4)+N45 -> 1.8267099 | P50: =F50 -> 0.20516211 | Q50: =J50 -> 0.93011384 | R50: =N50 -> 1.8267099 | S50: =R50 -> 1.8267099
A51: Customers — Enterprise | B51: customers | C51: =0*Assumptions!$D$56^(1/4)+C46 -> 0 | D51: =C51*Assumptions!$D$56^(1/4)+D46 -> 0 | E51: =D51*Assumptions!$D$56^(1/4)+E46 -> 0.021865716 | F51: =E51*Assumptions!$D$56^(1/4)+F46 -> 0.064909403 | G51: =F51*Assumptions!$D$56^(1/4)+G46 -> 0.11499923 | H51: =G51*Assumptions!$D$56^(1/4)+H46 -> 0.17191359 | I51: =H51*Assumptions!$D$56^(1/4)+I46 -> 0.23543781 | J51: =I51*Assumptions!$D$56^(1/4)+J46 -> 0.29696399 | K51: =J51*Assumptions!$D$56^(1/4)+K46 -> 0.36606402 | ... N51: =M51*Assumptions!$D$56^(1/4)+N46 -> 0.58823415 | P51: =F51 -> 0.064909403 | Q51: =J51 -> 0.29696399 | R51: =N51 -> 0.58823415 | S51: =R51 -> 0.58823415
A52: Customers — total | B52: customers | C52: =C49+C50+C51 -> 0 | D52: =D49+D50+D51 -> 0 | E52: =E49+E50+E51 -> 0.1822143 | F52: =F49+F50+F51 -> 0.53976549 | G52: =G49+G50+G51 -> 0.95382274 | H52: =H49+H50+H51 -> 1.4222558 | I52: =I49+I50+I51 -> 1.9430152 | J52: =J49+J50+J51 -> 2.444129 | ... N52: =N49+N50+N51 -> 4.7949449 | P52: =F52 -> 0.53976549 | Q52: =J52 -> 2.444129 | R52: =N52 -> 4.7949449 | S52: =R52 -> 4.7949449
A53: ARR — SMB (end of quarter) | B53: $ | C53: =0*Assumptions!$D$57^(1/4)+C44*$C$9 -> 0 | D53: =C53*Assumptions!$D$57^(1/4)+D44*$C$9 -> 0 | E53: =D53*Assumptions!$D$57^(1/4)+E44*$C$9 -> 487.60546 | F53: =E53*Assumptions!$D$57^(1/4)+F44*$C$9 -> 1452.7572 | G53: =F53*Assumptions!$D$57^(1/4)+G44*$C$9 -> 2585.3183 | H53: =G53*Assumptions!$D$57^(1/4)+H44*$C$9 -> 3881.835 | I53: =H53*Assumptions!$D$57^(1/4)+I44*$C$9 -> 5338.9251 | J53: =I53*Assumptions!$D$57^(1/4)+J44*$C$9 -> 6765.9559 | K53: =J53*Assumptions!$D$57^(1/4)+K44*$C$9 -> 8375.5988 | ... N53: =M53*Assumptions!$D$57^(1/4)+N44*$C$9 -> 13631.136 | P53: =F53 -> 1452.7572 | Q53: =J53 -> 6765.9559 | R53: =N53 -> 13631.136 | S53: =R53 -> 13631.136
A54: ARR — Mid-Market (end of quarter) | B54: $ | C54: =0*Assumptions!$D$58^(1/4)+C45*$C$10 -> 0 | D54: =C54*Assumptions!$D$58^(1/4)+D45*$C$10 -> 0 | E54: =D54*Assumptions!$D$58^(1/4)+E45*$C$10 -> 507.19627 | F54: =E54*Assumptions!$D$58^(1/4)+F45*$C$10 -> 1519.0336 | G54: =F54*Assumptions!$D$58^(1/4)+G45*$C$10 -> 2720.6194 | H54: =G54*Assumptions!$D$58^(1/4)+H45*$C$10 -> 4110.9977 | I54: =H54*Assumptions!$D$58^(1/4)+I45*$C$10 -> 5689.2175 | J54: =I54*Assumptions!$D$58^(1/4)+J45*$C$10 -> 7259.4863 | K54: =J54*Assumptions!$D$58^(1/4)+K45*$C$10 -> 9042.4151 | ... N54: =M54*Assumptions!$D$58^(1/4)+N45*$C$10 -> 14995.873 | P54: =F54 -> 1519.0336 | Q54: =J54 -> 7259.4863 | R54: =N54 -> 14995.873 | S54: =R54 -> 14995.873
A55: ARR — Enterprise (end of quarter) | B55: $ | C55: =0*Assumptions!$D$59^(1/4)+C46*$C$11 -> 0 | D55: =C55*Assumptions!$D$59^(1/4)+D46*$C$11 -> 0 | E55: =D55*Assumptions!$D$59^(1/4)+E46*$C$11 -> 1013.1193 | F55: =E55*Assumptions!$D$59^(1/4)+F46*$C$11 -> 3051.7912 | G55: =F55*Assumptions!$D$59^(1/4)+G46*$C$11 -> 5504.6852 | H55: =G55*Assumptions!$D$59^(1/4)+H46*$C$11 -> 8376.8847 | I55: =H55*Assumptions!$D$59^(1/4)+I46*$C$11 -> 11673.535 | J55: =I55*Assumptions!$D$59^(1/4)+J46*$C$11 -> 15010.644 | K55: =J55*Assumptions!$D$59^(1/4)+K46*$C$11 -> 18829.294 | ... N55: =M55*Assumptions!$D$59^(1/4)+N46*$C$11 -> 31906.783 | P55: =F55 -> 3051.7912 | Q55: =J55 -> 15010.644 | R55: =N55 -> 31906.783 | S55: =R55 -> 31906.783
A56: ARR — total (end of quarter) | B56: $ | C56: =C53+C54+C55 -> 0 | D56: =D53+D54+D55 -> 0 | E56: =E53+E54+E55 -> 2007.9211 | F56: =F53+F54+F55 -> 6023.5821 | G56: =G53+G54+G55 -> 10810.623 | H56: =H53+H54+H55 -> 16369.717 | I56: =I53+I54+I55 -> 22701.678 | J56: =J53+J54+J55 -> 29036.086 | ... N56: =N53+N54+N55 -> 60533.792 | P56: =F56 -> 6023.5821 | Q56: =J56 -> 29036.086 | R56: =N56 -> 60533.792 | S56: =R56 -> 60533.792
A57: New ARR booked (first-year ACV) | B57: $ | C57: =C44*$C$9+C45*$C$10+C46*$C$11 -> 0 | D57: =D44*$C$9+D45*$C$10+D46*$C$11 -> 0 | E57: =E44*$C$9+E45*$C$10+E46*$C$11 -> 2007.9211 | F57: =F44*$C$9+F45*$C$10+F46*$C$11 -> 4015.8421 | G57: =G44*$C$9+G45*$C$10+G46*$C$11 -> 4787.2112 | H57: =H44*$C$9+H45*$C$10+H46*$C$11 -> 5558.5803 | I57: =I44*$C$9+I45*$C$10+I46*$C$11 -> 6329.9494 | J57: =J44*$C$9+J45*$C$10+J46*$C$11 -> 6329.9494 | ... N57: =N44*$C$9+N45*$C$10+N46*$C$11 -> 8076.37 | P57: =SUM(C57:F57) -> 6023.7632 | Q57: =SUM(G57:J57) -> 23005.69 | R57: =SUM(K57:N57) -> 31432.27 | S57: =SUM(P57:R57) -> 60461.723
A58: Net expansion / (contraction) of existing ARR | B58: $ | C58: =C56-0-C57 -> 0 | D58: =D56-C56-D57 -> 0 | E58: =E56-D56-E57 -> 0 | F58: =F56-E56-F57 -> -0.18111263 | G58: =G56-F56-G57 -> -0.17036508 | H58: =H56-G56-H57 -> 0.51427798 | I58: =I56-H56-I57 -> 2.011264 | J58: =J56-I56-J57 -> 4.4583118 | K58: =K56-J56-K57 -> 8.0620287 | ... N58: =N56-M56-N57 -> 25.999783 | P58: =SUM(C58:F58) -> -0.18111263 | Q58: =SUM(G58:J58) -> 6.8134887 | R58: =SUM(K58:N58) -> 65.436677 | S58: =SUM(P58:R58) -> 72.069053
A59: Recognized revenue (average ARR ÷ 4) | B59: $ | C59: =(0+C56)/8 -> 0 | D59: =(C56+D56)/8 -> 0 | E59: =(D56+E56)/8 -> 250.99013 | F59: =(E56+F56)/8 -> 1003.9379 | G59: =(F56+G56)/8 -> 2104.2756 | H59: =(G56+H56)/8 -> 3397.5425 | I59: =(H56+I56)/8 -> 4883.9244 | J59: =(I56+J56)/8 -> 6467.2205 | K59: =(J56+K56)/8 -> 8160.4241 | ... N59: =(M56+N56)/8 -> 14120.652 | P59: =SUM(C59:F59) -> 1254.928 | Q59: =SUM(G59:J59) -> 16852.963 | R59: =SUM(K59:N59) -> 44450.021 | S59: =SUM(P59:R59) -> 62557.912
A60: Gross profit | B60: $ | C60: =C59*Assumptions!$D$72 -> 0 | D60: =D59*Assumptions!$D$72 -> 0 | E60: =E59*Assumptions!$D$72 -> 138.04457 | F60: =F59*Assumptions!$D$72 -> 552.16584 | G60: =G59*Assumptions!$D$72 -> 1157.3516 | H60: =H59*Assumptions!$D$72 -> 1868.6484 | I60: =I59*Assumptions!$D$72 -> 2686.1584 | J60: =J59*Assumptions!$D$72 -> 3556.9713 | ... N60: =N59*Assumptions!$D$72 -> 7766.3585 | P60: =SUM(C60:F60) -> 690.21041 | Q60: =SUM(G60:J60) -> 9269.1297 | R60: =SUM(K60:N60) -> 24447.511 | S60: =SUM(P60:R60) -> 34406.851
A61: Incremental cost of the vertical program | B61: Unit / note | C61: Q1 2027 | D61: Q2 2027 | E61: Q3 2027 | F61: Q4 2027 | G61: Q1 2028 | H61: Q2 2028 | I61: Q3 2028 | J61: Q4 2028 | K61: Q1 2029 | L61: Q2 2029 | M61: Q3 2029 | N61: Q4 2029 | P61: 2027 | Q61: 2028 | R61: 2029 | S61: 2027–29
A62: FTE — vertical lead | B62: FTE | C62: =Assumptions!$D$92*C19 -> 1 | D62: =Assumptions!$D$92*D19 -> 1 | E62: =Assumptions!$D$92*E19 -> 1 | F62: =Assumptions!$D$92*F19 -> 1 | G62: =Assumptions!$D$92*G19 -> 1 | H62: =Assumptions!$D$92*H19 -> 1 | I62: =Assumptions!$D$92*I19 -> 1 | J62: =Assumptions!$D$92*J19 -> 1 | ... N62: =Assumptions!$D$92*N19 -> 1 | P62: =AVERAGE(C62:F62) -> 1 | Q62: =AVERAGE(G62:J62) -> 1 | R62: =AVERAGE(K62:N62) -> 1
A63: FTE — dedicated AEs | B63: FTE | C63: =C38*C19 -> 0 | D63: =D38*D19 -> 0 | E63: =E38*E19 -> 0 | F63: =F38*F19 -> 0 | G63: =G38*G19 -> 0 | H63: =H38*H19 -> 0 | I63: =I38*I19 -> 0 | J63: =J38*J19 -> 0 | ... N63: =N38*N19 -> 0 | P63: =AVERAGE(C63:F63) -> 0 | Q63: =AVERAGE(G63:J63) -> 0 | R63: =AVERAGE(K63:N63) -> 0
A64: FTE — partner managers | B64: FTE | C64: =IF(C18<=4,Assumptions!$D$93,Assumptions!$D$94)*C19 -> 0 | D64: =IF(D18<=4,Assumptions!$D$93,Assumptions!$D$94)*D19 -> 0 | E64: =IF(E18<=4,Assumptions!$D$93,Assumptions!$D$94)*E19 -> 0 | F64: =IF(F18<=4,Assumptions!$D$93,Assumptions!$D$94)*F19 -> 0 | G64: =IF(G18<=4,Assumptions!$D$93,Assumptions!$D$94)*G19 -> 0.5 | H64: =IF(H18<=4,Assumptions!$D$93,Assumptions!$D$94)*H19 -> 0.5 | I64: =IF(I18<=4,Assumptions!$D$93,Assumptions!$D$94)*I19 -> 0.5 | J64: =IF(J18<=4,Assumptions!$D$93,Assumptions!$D$94)*J19 -> 0.5 | ... N64: =IF(N18<=4,Assumptions!$D$93,Assumptions!$D$94)*N19 -> 0.5 | P64: =AVERAGE(C64:F64) -> 0 | Q64: =AVERAGE(G64:J64) -> 0.5 | R64: =AVERAGE(K64:N64) -> 0.5
A65: FTE — GTM / solutions engineers | B65: FTE | C65: =IF(C18<=4,Assumptions!$D$95,Assumptions!$D$96)*C19 -> 1 | D65: =IF(D18<=4,Assumptions!$D$95,Assumptions!$D$96)*D19 -> 1 | E65: =IF(E18<=4,Assumptions!$D$95,Assumptions!$D$96)*E19 -> 1 | F65: =IF(F18<=4,Assumptions!$D$95,Assumptions!$D$96)*F19 -> 1 | G65: =IF(G18<=4,Assumptions!$D$95,Assumptions!$D$96)*G19 -> 0.5 | H65: =IF(H18<=4,Assumptions!$D$95,Assumptions!$D$96)*H19 -> 0.5 | I65: =IF(I18<=4,Assumptions!$D$95,Assumptions!$D$96)*I19 -> 0.5 | J65: =IF(J18<=4,Assumptions!$D$95,Assumptions!$D$96)*J19 -> 0.5 | ... N65: =IF(N18<=4,Assumptions!$D$95,Assumptions!$D$96)*N19 -> 0.5 | P65: =AVERAGE(C65:F65) -> 1 | Q65: =AVERAGE(G65:J65) -> 0.5 | R65: =AVERAGE(K65:N65) -> 0.5
A66: FTE — product marketing | B66: FTE | C66: =Assumptions!$D$97*C19 -> 0.25 | D66: =Assumptions!$D$97*D19 -> 0.25 | E66: =Assumptions!$D$97*E19 -> 0.25 | F66: =Assumptions!$D$97*F19 -> 0.25 | G66: =Assumptions!$D$97*G19 -> 0.25 | H66: =Assumptions!$D$97*H19 -> 0.25 | I66: =Assumptions!$D$97*I19 -> 0.25 | J66: =Assumptions!$D$97*J19 -> 0.25 | ... N66: =Assumptions!$D$97*N19 -> 0.25 | P66: =AVERAGE(C66:F66) -> 0.25 | Q66: =AVERAGE(G66:J66) -> 0.25 | R66: =AVERAGE(K66:N66) -> 0.25
A67: FTE — customer success (coverage ratios) | B67: FTE | C67: =(C50+C51)/Assumptions!$D$70+C49/Assumptions!$D$71 -> 0 | D67: =(D50+D51)/Assumptions!$D$70+D49/Assumptions!$D$71 -> 0 | E67: =(E50+E51)/Assumptions!$D$70+E49/Assumptions!$D$71 -> 0.0026421073 | F67: =(F50+F51)/Assumptions!$D$70+F49/Assumptions!$D$71 -> 0.0078305637 | G67: =(G50+G51)/Assumptions!$D$70+G49/Assumptions!$D$71 -> 0.013845992 | H67: =(H50+H51)/Assumptions!$D$70+H49/Assumptions!$D$71 -> 0.020658456 | I67: =(I50+I51)/Assumptions!$D$70+I49/Assumptions!$D$71 -> 0.028239108 | J67: =(J50+J51)/Assumptions!$D$70+J49/Assumptions!$D$71 -> 0.035545151 | ... N67: =(N50+N51)/Assumptions!$D$70+N49/Assumptions!$D$71 -> 0.069893605 | P67: =AVERAGE(C67:F67) -> 0.0026181677 | Q67: =AVERAGE(G67:J67) -> 0.024572177 | R67: =AVERAGE(K67:N67) -> 0.056975349
A68: Cost — vertical lead + partner managers | B68: $ | C68: =(C62+C64)*Assumptions!$D$66/Assumptions!$D$65/4 -> 66753.571 | D68: =(D62+D64)*Assumptions!$D$66/Assumptions!$D$65/4 -> 66753.571 | E68: =(E62+E64)*Assumptions!$D$66/Assumptions!$D$65/4 -> 66753.571 | F68: =(F62+F64)*Assumptions!$D$66/Assumptions!$D$65/4 -> 66753.571 | G68: =(G62+G64)*Assumptions!$D$66/Assumptions!$D$65/4 -> 100130.36 | H68: =(H62+H64)*Assumptions!$D$66/Assumptions!$D$65/4 -> 100130.36 | I68: =(I62+I64)*Assumptions!$D$66/Assumptions!$D$65/4 -> 100130.36 | J68: =(J62+J64)*Assumptions!$D$66/Assumptions!$D$65/4 -> 100130.36 | ... N68: =(N62+N64)*Assumptions!$D$66/Assumptions!$D$65/4 -> 100130.36 | P68: =SUM(C68:F68) -> 267014.29 | Q68: =SUM(G68:J68) -> 400521.43 | R68: =SUM(K68:N68) -> 400521.43 | S68: =SUM(P68:R68) -> 1068057.1
A69: Cost — dedicated AEs | B69: $ | C69: =C63*$C$14/4 -> 0 | D69: =D63*$C$14/4 -> 0 | E69: =E63*$C$14/4 -> 0 | F69: =F63*$C$14/4 -> 0 | G69: =G63*$C$14/4 -> 0 | H69: =H63*$C$14/4 -> 0 | I69: =I63*$C$14/4 -> 0 | J69: =J63*$C$14/4 -> 0 | ... N69: =N63*$C$14/4 -> 0 | P69: =SUM(C69:F69) -> 0 | Q69: =SUM(G69:J69) -> 0 | R69: =SUM(K69:N69) -> 0 | S69: =SUM(P69:R69) -> 0
A70: Cost — variable AE cost (shared capacity deals) | B70: $ | C70: =MAX(0,C41-C39*$C$15)*$C$16*Assumptions!$D$100 -> 0 | D70: =MAX(0,D41-D39*$C$15)*$C$16*Assumptions!$D$100 -> 0 | E70: =MAX(0,E41-E39*$C$15)*$C$16*Assumptions!$D$100 -> 1148.6636 | F70: =MAX(0,F41-F39*$C$15)*$C$16*Assumptions!$D$100 -> 2297.3272 | G70: =MAX(0,G41-G39*$C$15)*$C$16*Assumptions!$D$100 -> 2738.6013 | H70: =MAX(0,H41-H39*$C$15)*$C$16*Assumptions!$D$100 -> 3179.8754 | I70: =MAX(0,I41-I39*$C$15)*$C$16*Assumptions!$D$100 -> 3621.1495 | J70: =MAX(0,J41-J39*$C$15)*$C$16*Assumptions!$D$100 -> 3621.1495 | ... N70: =MAX(0,N41-N39*$C$15)*$C$16*Assumptions!$D$100 -> 4620.2176 | P70: =SUM(C70:F70) -> 3445.9908 | Q70: =SUM(G70:J70) -> 13160.776 | R70: =SUM(K70:N70) -> 17981.336 | S70: =SUM(P70:R70) -> 34588.103
A71: Cost — product marketing | B71: $ | C71: =C66*Assumptions!$D$67/Assumptions!$D$65/4 -> 18475.893 | D71: =D66*Assumptions!$D$67/Assumptions!$D$65/4 -> 18475.893 | E71: =E66*Assumptions!$D$67/Assumptions!$D$65/4 -> 18475.893 | F71: =F66*Assumptions!$D$67/Assumptions!$D$65/4 -> 18475.893 | G71: =G66*Assumptions!$D$67/Assumptions!$D$65/4 -> 18475.893 | H71: =H66*Assumptions!$D$67/Assumptions!$D$65/4 -> 18475.893 | I71: =I66*Assumptions!$D$67/Assumptions!$D$65/4 -> 18475.893 | J71: =J66*Assumptions!$D$67/Assumptions!$D$65/4 -> 18475.893 | ... N71: =N66*Assumptions!$D$67/Assumptions!$D$65/4 -> 18475.893 | P71: =SUM(C71:F71) -> 73903.571 | Q71: =SUM(G71:J71) -> 73903.571 | R71: =SUM(K71:N71) -> 73903.571 | S71: =SUM(P71:R71) -> 221710.71
A72: Cost — program and launch marketing | B72: $ | C72: =(Assumptions!$D$98+Assumptions!$D$73*((C18=Assumptions!$D$12)+(C18=Assumptions!$D$13)+(C18=Assumptions!$D$14)))*C19 -> 65000 | D72: =(Assumptions!$D$98+Assumptions!$D$73*((D18=Assumptions!$D$12)+(D18=Assumptions!$D$13)+(D18=Assumptions!$D$14)))*D19 -> 25000 | E72: =(Assumptions!$D$98+Assumptions!$D$73*((E18=Assumptions!$D$12)+(E18=Assumptions!$D$13)+(E18=Assumptions!$D$14)))*E19 -> 25000 | F72: =(Assumptions!$D$98+Assumptions!$D$73*((F18=Assumptions!$D$12)+(F18=Assumptions!$D$13)+(F18=Assumptions!$D$14)))*F19 -> 25000 | G72: =(Assumptions!$D$98+Assumptions!$D$73*((G18=Assumptions!$D$12)+(G18=Assumptions!$D$13)+(G18=Assumptions!$D$14)))*G19 -> 25000 | H72: =(Assumptions!$D$98+Assumptions!$D$73*((H18=Assumptions!$D$12)+(H18=Assumptions!$D$13)+(H18=Assumptions!$D$14)))*H19 -> 25000 | I72: =(Assumptions!$D$98+Assumptions!$D$73*((I18=Assumptions!$D$12)+(I18=Assumptions!$D$13)+(I18=Assumptions!$D$14)))*I19 -> 65000 | J72: =(Assumptions!$D$98+Assumptions!$D$73*((J18=Assumptions!$D$12)+(J18=Assumptions!$D$13)+(J18=Assumptions!$D$14)))*J19 -> 25000 | ... N72: =(Assumptions!$D$98+Assumptions!$D$73*((N18=Assumptions!$D$12)+(N18=Assumptions!$D$13)+(N18=Assumptions!$D$14)))*N19 -> 25000 | P72: =SUM(C72:F72) -> 140000 | Q72: =SUM(G72:J72) -> 140000 | R72: =SUM(K72:N72) -> 100000 | S72: =SUM(P72:R72) -> 380000
A73: Cost — partner fees on partner-sourced ACV | B73: $ | C73: =C57*C35*Assumptions!$D$74 -> 0 | D73: =D57*D35*Assumptions!$D$74 -> 0 | E73: =E57*E35*Assumptions!$D$74 -> 192.84227 | F73: =F57*F35*Assumptions!$D$74 -> 385.68454 | G73: =G57*G35*Assumptions!$D$74 -> 578.52681 | H73: =H57*H35*Assumptions!$D$74 -> 771.36908 | I73: =I57*I35*Assumptions!$D$74 -> 964.21135 | J73: =J57*J35*Assumptions!$D$74 -> 964.21135 | ... N73: =N57*N35*Assumptions!$D$74 -> 964.21135 | P73: =SUM(C73:F73) -> 578.52681 | Q73: =SUM(G73:J73) -> 3278.3186 | R73: =SUM(K73:N73) -> 3856.8454 | S73: =SUM(P73:R73) -> 7713.6908
A74: Cost — partner enablement | B74: $ | C74: =C27*Assumptions!$D$75 -> 2000 | D74: =D27*Assumptions!$D$75 -> 4000 | E74: =E27*Assumptions!$D$75 -> 6000 | F74: =F27*Assumptions!$D$75 -> 8000 | G74: =G27*Assumptions!$D$75 -> 10000 | H74: =H27*Assumptions!$D$75 -> 10000 | I74: =I27*Assumptions!$D$75 -> 10000 | J74: =J27*Assumptions!$D$75 -> 10000 | ... N74: =N27*Assumptions!$D$75 -> 10000 | P74: =SUM(C74:F74) -> 20000 | Q74: =SUM(G74:J74) -> 40000 | R74: =SUM(K74:N74) -> 40000 | S74: =SUM(P74:R74) -> 100000
A75: Cost — onboarding / co-build subsidy (MM & Ent) | B75: $ | C75: =(C45*$C$10+C46*$C$11)*Assumptions!$D$76 -> 0 | D75: =(D45*$C$10+D46*$C$11)*Assumptions!$D$76 -> 0 | E75: =(E45*$C$10+E46*$C$11)*Assumptions!$D$76 -> 304.06312 | F75: =(F45*$C$10+F46*$C$11)*Assumptions!$D$76 -> 608.12624 | G75: =(G45*$C$10+G46*$C$11)*Assumptions!$D$76 -> 724.93606 | H75: =(H45*$C$10+H46*$C$11)*Assumptions!$D$76 -> 841.74587 | I75: =(I45*$C$10+I46*$C$11)*Assumptions!$D$76 -> 958.55569 | J75: =(J45*$C$10+J46*$C$11)*Assumptions!$D$76 -> 958.55569 | ... N75: =(N45*$C$10+N46*$C$11)*Assumptions!$D$76 -> 1223.0193 | P75: =SUM(C75:F75) -> 912.18936 | Q75: =SUM(G75:J75) -> 3483.7933 | R75: =SUM(K75:N75) -> 4759.8455 | S75: =SUM(P75:R75) -> 9155.8281
A76: Sales & marketing cost (CAC basis) | B76: $ | C76: =C68+C69+C70+C71+C72+C73+C74+C75 -> 152229.46 | D76: =D68+D69+D70+D71+D72+D73+D74+D75 -> 114229.46 | E76: =E68+E69+E70+E71+E72+E73+E74+E75 -> 117875.03 | F76: =F68+F69+F70+F71+F72+F73+F74+F75 -> 121520.6 | G76: =G68+G69+G70+G71+G72+G73+G74+G75 -> 157648.31 | H76: =H68+H69+H70+H71+H72+H73+H74+H75 -> 158399.24 | I76: =I68+I69+I70+I71+I72+I73+I74+I75 -> 199150.17 | J76: =J68+J69+J70+J71+J72+J73+J74+J75 -> 159150.17 | ... N76: =N68+N69+N70+N71+N72+N73+N74+N75 -> 160413.7 | P76: =SUM(C76:F76) -> 505854.56 | Q76: =SUM(G76:J76) -> 674347.89 | R76: =SUM(K76:N76) -> 641023.03 | S76: =SUM(P76:R76) -> 1821225.5
A77: Cost — GTM / solutions engineers | B77: $ | C77: =C65*Assumptions!$D$68/Assumptions!$D$65/4 -> 56535.714 | D77: =D65*Assumptions!$D$68/Assumptions!$D$65/4 -> 56535.714 | E77: =E65*Assumptions!$D$68/Assumptions!$D$65/4 -> 56535.714 | F77: =F65*Assumptions!$D$68/Assumptions!$D$65/4 -> 56535.714 | G77: =G65*Assumptions!$D$68/Assumptions!$D$65/4 -> 28267.857 | H77: =H65*Assumptions!$D$68/Assumptions!$D$65/4 -> 28267.857 | I77: =I65*Assumptions!$D$68/Assumptions!$D$65/4 -> 28267.857 | J77: =J65*Assumptions!$D$68/Assumptions!$D$65/4 -> 28267.857 | ... N77: =N65*Assumptions!$D$68/Assumptions!$D$65/4 -> 28267.857 | P77: =SUM(C77:F77) -> 226142.86 | Q77: =SUM(G77:J77) -> 113071.43 | R77: =SUM(K77:N77) -> 113071.43 | S77: =SUM(P77:R77) -> 452285.71
A78: Cost — template & ERP-connector build (one-time) | B78: $ | C78: =IF(C18<=Assumptions!$D$78,Assumptions!$D$77/Assumptions!$D$78,0) -> 62500 | D78: =IF(D18<=Assumptions!$D$78,Assumptions!$D$77/Assumptions!$D$78,0) -> 62500 | E78: =IF(E18<=Assumptions!$D$78,Assumptions!$D$77/Assumptions!$D$78,0) -> 62500 | F78: =IF(F18<=Assumptions!$D$78,Assumptions!$D$77/Assumptions!$D$78,0) -> 62500 | G78: =IF(G18<=Assumptions!$D$78,Assumptions!$D$77/Assumptions!$D$78,0) -> 0 | H78: =IF(H18<=Assumptions!$D$78,Assumptions!$D$77/Assumptions!$D$78,0) -> 0 | I78: =IF(I18<=Assumptions!$D$78,Assumptions!$D$77/Assumptions!$D$78,0) -> 0 | J78: =IF(J18<=Assumptions!$D$78,Assumptions!$D$77/Assumptions!$D$78,0) -> 0 | ... N78: =IF(N18<=Assumptions!$D$78,Assumptions!$D$77/Assumptions!$D$78,0) -> 0 | P78: =SUM(C78:F78) -> 250000 | Q78: =SUM(G78:J78) -> 0 | R78: =SUM(K78:N78) -> 0 | S78: =SUM(P78:R78) -> 250000
A79: Cost — customer success | B79: $ | C79: =C67*Assumptions!$D$69/Assumptions!$D$65/4 -> 0 | D79: =D67*Assumptions!$D$69/Assumptions!$D$65/4 -> 0 | E79: =E67*Assumptions!$D$69/Assumptions!$D$65/4 -> 106.16553 | F79: =F67*Assumptions!$D$69/Assumptions!$D$65/4 -> 314.64883 | G79: =G67*Assumptions!$D$69/Assumptions!$D$65/4 -> 556.36164 | H79: =H67*Assumptions!$D$69/Assumptions!$D$65/4 -> 830.10105 | I79: =I67*Assumptions!$D$69/Assumptions!$D$65/4 -> 1134.7079 | J79: =J67*Assumptions!$D$69/Assumptions!$D$65/4 -> 1428.2803 | ... N79: =N67*Assumptions!$D$69/Assumptions!$D$65/4 -> 2808.4748 | P79: =SUM(C79:F79) -> 420.81436 | Q79: =SUM(G79:J79) -> 3949.4509 | R79: =SUM(K79:N79) -> 9157.5664 | S79: =SUM(P79:R79) -> 13527.832
A80: Total incremental program cost (excl. COGS) | B80: $ | C80: =C76+C77+C78+C79 -> 271265.18 | D80: =D76+D77+D78+D79 -> 233265.18 | E80: =E76+E77+E78+E79 -> 237016.91 | F80: =F76+F77+F78+F79 -> 240870.97 | G80: =G76+G77+G78+G79 -> 186472.53 | H80: =H76+H77+H78+H79 -> 187497.2 | I80: =I76+I77+I78+I79 -> 228552.73 | J80: =J76+J77+J78+J79 -> 188846.3 | ... N80: =N76+N77+N78+N79 -> 191490.03 | P80: =SUM(C80:F80) -> 982418.24 | Q80: =SUM(G80:J80) -> 791368.77 | R80: =SUM(K80:N80) -> 763252.02 | S80: =SUM(P80:R80) -> 2537039
A81: Program P&L and unit economics | B81: Unit / note | C81: Q1 2027 | D81: Q2 2027 | E81: Q3 2027 | F81: Q4 2027 | G81: Q1 2028 | H81: Q2 2028 | I81: Q3 2028 | J81: Q4 2028 | K81: Q1 2029 | L81: Q2 2029 | M81: Q3 2029 | N81: Q4 2029 | P81: 2027 | Q81: 2028 | R81: 2029 | S81: 2027–29
A82: Gross profit (from Revenue Model) | B82: $ | C82: =C60 -> 0 | D82: =D60 -> 0 | E82: =E60 -> 138.04457 | F82: =F60 -> 552.16584 | G82: =G60 -> 1157.3516 | H82: =H60 -> 1868.6484 | I82: =I60 -> 2686.1584 | J82: =J60 -> 3556.9713 | ... N82: =N60 -> 7766.3585 | P82: =SUM(C82:F82) -> 690.21041 | Q82: =SUM(G82:J82) -> 9269.1297 | R82: =SUM(K82:N82) -> 24447.511 | S82: =SUM(P82:R82) -> 34406.851
A83: Contribution after customer success | B83: $ | C83: =C60-C79 -> 0 | D83: =D60-D79 -> 0 | E83: =E60-E79 -> 31.87904 | F83: =F60-F79 -> 237.51701 | G83: =G60-G79 -> 600.98995 | H83: =H60-H79 -> 1038.5474 | I83: =I60-I79 -> 1551.4506 | J83: =J60-J79 -> 2128.6909 | ... N83: =N60-N79 -> 4957.8837 | P83: =SUM(C83:F83) -> 269.39605 | Q83: =SUM(G83:J83) -> 5319.6788 | R83: =SUM(K83:N83) -> 15289.945 | S83: =SUM(P83:R83) -> 20879.02
A84: Program P&L (gross profit − all incremental cost) | B84: $ | C84: =C60-C80 -> -271265.18 | D84: =D60-D80 -> -233265.18 | E84: =E60-E80 -> -236878.87 | F84: =F60-F80 -> -240318.8 | G84: =G60-G80 -> -185315.18 | H84: =H60-H80 -> -185628.55 | I84: =I60-I80 -> -225866.57 | J84: =J60-J80 -> -185289.33 | ... N84: =N60-N80 -> -183723.67 | P84: =SUM(C84:F84) -> -981728.03 | Q84: =SUM(G84:J84) -> -782099.64 | R84: =SUM(K84:N84) -> -738804.51 | S84: =SUM(P84:R84) -> -2502632.2
A85: Cumulative program P&L (investment position) | B85: $ | C85: =0+C84 -> -271265.18 | D85: =C85+D84 -> -504530.36 | E85: =D85+E84 -> -741409.23 | F85: =E85+F84 -> -981728.03 | G85: =F85+G84 -> -1167043.2 | H85: =G85+H84 -> -1352671.8 | I85: =H85+I84 -> -1578538.3 | J85: =I85+J84 -> -1763827.7 | K85: =J85+K84 -> -1949146.6 | ... N85: =M85+N84 -> -2502632.2 | P85: =F85 -> -981728.03 | Q85: =J85 -> -1763827.7 | R85: =N85 -> -2502632.2 | S85: =R85 -> -2502632.2
A86: Helper: quarter number if P&L > 0, else 99 | B86: # | C86: =IF(AND(C84>0,C19=1),C18,99) -> 99 | D86: =IF(AND(D84>0,D19=1),D18,99) -> 99 | E86: =IF(AND(E84>0,E19=1),E18,99) -> 99 | F86: =IF(AND(F84>0,F19=1),F18,99) -> 99 | G86: =IF(AND(G84>0,G19=1),G18,99) -> 99 | H86: =IF(AND(H84>0,H19=1),H18,99) -> 99 | I86: =IF(AND(I84>0,I19=1),I18,99) -> 99 | J86: =IF(AND(J84>0,J19=1),J18,99) -> 99 | ... N86: =IF(AND(N84>0,N19=1),N18,99) -> 99
A87: CAC (S&M ÷ new customers) | B87: $ | C87: =IFERROR(C76/C43,0) -> 0 | D87: =IFERROR(D76/D43,0) -> 0 | E87: =IFERROR(E76/E43,0) -> 646903.32 | F87: =IFERROR(F76/F43,0) -> 333455.18 | G87: =IFERROR(G76/G43,0) -> 362886.6 | H87: =IFERROR(H76/H43,0) -> 314017.17 | I87: =IFERROR(I76/I43,0) -> 346692.64 | J87: =IFERROR(J76/J43,0) -> 277058.23 | ... N87: =IFERROR(N76/N43,0) -> 218871.61 | P87: =IFERROR(P76/P43*1,0) -> 925383.97 | Q87: =IFERROR(Q76/Q43*1,0) -> 323007.73 | R87: =IFERROR(R76/R43*1,0) -> 224730.53 | S87: =IFERROR(S76/S43*1,0) -> 331930.67
A88: Average first-year ACV of new customers | B88: $ | C88: =IFERROR(C57/C43,0) -> 0 | D88: =IFERROR(D57/D43,0) -> 0 | E88: =IFERROR(E57/E43,0) -> 11019.558 | F88: =IFERROR(F57/F43,0) -> 11019.558 | G88: =IFERROR(G57/G43,0) -> 11019.558 | H88: =IFERROR(H57/H43,0) -> 11019.558 | I88: =IFERROR(I57/I43,0) -> 11019.558 | J88: =IFERROR(J57/J43,0) -> 11019.558 | ... N88: =IFERROR(N57/N43,0) -> 11019.558 | P88: =IFERROR(P57/P43*1,0) -> 11019.558 | Q88: =IFERROR(Q57/Q43*1,0) -> 11019.558 | R88: =IFERROR(R57/R43*1,0) -> 11019.558 | S88: =IFERROR(S57/S43*1,0) -> 11019.558
A89: CAC payback (months of gross profit) | B89: months | C89: =IFERROR(C87/(C88*Assumptions!$D$72/12),0) -> 0 | D89: =IFERROR(D87/(D88*Assumptions!$D$72/12),0) -> 0 | E89: =IFERROR(E87/(E88*Assumptions!$D$72/12),0) -> 1280.8367 | F89: =IFERROR(F87/(F88*Assumptions!$D$72/12),0) -> 660.22481 | G89: =IFERROR(G87/(G88*Assumptions!$D$72/12),0) -> 718.49756 | H89: =IFERROR(H87/(H88*Assumptions!$D$72/12),0) -> 621.73851 | I89: =IFERROR(I87/(I88*Assumptions!$D$72/12),0) -> 686.43433 | J89: =IFERROR(J87/(J88*Assumptions!$D$72/12),0) -> 548.56162 | ... N89: =IFERROR(N87/(N88*Assumptions!$D$72/12),0) -> 433.35499 | P89: =IFERROR(P87/(P88*Assumptions!$D$72/12),0) -> 1832.2146 | Q89: =IFERROR(Q87/(Q88*Assumptions!$D$72/12),0) -> 639.53938 | R89: =IFERROR(R87/(R88*Assumptions!$D$72/12),0) -> 444.95536 | S89: =IFERROR(S87/(S88*Assumptions!$D$72/12),0) -> 657.20636
A90: ARR-weighted blended GRR (new-customer mix) | C90: =(Assumptions!$D$29*$C$9*Assumptions!$D$54+Assumptions!$D$30*$C$10*Assumptions!$D$55+Assumptions!$D$31*$C$11*Assumptions!$D$56)/(Assumptions!$D$29*$C$9+Assumptions!$D$30*$C$10+Assumptions!$D$31*$C$11) -> 0.86766282
A91: Key outputs of this run | B91: Unit / note | C91: Q1 2027 | D91: Q2 2027 | E91: Q3 2027 | F91: Q4 2027 | G91: Q1 2028 | H91: Q2 2028 | I91: Q3 2028 | J91: Q4 2028 | K91: Q1 2029 | L91: Q2 2029 | M91: Q3 2029 | N91: Q4 2029 | P91: 2027 | Q91: 2028 | R91: 2029 | S91: 2027–29
A92: Exit ARR, Q4 2029 | C92: =N56 -> 60533.792
A93: Customers, Q4 2029 | C93: =N52 -> 4.7949449
A94: New customers 2027–29 | C94: =S43 -> 5.4867647
A95: Recognized revenue 2027–29 | C95: =S59 -> 62557.912
A96: S&M cost 2027–29 | C96: =S76 -> 1821225.5
A97: Total incremental cost 2027–29 | C97: =S80 -> 2537039
A98: Average first-year ACV | C98: =S88 -> 11019.558
A99: CAC (2027–29) | C99: =S87 -> 331930.67
A100: CAC payback, months (2027–29) | C100: =S89 -> 657.20636
A101: CAC payback, months (2029 cohort) | C101: =R89 -> 444.95536
...

Sheet Sources
A1: Sources
A2: Full register with dates, reliability and limitations: Research_Sources.csv
A4: ID | B4: Source | C4: Publisher | D4: Date / reference | E4: Used for | F4: URL
A5: S01 | B5: Clay pricing page (plans, Actions & Data Credits packs, Enterprise minimums) | C5: Clay Labs Inc. | D5: Live, Oct 2026 | E5: ACV Build prices and floors | F5: https://www.clay.com/pricing
A6: S02 | B6: Clay tender offer release (enterprise NRR > 200%) | C6: Business Wire | D6: 2026-01-28 | E6: NRR context | F6: https://www.businesswire.com/news/home/20260128514638/en
A7: S14 | B7: 2022 Economic Census — Employment Size of Firms | C7: U.S. Census Bureau | D7: Ref. year 2022 | E7: Firm counts, employees per firm | F7: https://data.census.gov/table/ECNSIZE2022.EC2200SIZEEMPFIRM
A8: S15 | B8: OEWS May 2025 industry-specific estimates (sales share) | C8: U.S. BLS | D8: May 2025 | E8: Sellers per firm | F8: https://data.bls.gov/oes/#/industry/423800/2025
A9: S16 | B9: Clay buyer pricing data | C9: Vendr | D9: Feb 2026 | E9: Enterprise discount, ACV check | F9: https://www.vendr.com/marketplace/clay
A10: S17 | B10: State of CRM in Distribution | C10: Distribution Strategy Group | D10: 2022 | E10: CRM-ready filter | F10: https://archive.distributionstrategy.com/wp-content/uploads/2022/10/DSG-The-State-of-CRM-in-Distribution-Making-the-Software-Work-for-You.pdf
A11: S43 | B11: 2025 B2B SaaS Retention Benchmarks | C11: SaaS Capital | D11: 2025-09 | E11: GRR / NRR by ACV band | F11: https://www.saas-capital.com/wp-content/uploads/2025/09/RB32WS1-2025-B2B-SaaS-Retention-Benchmarks.pdf
A12: S44 | B12: 2026 AE Models, Motions & Metrics | C12: The Bridge Group | D12: 2026-06-22 | E12: AE quota, OTE, ramp, attainment | F12: https://www.bridgegroupinc.com/research/2026-ae-models-motions-metrics
A13: S45 | B13: Employer Costs for Employee Compensation, June 2026 | C13: U.S. BLS (TED) | D13: 2026-09 | E13: Wage share 70.0% → cost loading | F13: https://www.bls.gov/opub/ted/2026/compensation-costs-for-private-industry-workers-averaged-46-89-per-hour-worked-in-june-2026.htm
A14: S46 | B14: OEWS May 2025 — Software Publishers (513200) wages | C14: U.S. BLS | D14: May 2025 | E14: Role wage rates | F14: https://data.bls.gov/oes/#/industry/513200/2025
A15: S47 | B15: CAC payback benchmarks (compilation of Maxio, Benchmarkit, MetricHQ) | C15: SaaS Hero | D15: Updated 2026-07-18 | E15: Payback benchmarks | F15: https://www.saashero.net/strategy/maxio-cac-benchmarks-b2b-saas/
... A20: S52 | B20: Clay company profile (margin structure, ARR estimate) | C20: Sacra | D20: 2026 | E20: Gross-margin context | F20: https://sacra.com/c/clay/
