Workbook

Sheet Cover
A1: 04 — Competitive Analysis: Does Clay have a defensible advantage by segment?
A2: Independent portfolio case study by Zhuoran (Zora) Wang · Not commissioned by or affiliated with Clay Labs Inc. · Research reference date: 2026-10-18 (accessed 2026-10-19)
A4: Question | B4: Which alternatives genuinely overlap with Clay in each candidate segment, where is Clay advantaged or disadvantaged, and how strong is its competitive position going into Phase 3 prioritization?
A5: Answer (short) | B5: Clay's differentiation (multi-source and off-LinkedIn data plus AI research) matters most in industrial distribution, where buyers are poorly covered by standard B2B databases. But that segment is also the hardest to self-serve. Professional services is the reverse: Clay is easy to adopt there, but the data advantage is less unique and the segment is already contested, including by Clay's own agency ecosystem.
A6: Method | B6: (1) Competitor register with an overlap check against 11 Clay use cases. (2) Comparison matrix on the 9 requested dimensions. (3) Illustrative list-price cost comparison by team size. (4) Persona data-coverage test (H3) using BLS education × Pew LinkedIn usage. (5) Segment competitive scoring feeding Phase 3. (6) Positioning map.
A7: Evidence classes | B7: A = verified public fact · B = external benchmark / third-party estimate · C = analyst estimate or judgment · D = scenario assumption. Rating confidence: S = sourced, K = analyst knowledge (to verify in primary research).
A8: Color legend | B8: Blue = hardcoded input · Black = formula · Yellow fill = judgment-based score (editable).
A9: Not used | B9: No interviews, win/loss data or Clay internal data. Vendor marketing claims are labeled as claims. ZoomInfo and HubSpot list prices are not public and are not estimated.
A10: Tabs | B10: Summary → Competitor_Register → Overlap_Check → Comparison_Matrix → Pricing_Compare → Persona_Coverage → Segment_Scoring → Positioning_Map → Sources

Sheet Summary
A1: Summary — Phase 2 competitive findings
A2: All values link to the analysis tabs.
A4: Metric | B4: A. Industrial Distribution | C4: B. Industrial Manufacturing | D4: C. B2B Prof. Services | E4: Source tab
A5: Competitive position score (1–5) | B5: =Segment_Scoring!D9 -> 4 | C5: =Segment_Scoring!E9 -> 3.3333333 | D5: =Segment_Scoring!F9 -> 2.3333333 | E5: Segment_Scoring
A6: Adoption / execution fit score (1–5) | B6: =Segment_Scoring!D13 -> 2 | C6: =Segment_Scoring!E13 -> 1.5 | D6: =Segment_Scoring!F13 -> 4.5 | E6: Segment_Scoring
A7: Incremental headroom flag (1–5) | B7: =Segment_Scoring!D15 -> 5 | C7: =Segment_Scoring!E15 -> 5 | D7: =Segment_Scoring!F15 -> 2 | E7: Segment_Scoring
A8: Est. LinkedIn use of customer personas (proxy for database coverage) | B8: =Persona_Coverage!D29 -> 0.26198625 | C8: =Persona_Coverage!D30 -> 0.409235 | D8: =Persona_Coverage!D31 -> 0.421712 | E8: Persona_Coverage
A9: … index vs professional-services personas | B9: =Persona_Coverage!F29 -> 0.62124447 | C9: =Persona_Coverage!F30 -> 0.97041346 | D9: =Persona_Coverage!F31 -> 1 | E9: Persona_Coverage
A11: Cross-segment facts
A12: Apollo coverage of Clay's 11 use cases (F + 0.5·P ÷ 11) | B12: =Overlap_Check!C21 -> 0.54545455 | E12: Overlap_Check
A13: Vertical specialists' coverage of Clay's 11 use cases | B13: =Overlap_Check!F21 -> 0.31818182 | E13: Overlap_Check
A14: Apollo Professional ÷ Clay Growth (mid) annual list cost at 28 users | B14: =Pricing_Compare!D25 -> 2.7041565 | E14: Pricing_Compare
A15: Apollo Professional ÷ Clay Growth (mid) annual list cost at 9 users | B15: =Pricing_Compare!C25 -> 0.86919315 | E15: Pricing_Compare
A17: Key takeaways
A18: 1. H3 supported for distribution: contractor buyer personas are estimated at roughly half the LinkedIn presence of professional-services buyers, and Regency Supply reports ZoomInfo and Apollo failed to find them. Weak for manufacturing, whose customers are white-collar buyers.
A19: 2. H5 supported: Clay's realistic industrial position is complementary. It sits on top of HubSpot, Salesforce or Dynamics and aggregates niche sources (Google Maps, Shovels). It does not replace CRMs, and it lacks an ERP connector.
A20: 3. The main competitor in industrials is inertia (spreadsheets, low CRM discipline), followed by turnkey tools (Apollo, HubSpot) that win on ease rather than data.
A21: 4. Apollo is converging on Clay's model (waterfall, spreadsheet beta), which narrows Clay's moat in horizontal and software segments more than in industrial niches.
A22: 5. Clay's unlimited-seat pricing is structurally cheaper than per-seat tools for seller-dense distributors, but only if the customer can operate it. Packaging and partners, not features, are the binding constraint (H4).

Sheet Competitor_Register
A1: Competitor register — direct, partial and alternative solutions
A2: Overlap is verified on the Overlap_Check tab, not assumed. Scale facts are company-reported [A] unless marked as an estimate [B].
A4: ID | B4: Competitor / alternative | C4: Type | D4: What it is | E4: Where it plays (segments) | F4: Pricing architecture | G4: Scale facts (class) | H4: Relevance to this decision | I4: Sources
A5: C01 | B5: Apollo.io | C5: Direct | D5: All-in-one prospecting: contact database, sequencing, dialer. Added waterfall enrichment across 18 providers (Oct 2025), acquired Pocus (Mar 2026), launched 'Apollo Anywhere' in AI assistants (Mar 2026) and a spreadsheet product in beta (Oct 2026). | E5: Horizontal; SMB and mid-market, expanding upmarket. | F5: Per seat: Basic $49, Professional $79, Organization $119 per user/month (annual billing); credit limits on mobile numbers and exports. | G5: ARR ~$265M (Sep 2026) and ~$194M (end-2025) [B, Sacra estimate]; $1.6B valuation (2023). | H5: The closest substitute. It is now copying Clay's waterfall and spreadsheet model while staying turnkey. Regency Supply reported Apollo was ineffective for finding local electrical contractors. | I5: S20, S23, S07
A6: C02 | B6: ZoomInfo (NASDAQ: GTM) | C6: Direct (data) / Partial (workflow) | D6: Proprietary B2B contact and company database with intent, website-visitor tracking and engagement tools; data from web scanning, a contributory network and human research. | E6: Horizontal; 74% of ACV 'upmarket'; detected web-tracking users skew to software (19%), IT services (10%), staffing (4%). | F6: Annual subscription contracts; list pricing not public. | G6: FY2025 revenue $1,249.5M (+3%); NRR 90%; 1,921 customers ≥$100K ACV; serves 35,000+ companies [A]. | H6: Incumbent data vendor. Slow growth and 90% NRR signal saturation in its core. Regency reported ZoomInfo was ineffective for local contractors. Can be used inside Clay with the customer's own API key (complement). | I6: S19, S33, S07
A7: C03 | B7: HubSpot (Sales Hub + Breeze Intelligence) | C7: Partial (substitute and platform) | D7: CRM suite with native enrichment, buyer intent and form shortening paid in HubSpot Credits (500 / 3,000 / 5,000 per month for Starter / Pro / Enterprise). | E7: SMB and mid-market across industries; the CRM used in the Regency case. | F7: Per-seat CRM subscription plus a credit allowance; extra credits ~$45/mo per 5,000 [B]. | G7: 306,446 customers; avg subscription revenue per customer $11,800 (Q2 2026) [A]. | H7: Both the system of record Clay plugs into (native integration) and a 'good-enough' built-in enrichment alternative for teams with low builder capacity. | I7: S21, S22, S07
A8: C04 | B8: Salesforce / Microsoft Dynamics 365 | C8: Complement (partial substitute) | D8: Enterprise CRMs; Clay lists native integrations with Salesforce and Dynamics 365. | E8: Mid-market and enterprise across industries. | F8: Per seat. | G8: Not quantified here. | H8: Systems of record; their native AI agents could absorb simple enrichment/research jobs. | I8: S36
A9: C05 | B9: Dun & Bradstreet (Hoovers) | C9: Partial (data) | D9: Firmographic and business-credit data; directories by industry including manufacturing. | E9: Enterprise data buyers; strong firmographic coverage of manufacturers. | F9: Enterprise data licenses. | G9: Taken private by Clearlake for $7.7B (2025) [A]. | H9: Firmographic depth on industrial firms; weaker on workflow. More likely a data source than a workflow competitor. | I9: S41
A10: C06 | B10: Vertical data specialists (Dodge Construction Network, Shovels, Thomasnet) | C10: Complement / partial substitute | D10: Industry-native data: construction projects and specifications (Dodge), building permits and contractor profiles (Shovels), industrial supplier discovery (Thomasnet). | E10: Construction-facing distributors and building-product manufacturers; industrial sourcing. | F10: Annual subscriptions (Dodge), self-serve API from $599/mo (Shovels), paid supplier placements ~$7K–$10K+/yr (Thomasnet). | G10: Dodge: 677K+ firms, 700K+ projects/yr [A, claim]. Shovels: 178M+ permits, ~3.65M contractor profiles, ~$3M ARR [B]. Thomasnet: 500K+ suppliers; no API [B]. | H10: The data industrial sellers actually need. Shovels already distributes through Clay; Dodge and Thomasnet do not appear to. Clay's opportunity is to aggregate them, and the risk is that they bundle their own workflow. | I10: S38, S26, S27
A11: C07 | B11: Distribution sales AI (e.g., Proton.ai) | C11: Partial (budget competitor) | D11: AI CRM and recommendation engine trained on distributors' ERP order history; launched a distributor 'industry cloud' (CRM, PIM, e-commerce recommendations) in Mar 2026. | E11: Mid-to-large distributors (e.g., MSC Industrial Supply). | F11: Enterprise subscription (not public). | G11: ~$30M raised; 51–200 employees [B]. | H11: Competes for the same distributor sales-productivity budget, focused on installed-base cross-sell rather than net-new prospecting, which is Clay's strength. | I11: S24
A12: C08 | B12: ERP-embedded CRM (Epicor Prophet 21/Eclipse, Infor, etc.) | C12: Alternative (status quo) | D12: CRM modules inside distribution ERPs, where order, pricing and customer data live. | E12: Distribution; Epicor was used by 59% of reporting Top-200 electrical distributors (2014, dated). | F12: Bundled with ERP. | G12: 9% of surveyed distributors use an ERP-provided CRM (2022) [B]. | H12: Clay has no native ERP connector (CRMs and warehouses only), which is a gap for distributors whose customer data lives in the ERP. | I12: S40, S17, S36
A13: C09 | B13: Professional-services vertical CRMs (Deltek Vantagepoint, Unanet CRM) | C13: Alternative / complement | D13: Project-based CRM/ERP for architecture & engineering and government contractors; pursuit and proposal management. | E13: A&E and GovCon professional services. | F13: Per seat / suite. | G13: Unanet: 3,400+ customers (2022) [B]. A&E median proposal win rate 50% (Deltek Clarity 2025, n≈700) [B]. | H13: Systems of record for RFP-driven business development; Clay would need to integrate through API. | I13: S42, S39
A14: C10 | B14: AI-native GTM platforms (Unify, Cargo, Common Room, Default, Warmly) | C14: Direct (software segment) | D14: Agentic outbound, signal and orchestration tools. | E14: Mostly software and AI companies. | F14: Usage- or seat-based. | G14: Not quantified here. | H14: Crowd Clay's core software segment; little visible industrial focus, so they are not a major factor in the industrial decision. | I14: S04
A15: C11 | B15: Internal build (Zapier, n8n, Make + LLM APIs) | C15: Alternative | D15: Self-assembled enrichment and research pipelines. | E15: Firms with technical GTM staff. | F15: Tool subscriptions plus engineer time. | G15: n8n named in 41% and Zapier in 40% of sampled GTM-engineer postings (n=209) [B]. | H15: A real substitute where builders exist (professional services, software); not viable where they don't (industrials). | I15: S30
... A17: C13 | B17: Status quo: spreadsheets, manual research, field reps | C17: Alternative (do nothing) | D17: Reps build lists by hand; relationship-led selling. | E17: Strongest in distribution and manufacturing. | F17: Labor cost. | G17: Distributors: 68% use spreadsheets, 56% use CRM, only 34% of CRM users log ≥75% of interactions (2026) [B]; 15% have no CRM (2022) [B]. | H17: The main competitor in industrials is inertia, not another vendor. | I17: S25, S17

Sheet Overlap_Check
A1: Overlap check — which alternatives genuinely cover Clay's use cases?
A2: F = full coverage (1.0), P = partial (0.5), N = none (0), ? = not verified (excluded from the index). Confidence: S = sourced, K = analyst knowledge, verify in primary research.
A4: Use case | B4: Clay | C4: Apollo | D4: ZoomInfo | E4: HubSpot Breeze | F4: Vertical data specialists | G4: Proton.ai | H4: Internal build | I4: Evidence / notes
A5: U1 TAM / account list sourcing | B5: F | C5: F | D5: F | E5: P | F5: P | G5: N | H5: P | I5: Clay Audiences/TAM sourcing (S01); Apollo/ZoomInfo databases (S19, S20); HubSpot enrichment fills existing records rather than building lists (S21) [K]; Dodge/Thomasnet list firms in their niche (S38, S27).
A6: U2 Contact enrichment (email, phone) | B6: F | C6: F | D6: F | E6: P | F6: N | G6: N | H6: P | I6: Core function of database vendors; Breeze enriches contact/company fields (S21).
A7: U3 Multi-provider waterfall enrichment | B7: F | C7: F | D7: N | E7: N | F7: N | G7: N | H7: P | I7: Clay waterfall across 150–200+ providers (S01); Apollo added an 18-provider waterfall in Oct 2025 (S23). ZoomInfo and HubSpot use their own data [K].
A8: U4 Off-LinkedIn / local business sourcing (maps, permits, licenses) | B8: F | C8: N | D8: N | E8: N | F8: F | G8: N | H8: P | I8: Clay Google Maps integration (S37) and Shovels permit/contractor data distributed via Clay (S26). Regency: ZoomInfo and Apollo could not find local contractors (S07). Dodge/Shovels are native here.
A9: U5 AI web research → custom data points | B9: F | C9: ? | D9: N | E9: P | F9: N | G9: N | H9: F | I9: Claygent / account agents (S01). Apollo's AI research depth not verified. Breeze offers AI features inside HubSpot [K]. Internal LLM pipelines can replicate (S30).
A10: U6 Signals (job change, intent, news) | B10: F | C10: P | D10: F | E10: P | F10: P | G10: N | H10: P | I10: Clay signals: job change, news, web intent (S01); ZoomInfo intent + visitor tracking (S19, S33); Breeze buyer intent (S21); Dodge spec/bid alerts (S38).
A11: U7 CRM sync and data hygiene | B11: F | C11: F | D11: F | E11: F | F11: P | G11: P | H11: P | I11: Clay native Salesforce/HubSpot/Dynamics sync at Growth+ (S01, S36). HubSpot is the CRM itself. Dodge leads importable to CRM (S38).
A12: U8 Inbound lead qualification and routing | B12: F | C12: P | D12: P | E12: F | F12: N | G12: N | H12: P | I12: Regency automated e-commerce registration qualification with Clay (S07); HubSpot form shortening and routing (S21) [K].
A13: U9 Outbound sequencing | B13: F | C13: F | D13: P | E13: F | F13: N | G13: N | H13: P | I13: Clay Sequencer (S01); Apollo sequencing (S20); HubSpot sequences [K].
A14: U10 Installed-base cross-sell from ERP / transaction data | B14: P | C14: N | D14: N | E14: P | F14: N | G14: F | H14: P | I14: Clay has no ERP connector, only CRMs and warehouses (S36), so partial via warehouse sync/HTTP API. Proton.ai is trained on ERP order history (S24).
A15: U11 Project, bid and permit intelligence | B15: P | C15: N | D15: N | E15: N | F15: F | G15: N | H15: N | I15: Clay added public-sector bid signals (GovSpend, Pursuit) in Sep 2026 (S09) and carries Shovels permits (S26); Dodge is the construction-project specialist (S38).
A17: Use cases rated (excl. '?') | B17: =COUNTIF(B5:B15,"F")+COUNTIF(B5:B15,"P")+COUNTIF(B5:B15,"N") -> 11 | C17: =COUNTIF(C5:C15,"F")+COUNTIF(C5:C15,"P")+COUNTIF(C5:C15,"N") -> 10 | D17: =COUNTIF(D5:D15,"F")+COUNTIF(D5:D15,"P")+COUNTIF(D5:D15,"N") -> 11 | E17: =COUNTIF(E5:E15,"F")+COUNTIF(E5:E15,"P")+COUNTIF(E5:E15,"N") -> 11 | F17: =COUNTIF(F5:F15,"F")+COUNTIF(F5:F15,"P")+COUNTIF(F5:F15,"N") -> 11 | G17: =COUNTIF(G5:G15,"F")+COUNTIF(G5:G15,"P")+COUNTIF(G5:G15,"N") -> 11 | H17: =COUNTIF(H5:H15,"F")+COUNTIF(H5:H15,"P")+COUNTIF(H5:H15,"N") -> 11
A18: Full coverage (F) | B18: =COUNTIF(B5:B15,"F") -> 9 | C18: =COUNTIF(C5:C15,"F") -> 5 | D18: =COUNTIF(D5:D15,"F") -> 4 | E18: =COUNTIF(E5:E15,"F") -> 3 | F18: =COUNTIF(F5:F15,"F") -> 2 | G18: =COUNTIF(G5:G15,"F") -> 1 | H18: =COUNTIF(H5:H15,"F") -> 1
A19: Partial coverage (P) | B19: =COUNTIF(B5:B15,"P") -> 2 | C19: =COUNTIF(C5:C15,"P") -> 2 | D19: =COUNTIF(D5:D15,"P") -> 2 | E19: =COUNTIF(E5:E15,"P") -> 5 | F19: =COUNTIF(F5:F15,"P") -> 3 | G19: =COUNTIF(G5:G15,"P") -> 1 | H19: =COUNTIF(H5:H15,"P") -> 9
A20: Coverage index (F + 0.5·P) ÷ rated | B20: =IFERROR((B18+0.5*B19)/B17,0) -> 0.90909091 | C20: =IFERROR((C18+0.5*C19)/C17,0) -> 0.6 | D20: =IFERROR((D18+0.5*D19)/D17,0) -> 0.45454545 | E20: =IFERROR((E18+0.5*E19)/E17,0) -> 0.5 | F20: =IFERROR((F18+0.5*F19)/F17,0) -> 0.31818182 | G20: =IFERROR((G18+0.5*G19)/G17,0) -> 0.13636364 | H20: =IFERROR((H18+0.5*H19)/H17,0) -> 0.5
A21: Overlap with Clay's full use-case set: (F + 0.5·P) ÷ 11 | B21: =(B18+0.5*B19)/11 -> 0.90909091 | C21: =(C18+0.5*C19)/11 -> 0.54545455 | D21: =(D18+0.5*D19)/11 -> 0.45454545 | E21: =(E18+0.5*E19)/11 -> 0.5 | F21: =(F18+0.5*F19)/11 -> 0.31818182 | G21: =(G18+0.5*G19)/11 -> 0.13636364 | H21: =(H18+0.5*H19)/11 -> 0.5
A23: Reading: Apollo is the only alternative that covers most of Clay's use cases. Its gaps are exactly the industrial-specific ones (U4 off-LinkedIn/local sourcing, U11 project and permit intelligence). Vertical specialists cover those gaps but little else. Clay's defensible overlap position is aggregating the specialists into a workflow that standard vendors don't cover.

Sheet Comparison_Matrix
A1: Comparison matrix — the nine requested dimensions
A2: Qualitative evidence with a 1–5 score (5 = strongest for an industrial mid-market buyer). Scores are analyst judgments [C]; sources on Competitor_Register and Sources.
A4: Dimension | B4: Clay | C4: Score | D4: Apollo | E4: Score | F4: ZoomInfo | G4: Score | H4: HubSpot (Breeze) | I4: Score | J4: Vertical specialists | K4: Score | L4: Internal build | M4: Score
A5: Product capabilities | B5: Data marketplace, waterfall, AI agents, signals, workflows, sequencer, ads audiences. | C5: 5 | D5: Database, sequencing, dialer; now waterfall and a spreadsheet beta. | E5: 4 | F5: Deep proprietary data, intent, engagement tools. | G5: 4 | H5: CRM-native enrichment, intent, form shortening. | I5: 3 | J5: Deep but narrow (projects, permits, suppliers). | K5: 2 | L5: Whatever is built. | M5: 3
A6: Customer segments | B6: Software/AI-heavy base (~40% software development among detected web-intent users); few industrial references. | C6: 2 | D6: Horizontal SMB and mid-market. | E6: 4 | F6: Upmarket (74% of ACV); diversified base. | G6: 3 | H6: Broad SMB and mid-market (306K customers). | I6: 5 | J6: Construction and industrial niches. | K6: 4 | L6: Firms with technical GTM staff. | M6: 2
A7: Pricing architecture | B7: Platform fee plus usage (Actions + Data Credits); unlimited seats; Growth ~$5.4K/yr at list. | C7: 4 | D7: Per seat $49–$119/user/mo plus credits. | E7: 3 | F7: Opaque annual contracts. | G7: 2 | H7: Per seat plus credit allowance. | I7: 3 | J7: Subscriptions; Shovels from $599/mo. | K7: 3 | L7: Low cash cost, high labor cost. | M7: 2
A8: Data coverage of industrial buyers | B8: Aggregates 150–200+ providers incl. Google Maps and Shovels; strongest for off-LinkedIn personas. | C8: 5 | D8: Large database but reported weak for local contractors. | E8: 2 | F8: Large database but reported weak for local contractors. | G8: 2 | H8: Own database; generic coverage. | I8: 2 | J8: Best within their niche. | K8: 4 | L8: Depends on sources licensed. | M8: 3
A9: Workflow automation | B9: Core strength: tables, workflows, functions, webhooks, CLI/API. | C9: 5 | D9: Sequences and workflow destinations; less flexible. | E9: 3 | F9: Workflow add-ons; less flexible. | G9: 3 | H9: HubSpot workflows inside the CRM. | I9: 4 | J9: Minimal. | K9: 1 | L9: Unlimited but self-maintained. | M9: 4
A10: CRM integration | B10: Native Salesforce, HubSpot, Dynamics 365, Pipedrive at Growth+; no ERP connector. | C10: 4 | D10: Standard CRM syncs [K]. | E10: 4 | F10: Standard CRM syncs [K]. | G10: 4 | H10: Is the CRM. | I10: 5 | J10: Dodge imports into CRM; Thomasnet has no API. | K10: 2 | L10: Custom. | M10: 3
A11: Implementation complexity (5 = easiest) | B11: High: value depends on a builder; Regency's workflows were custom-built. | C11: 2 | D11: Low: turnkey per-seat tool. | E11: 5 | F11: Medium: admin plus training. | G11: 3 | H11: Lowest: already inside the CRM. | I11: 5 | J11: Low: search portals. | K11: 4 | L11: Highest: engineering required. | M11: 1
A12: Differentiation for industrial sellers | B12: Only option combining off-LinkedIn data, AI research and CRM sync in one workflow. | C12: 5 | D12: Price and simplicity. | E12: 3 | F12: Data breadth for white-collar personas. | G12: 3 | H12: Convenience. | I12: 2 | J12: Industry-native data. | K12: 4 | L12: Full control. | M12: 2
A13: Switching costs once adopted | B13: High: workflows, functions and history become embedded (unlimited seats spread usage). | C13: 4 | D13: Medium: sequences and seats. | E13: 3 | F13: Medium-high: annual contracts. | G13: 3 | H13: Very high: system of record. | I13: 5 | J13: Low-medium. | K13: 2 | L13: High: sunk build. | M13: 4
A14: Average score (unweighted) | C14: =AVERAGE(C5:C13) -> 4 | E14: =AVERAGE(E5:E13) -> 3.4444444 | G14: =AVERAGE(G5:G13) -> 3 | I14: =AVERAGE(I5:I13) -> 3.7777778 | K14: =AVERAGE(K5:K13) -> 2.8888889 | M14: =AVERAGE(M5:M13) -> 2.6666667
A15: Implementation complexity score | C15: =C11 -> 2 | E15: =E11 -> 5 | G15: =G11 -> 3 | I15: =I11 -> 5 | K15: =K11 -> 4 | M15: =M11 -> 1
A17: Reading: Clay leads on capability, industrial data coverage and differentiation, but scores lowest among commercial vendors on implementation ease. The competitive question in industrials is less 'can Clay out-feature Apollo' than 'can Clay be made as easy to adopt as Apollo or HubSpot'.

Sheet Pricing_Compare
A1: Illustrative annual list cost by team size — seat-based vs unlimited-seat pricing
A2: List prices, annual billing, before discounts and add-ons. ZoomInfo and HubSpot seat prices are not public / not captured and are excluded rather than estimated. [A] inputs → [C] outputs.
A4: Inputs (monthly, annual billing)
A5: Item | B5: $ / month | C5: Source
A6: Clay Growth — Actions 480K/yr tier | B6: 185 | C6: S01
A7: Clay Growth — Data Credits 72K/yr tier | B7: 261 | C7: S01
A8: Clay Growth — Actions 1.2M/yr tier | B8: 405 | C8: S01
A9: Clay Growth — Data Credits 120K/yr tier | B9: 413 | C9: S01
A10: Clay Growth — Actions 2.4M/yr tier | B10: 765 | C10: S01
A11: Clay Growth — Data Credits 240K/yr tier | B11: 792 | C11: S01
A12: Apollo Basic — per user | B12: 49 | C12: S20
A13: Apollo Professional — per user | B13: 79 | C13: S20
A14: Apollo Organization — per user | B14: 119 | C14: S20
A16: Annual cost by number of users who need data ($/yr)
A17: Option | B17: 3 users | C17: 9 users | D17: 28 users | E17: 50 users | F17: Note
A18: Clay Growth — entry configuration | B18: =($B$6+$B$7)*12 -> 5352 | C18: =($B$6+$B$7)*12 -> 5352 | D18: =($B$6+$B$7)*12 -> 5352 | E18: =($B$6+$B$7)*12 -> 5352 | F18: Unlimited seats. Entry tier = the Phase 1 SMB ACV floor ($5,352).
A19: Clay Growth — mid configuration | B19: =($B$8+$B$9)*12 -> 9816 | C19: =($B$8+$B$9)*12 -> 9816 | D19: =($B$8+$B$9)*12 -> 9816 | E19: =($B$8+$B$9)*12 -> 9816 | F19: Same seat count, higher usage.
A20: Clay Growth — high configuration | B20: =($B$10+$B$11)*12 -> 18684 | C20: =($B$10+$B$11)*12 -> 18684 | D20: =($B$10+$B$11)*12 -> 18684 | E20: =($B$10+$B$11)*12 -> 18684 | F20: Upper bound of self-serve Growth before Enterprise.
A21: Apollo Basic | B21: =$B$12*12*3 -> 1764 | C21: =$B$12*12*9 -> 5292 | D21: =$B$12*12*28 -> 16464 | E21: =$B$12*12*50 -> 29400 | F21: Scales linearly with seats.
A22: Apollo Professional | B22: =$B$13*12*3 -> 2844 | C22: =$B$13*12*9 -> 8532 | D22: =$B$13*12*28 -> 26544 | E22: =$B$13*12*50 -> 47400 | F22: Most common tier for sales teams [K].
A23: Apollo Organization | B23: =$B$14*12*3 -> 4284 | C23: =$B$14*12*9 -> 12852 | D23: =$B$14*12*28 -> 39984 | E23: =$B$14*12*50 -> 71400
A25: Apollo Professional ÷ Clay Growth mid configuration | B25: =B22/B19 -> 0.28973105 | C25: =C22/C19 -> 0.86919315 | D25: =D22/D19 -> 2.7041565 | E25: =E22/E19 -> 4.8288509
A27: Why 28 users: Phase 1 estimates ~28 sales staff per in-scope distributor vs ~9 per professional-services firm (02_Market_Sizing, Segment_Profile). At distributor team sizes, seat-based tools cost several times Clay's mid configuration at list. That is a structural price advantage, but it only materializes if the distributor can operate Clay's workflows.

Sheet Persona_Coverage
A1: H3 test — are each segment's buyer personas likely to be covered by LinkedIn-derived B2B databases?
A2: Estimated LinkedIn use = Σ (share of workers by education) × (LinkedIn use rate for that education group). Education: BLS (S29). LinkedIn use: Pew, fielded May–Sep 2023 (S28). Analyst estimate [C].
A4: Pew LinkedIn use rate by education (U.S. adults)
A5: High school or less | B5: 0.1
A6: Some college (incl. associate's) | B6: 0.28
A7: Bachelor's degree or higher | B7: 0.53
A9: Buyer persona (BLS occupation) | B9: SOC | C9: Persona of which segment's customers | D9: < HS | E9: HS | F9: Some college | G9: Associate | H9: Bachelor's | I9: Master's | J9: Doctoral/prof. | K9: Bachelor's+ share | L9: Est. LinkedIn use | M9: Index vs all workers
A10: Total, all occupations | B10: 00-0000 | C10: Reference | D10: 0.074 | E10: 0.224 | F10: 0.182 | G10: 0.094 | H10: 0.255 | I10: 0.121 | J10: 0.05 | K10: =SUM(H10:J10) -> 0.426 | L10: =(D10+E10)*$B$5+(F10+G10)*$B$6+(H10+I10+J10)*$B$7 -> 0.33286 | M10: =L10/$L$10 -> 1
A11: Electricians | B11: 47-2111 | C11: A. Distribution (contractor-facing) | D11: 0.084 | E11: 0.378 | F11: 0.291 | G11: 0.154 | H11: 0.075 | I11: 0.014 | J11: 0.003 | K11: =SUM(H11:J11) -> 0.092 | L11: =(D11+E11)*$B$5+(F11+G11)*$B$6+(H11+I11+J11)*$B$7 -> 0.21956 | M11: =L11/$L$10 -> 0.65961666
A12: Plumbers, pipefitters & steamfitters | B12: 47-2152 | C12: A. Distribution (contractor-facing) | D12: 0.144 | E12: 0.466 | F12: 0.234 | G12: 0.089 | H12: 0.054 | I12: 0.01 | J12: 0.003 | K12: =SUM(H12:J12) -> 0.067 | L12: =(D12+E12)*$B$5+(F12+G12)*$B$6+(H12+I12+J12)*$B$7 -> 0.18695 | M12: =L12/$L$10 -> 0.56164754
A13: HVAC & refrigeration mechanics/installers | B13: 49-9021 | C13: A. Distribution (contractor-facing) | D13: 0.1 | E13: 0.416 | F13: 0.277 | G13: 0.135 | H13: 0.058 | I13: 0.012 | J13: 0.002 | K13: =SUM(H13:J13) -> 0.072 | L13: =(D13+E13)*$B$5+(F13+G13)*$B$6+(H13+I13+J13)*$B$7 -> 0.20512 | M13: =L13/$L$10 -> 0.61623505
A14: First-line supervisors of construction trades | B14: 47-1011 | C14: A. Distribution (contractor-facing) | D14: 0.171 | E14: 0.431 | F14: 0.221 | G14: 0.076 | H14: 0.083 | I14: 0.015 | J14: 0.003 | K14: =SUM(H14:J14) -> 0.101 | L14: =(D14+E14)*$B$5+(F14+G14)*$B$6+(H14+I14+J14)*$B$7 -> 0.19689 | M14: =L14/$L$10 -> 0.59150994
A15: Maintenance & repair workers, general | B15: 49-9071 | C15: A. Distribution (MRO / plant-facing) | D15: 0.12 | E15: 0.433 | F15: 0.249 | G15: 0.114 | H15: 0.068 | I15: 0.012 | J15: 0.003 | K15: =SUM(H15:J15) -> 0.083 | L15: =(D15+E15)*$B$5+(F15+G15)*$B$6+(H15+I15+J15)*$B$7 -> 0.20093 | M15: =L15/$L$10 -> 0.60364718
A16: Construction managers | B16: 11-9021 | C16: A. Distribution (contractor-facing) | D16: 0.081 | E16: 0.267 | F16: 0.216 | G16: 0.089 | H16: 0.272 | I16: 0.066 | J16: 0.009 | K16: =SUM(H16:J16) -> 0.347 | L16: =(D16+E16)*$B$5+(F16+G16)*$B$6+(H16+I16+J16)*$B$7 -> 0.30411 | M16: =L16/$L$10 -> 0.91362735
A17: Purchasing managers | B17: 11-3061 | C17: A. Distribution and B. Manufacturing | D17: 0.011 | E17: 0.112 | F17: 0.148 | G17: 0.08 | H17: 0.392 | I17: 0.223 | J17: 0.033 | K17: =SUM(H17:J17) -> 0.648 | L17: =(D17+E17)*$B$5+(F17+G17)*$B$6+(H17+I17+J17)*$B$7 -> 0.41958 | M17: =L17/$L$10 -> 1.26053
A18: Industrial production managers | B18: 11-3051 | C18: A. Distribution and B. Manufacturing | D18: 0.034 | E18: 0.195 | F18: 0.189 | G18: 0.084 | H18: 0.344 | I18: 0.135 | J18: 0.018 | K18: =SUM(H18:J18) -> 0.497 | L18: =(D18+E18)*$B$5+(F18+G18)*$B$6+(H18+I18+J18)*$B$7 -> 0.36275 | M18: =L18/$L$10 -> 1.0897975
A19: Civil engineers | B19: 17-2051 | C19: B. Manufacturing (OEM / project buyers) | D19: 0.008 | E19: 0.033 | F19: 0.041 | G19: 0.035 | H19: 0.581 | I19: 0.262 | J19: 0.04 | K19: =SUM(H19:J19) -> 0.883 | L19: =(D19+E19)*$B$5+(F19+G19)*$B$6+(H19+I19+J19)*$B$7 -> 0.49337 | M19: =L19/$L$10 -> 1.4822147
A20: General & operations managers | B20: 11-1021 | C20: B. Manufacturing and C. Prof. services | D20: 0.033 | E20: 0.17 | F20: 0.232 | G20: 0.096 | H20: 0.336 | I20: 0.114 | J20: 0.02 | K20: =SUM(H20:J20) -> 0.47 | L20: =(D20+E20)*$B$5+(F20+G20)*$B$6+(H20+I20+J20)*$B$7 -> 0.36124 | M20: =L20/$L$10 -> 1.0852611
A21: Chief executives | B21: 11-1011 | C21: C. Prof. services | D21: 0.015 | E21: 0.077 | F21: 0.125 | G21: 0.05 | H21: 0.409 | I21: 0.253 | J21: 0.07 | K21: =SUM(H21:J21) -> 0.732 | L21: =(D21+E21)*$B$5+(F21+G21)*$B$6+(H21+I21+J21)*$B$7 -> 0.44616 | M21: =L21/$L$10 -> 1.3403833
... A24: Software developers | B24: 15-1252 | C24: C. Prof. services (IT services clients) | D24: 0.006 | E24: 0.022 | F24: 0.073 | G24: 0.039 | H24: 0.517 | I24: 0.302 | J24: 0.04 | K24: =SUM(H24:J24) -> 0.859 | L24: =(D24+E24)*$B$5+(F24+G24)*$B$6+(H24+I24+J24)*$B$7 -> 0.48943 | M24: =L24/$L$10 -> 1.4703779
A26: Segment summary (simple average of mapped personas)
A27: Segment | B27: Personas averaged | D27: Est. LinkedIn use | E27: Index vs all workers | F27: Index vs Prof. services
A28: A. Distribution — contractor-facing personas | B28: Electricians, plumbers, HVAC, construction supervisors | D28: =AVERAGE(L11,L12,L13,L14) -> 0.20213 | E28: =D28/$L$10 -> 0.6072523 | F28: =D28/$D$31 -> 0.47930815
A29: A. Distribution — all mapped personas | B29: Contractor + MRO + construction/purchasing/production managers | D29: =AVERAGE(L11,L12,L13,L14,L15,L16,L17,L18) -> 0.26198625 | E29: =D29/$L$10 -> 0.7870764 | F29: =D29/$D$31 -> 0.62124447
A30: B. Manufacturing — customer personas | B30: Purchasing, production managers, civil engineers, G&O managers | D30: =AVERAGE(L17,L18,L19,L20) -> 0.409235 | E30: =D30/$L$10 -> 1.2294508 | F30: =D30/$D$31 -> 0.97041346
A31: C. Prof. services — customer personas | B31: CEOs, G&O, marketing, facilities managers, software developers | D31: =AVERAGE(L20,L21,L22,L23,L24) -> 0.421712 | E31: =D31/$L$10 -> 1.266935 | F31: =D31/$D$31 -> 1
A33: Caveats: (1) assumes LinkedIn use depends only on education. Occupation likely lowers trades' use further, so the gap shown is conservative. (2) B2B databases also use web crawling and contributory networks (ZoomInfo, S19), so LinkedIn presence is a proxy for coverage, not a measurement. (3) Direct corroboration: Regency Supply found ZoomInfo and Apollo ineffective for local electrical contractors and used Google Maps listings instead (S07).

Sheet Segment_Scoring
A1: Segment competitive scoring — inputs to Phase 3 (1 = weak for Clay, 5 = strong)
A2: Factor scores are analyst judgments [C] tied to evidence; weights are assumptions [D]. Competitive position and adoption fit are kept separate so Phase 3 does not double-count ease of execution.
A4: Factor | B4: Feeds Phase 3 criterion | C4: Weight within block | D4: A. Industrial Distribution | E4: B. Industrial Manufacturing | F4: C. B2B Prof. Services | G4: Evidence
A5: BLOCK 1 — Competitive position
A6: F1 Relevance of Clay's data differentiation (off-LinkedIn, multi-source, AI research) | B6: Competitive Position | C6: 0.33333333 | D6: 5 | E6: 3 | F6: 2 | G6: Persona_Coverage: contractor personas ≈0.45–0.5× professional-services personas in estimated LinkedIn use; Regency case (S07). Manufacturing's customers (purchasing, engineers) are near-average. Prof.-services buyers are well covered by standard databases, so Clay's edge there is workflow flexibility, not data.
A7: F2 Incumbent saturation (5 = little entrenched sales-intelligence use) | B7: Competitive Position | C7: 0.33333333 | D7: 4 | E7: 4 | F7: 2 | G7: Distributors: 15% no CRM, 68% spreadsheets, only 34% of CRM users log most interactions (S17, S25). ZoomInfo's detected users skew to software, IT services, staffing, advertising (S33). IT services and agencies are heavy users of sales-intelligence tools [K].
A8: F3 Threat from vertical specialists / systems of record (5 = low) | B8: Competitive Position | C8: 0.33333333 | D8: 3 | E8: 3 | F8: 3 | G8: Distribution: Proton.ai and ERP CRMs (S24, S17), but focused on installed base. Manufacturing: Thomasnet/D&B are data, not workflow (S27, S41). Prof. services: Deltek/Unanet own pursuit records in A&E (S39, S42). All largely complementary.
A9: Competitive position score | C9: =SUM(C6:C8) -> 1 | D9: =SUMPRODUCT($C6:$C8,D6:D8)/SUM($C6:$C8) -> 4 | E9: =SUMPRODUCT($C6:$C8,E6:E8)/SUM($C6:$C8) -> 3.3333333 | F9: =SUMPRODUCT($C6:$C8,F6:F8)/SUM($C6:$C8) -> 2.3333333 | G9: Weighted average of F1–F3.
A10: BLOCK 2 — Adoption / execution fit
A11: F4 Builder capacity to self-serve Clay | B11: Ease of Execution | C11: 0.5 | D11: 2 | E11: 1 | F11: 5 | G11: Computer-occupation index vs all industries: 0.69 / 0.45 / 7.15; marketing-ops index 1.46 / 0.62 / 5.48 (02_Market_Sizing). GTM-engineer postings concentrate in software (43.9%, S31).
A12: F5 Existing references and partner channel | B12: Ease of Execution | C12: 0.5 | D12: 2 | E12: 2 | F12: 4 | G12: Distribution: one public case study (Regency, S07). Manufacturing: LG pilot via Marketbridge (S08) and agency marketing (S12). Prof. services: a case-study filter of its own (S06); Clay's solution partners are mostly marketing and consulting firms (S34). No industrial-specialist partners found on the visible directory pages (S35).
A13: Adoption / execution fit score | C13: =SUM(C11:C12) -> 1 | D13: =SUMPRODUCT($C11:$C12,D11:D12)/SUM($C11:$C12) -> 2 | E13: =SUMPRODUCT($C11:$C12,E11:E12)/SUM($C11:$C12) -> 1.5 | F13: =SUMPRODUCT($C11:$C12,F11:F12)/SUM($C11:$C12) -> 4.5 | G13: Weighted average of F4–F5.
A14: BLOCK 3 — Flag for Phase 3 market attractiveness
A15: F6 Incremental headroom (5 = largely unpenetrated by Clay) | B15: Market Attractiveness (adjustment) | C15: n/a | D15: 5 | E15: 5 | F15: 2 | G15: Clay's detected web-intent users are ~40% software development, with no industrial industry in the top 5 (S32; small, feature-specific sample). Agencies and consultancies are already Clay customers and partners (S34), so the incremental professional-services pool is smaller than Phase 1's SOM implies.
A17: Reading: Clay's competitive position is strongest where its execution fit is weakest. Distribution scores highest on position because the data gap is real and incumbents are thin, but lowest-but-one on the ability to adopt. Professional services is the mirror image. This is the core trade-off Phase 3 must price explicitly.

Sheet Positioning_Map
A1: Competitive positioning framework — industrial buyer's view
A2: X = coverage of industrial / off-LinkedIn buyer data (1–5). Y = ease of adoption for teams without technical GTM staff (1–5). Coordinates are analyst judgments [C] derived from Comparison_Matrix.
A4: Player | B4: X: industrial data coverage | C4: Y: ease of adoption | D4: Rationale
A5: Clay (today) | B5: =Comparison_Matrix!C8 -> 5 | C5: =Comparison_Matrix!C11 -> 2 | D5: Strongest industrial data aggregation; adoption requires a builder.
A6: Apollo | B6: =Comparison_Matrix!E8 -> 2 | C6: =Comparison_Matrix!E11 -> 5 | D6: Turnkey; weak on local contractors per Regency.
A7: ZoomInfo | B7: =Comparison_Matrix!G8 -> 2 | C7: =Comparison_Matrix!G11 -> 3 | D7: Large database; enterprise contracting and admin.
A8: HubSpot (Breeze) | B8: =Comparison_Matrix!I8 -> 2 | C8: =Comparison_Matrix!I11 -> 5 | D8: Easiest; generic data.
A9: Vertical specialists | B9: =Comparison_Matrix!K8 -> 4 | C9: =Comparison_Matrix!K11 -> 4 | D9: Deep niche data; portal-style ease.
A10: Internal build | B10: =Comparison_Matrix!M8 -> 3 | C10: =Comparison_Matrix!M11 -> 1 | D10: Any data; needs engineers.
A11: Target: packaged 'Clay for industrial distribution' | B11: 5 | C11: 4 | D11: Hypothesized white space: Clay's data plus pre-built templates and partner delivery (tested in Phases 3–5).
A12: Note: Apollo and HubSpot plot at the same point (2, 5). Both are turnkey but generic for industrial personas.

Sheet Sources
A1: Sources used in this workbook
A2: Full register with dates, reliability and limitations: Research_Sources.csv
A4: ID | B4: Source | C4: Publisher | D4: Date / reference | E4: URL
A5: S01 | B5: Clay pricing page | C5: Clay Labs Inc. | D5: Live, Oct 2026 | E5: https://www.clay.com/pricing
A6: S04 | B6: Clay company profile / ARR estimate | C6: Sacra | D6: 2026 | E6: https://sacra.com/c/clay/
A7: S06 | B7: Clay customer stories (industry filters) | C7: Clay Labs Inc. | D7: Live, Oct 2026 | E7: https://www.clay.com/customers
A8: S07 | B8: Regency Supply case study | C8: Clay Labs Inc. | D8: Undated (~2025) | E8: https://www.clay.com/customers/regency-supply
A9: S08 | B9: Clay–Marketbridge partnership | C9: B2BMX Insights | D9: 2026-10-06 | E9: https://www.demandgenreport.com/industry-news/news-brief/clay-marketbridge-partner-to-modernize-b2b-gtm-execution/54721/
A10: S09 | B10: Clay integrations roundup | C10: Clay Labs Inc. | D10: 2026-09-29 | E10: https://www.clay.com/changelog/integrations-roundup
A11: S12 | B11: Clay agency for manufacturing (city pages) | C11: DevCommX | D11: Undated | E11: https://www.devcommx.com/clay-agency/akron/manufacturing
A12: S17 | B12: State of CRM in Distribution | C12: Distribution Strategy Group | D12: 2022 | E12: https://archive.distributionstrategy.com/wp-content/uploads/2022/10/DSG-The-State-of-CRM-in-Distribution-Making-the-Software-Work-for-You.pdf
A13: S19 | B13: ZoomInfo Q4 and FY2025 results | C13: ZoomInfo via Business Wire | D13: 2026-02-09 | E13: https://www.businesswire.com/news/home/20260209677262/en/
A14: S20 | B14: Apollo.io pricing in 2026 (third-party summary) | C14: Docket | D14: Verified Apr 2026 | E14: https://docket.io/resources/research/apollo-pricing
A15: S21 | B15: HubSpot Breeze Intelligence pricing guide | C15: eesel AI | D15: Edited 2026-10-14 | E15: https://www.eesel.ai/blog/hubspot-breeze-intelligence-pricing
... A36: S42 | B36: Unanet Q1 momentum (customer count) | C36: Unanet | D36: 2022-04-28 | E36: https://unanet.com/news/unanet-demonstrates-continued-momentum-in-first-quarter-winning-erp-and-crm-market-share-with-innovation-and-customer-service
