Workbook

Sheet Cover
A1: 06 — Segment Prioritization v2: which segment, if any, should Clay test first?
A2: Independent portfolio case study by Zhuoran (Zora) Wang · Not commissioned by or affiliated with Clay Labs Inc. · v2 rebuilt 2026-10-19 after partner review (issue C5)
A4: Question | B4: Ranking of industrial distribution, industrial manufacturing and B2B professional services on six criteria with the brief's weights.
A5: v2 rule | B5: One indicator per criterion. No input feeds two criteria. Phase 4's usage-based ACV replaces the assumed seller-density uplift.
A6: Structure | B6: Executive_Summary → Weights → Inputs → Scorecard → Bridge_v1_v2 → Weight_Sensitivity → Random_Weights → Stress_Tests → Economic_Crosscheck → Subsegment_Drilldown → Change_Log → Sources
A7: Evidence classes | B7: A verified fact · B benchmark · C analyst estimate · D scenario assumption · E recommendation. Judgment inputs are yellow.
A8: Not a forecast | B8: Scores are analyst estimates from public data. Economic values are illustrative scenario outputs, not Clay forecasts.

Sheet Executive_Summary
A1: Executive Summary — segment prioritization v2 (after partner review)
A2: Independent case study · not commissioned by or affiliated with Clay Labs Inc. · scores are analyst estimates [C] built from public data
A4: Result | B4: Distribution | C4: Manufacturing | D4: Prof. services | E4: Note
A5: Weighted total — v2 base (brief weights) | B5: =Scorecard!C18 -> 3.7899971 | C5: =Scorecard!D18 -> 2.9055556 | D5: =Scorecard!E18 -> 3.849499 | E5: One indicator per criterion; Phase 4 ACV fed back
A6: Weighted total — display precision (1 decimal) | B6: =ROUND(Scorecard!C18,1) -> 3.8 | C6: =ROUND(Scorecard!D18,1) -> 2.9 | D6: =ROUND(Scorecard!E18,1) -> 3.8 | E6: Judgment-based inputs do not support two-decimal precision (review m7)
A7: Score range — P10, centered random weights | B7: =PERCENTILE(Random_Weights!$R$5:$R$1004,0.1) -> 3.5332569 | C7: =PERCENTILE(Random_Weights!$S$5:$S$1004,0.1) -> 2.6698973 | D7: =PERCENTILE(Random_Weights!$T$5:$T$1004,0.1) -> 3.5673479 | E7: Dirichlet(30 × brief weights), 1,000 draws
A8: Score range — P90, centered random weights | B8: =PERCENTILE(Random_Weights!$R$5:$R$1004,0.9) -> 4.0508009 | C8: =PERCENTILE(Random_Weights!$S$5:$S$1004,0.9) -> 3.1443365 | D8: =PERCENTILE(Random_Weights!$T$5:$T$1004,0.9) -> 4.1237207 | E8: Distribution and professional services ranges overlap: a tie
A9: Weighted total — v1 (as published) | B9: =Bridge_v1_v2!C5 -> 3.9677801 | C9: =Bridge_v1_v2!D5 -> 2.7044653 | D9: =Bridge_v1_v2!E5 -> 3.41185 | E9: Archived v1
A10: Named weight sets won (of 6) | B10: =COUNTIF(Weight_Sensitivity!$E$5:$E$10,"Distribution") -> 1 | C10: =COUNTIF(Weight_Sensitivity!$E$5:$E$10,"Manufacturing") -> 0 | D10: =COUNTIF(Weight_Sensitivity!$E$5:$E$10,"Prof. services") -> 5 | E10: Weight_Sensitivity Block A
A11: Random weights won — flat Dirichlet | B11: =Weight_Sensitivity!B27 -> 0.429 | C11: =Weight_Sensitivity!C27 -> 0 | D11: =Weight_Sensitivity!D27 -> 0.571 | E11: 1,000 draws
A12: Random weights won — centered Dirichlet | B12: =Weight_Sensitivity!B28 -> 0.446 | C12: =Weight_Sensitivity!C28 -> 0 | D12: =Weight_Sensitivity!D28 -> 0.554 | E12: 1,000 draws
A13: Stress tests won (of 14) | B13: =COUNTIF(Stress_Tests!$F$5:$F$18,"Distribution") -> 5 | C13: =COUNTIF(Stress_Tests!$F$5:$F$18,"Manufacturing") -> 0 | D13: =COUNTIF(Stress_Tests!$F$5:$F$18,"Prof. services") -> 9 | E13: Stress_Tests summary
A15: What changed and what it means
A16: 1. Distribution's lead disappears. v1: 3.97 vs 3.41 (+0.56). v2: 3.79 vs 3.85 (−0.06); manufacturing 2.91 stays last. With one indicator per criterion and Phase 4's list-price ACV, the two leading segments are a statistical tie: moving a single criterion's weight by about 2–6 points flips the order (Weight_Sensitivity Block B).
A17: 2. Bridge from v1 (distribution − professional services gap): reachable accounts instead of SAM dollars −0.64; dropping the duplicated coverage half of Need +0.14; evidence-based product-fit index −0.20; usage-based ACV +0.09. v1's lead came mostly from scoring market size in dollars at a uniform ACV with a filter built on the same sales share that also drove Need and Revenue.
A18: 3. Robustness is now two-sided: professional services wins 5 of 6 named weight sets and 57% of flat random weightings; distribution wins under concave size scoring (T11: 3.99 vs 3.85), min-max scaling, Upside usage, the v1 market definition and a working partner channel (T1). Neither segment wins robustly.
A19: 4. The scorecard can no longer decide the segment on its own. Tie-breakers: (a) Clay's differentiation is real only in distribution (competitive position 4.0 vs 2.3); (b) on the 07 v2 economics distribution is better on all six comparisons (Economic_Crosscheck), mainly because more professional-services wins would arrive through Clay's horizontal motion anyway and its list-price ACV sits at the Growth floor.
A20: 5. Implication: if Clay tests a vertical at all (07 v2 supports only a low-cost validation or solution play), distribution remains the better test bed, and professional services stays in the horizontal motion. The beachhead is reopened: 4238 machinery/MRO outscores 4236 electrical on v2 indicators (4.70 vs 4.07); 4236's edges are higher ACV per account and the only public reference (Regency) (Subsegment_Drilldown).

Sheet Weights
A1: Weights — the brief's suggested weights plus five alternative sets (unchanged from v1 for comparability)
A2: Blue = input. Each column must sum to 100%.
A4: Criterion | B4: Base (brief) | C4: Equal | D4: Market-size first | E4: Execution first | F4: Differentiation first | G4: Near-term revenue | H4: Single indicator used in v2
A5: Market Attractiveness | B5: 0.2 | C5: 0.16666667 | D5: 0.3 | E5: 0.15 | F5: 0.15 | G5: 0.15 | H5: Reachable accounts: unique firms (20+) × CRM in use × (1 − already Clay customers)
A6: Customer Need | B6: 0.2 | C6: 0.16666667 | D6: 0.15 | E6: 0.15 | F6: 0.2 | G6: 0.1 | H6: Sales intensity: sales occupations share of employment ÷ all-industry share
A7: Product-Market Fit | B7: 0.2 | C7: 0.16666667 | D7: 0.15 | E7: 0.2 | F7: 0.15 | G7: 0.2 | H7: Capability-fit index: mean fit of Clay's current product across the segment's core jobs (05 §3), builder-capacity gap excluded
A8: Revenue Potential | B8: 0.15 | C8: 0.16666667 | D8: 0.25 | E8: 0.1 | F8: 0.1 | G8: 0.3 | H8: Revenue per account: usage-based first-year ACV per won account at list prices, account-mix weighted (Phase 4 method)
A9: Competitive Position | B9: 0.15 | C9: 0.16666667 | D9: 0.1 | E9: 0.1 | F9: 0.3 | G9: 0.1 | H9: Competitive position: 04 factors F1 data differentiation, F2 incumbent saturation, F3 specialist threat (the coverage proxy enters only here, via F1)
A10: Ease of Execution | B10: 0.1 | C10: 0.16666667 | D10: 0.05 | E10: 0.3 | F10: 0.1 | G10: 0.15 | H10: Adoption / execution fit: 04 factors F4 builder capacity, F5 references and partner channel
A11: Check: sum | B11: =SUM(B5:B10) -> 1 | C11: =SUM(C5:C10) -> 1 | D11: =SUM(D5:D10) -> 1 | E11: =SUM(E5:E10) -> 1 | F11: =SUM(F5:F10) -> 1 | G11: =SUM(G5:G10) -> 1

Sheet Inputs
A1: Inputs — one indicator per criterion (v2)
A2: Blue = input copied from the named source; black = formula. Yellow = analyst judgment.
A4: ID | B4: Indicator | C4: Criterion | D4: A. Industrial Distribution | E4: B. Industrial Manufacturing | F4: C. B2B Prof. Services | G4: Unit | H4: Class | I4: Source
A5: I1 | B5: Unique U.S. firms with 20+ employees (de-duplicated) | D5: 11494 | E5: 23785 | F5: 33035 | G5: firms | H5: C from A | I5: 02_Market_Sizing › Firm_Counts (Census 2022, S14)
A6: I2 | B6: Share with a CRM in use (integrable today) | D6: 0.56 | E6: 0.6 | F6: 0.7 | G6: % | H6: B / D | I6: Dist: Phocas/DSG 2026, 56% use CRM (S25). Mfg, PS: Phase 1 assumptions (02 A8, A9)
A7: I3 | B7: Share already Clay customers (excluded) | D7: 0.03 | E7: 0.03 | F7: 0.1 | G7: % | H7: D | I7: 07 v2 Assumptions; PS higher: Clay markets to PS (S06), IT services top detected industry (S32)
A8: I4 | B8: Reachable accounts = I1 × I2 × (1 − I3) | C8: Market Attractiveness | D8: =D5*D6*(1-D7) -> 6243.5408 | E8: =E5*E6*(1-E7) -> 13842.87 | F8: =F5*F6*(1-F7) -> 20812.05 | G8: accounts | H8: C | I8: Formula
A9: I5 | B9: Sales occupations share of employment | D9: 0.21956 | E9: 0.02739 | F9: 0.061719 | G9: % | H9: A → C | I9: BLS OEWS May 2025 (S15) via 02 Segment_Profile
A10: I6 | B10: Sales intensity index = I5 ÷ all-industry share | C10: Customer Need | D10: =D9/Inputs!$D$17 -> 2.5431972 | E10: =E9/Inputs!$D$17 -> 0.31726258 | F10: =F9/Inputs!$D$17 -> 0.71490066 | G10: index | H10: C | I10: Formula; all industries 8.633% (S15)
A11: I7 | B11: Capability-fit index (mean of pain-point fit, 1–3) | D11: =D30 -> 2.5 | E11: =E30 -> 2 | F11: =F30 -> 3 | G11: 1–3 | H11: C | I11: Pain-to-capability map below (05 §3)
A12: I8 | B12: Product-market fit score = 1 + 4 × (I7 − 1) ÷ 2 | C12: Product-Market Fit | D12: =1+4*(D11-1)/2 -> 4 | E12: =1+4*(E11-1)/2 -> 3 | F12: =1+4*(F11-1)/2 -> 5 | G12: 1–5 | H12: C | I12: Formula
A13: I9 | B13: Usage-based first-year ACV per won account (Base usage) | C13: Revenue Potential | D13: =D100 -> 8939.6836 | E13: =E100 -> 7057.0783 | F13: =F100 -> 7071.5361 | G13: $ | H13: C / D | I13: ACV block below (07 v2 method, published Growth prices S01)
A14: I10 | B14: Same, at Upside usage (1.5×) — stress test T10 only | D14: =D101 -> 11632.506 | E14: =E101 -> 7057.0783 | F14: =F101 -> 7071.5361 | G14: $ | H14: D | I14: ACV block below
A15: I11 | B15: Competitive position (mean of F1–F3) | C15: Competitive Position | D15: =AVERAGE(D34:D36) -> 4 | E15: =AVERAGE(E34:E36) -> 3.3333333 | F15: =AVERAGE(F34:F36) -> 2.3333333 | G15: 1–5 | H15: C | I15: 04_Competitive_Analysis › Segment_Scoring
A16: I12 | B16: Adoption / execution fit (mean of F4–F5) | C16: Ease of Execution | D16: =AVERAGE(D37:D38) -> 2 | E16: =AVERAGE(E37:E38) -> 1.5 | F16: =AVERAGE(F37:F38) -> 4.5 | G16: 1–5 | H16: C | I16: 04_Competitive_Analysis › Segment_Scoring
A17: All-industry sales occupations share | D17: 0.086332274 | I17: BLS OEWS May 2025: 13,424,300 ÷ 155,495,730 (S15)
A19: Pain-to-capability map (05 §3). Fit: 3 = strong, 2 = partial, 1 = weak/gap; blank = not a core job for the segment. The builder-capacity gap is excluded here and scored under Ease of Execution.
A20: # | B20: Pain point / core job | C20: Clay capability | D20: A. Industrial Distribution | E20: B. Industrial Manufacturing | F20: C. B2B Prof. Services | I20: Gap
A21: 1 | B21: Finding contractors and local accounts missing from B2B databases | C21: Google Maps, Shovels permits, waterfall, Claygent | D21: 3 | I21: Construction-project and licence data
A22: 2 | B22: Prioritizing accounts by territory and branch | C22: Scoring, audiences, signals | D22: 3 | I22: Branch-level templates
A23: 3 | B23: Keeping CRM complete when reps don't log | C23: CRM auto-sync, enrichment, job-change tracking | D23: 3 | E23: 3 | I23: Needs a CRM
A24: 4 | B24: Vetting e-commerce and inbound registrations | C24: Webhook → AI verification → routing | D24: 3 | I24: Packaged template
A25: 5 | B25: Cross-selling to existing accounts from order history | C25: Warehouse sync / HTTP API only | D25: 1 | I25: No ERP connector (Proton.ai, ERP CRMs own this)
A26: 6 | B26: Construction project and bid timing | C26: Public bid signals, permits | D26: 2 | E26: 2 | I26: Private projects (Dodge) not in marketplace
A27: 7 | B27: Capturing sourcing-platform demand (Thomasnet) | C27: — | E27: 1 | I27: No API
A28: 8 | B28: Researching prospects before pursuits / RFPs | C28: Claygent, account agents, pre-call prep | F28: 3 | I28: —
A29: 9 | B29: Targeted outbound for new clients | C29: Audiences, signals, sequencer | F29: 3 | I29: Strong substitutes (Apollo, internal builds)
B30: Mean fit (I7) and number of core jobs mapped | D30: =AVERAGE(D21:D29) -> 2.5 | E30: =AVERAGE(E21:E29) -> 2 | F30: =AVERAGE(F21:F29) -> 3
B31: Core jobs mapped (small samples: read I8 with care) | D31: =COUNT(D21:D29) -> 6 | E31: =COUNT(E21:E29) -> 3 | F31: =COUNT(F21:F29) -> 2
A33: Competitive position and adoption factors (04 › Segment_Scoring; analyst judgments [C] tied to evidence there)
A34: F1 | B34: Relevance of Clay's data differentiation (off-LinkedIn, multi-source) | C34: → I11 | D34: 5 | E34: 3 | F34: 2
A35: F2 | B35: Incumbent saturation (5 = little entrenched sales-intelligence use) | C35: → I11 | D35: 4 | E35: 4 | F35: 2
A36: F3 | B36: Threat from vertical specialists / systems of record (5 = low) | C36: → I11 | D36: 3 | E36: 3 | F36: 3
A37: F4 | B37: Builder capacity to self-serve Clay | C37: → I12 | D37: 2 | E37: 1 | F37: 5
A38: F5 | B38: Existing references and partner channel | C38: → I12 | D38: 2 | E38: 2 | F38: 4
A40: Usage-based ACV per won account (07 v2 method). Pricing and usage parameters from 07 › Assumptions (Base).
B41: Data-credit pack price ($/mo) | D41: 261
B42: Data-credit pack size (credits/yr) | D42: 72000
B43: Actions pack price ($/mo) | D43: 185
B44: Actions pack size (actions/yr) | D44: 480000
B45: Accounts tracked per seller | D45: 150
B46: Contacts per account | D46: 2
B47: Refreshes per year | D47: 2
B48: Credits per contact refresh | D48: 6
B49: AI credits per account | D49: 4
B50: New accounts sourced per year (% of tracked) | D50: 0.25
B51: Credits per new account | D51: 8
B52: Actions per row operation | D52: 6
... B58: Enterprise propensity | D58: 0.7
B59: Usage intensity — Base / Upside | D59: 1 | E59: 1.5
A61: NAICS | B61: Industry (Census 2022, S14) | C61: Segment | D61: Firms 20–49 | E61: 50–99 | F61: 100–249 | G61: 250–499 | H61: 500+ | I61: Employees 20–49 · 50–99 · 100–249 · 250–499 · 500+ (cols J–N) | J61: Emp 20–49 | K61: 50–99 | L61: 100–249 | M61: 250–499 | N61: 500+
A62: 4236 | B62: 4236 | C62: Distribution | D62: 1408 | E62: 570 | F62: 350 | G62: 136 | H62: 114 | J62: 42698 | K62: 39297 | L62: 54183 | M62: 47492 | N62: 315093
A63: 4237 | B63: 4237 | C63: Distribution | D63: 1013 | E63: 424 | F63: 242 | G63: 85 | H63: 57 | J63: 31260 | K63: 29270 | L63: 36995 | M63: 29008 | N63: 116895
A64: 4238 | B64: 4238 | C64: Distribution | D64: 3622 | E64: 1218 | F64: 746 | G64: 240 | H64: 183 | J64: 110129 | K64: 83565 | L64: 115979 | M64: 83365 | N64: 220621
A65: 326 | B65: 326 | C65: Manufacturing | D65: 1505 | E65: 935 | F65: 760 | G65: 313 | H65: 277 | J65: 48064 | K65: 66254 | L65: 119875 | M65: 108128 | N65: 450163
A66: 332 | B66: 332 | C66: Manufacturing | D66: 7758 | E66: 3050 | F66: 1685 | G66: 423 | H66: 278 | J66: 238654 | K66: 210252 | L66: 253795 | M66: 147406 | N66: 354948
A67: 333 | B67: 333 | C67: Manufacturing | D67: 3291 | E67: 1484 | F67: 997 | G67: 358 | H67: 295 | J67: 102872 | K67: 103029 | L67: 151690 | M67: 123683 | N67: 513567
A68: 335 | B68: 335 | C68: Manufacturing | D68: 775 | E68: 422 | F68: 288 | G68: 108 | H68: 129 | J68: 24550 | K68: 29321 | L68: 44277 | M68: 37403 | N68: 220680
A69: 5413 | B69: 5413 | C69: Prof. services | D69: 5930 | E69: 2104 | F69: 1251 | G69: 429 | H69: 387 | J69: 179028 | K69: 145073 | L69: 189979 | M69: 149368 | N69: 727292
A70: 5415 | B70: 5415 | C70: Prof. services | D70: 5831 | E70: 2359 | F70: 1581 | G70: 561 | H70: 447 | J70: 179046 | K70: 164769 | L70: 240853 | M70: 195289 | N70: 1156449
A71: 5416 | B71: 5416 | C71: Prof. services | D71: 5789 | E71: 2151 | F71: 1244 | G71: 430 | H71: 339 | J71: 174222 | K71: 148901 | L71: 188821 | M71: 149492 | N71: 677207
A72: 5418 | B72: 5418 | C72: Prof. services | D72: 1655 | E72: 584 | F72: 371 | G72: 132 | H72: 102 | J72: 49648 | K72: 40398 | L72: 56587 | M72: 44231 | N72: 230304
B73: De-duplication factor by band — Distribution | D73: 0.973 | E73: 1 | F73: 1 | G73: 1 | H73: 1
B74: De-duplication factor by band — Manufacturing | D74: 0.97 | E74: 0.936 | F74: 0.9 | G74: 0.908 | H74: 0.913
B75: De-duplication factor by band — Prof. services | D75: 0.988 | E75: 0.979 | F75: 0.967 | G75: 0.951 | H75: 0.972
B76: Manufacturing factors: sector 31-33 ÷ Σ subsectors (overlap_raw.csv); 250+ bands omit suppressed subsectors
A78: Band | B78: Line | D78: A. Industrial Distribution | E78: B. Industrial Manufacturing | F78: C. B2B Prof. Services | I78: Formula
A79: SMB 20–99 | B79: Firms (de-duplicated) | D79: =D62*D$73+E62*E$73+D63*D$73+E63*E$73+D64*D$73+E64*E$73 -> 8091.839 | E79: =D65*D$74+E65*E$74+D66*D$74+E66*E$74+D67*D$74+E67*E$74+D68*D$74+E68*E$74 -> 18443.106 | F79: =D69*D$75+E69*E$75+D70*D$75+E70*E$75+D71*D$75+E71*E$75+D72*D$75+E72*E$75 -> 26021.382
B80: Employees | D80: =J62+K62+J63+K63+J64+K64 -> 336219 | E80: =J65+K65+J66+K66+J67+K67+J68+K68 -> 822996 | F80: =J69+K69+J70+K70+J71+K71+J72+K72 -> 1081085
B81: Firms (raw, for averages) | D81: =D62+E62+D63+E63+D64+E64 -> 8255 | E81: =D65+E65+D66+E66+D67+E67+D68+E68 -> 19220 | F81: =D69+E69+D70+E70+D71+E71+D72+E72 -> 26403
B82: Sellers per firm = employees ÷ firms × sales share | D82: =D80/D81*D$9 -> 8.9424886 | E82: =E80/E81*E$9 -> 1.1728335 | F82: =F80/F81*F$9 -> 2.5271176
B83: First-year ACV at Base usage | D83: =MAX((Inputs!$D$41+Inputs!$D$43)*12,((((D82*Inputs!$D$45*Inputs!$D$59)*Inputs!$D$46)*Inputs!$D$47*Inputs!$D$48+(D82*Inputs!$D$45*Inputs!$D$59)*Inputs!$D$49+(D82*Inputs!$D$45*Inputs!$D$59)*Inputs!$D$50*Inputs!$D$51)*(Inputs!$D$41*12/Inputs!$D$42)+(((D82*Inputs!$D$45*Inputs!$D$59)*Inputs!$D$46)*Inputs!$D$47+(D82*Inputs!$D$45*Inputs!$D$59)+(D82*Inputs!$D$45*Inputs!$D$59)*Inputs!$D$50)*Inputs!$D$52*(Inputs!$D$43*12/Inputs!$D$44))) -> 5352 | E83: =MAX((Inputs!$D$41+Inputs!$D$43)*12,((((E82*Inputs!$D$45*Inputs!$D$59)*Inputs!$D$46)*Inputs!$D$47*Inputs!$D$48+(E82*Inputs!$D$45*Inputs!$D$59)*Inputs!$D$49+(E82*Inputs!$D$45*Inputs!$D$59)*Inputs!$D$50*Inputs!$D$51)*(Inputs!$D$41*12/Inputs!$D$42)+(((E82*Inputs!$D$45*Inputs!$D$59)*Inputs!$D$46)*Inputs!$D$47+(E82*Inputs!$D$45*Inputs!$D$59)+(E82*Inputs!$D$45*Inputs!$D$59)*Inputs!$D$50)*Inputs!$D$52*(Inputs!$D$43*12/Inputs!$D$44))) -> 5352 | F83: =MAX((Inputs!$D$41+Inputs!$D$43)*12,((((F82*Inputs!$D$45*Inputs!$D$59)*Inputs!$D$46)*Inputs!$D$47*Inputs!$D$48+(F82*Inputs!$D$45*Inputs!$D$59)*Inputs!$D$49+(F82*Inputs!$D$45*Inputs!$D$59)*Inputs!$D$50*Inputs!$D$51)*(Inputs!$D$41*12/Inputs!$D$42)+(((F82*Inputs!$D$45*Inputs!$D$59)*Inputs!$D$46)*Inputs!$D$47+(F82*Inputs!$D$45*Inputs!$D$59)+(F82*Inputs!$D$45*Inputs!$D$59)*Inputs!$D$50)*Inputs!$D$52*(Inputs!$D$43*12/Inputs!$D$44))) -> 5352
B84: First-year ACV at Upside usage | D84: =MAX((Inputs!$D$41+Inputs!$D$43)*12,((((D82*Inputs!$D$45*Inputs!$E$59)*Inputs!$D$46)*Inputs!$D$47*Inputs!$D$48+(D82*Inputs!$D$45*Inputs!$E$59)*Inputs!$D$49+(D82*Inputs!$D$45*Inputs!$E$59)*Inputs!$D$50*Inputs!$D$51)*(Inputs!$D$41*12/Inputs!$D$42)+(((D82*Inputs!$D$45*Inputs!$E$59)*Inputs!$D$46)*Inputs!$D$47+(D82*Inputs!$D$45*Inputs!$E$59)+(D82*Inputs!$D$45*Inputs!$E$59)*Inputs!$D$50)*Inputs!$D$52*(Inputs!$D$43*12/Inputs!$D$44))) -> 5352 | E84: =MAX((Inputs!$D$41+Inputs!$D$43)*12,((((E82*Inputs!$D$45*Inputs!$E$59)*Inputs!$D$46)*Inputs!$D$47*Inputs!$D$48+(E82*Inputs!$D$45*Inputs!$E$59)*Inputs!$D$49+(E82*Inputs!$D$45*Inputs!$E$59)*Inputs!$D$50*Inputs!$D$51)*(Inputs!$D$41*12/Inputs!$D$42)+(((E82*Inputs!$D$45*Inputs!$E$59)*Inputs!$D$46)*Inputs!$D$47+(E82*Inputs!$D$45*Inputs!$E$59)+(E82*Inputs!$D$45*Inputs!$E$59)*Inputs!$D$50)*Inputs!$D$52*(Inputs!$D$43*12/Inputs!$D$44))) -> 5352 | F84: =MAX((Inputs!$D$41+Inputs!$D$43)*12,((((F82*Inputs!$D$45*Inputs!$E$59)*Inputs!$D$46)*Inputs!$D$47*Inputs!$D$48+(F82*Inputs!$D$45*Inputs!$E$59)*Inputs!$D$49+(F82*Inputs!$D$45*Inputs!$E$59)*Inputs!$D$50*Inputs!$D$51)*(Inputs!$D$41*12/Inputs!$D$42)+(((F82*Inputs!$D$45*Inputs!$E$59)*Inputs!$D$46)*Inputs!$D$47+(F82*Inputs!$D$45*Inputs!$E$59)+(F82*Inputs!$D$45*Inputs!$E$59)*Inputs!$D$50)*Inputs!$D$52*(Inputs!$D$43*12/Inputs!$D$44))) -> 5352
B85: Opportunity weight = firms × tilt × propensity | D85: =D79*1 -> 8091.839 | E85: =E79*1 -> 18443.106 | F85: =F79*1 -> 26021.382
A86: Mid-Market 100–499 | B86: Firms (de-duplicated) | D86: =F62*F$73+G62*G$73+F63*F$73+G63*G$73+F64*F$73+G64*G$73 -> 1799 | E86: =F65*F$74+G65*G$74+F66*F$74+G66*G$74+F67*F$74+G67*G$74+F68*F$74+G68*G$74 -> 4448.416 | F86: =F69*F$75+G69*G$75+F70*F$75+G70*G$75+F71*F$75+G71*G$75+F72*F$75+G72*G$75 -> 5776.201
B87: Employees | D87: =L62+M62+L63+M63+L64+M64 -> 367022 | E87: =L65+M65+L66+M66+L67+M67+L68+M68 -> 986257 | F87: =L69+M69+L70+M70+L71+M71+L72+M72 -> 1214620
B88: Firms (raw, for averages) | D88: =F62+G62+F63+G63+F64+G64 -> 1799 | E88: =F65+G65+F66+G66+F67+G67+F68+G68 -> 4932 | F88: =F69+G69+F70+G70+F71+G71+F72+G72 -> 5999
B89: Sellers per firm = employees ÷ firms × sales share | D89: =D87/D88*D$9 -> 44.793413 | E89: =E87/E88*E$9 -> 5.4772058 | F89: =F87/F88*F$9 -> 12.496271
B90: First-year ACV at Base usage | D90: =MAX((Inputs!$D$41+Inputs!$D$43)*12,((((D89*Inputs!$D$45*Inputs!$D$59)*Inputs!$D$46)*Inputs!$D$47*Inputs!$D$48+(D89*Inputs!$D$45*Inputs!$D$59)*Inputs!$D$49+(D89*Inputs!$D$45*Inputs!$D$59)*Inputs!$D$50*Inputs!$D$51)*(Inputs!$D$41*12/Inputs!$D$42)+(((D89*Inputs!$D$45*Inputs!$D$59)*Inputs!$D$46)*Inputs!$D$47+(D89*Inputs!$D$45*Inputs!$D$59)+(D89*Inputs!$D$45*Inputs!$D$59)*Inputs!$D$50)*Inputs!$D$52*(Inputs!$D$43*12/Inputs!$D$44))) -> 9747.1867 | E90: =MAX((Inputs!$D$41+Inputs!$D$43)*12,((((E89*Inputs!$D$45*Inputs!$D$59)*Inputs!$D$46)*Inputs!$D$47*Inputs!$D$48+(E89*Inputs!$D$45*Inputs!$D$59)*Inputs!$D$49+(E89*Inputs!$D$45*Inputs!$D$59)*Inputs!$D$50*Inputs!$D$51)*(Inputs!$D$41*12/Inputs!$D$42)+(((E89*Inputs!$D$45*Inputs!$D$59)*Inputs!$D$46)*Inputs!$D$47+(E89*Inputs!$D$45*Inputs!$D$59)+(E89*Inputs!$D$45*Inputs!$D$59)*Inputs!$D$50)*Inputs!$D$52*(Inputs!$D$43*12/Inputs!$D$44))) -> 5352 | F90: =MAX((Inputs!$D$41+Inputs!$D$43)*12,((((F89*Inputs!$D$45*Inputs!$D$59)*Inputs!$D$46)*Inputs!$D$47*Inputs!$D$48+(F89*Inputs!$D$45*Inputs!$D$59)*Inputs!$D$49+(F89*Inputs!$D$45*Inputs!$D$59)*Inputs!$D$50*Inputs!$D$51)*(Inputs!$D$41*12/Inputs!$D$42)+(((F89*Inputs!$D$45*Inputs!$D$59)*Inputs!$D$46)*Inputs!$D$47+(F89*Inputs!$D$45*Inputs!$D$59)+(F89*Inputs!$D$45*Inputs!$D$59)*Inputs!$D$50)*Inputs!$D$52*(Inputs!$D$43*12/Inputs!$D$44))) -> 5352
B91: First-year ACV at Upside usage | D91: =MAX((Inputs!$D$41+Inputs!$D$43)*12,((((D89*Inputs!$D$45*Inputs!$E$59)*Inputs!$D$46)*Inputs!$D$47*Inputs!$D$48+(D89*Inputs!$D$45*Inputs!$E$59)*Inputs!$D$49+(D89*Inputs!$D$45*Inputs!$E$59)*Inputs!$D$50*Inputs!$D$51)*(Inputs!$D$41*12/Inputs!$D$42)+(((D89*Inputs!$D$45*Inputs!$E$59)*Inputs!$D$46)*Inputs!$D$47+(D89*Inputs!$D$45*Inputs!$E$59)+(D89*Inputs!$D$45*Inputs!$E$59)*Inputs!$D$50)*Inputs!$D$52*(Inputs!$D$43*12/Inputs!$D$44))) -> 14620.78 | E91: =MAX((Inputs!$D$41+Inputs!$D$43)*12,((((E89*Inputs!$D$45*Inputs!$E$59)*Inputs!$D$46)*Inputs!$D$47*Inputs!$D$48+(E89*Inputs!$D$45*Inputs!$E$59)*Inputs!$D$49+(E89*Inputs!$D$45*Inputs!$E$59)*Inputs!$D$50*Inputs!$D$51)*(Inputs!$D$41*12/Inputs!$D$42)+(((E89*Inputs!$D$45*Inputs!$E$59)*Inputs!$D$46)*Inputs!$D$47+(E89*Inputs!$D$45*Inputs!$E$59)+(E89*Inputs!$D$45*Inputs!$E$59)*Inputs!$D$50)*Inputs!$D$52*(Inputs!$D$43*12/Inputs!$D$44))) -> 5352 | F91: =MAX((Inputs!$D$41+Inputs!$D$43)*12,((((F89*Inputs!$D$45*Inputs!$E$59)*Inputs!$D$46)*Inputs!$D$47*Inputs!$D$48+(F89*Inputs!$D$45*Inputs!$E$59)*Inputs!$D$49+(F89*Inputs!$D$45*Inputs!$E$59)*Inputs!$D$50*Inputs!$D$51)*(Inputs!$D$41*12/Inputs!$D$42)+(((F89*Inputs!$D$45*Inputs!$E$59)*Inputs!$D$46)*Inputs!$D$47+(F89*Inputs!$D$45*Inputs!$E$59)+(F89*Inputs!$D$45*Inputs!$E$59)*Inputs!$D$50)*Inputs!$D$52*(Inputs!$D$43*12/Inputs!$D$44))) -> 5352
B92: Opportunity weight = firms × tilt × propensity | D92: =D86*Inputs!$D$56 -> 3598 | E92: =E86*Inputs!$D$56 -> 8896.832 | F92: =F86*Inputs!$D$56 -> 11552.402
A93: Enterprise 500+ | B93: Firms (de-duplicated) | D93: =H62*H$73+H63*H$73+H64*H$73 -> 354 | E93: =H65*H$74+H66*H$74+H67*H$74+H68*H$74 -> 893.827 | F93: =H69*H$75+H70*H$75+H71*H$75+H72*H$75 -> 1239.3
B94: Employees | D94: =N62+N63+N64 -> 652609 | E94: =N65+N66+N67+N68 -> 1539358 | F94: =N69+N70+N71+N72 -> 2791252
B95: Firms (raw, for averages) | D95: =H62+H63+H64 -> 354 | E95: =H65+H66+H67+H68 -> 979 | F95: =H69+H70+H71+H72 -> 1275
B96: Sellers per firm = employees ÷ firms × sales share | D96: =D94/D95*D$9 -> 404.76506 | E96: =E94/E95*E$9 -> 43.067432 | F96: =F94/F95*F$9 -> 135.1163
B97: First-year ACV at Base usage | D97: =MAX(Inputs!$D$53*(Inputs!$D$41*12/Inputs!$D$42)+Inputs!$D$54*(Inputs!$D$43*12/Inputs!$D$44),((((D96*Inputs!$D$45*Inputs!$D$59)*Inputs!$D$46)*Inputs!$D$47*Inputs!$D$48+(D96*Inputs!$D$45*Inputs!$D$59)*Inputs!$D$49+(D96*Inputs!$D$45*Inputs!$D$59)*Inputs!$D$50*Inputs!$D$51)*(Inputs!$D$41*12/Inputs!$D$42)+(((D96*Inputs!$D$45*Inputs!$D$59)*Inputs!$D$46)*Inputs!$D$47+(D96*Inputs!$D$45*Inputs!$D$59)+(D96*Inputs!$D$45*Inputs!$D$59)*Inputs!$D$50)*Inputs!$D$52*(Inputs!$D$43*12/Inputs!$D$44)))*(1-Inputs!$D$55) -> 61654.7 | E97: =MAX(Inputs!$D$53*(Inputs!$D$41*12/Inputs!$D$42)+Inputs!$D$54*(Inputs!$D$43*12/Inputs!$D$44),((((E96*Inputs!$D$45*Inputs!$D$59)*Inputs!$D$46)*Inputs!$D$47*Inputs!$D$48+(E96*Inputs!$D$45*Inputs!$D$59)*Inputs!$D$49+(E96*Inputs!$D$45*Inputs!$D$59)*Inputs!$D$50*Inputs!$D$51)*(Inputs!$D$41*12/Inputs!$D$42)+(((E96*Inputs!$D$45*Inputs!$D$59)*Inputs!$D$46)*Inputs!$D$47+(E96*Inputs!$D$45*Inputs!$D$59)+(E96*Inputs!$D$45*Inputs!$D$59)*Inputs!$D$50)*Inputs!$D$52*(Inputs!$D$43*12/Inputs!$D$44)))*(1-Inputs!$D$55) -> 44310 | F97: =MAX(Inputs!$D$53*(Inputs!$D$41*12/Inputs!$D$42)+Inputs!$D$54*(Inputs!$D$43*12/Inputs!$D$44),((((F96*Inputs!$D$45*Inputs!$D$59)*Inputs!$D$46)*Inputs!$D$47*Inputs!$D$48+(F96*Inputs!$D$45*Inputs!$D$59)*Inputs!$D$49+(F96*Inputs!$D$45*Inputs!$D$59)*Inputs!$D$50*Inputs!$D$51)*(Inputs!$D$41*12/Inputs!$D$42)+(((F96*Inputs!$D$45*Inputs!$D$59)*Inputs!$D$46)*Inputs!$D$47+(F96*Inputs!$D$45*Inputs!$D$59)+(F96*Inputs!$D$45*Inputs!$D$59)*Inputs!$D$50)*Inputs!$D$52*(Inputs!$D$43*12/Inputs!$D$44)))*(1-Inputs!$D$55) -> 44310
B98: First-year ACV at Upside usage | D98: =MAX(Inputs!$D$53*(Inputs!$D$41*12/Inputs!$D$42)+Inputs!$D$54*(Inputs!$D$43*12/Inputs!$D$44),((((D96*Inputs!$D$45*Inputs!$E$59)*Inputs!$D$46)*Inputs!$D$47*Inputs!$D$48+(D96*Inputs!$D$45*Inputs!$E$59)*Inputs!$D$49+(D96*Inputs!$D$45*Inputs!$E$59)*Inputs!$D$50*Inputs!$D$51)*(Inputs!$D$41*12/Inputs!$D$42)+(((D96*Inputs!$D$45*Inputs!$E$59)*Inputs!$D$46)*Inputs!$D$47+(D96*Inputs!$D$45*Inputs!$E$59)+(D96*Inputs!$D$45*Inputs!$E$59)*Inputs!$D$50)*Inputs!$D$52*(Inputs!$D$43*12/Inputs!$D$44)))*(1-Inputs!$D$55) -> 92482.05 | E98: =MAX(Inputs!$D$53*(Inputs!$D$41*12/Inputs!$D$42)+Inputs!$D$54*(Inputs!$D$43*12/Inputs!$D$44),((((E96*Inputs!$D$45*Inputs!$E$59)*Inputs!$D$46)*Inputs!$D$47*Inputs!$D$48+(E96*Inputs!$D$45*Inputs!$E$59)*Inputs!$D$49+(E96*Inputs!$D$45*Inputs!$E$59)*Inputs!$D$50*Inputs!$D$51)*(Inputs!$D$41*12/Inputs!$D$42)+(((E96*Inputs!$D$45*Inputs!$E$59)*Inputs!$D$46)*Inputs!$D$47+(E96*Inputs!$D$45*Inputs!$E$59)+(E96*Inputs!$D$45*Inputs!$E$59)*Inputs!$D$50)*Inputs!$D$52*(Inputs!$D$43*12/Inputs!$D$44)))*(1-Inputs!$D$55) -> 44310 | F98: =MAX(Inputs!$D$53*(Inputs!$D$41*12/Inputs!$D$42)+Inputs!$D$54*(Inputs!$D$43*12/Inputs!$D$44),((((F96*Inputs!$D$45*Inputs!$E$59)*Inputs!$D$46)*Inputs!$D$47*Inputs!$D$48+(F96*Inputs!$D$45*Inputs!$E$59)*Inputs!$D$49+(F96*Inputs!$D$45*Inputs!$E$59)*Inputs!$D$50*Inputs!$D$51)*(Inputs!$D$41*12/Inputs!$D$42)+(((F96*Inputs!$D$45*Inputs!$E$59)*Inputs!$D$46)*Inputs!$D$47+(F96*Inputs!$D$45*Inputs!$E$59)+(F96*Inputs!$D$45*Inputs!$E$59)*Inputs!$D$50)*Inputs!$D$52*(Inputs!$D$43*12/Inputs!$D$44)))*(1-Inputs!$D$55) -> 44310
B99: Opportunity weight = firms × tilt × propensity | D99: =D93*Inputs!$D$57*Inputs!$D$58 -> 495.6 | E99: =E93*Inputs!$D$57*Inputs!$D$58 -> 1251.3578 | F99: =F93*Inputs!$D$57*Inputs!$D$58 -> 1735.02
B100: Blended ACV per won account (Base usage) = Σ weight × ACV ÷ Σ weight | D100: =(D85*D83+D92*D90+D99*D97)/(D85+D92+D99) -> 8939.6836 | E100: =(E85*E83+E92*E90+E99*E97)/(E85+E92+E99) -> 7057.0783 | F100: =(F85*F83+F92*F90+F99*F97)/(F85+F92+F99) -> 7071.5361
B101: Blended ACV per won account (Upside usage) = Σ weight × ACV ÷ Σ weight | D101: =(D85*D84+D92*D91+D99*D98)/(D85+D92+D99) -> 11632.506 | E101: =(E85*E84+E92*E91+E99*E98)/(E85+E92+E99) -> 7057.0783 | F101: =(F85*F84+F92*F91+F99*F98)/(F85+F92+F99) -> 7071.5361
A103: Distribution ACV uses 4236–4238 (4235 has suppressed Census cells); the account count I1 uses Phase 1's full four-industry segment. Manufacturing and professional-services SMB and Mid-Market ACVs sit at the Growth floor because they have few sellers per firm.

Sheet Scorecard
A1: Scorecard v2 — one indicator per criterion, Phase 4 economics fed back
A2: Base weights from the brief. Quantitative indicators scale 1 + 4 × v ÷ max; judgment indicators are already 1–5.
A4: Base case (brief weights, ratio-to-max scaling)
A5: Criterion | B5: Line | C5: Distribution | D5: Manufacturing | E5: Prof. services | F5: Scoring
A6: Market Attractiveness | B6: metric | C6: =Inputs!D8 -> 6243.5408 | D6: =Inputs!E8 -> 13842.87 | E6: =Inputs!F8 -> 20812.05
A7: Customer Need | B7: metric | C7: =Inputs!D10 -> 2.5431972 | D7: =Inputs!E10 -> 0.31726258 | E7: =Inputs!F10 -> 0.71490066
A8: Product-Market Fit | B8: metric | C8: =Inputs!D12 -> 4 | D8: =Inputs!E12 -> 3 | E8: =Inputs!F12 -> 5
A9: Revenue Potential | B9: metric | C9: =Inputs!D13 -> 8939.6836 | D9: =Inputs!E13 -> 7057.0783 | E9: =Inputs!F13 -> 7071.5361
A10: Competitive Position | B10: metric | C10: =Inputs!D15 -> 4 | D10: =Inputs!E15 -> 3.3333333 | E10: =Inputs!F15 -> 2.3333333
A11: Ease of Execution | B11: metric | C11: =Inputs!D16 -> 2 | D11: =Inputs!E16 -> 1.5 | E11: =Inputs!F16 -> 4.5
A12: Market Attractiveness | B12: score 1–5 | C12: =1+4*C6/MAX($C$6:$E$6) -> 2.1999857 | D12: =1+4*D6/MAX($C$6:$E$6) -> 3.6605491 | E12: =1+4*E6/MAX($C$6:$E$6) -> 5 | F12: 1 + 4 × v ÷ max
A13: Customer Need | B13: score 1–5 | C13: =1+4*C7/MAX($C$7:$E$7) -> 5 | D13: =1+4*D7/MAX($C$7:$E$7) -> 1.498998 | E13: =1+4*E7/MAX($C$7:$E$7) -> 2.1244125 | F13: 1 + 4 × v ÷ max
A14: Product-Market Fit | B14: score 1–5 | C14: =C8 -> 4 | D14: =D8 -> 3 | E14: =E8 -> 5 | F14: already 1–5
A15: Revenue Potential | B15: score 1–5 | C15: =1+4*C9/MAX($C$9:$E$9) -> 5 | D15: =1+4*D9/MAX($C$9:$E$9) -> 4.1576412 | E15: =1+4*E9/MAX($C$9:$E$9) -> 4.1641103 | F15: 1 + 4 × v ÷ max
A16: Competitive Position | B16: score 1–5 | C16: =C10 -> 4 | D16: =D10 -> 3.3333333 | E16: =E10 -> 2.3333333 | F16: already 1–5
A17: Ease of Execution | B17: score 1–5 | C17: =C11 -> 2 | D17: =D11 -> 1.5 | E17: =E11 -> 4.5 | F17: already 1–5
A18: Weighted total | B18: Σ weight × score | C18: =SUMPRODUCT(Weights!$B$5:$B$10,C12:C17) -> 3.7899971 | D18: =SUMPRODUCT(Weights!$B$5:$B$10,D12:D17) -> 2.9055556 | E18: =SUMPRODUCT(Weights!$B$5:$B$10,E12:E17) -> 3.849499
A19: Winner / margin of distribution over professional services | C19: =INDEX({"Distribution","Manufacturing","Prof. services"},MATCH(MAX(C18:E18),C18:E18,0)) -> Prof. services | E19: =C18-E18 -> -0.059501883
A21: Contribution to total (weight × score)
A22: Market Attractiveness | B22: =Weights!$B$5 -> 0.2 | C22: =$B22*C12 -> 0.43999715 | D22: =$B22*D12 -> 0.73210981 | E22: =$B22*E12 -> 1
A23: Customer Need | B23: =Weights!$B$6 -> 0.2 | C23: =$B23*C13 -> 1 | D23: =$B23*D13 -> 0.2997996 | E23: =$B23*E13 -> 0.42488249
A24: Product-Market Fit | B24: =Weights!$B$7 -> 0.2 | C24: =$B24*C14 -> 0.8 | D24: =$B24*D14 -> 0.6 | E24: =$B24*E14 -> 1
A25: Revenue Potential | B25: =Weights!$B$8 -> 0.15 | C25: =$B25*C15 -> 0.75 | D25: =$B25*D15 -> 0.62364618 | E25: =$B25*E15 -> 0.62461654
A26: Competitive Position | B26: =Weights!$B$9 -> 0.15 | C26: =$B26*C16 -> 0.6 | D26: =$B26*D16 -> 0.5 | E26: =$B26*E16 -> 0.35
A27: Ease of Execution | B27: =Weights!$B$10 -> 0.1 | C27: =$B27*C17 -> 0.2 | D27: =$B27*D17 -> 0.15 | E27: =$B27*E17 -> 0.45
A29: Evidence behind each criterion
A30: Market Attractiveness | B30: Reachable accounts after the CRM screen and excluding existing Clay customers: ~6,200 distributors vs ~13,800 manufacturers and ~20,800 professional-services firms. Scaled linearly (T11 tests concave scaling).
A31: Customer Need | B31: Sales occupations are 22.0% of distribution employment, 2.5× the economy (S15). The coverage proxy no longer enters here (moved to Competitive Position only).
A32: Product-Market Fit | B32: Mean fit across each segment's mapped core jobs (05 §3). Professional services' research and outbound jobs are Clay's horizontal sweet spot (fit 3.0); distribution 2.5 (ERP cross-sell gap); manufacturing 2.0.
A33: Revenue Potential | B33: Usage-based ACV per won account at list prices (Phase 4): distribution ~$9.0K; manufacturing and professional services ~$7.1K because their SMB and Mid-Market ACVs sit at the Growth floor.
A34: Competitive Position | B34: Unchanged from 04: off-LinkedIn data relevance, incumbent saturation, specialist threat. The only criterion that uses the LinkedIn-coverage proxy.
A35: Ease of Execution | B35: Unchanged from 04: builder capacity and references/partners. Professional services 4.5 vs distribution 2.0.

Sheet Bridge_v1_v2
A1: Bridge v1 → v2 — how each definitional change moves the totals
A2: v1 criterion scores are typed from the archived v1 workbook; v2 scores link to the Scorecard. Each step swaps one criterion from its v1 to its v2 definition.
A4: Step | B4: What changed | C4: Distribution | D4: Manufacturing | E4: Prof. services | F4: Distribution − Prof. services
A5: v1 total (as published) | B5: Market = SAM $ + headroom flag; Need = sales intensity + coverage gap; PMF = judgment 4/2/4; Revenue = SOM + seller density | C5: =Weights!$B$5*C21+Weights!$B$6*C22+Weights!$B$7*C23+Weights!$B$8*C24+Weights!$B$9*C25+Weights!$B$10*C26 -> 3.9677801 | D5: =Weights!$B$5*D21+Weights!$B$6*D22+Weights!$B$7*D23+Weights!$B$8*D24+Weights!$B$9*D25+Weights!$B$10*D26 -> 2.7044653 | E5: =Weights!$B$5*E21+Weights!$B$6*E22+Weights!$B$7*E23+Weights!$B$8*E24+Weights!$B$9*E25+Weights!$B$10*E26 -> 3.41185 | F5: =C5-E5 -> 0.55593004
A6: 1. Market attractiveness | B6: SAM $ (uniform Phase 1 ACV) and a separate headroom flag → reachable accounts net of existing Clay customers | C6: =Weights!$B$5*Scorecard!C12+Weights!$B$6*C22+Weights!$B$7*C23+Weights!$B$8*C24+Weights!$B$9*C25+Weights!$B$10*C26 -> 3.6238346 | D6: =Weights!$B$5*Scorecard!D12+Weights!$B$6*D22+Weights!$B$7*D23+Weights!$B$8*D24+Weights!$B$9*D25+Weights!$B$10*D26 -> 2.6319095 | E6: =Weights!$B$5*Scorecard!E12+Weights!$B$6*E22+Weights!$B$7*E23+Weights!$B$8*E24+Weights!$B$9*E25+Weights!$B$10*E26 -> 3.71185 | F6: =C6-E6 -> -0.088015456
A7: 2. Customer need | B7: Drop the coverage-gap half (it already drives Competitive Position F1) → sales intensity only | C7: =Weights!$B$5*Scorecard!C12+Weights!$B$6*Scorecard!C13+Weights!$B$7*C23+Weights!$B$8*C24+Weights!$B$9*C25+Weights!$B$10*C26 -> 3.6238346 | D7: =Weights!$B$5*Scorecard!D12+Weights!$B$6*Scorecard!D13+Weights!$B$7*D23+Weights!$B$8*D24+Weights!$B$9*D25+Weights!$B$10*D26 -> 2.4257452 | E7: =Weights!$B$5*Scorecard!E12+Weights!$B$6*Scorecard!E13+Weights!$B$7*E23+Weights!$B$8*E24+Weights!$B$9*E25+Weights!$B$10*E26 -> 3.5758161 | F7: =C7-E7 -> 0.048018439
A8: 3. Product-market fit | B8: Free judgment 4/2/4 → capability-fit index from the 05 pain map | C8: =Weights!$B$5*Scorecard!C12+Weights!$B$6*Scorecard!C13+Weights!$B$7*Scorecard!C14+Weights!$B$8*C24+Weights!$B$9*C25+Weights!$B$10*C26 -> 3.6238346 | D8: =Weights!$B$5*Scorecard!D12+Weights!$B$6*Scorecard!D13+Weights!$B$7*Scorecard!D14+Weights!$B$8*D24+Weights!$B$9*D25+Weights!$B$10*D26 -> 2.6257452 | E8: =Weights!$B$5*Scorecard!E12+Weights!$B$6*Scorecard!E13+Weights!$B$7*Scorecard!E14+Weights!$B$8*E24+Weights!$B$9*E25+Weights!$B$10*E26 -> 3.7758161 | F8: =C8-E8 -> -0.15198156
A9: 4. Revenue potential | B9: SOM + seller density (assumed ACV lift) → usage-based ACV per won account (Phase 4) | C9: =Weights!$B$5*Scorecard!C12+Weights!$B$6*Scorecard!C13+Weights!$B$7*Scorecard!C14+Weights!$B$8*Scorecard!C15+Weights!$B$9*C25+Weights!$B$10*C26 -> 3.7899971 | D9: =Weights!$B$5*Scorecard!D12+Weights!$B$6*Scorecard!D13+Weights!$B$7*Scorecard!D14+Weights!$B$8*Scorecard!D15+Weights!$B$9*D25+Weights!$B$10*D26 -> 2.9055506 | E9: =Weights!$B$5*Scorecard!E12+Weights!$B$6*Scorecard!E13+Weights!$B$7*Scorecard!E14+Weights!$B$8*Scorecard!E15+Weights!$B$9*E25+Weights!$B$10*E26 -> 3.849494 | F9: =C9-E9 -> -0.059496883
A10: v2 total | B10: Competitive position and ease unchanged | C10: =Weights!$B$5*Scorecard!C12+Weights!$B$6*Scorecard!C13+Weights!$B$7*Scorecard!C14+Weights!$B$8*Scorecard!C15+Weights!$B$9*C25+Weights!$B$10*C26 -> 3.7899971 | D10: =Weights!$B$5*Scorecard!D12+Weights!$B$6*Scorecard!D13+Weights!$B$7*Scorecard!D14+Weights!$B$8*Scorecard!D15+Weights!$B$9*D25+Weights!$B$10*D26 -> 2.9055506 | E10: =Weights!$B$5*Scorecard!E12+Weights!$B$6*Scorecard!E13+Weights!$B$7*Scorecard!E14+Weights!$B$8*Scorecard!E15+Weights!$B$9*E25+Weights!$B$10*E26 -> 3.849494 | F10: =C10-E10 -> -0.059496883
A12: Check: v2 total equals Scorecard (should be 0) | C12: =ROUND(C10-Scorecard!C18,6)+ROUND(E10-Scorecard!E18,6) -> -5e-06
A14: Reading: the largest swing is market attractiveness — counting reachable accounts instead of SAM dollars (which carried a uniform ACV and an outbound filter rationalized with the same sales share) moves ~0.3 points from distribution to professional services. Revenue potential moves the other way once Phase 4's usage-based ACV replaces the assumed seller-density lift.
A20: v1 criterion scores (typed)
A21: Market Attractiveness | C21: 3.9197132 | D21: 4.023328 | E21: 3.5
A22: Customer Need | C22: 5 | D22: 2.5298196 | E22: 2.8045819
A23: Product-Market Fit | C23: 4 | D23: 2 | E23: 4
A24: Revenue Potential | C24: 3.8922494 | D24: 2.2922718 | E24: 3.6729242
A25: Competitive Position | C25: 4 | D25: 3.3333 | E25: 2.3333
A26: Ease of Execution | C26: 2 | D26: 1.5 | E26: 4.5

Sheet Weight_Sensitivity
A1: Weight sensitivity — named weight sets and break-even weights
A2: Block A: totals under six named weight sets. Block B: the weight on each criterion at which distribution and professional services tie (others rescaled proportionally).
A4: Weight set | B4: Distribution | C4: Manufacturing | D4: Prof. services | E4: Winner | F4: Dist − PS
A5: Base (brief) | B5: =SUMPRODUCT(Weights!$B$5:$B$10,Scorecard!C12:C17) -> 3.7899971 | C5: =SUMPRODUCT(Weights!$B$5:$B$10,Scorecard!D12:D17) -> 2.9055556 | D5: =SUMPRODUCT(Weights!$B$5:$B$10,Scorecard!E12:E17) -> 3.849499 | E5: =INDEX({"Distribution","Manufacturing","Prof. services"},MATCH(MAX(B5:D5),B5:D5,0)) -> Prof. services | F5: =B5-D5 -> -0.059501883
A6: Equal | B6: =SUMPRODUCT(Weights!$C$5:$C$10,Scorecard!C12:C17) -> 3.6999976 | C6: =SUMPRODUCT(Weights!$C$5:$C$10,Scorecard!D12:D17) -> 2.8584203 | D6: =SUMPRODUCT(Weights!$C$5:$C$10,Scorecard!E12:E17) -> 3.8536427 | E6: =INDEX({"Distribution","Manufacturing","Prof. services"},MATCH(MAX(B6:D6),B6:D6,0)) -> Prof. services | F6: =B6-D6 -> -0.15364505
A7: Market-size first | B7: =SUMPRODUCT(Weights!$D$5:$D$10,Scorecard!C12:C17) -> 3.7599957 | C7: =SUMPRODUCT(Weights!$D$5:$D$10,Scorecard!D12:D17) -> 3.220758 | D7: =SUMPRODUCT(Weights!$D$5:$D$10,Scorecard!E12:E17) -> 4.0680228 | E7: =INDEX({"Distribution","Manufacturing","Prof. services"},MATCH(MAX(B7:D7),B7:D7,0)) -> Prof. services | F7: =B7-D7 -> -0.30802704
A8: Execution first | B8: =SUMPRODUCT(Weights!$E$5:$E$10,Scorecard!C12:C17) -> 3.3799979 | C8: =SUMPRODUCT(Weights!$E$5:$E$10,Scorecard!D12:D17) -> 2.5730295 | D8: =SUMPRODUCT(Weights!$E$5:$E$10,Scorecard!E12:E17) -> 4.0684062 | E8: =INDEX({"Distribution","Manufacturing","Prof. services"},MATCH(MAX(B8:D8),B8:D8,0)) -> Prof. services | F8: =B8-D8 -> -0.68840837
A9: Differentiation first | B9: =SUMPRODUCT(Weights!$F$5:$F$10,Scorecard!C12:C17) -> 3.8299979 | C9: =SUMPRODUCT(Weights!$F$5:$F$10,Scorecard!D12:D17) -> 2.8646461 | D9: =SUMPRODUCT(Weights!$F$5:$F$10,Scorecard!E12:E17) -> 3.4912935 | E9: =INDEX({"Distribution","Manufacturing","Prof. services"},MATCH(MAX(B9:D9),B9:D9,0)) -> Distribution | F9: =B9-D9 -> 0.33870434
A10: Near-term revenue | B10: =SUMPRODUCT(Weights!$G$5:$G$10,Scorecard!C12:C17) -> 3.8299979 | C10: =SUMPRODUCT(Weights!$G$5:$G$10,Scorecard!D12:D17) -> 3.1046078 | D10: =SUMPRODUCT(Weights!$G$5:$G$10,Scorecard!E12:E17) -> 4.1200077 | E10: =INDEX({"Distribution","Manufacturing","Prof. services"},MATCH(MAX(B10:D10),B10:D10,0)) -> Prof. services | F10: =B10-D10 -> -0.2900098
A11: Named sets won by distribution | B11: =COUNTIF(E5:E10,"Distribution") -> 1
A12: Named sets won by professional services | B12: =COUNTIF(E5:E10,"Prof. services") -> 5
A15: Block B — break-even weight: distribution = professional services
A16: Criterion | B16: Base weight | C16: Score gap (Dist − PS) | D16: Rest-of-card gap | E16: Break-even weight | F16: Reading
A17: Market Attractiveness | B17: =Weights!$B$5 -> 0.2 | C17: =Scorecard!C12-Scorecard!E12 -> -2.8000143 | D17: =((Scorecard!C18-Scorecard!E18)-B17*C17)/(1-B17) -> 0.62562621 | E17: =IFERROR(IF(AND(D17/(D17-C17)>=0,D17/(D17-C17)<=1),D17/(D17-C17),"none in 0–100%"),"none") -> 0.18263044 | F17: =IF(ISNUMBER(E17),IF(C17>0,"Distribution leads above this weight","Prof. services leads above this weight"),"") -> Prof. services leads above this weight
A18: Customer Need | B18: =Weights!$B$6 -> 0.2 | C18: =Scorecard!C13-Scorecard!E13 -> 2.8755875 | D18: =((Scorecard!C18-Scorecard!E18)-B18*C18)/(1-B18) -> -0.79327424 | E18: =IFERROR(IF(AND(D18/(D18-C18)>=0,D18/(D18-C18)<=1),D18/(D18-C18),"none in 0–100%"),"none") -> 0.21621808 | F18: =IF(ISNUMBER(E18),IF(C18>0,"Distribution leads above this weight","Prof. services leads above this weight"),"") -> Distribution leads above this weight
A19: Product-Market Fit | B19: =Weights!$B$7 -> 0.2 | C19: =Scorecard!C14-Scorecard!E14 -> -1 | D19: =((Scorecard!C18-Scorecard!E18)-B19*C19)/(1-B19) -> 0.17562265 | E19: =IFERROR(IF(AND(D19/(D19-C19)>=0,D19/(D19-C19)<=1),D19/(D19-C19),"none in 0–100%"),"none") -> 0.14938692 | F19: =IF(ISNUMBER(E19),IF(C19>0,"Distribution leads above this weight","Prof. services leads above this weight"),"") -> Prof. services leads above this weight
A20: Revenue Potential | B20: =Weights!$B$8 -> 0.15 | C20: =Scorecard!C15-Scorecard!E15 -> 0.83588974 | D20: =((Scorecard!C18-Scorecard!E18)-B20*C20)/(1-B20) -> -0.21751217 | E20: =IFERROR(IF(AND(D20/(D20-C20)>=0,D20/(D20-C20)<=1),D20/(D20-C20),"none in 0–100%"),"none") -> 0.20648545 | F20: =IF(ISNUMBER(E20),IF(C20>0,"Distribution leads above this weight","Prof. services leads above this weight"),"") -> Distribution leads above this weight
A21: Competitive Position | B21: =Weights!$B$9 -> 0.15 | C21: =Scorecard!C16-Scorecard!E16 -> 1.6666667 | D21: =((Scorecard!C18-Scorecard!E18)-B21*C21)/(1-B21) -> -0.36411986 | E21: =IFERROR(IF(AND(D21/(D21-C21)>=0,D21/(D21-C21)<=1),D21/(D21-C21),"none in 0–100%"),"none") -> 0.17929992 | F21: =IF(ISNUMBER(E21),IF(C21>0,"Distribution leads above this weight","Prof. services leads above this weight"),"") -> Distribution leads above this weight
A22: Ease of Execution | B22: =Weights!$B$10 -> 0.1 | C22: =Scorecard!C17-Scorecard!E17 -> -2.5 | D22: =((Scorecard!C18-Scorecard!E18)-B22*C22)/(1-B22) -> 0.21166457 | E22: =IFERROR(IF(AND(D22/(D22-C22)>=0,D22/(D22-C22)<=1),D22/(D22-C22),"none in 0–100%"),"none") -> 0.078057064 | F22: =IF(ISNUMBER(E22),IF(C22>0,"Distribution leads above this weight","Prof. services leads above this weight"),"") -> Prof. services leads above this weight
A25: Block C — random-weight simulation
A26: Simulation | B26: Distribution | C26: Manufacturing | D26: Prof. services
A27: Flat Dirichlet — share of 1,000 draws won | B27: =COUNTIF(Random_Weights!$J$5:$J$1004,"Distribution")/1000 -> 0.429 | C27: =COUNTIF(Random_Weights!$J$5:$J$1004,"Manufacturing")/1000 -> 0 | D27: =COUNTIF(Random_Weights!$J$5:$J$1004,"Prof. services")/1000 -> 0.571
A28: Centered Dirichlet — share of 1,000 draws won | B28: =COUNTIF(Random_Weights!$U$5:$U$1004,"Distribution")/1000 -> 0.446 | C28: =COUNTIF(Random_Weights!$U$5:$U$1004,"Manufacturing")/1000 -> 0 | D28: =COUNTIF(Random_Weights!$U$5:$U$1004,"Prof. services")/1000 -> 0.554

Sheet Random_Weights
A1: Random weights — 1,000 flat and 1,000 centered Dirichlet draws (numpy, seed 42; stored values), totals are live formulas
A2: Flat: any weighting equally likely. Centered: Dirichlet(30 × base weights), reasonable disagreement around the brief.
A3: Flat Dirichlet(1, …, 1) | L3: Centered Dirichlet(30 × base weights)
A4: Market Attra | B4: Customer Nee | C4: Product-Mark | D4: Revenue Pote | E4: Competitive | F4: Ease of Exec | G4: Distribution | H4: Manufacturing | I4: Prof. services | J4: Winner | L4: Market Attra | M4: Customer Nee | N4: Product-Mark | O4: Revenue Pote | P4: Competitive | Q4: Ease of Exec | R4: Distribution | S4: Manufacturing | T4: Prof. services | U4: Winner
A5: 0.268805 | B5: 0.2612 | C5: 0.266631 | D5: 0.031283 | E5: 0.009664 | F5: 0.162416 | G5: =A5*Scorecard!$C$12+B5*Scorecard!$C$13+C5*Scorecard!$C$14+D5*Scorecard!$C$15+E5*Scorecard!$C$16+F5*Scorecard!$C$17 -> 3.4837942 | H5: =A5*Scorecard!$D$12+B5*Scorecard!$D$13+C5*Scorecard!$D$14+D5*Scorecard!$D$15+E5*Scorecard!$D$16+F5*Scorecard!$D$17 -> 2.581306 | I5: =A5*Scorecard!$E$12+B5*Scorecard!$E$13+C5*Scorecard!$E$14+D5*Scorecard!$E$15+E5*Scorecard!$E$16+F5*Scorecard!$E$17 -> 4.1157637 | J5: =IF(AND(G5>=H5,G5>=I5),"Distribution",IF(I5>=H5,"Prof. services","Manufacturing")) -> Prof. services | L5: 0.186652 | M5: 0.140559 | N5: 0.290406 | O5: 0.237903 | P5: 0.065232 | Q5: 0.079249 | R5: =L5*Scorecard!$C$12+M5*Scorecard!$C$13+N5*Scorecard!$C$14+O5*Scorecard!$C$15+P5*Scorecard!$C$16+Q5*Scorecard!$C$17 -> 3.8839917 | S5: =L5*Scorecard!$D$12+M5*Scorecard!$D$13+N5*Scorecard!$D$14+O5*Scorecard!$D$15+P5*Scorecard!$D$16+Q5*Scorecard!$D$17 -> 3.0905933 | T5: =L5*Scorecard!$E$12+M5*Scorecard!$E$13+N5*Scorecard!$E$14+O5*Scorecard!$E$15+P5*Scorecard!$E$16+Q5*Scorecard!$E$17 -> 4.1833781 | U5: =IF(AND(R5>=S5,R5>=T5),"Distribution",IF(T5>=S5,"Prof. services","Manufacturing")) -> Prof. services
A6: 0.206752 | B6: 0.458137 | C6: 0.011627 | D6: 0.153464 | E6: 0.010329 | F6: 0.159691 | G6: =A6*Scorecard!$C$12+B6*Scorecard!$C$13+C6*Scorecard!$C$14+D6*Scorecard!$C$15+E6*Scorecard!$C$16+F6*Scorecard!$C$17 -> 3.9200625 | H6: =A6*Scorecard!$D$12+B6*Scorecard!$D$13+C6*Scorecard!$D$14+D6*Scorecard!$D$15+E6*Scorecard!$D$16+F6*Scorecard!$D$17 -> 2.390468 | I6: =A6*Scorecard!$E$12+B6*Scorecard!$E$13+C6*Scorecard!$E$14+D6*Scorecard!$E$15+E6*Scorecard!$E$16+F6*Scorecard!$E$17 -> 3.4469185 | J6: =IF(AND(G6>=H6,G6>=I6),"Distribution",IF(I6>=H6,"Prof. services","Manufacturing")) -> Distribution | L6: 0.102209 | M6: 0.227109 | N6: 0.328271 | O6: 0.136088 | P6: 0.103459 | Q6: 0.102865 | R6: =L6*Scorecard!$C$12+M6*Scorecard!$C$13+N6*Scorecard!$C$14+O6*Scorecard!$C$15+P6*Scorecard!$C$16+Q6*Scorecard!$C$17 -> 3.9734933 | S6: =L6*Scorecard!$D$12+M6*Scorecard!$D$13+N6*Scorecard!$D$14+O6*Scorecard!$D$15+P6*Scorecard!$D$16+Q6*Scorecard!$D$17 -> 2.7643559 | T6: =L6*Scorecard!$E$12+M6*Scorecard!$E$13+N6*Scorecard!$E$14+O6*Scorecard!$E$15+P6*Scorecard!$E$16+Q6*Scorecard!$E$17 -> 3.9058555 | U6: =IF(AND(R6>=S6,R6>=T6),"Distribution",IF(T6>=S6,"Prof. services","Manufacturing")) -> Distribution
A7: 0.442756 | B7: 0.098942 | C7: 0.314956 | D7: 0.039325 | E7: 0.023419 | F7: 0.080602 | G7: =A7*Scorecard!$C$12+B7*Scorecard!$C$13+C7*Scorecard!$C$14+D7*Scorecard!$C$15+E7*Scorecard!$C$16+F7*Scorecard!$C$17 -> 3.1800959 | H7: =A7*Scorecard!$D$12+B7*Scorecard!$D$13+C7*Scorecard!$D$14+D7*Scorecard!$D$15+E7*Scorecard!$D$16+F7*Scorecard!$D$17 -> 3.0763775 | I7: =A7*Scorecard!$E$12+B7*Scorecard!$E$13+C7*Scorecard!$E$14+D7*Scorecard!$E$15+E7*Scorecard!$E$16+F7*Scorecard!$E$17 -> 4.5798606 | J7: =IF(AND(G7>=H7,G7>=I7),"Distribution",IF(I7>=H7,"Prof. services","Manufacturing")) -> Prof. services | L7: 0.26233 | M7: 0.263046 | N7: 0.154498 | O7: 0.097962 | P7: 0.151289 | Q7: 0.070875 | R7: =L7*Scorecard!$C$12+M7*Scorecard!$C$13+N7*Scorecard!$C$14+O7*Scorecard!$C$15+P7*Scorecard!$C$16+Q7*Scorecard!$C$17 -> 3.7470603 | S7: =L7*Scorecard!$D$12+M7*Scorecard!$D$13+N7*Scorecard!$D$14+O7*Scorecard!$D$15+P7*Scorecard!$D$16+Q7*Scorecard!$D$17 -> 2.8359713 | T7: =L7*Scorecard!$E$12+M7*Scorecard!$E$13+N7*Scorecard!$E$14+O7*Scorecard!$E$15+P7*Scorecard!$E$16+Q7*Scorecard!$E$17 -> 3.7228279 | U7: =IF(AND(R7>=S7,R7>=T7),"Distribution",IF(T7>=S7,"Prof. services","Manufacturing")) -> Distribution
A8: 0.154046 | B8: 0.070593 | C8: 0.213221 | D8: 0.038217 | E8: 0.314172 | F8: 0.209751 | G8: =A8*Scorecard!$C$12+B8*Scorecard!$C$13+C8*Scorecard!$C$14+D8*Scorecard!$C$15+E8*Scorecard!$C$16+F8*Scorecard!$C$17 -> 3.412023 | H8: =A8*Scorecard!$D$12+B8*Scorecard!$D$13+C8*Scorecard!$D$14+D8*Scorecard!$D$15+E8*Scorecard!$D$16+F8*Scorecard!$D$17 -> 2.8301338 | I8: =A8*Scorecard!$E$12+B8*Scorecard!$E$13+C8*Scorecard!$E$14+D8*Scorecard!$E$15+E8*Scorecard!$E$16+F8*Scorecard!$E$17 -> 3.822391 | J8: =IF(AND(G8>=H8,G8>=I8),"Distribution",IF(I8>=H8,"Prof. services","Manufacturing")) -> Prof. services | L8: 0.317416 | M8: 0.170633 | N8: 0.203849 | O8: 0.173618 | P8: 0.068366 | Q8: 0.066118 | R8: =L8*Scorecard!$C$12+M8*Scorecard!$C$13+N8*Scorecard!$C$14+O8*Scorecard!$C$15+P8*Scorecard!$C$16+Q8*Scorecard!$C$17 -> 3.6406617 | S8: =L8*Scorecard!$D$12+M8*Scorecard!$D$13+N8*Scorecard!$D$14+O8*Scorecard!$D$15+P8*Scorecard!$D$16+Q8*Scorecard!$D$17 -> 3.0781474 | T8: =L8*Scorecard!$E$12+M8*Scorecard!$E$13+N8*Scorecard!$E$14+O8*Scorecard!$E$15+P8*Scorecard!$E$16+Q8*Scorecard!$E$17 -> 4.148836 | U8: =IF(AND(R8>=S8,R8>=T8),"Distribution",IF(T8>=S8,"Prof. services","Manufacturing")) -> Prof. services
A9: 0.265695 | B9: 0.168982 | C9: 0.183662 | D9: 0.031228 | E9: 0.072778 | F9: 0.277656 | G9: =A9*Scorecard!$C$12+B9*Scorecard!$C$13+C9*Scorecard!$C$14+D9*Scorecard!$C$15+E9*Scorecard!$C$16+F9*Scorecard!$C$17 -> 3.1666472 | H9: =A9*Scorecard!$D$12+B9*Scorecard!$D$13+C9*Scorecard!$D$14+D9*Scorecard!$D$15+E9*Scorecard!$D$16+F9*Scorecard!$D$17 -> 2.5657914 | I9: =A9*Scorecard!$E$12+B9*Scorecard!$E$13+C9*Scorecard!$E$14+D9*Scorecard!$E$15+E9*Scorecard!$E$16+F9*Scorecard!$E$17 -> 4.1550766 | J9: =IF(AND(G9>=H9,G9>=I9),"Distribution",IF(I9>=H9,"Prof. services","Manufacturing")) -> Prof. services | L9: 0.290348 | M9: 0.201028 | N9: 0.122501 | O9: 0.14603 | P9: 0.180414 | Q9: 0.05968 | R9: =L9*Scorecard!$C$12+M9*Scorecard!$C$13+N9*Scorecard!$C$14+O9*Scorecard!$C$15+P9*Scorecard!$C$16+Q9*Scorecard!$C$17 -> 3.7050715 | S9: =L9*Scorecard!$D$12+M9*Scorecard!$D$13+N9*Scorecard!$D$14+O9*Scorecard!$D$15+P9*Scorecard!$D$16+Q9*Scorecard!$D$17 -> 3.029717 | T9: =L9*Scorecard!$E$12+M9*Scorecard!$E$13+N9*Scorecard!$E$14+O9*Scorecard!$E$15+P9*Scorecard!$E$16+Q9*Scorecard!$E$17 -> 3.7889224 | U9: =IF(AND(R9>=S9,R9>=T9),"Distribution",IF(T9>=S9,"Prof. services","Manufacturing")) -> Prof. services
A10: 0.104993 | B10: 0.341497 | C10: 0.191383 | D10: 0.064271 | E10: 0.124553 | F10: 0.173302 | G10: =A10*Scorecard!$C$12+B10*Scorecard!$C$13+C10*Scorecard!$C$14+D10*Scorecard!$C$15+E10*Scorecard!$C$16+F10*Scorecard!$C$17 -> 3.8701711 | H10: =A10*Scorecard!$D$12+B10*Scorecard!$D$13+C10*Scorecard!$D$14+D10*Scorecard!$D$15+E10*Scorecard!$D$16+F10*Scorecard!$D$17 -> 2.4127298 | I10: =A10*Scorecard!$E$12+B10*Scorecard!$E$13+C10*Scorecard!$E$14+D10*Scorecard!$E$15+E10*Scorecard!$E$16+F10*Scorecard!$E$17 -> 3.5454747 | J10: =IF(AND(G10>=H10,G10>=I10),"Distribution",IF(I10>=H10,"Prof. services","Manufacturing")) -> Distribution | L10: 0.206832 | M10: 0.195027 | N10: 0.089793 | O10: 0.099858 | P10: 0.220658 | Q10: 0.187832 | R10: =L10*Scorecard!$C$12+M10*Scorecard!$C$13+N10*Scorecard!$C$14+O10*Scorecard!$C$15+P10*Scorecard!$C$16+Q10*Scorecard!$C$17 -> 3.5469205 | S10: =L10*Scorecard!$D$12+M10*Scorecard!$D$13+N10*Scorecard!$D$14+O10*Scorecard!$D$15+P10*Scorecard!$D$16+Q10*Scorecard!$D$17 -> 2.7512912 | T10: =L10*Scorecard!$E$12+M10*Scorecard!$E$13+N10*Scorecard!$E$14+O10*Scorecard!$E$15+P10*Scorecard!$E$16+Q10*Scorecard!$E$17 -> 3.6733752 | U10: =IF(AND(R10>=S10,R10>=T10),"Distribution",IF(T10>=S10,"Prof. services","Manufacturing")) -> Prof. services
A11: 0.0753 | B11: 0.070499 | C11: 0.192484 | D11: 0.065032 | E11: 0.292083 | F11: 0.304602 | G11: =A11*Scorecard!$C$12+B11*Scorecard!$C$13+C11*Scorecard!$C$14+D11*Scorecard!$C$15+E11*Scorecard!$C$16+F11*Scorecard!$C$17 -> 3.3907859 | H11: =A11*Scorecard!$D$12+B11*Scorecard!$D$13+C11*Scorecard!$D$14+D11*Scorecard!$D$15+E11*Scorecard!$D$16+F11*Scorecard!$D$17 -> 2.6596619 | I11: =A11*Scorecard!$E$12+B11*Scorecard!$E$13+C11*Scorecard!$E$14+D11*Scorecard!$E$15+E11*Scorecard!$E$16+F11*Scorecard!$E$17 -> 3.8117254 | J11: =IF(AND(G11>=H11,G11>=I11),"Distribution",IF(I11>=H11,"Prof. services","Manufacturing")) -> Prof. services | L11: 0.30896 | M11: 0.169517 | N11: 0.076404 | O11: 0.111919 | P11: 0.08208 | Q11: 0.25112 | R11: =L11*Scorecard!$C$12+M11*Scorecard!$C$13+N11*Scorecard!$C$14+O11*Scorecard!$C$15+P11*Scorecard!$C$16+Q11*Scorecard!$C$17 -> 3.2230636 | S11: =L11*Scorecard!$D$12+M11*Scorecard!$D$13+N11*Scorecard!$D$14+O11*Scorecard!$D$15+P11*Scorecard!$D$16+Q11*Scorecard!$D$17 -> 2.7298799 | T11: =L11*Scorecard!$E$12+M11*Scorecard!$E$13+N11*Scorecard!$E$14+O11*Scorecard!$E$15+P11*Scorecard!$E$16+Q11*Scorecard!$E$17 -> 4.0745471 | U11: =IF(AND(R11>=S11,R11>=T11),"Distribution",IF(T11>=S11,"Prof. services","Manufacturing")) -> Prof. services
A12: 0.214772 | B12: 0.014468 | C12: 0.224674 | D12: 0.268313 | E12: 0.222291 | F12: 0.055482 | G12: =A12*Scorecard!$C$12+B12*Scorecard!$C$13+C12*Scorecard!$C$14+D12*Scorecard!$C$15+E12*Scorecard!$C$16+F12*Scorecard!$C$17 -> 3.7852243 | H12: =A12*Scorecard!$D$12+B12*Scorecard!$D$13+C12*Scorecard!$D$14+D12*Scorecard!$D$15+E12*Scorecard!$D$16+F12*Scorecard!$D$17 -> 3.4216351 | I12: =A12*Scorecard!$E$12+B12*Scorecard!$E$13+C12*Scorecard!$E$14+D12*Scorecard!$E$15+E12*Scorecard!$E$16+F12*Scorecard!$E$17 -> 4.1135989 | J12: =IF(AND(G12>=H12,G12>=I12),"Distribution",IF(I12>=H12,"Prof. services","Manufacturing")) -> Prof. services | L12: 0.087949 | M12: 0.12169 | N12: 0.218965 | O12: 0.148225 | P12: 0.288673 | Q12: 0.134499 | R12: =L12*Scorecard!$C$12+M12*Scorecard!$C$13+N12*Scorecard!$C$14+O12*Scorecard!$C$15+P12*Scorecard!$C$16+Q12*Scorecard!$C$17 -> 3.8426115 | S12: =L12*Scorecard!$D$12+M12*Scorecard!$D$13+N12*Scorecard!$D$14+O12*Scorecard!$D$15+P12*Scorecard!$D$16+Q12*Scorecard!$D$17 -> 2.9415079 | T12: =L12*Scorecard!$E$12+M12*Scorecard!$E$13+N12*Scorecard!$E$14+O12*Scorecard!$E$15+P12*Scorecard!$E$16+Q12*Scorecard!$E$17 -> 3.6891308 | U12: =IF(AND(R12>=S12,R12>=T12),"Distribution",IF(T12>=S12,"Prof. services","Manufacturing")) -> Distribution
A13: 0.136884 | B13: 0.070689 | C13: 0.151141 | D13: 0.009016 | E13: 0.07138 | F13: 0.56089 | G13: =A13*Scorecard!$C$12+B13*Scorecard!$C$13+C13*Scorecard!$C$14+D13*Scorecard!$C$15+E13*Scorecard!$C$16+F13*Scorecard!$C$17 -> 2.7115318 | H13: =A13*Scorecard!$D$12+B13*Scorecard!$D$13+C13*Scorecard!$D$14+D13*Scorecard!$D$15+E13*Scorecard!$D$16+F13*Scorecard!$D$17 -> 2.1772099 | I13: =A13*Scorecard!$E$12+B13*Scorecard!$E$13+C13*Scorecard!$E$14+D13*Scorecard!$E$15+E13*Scorecard!$E$16+F13*Scorecard!$E$17 -> 4.3183995 | J13: =IF(AND(G13>=H13,G13>=I13),"Distribution",IF(I13>=H13,"Prof. services","Manufacturing")) -> Prof. services | L13: 0.173818 | M13: 0.298028 | N13: 0.156266 | O13: 0.275322 | P13: 0.087954 | Q13: 0.008612 | R13: =L13*Scorecard!$C$12+M13*Scorecard!$C$13+N13*Scorecard!$C$14+O13*Scorecard!$C$15+P13*Scorecard!$C$16+Q13*Scorecard!$C$17 -> 4.2432511 | S13: =L13*Scorecard!$D$12+M13*Scorecard!$D$13+N13*Scorecard!$D$14+O13*Scorecard!$D$15+P13*Scorecard!$D$16+Q13*Scorecard!$D$17 -> 3.0025988 | T13: =L13*Scorecard!$E$12+M13*Scorecard!$E$13+N13*Scorecard!$E$14+O13*Scorecard!$E$15+P13*Scorecard!$E$16+Q13*Scorecard!$E$17 -> 3.6740056 | U13: =IF(AND(R13>=S13,R13>=T13),"Distribution",IF(T13>=S13,"Prof. services","Manufacturing")) -> Distribution
A14: 0.697088 | B14: 0.098313 | C14: 0.049553 | D14: 0.069391 | E14: 0.063039 | F14: 0.022616 | G14: =A14*Scorecard!$C$12+B14*Scorecard!$C$13+C14*Scorecard!$C$14+D14*Scorecard!$C$15+E14*Scorecard!$C$16+F14*Scorecard!$C$17 -> 2.8677037 | H14: =A14*Scorecard!$D$12+B14*Scorecard!$D$13+C14*Scorecard!$D$14+D14*Scorecard!$D$15+E14*Scorecard!$D$16+F14*Scorecard!$D$17 -> 3.3803117 | I14: =A14*Scorecard!$E$12+B14*Scorecard!$E$13+C14*Scorecard!$E$14+D14*Scorecard!$E$15+E14*Scorecard!$E$16+F14*Scorecard!$E$17 -> 4.4798771 | J14: =IF(AND(G14>=H14,G14>=I14),"Distribution",IF(I14>=H14,"Prof. services","Manufacturing")) -> Prof. services | L14: 0.178951 | M14: 0.068043 | N14: 0.262058 | O14: 0.144688 | P14: 0.271737 | Q14: 0.074522 | R14: =L14*Scorecard!$C$12+M14*Scorecard!$C$13+N14*Scorecard!$C$14+O14*Scorecard!$C$15+P14*Scorecard!$C$16+Q14*Scorecard!$C$17 -> 3.7415686 | S14: =L14*Scorecard!$D$12+M14*Scorecard!$D$13+N14*Scorecard!$D$14+O14*Scorecard!$D$15+P14*Scorecard!$D$16+Q14*Scorecard!$D$17 -> 3.162363 | T14: =L14*Scorecard!$E$12+M14*Scorecard!$E$13+N14*Scorecard!$E$14+O14*Scorecard!$E$15+P14*Scorecard!$E$16+Q14*Scorecard!$E$17 -> 3.9214952 | U14: =IF(AND(R14>=S14,R14>=T14),"Distribution",IF(T14>=S14,"Prof. services","Manufacturing")) -> Prof. services
A15: 0.083151 | B15: 0.105604 | C15: 0.115733 | D15: 0.407562 | E15: 0.161698 | F15: 0.126252 | G15: =A15*Scorecard!$C$12+B15*Scorecard!$C$13+C15*Scorecard!$C$14+D15*Scorecard!$C$15+E15*Scorecard!$C$16+F15*Scorecard!$C$17 -> 4.110989 | H15: =A15*Scorecard!$D$12+B15*Scorecard!$D$13+C15*Scorecard!$D$14+D15*Scorecard!$D$15+E15*Scorecard!$D$16+F15*Scorecard!$D$17 -> 3.2327454 | I15: =A15*Scorecard!$E$12+B15*Scorecard!$E$13+C15*Scorecard!$E$14+D15*Scorecard!$E$15+E15*Scorecard!$E$16+F15*Scorecard!$E$17 -> 3.8613289 | J15: =IF(AND(G15>=H15,G15>=I15),"Distribution",IF(I15>=H15,"Prof. services","Manufacturing")) -> Distribution | L15: 0.103279 | M15: 0.23734 | N15: 0.156959 | O15: 0.207592 | P15: 0.095117 | Q15: 0.199714 | R15: =L15*Scorecard!$C$12+M15*Scorecard!$C$13+N15*Scorecard!$C$14+O15*Scorecard!$C$15+P15*Scorecard!$C$16+Q15*Scorecard!$C$17 -> 3.8596043 | S15: =L15*Scorecard!$D$12+M15*Scorecard!$D$13+N15*Scorecard!$D$14+O15*Scorecard!$D$15+P15*Scorecard!$D$16+Q15*Scorecard!$D$17 -> 2.6844277 | T15: =L15*Scorecard!$E$12+M15*Scorecard!$E$13+N15*Scorecard!$E$14+O15*Scorecard!$E$15+P15*Scorecard!$E$16+Q15*Scorecard!$E$17 -> 3.7904867 | U15: =IF(AND(R15>=S15,R15>=T15),"Distribution",IF(T15>=S15,"Prof. services","Manufacturing")) -> Distribution
A16: 0.218926 | B16: 0.124312 | C16: 0.009326 | D16: 0.200696 | E16: 0.130367 | F16: 0.316372 | G16: =A16*Scorecard!$C$12+B16*Scorecard!$C$13+C16*Scorecard!$C$14+D16*Scorecard!$C$15+E16*Scorecard!$C$16+F16*Scorecard!$C$17 -> 3.2981901 | H16: =A16*Scorecard!$D$12+B16*Scorecard!$D$13+C16*Scorecard!$D$14+D16*Scorecard!$D$15+E16*Scorecard!$D$16+F16*Scorecard!$D$17 -> 2.7592474 | I16: =A16*Scorecard!$E$12+B16*Scorecard!$E$13+C16*Scorecard!$E$14+D16*Scorecard!$E$15+E16*Scorecard!$E$16+F16*Scorecard!$E$17 -> 3.9689339 | J16: =IF(AND(G16>=H16,G16>=I16),"Distribution",IF(I16>=H16,"Prof. services","Manufacturing")) -> Prof. services | L16: 0.169281 | M16: 0.155183 | N16: 0.273695 | O16: 0.186502 | P16: 0.084814 | Q16: 0.130525 | R16: =L16*Scorecard!$C$12+M16*Scorecard!$C$13+N16*Scorecard!$C$14+O16*Scorecard!$C$15+P16*Scorecard!$C$16+Q16*Scorecard!$C$17 -> 3.7759268 | S16: =L16*Scorecard!$D$12+M16*Scorecard!$D$13+N16*Scorecard!$D$14+O16*Scorecard!$D$15+P16*Scorecard!$D$16+Q16*Scorecard!$D$17 -> 2.9272746 | T16: =L16*Scorecard!$E$12+M16*Scorecard!$E$13+N16*Scorecard!$E$14+O16*Scorecard!$E$15+P16*Scorecard!$E$16+Q16*Scorecard!$E$17 -> 4.1064294 | U16: =IF(AND(R16>=S16,R16>=T16),"Distribution",IF(T16>=S16,"Prof. services","Manufacturing")) -> Prof. services
... A1004: 0.270233 | B1004: 0.300359 | C1004: 0.072364 | D1004: 0.099786 | E1004: 0.100903 | F1004: 0.156355 | G1004: =A1004*Scorecard!$C$12+B1004*Scorecard!$C$13+C1004*Scorecard!$C$14+D1004*Scorecard!$C$15+E1004*Scorecard!$C$16+F1004*Scorecard!$C$17 -> 3.6010117 | H1004: =A1004*Scorecard!$D$12+B1004*Scorecard!$D$13+C1004*Scorecard!$D$14+D1004*Scorecard!$D$15+E1004*Scorecard!$D$16+F1004*Scorecard!$D$17 -> 2.6422809 | I1004: =A1004*Scorecard!$E$12+B1004*Scorecard!$E$13+C1004*Scorecard!$E$14+D1004*Scorecard!$E$15+E1004*Scorecard!$E$16+F1004*Scorecard!$E$17 -> 3.7056291 | J1004: =IF(AND(G1004>=H1004,G1004>=I1004),"Distribution",IF(I1004>=H1004,"Prof. services","Manufacturing")) -> Prof. services | L1004: 0.231734 | M1004: 0.106886 | N1004: 0.151498 | O1004: 0.246101 | P1004: 0.22023 | Q1004: 0.043551 | R1004: =L1004*Scorecard!$C$12+M1004*Scorecard!$C$13+N1004*Scorecard!$C$14+O1004*Scorecard!$C$15+P1004*Scorecard!$C$16+Q1004*Scorecard!$C$17 -> 3.8487605 | S1004: =L1004*Scorecard!$D$12+M1004*Scorecard!$D$13+N1004*Scorecard!$D$14+O1004*Scorecard!$D$15+P1004*Scorecard!$D$16+Q1004*Scorecard!$D$17 -> 3.2856157 | T1004: =L1004*Scorecard!$E$12+M1004*Scorecard!$E$13+N1004*Scorecard!$E$14+O1004*Scorecard!$E$15+P1004*Scorecard!$E$16+Q1004*Scorecard!$E$17 -> 3.8778711 | U1004: =IF(AND(R1004>=S1004,R1004>=T1004),"Distribution",IF(T1004>=S1004,"Prof. services","Manufacturing")) -> Prof. services

Sheet Stress_Tests
A1: Stress tests — what has to be true for each segment to win
A2: Each block changes only the yellow inputs. Summary first; detail blocks below.
A4: Test | B4: What changes | C4: Distribution | D4: Manufacturing | E4: Prof. services | F4: Winner | G4: Dist − PS
A5: T0 Base case | B5: Nothing (reproduces Scorecard) | C5: =C36 -> 3.7899971 | D5: =D36 -> 2.9055556 | E5: =E36 -> 3.849499 | F5: =C37 -> Prof. services | G5: =C5-E5 -> -0.059501883
A6: T1 Partner channel works | B6: Distribution ease 2.0 → 3.5 (templates and partners close the builder gap) | C6: =C53 -> 3.9399971 | D6: =D53 -> 2.9055556 | E6: =E53 -> 3.849499 | F6: =C54 -> Distribution | G6: =C6-E6 -> 0.090498117
A7: T2 More PS headroom | B7: Prof. services already-Clay share 10% → 5% | C7: =C70 -> 3.7773657 | D7: =D70 -> 2.8775498 | E7: =E70 -> 3.849499 | F7: =C71 -> Prof. services | G7: =C7-E7 -> -0.072133312
A8: T3 Less PS headroom | B8: Prof. services already-Clay share 10% → 25% | C8: =C87 -> 3.8379966 | D8: =D87 -> 3.0119775 | E8: =E87 -> 3.849499 | F8: =C88 -> Prof. services | G8: =C8-E8 -> -0.011502453
A9: T4 Coverage proxy wrong | B9: Distribution F1 data differentiation 5 → 3 (competitive 4.0 → 3.33) | C9: =C104 -> 3.6899971 | D9: =D104 -> 2.9055556 | E9: =E104 -> 3.849499 | F9: =C105 -> Prof. services | G9: =C9-E9 -> -0.15950188
A10: T5 ERP gap binds | B10: Distribution product-market fit 4.0 → 3.0 | C10: =C121 -> 3.5899971 | D10: =D121 -> 2.9055556 | E10: =E121 -> 3.849499 | F10: =C122 -> Prof. services | G10: =C10-E10 -> -0.25950188
A11: T6 Apollo/HubSpot close the local-data gap | B11: Distribution competitive position 4.0 → 3.0 | C11: =C138 -> 3.6399971 | D11: =D138 -> 2.9055556 | E11: =E138 -> 3.849499 | F11: =C139 -> Prof. services | G11: =C11-E11 -> -0.20950188
A12: T7 Distribution combined downside | B12: T5 + T6 | C12: =C155 -> 3.4399971 | D12: =D155 -> 2.9055556 | E12: =E155 -> 3.849499 | F12: =C156 -> Prof. services | G12: =C12-E12 -> -0.40950188
A13: T8 Prof. services best case | B13: PS competitive 2.33 → 3.0; ease 4.5 → 5.0 | C13: =C172 -> 3.7899971 | D13: =D172 -> 2.9055556 | E13: =E172 -> 3.999499 | F13: =C173 -> Prof. services | G13: =C13-E13 -> -0.20950188
A14: T9 Worst case for A + best case for C | B14: T7 + T8 | C14: =C189 -> 3.4399971 | D14: =D189 -> 2.9055556 | E14: =E189 -> 3.999499 | F14: =C190 -> Prof. services | G14: =C14-E14 -> -0.55950188
A15: T10 Upside usage | B15: ACV at 1.5× usage for every segment | C15: =C206 -> 3.7899971 | D15: =D206 -> 2.7959107 | E15: =E206 -> 3.7396295 | F15: =C207 -> Distribution | G15: =C15-E15 -> 0.050367655
A16: T11 Concave size scoring | B16: Market attractiveness scored 1 + 4 × √(v ÷ max): a pilot can serve only a few hundred accounts | C16: =C223 -> 3.9881754 | D16: =D223 -> 3.0258934 | E16: =E223 -> 3.849499 | F16: =C224 -> Distribution | G16: =C16-E16 -> 0.13867641
A17: T12 Min-max scaling | B17: All quantitative indicators scaled min-max instead of ratio-to-max | C17: =C240 -> 3.55 | D17: =D240 -> 2.2173017 | E17: =E240 -> 3.2975188 | F17: =C241 -> Distribution | G17: =C17-E17 -> 0.25248121
A18: T13 v1 market definition | B18: Reachable accounts × v1 outbound-motion filter (80% / 45% / 55%) | C18: =C257 -> 3.8990868 | D18: =D257 -> 2.8088083 | E18: =E257 -> 3.849499 | F18: =C258 -> Distribution | G18: =C18-E18 -> 0.04958773
A19: Tests won by distribution / professional services | C19: =COUNTIF(F5:F18,"Distribution") -> 5 | E19: =COUNTIF(F5:F18,"Prof. services") -> 9
A22: T0 Base case | F22: Nothing (reproduces Scorecard)
A23: Criterion | B23: Line | C23: Distribution | D23: Manufacturing | E23: Prof. services | F23: Scoring
A24: Market Attractiveness | B24: metric | C24: =Inputs!D8 -> 6243.5408 | D24: =Inputs!E8 -> 13842.87 | E24: =Inputs!F8 -> 20812.05
A25: Customer Need | B25: metric | C25: =Inputs!D10 -> 2.5431972 | D25: =Inputs!E10 -> 0.31726258 | E25: =Inputs!F10 -> 0.71490066
A26: Product-Market Fit | B26: metric | C26: =Inputs!D12 -> 4 | D26: =Inputs!E12 -> 3 | E26: =Inputs!F12 -> 5
A27: Revenue Potential | B27: metric | C27: =Inputs!D13 -> 8939.6836 | D27: =Inputs!E13 -> 7057.0783 | E27: =Inputs!F13 -> 7071.5361
A28: Competitive Position | B28: metric | C28: =Inputs!D15 -> 4 | D28: =Inputs!E15 -> 3.3333333 | E28: =Inputs!F15 -> 2.3333333
A29: Ease of Execution | B29: metric | C29: =Inputs!D16 -> 2 | D29: =Inputs!E16 -> 1.5 | E29: =Inputs!F16 -> 4.5
A30: Market Attractiveness | B30: score 1–5 | C30: =1+4*C24/MAX($C$24:$E$24) -> 2.1999857 | D30: =1+4*D24/MAX($C$24:$E$24) -> 3.6605491 | E30: =1+4*E24/MAX($C$24:$E$24) -> 5 | F30: 1 + 4 × v ÷ max
A31: Customer Need | B31: score 1–5 | C31: =1+4*C25/MAX($C$25:$E$25) -> 5 | D31: =1+4*D25/MAX($C$25:$E$25) -> 1.498998 | E31: =1+4*E25/MAX($C$25:$E$25) -> 2.1244125 | F31: 1 + 4 × v ÷ max
A32: Product-Market Fit | B32: score 1–5 | C32: =C26 -> 4 | D32: =D26 -> 3 | E32: =E26 -> 5 | F32: already 1–5
A33: Revenue Potential | B33: score 1–5 | C33: =1+4*C27/MAX($C$27:$E$27) -> 5 | D33: =1+4*D27/MAX($C$27:$E$27) -> 4.1576412 | E33: =1+4*E27/MAX($C$27:$E$27) -> 4.1641103 | F33: 1 + 4 × v ÷ max
A34: Competitive Position | B34: score 1–5 | C34: =C28 -> 4 | D34: =D28 -> 3.3333333 | E34: =E28 -> 2.3333333 | F34: already 1–5
A35: Ease of Execution | B35: score 1–5 | C35: =C29 -> 2 | D35: =D29 -> 1.5 | E35: =E29 -> 4.5 | F35: already 1–5
A36: Weighted total | B36: Σ weight × score | C36: =SUMPRODUCT(Weights!$B$5:$B$10,C30:C35) -> 3.7899971 | D36: =SUMPRODUCT(Weights!$B$5:$B$10,D30:D35) -> 2.9055556 | E36: =SUMPRODUCT(Weights!$B$5:$B$10,E30:E35) -> 3.849499
A37: Winner / margin of distribution over professional services | C37: =INDEX({"Distribution","Manufacturing","Prof. services"},MATCH(MAX(C36:E36),C36:E36,0)) -> Prof. services | E37: =C36-E36 -> -0.059501883
A39: T1 Partner channel works | F39: Distribution ease 2.0 → 3.5 (templates and partners close the builder gap)
A40: Criterion | B40: Line | C40: Distribution | D40: Manufacturing | E40: Prof. services | F40: Scoring
A41: Market Attractiveness | B41: metric | C41: =Inputs!D8 -> 6243.5408 | D41: =Inputs!E8 -> 13842.87 | E41: =Inputs!F8 -> 20812.05
A42: Customer Need | B42: metric | C42: =Inputs!D10 -> 2.5431972 | D42: =Inputs!E10 -> 0.31726258 | E42: =Inputs!F10 -> 0.71490066
A43: Product-Market Fit | B43: metric | C43: =Inputs!D12 -> 4 | D43: =Inputs!E12 -> 3 | E43: =Inputs!F12 -> 5
A44: Revenue Potential | B44: metric | C44: =Inputs!D13 -> 8939.6836 | D44: =Inputs!E13 -> 7057.0783 | E44: =Inputs!F13 -> 7071.5361
A45: Competitive Position | B45: metric | C45: =Inputs!D15 -> 4 | D45: =Inputs!E15 -> 3.3333333 | E45: =Inputs!F15 -> 2.3333333
A46: Ease of Execution | B46: metric | C46: =3.5 -> 3.5 | D46: =Inputs!E16 -> 1.5 | E46: =Inputs!F16 -> 4.5
A47: Market Attractiveness | B47: score 1–5 | C47: =1+4*C41/MAX($C$41:$E$41) -> 2.1999857 | D47: =1+4*D41/MAX($C$41:$E$41) -> 3.6605491 | E47: =1+4*E41/MAX($C$41:$E$41) -> 5 | F47: 1 + 4 × v ÷ max
A48: Customer Need | B48: score 1–5 | C48: =1+4*C42/MAX($C$42:$E$42) -> 5 | D48: =1+4*D42/MAX($C$42:$E$42) -> 1.498998 | E48: =1+4*E42/MAX($C$42:$E$42) -> 2.1244125 | F48: 1 + 4 × v ÷ max
A49: Product-Market Fit | B49: score 1–5 | C49: =C43 -> 4 | D49: =D43 -> 3 | E49: =E43 -> 5 | F49: already 1–5
A50: Revenue Potential | B50: score 1–5 | C50: =1+4*C44/MAX($C$44:$E$44) -> 5 | D50: =1+4*D44/MAX($C$44:$E$44) -> 4.1576412 | E50: =1+4*E44/MAX($C$44:$E$44) -> 4.1641103 | F50: 1 + 4 × v ÷ max
A51: Competitive Position | B51: score 1–5 | C51: =C45 -> 4 | D51: =D45 -> 3.3333333 | E51: =E45 -> 2.3333333 | F51: already 1–5
A52: Ease of Execution | B52: score 1–5 | C52: =C46 -> 3.5 | D52: =D46 -> 1.5 | E52: =E46 -> 4.5 | F52: already 1–5
A53: Weighted total | B53: Σ weight × score | C53: =SUMPRODUCT(Weights!$B$5:$B$10,C47:C52) -> 3.9399971 | D53: =SUMPRODUCT(Weights!$B$5:$B$10,D47:D52) -> 2.9055556 | E53: =SUMPRODUCT(Weights!$B$5:$B$10,E47:E52) -> 3.849499
A54: Winner / margin of distribution over professional services | C54: =INDEX({"Distribution","Manufacturing","Prof. services"},MATCH(MAX(C53:E53),C53:E53,0)) -> Distribution | E54: =C53-E53 -> 0.090498117
A56: T2 More PS headroom | F56: Prof. services already-Clay share 10% → 5%
A57: Criterion | B57: Line | C57: Distribution | D57: Manufacturing | E57: Prof. services | F57: Scoring
A58: Market Attractiveness | B58: metric | C58: =Inputs!D8 -> 6243.5408 | D58: =Inputs!E8 -> 13842.87 | E58: =Inputs!F5*Inputs!F6*(1-0.05) -> 21968.275
A59: Customer Need | B59: metric | C59: =Inputs!D10 -> 2.5431972 | D59: =Inputs!E10 -> 0.31726258 | E59: =Inputs!F10 -> 0.71490066
A60: Product-Market Fit | B60: metric | C60: =Inputs!D12 -> 4 | D60: =Inputs!E12 -> 3 | E60: =Inputs!F12 -> 5
A61: Revenue Potential | B61: metric | C61: =Inputs!D13 -> 8939.6836 | D61: =Inputs!E13 -> 7057.0783 | E61: =Inputs!F13 -> 7071.5361
A62: Competitive Position | B62: metric | C62: =Inputs!D15 -> 4 | D62: =Inputs!E15 -> 3.3333333 | E62: =Inputs!F15 -> 2.3333333
A63: Ease of Execution | B63: metric | C63: =Inputs!D16 -> 2 | D63: =Inputs!E16 -> 1.5 | E63: =Inputs!F16 -> 4.5
A64: Market Attractiveness | B64: score 1–5 | C64: =1+4*C58/MAX($C$58:$E$58) -> 2.1368286 | D64: =1+4*D58/MAX($C$58:$E$58) -> 3.5205202 | E64: =1+4*E58/MAX($C$58:$E$58) -> 5 | F64: 1 + 4 × v ÷ max
A65: Customer Need | B65: score 1–5 | C65: =1+4*C59/MAX($C$59:$E$59) -> 5 | D65: =1+4*D59/MAX($C$59:$E$59) -> 1.498998 | E65: =1+4*E59/MAX($C$59:$E$59) -> 2.1244125 | F65: 1 + 4 × v ÷ max
A66: Product-Market Fit | B66: score 1–5 | C66: =C60 -> 4 | D66: =D60 -> 3 | E66: =E60 -> 5 | F66: already 1–5
A67: Revenue Potential | B67: score 1–5 | C67: =1+4*C61/MAX($C$61:$E$61) -> 5 | D67: =1+4*D61/MAX($C$61:$E$61) -> 4.1576412 | E67: =1+4*E61/MAX($C$61:$E$61) -> 4.1641103 | F67: 1 + 4 × v ÷ max
A68: Competitive Position | B68: score 1–5 | C68: =C62 -> 4 | D68: =D62 -> 3.3333333 | E68: =E62 -> 2.3333333 | F68: already 1–5
A69: Ease of Execution | B69: score 1–5 | C69: =C63 -> 2 | D69: =D63 -> 1.5 | E69: =E63 -> 4.5 | F69: already 1–5
A70: Weighted total | B70: Σ weight × score | C70: =SUMPRODUCT(Weights!$B$5:$B$10,C64:C69) -> 3.7773657 | D70: =SUMPRODUCT(Weights!$B$5:$B$10,D64:D69) -> 2.8775498 | E70: =SUMPRODUCT(Weights!$B$5:$B$10,E64:E69) -> 3.849499
A71: Winner / margin of distribution over professional services | C71: =INDEX({"Distribution","Manufacturing","Prof. services"},MATCH(MAX(C70:E70),C70:E70,0)) -> Prof. services | E71: =C70-E70 -> -0.072133312
A73: T3 Less PS headroom | F73: Prof. services already-Clay share 10% → 25%
A74: Criterion | B74: Line | C74: Distribution | D74: Manufacturing | E74: Prof. services | F74: Scoring
A75: Market Attractiveness | B75: metric | C75: =Inputs!D8 -> 6243.5408 | D75: =Inputs!E8 -> 13842.87 | E75: =Inputs!F5*Inputs!F6*(1-0.25) -> 17343.375
A76: Customer Need | B76: metric | C76: =Inputs!D10 -> 2.5431972 | D76: =Inputs!E10 -> 0.31726258 | E76: =Inputs!F10 -> 0.71490066
A77: Product-Market Fit | B77: metric | C77: =Inputs!D12 -> 4 | D77: =Inputs!E12 -> 3 | E77: =Inputs!F12 -> 5
A78: Revenue Potential | B78: metric | C78: =Inputs!D13 -> 8939.6836 | D78: =Inputs!E13 -> 7057.0783 | E78: =Inputs!F13 -> 7071.5361
A79: Competitive Position | B79: metric | C79: =Inputs!D15 -> 4 | D79: =Inputs!E15 -> 3.3333333 | E79: =Inputs!F15 -> 2.3333333
A80: Ease of Execution | B80: metric | C80: =Inputs!D16 -> 2 | D80: =Inputs!E16 -> 1.5 | E80: =Inputs!F16 -> 4.5
A81: Market Attractiveness | B81: score 1–5 | C81: =1+4*C75/MAX($C$75:$E$75) -> 2.4399829 | D81: =1+4*D75/MAX($C$75:$E$75) -> 4.1926589 | E81: =1+4*E75/MAX($C$75:$E$75) -> 5 | F81: 1 + 4 × v ÷ max
A82: Customer Need | B82: score 1–5 | C82: =1+4*C76/MAX($C$76:$E$76) -> 5 | D82: =1+4*D76/MAX($C$76:$E$76) -> 1.498998 | E82: =1+4*E76/MAX($C$76:$E$76) -> 2.1244125 | F82: 1 + 4 × v ÷ max
A83: Product-Market Fit | B83: score 1–5 | C83: =C77 -> 4 | D83: =D77 -> 3 | E83: =E77 -> 5 | F83: already 1–5
A84: Revenue Potential | B84: score 1–5 | C84: =1+4*C78/MAX($C$78:$E$78) -> 5 | D84: =1+4*D78/MAX($C$78:$E$78) -> 4.1576412 | E84: =1+4*E78/MAX($C$78:$E$78) -> 4.1641103 | F84: 1 + 4 × v ÷ max
A85: Competitive Position | B85: score 1–5 | C85: =C79 -> 4 | D85: =D79 -> 3.3333333 | E85: =E79 -> 2.3333333 | F85: already 1–5
A86: Ease of Execution | B86: score 1–5 | C86: =C80 -> 2 | D86: =D80 -> 1.5 | E86: =E80 -> 4.5 | F86: already 1–5
A87: Weighted total | B87: Σ weight × score | C87: =SUMPRODUCT(Weights!$B$5:$B$10,C81:C86) -> 3.8379966 | D87: =SUMPRODUCT(Weights!$B$5:$B$10,D81:D86) -> 3.0119775 | E87: =SUMPRODUCT(Weights!$B$5:$B$10,E81:E86) -> 3.849499
A88: Winner / margin of distribution over professional services | C88: =INDEX({"Distribution","Manufacturing","Prof. services"},MATCH(MAX(C87:E87),C87:E87,0)) -> Prof. services | E88: =C87-E87 -> -0.011502453
A90: T4 Coverage proxy wrong | F90: Distribution F1 data differentiation 5 → 3 (competitive 4.0 → 3.33)
A91: Criterion | B91: Line | C91: Distribution | D91: Manufacturing | E91: Prof. services | F91: Scoring
A92: Market Attractiveness | B92: metric | C92: =Inputs!D8 -> 6243.5408 | D92: =Inputs!E8 -> 13842.87 | E92: =Inputs!F8 -> 20812.05
A93: Customer Need | B93: metric | C93: =Inputs!D10 -> 2.5431972 | D93: =Inputs!E10 -> 0.31726258 | E93: =Inputs!F10 -> 0.71490066
A94: Product-Market Fit | B94: metric | C94: =Inputs!D12 -> 4 | D94: =Inputs!E12 -> 3 | E94: =Inputs!F12 -> 5
A95: Revenue Potential | B95: metric | C95: =Inputs!D13 -> 8939.6836 | D95: =Inputs!E13 -> 7057.0783 | E95: =Inputs!F13 -> 7071.5361
A96: Competitive Position | B96: metric | C96: =10/3 -> 3.3333333 | D96: =Inputs!E15 -> 3.3333333 | E96: =Inputs!F15 -> 2.3333333
A97: Ease of Execution | B97: metric | C97: =Inputs!D16 -> 2 | D97: =Inputs!E16 -> 1.5 | E97: =Inputs!F16 -> 4.5
A98: Market Attractiveness | B98: score 1–5 | C98: =1+4*C92/MAX($C$92:$E$92) -> 2.1999857 | D98: =1+4*D92/MAX($C$92:$E$92) -> 3.6605491 | E98: =1+4*E92/MAX($C$92:$E$92) -> 5 | F98: 1 + 4 × v ÷ max
A99: Customer Need | B99: score 1–5 | C99: =1+4*C93/MAX($C$93:$E$93) -> 5 | D99: =1+4*D93/MAX($C$93:$E$93) -> 1.498998 | E99: =1+4*E93/MAX($C$93:$E$93) -> 2.1244125 | F99: 1 + 4 × v ÷ max
A100: Product-Market Fit | B100: score 1–5 | C100: =C94 -> 4 | D100: =D94 -> 3 | E100: =E94 -> 5 | F100: already 1–5
A101: Revenue Potential | B101: score 1–5 | C101: =1+4*C95/MAX($C$95:$E$95) -> 5 | D101: =1+4*D95/MAX($C$95:$E$95) -> 4.1576412 | E101: =1+4*E95/MAX($C$95:$E$95) -> 4.1641103 | F101: 1 + 4 × v ÷ max
A102: Competitive Position | B102: score 1–5 | C102: =C96 -> 3.3333333 | D102: =D96 -> 3.3333333 | E102: =E96 -> 2.3333333 | F102: already 1–5
A103: Ease of Execution | B103: score 1–5 | C103: =C97 -> 2 | D103: =D97 -> 1.5 | E103: =E97 -> 4.5 | F103: already 1–5
A104: Weighted total | B104: Σ weight × score | C104: =SUMPRODUCT(Weights!$B$5:$B$10,C98:C103) -> 3.6899971 | D104: =SUMPRODUCT(Weights!$B$5:$B$10,D98:D103) -> 2.9055556 | E104: =SUMPRODUCT(Weights!$B$5:$B$10,E98:E103) -> 3.849499
A105: Winner / margin of distribution over professional services | C105: =INDEX({"Distribution","Manufacturing","Prof. services"},MATCH(MAX(C104:E104),C104:E104,0)) -> Prof. services | E105: =C104-E104 -> -0.15950188
A107: T5 ERP gap binds | F107: Distribution product-market fit 4.0 → 3.0
A108: Criterion | B108: Line | C108: Distribution | D108: Manufacturing | E108: Prof. services | F108: Scoring
...

Sheet Economic_Crosscheck
A1: Economic cross-check — the same two segments on the 07 v2 engine
A2: Values copied from 07_Financial_Model.xlsx (v2, Scenarios and Monte Carlo sheets) at build time; they are not part of the weighted score, to avoid double counting revenue potential.
A4: Metric (07 v2) | B4: Distribution | C4: Prof. services | D4: Better | E4: Source
A5: Lean pilot — Base NPV at 12% | B5: -1892877 | C5: -2044077 | D5: =IF(B5>C5,"Distribution","Prof. services") -> Distribution | E5: 07 › Scenarios
A6: Lean pilot — Upside NPV at 12% | B6: 1527389 | C6: -249190 | D6: =IF(B6>C6,"Distribution","Prof. services") -> Distribution | E6: 07 › Scenarios
A7: Solution play — Base NPV | B7: -544642 | C7: -620644 | D7: =IF(B7>C7,"Distribution","Prof. services") -> Distribution | E7: 07 › Scenarios
A8: Solution play — Upside NPV advantage over Option 0 | B8: 358264 | C8: -441386 | D8: =IF(B8>C8,"Distribution","Prof. services") -> Distribution | E8: 07 › Scenarios
A9: Lean pilot, staged — simulated mean NPV | B9: -1486097 | C9: -1663742 | D9: =IF(B9>C9,"Distribution","Prof. services") -> Distribution | E9: 07 › Monte Carlo
A10: Lean pilot — Base average first-year ACV | B10: 8848 | C10: 6864 | D10: =IF(B10>C10,"Distribution","Prof. services") -> Distribution | E10: 07 › Scenarios
A11: Metrics on which distribution is better | B11: =COUNTIF(D5:D10,"Distribution")&" of 6" -> 6 of 6
A13: Reading: on the full economics distribution is modestly better than professional services in every comparison — mainly because more of a professional-services program's wins would have come through Clay's horizontal motion anyway, and its list-price ACV sits at the Growth floor. Both are NPV-negative in Base.

Sheet Subsegment_Drilldown
A1: Sub-segment drilldown — which distribution industry first? (v2 indicators)
A2: Only the criteria that differ by sub-industry are scored (market, need, revenue; base weights renormalized). Product fit, competitive position and ease are assumed equal across the three. Reference customers are a tie-breaker, not a score.
A4: Indicator | B4: 4236 Electrical | C4: 4237 Plumbing / HVAC | D4: 4238 Machinery / MRO | E4: Weight | G4: Source
A5: Firms 20+ (de-duplicated, 20–49 × 0.973) | B5: =Inputs!D62*0.973+SUM(Inputs!E62:H62) -> 2539.984 | C5: =Inputs!D63*0.973+SUM(Inputs!E63:H63) -> 1793.649 | D5: =Inputs!D64*0.973+SUM(Inputs!E64:H64) -> 5911.206 | G5: Census 2022 (S14)
A6: Reachable accounts = firms × CRM in use × (1 − already Clay) | B6: =B5*Inputs!$D$6*(1-Inputs!$D$7) -> 1379.7193 | C6: =C5*Inputs!$D$6*(1-Inputs!$D$7) -> 974.31014 | D6: =D5*Inputs!$D$6*(1-Inputs!$D$7) -> 3210.9671 | E6: =Weights!B5/(Weights!B5+Weights!B6+Weights!B8) -> 0.36363636
A7: Sales occupations share of employment | B7: 0.21429996 | C7: 0.21429996 | D7: 0.22986547 | E7: =Weights!B6/(Weights!B5+Weights!B6+Weights!B8) -> 0.36363636 | G7: OEWS May 2025 (S15): 4236/4237 share the 4230A1 group (durable goods ex-machinery, 21.4%); 4238 23.0%. Cannot separate 4236 from 4237.
A8: Usage-based ACV per won account (Base) | B8: =((Inputs!D62*0.973+Inputs!E62)*1*MAX((Inputs!$D$41+Inputs!$D$43)*12,((((((Inputs!J62+Inputs!K62)/(Inputs!D62+Inputs!E62)*B7)*Inputs!$D$45*Inputs!$D$59)*Inputs!$D$46)*Inputs!$D$47*Inputs!$D$48+(((Inputs!J62+Inputs!K62)/(Inputs!D62+Inputs!E62)*B7)*Inputs!$D$45*Inputs!$D$59)*Inputs!$D$49+(((Inputs!J62+Inputs!K62)/(Inputs!D62+Inputs!E62)*B7)*Inputs!$D$45*Inputs!$D$59)*Inputs!$D$50*Inputs!$D$51)*(Inputs!$D$41*12/Inputs!$D$42)+(((((Inputs!J62+Inputs!K62)/(Inputs!D62+Inputs!E62)*B7)*Inputs!$D$45*Inputs!$D$59)*Inputs!$D$46)*Inputs!$D$47+(((Inputs!J62+Inputs!K62)/(Inputs!D62+Inputs!E62)*B7)*Inputs!$D$45*Inputs!$D$59)+(((Inputs!J62+Inputs!K62)/(Inputs!D62+Inputs!E62)*B7)*Inputs!$D$45*Inputs!$D$59)*Inputs!$D$50)*Inputs!$D$52*(Inputs!$D$43*12/Inputs!$D$44)))+(Inputs!F62+Inputs!G62)*Inputs!$D$56*MAX((Inputs!$D$41+Inputs!$D$43)*12,((((((Inputs!L62+Inputs!M62)/(Inputs!F62+Inputs!G62)*B7)*Inputs!$D$45*Inputs!$D$59)*Inputs!$D$46)*Inputs!$D$47*Inputs!$D$48+(((Inputs!L62+Inputs!M62)/(Inputs!F62+Inputs!G62)*B7)*Inputs!$D$45*Inputs!$D$59)*Inputs!$D$49+(((Inputs!L62+Inputs!M62)/(Inputs!F62+Inputs!G62)*B7)*Inputs!$D$45*Inputs!$D$59)*Inputs!$D$50*Inputs!$D$51)*(Inputs!$D$41*12/Inputs!$D$42)+(((((Inputs!L62+Inputs!M62)/(Inputs!F62+Inputs!G62)*B7)*Inputs!$D$45*Inputs!$D$59)*Inputs!$D$46)*Inputs!$D$47+(((Inputs!L62+Inputs!M62)/(Inputs!F62+Inputs!G62)*B7)*Inputs!$D$45*Inputs!$D$59)+(((Inputs!L62+Inputs!M62)/(Inputs!F62+Inputs!G62)*B7)*Inputs!$D$45*Inputs!$D$59)*Inputs!$D$50)*Inputs!$D$52*(Inputs!$D$43*12/Inputs!$D$44)))+(Inputs!H62)*Inputs!$D$57*Inputs!$D$58*MAX(Inputs!$D$53*(Inputs!$D$41*12/Inputs!$D$42)+Inputs!$D$54*(Inputs!$D$43*12/Inputs!$D$44),((((((Inputs!N62)/(Inputs!H62)*B7)*Inputs!$D$45*Inputs!$D$59)*Inputs!$D$46)*Inputs!$D$47*Inputs!$D$48+(((Inputs!N62)/(Inputs!H62)*B7)*Inputs!$D$45*Inputs!$D$59)*Inputs!$D$49+(((Inputs!N62)/(Inputs!H62)*B7)*Inputs!$D$45*Inputs!$D$59)*Inputs!$D$50*Inputs!$D$51)*(Inputs!$D$41*12/Inputs!$D$42)+(((((Inputs!N62)/(Inputs!H62)*B7)*Inputs!$D$45*Inputs!$D$59)*Inputs!$D$46)*Inputs!$D$47+(((Inputs!N62)/(Inputs!H62)*B7)*Inputs!$D$45*Inputs!$D$59)+(((Inputs!N62)/(Inputs!H62)*B7)*Inputs!$D$45*Inputs!$D$59)*Inputs!$D$50)*Inputs!$D$52*(Inputs!$D$43*12/Inputs!$D$44)))*(1-Inputs!$D$55))/((Inputs!D62*0.973+Inputs!E62)*1+(Inputs!F62+Inputs!G62)*Inputs!$D$56+(Inputs!H62)*Inputs!$D$57*Inputs!$D$58) -> 11155.526 | C8: =((Inputs!D63*0.973+Inputs!E63)*1*MAX((Inputs!$D$41+Inputs!$D$43)*12,((((((Inputs!J63+Inputs!K63)/(Inputs!D63+Inputs!E63)*C7)*Inputs!$D$45*Inputs!$D$59)*Inputs!$D$46)*Inputs!$D$47*Inputs!$D$48+(((Inputs!J63+Inputs!K63)/(Inputs!D63+Inputs!E63)*C7)*Inputs!$D$45*Inputs!$D$59)*Inputs!$D$49+(((Inputs!J63+Inputs!K63)/(Inputs!D63+Inputs!E63)*C7)*Inputs!$D$45*Inputs!$D$59)*Inputs!$D$50*Inputs!$D$51)*(Inputs!$D$41*12/Inputs!$D$42)+(((((Inputs!J63+Inputs!K63)/(Inputs!D63+Inputs!E63)*C7)*Inputs!$D$45*Inputs!$D$59)*Inputs!$D$46)*Inputs!$D$47+(((Inputs!J63+Inputs!K63)/(Inputs!D63+Inputs!E63)*C7)*Inputs!$D$45*Inputs!$D$59)+(((Inputs!J63+Inputs!K63)/(Inputs!D63+Inputs!E63)*C7)*Inputs!$D$45*Inputs!$D$59)*Inputs!$D$50)*Inputs!$D$52*(Inputs!$D$43*12/Inputs!$D$44)))+(Inputs!F63+Inputs!G63)*Inputs!$D$56*MAX((Inputs!$D$41+Inputs!$D$43)*12,((((((Inputs!L63+Inputs!M63)/(Inputs!F63+Inputs!G63)*C7)*Inputs!$D$45*Inputs!$D$59)*Inputs!$D$46)*Inputs!$D$47*Inputs!$D$48+(((Inputs!L63+Inputs!M63)/(Inputs!F63+Inputs!G63)*C7)*Inputs!$D$45*Inputs!$D$59)*Inputs!$D$49+(((Inputs!L63+Inputs!M63)/(Inputs!F63+Inputs!G63)*C7)*Inputs!$D$45*Inputs!$D$59)*Inputs!$D$50*Inputs!$D$51)*(Inputs!$D$41*12/Inputs!$D$42)+(((((Inputs!L63+Inputs!M63)/(Inputs!F63+Inputs!G63)*C7)*Inputs!$D$45*Inputs!$D$59)*Inputs!$D$46)*Inputs!$D$47+(((Inputs!L63+Inputs!M63)/(Inputs!F63+Inputs!G63)*C7)*Inputs!$D$45*Inputs!$D$59)+(((Inputs!L63+Inputs!M63)/(Inputs!F63+Inputs!G63)*C7)*Inputs!$D$45*Inputs!$D$59)*Inputs!$D$50)*Inputs!$D$52*(Inputs!$D$43*12/Inputs!$D$44)))+(Inputs!H63)*Inputs!$D$57*Inputs!$D$58*MAX(Inputs!$D$53*(Inputs!$D$41*12/Inputs!$D$42)+Inputs!$D$54*(Inputs!$D$43*12/Inputs!$D$44),((((((Inputs!N63)/(Inputs!H63)*C7)*Inputs!$D$45*Inputs!$D$59)*Inputs!$D$46)*Inputs!$D$47*Inputs!$D$48+(((Inputs!N63)/(Inputs!H63)*C7)*Inputs!$D$45*Inputs!$D$59)*Inputs!$D$49+(((Inputs!N63)/(Inputs!H63)*C7)*Inputs!$D$45*Inputs!$D$59)*Inputs!$D$50*Inputs!$D$51)*(Inputs!$D$41*12/Inputs!$D$42)+(((((Inputs!N63)/(Inputs!H63)*C7)*Inputs!$D$45*Inputs!$D$59)*Inputs!$D$46)*Inputs!$D$47+(((Inputs!N63)/(Inputs!H63)*C7)*Inputs!$D$45*Inputs!$D$59)+(((Inputs!N63)/(Inputs!H63)*C7)*Inputs!$D$45*Inputs!$D$59)*Inputs!$D$50)*Inputs!$D$52*(Inputs!$D$43*12/Inputs!$D$44)))*(1-Inputs!$D$55))/((Inputs!D63*0.973+Inputs!E63)*1+(Inputs!F63+Inputs!G63)*Inputs!$D$56+(Inputs!H63)*Inputs!$D$57*Inputs!$D$58) -> 8883.9325 | D8: =((Inputs!D64*0.973+Inputs!E64)*1*MAX((Inputs!$D$41+Inputs!$D$43)*12,((((((Inputs!J64+Inputs!K64)/(Inputs!D64+Inputs!E64)*D7)*Inputs!$D$45*Inputs!$D$59)*Inputs!$D$46)*Inputs!$D$47*Inputs!$D$48+(((Inputs!J64+Inputs!K64)/(Inputs!D64+Inputs!E64)*D7)*Inputs!$D$45*Inputs!$D$59)*Inputs!$D$49+(((Inputs!J64+Inputs!K64)/(Inputs!D64+Inputs!E64)*D7)*Inputs!$D$45*Inputs!$D$59)*Inputs!$D$50*Inputs!$D$51)*(Inputs!$D$41*12/Inputs!$D$42)+(((((Inputs!J64+Inputs!K64)/(Inputs!D64+Inputs!E64)*D7)*Inputs!$D$45*Inputs!$D$59)*Inputs!$D$46)*Inputs!$D$47+(((Inputs!J64+Inputs!K64)/(Inputs!D64+Inputs!E64)*D7)*Inputs!$D$45*Inputs!$D$59)+(((Inputs!J64+Inputs!K64)/(Inputs!D64+Inputs!E64)*D7)*Inputs!$D$45*Inputs!$D$59)*Inputs!$D$50)*Inputs!$D$52*(Inputs!$D$43*12/Inputs!$D$44)))+(Inputs!F64+Inputs!G64)*Inputs!$D$56*MAX((Inputs!$D$41+Inputs!$D$43)*12,((((((Inputs!L64+Inputs!M64)/(Inputs!F64+Inputs!G64)*D7)*Inputs!$D$45*Inputs!$D$59)*Inputs!$D$46)*Inputs!$D$47*Inputs!$D$48+(((Inputs!L64+Inputs!M64)/(Inputs!F64+Inputs!G64)*D7)*Inputs!$D$45*Inputs!$D$59)*Inputs!$D$49+(((Inputs!L64+Inputs!M64)/(Inputs!F64+Inputs!G64)*D7)*Inputs!$D$45*Inputs!$D$59)*Inputs!$D$50*Inputs!$D$51)*(Inputs!$D$41*12/Inputs!$D$42)+(((((Inputs!L64+Inputs!M64)/(Inputs!F64+Inputs!G64)*D7)*Inputs!$D$45*Inputs!$D$59)*Inputs!$D$46)*Inputs!$D$47+(((Inputs!L64+Inputs!M64)/(Inputs!F64+Inputs!G64)*D7)*Inputs!$D$45*Inputs!$D$59)+(((Inputs!L64+Inputs!M64)/(Inputs!F64+Inputs!G64)*D7)*Inputs!$D$45*Inputs!$D$59)*Inputs!$D$50)*Inputs!$D$52*(Inputs!$D$43*12/Inputs!$D$44)))+(Inputs!H64)*Inputs!$D$57*Inputs!$D$58*MAX(Inputs!$D$53*(Inputs!$D$41*12/Inputs!$D$42)+Inputs!$D$54*(Inputs!$D$43*12/Inputs!$D$44),((((((Inputs!N64)/(Inputs!H64)*D7)*Inputs!$D$45*Inputs!$D$59)*Inputs!$D$46)*Inputs!$D$47*Inputs!$D$48+(((Inputs!N64)/(Inputs!H64)*D7)*Inputs!$D$45*Inputs!$D$59)*Inputs!$D$49+(((Inputs!N64)/(Inputs!H64)*D7)*Inputs!$D$45*Inputs!$D$59)*Inputs!$D$50*Inputs!$D$51)*(Inputs!$D$41*12/Inputs!$D$42)+(((((Inputs!N64)/(Inputs!H64)*D7)*Inputs!$D$45*Inputs!$D$59)*Inputs!$D$46)*Inputs!$D$47+(((Inputs!N64)/(Inputs!H64)*D7)*Inputs!$D$45*Inputs!$D$59)+(((Inputs!N64)/(Inputs!H64)*D7)*Inputs!$D$45*Inputs!$D$59)*Inputs!$D$50)*Inputs!$D$52*(Inputs!$D$43*12/Inputs!$D$44)))*(1-Inputs!$D$55))/((Inputs!D64*0.973+Inputs!E64)*1+(Inputs!F64+Inputs!G64)*Inputs!$D$56+(Inputs!H64)*Inputs!$D$57*Inputs!$D$58) -> 8130.7546 | E8: =Weights!B8/(Weights!B5+Weights!B6+Weights!B8) -> 0.27272727 | G8: Same method as Inputs; each sub-industry's own employees per firm
A10: Scores (ratio-to-max)
A11: Market (reachable accounts) | B11: =1+4*B6/MAX($B$6:$D$6) -> 2.7187586 | C11: =1+4*C6/MAX($B$6:$D$6) -> 2.213728 | D11: =1+4*D6/MAX($B$6:$D$6) -> 5
A12: Need (sales share) | B12: =1+4*B7/MAX($B$7:$D$7) -> 4.7291371 | C12: =1+4*C7/MAX($B$7:$D$7) -> 4.7291371 | D12: =1+4*D7/MAX($B$7:$D$7) -> 5
A13: Revenue (ACV per account) | B13: =1+4*B8/MAX($B$8:$D$8) -> 5 | C13: =1+4*C8/MAX($B$8:$D$8) -> 4.1854823 | D13: =1+4*D8/MAX($B$8:$D$8) -> 3.9154178
A14: Weighted score (market, need, revenue) | B14: =$E$6*B11+$E$7*B12+$E$8*B13 -> 4.0719621 | C14: =$E$6*C11+$E$7*C12+$E$8*C13 -> 3.6661734 | D14: =$E$6*D11+$E$7*D12+$E$8*D13 -> 4.7042048
A15: Same, with concave market scoring (√) | B15: =$E$6*(1+4*SQRT(B6/MAX($B$6:$D$6)))+$E$7*B12+$E$8*B13 -> 4.4004239 | C15: =$E$6*(1+4*SQRT(C6/MAX($B$6:$D$6)))+$E$7*C12+$E$8*C13 -> 4.0260492 | D15: =$E$6*(1+4*SQRT(D6/MAX($B$6:$D$6)))+$E$7*D12+$E$8*D13 -> 4.7042048
A17: Not scored — tie-breakers
A18: Public Clay reference customer | B18: Regency Supply (S07) | C18: None found | D18: None found
A19: Contractor-facing (permits / Maps sourcing relevance) | B19: High (electrical contractors) | C19: Highest (plumbing, HVAC contractors) | D19: Mixed (plants, MRO buyers)
A20: Establishments per firm, full-year firms (territory complexity) | B20: 1.64 | C20: 2.21 | D20: 1.57
A21: Industry association channel | B21: NAED (S53) | C21: ASA, 4,000+ branch locations (S54) | D21: ISA, PTDA [K]
A23: Reading: on v2 indicators, 4238 machinery/MRO scores highest — the largest account base and the highest sales share, with ACV close to 4236's. 4236 electrical remains a defensible first wave only because it has the one public Clay reference (Regency) and a single association channel. A validation sprint should test both 4236 and 4238 rather than assume the beachhead.

Sheet Change_Log
A1: Change Log — v1 → v2 (review issue C5)
A2: Partner review: review/Partner_Review_2026-10-19.md. v1 archived in appendix/archive/.
A4: Criterion / item | B4: v1 | C4: v2 | D4: Why
A5: Market Attractiveness | B5: 50% SAM $ (uniform ACV, outbound filter) + 50% headroom flag (5/5/2) | C5: Reachable accounts = firms × CRM in use × (1 − already Clay) | D5: SAM $ embedded an ACV assumption and a sales-share-based filter; headroom double-penalized PS with F2
A6: Customer Need | B6: 50% sales intensity + 50% LinkedIn coverage gap | C6: Sales intensity only | D6: Coverage proxy already drives Competitive Position F1
A7: Product-Market Fit | B7: Free judgment 4 / 2 / 4 | C7: Capability-fit index from the 05 pain-to-capability map → 4.0 / 3.0 / 5.0 | D7: Traceable to evidence; builder gap kept out (it is Ease)
A8: Revenue Potential | B8: 50% SOM ARR + 50% sales staff per firm (assumed ACV lift) | C8: Usage-based first-year ACV per won account at list prices | D8: Phase 4 showed seller density lifts ACV only from Mid-Market up
A9: CRM readiness (distribution) | B9: 65% (DSG 2022) | C9: 56% (Phocas/DSG 2026, S25) | D9: Newest evidence (review M2)
A10: Robustness | B10: 11 stress tests, 6 weight sets, random weights | C10: 14 stress tests incl. concave size scoring and the v1 market definition; same weight sets; random weights; economic cross-check from 07 v2
A11: Precision (review m7) | B11: Totals shown to two decimals and read as a ranking | C11: Totals displayed to one decimal with P10–P90 ranges under centered random weights (Executive_Summary); deck shows the same | D11: Judgment scores cannot separate 3.79 from 3.85
A12: Drilldown | B12: Receipts/judgment indicators; 4236 first | C12: v2 indicators; 4238 scores first; Regency kept as a tie-breaker | D12: Beachhead reopened

Sheet Sources
A1: Sources
A2: Full register: Research_Sources.csv
A4: ID | B4: Source | C4: Used for
A5: S14 | B5: U.S. Census Bureau, 2022 Economic Census — Employment Size of Firms | C5: Firm and employee counts, de-duplication
A6: S15 | B6: U.S. BLS, OEWS May 2025 industry-specific estimates | C6: Sales occupations share
A7: S01 | B7: Clay pricing page | C7: Usage-based ACV
A8: S25 | B8: Phocas / DSG, State of Sales in Distribution 2026 | C8: CRM in use 56%
A9: S06 / S32 | B9: Clay case-study filters; Bloomberry Clay user analysis | C9: Already-Clay share assumptions
A10: S07 | B10: Clay case study: Regency Supply | C10: Drilldown tie-breaker
A11: S53 / S54 | B11: NAED; American Supply Association | C11: Drilldown channels
A12: 04, 05, 07 | B12: Project workbooks and memos | C12: Competitive factors, pain map, economic cross-check
