Workbook

Sheet Cover
A1: 07 — Financial Model v2: should Clay fund a U.S. vertical program in 2027–2029?
A2: Independent portfolio case study by Zhuoran (Zora) Wang · Not commissioned by or affiliated with Clay Labs Inc. · v2 rebuilt 2026-10-19 after partner review
A4: Question | B4: Does any vertical program (distribution or professional services; lean pilot, sales-led team or solution play) create value above a 12% hurdle and above Option 0 — the same money spent in Clay's core motion?
A5: Structure | B5: Assumptions (3 selectors) → Market Sizing → ACV Build → GTM Funnel → Revenue Model → Unit Economics (live) → Scenarios, Sensitivity (full model copies on Engine Runs) → Monte Carlo (Python mirror, reconciled run by run) → Executive Output. Change Log maps v1 → v2.
A6: Time and units | B6: Quarterly, Q1 2027–Q4 2029; annual totals P–R, 2027–29 in S. US$ nominal. ARR is end-of-quarter run-rate; recognized revenue = average ARR ÷ 4.
A7: Valuation | B7: NPV = Σ PV[(gross profit × (1 − incrementality haircut)) − incremental cost] + PV of 5 years of gross profit from the 2029 ARR base (net of CS, decaying at GRR, haircut). Option 0 NPV is computed on the same non-CS spend.
A8: Evidence classes | B8: A verified fact · B benchmark · C analyst estimate · D scenario assumption · E recommendation. Each input row carries its class, Monte Carlo group and source.
A9: Color legend | B9: Blue = input · black = formula · green = link to another tab · yellow fill = judgment · green fill = key output · red fill = negative NPV.
A10: Not a forecast | B10: Outputs are scenario and simulation estimates, not Clay forecasts. Monte Carlo values are static results of appendix/clay_engine.py (seed 42).

Sheet Executive Output
A1: Executive Output — is any vertical program worth funding in 2027–2029? (v2, after partner review)
A2: Scenario and simulation outputs are illustrative estimates built from public data and labeled assumptions. They are not Clay forecasts and use no Clay internal data.
A3: ="Live model: "&Assumptions!$E$5&" · "&Assumptions!$E$4&" · "&Assumptions!$E$6&" (selectors on Assumptions D4:D6)" -> Live model: Industrial distribution · Base · Lean partner-led pilot (selectors on Assumptions D4:D6)
A5: Option (Base case, deterministic) | B5: NPV at 12% | C5: NPV advantage vs Option 0 | D5: Exit ARR Q4 2029 | E5: Average first-year ACV | F5: CAC payback, 2029 cohort | G5: Cumulative P&L 2027–29 | H5: Peak investment
A6: Industrial distribution — Lean partner-led pilot | B6: =Scenarios!D5 -> -1892877 | C6: =Scenarios!D7 -> -3405399 | D6: =Scenarios!D8 -> 509612.73 | E6: =Scenarios!D11 -> 8847.9735 | F6: =Scenarios!D14 -> 53.740167 | G6: =Scenarios!D16 -> -2645899.1 | H6: =Scenarios!D17 -> -2645899.1
A7: Industrial distribution — Sales-led vertical team | B7: =Scenarios!G5 -> -5438648.7 | C7: =Scenarios!G7 -> -9174954.9 | D7: =Scenarios!G8 -> 820721.59 | E7: =Scenarios!G11 -> 8863.8206 | F7: =Scenarios!G14 -> 117.74997 | G7: =Scenarios!G16 -> -7222893 | H7: =Scenarios!G17 -> -7222893
A8: Industrial distribution — Solution play (no vertical team) | B8: =Scenarios!J5 -> -544641.96 | C8: =Scenarios!J7 -> -1072505.1 | D8: =Scenarios!J8 -> 246156.7 | E8: =Scenarios!J11 -> 8850.6126 | F8: =Scenarios!J14 -> 25.70966 | G8: =Scenarios!J16 -> -821017.4 | H8: =Scenarios!J17 -> -821017.4
A9: Professional services — Lean partner-led pilot | B9: =Scenarios!M5 -> -2044076.8 | C9: =Scenarios!M7 -> -3569477.8 | D9: =Scenarios!M8 -> 680163.89 | E9: =Scenarios!M11 -> 6863.9789 | F9: =Scenarios!M14 -> 42.271735 | G9: =Scenarios!M16 -> -2610408.3 | H9: =Scenarios!M17 -> -2610408.3
A10: Professional services — Sales-led vertical team | B10: =Scenarios!P5 -> -5731151.9 | C10: =Scenarios!P7 -> -9458007.8 | D10: =Scenarios!P8 -> 914355.66 | E10: =Scenarios!P11 -> 6868.9908 | F10: =Scenarios!P14 -> 110.90519 | G10: =Scenarios!P16 -> -7171119.1 | H10: =Scenarios!P17 -> -7171119.1
A11: Professional services — Solution play (no vertical team) | B11: =Scenarios!S5 -> -620644.16 | C11: =Scenarios!S7 -> -1153233.5 | D11: =Scenarios!S8 -> 317295.3 | E11: =Scenarios!S11 -> 6865.7947 | F11: =Scenarios!S14 -> 20.487621 | G11: =Scenarios!S16 -> -803970.51 | H11: =Scenarios!S17 -> -803970.51
A13: Simulation (5,000 draws; correlated inputs) | B13: Mean NPV | C13: P10 | D13: P90 | E13: P(NPV > 0) | F13: P(beats Option 0) | G13: Stopped at Gate 1 | H13: Scaled at Gate 1
A14: Industrial distribution — Lean pilot, staged | B14: ='Monte Carlo'!B6 -> -1486097 | C14: ='Monte Carlo'!C6 -> -1979643 | D14: ='Monte Carlo'!E6 -> -868884 | E14: ='Monte Carlo'!F6 -> 0 | F14: ='Monte Carlo'!H6 -> 0 | G14: ='Monte Carlo'!I6 -> 0.337 | H14: ='Monte Carlo'!J6 -> 0.0112
A15: Industrial distribution — Sales-led team | B15: ='Monte Carlo'!B7 -> -5315702 | C15: ='Monte Carlo'!C7 -> -5740374 | D15: ='Monte Carlo'!E7 -> -4775974 | E15: ='Monte Carlo'!F7 -> 0 | F15: ='Monte Carlo'!H7 -> 0 | G15: ='Monte Carlo'!I7 -> 0 | H15: ='Monte Carlo'!J7 -> 0
A16: Industrial distribution — Solution play | B16: ='Monte Carlo'!B8 -> -511201 | C16: ='Monte Carlo'!C8 -> -604824 | D16: ='Monte Carlo'!E8 -> -388453 | E16: ='Monte Carlo'!F8 -> 0.0002 | F16: ='Monte Carlo'!H8 -> 0 | G16: ='Monte Carlo'!I8 -> 0 | H16: ='Monte Carlo'!J8 -> 0
A17: Professional services — Lean pilot, staged | B17: ='Monte Carlo'!B10 -> -1663742 | C17: ='Monte Carlo'!C10 -> -2146572 | D17: ='Monte Carlo'!E10 -> -897861 | E17: ='Monte Carlo'!F10 -> 0 | F17: ='Monte Carlo'!H10 -> 0 | G17: ='Monte Carlo'!I10 -> 0.3346 | H17: ='Monte Carlo'!J10 -> 0.0184
A18: Professional services — Sales-led team | B18: ='Monte Carlo'!B11 -> -5726126 | C18: ='Monte Carlo'!C11 -> -5939510 | D18: ='Monte Carlo'!E11 -> -5456822 | E18: ='Monte Carlo'!F11 -> 0 | F18: ='Monte Carlo'!H11 -> 0 | G18: ='Monte Carlo'!I11 -> 0 | H18: ='Monte Carlo'!J11 -> 0
A19: Professional services — Solution play | B19: ='Monte Carlo'!B12 -> -614778 | C19: ='Monte Carlo'!C12 -> -673722 | D19: ='Monte Carlo'!E12 -> -544597 | E19: ='Monte Carlo'!F12 -> 0 | F19: ='Monte Carlo'!H12 -> 0 | G19: ='Monte Carlo'!I12 -> 0 | H19: ='Monte Carlo'!J12 -> 0
A21: Model checks
A22: Live model reconciles to engine runs (0 = pass) | B22: =ABS(Scenarios!C42)+ABS(Scenarios!C43) -> 0
A23: Python engine reconciles to Excel engine (max abs. NPV difference, $) | B23: ='Monte Carlo'!D54 -> 0
A25: What the model shows (v2)
A26: 1. No option clears a 12% hurdle in Base. Distribution lean pilot: NPV −$1.89M, exit ARR $0.51M, average first-year ACV $8.8K once the win mix is derived from the account base (v1 assumed $13.8K).
A27: 2. Upside is NPV-positive (+$1.53M) only when favorable values occur together. With correlated uncertainty, the staged pilot's P(NPV > 0) is 0% and its P90 is −$0.87M; even near-comonotonic inputs or 2× wider ranges keep P(NPV > 0) at or below 10%.
A28: 3. Against Option 0 (the same spend in Clay's core motion at a discounted benchmark payback) every staffed option loses, in Base and in Upside. The bar a vertical must clear is the core's return, not zero.
A29: 4. A sales-led team now builds its own pipeline and adds ARR (exit $0.82M vs $0.51M lean), but NPV falls to −$5.44M: a ~5,000-account market cannot carry six AEs.
A30: 5. Professional services is no better on the same engine: list-price ACV sits at the Growth floor for SMB and Mid-Market, and more of its wins would have come anyway (Base NPV −$2.04M).
A31: 6. The cheapest test — a solution play with templates and data providers but no vertical team — loses least (distribution Base NPV −$0.54M; simulated P(NPV > 0) 0%) and is the only option that beats Option 0 in Upside. Recommendation: validate before staffing anything.

Sheet Assumptions
A1: Assumptions — every input, by segment and scenario (v2)
A2: Edit blue cells only. 'Live' feeds the main model via the three selectors. Scenarios, Sensitivity and Monte Carlo run their own copies. Segment-level market inputs are fixed across scenarios: the universe does not flex, only performance does.
A4: Scenario (1 = Downside, 2 = Base, 3 = Upside) | D4: 2 | E4: =CHOOSE($D$4,"Downside","Base","Upside") -> Base
A5: Segment (1 = Industrial distribution, 2 = Professional services) | D5: 1 | E5: =CHOOSE($D$5,"Industrial distribution","Professional services") -> Industrial distribution
A6: Motion (1 = Lean partner-led pilot, 2 = Sales-led vertical team, 3 = Solution play, no vertical team) | D6: 1 | E6: =CHOOSE($D$6,"Lean partner-led pilot","Sales-led vertical team","Solution play") -> Lean partner-led pilot
A8: ID | B8: Input | C8: Unit | D8: Dist: Downside | E8: Dist: Base | F8: Dist: Upside | G8: PS: Downside | H8: PS: Base | I8: PS: Upside | J8: Live | K8: Class | L8: MC group | M8: Source / rationale
A9: MARKET (fixed across scenarios)
A10: A1 | B10: SAM filter 1: active outbound / territory sales motion | C10: % | D10: 0.8 | E10: 0.8 | F10: 0.8 | G10: 0.55 | H10: 0.55 | I10: 0.55 | J10: =INDEX(D10:I10,1,(Assumptions!$D$5-1)*3+Assumptions!$D$4) -> 0.8 | K10: D | L10: fixed | M10: Phase 1 (02 A4/A6); sales occupations 22.0% vs 6.2% (S15)
A11: A2 | B11: SAM filter 2: CRM in use (integrable today) | C11: % | D11: 0.56 | E11: 0.56 | F11: 0.56 | G11: 0.7 | H11: 0.7 | I11: 0.7 | J11: =INDEX(D11:I11,1,(Assumptions!$D$5-1)*3+Assumptions!$D$4) -> 0.56 | K11: B/D | L11: fixed | M11: Dist: 56% use CRM, Phocas/DSG 2026 (S25) — newest evidence (v1 used 65%). PS: no public rate; Phase 1 assumption (02 A9)
A12: A3 | B12: Share of SAM already Clay customers (excluded) | C12: % | D12: 0.03 | E12: 0.03 | F12: 0.03 | G12: 0.1 | H12: 0.1 | I12: 0.1 | J12: =INDEX(D12:I12,1,(Assumptions!$D$5-1)*3+Assumptions!$D$4) -> 0.03 | K12: D | L12: fixed | M12: No public data. PS higher: Clay markets to PS (S06) and IT services is a top industry of detected Clay users (S32)
A13: A4 | B13: Wave 1 launch quarter (Dist 4236 electrical · PS 5413 A&E) | C13: qtr | D13: 1 | E13: 1 | F13: 1 | G13: 1 | H13: 1 | I13: 1 | J13: =INDEX(D13:I13,1,(Assumptions!$D$5-1)*3+Assumptions!$D$4) -> 1 | K13: E | L13: fixed | M13: Beachheads: 06 drilldown (Dist); A&E pursuit-data gap, Deltek/Unanet ecosystem (PS, 05)
A14: A5 | B14: Wave 2 launch quarter (Dist 4237 PHVAC · PS 5416 consulting) | C14: qtr | D14: 7 | E14: 5 | F14: 4 | G14: 7 | H14: 5 | I14: 4 | J14: =INDEX(D14:I14,1,(Assumptions!$D$5-1)*3+Assumptions!$D$4) -> 5 | K14: D | L14: timing | M14: After Gate 1; Downside delays
A15: A6 | B15: Wave 3 launch quarter, 99 = never (Dist 4238 MRO · PS 5415 IT services) | C15: qtr | D15: 99 | E15: 7 | F15: 6 | G15: 99 | H15: 7 | I15: 6 | J15: =INDEX(D15:I15,1,(Assumptions!$D$5-1)*3+Assumptions!$D$4) -> 7 | K15: D | L15: timing | M15: PS excludes 5418 advertising/PR: Clay's agency partners (channel conflict) [E]
A16: DEMAND AND FUNNEL
A17: A7 | B17: Automated outbound coverage: share of active SAM sequenced per quarter | C17: % | D17: 0.3 | E17: 0.4 | F17: 0.5 | G17: 0.3 | H17: 0.4 | I17: 0.5 | J17: =INDEX(D17:I17,1,(Assumptions!$D$5-1)*3+Assumptions!$D$4) -> 0.4 | K17: D | L17: demand | M17: Clay-run outbound with its own product
A18: A8 | B18: ICP tilt: outbound weight on Mid-Market accounts (vs SMB = 1) | C18: x | D18: 2 | E18: 2 | F18: 2 | G18: 2 | H18: 2 | I18: 2 | J18: =INDEX(D18:I18,1,(Assumptions!$D$5-1)*3+Assumptions!$D$4) -> 2 | K18: E | L18: fixed | M18: Strategic lever (08 ICP); changes allocation of the same coverage, not the total
A19: A9 | B19: ICP tilt: outbound weight on Enterprise accounts (vs SMB = 1) | C19: x | D19: 2 | E19: 2 | F19: 2 | G19: 2 | H19: 2 | I19: 2 | J19: =INDEX(D19:I19,1,(Assumptions!$D$5-1)*3+Assumptions!$D$4) -> 2 | K19: E | L19: fixed | M19: Strategic lever
A20: A10 | B20: Meeting rate per account sequenced (first year) | C20: % | D20: 0.02 | E20: 0.03 | F20: 0.045 | G20: 0.015 | H20: 0.025 | I20: 0.035 | J20: =INDEX(D20:I20,1,(Assumptions!$D$5-1)*3+Assumptions!$D$4) -> 0.03 | K20: D | L20: demand | M20: Cold outbound 1–5% [K]; PS buyers more heavily prospected → lower
A21: A11 | B21: Meeting-rate retention per year of re-sequencing the same accounts | C21: x/yr | D21: 0.6 | E21: 0.75 | F21: 0.85 | G21: 0.6 | H21: 0.75 | I21: 0.85 | J21: =INDEX(D21:I21,1,(Assumptions!$D$5-1)*3+Assumptions!$D$4) -> 0.75 | K21: D | L21: indep | M21: Outbound fatigue (review m3); applied by wave age
A22: A12 | B22: Inbound / template MQLs per quarter at base program spend (% of active SAM) | C22: % | D22: 0.005 | E22: 0.01 | F22: 0.015 | G22: 0.01 | H22: 0.015 | I22: 0.02 | J22: =INDEX(D22:I22,1,(Assumptions!$D$5-1)*3+Assumptions!$D$4) -> 0.01 | K22: D | L22: demand | M22: PS more digital → higher
A23: A13 | B23: Cost per extra MQL from program spend above base | C23: $ | D23: 600 | E23: 400 | F23: 250 | G23: 600 | H23: 400 | I23: 250 | J23: =INDEX(D23:I23,1,(Assumptions!$D$5-1)*3+Assumptions!$D$4) -> 400 | K23: B/D | L23: cost | M23: SaaS CPL commonly cited at $200–350 (S55); niche industrial audience costs more
A24: A14 | B24: Ceiling on extra MQLs per quarter (% of active SAM) | C24: % | D24: 0.03 | E24: 0.03 | F24: 0.03 | G24: 0.03 | H24: 0.03 | I24: 0.03 | J24: =INDEX(D24:I24,1,(Assumptions!$D$5-1)*3+Assumptions!$D$4) -> 0.03 | K24: D | L24: fixed | M24: Diminishing returns: extra MQLs = cap × (1 − e^(−spend/(CPL × cap)))
A25: A15 | B25: Partners active at launch | C25: # | D25: 1 | E25: 2 | F25: 3 | G25: 2 | H25: 3 | I25: 4 | J25: =INDEX(D25:I25,1,(Assumptions!$D$5-1)*3+Assumptions!$D$4) -> 2 | K25: D | L25: demand | M25: Dist: no distribution partners visible today (S35). PS: agency ecosystem exists (S34) but competes
A26: A16 | B26: Partners added per quarter | C26: #/qtr | D26: 1 | E26: 1 | F26: 2 | G26: 1 | H26: 1 | I26: 2 | J26: =INDEX(D26:I26,1,(Assumptions!$D$5-1)*3+Assumptions!$D$4) -> 1 | K26: D | L26: demand
A27: A17 | B27: Partner network cap | C27: # | D27: 5 | E27: 10 | F27: 15 | G27: 6 | H27: 10 | I27: 14 | J27: =INDEX(D27:I27,1,(Assumptions!$D$5-1)*3+Assumptions!$D$4) -> 10 | K27: D | L27: demand
A28: A18 | B28: Introductions per active partner per quarter | C28: #/qtr | D28: 2 | E28: 3 | F28: 4 | G28: 2 | H28: 3 | I28: 4 | J28: =INDEX(D28:I28,1,(Assumptions!$D$5-1)*3+Assumptions!$D$4) -> 3 | K28: D | L28: demand
A29: A19 | B29: Outbound meeting → opportunity | C29: % | D29: 0.3 | E29: 0.4 | F29: 0.5 | G29: 0.3 | H29: 0.4 | I29: 0.5 | J29: =INDEX(D29:I29,1,(Assumptions!$D$5-1)*3+Assumptions!$D$4) -> 0.4 | K29: B/D | L29: demand | M29: SQL→opportunity 42% (S49); a booked meeting ≈ SQL stage (fixes v1 stage mix-up, review M4)
A30: A20 | B30: Partner introduction → opportunity | C30: % | D30: 0.4 | E30: 0.5 | F30: 0.6 | G30: 0.4 | H30: 0.5 | I30: 0.6 | J30: =INDEX(D30:I30,1,(Assumptions!$D$5-1)*3+Assumptions!$D$4) -> 0.5 | K30: D | L30: demand | M30: Warm, pre-vetted introductions
A31: A21 | B31: Inbound MQL → opportunity | C31: % | D31: 0.1 | E31: 0.16 | F31: 0.22 | G31: 0.1 | H31: 0.16 | I31: 0.22 | J31: =INDEX(D31:I31,1,(Assumptions!$D$5-1)*3+Assumptions!$D$4) -> 0.16 | K31: B | L31: demand | M31: MQL→SQL 39% × SQL→opp 42% (S49)
A32: A22 | B32: Win rate (opportunity → won) | C32: % | D32: 0.15 | E32: 0.21 | F32: 0.3 | G32: 0.13 | H32: 0.18 | I32: 0.25 | J32: =INDEX(D32:I32,1,(Assumptions!$D$5-1)*3+Assumptions!$D$4) -> 0.21 | K32: B/D | L32: demand | M32: HubSpot average 21% (S48) as Base for a new vertical with one reference (v1: 28%). PS lower: competitive position 2.3 vs 4.0 (04)
A33: A23 | B33: Mid-Market opportunity propensity per sequenced account (SMB = 1) | C33: x | D33: 1 | E33: 1 | F33: 1 | G33: 1 | H33: 1 | I33: 1 | J33: =INDEX(D33:I33,1,(Assumptions!$D$5-1)*3+Assumptions!$D$4) -> 1 | K33: D | L33: fixed
A34: A24 | B34: Enterprise opportunity propensity per sequenced account (SMB = 1) | C34: x | D34: 0.5 | E34: 0.7 | F34: 0.9 | G34: 0.5 | H34: 0.7 | I34: 0.9 | J34: =INDEX(D34:I34,1,(Assumptions!$D$5-1)*3+Assumptions!$D$4) -> 0.7 | K34: D | L34: value | M34: Enterprise: buying committees, incumbents; lower conversion (review C2)
A35: A25 | B35: Sales cycle, SMB & Mid-Market (quarters from opportunity to close) | C35: qtr | D35: 1 | E35: 1 | F35: 1 | G35: 1 | H35: 1 | I35: 1 | J35: =INDEX(D35:I35,1,(Assumptions!$D$5-1)*3+Assumptions!$D$4) -> 1 | K35: B | L35: fixed | M35: Deals < $25K close in 2–3 months (S48)
A36: A26 | B36: Sales cycle, Enterprise (quarters) | C36: qtr | D36: 2 | E36: 2 | F36: 2 | G36: 2 | H36: 2 | I36: 2 | J36: =INDEX(D36:I36,1,(Assumptions!$D$5-1)*3+Assumptions!$D$4) -> 2 | K36: B/D | L36: fixed | M36: Longer enterprise cycles (review C2)
A37: A27 | B37: Self-serve share of SMB wins (no AE) | C37: % | D37: 0.15 | E37: 0.3 | F37: 0.4 | G37: 0.3 | H37: 0.45 | I37: 0.6 | J37: =INDEX(D37:I37,1,(Assumptions!$D$5-1)*3+Assumptions!$D$4) -> 0.3 | K37: D | L37: value | M37: Builder capacity: Dist 0.69× vs PS 7.2× technical-talent index (H4)
A38: A28 | B38: Accounts a ramped dedicated AE works per quarter (beyond automated coverage) | C38: #/qtr | D38: 100 | E38: 150 | F38: 200 | G38: 100 | H38: 150 | I38: 200 | J38: =INDEX(D38:I38,1,(Assumptions!$D$5-1)*3+Assumptions!$D$4) -> 150 | K38: D | L38: demand | M38: AE self-sourcing (review C1); practitioner guidance: AEs self-source < ~30% of pipeline [K]
A39: A29 | B39: AE outreach meeting-rate multiplier vs automated outbound | C39: x | D39: 1.25 | E39: 1.5 | F39: 1.75 | G39: 1.25 | H39: 1.5 | I39: 1.75 | J39: =INDEX(D39:I39,1,(Assumptions!$D$5-1)*3+Assumptions!$D$4) -> 1.5 | K39: D | L39: demand | M39: Human, multi-channel prospecting
A40: ACV BUILD (usage-based pricing)
A41: A30 | B41: Sales occupations share of employment | C41: % | D41: 0.22 | E41: 0.22 | F41: 0.22 | G41: 0.062 | H41: 0.062 | I41: 0.062 | J41: =INDEX(D41:I41,1,(Assumptions!$D$5-1)*3+Assumptions!$D$4) -> 0.22 | K41: A→C | L41: fixed | M41: OEWS May 2025 (S15)
A42: A31 | B42: Accounts tracked per seller | C42: # | D42: 150 | E42: 150 | F42: 150 | G42: 150 | H42: 150 | I42: 150 | J42: =INDEX(D42:I42,1,(Assumptions!$D$5-1)*3+Assumptions!$D$4) -> 150 | K42: D | L42: fixed | M42: Same for both segments (neutrality)
A43: A32 | B43: Usage intensity factor | C43: x | D43: 0.75 | E43: 1 | F43: 1.5 | G43: 0.75 | H43: 1 | I43: 1.5 | J43: =INDEX(D43:I43,1,(Assumptions!$D$5-1)*3+Assumptions!$D$4) -> 1 | K43: D | L43: value
A44: A33 | B44: Contacts per account | C44: # | D44: 2 | E44: 2 | F44: 2 | G44: 2 | H44: 2 | I44: 2 | J44: =INDEX(D44:I44,1,(Assumptions!$D$5-1)*3+Assumptions!$D$4) -> 2 | K44: D | L44: fixed
A45: A34 | B45: Contact refreshes per year | C45: #/yr | D45: 2 | E45: 2 | F45: 2 | G45: 2 | H45: 2 | I45: 2 | J45: =INDEX(D45:I45,1,(Assumptions!$D$5-1)*3+Assumptions!$D$4) -> 2 | K45: D | L45: fixed
A46: A35 | B46: Data credits per contact refresh | C46: credits | D46: 6 | E46: 6 | F46: 6 | G46: 6 | H46: 6 | I46: 6 | J46: =INDEX(D46:I46,1,(Assumptions!$D$5-1)*3+Assumptions!$D$4) -> 6 | K46: B/D | L46: fixed | M46: S51
A47: A36 | B47: AI research credits per account per year | C47: credits | D47: 4 | E47: 4 | F47: 4 | G47: 4 | H47: 4 | I47: 4 | J47: =INDEX(D47:I47,1,(Assumptions!$D$5-1)*3+Assumptions!$D$4) -> 4 | K47: D | L47: fixed | M47: S01
A48: A37 | B48: New accounts sourced per year (% of tracked) | C48: % | D48: 0.25 | E48: 0.25 | F48: 0.25 | G48: 0.25 | H48: 0.25 | I48: 0.25 | J48: =INDEX(D48:I48,1,(Assumptions!$D$5-1)*3+Assumptions!$D$4) -> 0.25 | K48: D | L48: fixed
A49: A38 | B49: Data credits per new account sourced | C49: credits | D49: 8 | E49: 8 | F49: 8 | G49: 8 | H49: 8 | I49: 8 | J49: =INDEX(D49:I49,1,(Assumptions!$D$5-1)*3+Assumptions!$D$4) -> 8 | K49: D | L49: fixed
A50: A39 | B50: Actions per row operation | C50: actions | D50: 6 | E50: 6 | F50: 6 | G50: 6 | H50: 6 | I50: 6 | J50: =INDEX(D50:I50,1,(Assumptions!$D$5-1)*3+Assumptions!$D$4) -> 6 | K50: D | L50: fixed
A51: A40 | B51: Data-credit pack price (Growth, 72K credits/yr) | C51: $/mo | D51: 261 | E51: 261 | F51: 261 | G51: 261 | H51: 261 | I51: 261 | J51: =INDEX(D51:I51,1,(Assumptions!$D$5-1)*3+Assumptions!$D$4) -> 261 | K51: A | L51: fixed | M51: S01
A52: A41 | B52: Data-credit pack size | C52: credits | D52: 72000 | E52: 72000 | F52: 72000 | G52: 72000 | H52: 72000 | I52: 72000 | J52: =INDEX(D52:I52,1,(Assumptions!$D$5-1)*3+Assumptions!$D$4) -> 72000 | K52: A | L52: fixed | M52: S01
A53: A42 | B53: Actions pack price (Growth, 480K actions/yr) | C53: $/mo | D53: 185 | E53: 185 | F53: 185 | G53: 185 | H53: 185 | I53: 185 | J53: =INDEX(D53:I53,1,(Assumptions!$D$5-1)*3+Assumptions!$D$4) -> 185 | K53: A | L53: fixed | M53: S01
A54: A43 | B54: Actions pack size | C54: actions | D54: 480000 | E54: 480000 | F54: 480000 | G54: 480000 | H54: 480000 | I54: 480000 | J54: =INDEX(D54:I54,1,(Assumptions!$D$5-1)*3+Assumptions!$D$4) -> 480000 | K54: A | L54: fixed | M54: S01
A55: A44 | B55: Enterprise minimum data credits per year | C55: credits | D55: 1200000 | E55: 1200000 | F55: 1200000 | G55: 1200000 | H55: 1200000 | I55: 1200000 | J55: =INDEX(D55:I55,1,(Assumptions!$D$5-1)*3+Assumptions!$D$4) -> 1200000 | K55: A | L55: fixed | M55: S01
A56: A45 | B56: Enterprise minimum actions per year | C56: actions | D56: 2400000 | E56: 2400000 | F56: 2400000 | G56: 2400000 | H56: 2400000 | I56: 2400000 | J56: =INDEX(D56:I56,1,(Assumptions!$D$5-1)*3+Assumptions!$D$4) -> 2400000 | K56: A | L56: fixed | M56: S01
A57: A46 | B57: Enterprise discount vs list | C57: % | D57: 0.3 | E57: 0.3 | F57: 0.3 | G57: 0.3 | H57: 0.3 | I57: 0.3 | J57: =INDEX(D57:I57,1,(Assumptions!$D$5-1)*3+Assumptions!$D$4) -> 0.3 | K57: B | L57: fixed | M57: Vendr (S16)
A58: RETENTION AND EXPANSION (annual)
A59: A47 | B59: GRR — SMB | C59: % | D59: 0.85 | E59: 0.88 | F59: 0.91 | G59: 0.85 | H59: 0.88 | I59: 0.91 | J59: =INDEX(D59:I59,1,(Assumptions!$D$5-1)*3+Assumptions!$D$4) -> 0.88 | K59: B | L59: value | M59: SaaS Capital 2025 (S43)
A60: A48 | B60: GRR — Mid-Market | C60: % | D60: 0.86 | E60: 0.9 | F60: 0.93 | G60: 0.86 | H60: 0.9 | I60: 0.93 | J60: =INDEX(D60:I60,1,(Assumptions!$D$5-1)*3+Assumptions!$D$4) -> 0.9 | K60: B | L60: value | M60: S43
A61: A49 | B61: GRR — Enterprise | C61: % | D61: 0.88 | E61: 0.92 | F61: 0.95 | G61: 0.88 | H61: 0.92 | I61: 0.95 | J61: =INDEX(D61:I61,1,(Assumptions!$D$5-1)*3+Assumptions!$D$4) -> 0.92 | K61: B | L61: value | M61: S43
A62: A50 | B62: NRR — SMB | C62: % | D62: 0.92 | E62: 1 | F62: 1.06 | G62: 0.92 | H62: 1 | I62: 1.06 | J62: =INDEX(D62:I62,1,(Assumptions!$D$5-1)*3+Assumptions!$D$4) -> 1 | K62: B | L62: value | M62: S43
A63: A51 | B63: NRR — Mid-Market | C63: % | D63: 0.98 | E63: 1.06 | F63: 1.15 | G63: 0.98 | H63: 1.06 | I63: 1.15 | J63: =INDEX(D63:I63,1,(Assumptions!$D$5-1)*3+Assumptions!$D$4) -> 1.06 | K63: B | L63: value | M63: S43
A64: A52 | B64: NRR — Enterprise | C64: % | D64: 1.05 | E64: 1.15 | F64: 1.3 | G64: 1.05 | H64: 1.15 | I64: 1.3 | J64: =INDEX(D64:I64,1,(Assumptions!$D$5-1)*3+Assumptions!$D$4) -> 1.15 | K64: B | L64: value | M64: S43; Clay enterprise NRR > 200% (S02) not assumed
A65: SALES CAPACITY AND COST RATES
A66: A53 | B66: AE annual quota | C66: $ | D66: 875000 | E66: 875000 | F66: 875000 | G66: 875000 | H66: 875000 | I66: 875000 | J66: =INDEX(D66:I66,1,(Assumptions!$D$5-1)*3+Assumptions!$D$4) -> 875000 | K66: B | L66: fixed | M66: Bridge Group 2026 (S44)
A67: A54 | B67: AE productivity (attainment) | C67: % | D67: 0.55 | E67: 0.7 | F67: 0.85 | G67: 0.55 | H67: 0.7 | I67: 0.85 | J67: =INDEX(D67:I67,1,(Assumptions!$D$5-1)*3+Assumptions!$D$4) -> 0.7 | K67: B | L67: demand | M67: S44: 48% of reps at quota
A68: A55 | B68: AE on-target earnings | C68: $ | D68: 200000 | E68: 200000 | F68: 200000 | G68: 200000 | H68: 200000 | I68: 200000 | J68: =INDEX(D68:I68,1,(Assumptions!$D$5-1)*3+Assumptions!$D$4) -> 200000 | K68: B | L68: fixed | M68: S44
A69: A56 | B69: Wages as share of total compensation | C69: % | D69: 0.7 | E69: 0.7 | F69: 0.7 | G69: 0.7 | H69: 0.7 | I69: 0.7 | J69: =INDEX(D69:I69,1,(Assumptions!$D$5-1)*3+Assumptions!$D$4) -> 0.7 | K69: A | L69: fixed | M69: BLS ECEC June 2026 (S45)
A70: A57 | B70: Sales manager wage | C70: $ | D70: 186910 | E70: 186910 | F70: 186910 | G70: 186910 | H70: 186910 | I70: 186910 | J70: =INDEX(D70:I70,1,(Assumptions!$D$5-1)*3+Assumptions!$D$4) -> 186910 | K70: A | L70: fixed | M70: OEWS 513200 (S46)
A71: A58 | B71: Marketing manager wage | C71: $ | D71: 206930 | E71: 206930 | F71: 206930 | G71: 206930 | H71: 206930 | I71: 206930 | J71: =INDEX(D71:I71,1,(Assumptions!$D$5-1)*3+Assumptions!$D$4) -> 206930 | K71: A | L71: fixed | M71: S46
A72: A59 | B72: Software developer wage | C72: $ | D72: 158300 | E72: 158300 | F72: 158300 | G72: 158300 | H72: 158300 | I72: 158300 | J72: =INDEX(D72:I72,1,(Assumptions!$D$5-1)*3+Assumptions!$D$4) -> 158300 | K72: A | L72: fixed | M72: S46
A73: A60 | B73: Business operations specialist wage (CS) | C73: $ | D73: 112510 | E73: 112510 | F73: 112510 | G73: 112510 | H73: 112510 | I73: 112510 | J73: =INDEX(D73:I73,1,(Assumptions!$D$5-1)*3+Assumptions!$D$4) -> 112510 | K73: A | L73: fixed | M73: S46
A74: A61 | B74: Mid-Market + Enterprise accounts per CSM | C74: # | D74: 40 | E74: 40 | F74: 40 | G74: 40 | H74: 40 | I74: 40 | J74: =INDEX(D74:I74,1,(Assumptions!$D$5-1)*3+Assumptions!$D$4) -> 40 | K74: D | L74: fixed
A75: A62 | B75: SMB accounts per CSM | C75: # | D75: 250 | E75: 250 | F75: 250 | G75: 250 | H75: 250 | I75: 250 | J75: =INDEX(D75:I75,1,(Assumptions!$D$5-1)*3+Assumptions!$D$4) -> 250 | K75: D | L75: fixed
A76: A63 | B76: Gross margin on Clay revenue | C76: % | D76: 0.55 | E76: 0.65 | F76: 0.72 | G76: 0.55 | H76: 0.65 | I76: 0.72 | J76: =INDEX(D76:I76,1,(Assumptions!$D$5-1)*3+Assumptions!$D$4) -> 0.65 | K76: D | L76: value | M76: No reported figure; data-heavy margins (S52)
A77: A64 | B77: Launch marketing per wave | C77: $ | D77: 40000 | E77: 40000 | F77: 40000 | G77: 40000 | H77: 40000 | I77: 40000 | J77: =INDEX(D77:I77,1,(Assumptions!$D$5-1)*3+Assumptions!$D$4) -> 40000 | K77: D | L77: fixed
A78: A65 | B78: Program spend embedded in the base inbound rate | C78: $/qtr | D78: 25000 | E78: 25000 | F78: 25000 | G78: 25000 | H78: 25000 | I78: 25000 | J78: =INDEX(D78:I78,1,(Assumptions!$D$5-1)*3+Assumptions!$D$4) -> 25000 | K78: D | L78: fixed | M78: Spend above this buys extra MQLs at the CPL
A79: A66 | B79: Partner fee on partner-sourced first-year ACV | C79: % | D79: 0.25 | E79: 0.2 | F79: 0.15 | G79: 0.25 | H79: 0.2 | I79: 0.15 | J79: =INDEX(D79:I79,1,(Assumptions!$D$5-1)*3+Assumptions!$D$4) -> 0.2 | K79: B | L79: cost | M79: S50
A80: A67 | B80: Enablement per active partner per quarter | C80: $/qtr | D80: 2000 | E80: 2000 | F80: 2000 | G80: 2000 | H80: 2000 | I80: 2000 | J80: =INDEX(D80:I80,1,(Assumptions!$D$5-1)*3+Assumptions!$D$4) -> 2000 | K80: D | L80: fixed
A81: A68 | B81: Onboarding subsidy, MM & Ent (% first-year ACV) | C81: % | D81: 0.2 | E81: 0.15 | F81: 0.1 | G81: 0.1 | H81: 0.07 | I81: 0.05 | J81: =INDEX(D81:I81,1,(Assumptions!$D$5-1)*3+Assumptions!$D$4) -> 0.15 | K81: B/D | L81: cost | M81: S50; PS buyers need less help (adoption fit 4.5 vs 2.0)
A82: A69 | B82: Template & connector build (one-time) | C82: $ | D82: 250000 | E82: 250000 | F82: 250000 | G82: 250000 | H82: 250000 | I82: 250000 | J82: =INDEX(D82:I82,1,(Assumptions!$D$5-1)*3+Assumptions!$D$4) -> 250000 | K82: D | L82: fixed
A83: A70 | B83: Quarters over which build is spent | C83: qtrs | D83: 4 | E83: 4 | F83: 4 | G83: 4 | H83: 4 | I83: 4 | J83: =INDEX(D83:I83,1,(Assumptions!$D$5-1)*3+Assumptions!$D$4) -> 4 | K83: D | L83: fixed
A84: A71 | B84: Program stop quarter (99 = never; 4 = stopped at Gate 1) | C84: qtr | D84: 99 | E84: 99 | F84: 99 | G84: 99 | H84: 99 | I84: 99 | J84: =INDEX(D84:I84,1,(Assumptions!$D$5-1)*3+Assumptions!$D$4) -> 99 | K84: D | L84: fixed
A85: A72 | B85: Years of post-2029 value from the 2029 ARR base | C85: yrs | D85: 5 | E85: 5 | F85: 5 | G85: 5 | H85: 5 | I85: 5 | J85: =INDEX(D85:I85,1,(Assumptions!$D$5-1)*3+Assumptions!$D$4) -> 5 | K85: D | L85: fixed
A86: VALUATION, INCREMENTALITY AND OPTION 0
A87: A73 | B87: Discount rate (hurdle) for NPV | C87: % | D87: 0.12 | E87: 0.12 | F87: 0.12 | G87: 0.12 | H87: 0.12 | I87: 0.12 | J87: =INDEX(D87:I87,1,(Assumptions!$D$5-1)*3+Assumptions!$D$4) -> 0.12 | K87: D | L87: fixed | M87: Typical growth-software hurdle; tested 8–15% on Sensitivity
A88: A74 | B88: Incrementality haircut: share of program wins that would have happened anyway | C88: % | D88: 0.3 | E88: 0.2 | F88: 0.1 | G88: 0.6 | H88: 0.45 | I88: 0.3 | J88: =INDEX(D88:I88,1,(Assumptions!$D$5-1)*3+Assumptions!$D$4) -> 0.2 | K88: D | L88: indep | M88: Dist: few organic distributor wins (one case study). PS: Clay already markets to and sells in PS (S06, S32, S34)
A89: A75 | B89: Option 0: CAC payback of marginal spend in Clay's core motion | C89: months | D89: 16 | E89: 16 | F89: 16 | G89: 16 | H89: 16 | I89: 16 | J89: =INDEX(D89:I89,1,(Assumptions!$D$5-1)*3+Assumptions!$D$4) -> 16 | K89: B | L89: fixed | M89: Mid-market benchmark 14–18 months (S47)
A90: A76 | B90: Option 0: marginal efficiency vs benchmark (diminishing returns) | C90: x | D90: 0.6 | E90: 0.6 | F90: 0.6 | G90: 0.6 | H90: 0.6 | I90: 0.6 | J90: =INDEX(D90:I90,1,(Assumptions!$D$5-1)*3+Assumptions!$D$4) -> 0.6 | K90: D | L90: fixed | M90: Core already funded; marginal $ assumed 40% less efficient than average
A91: A77 | B91: Option 0: GRR of core customers | C91: % | D91: 0.9 | E91: 0.9 | F91: 0.9 | G91: 0.9 | H91: 0.9 | I91: 0.9 | J91: =INDEX(D91:I91,1,(Assumptions!$D$5-1)*3+Assumptions!$D$4) -> 0.9 | K91: B | L91: fixed | M91: SaaS Capital median 91% (S43)
A92: A78 | B92: Option 0: NRR of core customers | C92: % | D92: 1.01 | E92: 1.01 | F92: 1.01 | G92: 1.01 | H92: 1.01 | I92: 1.01 | J92: =INDEX(D92:I92,1,(Assumptions!$D$5-1)*3+Assumptions!$D$4) -> 1.01 | K92: B | L92: fixed | M92: SaaS Capital median 101% (S43)
A93: A79 | B93: Option 0: customer-success cost as % of ARR | C93: % | D93: 0.05 | E93: 0.05 | F93: 0.05 | G93: 0.05 | H93: 0.05 | I93: 0.05 | J93: =INDEX(D93:I93,1,(Assumptions!$D$5-1)*3+Assumptions!$D$4) -> 0.05 | K93: D | L93: fixed
A95: MOTION DESIGN (team, programs, scope)
A96: ID | B96: Input | C96: Unit | D96: Lean pilot | E96: Sales-led | F96: Solution play | J96: Live | K96: Class | M96: Rationale
A97: M1 | B97: Vertical lead (FTE) | C97: FTE | D97: 1 | E97: 1 | F97: 0 | J97: =INDEX(D97:F97,1,Assumptions!$D$6) -> 1 | K97: D/E | M97: Owns the vertical P&L; none in the solution play
A98: M2 | B98: Partner managers — 2027 (FTE) | C98: FTE | D98: 0 | E98: 1 | F98: 0 | J98: =INDEX(D98:F98,1,Assumptions!$D$6) -> 0 | K98: D/E
A99: M3 | B99: Partner managers — 2028+ (FTE) | C99: FTE | D99: 0.5 | E99: 1 | F99: 0 | J99: =INDEX(D99:F99,1,Assumptions!$D$6) -> 0.5 | K99: D/E
A100: M4 | B100: GTM / solutions engineers — 2027 (FTE) | C100: FTE | D100: 1 | E100: 1 | F100: 0.5 | J100: =INDEX(D100:F100,1,Assumptions!$D$6) -> 1 | K100: D/E
A101: M5 | B101: GTM / solutions engineers — 2028+ (FTE) | C101: FTE | D101: 0.5 | E101: 0.5 | F101: 0.25 | J101: =INDEX(D101:F101,1,Assumptions!$D$6) -> 0.5 | K101: D/E
A102: M6 | B102: Product marketing (FTE) | C102: FTE | D102: 0.25 | E102: 0.5 | F102: 0.1 | J102: =INDEX(D102:F102,1,Assumptions!$D$6) -> 0.25 | K102: D/E
A103: M7 | B103: Program marketing per quarter | C103: $ | D103: 25000 | E103: 60000 | F103: 10000 | J103: =INDEX(D103:F103,1,Assumptions!$D$6) -> 25000 | K103: D/E | M103: Above $25K buys extra MQLs at the CPL (diminishing); below $25K scales inbound down
...

Sheet Market Sizing
A1: Market Sizing — unique firms with 20+ employees by wave and size band (Census 2022, S14)
A2: Distribution waves: 4236 electrical → 4237 PHVAC → 4238 machinery/MRO. Professional-services waves: 5413 A&E → 5416 consulting → 5415 IT services (5418 advertising/PR excluded: Clay's agency partner channel). Firms, not establishments.
A4: NAICS | B4: Sub-industry | C4: Firms 20–49 | D4: 50–99 | E4: 100–249 | F4: 250–499 | G4: 500+ | H4: Emp. 20–49 | I4: 50–99 | J4: 100–249 | K4: 250–499 | L4: 500+
A5: 4236 | B5: Electrical & electronic goods wholesalers | C5: 1408 | D5: 570 | E5: 350 | F5: 136 | G5: 114 | H5: 42698 | I5: 39297 | J5: 54183 | K5: 47492 | L5: 315093
A6: 4237 | B6: Hardware, plumbing & HVAC wholesalers | C6: 1013 | D6: 424 | E6: 242 | F6: 85 | G6: 57 | H6: 31260 | I6: 29270 | J6: 36995 | K6: 29008 | L6: 116895
A7: 4238 | B7: Machinery, equipment & supplies wholesalers | C7: 3622 | D7: 1218 | E7: 746 | F7: 240 | G7: 183 | H7: 110129 | I7: 83565 | J7: 115979 | K7: 83365 | L7: 220621
A8: 5413 | B8: Architectural & engineering services | C8: 5930 | D8: 2104 | E8: 1251 | F8: 429 | G8: 387 | H8: 179028 | I8: 145073 | J8: 189979 | K8: 149368 | L8: 727292
A9: 5416 | B9: Management & technical consulting | C9: 5789 | D9: 2151 | E9: 1244 | F9: 430 | G9: 339 | H9: 174222 | I9: 148901 | J9: 188821 | K9: 149492 | L9: 677207
A10: 5415 | B10: Computer systems design (IT services) | C10: 5831 | D10: 2359 | E10: 1581 | F10: 561 | G10: 447 | H10: 179046 | I10: 164769 | J10: 240853 | K10: 195289 | L10: 1156449
A12: De-duplication factor by band (sector firms ÷ Σ sub-industry firms)
A13: DIST | B13: Sector 423 (50–499 not measurable: suppressed cells → 1.0) | C13: 0.973 | D13: 1 | E13: 1 | F13: 1 | G13: 1
A14: PS | B14: Sector 54 | C14: 0.988 | D14: 0.979 | E14: 0.967 | F14: 0.951 | G14: 0.972
A16: Wave | B16: Sub-industry | C16: SMB 20–99 | D16: Mid-Market 100–499 | E16: Enterprise 500+ | F16: Total
A17: DIST W1 | B17: =B5 -> Electrical & electronic goods wholesalers | C17: =C5*C$13+D5*D$13 -> 1939.984 | D17: =E5*E$13+F5*F$13 -> 486 | E17: =G5*G$13 -> 114 | F17: =SUM(C17:E17) -> 2539.984
A18: DIST W2 | B18: =B6 -> Hardware, plumbing & HVAC wholesalers | C18: =C6*C$13+D6*D$13 -> 1409.649 | D18: =E6*E$13+F6*F$13 -> 327 | E18: =G6*G$13 -> 57 | F18: =SUM(C18:E18) -> 1793.649
A19: DIST W3 | B19: =B7 -> Machinery, equipment & supplies wholesalers | C19: =C7*C$13+D7*D$13 -> 4742.206 | D19: =E7*E$13+F7*F$13 -> 986 | E19: =G7*G$13 -> 183 | F19: =SUM(C19:E19) -> 5911.206
A20: PS W1 | B20: =B8 -> Architectural & engineering services | C20: =C8*C$14+D8*D$14 -> 7918.656 | D20: =E8*E$14+F8*F$14 -> 1617.696 | E20: =G8*G$14 -> 376.164 | F20: =SUM(C20:E20) -> 9912.516
A21: PS W2 | B21: =B9 -> Management & technical consulting | C21: =C9*C$14+D9*D$14 -> 7825.361 | D21: =E9*E$14+F9*F$14 -> 1611.878 | E21: =G9*G$14 -> 329.508 | F21: =SUM(C21:E21) -> 9766.747
A22: PS W3 | B22: =B10 -> Computer systems design (IT services) | C22: =C10*C$14+D10*D$14 -> 8070.489 | D22: =E10*E$14+F10*F$14 -> 2062.338 | E22: =G10*G$14 -> 434.484 | F22: =SUM(C22:E22) -> 10567.311
A24: Segment | B24: Band | C24: Firms (3 waves) | D24: Employees | E24: Avg employees per firm
A25: Industrial distribution | B25: SMB 20–99 | C25: =C5+C6+C7+D5+D6+D7 -> 8255 | D25: =H5+H6+H7+I5+I6+I7 -> 336219 | E25: =D25/C25 -> 40.729134
A26: Industrial distribution | B26: Mid-Market 100–499 | C26: =E5+E6+E7+F5+F6+F7 -> 1799 | D26: =J5+J6+J7+K5+K6+K7 -> 367022 | E26: =D26/C26 -> 204.01445
A27: Industrial distribution | B27: Enterprise 500+ | C27: =G5+G6+G7 -> 354 | D27: =L5+L6+L7 -> 652609 | E27: =D27/C27 -> 1843.5282
A28: Professional services | B28: SMB 20–99 | C28: =C8+C9+C10+D8+D9+D10 -> 24164 | D28: =H8+H9+H10+I8+I9+I10 -> 991039 | E28: =D28/C28 -> 41.013036
A29: Professional services | B29: Mid-Market 100–499 | C29: =E8+E9+E10+F8+F9+F10 -> 5496 | D29: =J8+J9+J10+K8+K9+K10 -> 1113802 | E29: =D29/C29 -> 202.65684
A30: Professional services | B30: Enterprise 500+ | C30: =G8+G9+G10 -> 1173 | D30: =L8+L9+L10 -> 2560948 | E30: =D30/C30 -> 2183.2464
A32: Serviceable accounts (SAM) are computed inside each model run as firms × filter 1 × filter 2 × (1 − existing Clay customers), with the filters fixed across scenarios (v2, review M1/M2). Known limitation (review M3): Census sizes firms by total firm employment, and NAICS wholesale includes manufacturers' sales branches, so 500+ 'distributors' include manufacturers' sales arms: 4–22% of the band per Census type of operation (02 Firm_Counts Block 7). Removing them moves the lean-pilot Base NPV by −$0.01M to −$0.03M (appendix/msbo_sensitivity.py).

Sheet ACV Build
A1: ACV Build — usage-based first-year ACV by segment, band and scenario
A2: Sellers per firm × accounts tracked × Clay's published usage meters (S01). SMB/Mid-Market floored at the Growth plan; Enterprise floored at the Enterprise minimum, less discount.
A4: Band | B4: Dist: Downside | C4: Dist: Base | D4: Dist: Upside | E4: PS: Downside | F4: PS: Base | G4: PS: Upside | H4: Live
A5: SMB (20–99) | B5: =MAX((Assumptions!$D$51+Assumptions!$D$53)*12,(((('Market Sizing'!$E$25*Assumptions!$D$41*Assumptions!$D$42*Assumptions!$D$43)*Assumptions!$D$44)*Assumptions!$D$45*Assumptions!$D$46+('Market Sizing'!$E$25*Assumptions!$D$41*Assumptions!$D$42*Assumptions!$D$43)*Assumptions!$D$47+('Market Sizing'!$E$25*Assumptions!$D$41*Assumptions!$D$42*Assumptions!$D$43)*Assumptions!$D$48*Assumptions!$D$49)*(Assumptions!$D$51*12/Assumptions!$D$52)+((('Market Sizing'!$E$25*Assumptions!$D$41*Assumptions!$D$42*Assumptions!$D$43)*Assumptions!$D$44)*Assumptions!$D$45+('Market Sizing'!$E$25*Assumptions!$D$41*Assumptions!$D$42*Assumptions!$D$43)+('Market Sizing'!$E$25*Assumptions!$D$41*Assumptions!$D$42*Assumptions!$D$43)*Assumptions!$D$48)*Assumptions!$D$50*(Assumptions!$D$53*12/Assumptions!$D$54))) -> 5352 | C5: =MAX((Assumptions!$E$51+Assumptions!$E$53)*12,(((('Market Sizing'!$E$25*Assumptions!$E$41*Assumptions!$E$42*Assumptions!$E$43)*Assumptions!$E$44)*Assumptions!$E$45*Assumptions!$E$46+('Market Sizing'!$E$25*Assumptions!$E$41*Assumptions!$E$42*Assumptions!$E$43)*Assumptions!$E$47+('Market Sizing'!$E$25*Assumptions!$E$41*Assumptions!$E$42*Assumptions!$E$43)*Assumptions!$E$48*Assumptions!$E$49)*(Assumptions!$E$51*12/Assumptions!$E$52)+((('Market Sizing'!$E$25*Assumptions!$E$41*Assumptions!$E$42*Assumptions!$E$43)*Assumptions!$E$44)*Assumptions!$E$45+('Market Sizing'!$E$25*Assumptions!$E$41*Assumptions!$E$42*Assumptions!$E$43)+('Market Sizing'!$E$25*Assumptions!$E$41*Assumptions!$E$42*Assumptions!$E$43)*Assumptions!$E$48)*Assumptions!$E$50*(Assumptions!$E$53*12/Assumptions!$E$54))) -> 5352 | D5: =MAX((Assumptions!$F$51+Assumptions!$F$53)*12,(((('Market Sizing'!$E$25*Assumptions!$F$41*Assumptions!$F$42*Assumptions!$F$43)*Assumptions!$F$44)*Assumptions!$F$45*Assumptions!$F$46+('Market Sizing'!$E$25*Assumptions!$F$41*Assumptions!$F$42*Assumptions!$F$43)*Assumptions!$F$47+('Market Sizing'!$E$25*Assumptions!$F$41*Assumptions!$F$42*Assumptions!$F$43)*Assumptions!$F$48*Assumptions!$F$49)*(Assumptions!$F$51*12/Assumptions!$F$52)+((('Market Sizing'!$E$25*Assumptions!$F$41*Assumptions!$F$42*Assumptions!$F$43)*Assumptions!$F$44)*Assumptions!$F$45+('Market Sizing'!$E$25*Assumptions!$F$41*Assumptions!$F$42*Assumptions!$F$43)+('Market Sizing'!$E$25*Assumptions!$F$41*Assumptions!$F$42*Assumptions!$F$43)*Assumptions!$F$48)*Assumptions!$F$50*(Assumptions!$F$53*12/Assumptions!$F$54))) -> 5352 | E5: =MAX((Assumptions!$G$51+Assumptions!$G$53)*12,(((('Market Sizing'!$E$28*Assumptions!$G$41*Assumptions!$G$42*Assumptions!$G$43)*Assumptions!$G$44)*Assumptions!$G$45*Assumptions!$G$46+('Market Sizing'!$E$28*Assumptions!$G$41*Assumptions!$G$42*Assumptions!$G$43)*Assumptions!$G$47+('Market Sizing'!$E$28*Assumptions!$G$41*Assumptions!$G$42*Assumptions!$G$43)*Assumptions!$G$48*Assumptions!$G$49)*(Assumptions!$G$51*12/Assumptions!$G$52)+((('Market Sizing'!$E$28*Assumptions!$G$41*Assumptions!$G$42*Assumptions!$G$43)*Assumptions!$G$44)*Assumptions!$G$45+('Market Sizing'!$E$28*Assumptions!$G$41*Assumptions!$G$42*Assumptions!$G$43)+('Market Sizing'!$E$28*Assumptions!$G$41*Assumptions!$G$42*Assumptions!$G$43)*Assumptions!$G$48)*Assumptions!$G$50*(Assumptions!$G$53*12/Assumptions!$G$54))) -> 5352 | F5: =MAX((Assumptions!$H$51+Assumptions!$H$53)*12,(((('Market Sizing'!$E$28*Assumptions!$H$41*Assumptions!$H$42*Assumptions!$H$43)*Assumptions!$H$44)*Assumptions!$H$45*Assumptions!$H$46+('Market Sizing'!$E$28*Assumptions!$H$41*Assumptions!$H$42*Assumptions!$H$43)*Assumptions!$H$47+('Market Sizing'!$E$28*Assumptions!$H$41*Assumptions!$H$42*Assumptions!$H$43)*Assumptions!$H$48*Assumptions!$H$49)*(Assumptions!$H$51*12/Assumptions!$H$52)+((('Market Sizing'!$E$28*Assumptions!$H$41*Assumptions!$H$42*Assumptions!$H$43)*Assumptions!$H$44)*Assumptions!$H$45+('Market Sizing'!$E$28*Assumptions!$H$41*Assumptions!$H$42*Assumptions!$H$43)+('Market Sizing'!$E$28*Assumptions!$H$41*Assumptions!$H$42*Assumptions!$H$43)*Assumptions!$H$48)*Assumptions!$H$50*(Assumptions!$H$53*12/Assumptions!$H$54))) -> 5352 | G5: =MAX((Assumptions!$I$51+Assumptions!$I$53)*12,(((('Market Sizing'!$E$28*Assumptions!$I$41*Assumptions!$I$42*Assumptions!$I$43)*Assumptions!$I$44)*Assumptions!$I$45*Assumptions!$I$46+('Market Sizing'!$E$28*Assumptions!$I$41*Assumptions!$I$42*Assumptions!$I$43)*Assumptions!$I$47+('Market Sizing'!$E$28*Assumptions!$I$41*Assumptions!$I$42*Assumptions!$I$43)*Assumptions!$I$48*Assumptions!$I$49)*(Assumptions!$I$51*12/Assumptions!$I$52)+((('Market Sizing'!$E$28*Assumptions!$I$41*Assumptions!$I$42*Assumptions!$I$43)*Assumptions!$I$44)*Assumptions!$I$45+('Market Sizing'!$E$28*Assumptions!$I$41*Assumptions!$I$42*Assumptions!$I$43)+('Market Sizing'!$E$28*Assumptions!$I$41*Assumptions!$I$42*Assumptions!$I$43)*Assumptions!$I$48)*Assumptions!$I$50*(Assumptions!$I$53*12/Assumptions!$I$54))) -> 5352 | H5: =INDEX(B5:G5,1,(Assumptions!$D$5-1)*3+Assumptions!$D$4) -> 5352
A6: Mid-Market (100–499) | B6: =MAX((Assumptions!$D$51+Assumptions!$D$53)*12,(((('Market Sizing'!$E$26*Assumptions!$D$41*Assumptions!$D$42*Assumptions!$D$43)*Assumptions!$D$44)*Assumptions!$D$45*Assumptions!$D$46+('Market Sizing'!$E$26*Assumptions!$D$41*Assumptions!$D$42*Assumptions!$D$43)*Assumptions!$D$47+('Market Sizing'!$E$26*Assumptions!$D$41*Assumptions!$D$42*Assumptions!$D$43)*Assumptions!$D$48*Assumptions!$D$49)*(Assumptions!$D$51*12/Assumptions!$D$52)+((('Market Sizing'!$E$26*Assumptions!$D$41*Assumptions!$D$42*Assumptions!$D$43)*Assumptions!$D$44)*Assumptions!$D$45+('Market Sizing'!$E$26*Assumptions!$D$41*Assumptions!$D$42*Assumptions!$D$43)+('Market Sizing'!$E$26*Assumptions!$D$41*Assumptions!$D$42*Assumptions!$D$43)*Assumptions!$D$48)*Assumptions!$D$50*(Assumptions!$D$53*12/Assumptions!$D$54))) -> 7325.0401 | C6: =MAX((Assumptions!$E$51+Assumptions!$E$53)*12,(((('Market Sizing'!$E$26*Assumptions!$E$41*Assumptions!$E$42*Assumptions!$E$43)*Assumptions!$E$44)*Assumptions!$E$45*Assumptions!$E$46+('Market Sizing'!$E$26*Assumptions!$E$41*Assumptions!$E$42*Assumptions!$E$43)*Assumptions!$E$47+('Market Sizing'!$E$26*Assumptions!$E$41*Assumptions!$E$42*Assumptions!$E$43)*Assumptions!$E$48*Assumptions!$E$49)*(Assumptions!$E$51*12/Assumptions!$E$52)+((('Market Sizing'!$E$26*Assumptions!$E$41*Assumptions!$E$42*Assumptions!$E$43)*Assumptions!$E$44)*Assumptions!$E$45+('Market Sizing'!$E$26*Assumptions!$E$41*Assumptions!$E$42*Assumptions!$E$43)+('Market Sizing'!$E$26*Assumptions!$E$41*Assumptions!$E$42*Assumptions!$E$43)*Assumptions!$E$48)*Assumptions!$E$50*(Assumptions!$E$53*12/Assumptions!$E$54))) -> 9766.7201 | D6: =MAX((Assumptions!$F$51+Assumptions!$F$53)*12,(((('Market Sizing'!$E$26*Assumptions!$F$41*Assumptions!$F$42*Assumptions!$F$43)*Assumptions!$F$44)*Assumptions!$F$45*Assumptions!$F$46+('Market Sizing'!$E$26*Assumptions!$F$41*Assumptions!$F$42*Assumptions!$F$43)*Assumptions!$F$47+('Market Sizing'!$E$26*Assumptions!$F$41*Assumptions!$F$42*Assumptions!$F$43)*Assumptions!$F$48*Assumptions!$F$49)*(Assumptions!$F$51*12/Assumptions!$F$52)+((('Market Sizing'!$E$26*Assumptions!$F$41*Assumptions!$F$42*Assumptions!$F$43)*Assumptions!$F$44)*Assumptions!$F$45+('Market Sizing'!$E$26*Assumptions!$F$41*Assumptions!$F$42*Assumptions!$F$43)+('Market Sizing'!$E$26*Assumptions!$F$41*Assumptions!$F$42*Assumptions!$F$43)*Assumptions!$F$48)*Assumptions!$F$50*(Assumptions!$F$53*12/Assumptions!$F$54))) -> 14650.08 | E6: =MAX((Assumptions!$G$51+Assumptions!$G$53)*12,(((('Market Sizing'!$E$29*Assumptions!$G$41*Assumptions!$G$42*Assumptions!$G$43)*Assumptions!$G$44)*Assumptions!$G$45*Assumptions!$G$46+('Market Sizing'!$E$29*Assumptions!$G$41*Assumptions!$G$42*Assumptions!$G$43)*Assumptions!$G$47+('Market Sizing'!$E$29*Assumptions!$G$41*Assumptions!$G$42*Assumptions!$G$43)*Assumptions!$G$48*Assumptions!$G$49)*(Assumptions!$G$51*12/Assumptions!$G$52)+((('Market Sizing'!$E$29*Assumptions!$G$41*Assumptions!$G$42*Assumptions!$G$43)*Assumptions!$G$44)*Assumptions!$G$45+('Market Sizing'!$E$29*Assumptions!$G$41*Assumptions!$G$42*Assumptions!$G$43)+('Market Sizing'!$E$29*Assumptions!$G$41*Assumptions!$G$42*Assumptions!$G$43)*Assumptions!$G$48)*Assumptions!$G$50*(Assumptions!$G$53*12/Assumptions!$G$54))) -> 5352 | F6: =MAX((Assumptions!$H$51+Assumptions!$H$53)*12,(((('Market Sizing'!$E$29*Assumptions!$H$41*Assumptions!$H$42*Assumptions!$H$43)*Assumptions!$H$44)*Assumptions!$H$45*Assumptions!$H$46+('Market Sizing'!$E$29*Assumptions!$H$41*Assumptions!$H$42*Assumptions!$H$43)*Assumptions!$H$47+('Market Sizing'!$E$29*Assumptions!$H$41*Assumptions!$H$42*Assumptions!$H$43)*Assumptions!$H$48*Assumptions!$H$49)*(Assumptions!$H$51*12/Assumptions!$H$52)+((('Market Sizing'!$E$29*Assumptions!$H$41*Assumptions!$H$42*Assumptions!$H$43)*Assumptions!$H$44)*Assumptions!$H$45+('Market Sizing'!$E$29*Assumptions!$H$41*Assumptions!$H$42*Assumptions!$H$43)+('Market Sizing'!$E$29*Assumptions!$H$41*Assumptions!$H$42*Assumptions!$H$43)*Assumptions!$H$48)*Assumptions!$H$50*(Assumptions!$H$53*12/Assumptions!$H$54))) -> 5352 | G6: =MAX((Assumptions!$I$51+Assumptions!$I$53)*12,(((('Market Sizing'!$E$29*Assumptions!$I$41*Assumptions!$I$42*Assumptions!$I$43)*Assumptions!$I$44)*Assumptions!$I$45*Assumptions!$I$46+('Market Sizing'!$E$29*Assumptions!$I$41*Assumptions!$I$42*Assumptions!$I$43)*Assumptions!$I$47+('Market Sizing'!$E$29*Assumptions!$I$41*Assumptions!$I$42*Assumptions!$I$43)*Assumptions!$I$48*Assumptions!$I$49)*(Assumptions!$I$51*12/Assumptions!$I$52)+((('Market Sizing'!$E$29*Assumptions!$I$41*Assumptions!$I$42*Assumptions!$I$43)*Assumptions!$I$44)*Assumptions!$I$45+('Market Sizing'!$E$29*Assumptions!$I$41*Assumptions!$I$42*Assumptions!$I$43)+('Market Sizing'!$E$29*Assumptions!$I$41*Assumptions!$I$42*Assumptions!$I$43)*Assumptions!$I$48)*Assumptions!$I$50*(Assumptions!$I$53*12/Assumptions!$I$54))) -> 5352 | H6: =INDEX(B6:G6,1,(Assumptions!$D$5-1)*3+Assumptions!$D$4) -> 9766.7201
A7: Enterprise (500+) | B7: =MAX(Assumptions!$D$55*(Assumptions!$D$51*12/Assumptions!$D$52)+Assumptions!$D$56*(Assumptions!$D$53*12/Assumptions!$D$54),(((('Market Sizing'!$E$27*Assumptions!$D$41*Assumptions!$D$42*Assumptions!$D$43)*Assumptions!$D$44)*Assumptions!$D$45*Assumptions!$D$46+('Market Sizing'!$E$27*Assumptions!$D$41*Assumptions!$D$42*Assumptions!$D$43)*Assumptions!$D$47+('Market Sizing'!$E$27*Assumptions!$D$41*Assumptions!$D$42*Assumptions!$D$43)*Assumptions!$D$48*Assumptions!$D$49)*(Assumptions!$D$51*12/Assumptions!$D$52)+((('Market Sizing'!$E$27*Assumptions!$D$41*Assumptions!$D$42*Assumptions!$D$43)*Assumptions!$D$44)*Assumptions!$D$45+('Market Sizing'!$E$27*Assumptions!$D$41*Assumptions!$D$42*Assumptions!$D$43)+('Market Sizing'!$E$27*Assumptions!$D$41*Assumptions!$D$42*Assumptions!$D$43)*Assumptions!$D$48)*Assumptions!$D$50*(Assumptions!$D$53*12/Assumptions!$D$54)))*(1-Assumptions!$D$57) -> 46333.692 | C7: =MAX(Assumptions!$E$55*(Assumptions!$E$51*12/Assumptions!$E$52)+Assumptions!$E$56*(Assumptions!$E$53*12/Assumptions!$E$54),(((('Market Sizing'!$E$27*Assumptions!$E$41*Assumptions!$E$42*Assumptions!$E$43)*Assumptions!$E$44)*Assumptions!$E$45*Assumptions!$E$46+('Market Sizing'!$E$27*Assumptions!$E$41*Assumptions!$E$42*Assumptions!$E$43)*Assumptions!$E$47+('Market Sizing'!$E$27*Assumptions!$E$41*Assumptions!$E$42*Assumptions!$E$43)*Assumptions!$E$48*Assumptions!$E$49)*(Assumptions!$E$51*12/Assumptions!$E$52)+((('Market Sizing'!$E$27*Assumptions!$E$41*Assumptions!$E$42*Assumptions!$E$43)*Assumptions!$E$44)*Assumptions!$E$45+('Market Sizing'!$E$27*Assumptions!$E$41*Assumptions!$E$42*Assumptions!$E$43)+('Market Sizing'!$E$27*Assumptions!$E$41*Assumptions!$E$42*Assumptions!$E$43)*Assumptions!$E$48)*Assumptions!$E$50*(Assumptions!$E$53*12/Assumptions!$E$54)))*(1-Assumptions!$E$57) -> 61778.256 | D7: =MAX(Assumptions!$F$55*(Assumptions!$F$51*12/Assumptions!$F$52)+Assumptions!$F$56*(Assumptions!$F$53*12/Assumptions!$F$54),(((('Market Sizing'!$E$27*Assumptions!$F$41*Assumptions!$F$42*Assumptions!$F$43)*Assumptions!$F$44)*Assumptions!$F$45*Assumptions!$F$46+('Market Sizing'!$E$27*Assumptions!$F$41*Assumptions!$F$42*Assumptions!$F$43)*Assumptions!$F$47+('Market Sizing'!$E$27*Assumptions!$F$41*Assumptions!$F$42*Assumptions!$F$43)*Assumptions!$F$48*Assumptions!$F$49)*(Assumptions!$F$51*12/Assumptions!$F$52)+((('Market Sizing'!$E$27*Assumptions!$F$41*Assumptions!$F$42*Assumptions!$F$43)*Assumptions!$F$44)*Assumptions!$F$45+('Market Sizing'!$E$27*Assumptions!$F$41*Assumptions!$F$42*Assumptions!$F$43)+('Market Sizing'!$E$27*Assumptions!$F$41*Assumptions!$F$42*Assumptions!$F$43)*Assumptions!$F$48)*Assumptions!$F$50*(Assumptions!$F$53*12/Assumptions!$F$54)))*(1-Assumptions!$F$57) -> 92667.384 | E7: =MAX(Assumptions!$G$55*(Assumptions!$G$51*12/Assumptions!$G$52)+Assumptions!$G$56*(Assumptions!$G$53*12/Assumptions!$G$54),(((('Market Sizing'!$E$30*Assumptions!$G$41*Assumptions!$G$42*Assumptions!$G$43)*Assumptions!$G$44)*Assumptions!$G$45*Assumptions!$G$46+('Market Sizing'!$E$30*Assumptions!$G$41*Assumptions!$G$42*Assumptions!$G$43)*Assumptions!$G$47+('Market Sizing'!$E$30*Assumptions!$G$41*Assumptions!$G$42*Assumptions!$G$43)*Assumptions!$G$48*Assumptions!$G$49)*(Assumptions!$G$51*12/Assumptions!$G$52)+((('Market Sizing'!$E$30*Assumptions!$G$41*Assumptions!$G$42*Assumptions!$G$43)*Assumptions!$G$44)*Assumptions!$G$45+('Market Sizing'!$E$30*Assumptions!$G$41*Assumptions!$G$42*Assumptions!$G$43)+('Market Sizing'!$E$30*Assumptions!$G$41*Assumptions!$G$42*Assumptions!$G$43)*Assumptions!$G$48)*Assumptions!$G$50*(Assumptions!$G$53*12/Assumptions!$G$54)))*(1-Assumptions!$G$57) -> 44310 | F7: =MAX(Assumptions!$H$55*(Assumptions!$H$51*12/Assumptions!$H$52)+Assumptions!$H$56*(Assumptions!$H$53*12/Assumptions!$H$54),(((('Market Sizing'!$E$30*Assumptions!$H$41*Assumptions!$H$42*Assumptions!$H$43)*Assumptions!$H$44)*Assumptions!$H$45*Assumptions!$H$46+('Market Sizing'!$E$30*Assumptions!$H$41*Assumptions!$H$42*Assumptions!$H$43)*Assumptions!$H$47+('Market Sizing'!$E$30*Assumptions!$H$41*Assumptions!$H$42*Assumptions!$H$43)*Assumptions!$H$48*Assumptions!$H$49)*(Assumptions!$H$51*12/Assumptions!$H$52)+((('Market Sizing'!$E$30*Assumptions!$H$41*Assumptions!$H$42*Assumptions!$H$43)*Assumptions!$H$44)*Assumptions!$H$45+('Market Sizing'!$E$30*Assumptions!$H$41*Assumptions!$H$42*Assumptions!$H$43)+('Market Sizing'!$E$30*Assumptions!$H$41*Assumptions!$H$42*Assumptions!$H$43)*Assumptions!$H$48)*Assumptions!$H$50*(Assumptions!$H$53*12/Assumptions!$H$54)))*(1-Assumptions!$H$57) -> 44310 | G7: =MAX(Assumptions!$I$55*(Assumptions!$I$51*12/Assumptions!$I$52)+Assumptions!$I$56*(Assumptions!$I$53*12/Assumptions!$I$54),(((('Market Sizing'!$E$30*Assumptions!$I$41*Assumptions!$I$42*Assumptions!$I$43)*Assumptions!$I$44)*Assumptions!$I$45*Assumptions!$I$46+('Market Sizing'!$E$30*Assumptions!$I$41*Assumptions!$I$42*Assumptions!$I$43)*Assumptions!$I$47+('Market Sizing'!$E$30*Assumptions!$I$41*Assumptions!$I$42*Assumptions!$I$43)*Assumptions!$I$48*Assumptions!$I$49)*(Assumptions!$I$51*12/Assumptions!$I$52)+((('Market Sizing'!$E$30*Assumptions!$I$41*Assumptions!$I$42*Assumptions!$I$43)*Assumptions!$I$44)*Assumptions!$I$45+('Market Sizing'!$E$30*Assumptions!$I$41*Assumptions!$I$42*Assumptions!$I$43)+('Market Sizing'!$E$30*Assumptions!$I$41*Assumptions!$I$42*Assumptions!$I$43)*Assumptions!$I$48)*Assumptions!$I$50*(Assumptions!$I$53*12/Assumptions!$I$54)))*(1-Assumptions!$I$57) -> 44310 | H7: =INDEX(B7:G7,1,(Assumptions!$D$5-1)*3+Assumptions!$D$4) -> 61778.256
A9: Sellers per firm (Base)
A10: SMB | C10: ='Market Sizing'!$E$25*Assumptions!$E$41 -> 8.9604094 | F10: ='Market Sizing'!$E$28*Assumptions!$H$41 -> 2.5428082
A11: Mid-Market | C11: ='Market Sizing'!$E$26*Assumptions!$E$41 -> 44.88318 | F11: ='Market Sizing'!$E$29*Assumptions!$H$41 -> 12.564724
A12: Enterprise | C12: ='Market Sizing'!$E$27*Assumptions!$E$41 -> 405.57621 | F12: ='Market Sizing'!$E$30*Assumptions!$H$41 -> 135.36128
A14: Reading: at list prices, a distributor's seller density lifts ACV above the Growth floor only from Mid-Market up. Professional-services firms have ~4× fewer sellers per firm, so their SMB and Mid-Market ACV both sit at the floor. Base Enterprise ACV for distribution ≈ Vendr's median Clay buyer ($59,996, S16).

Sheet GTM Funnel
A1: GTM Funnel — live model (selected segment, scenario and motion)
A2: Accounts → meetings, MQLs and partner introductions → opportunities (mix by band derived from accounts) → wins, with a closing-capacity constraint.
A3: ="Live run: "&Assumptions!$E$5&" · "&Assumptions!$E$4&" · "&Assumptions!$E$6 -> Live run: Industrial distribution · Base · Lean partner-led pilot
A5: Live model — run constants | B5: Unit / note | C5: Q1 2027 | D5: Q2 2027 | E5: Q3 2027 | F5: Q4 2027 | G5: Q1 2028 | H5: Q2 2028 | I5: Q3 2028 | J5: Q4 2028 | K5: Q1 2029 | L5: Q2 2029 | M5: Q3 2029 | N5: Q4 2029 | P5: 2027 | Q5: 2028 | R5: 2029 | S5: 2027–29
A6: SAM accounts — wave 1, S | B6: firms × filters | C6: =IF(Assumptions!$D$5=1,'Market Sizing'!$C$17,'Market Sizing'!$C$20)*Assumptions!$J$10*Assumptions!$J$11*(1-Assumptions!$J$12) -> 843.03945
A7: SAM accounts — wave 1, M | B7: firms × filters | C7: =IF(Assumptions!$D$5=1,'Market Sizing'!$D$17,'Market Sizing'!$D$20)*Assumptions!$J$10*Assumptions!$J$11*(1-Assumptions!$J$12) -> 211.19616
A8: SAM accounts — wave 1, E | B8: firms × filters | C8: =IF(Assumptions!$D$5=1,'Market Sizing'!$E$17,'Market Sizing'!$E$20)*Assumptions!$J$10*Assumptions!$J$11*(1-Assumptions!$J$12) -> 49.53984
A9: SAM accounts — wave 1, total | C9: =$C$6+$C$7+$C$8 -> 1103.7754
A10: SAM accounts — wave 2, S | B10: firms × filters | C10: =IF(Assumptions!$D$5=1,'Market Sizing'!$C$18,'Market Sizing'!$C$21)*Assumptions!$J$10*Assumptions!$J$11*(1-Assumptions!$J$12) -> 612.57707
A11: SAM accounts — wave 2, M | B11: firms × filters | C11: =IF(Assumptions!$D$5=1,'Market Sizing'!$D$18,'Market Sizing'!$D$21)*Assumptions!$J$10*Assumptions!$J$11*(1-Assumptions!$J$12) -> 142.10112
A12: SAM accounts — wave 2, E | B12: firms × filters | C12: =IF(Assumptions!$D$5=1,'Market Sizing'!$E$18,'Market Sizing'!$E$21)*Assumptions!$J$10*Assumptions!$J$11*(1-Assumptions!$J$12) -> 24.76992
A13: SAM accounts — wave 2, total | C13: =$C$10+$C$11+$C$12 -> 779.44811
A14: SAM accounts — wave 3, S | B14: firms × filters | C14: =IF(Assumptions!$D$5=1,'Market Sizing'!$C$19,'Market Sizing'!$C$22)*Assumptions!$J$10*Assumptions!$J$11*(1-Assumptions!$J$12) -> 2060.773
A15: SAM accounts — wave 3, M | B15: firms × filters | C15: =IF(Assumptions!$D$5=1,'Market Sizing'!$D$19,'Market Sizing'!$D$22)*Assumptions!$J$10*Assumptions!$J$11*(1-Assumptions!$J$12) -> 428.47616
A16: SAM accounts — wave 3, E | B16: firms × filters | C16: =IF(Assumptions!$D$5=1,'Market Sizing'!$E$19,'Market Sizing'!$E$22)*Assumptions!$J$10*Assumptions!$J$11*(1-Assumptions!$J$12) -> 79.52448
A17: SAM accounts — wave 3, total | C17: =$C$14+$C$15+$C$16 -> 2568.7737
A18: First-year ACV — S | B18: usage build | C18: =IF(Assumptions!$D$5=1,MAX((Assumptions!$J$51+Assumptions!$J$53)*12,(((('Market Sizing'!$E$25*Assumptions!$J$41*Assumptions!$J$42*Assumptions!$J$43)*Assumptions!$J$44)*Assumptions!$J$45*Assumptions!$J$46+('Market Sizing'!$E$25*Assumptions!$J$41*Assumptions!$J$42*Assumptions!$J$43)*Assumptions!$J$47+('Market Sizing'!$E$25*Assumptions!$J$41*Assumptions!$J$42*Assumptions!$J$43)*Assumptions!$J$48*Assumptions!$J$49)*(Assumptions!$J$51*12/Assumptions!$J$52)+((('Market Sizing'!$E$25*Assumptions!$J$41*Assumptions!$J$42*Assumptions!$J$43)*Assumptions!$J$44)*Assumptions!$J$45+('Market Sizing'!$E$25*Assumptions!$J$41*Assumptions!$J$42*Assumptions!$J$43)+('Market Sizing'!$E$25*Assumptions!$J$41*Assumptions!$J$42*Assumptions!$J$43)*Assumptions!$J$48)*Assumptions!$J$50*(Assumptions!$J$53*12/Assumptions!$J$54))),MAX((Assumptions!$J$51+Assumptions!$J$53)*12,(((('Market Sizing'!$E$28*Assumptions!$J$41*Assumptions!$J$42*Assumptions!$J$43)*Assumptions!$J$44)*Assumptions!$J$45*Assumptions!$J$46+('Market Sizing'!$E$28*Assumptions!$J$41*Assumptions!$J$42*Assumptions!$J$43)*Assumptions!$J$47+('Market Sizing'!$E$28*Assumptions!$J$41*Assumptions!$J$42*Assumptions!$J$43)*Assumptions!$J$48*Assumptions!$J$49)*(Assumptions!$J$51*12/Assumptions!$J$52)+((('Market Sizing'!$E$28*Assumptions!$J$41*Assumptions!$J$42*Assumptions!$J$43)*Assumptions!$J$44)*Assumptions!$J$45+('Market Sizing'!$E$28*Assumptions!$J$41*Assumptions!$J$42*Assumptions!$J$43)+('Market Sizing'!$E$28*Assumptions!$J$41*Assumptions!$J$42*Assumptions!$J$43)*Assumptions!$J$48)*Assumptions!$J$50*(Assumptions!$J$53*12/Assumptions!$J$54)))) -> 5352
A19: First-year ACV — M | B19: usage build | C19: =IF(Assumptions!$D$5=1,MAX((Assumptions!$J$51+Assumptions!$J$53)*12,(((('Market Sizing'!$E$26*Assumptions!$J$41*Assumptions!$J$42*Assumptions!$J$43)*Assumptions!$J$44)*Assumptions!$J$45*Assumptions!$J$46+('Market Sizing'!$E$26*Assumptions!$J$41*Assumptions!$J$42*Assumptions!$J$43)*Assumptions!$J$47+('Market Sizing'!$E$26*Assumptions!$J$41*Assumptions!$J$42*Assumptions!$J$43)*Assumptions!$J$48*Assumptions!$J$49)*(Assumptions!$J$51*12/Assumptions!$J$52)+((('Market Sizing'!$E$26*Assumptions!$J$41*Assumptions!$J$42*Assumptions!$J$43)*Assumptions!$J$44)*Assumptions!$J$45+('Market Sizing'!$E$26*Assumptions!$J$41*Assumptions!$J$42*Assumptions!$J$43)+('Market Sizing'!$E$26*Assumptions!$J$41*Assumptions!$J$42*Assumptions!$J$43)*Assumptions!$J$48)*Assumptions!$J$50*(Assumptions!$J$53*12/Assumptions!$J$54))),MAX((Assumptions!$J$51+Assumptions!$J$53)*12,(((('Market Sizing'!$E$29*Assumptions!$J$41*Assumptions!$J$42*Assumptions!$J$43)*Assumptions!$J$44)*Assumptions!$J$45*Assumptions!$J$46+('Market Sizing'!$E$29*Assumptions!$J$41*Assumptions!$J$42*Assumptions!$J$43)*Assumptions!$J$47+('Market Sizing'!$E$29*Assumptions!$J$41*Assumptions!$J$42*Assumptions!$J$43)*Assumptions!$J$48*Assumptions!$J$49)*(Assumptions!$J$51*12/Assumptions!$J$52)+((('Market Sizing'!$E$29*Assumptions!$J$41*Assumptions!$J$42*Assumptions!$J$43)*Assumptions!$J$44)*Assumptions!$J$45+('Market Sizing'!$E$29*Assumptions!$J$41*Assumptions!$J$42*Assumptions!$J$43)+('Market Sizing'!$E$29*Assumptions!$J$41*Assumptions!$J$42*Assumptions!$J$43)*Assumptions!$J$48)*Assumptions!$J$50*(Assumptions!$J$53*12/Assumptions!$J$54)))) -> 9766.7201
A20: First-year ACV — E | B20: usage build | C20: =IF(Assumptions!$D$5=1,MAX(Assumptions!$J$55*(Assumptions!$J$51*12/Assumptions!$J$52)+Assumptions!$J$56*(Assumptions!$J$53*12/Assumptions!$J$54),(((('Market Sizing'!$E$27*Assumptions!$J$41*Assumptions!$J$42*Assumptions!$J$43)*Assumptions!$J$44)*Assumptions!$J$45*Assumptions!$J$46+('Market Sizing'!$E$27*Assumptions!$J$41*Assumptions!$J$42*Assumptions!$J$43)*Assumptions!$J$47+('Market Sizing'!$E$27*Assumptions!$J$41*Assumptions!$J$42*Assumptions!$J$43)*Assumptions!$J$48*Assumptions!$J$49)*(Assumptions!$J$51*12/Assumptions!$J$52)+((('Market Sizing'!$E$27*Assumptions!$J$41*Assumptions!$J$42*Assumptions!$J$43)*Assumptions!$J$44)*Assumptions!$J$45+('Market Sizing'!$E$27*Assumptions!$J$41*Assumptions!$J$42*Assumptions!$J$43)+('Market Sizing'!$E$27*Assumptions!$J$41*Assumptions!$J$42*Assumptions!$J$43)*Assumptions!$J$48)*Assumptions!$J$50*(Assumptions!$J$53*12/Assumptions!$J$54)))*(1-Assumptions!$J$57),MAX(Assumptions!$J$55*(Assumptions!$J$51*12/Assumptions!$J$52)+Assumptions!$J$56*(Assumptions!$J$53*12/Assumptions!$J$54),(((('Market Sizing'!$E$30*Assumptions!$J$41*Assumptions!$J$42*Assumptions!$J$43)*Assumptions!$J$44)*Assumptions!$J$45*Assumptions!$J$46+('Market Sizing'!$E$30*Assumptions!$J$41*Assumptions!$J$42*Assumptions!$J$43)*Assumptions!$J$47+('Market Sizing'!$E$30*Assumptions!$J$41*Assumptions!$J$42*Assumptions!$J$43)*Assumptions!$J$48*Assumptions!$J$49)*(Assumptions!$J$51*12/Assumptions!$J$52)+((('Market Sizing'!$E$30*Assumptions!$J$41*Assumptions!$J$42*Assumptions!$J$43)*Assumptions!$J$44)*Assumptions!$J$45+('Market Sizing'!$E$30*Assumptions!$J$41*Assumptions!$J$42*Assumptions!$J$43)+('Market Sizing'!$E$30*Assumptions!$J$41*Assumptions!$J$42*Assumptions!$J$43)*Assumptions!$J$48)*Assumptions!$J$50*(Assumptions!$J$53*12/Assumptions!$J$54)))*(1-Assumptions!$J$57)) -> 61778.256
A21: Automated outbound coverage per quarter | B21: coverage × motion multiplier | C21: =Assumptions!$J$17*Assumptions!$J$106 -> 0.4
A22: AE fully loaded annual cost | B22: OTE ÷ wage share | C22: =Assumptions!$J$68/Assumptions!$J$69 -> 285714.29
A23: ARR one ramped AE closes per quarter | B23: quota × productivity ÷ 4 | C23: =Assumptions!$J$66*Assumptions!$J$67/4 -> 153125
A24: AE cost per $ of first-year ACV closed | C24: =$C$22/Assumptions!$J$66/Assumptions!$J$67 -> 0.4664723
A25: Program spend above base, per quarter | C25: =MAX(0,Assumptions!$J$103-Assumptions!$J$78) -> 0
A26: Demand and funnel | B26: Unit / note | C26: Q1 2027 | D26: Q2 2027 | E26: Q3 2027 | F26: Q4 2027 | G26: Q1 2028 | H26: Q2 2028 | I26: Q3 2028 | J26: Q4 2028 | K26: Q1 2029 | L26: Q2 2029 | M26: Q3 2029 | N26: Q4 2029 | P26: 2027 | Q26: 2028 | R26: 2029 | S26: 2027–29
A27: Quarter number | B27: # | C27: 1 | D27: 2 | E27: 3 | F27: 4 | G27: 5 | H27: 6 | I27: 7 | J27: 8 | K27: 9 | L27: 10 | M27: 11 | N27: 12
A28: Program running (1) / stopped (0) | B28: flag | C28: =IF(C27<=Assumptions!$J$84,1,0) -> 1 | D28: =IF(D27<=Assumptions!$J$84,1,0) -> 1 | E28: =IF(E27<=Assumptions!$J$84,1,0) -> 1 | F28: =IF(F27<=Assumptions!$J$84,1,0) -> 1 | G28: =IF(G27<=Assumptions!$J$84,1,0) -> 1 | H28: =IF(H27<=Assumptions!$J$84,1,0) -> 1 | I28: =IF(I27<=Assumptions!$J$84,1,0) -> 1 | J28: =IF(J27<=Assumptions!$J$84,1,0) -> 1 | ... N28: =IF(N27<=Assumptions!$J$84,1,0) -> 1
A29: Wave 1 active (0.5 in launch quarter) | B29: factor | C29: =IF(C27=Assumptions!$J$13,0.5,IF(C27>Assumptions!$J$13,1,0)) -> 0.5 | D29: =IF(D27=Assumptions!$J$13,0.5,IF(D27>Assumptions!$J$13,1,0)) -> 1 | E29: =IF(E27=Assumptions!$J$13,0.5,IF(E27>Assumptions!$J$13,1,0)) -> 1 | F29: =IF(F27=Assumptions!$J$13,0.5,IF(F27>Assumptions!$J$13,1,0)) -> 1 | G29: =IF(G27=Assumptions!$J$13,0.5,IF(G27>Assumptions!$J$13,1,0)) -> 1 | H29: =IF(H27=Assumptions!$J$13,0.5,IF(H27>Assumptions!$J$13,1,0)) -> 1 | I29: =IF(I27=Assumptions!$J$13,0.5,IF(I27>Assumptions!$J$13,1,0)) -> 1 | J29: =IF(J27=Assumptions!$J$13,0.5,IF(J27>Assumptions!$J$13,1,0)) -> 1 | ... N29: =IF(N27=Assumptions!$J$13,0.5,IF(N27>Assumptions!$J$13,1,0)) -> 1
A30: Wave 2 active (0.5 in launch quarter) | B30: factor | C30: =IF(C27=Assumptions!$J$14,0.5,IF(C27>Assumptions!$J$14,1,0)) -> 0 | D30: =IF(D27=Assumptions!$J$14,0.5,IF(D27>Assumptions!$J$14,1,0)) -> 0 | E30: =IF(E27=Assumptions!$J$14,0.5,IF(E27>Assumptions!$J$14,1,0)) -> 0 | F30: =IF(F27=Assumptions!$J$14,0.5,IF(F27>Assumptions!$J$14,1,0)) -> 0 | G30: =IF(G27=Assumptions!$J$14,0.5,IF(G27>Assumptions!$J$14,1,0)) -> 0.5 | H30: =IF(H27=Assumptions!$J$14,0.5,IF(H27>Assumptions!$J$14,1,0)) -> 1 | I30: =IF(I27=Assumptions!$J$14,0.5,IF(I27>Assumptions!$J$14,1,0)) -> 1 | J30: =IF(J27=Assumptions!$J$14,0.5,IF(J27>Assumptions!$J$14,1,0)) -> 1 | ... N30: =IF(N27=Assumptions!$J$14,0.5,IF(N27>Assumptions!$J$14,1,0)) -> 1
A31: Wave 3 active (0.5 in launch quarter) | B31: factor | C31: =IF(C27=Assumptions!$J$15,0.5,IF(C27>Assumptions!$J$15,1,0)) -> 0 | D31: =IF(D27=Assumptions!$J$15,0.5,IF(D27>Assumptions!$J$15,1,0)) -> 0 | E31: =IF(E27=Assumptions!$J$15,0.5,IF(E27>Assumptions!$J$15,1,0)) -> 0 | F31: =IF(F27=Assumptions!$J$15,0.5,IF(F27>Assumptions!$J$15,1,0)) -> 0 | G31: =IF(G27=Assumptions!$J$15,0.5,IF(G27>Assumptions!$J$15,1,0)) -> 0 | H31: =IF(H27=Assumptions!$J$15,0.5,IF(H27>Assumptions!$J$15,1,0)) -> 0 | I31: =IF(I27=Assumptions!$J$15,0.5,IF(I27>Assumptions!$J$15,1,0)) -> 0.5 | J31: =IF(J27=Assumptions!$J$15,0.5,IF(J27>Assumptions!$J$15,1,0)) -> 1 | ... N31: =IF(N27=Assumptions!$J$15,0.5,IF(N27>Assumptions!$J$15,1,0)) -> 1
A32: Wave 1 outbound fatigue factor | B32: factor | C32: =Assumptions!$J$21^(MAX(0,C27-Assumptions!$J$13)/4) -> 1 | D32: =Assumptions!$J$21^(MAX(0,D27-Assumptions!$J$13)/4) -> 0.93060486 | E32: =Assumptions!$J$21^(MAX(0,E27-Assumptions!$J$13)/4) -> 0.8660254 | F32: =Assumptions!$J$21^(MAX(0,F27-Assumptions!$J$13)/4) -> 0.80592745 | G32: =Assumptions!$J$21^(MAX(0,G27-Assumptions!$J$13)/4) -> 0.75 | H32: =Assumptions!$J$21^(MAX(0,H27-Assumptions!$J$13)/4) -> 0.69795364 | I32: =Assumptions!$J$21^(MAX(0,I27-Assumptions!$J$13)/4) -> 0.64951905 | J32: =Assumptions!$J$21^(MAX(0,J27-Assumptions!$J$13)/4) -> 0.60444559 | ... N32: =Assumptions!$J$21^(MAX(0,N27-Assumptions!$J$13)/4) -> 0.45333419
A33: Wave 2 outbound fatigue factor | B33: factor | C33: =Assumptions!$J$21^(MAX(0,C27-Assumptions!$J$14)/4) -> 1 | D33: =Assumptions!$J$21^(MAX(0,D27-Assumptions!$J$14)/4) -> 1 | E33: =Assumptions!$J$21^(MAX(0,E27-Assumptions!$J$14)/4) -> 1 | F33: =Assumptions!$J$21^(MAX(0,F27-Assumptions!$J$14)/4) -> 1 | G33: =Assumptions!$J$21^(MAX(0,G27-Assumptions!$J$14)/4) -> 1 | H33: =Assumptions!$J$21^(MAX(0,H27-Assumptions!$J$14)/4) -> 0.93060486 | I33: =Assumptions!$J$21^(MAX(0,I27-Assumptions!$J$14)/4) -> 0.8660254 | J33: =Assumptions!$J$21^(MAX(0,J27-Assumptions!$J$14)/4) -> 0.80592745 | ... N33: =Assumptions!$J$21^(MAX(0,N27-Assumptions!$J$14)/4) -> 0.60444559
A34: Wave 3 outbound fatigue factor | B34: factor | C34: =Assumptions!$J$21^(MAX(0,C27-Assumptions!$J$15)/4) -> 1 | D34: =Assumptions!$J$21^(MAX(0,D27-Assumptions!$J$15)/4) -> 1 | E34: =Assumptions!$J$21^(MAX(0,E27-Assumptions!$J$15)/4) -> 1 | F34: =Assumptions!$J$21^(MAX(0,F27-Assumptions!$J$15)/4) -> 1 | G34: =Assumptions!$J$21^(MAX(0,G27-Assumptions!$J$15)/4) -> 1 | H34: =Assumptions!$J$21^(MAX(0,H27-Assumptions!$J$15)/4) -> 1 | I34: =Assumptions!$J$21^(MAX(0,I27-Assumptions!$J$15)/4) -> 1 | J34: =Assumptions!$J$21^(MAX(0,J27-Assumptions!$J$15)/4) -> 0.93060486 | ... N34: =Assumptions!$J$21^(MAX(0,N27-Assumptions!$J$15)/4) -> 0.69795364
A35: Active SAM accounts — S | B35: accounts | C35: =$C$6*C29+$C$10*C30+$C$14*C31 -> 421.51972 | D35: =$C$6*D29+$C$10*D30+$C$14*D31 -> 843.03945 | E35: =$C$6*E29+$C$10*E30+$C$14*E31 -> 843.03945 | F35: =$C$6*F29+$C$10*F30+$C$14*F31 -> 843.03945 | G35: =$C$6*G29+$C$10*G30+$C$14*G31 -> 1149.328 | H35: =$C$6*H29+$C$10*H30+$C$14*H31 -> 1455.6165 | I35: =$C$6*I29+$C$10*I30+$C$14*I31 -> 2486.003 | J35: =$C$6*J29+$C$10*J30+$C$14*J31 -> 3516.3896 | ... N35: =$C$6*N29+$C$10*N30+$C$14*N31 -> 3516.3896 | P35: =F35 -> 843.03945 | Q35: =J35 -> 3516.3896 | R35: =N35 -> 3516.3896 | S35: =R35 -> 3516.3896
A36: Active SAM accounts — M | B36: accounts | C36: =$C$7*C29+$C$11*C30+$C$15*C31 -> 105.59808 | D36: =$C$7*D29+$C$11*D30+$C$15*D31 -> 211.19616 | E36: =$C$7*E29+$C$11*E30+$C$15*E31 -> 211.19616 | F36: =$C$7*F29+$C$11*F30+$C$15*F31 -> 211.19616 | G36: =$C$7*G29+$C$11*G30+$C$15*G31 -> 282.24672 | H36: =$C$7*H29+$C$11*H30+$C$15*H31 -> 353.29728 | I36: =$C$7*I29+$C$11*I30+$C$15*I31 -> 567.53536 | J36: =$C$7*J29+$C$11*J30+$C$15*J31 -> 781.77344 | ... N36: =$C$7*N29+$C$11*N30+$C$15*N31 -> 781.77344 | P36: =F36 -> 211.19616 | Q36: =J36 -> 781.77344 | R36: =N36 -> 781.77344 | S36: =R36 -> 781.77344
A37: Active SAM accounts — E | B37: accounts | C37: =$C$8*C29+$C$12*C30+$C$16*C31 -> 24.76992 | D37: =$C$8*D29+$C$12*D30+$C$16*D31 -> 49.53984 | E37: =$C$8*E29+$C$12*E30+$C$16*E31 -> 49.53984 | F37: =$C$8*F29+$C$12*F30+$C$16*F31 -> 49.53984 | G37: =$C$8*G29+$C$12*G30+$C$16*G31 -> 61.9248 | H37: =$C$8*H29+$C$12*H30+$C$16*H31 -> 74.30976 | I37: =$C$8*I29+$C$12*I30+$C$16*I31 -> 114.072 | J37: =$C$8*J29+$C$12*J30+$C$16*J31 -> 153.83424 | ... N37: =$C$8*N29+$C$12*N30+$C$16*N31 -> 153.83424 | P37: =F37 -> 49.53984 | Q37: =J37 -> 153.83424 | R37: =N37 -> 153.83424 | S37: =R37 -> 153.83424
A38: Active SAM accounts — total | B38: accounts | C38: =C35+C36+C37 -> 551.88772 | D38: =D35+D36+D37 -> 1103.7754 | E38: =E35+E36+E37 -> 1103.7754 | F38: =F35+F36+F37 -> 1103.7754 | G38: =G35+G36+G37 -> 1493.4995 | H38: =H35+H36+H37 -> 1883.2236 | I38: =I35+I36+I37 -> 3167.6104 | J38: =J35+J36+J37 -> 4451.9972 | ... N38: =N35+N36+N37 -> 4451.9972 | P38: =F38 -> 1103.7754 | Q38: =J38 -> 4451.9972 | R38: =N38 -> 4451.9972 | S38: =R38 -> 4451.9972
A39: Fatigue-weighted active accounts | B39: accounts | C39: =$C$9*C29*C32+$C$13*C30*C33+$C$17*C31*C34 -> 551.88772 | D39: =$C$9*D29*D32+$C$13*D30*D33+$C$17*D31*D34 -> 1027.1788 | E39: =$C$9*E29*E32+$C$13*E30*E33+$C$17*E31*E34 -> 955.89758 | F39: =$C$9*F29*F32+$C$13*F30*F33+$C$17*F31*F34 -> 889.56293 | G39: =$C$9*G29*G32+$C$13*G30*G33+$C$17*G31*G34 -> 1217.5556 | H39: =$C$9*H29*H32+$C$13*H30*H33+$C$17*H31*H34 -> 1495.7423 | I39: =$C$9*I29*I32+$C$13*I30*I33+$C$17*I31*I34 -> 2676.3319 | J39: =$C$9*J29*J32+$C$13*J30*J33+$C$17*J31*J34 -> 3685.8641 | ... N39: =$C$9*N29*N32+$C$13*N30*N33+$C$17*N31*N34 -> 2764.3981
A40: Meetings — automated outbound | B40: meetings | C40: =$C$21*Assumptions!$J$20*C28*C39 -> 6.6226527 | D40: =$C$21*Assumptions!$J$20*D28*D39 -> 12.326146 | E40: =$C$21*Assumptions!$J$20*E28*E39 -> 11.470771 | F40: =$C$21*Assumptions!$J$20*F28*F39 -> 10.674755 | G40: =$C$21*Assumptions!$J$20*G28*G39 -> 14.610668 | H40: =$C$21*Assumptions!$J$20*H28*H39 -> 17.948908 | I40: =$C$21*Assumptions!$J$20*I28*I39 -> 32.115983 | J40: =$C$21*Assumptions!$J$20*J28*J39 -> 44.230369 | ... N40: =$C$21*Assumptions!$J$20*N28*N39 -> 33.172777 | P40: =SUM(C40:F40) -> 41.094324 | Q40: =SUM(G40:J40) -> 108.90593 | R40: =SUM(K40:N40) -> 148.28487 | S40: =SUM(P40:R40) -> 298.28512
A41: Dedicated AEs (headcount) | B41: FTE | C41: =Assumptions!$D$115 -> 0 | D41: =Assumptions!$E$115 -> 0 | E41: =Assumptions!$F$115 -> 0 | F41: =Assumptions!$G$115 -> 0 | G41: =Assumptions!$H$115 -> 0 | H41: =Assumptions!$I$115 -> 0 | I41: =Assumptions!$J$115 -> 0 | J41: =Assumptions!$K$115 -> 0 | K41: =Assumptions!$L$115 -> 0 | L41: =Assumptions!$M$115 -> 0 | M41: =Assumptions!$N$115 -> 0 | N41: =Assumptions!$O$115 -> 0 | P41: =F41 -> 0 | Q41: =J41 -> 0 | R41: =N41 -> 0 | S41: =R41 -> 0
A42: Ramped dedicated AEs (≈6-month ramp) | B42: FTE | C42: =0 -> 0 | D42: =0.5*C41 -> 0 | E42: =C41+0.5*(D41-C41) -> 0 | F42: =D41+0.5*(E41-D41) -> 0 | G42: =E41+0.5*(F41-E41) -> 0 | H42: =F41+0.5*(G41-F41) -> 0 | I42: =G41+0.5*(H41-G41) -> 0 | J42: =H41+0.5*(I41-H41) -> 0 | K42: =I41+0.5*(J41-I41) -> 0 | L42: =J41+0.5*(K41-J41) -> 0 | ... N42: =L41+0.5*(M41-L41) -> 0 | P42: =F42 -> 0 | Q42: =J42 -> 0 | R42: =N42 -> 0 | S42: =R42 -> 0
A43: Accounts worked by dedicated AEs | B43: accounts | C43: =MIN(C42*Assumptions!$J$38,C38*(1-$C$21)) -> 0 | D43: =MIN(D42*Assumptions!$J$38,D38*(1-$C$21)) -> 0 | E43: =MIN(E42*Assumptions!$J$38,E38*(1-$C$21)) -> 0 | F43: =MIN(F42*Assumptions!$J$38,F38*(1-$C$21)) -> 0 | G43: =MIN(G42*Assumptions!$J$38,G38*(1-$C$21)) -> 0 | H43: =MIN(H42*Assumptions!$J$38,H38*(1-$C$21)) -> 0 | I43: =MIN(I42*Assumptions!$J$38,I38*(1-$C$21)) -> 0 | J43: =MIN(J42*Assumptions!$J$38,J38*(1-$C$21)) -> 0 | ... N43: =MIN(N42*Assumptions!$J$38,N38*(1-$C$21)) -> 0 | P43: =SUM(C43:F43) -> 0 | Q43: =SUM(G43:J43) -> 0 | R43: =SUM(K43:N43) -> 0 | S43: =SUM(P43:R43) -> 0
A44: Meetings — AE self-sourced outreach | B44: meetings | C44: =C43*Assumptions!$J$20*Assumptions!$J$39*IF(C38>0,C39/C38,0)*C28 -> 0 | D44: =D43*Assumptions!$J$20*Assumptions!$J$39*IF(D38>0,D39/D38,0)*D28 -> 0 | E44: =E43*Assumptions!$J$20*Assumptions!$J$39*IF(E38>0,E39/E38,0)*E28 -> 0 | F44: =F43*Assumptions!$J$20*Assumptions!$J$39*IF(F38>0,F39/F38,0)*F28 -> 0 | G44: =G43*Assumptions!$J$20*Assumptions!$J$39*IF(G38>0,G39/G38,0)*G28 -> 0 | H44: =H43*Assumptions!$J$20*Assumptions!$J$39*IF(H38>0,H39/H38,0)*H28 -> 0 | I44: =I43*Assumptions!$J$20*Assumptions!$J$39*IF(I38>0,I39/I38,0)*I28 -> 0 | J44: =J43*Assumptions!$J$20*Assumptions!$J$39*IF(J38>0,J39/J38,0)*J28 -> 0 | ... N44: =N43*Assumptions!$J$20*Assumptions!$J$39*IF(N38>0,N39/N38,0)*N28 -> 0 | P44: =SUM(C44:F44) -> 0 | Q44: =SUM(G44:J44) -> 0 | R44: =SUM(K44:N44) -> 0 | S44: =SUM(P44:R44) -> 0
A45: Extra MQLs bought by program spend above base | B45: MQLs | C45: =IF(AND(C38>0,$C$25>0),C38*Assumptions!$J$24*(1-EXP(-$C$25/(Assumptions!$J$23*C38*Assumptions!$J$24))),0) -> 0 | D45: =IF(AND(D38>0,$C$25>0),D38*Assumptions!$J$24*(1-EXP(-$C$25/(Assumptions!$J$23*D38*Assumptions!$J$24))),0) -> 0 | E45: =IF(AND(E38>0,$C$25>0),E38*Assumptions!$J$24*(1-EXP(-$C$25/(Assumptions!$J$23*E38*Assumptions!$J$24))),0) -> 0 | F45: =IF(AND(F38>0,$C$25>0),F38*Assumptions!$J$24*(1-EXP(-$C$25/(Assumptions!$J$23*F38*Assumptions!$J$24))),0) -> 0 | G45: =IF(AND(G38>0,$C$25>0),G38*Assumptions!$J$24*(1-EXP(-$C$25/(Assumptions!$J$23*G38*Assumptions!$J$24))),0) -> 0 | H45: =IF(AND(H38>0,$C$25>0),H38*Assumptions!$J$24*(1-EXP(-$C$25/(Assumptions!$J$23*H38*Assumptions!$J$24))),0) -> 0 | I45: =IF(AND(I38>0,$C$25>0),I38*Assumptions!$J$24*(1-EXP(-$C$25/(Assumptions!$J$23*I38*Assumptions!$J$24))),0) -> 0 | J45: =IF(AND(J38>0,$C$25>0),J38*Assumptions!$J$24*(1-EXP(-$C$25/(Assumptions!$J$23*J38*Assumptions!$J$24))),0) -> 0 | ... N45: =IF(AND(N38>0,$C$25>0),N38*Assumptions!$J$24*(1-EXP(-$C$25/(Assumptions!$J$23*N38*Assumptions!$J$24))),0) -> 0 | P45: =SUM(C45:F45) -> 0 | Q45: =SUM(G45:J45) -> 0 | R45: =SUM(K45:N45) -> 0 | S45: =SUM(P45:R45) -> 0
A46: MQLs — inbound / templates | B46: MQLs | C46: =(C38*Assumptions!$J$22*MIN(1,Assumptions!$J$103/Assumptions!$J$78)+C45)*C28 -> 5.5188772 | D46: =(D38*Assumptions!$J$22*MIN(1,Assumptions!$J$103/Assumptions!$J$78)+D45)*D28 -> 11.037754 | E46: =(E38*Assumptions!$J$22*MIN(1,Assumptions!$J$103/Assumptions!$J$78)+E45)*E28 -> 11.037754 | F46: =(F38*Assumptions!$J$22*MIN(1,Assumptions!$J$103/Assumptions!$J$78)+F45)*F28 -> 11.037754 | G46: =(G38*Assumptions!$J$22*MIN(1,Assumptions!$J$103/Assumptions!$J$78)+G45)*G28 -> 14.934995 | H46: =(H38*Assumptions!$J$22*MIN(1,Assumptions!$J$103/Assumptions!$J$78)+H45)*H28 -> 18.832236 | I46: =(I38*Assumptions!$J$22*MIN(1,Assumptions!$J$103/Assumptions!$J$78)+I45)*I28 -> 31.676104 | J46: =(J38*Assumptions!$J$22*MIN(1,Assumptions!$J$103/Assumptions!$J$78)+J45)*J28 -> 44.519972 | ... N46: =(N38*Assumptions!$J$22*MIN(1,Assumptions!$J$103/Assumptions!$J$78)+N45)*N28 -> 44.519972 | P46: =SUM(C46:F46) -> 38.632141 | Q46: =SUM(G46:J46) -> 109.96331 | R46: =SUM(K46:N46) -> 178.07989 | S46: =SUM(P46:R46) -> 326.67534
A47: Active partners | B47: partners | C47: =C28*MIN(Assumptions!$J$27,Assumptions!$J$25+Assumptions!$J$26*(C27-1))*Assumptions!$J$107 -> 2 | D47: =D28*MIN(Assumptions!$J$27,Assumptions!$J$25+Assumptions!$J$26*(D27-1))*Assumptions!$J$107 -> 3 | E47: =E28*MIN(Assumptions!$J$27,Assumptions!$J$25+Assumptions!$J$26*(E27-1))*Assumptions!$J$107 -> 4 | F47: =F28*MIN(Assumptions!$J$27,Assumptions!$J$25+Assumptions!$J$26*(F27-1))*Assumptions!$J$107 -> 5 | G47: =G28*MIN(Assumptions!$J$27,Assumptions!$J$25+Assumptions!$J$26*(G27-1))*Assumptions!$J$107 -> 6 | H47: =H28*MIN(Assumptions!$J$27,Assumptions!$J$25+Assumptions!$J$26*(H27-1))*Assumptions!$J$107 -> 7 | I47: =I28*MIN(Assumptions!$J$27,Assumptions!$J$25+Assumptions!$J$26*(I27-1))*Assumptions!$J$107 -> 8 | J47: =J28*MIN(Assumptions!$J$27,Assumptions!$J$25+Assumptions!$J$26*(J27-1))*Assumptions!$J$107 -> 9 | ... N47: =N28*MIN(Assumptions!$J$27,Assumptions!$J$25+Assumptions!$J$26*(N27-1))*Assumptions!$J$107 -> 10 | P47: =F47 -> 5 | Q47: =J47 -> 9 | R47: =N47 -> 10 | S47: =R47 -> 10
A48: Partner introductions | B48: intros | C48: =C47*Assumptions!$J$28 -> 6 | D48: =D47*Assumptions!$J$28 -> 9 | E48: =E47*Assumptions!$J$28 -> 12 | F48: =F47*Assumptions!$J$28 -> 15 | G48: =G47*Assumptions!$J$28 -> 18 | H48: =H47*Assumptions!$J$28 -> 21 | I48: =I47*Assumptions!$J$28 -> 24 | J48: =J47*Assumptions!$J$28 -> 27 | ... N48: =N47*Assumptions!$J$28 -> 30 | P48: =SUM(C48:F48) -> 42 | Q48: =SUM(G48:J48) -> 90 | R48: =SUM(K48:N48) -> 120 | S48: =SUM(P48:R48) -> 252
A49: Opportunities — outbound (automated + AE) | B49: opps | C49: =(C40+C44)*Assumptions!$J$29 -> 2.6490611 | D49: =(D40+D44)*Assumptions!$J$29 -> 4.9304582 | E49: =(E40+E44)*Assumptions!$J$29 -> 4.5883084 | F49: =(F40+F44)*Assumptions!$J$29 -> 4.2699021 | G49: =(G40+G44)*Assumptions!$J$29 -> 5.8442671 | H49: =(H40+H44)*Assumptions!$J$29 -> 7.179563 | I49: =(I40+I44)*Assumptions!$J$29 -> 12.846393 | J49: =(J40+J44)*Assumptions!$J$29 -> 17.692148 | ... N49: =(N40+N44)*Assumptions!$J$29 -> 13.269111 | P49: =SUM(C49:F49) -> 16.43773 | Q49: =SUM(G49:J49) -> 43.562371 | R49: =SUM(K49:N49) -> 59.313946 | S49: =SUM(P49:R49) -> 119.31405
A50: Opportunities — inbound | B50: opps | C50: =C46*Assumptions!$J$31 -> 0.88302036 | D50: =D46*Assumptions!$J$31 -> 1.7660407 | E50: =E46*Assumptions!$J$31 -> 1.7660407 | F50: =F46*Assumptions!$J$31 -> 1.7660407 | G50: =G46*Assumptions!$J$31 -> 2.3895992 | H50: =H46*Assumptions!$J$31 -> 3.0131577 | I50: =I46*Assumptions!$J$31 -> 5.0681766 | J50: =J46*Assumptions!$J$31 -> 7.1231956 | ... N50: =N46*Assumptions!$J$31 -> 7.1231956 | P50: =SUM(C50:F50) -> 6.1811425 | Q50: =SUM(G50:J50) -> 17.594129 | R50: =SUM(K50:N50) -> 28.492782 | S50: =SUM(P50:R50) -> 52.268054
A51: Opportunities — partner | B51: opps | C51: =C48*Assumptions!$J$30 -> 3 | D51: =D48*Assumptions!$J$30 -> 4.5 | E51: =E48*Assumptions!$J$30 -> 6 | F51: =F48*Assumptions!$J$30 -> 7.5 | G51: =G48*Assumptions!$J$30 -> 9 | H51: =H48*Assumptions!$J$30 -> 10.5 | I51: =I48*Assumptions!$J$30 -> 12 | J51: =J48*Assumptions!$J$30 -> 13.5 | ... N51: =N48*Assumptions!$J$30 -> 15 | P51: =SUM(C51:F51) -> 21 | Q51: =SUM(G51:J51) -> 45 | R51: =SUM(K51:N51) -> 60 | S51: =SUM(P51:R51) -> 126
A52: Opportunities — total | B52: opps | C52: =C49+C50+C51 -> 6.5320814 | D52: =D49+D50+D51 -> 11.196499 | E52: =E49+E50+E51 -> 12.354349 | F52: =F49+F50+F51 -> 13.535943 | G52: =G49+G50+G51 -> 17.233866 | H52: =H49+H50+H51 -> 20.692721 | I52: =I49+I50+I51 -> 29.91457 | J52: =J49+J50+J51 -> 38.315343 | ... N52: =N49+N50+N51 -> 35.392306 | P52: =SUM(C52:F52) -> 43.618872 | Q52: =SUM(G52:J52) -> 106.1565 | R52: =SUM(K52:N52) -> 147.80673 | S52: =SUM(P52:R52) -> 297.5821
A53: Band weight — SMB (accounts) | B53: weight | C53: =C35 -> 421.51972 | D53: =D35 -> 843.03945 | E53: =E35 -> 843.03945 | F53: =F35 -> 843.03945 | G53: =G35 -> 1149.328 | H53: =H35 -> 1455.6165 | I53: =I35 -> 2486.003 | J53: =J35 -> 3516.3896 | ... N53: =N35 -> 3516.3896
A54: Band weight — Mid-Market (accounts × tilt × propensity) | B54: weight | C54: =C36*Assumptions!$J$18*Assumptions!$J$33 -> 211.19616 | D54: =D36*Assumptions!$J$18*Assumptions!$J$33 -> 422.39232 | E54: =E36*Assumptions!$J$18*Assumptions!$J$33 -> 422.39232 | F54: =F36*Assumptions!$J$18*Assumptions!$J$33 -> 422.39232 | G54: =G36*Assumptions!$J$18*Assumptions!$J$33 -> 564.49344 | H54: =H36*Assumptions!$J$18*Assumptions!$J$33 -> 706.59456 | I54: =I36*Assumptions!$J$18*Assumptions!$J$33 -> 1135.0707 | J54: =J36*Assumptions!$J$18*Assumptions!$J$33 -> 1563.5469 | ... N54: =N36*Assumptions!$J$18*Assumptions!$J$33 -> 1563.5469
A55: Band weight — Enterprise (accounts × tilt × propensity) | B55: weight | C55: =C37*Assumptions!$J$19*Assumptions!$J$34 -> 34.677888 | D55: =D37*Assumptions!$J$19*Assumptions!$J$34 -> 69.355776 | E55: =E37*Assumptions!$J$19*Assumptions!$J$34 -> 69.355776 | F55: =F37*Assumptions!$J$19*Assumptions!$J$34 -> 69.355776 | G55: =G37*Assumptions!$J$19*Assumptions!$J$34 -> 86.69472 | H55: =H37*Assumptions!$J$19*Assumptions!$J$34 -> 104.03366 | I55: =I37*Assumptions!$J$19*Assumptions!$J$34 -> 159.7008 | J55: =J37*Assumptions!$J$19*Assumptions!$J$34 -> 215.36794 | ... N55: =N37*Assumptions!$J$19*Assumptions!$J$34 -> 215.36794
A56: Opportunity mix — S (derived, not assumed) | B56: % | C56: =IFERROR(C53/(C53+C54+C55),0) -> 0.63159074 | D56: =IFERROR(D53/(D53+D54+D55),0) -> 0.63159074 | E56: =IFERROR(E53/(E53+E54+E55),0) -> 0.63159074 | F56: =IFERROR(F53/(F53+F54+F55),0) -> 0.63159074 | G56: =IFERROR(G53/(G53+G54+G55),0) -> 0.63833251 | H56: =IFERROR(H53/(H53+H54+H55),0) -> 0.64230332 | I56: =IFERROR(I53/(I53+I54+I55),0) -> 0.65753803 | J56: =IFERROR(J53/(J53+J54+J55),0) -> 0.66405806 | ... N56: =IFERROR(N53/(N53+N54+N55),0) -> 0.66405806
A57: Opportunity mix — M (derived, not assumed) | B57: % | C57: =IFERROR(C54/(C53+C54+C55),0) -> 0.3164491 | D57: =IFERROR(D54/(D53+D54+D55),0) -> 0.3164491 | E57: =IFERROR(E54/(E53+E54+E55),0) -> 0.3164491 | F57: =IFERROR(F54/(F53+F54+F55),0) -> 0.3164491 | G57: =IFERROR(G54/(G53+G54+G55),0) -> 0.31351757 | H57: =IFERROR(H54/(H53+H54+H55),0) -> 0.31179093 | I57: =IFERROR(I54/(I53+I54+I55),0) -> 0.30022174 | J57: =IFERROR(J54/(J53+J54+J55),0) -> 0.29527045 | ... N57: =IFERROR(N54/(N53+N54+N55),0) -> 0.29527045
A58: Opportunity mix — E (derived, not assumed) | B58: % | C58: =IFERROR(C55/(C53+C54+C55),0) -> 0.051960161 | D58: =IFERROR(D55/(D53+D54+D55),0) -> 0.051960161 | E58: =IFERROR(E55/(E53+E54+E55),0) -> 0.051960161 | F58: =IFERROR(F55/(F53+F54+F55),0) -> 0.051960161 | G58: =IFERROR(G55/(G53+G54+G55),0) -> 0.048149927 | H58: =IFERROR(H55/(H53+H54+H55),0) -> 0.04590575 | I58: =IFERROR(I55/(I53+I54+I55),0) -> 0.042240233 | J58: =IFERROR(J55/(J53+J54+J55),0) -> 0.040671493 | ... N58: =IFERROR(N55/(N53+N54+N55),0) -> 0.040671493
A59: Wins (demand) — SMB | B59: wins | C59: =IF(C27-Assumptions!$J$35<1,0,INDEX($C$52:$N$52,1,C27-Assumptions!$J$35)*INDEX($C$56:$N$56,1,C27-Assumptions!$J$35)*Assumptions!$J$32) -> 0 | D59: =IF(D27-Assumptions!$J$35<1,0,INDEX($C$52:$N$52,1,D27-Assumptions!$J$35)*INDEX($C$56:$N$56,1,D27-Assumptions!$J$35)*Assumptions!$J$32) -> 0.86637645 | E59: =IF(E27-Assumptions!$J$35<1,0,INDEX($C$52:$N$52,1,E27-Assumptions!$J$35)*INDEX($C$56:$N$56,1,E27-Assumptions!$J$35)*Assumptions!$J$32) -> 1.4850371 | F59: =IF(F27-Assumptions!$J$35<1,0,INDEX($C$52:$N$52,1,F27-Assumptions!$J$35)*INDEX($C$56:$N$56,1,F27-Assumptions!$J$35)*Assumptions!$J$32) -> 1.6386074 | G59: =IF(G27-Assumptions!$J$35<1,0,INDEX($C$52:$N$52,1,G27-Assumptions!$J$35)*INDEX($C$56:$N$56,1,G27-Assumptions!$J$35)*Assumptions!$J$32) -> 1.795327 | H59: =IF(H27-Assumptions!$J$35<1,0,INDEX($C$52:$N$52,1,H27-Assumptions!$J$35)*INDEX($C$56:$N$56,1,H27-Assumptions!$J$35)*Assumptions!$J$32) -> 2.3101968 | I59: =IF(I27-Assumptions!$J$35<1,0,INDEX($C$52:$N$52,1,I27-Assumptions!$J$35)*INDEX($C$56:$N$56,1,I27-Assumptions!$J$35)*Assumptions!$J$32) -> 2.7911107 | J59: =IF(J27-Assumptions!$J$35<1,0,INDEX($C$52:$N$52,1,J27-Assumptions!$J$35)*INDEX($C$56:$N$56,1,J27-Assumptions!$J$35)*Assumptions!$J$32) -> 4.1306931 | ... N59: =IF(N27-Assumptions!$J$35<1,0,INDEX($C$52:$N$52,1,N27-Assumptions!$J$35)*INDEX($C$56:$N$56,1,N27-Assumptions!$J$35)*Assumptions!$J$32) -> 5.0735194 | P59: =SUM(C59:F59) -> 3.9900209 | Q59: =SUM(G59:J59) -> 11.027328 | R59: =SUM(K59:N59) -> 21.019596 | S59: =SUM(P59:R59) -> 36.036945
A60: Wins (demand) — Mid-Market | B60: wins | C60: =IF(C27-Assumptions!$J$35<1,0,INDEX($C$52:$N$52,1,C27-Assumptions!$J$35)*INDEX($C$57:$N$57,1,C27-Assumptions!$J$35)*Assumptions!$J$32) -> 0 | D60: =IF(D27-Assumptions!$J$35<1,0,INDEX($C$52:$N$52,1,D27-Assumptions!$J$35)*INDEX($C$57:$N$57,1,D27-Assumptions!$J$35)*Assumptions!$J$32) -> 0.43408497 | E60: =IF(E27-Assumptions!$J$35<1,0,INDEX($C$52:$N$52,1,E27-Assumptions!$J$35)*INDEX($C$57:$N$57,1,E27-Assumptions!$J$35)*Assumptions!$J$32) -> 0.74405563 | F60: =IF(F27-Assumptions!$J$35<1,0,INDEX($C$52:$N$52,1,F27-Assumptions!$J$35)*INDEX($C$57:$N$57,1,F27-Assumptions!$J$35)*Assumptions!$J$32) -> 0.82099976 | G60: =IF(G27-Assumptions!$J$35<1,0,INDEX($C$52:$N$52,1,G27-Assumptions!$J$35)*INDEX($C$57:$N$57,1,G27-Assumptions!$J$35)*Assumptions!$J$32) -> 0.89952176 | H60: =IF(H27-Assumptions!$J$35<1,0,INDEX($C$52:$N$52,1,H27-Assumptions!$J$35)*INDEX($C$57:$N$57,1,H27-Assumptions!$J$35)*Assumptions!$J$32) -> 1.1346552 | I60: =IF(I27-Assumptions!$J$35<1,0,INDEX($C$52:$N$52,1,I27-Assumptions!$J$35)*INDEX($C$57:$N$57,1,I27-Assumptions!$J$35)*Assumptions!$J$32) -> 1.3548786 | J60: =IF(J27-Assumptions!$J$35<1,0,INDEX($C$52:$N$52,1,J27-Assumptions!$J$35)*INDEX($C$57:$N$57,1,J27-Assumptions!$J$35)*Assumptions!$J$32) -> 1.8860109 | ... N60: =IF(N27-Assumptions!$J$35<1,0,INDEX($C$52:$N$52,1,N27-Assumptions!$J$35)*INDEX($C$57:$N$57,1,N27-Assumptions!$J$35)*Assumptions!$J$32) -> 2.2559177 | P60: =SUM(C60:F60) -> 1.9991404 | Q60: =SUM(G60:J60) -> 5.2750664 | R60: =SUM(K60:N60) -> 9.3462694 | S60: =SUM(P60:R60) -> 16.620476
A61: Wins (demand) — Enterprise (longer cycle) | B61: wins | C61: =IF(C27-Assumptions!$J$36<1,0,INDEX($C$52:$N$52,1,C27-Assumptions!$J$36)*INDEX($C$58:$N$58,1,C27-Assumptions!$J$36)*Assumptions!$J$32) -> 0 | D61: =IF(D27-Assumptions!$J$36<1,0,INDEX($C$52:$N$52,1,D27-Assumptions!$J$36)*INDEX($C$58:$N$58,1,D27-Assumptions!$J$36)*Assumptions!$J$32) -> 0 | E61: =IF(E27-Assumptions!$J$36<1,0,INDEX($C$52:$N$52,1,E27-Assumptions!$J$36)*INDEX($C$58:$N$58,1,E27-Assumptions!$J$36)*Assumptions!$J$32) -> 0.071275681 | F61: =IF(F27-Assumptions!$J$36<1,0,INDEX($C$52:$N$52,1,F27-Assumptions!$J$36)*INDEX($C$58:$N$58,1,F27-Assumptions!$J$36)*Assumptions!$J$32) -> 0.1221721 | G61: =IF(G27-Assumptions!$J$36<1,0,INDEX($C$52:$N$52,1,G27-Assumptions!$J$36)*INDEX($C$58:$N$58,1,G27-Assumptions!$J$36)*Assumptions!$J$32) -> 0.13480613 | H61: =IF(H27-Assumptions!$J$36<1,0,INDEX($C$52:$N$52,1,H27-Assumptions!$J$36)*INDEX($C$58:$N$58,1,H27-Assumptions!$J$36)*Assumptions!$J$32) -> 0.14769925 | I61: =IF(I27-Assumptions!$J$36<1,0,INDEX($C$52:$N$52,1,I27-Assumptions!$J$36)*INDEX($C$58:$N$58,1,I27-Assumptions!$J$36)*Assumptions!$J$32) -> 0.17425997 | J61: =IF(J27-Assumptions!$J$36<1,0,INDEX($C$52:$N$52,1,J27-Assumptions!$J$36)*INDEX($C$58:$N$58,1,J27-Assumptions!$J$36)*Assumptions!$J$32) -> 0.19948212 | ... N61: =IF(N27-Assumptions!$J$36<1,0,INDEX($C$52:$N$52,1,N27-Assumptions!$J$36)*INDEX($C$58:$N$58,1,N27-Assumptions!$J$36)*Assumptions!$J$32) -> 0.31981864 | P61: =SUM(C61:F61) -> 0.19344778 | Q61: =SUM(G61:J61) -> 0.65624748 | R61: =SUM(K61:N61) -> 1.2420033 | S61: =SUM(P61:R61) -> 2.0916986
A62: Partner-sourced share of closing opportunities | B62: % | C62: =IF(C27-Assumptions!$J$35<1,0,IFERROR(INDEX($C$51:$N$51,1,C27-Assumptions!$J$35)/INDEX($C$52:$N$52,1,C27-Assumptions!$J$35),0)) -> 0 | D62: =IF(D27-Assumptions!$J$35<1,0,IFERROR(INDEX($C$51:$N$51,1,D27-Assumptions!$J$35)/INDEX($C$52:$N$52,1,D27-Assumptions!$J$35),0)) -> 0.45927168 | E62: =IF(E27-Assumptions!$J$35<1,0,IFERROR(INDEX($C$51:$N$51,1,E27-Assumptions!$J$35)/INDEX($C$52:$N$52,1,E27-Assumptions!$J$35),0)) -> 0.40191135 | F62: =IF(F27-Assumptions!$J$35<1,0,IFERROR(INDEX($C$51:$N$51,1,F27-Assumptions!$J$35)/INDEX($C$52:$N$52,1,F27-Assumptions!$J$35),0)) -> 0.48565893 | G62: =IF(G27-Assumptions!$J$35<1,0,IFERROR(INDEX($C$51:$N$51,1,G27-Assumptions!$J$35)/INDEX($C$52:$N$52,1,G27-Assumptions!$J$35),0)) -> 0.55408036 | H62: =IF(H27-Assumptions!$J$35<1,0,IFERROR(INDEX($C$51:$N$51,1,H27-Assumptions!$J$35)/INDEX($C$52:$N$52,1,H27-Assumptions!$J$35),0)) -> 0.52222756 | I62: =IF(I27-Assumptions!$J$35<1,0,IFERROR(INDEX($C$51:$N$51,1,I27-Assumptions!$J$35)/INDEX($C$52:$N$52,1,I27-Assumptions!$J$35),0)) -> 0.50742482 | J62: =IF(J27-Assumptions!$J$35<1,0,IFERROR(INDEX($C$51:$N$51,1,J27-Assumptions!$J$35)/INDEX($C$52:$N$52,1,J27-Assumptions!$J$35),0)) -> 0.40114232 | ... N62: =IF(N27-Assumptions!$J$35<1,0,IFERROR(INDEX($C$51:$N$51,1,N27-Assumptions!$J$35)/INDEX($C$52:$N$52,1,N27-Assumptions!$J$35),0)) -> 0.41229425
A63: Self-serve SMB wins (no AE) | B63: wins | C63: =C59*Assumptions!$J$37 -> 0 | D63: =D59*Assumptions!$J$37 -> 0.25991293 | E63: =E59*Assumptions!$J$37 -> 0.44551112 | F63: =F59*Assumptions!$J$37 -> 0.49158222 | G63: =G59*Assumptions!$J$37 -> 0.53859809 | H63: =H59*Assumptions!$J$37 -> 0.69305903 | I63: =I59*Assumptions!$J$37 -> 0.8373332 | J63: =J59*Assumptions!$J$37 -> 1.2392079 | ... N63: =N59*Assumptions!$J$37 -> 1.5220558 | P63: =SUM(C63:F63) -> 1.1970063 | Q63: =SUM(G63:J63) -> 3.3081983 | R63: =SUM(K63:N63) -> 6.3058789 | S63: =SUM(P63:R63) -> 10.811083
A64: Sales-assisted demand — SMB | B64: wins | C64: =C59*(1-Assumptions!$J$37) -> 0 | D64: =D59*(1-Assumptions!$J$37) -> 0.60646351 | E64: =E59*(1-Assumptions!$J$37) -> 1.0395259 | F64: =F59*(1-Assumptions!$J$37) -> 1.1470252 | G64: =G59*(1-Assumptions!$J$37) -> 1.2567289 | H64: =H59*(1-Assumptions!$J$37) -> 1.6171377 | I64: =I59*(1-Assumptions!$J$37) -> 1.9537775 | J64: =J59*(1-Assumptions!$J$37) -> 2.8914852 | ... N64: =N59*(1-Assumptions!$J$37) -> 3.5514636 | P64: =SUM(C64:F64) -> 2.7930146 | Q64: =SUM(G64:J64) -> 7.7191293 | R64: =SUM(K64:N64) -> 14.713717 | S64: =SUM(P64:R64) -> 25.225861
A65: Sales-assisted demand (first-year ACV) | B65: $ | C65: =C64*$C$18+C60*$C$19+C61*$C$20 -> 0 | D65: =D64*$C$18+D60*$C$19+D61*$C$20 -> 7485.3792 | E65: =E64*$C$18+E60*$C$19+E61*$C$20 -> 17233.813 | F65: =F64*$C$18+F60*$C$19+F61*$C$20 -> 21704.933 | G65: =G64*$C$18+G60*$C$19+G61*$C$20 -> 23839.478 | H65: =H64*$C$18+H60*$C$19+H61*$C$20 -> 28861.383 | I65: =I64*$C$18+I60*$C$19+I61*$C$20 -> 34454.814 | J65: =J64*$C$18+J60*$C$19+J61*$C$20 -> 46219.027 | ... N65: =N64*$C$18+N60*$C$19+N61*$C$20 -> 60798.188 | P65: =SUM(C65:F65) -> 46424.125 | Q65: =SUM(G65:J65) -> 133374.7 | R65: =SUM(K65:N65) -> 246759.01 | S65: =SUM(P65:R65) -> 426557.84
A66: Closing capacity (dedicated + shared AEs) | B66: $ | C66: =(C42+Assumptions!$J$104*C28)*$C$23 -> 306250 | D66: =(D42+Assumptions!$J$104*D28)*$C$23 -> 306250 | E66: =(E42+Assumptions!$J$104*E28)*$C$23 -> 306250 | F66: =(F42+Assumptions!$J$104*F28)*$C$23 -> 306250 | G66: =(G42+Assumptions!$J$104*G28)*$C$23 -> 306250 | H66: =(H42+Assumptions!$J$104*H28)*$C$23 -> 306250 | I66: =(I42+Assumptions!$J$104*I28)*$C$23 -> 306250 | J66: =(J42+Assumptions!$J$104*J28)*$C$23 -> 306250 | ... N66: =(N42+Assumptions!$J$104*N28)*$C$23 -> 306250 | P66: =SUM(C66:F66) -> 1225000 | Q66: =SUM(G66:J66) -> 1225000 | R66: =SUM(K66:N66) -> 1225000 | S66: =SUM(P66:R66) -> 3675000
A67: Share of demand closed = MIN(1, capacity ÷ demand) | B67: % | C67: =IF(C65>0,MIN(1,C66/C65),1) -> 1 | D67: =IF(D65>0,MIN(1,D66/D65),1) -> 1 | E67: =IF(E65>0,MIN(1,E66/E65),1) -> 1 | F67: =IF(F65>0,MIN(1,F66/F65),1) -> 1 | G67: =IF(G65>0,MIN(1,G66/G65),1) -> 1 | H67: =IF(H65>0,MIN(1,H66/H65),1) -> 1 | I67: =IF(I65>0,MIN(1,I66/I65),1) -> 1 | J67: =IF(J65>0,MIN(1,J66/J65),1) -> 1 | ... N67: =IF(N65>0,MIN(1,N66/N65),1) -> 1
A68: First-year ACV lost to the capacity constraint | B68: $ | C68: =C65*(1-C67) -> 0 | D68: =D65*(1-D67) -> 0 | E68: =E65*(1-E67) -> 0 | F68: =F65*(1-F67) -> 0 | G68: =G65*(1-G67) -> 0 | H68: =H65*(1-H67) -> 0 | I68: =I65*(1-I67) -> 0 | J68: =J65*(1-J67) -> 0 | ... N68: =N65*(1-N67) -> 0 | P68: =SUM(C68:F68) -> 0 | Q68: =SUM(G68:J68) -> 0 | R68: =SUM(K68:N68) -> 0 | S68: =SUM(P68:R68) -> 0
A69: New customers — SMB | B69: customers | C69: =C63+C64*C67 -> 0 | D69: =D63+D64*D67 -> 0.86637645 | E69: =E63+E64*E67 -> 1.4850371 | F69: =F63+F64*F67 -> 1.6386074 | G69: =G63+G64*G67 -> 1.795327 | H69: =H63+H64*H67 -> 2.3101968 | I69: =I63+I64*I67 -> 2.7911107 | J69: =J63+J64*J67 -> 4.1306931 | ... N69: =N63+N64*N67 -> 5.0735194 | P69: =SUM(C69:F69) -> 3.9900209 | Q69: =SUM(G69:J69) -> 11.027328 | R69: =SUM(K69:N69) -> 21.019596 | S69: =SUM(P69:R69) -> 36.036945
A70: New customers — Mid-Market | B70: customers | C70: =C60*C67 -> 0 | D70: =D60*D67 -> 0.43408497 | E70: =E60*E67 -> 0.74405563 | F70: =F60*F67 -> 0.82099976 | G70: =G60*G67 -> 0.89952176 | H70: =H60*H67 -> 1.1346552 | I70: =I60*I67 -> 1.3548786 | J70: =J60*J67 -> 1.8860109 | ... N70: =N60*N67 -> 2.2559177 | P70: =SUM(C70:F70) -> 1.9991404 | Q70: =SUM(G70:J70) -> 5.2750664 | R70: =SUM(K70:N70) -> 9.3462694 | S70: =SUM(P70:R70) -> 16.620476
A71: New customers — Enterprise | B71: customers | C71: =C61*C67 -> 0 | D71: =D61*D67 -> 0 | E71: =E61*E67 -> 0.071275681 | F71: =F61*F67 -> 0.1221721 | G71: =G61*G67 -> 0.13480613 | H71: =H61*H67 -> 0.14769925 | I71: =I61*I67 -> 0.17425997 | J71: =J61*J67 -> 0.19948212 | ... N71: =N61*N67 -> 0.31981864 | P71: =SUM(C71:F71) -> 0.19344778 | Q71: =SUM(G71:J71) -> 0.65624748 | R71: =SUM(K71:N71) -> 1.2420033 | S71: =SUM(P71:R71) -> 2.0916986
A72: New customers — total | B72: customers | C72: =C69+C70+C71 -> 0 | D72: =D69+D70+D71 -> 1.3004614 | E72: =E69+E70+E71 -> 2.3003684 | F72: =F69+F70+F71 -> 2.5817793 | G72: =G69+G70+G71 -> 2.8296549 | H72: =H69+H70+H71 -> 3.5925512 | I72: =I69+I70+I71 -> 4.3202492 | J72: =J69+J70+J71 -> 6.2161861 | ... N72: =N69+N70+N71 -> 7.6492558 | P72: =SUM(C72:F72) -> 6.182609 | Q72: =SUM(G72:J72) -> 16.958641 | R72: =SUM(K72:N72) -> 31.607869 | S72: =SUM(P72:R72) -> 54.749119

Sheet Revenue Model
A1: Revenue Model — customers, ARR and recognized revenue
A2: ARR = prior ARR × NRR^(1/4) + new customers × ACV. Recognized revenue = average ARR ÷ 4 (kept separate from ARR).
A3: ="Live run: "&Assumptions!$E$5&" · "&Assumptions!$E$4&" · "&Assumptions!$E$6 -> Live run: Industrial distribution · Base · Lean partner-led pilot
A5: Customers, ARR and revenue | B5: Unit / note | C5: Q1 2027 | D5: Q2 2027 | E5: Q3 2027 | F5: Q4 2027 | G5: Q1 2028 | H5: Q2 2028 | I5: Q3 2028 | J5: Q4 2028 | K5: Q1 2029 | L5: Q2 2029 | M5: Q3 2029 | N5: Q4 2029 | P5: 2027 | Q5: 2028 | R5: 2029 | S5: 2027–29
A6: Customers — SMB | B6: customers | C6: =0*Assumptions!$J$59^(1/4)+'GTM Funnel'!C69 -> 0 | D6: =C6*Assumptions!$J$59^(1/4)+'GTM Funnel'!D69 -> 0.86637645 | E6: =D6*Assumptions!$J$59^(1/4)+'GTM Funnel'!E69 -> 2.3241633 | F6: =E6*Assumptions!$J$59^(1/4)+'GTM Funnel'!F69 -> 3.8896686 | G6: =F6*Assumptions!$J$59^(1/4)+'GTM Funnel'!G69 -> 5.5626536 | H6: =G6*Assumptions!$J$59^(1/4)+'GTM Funnel'!H69 -> 7.6978878 | I6: =H6*Assumptions!$J$59^(1/4)+'GTM Funnel'!I69 -> 10.246876 | J6: =I6*Assumptions!$J$59^(1/4)+'GTM Funnel'!J69 -> 14.055274 | K6: =J6*Assumptions!$J$59^(1/4)+'GTM Funnel'!K69 -> 18.956351 | ... N6: =M6*Assumptions!$J$59^(1/4)+'GTM Funnel'!N69 -> 32.402329 | P6: =F6 -> 3.8896686 | Q6: =J6 -> 14.055274 | R6: =N6 -> 32.402329 | S6: =R6 -> 32.402329
A7: Customers — Mid-Market | B7: customers | C7: =0*Assumptions!$J$60^(1/4)+'GTM Funnel'!C70 -> 0 | D7: =C7*Assumptions!$J$60^(1/4)+'GTM Funnel'!D70 -> 0.43408497 | E7: =D7*Assumptions!$J$60^(1/4)+'GTM Funnel'!E70 -> 1.166856 | F7: =E7*Assumptions!$J$60^(1/4)+'GTM Funnel'!F70 -> 1.9575219 | G7: =F7*Assumptions!$J$60^(1/4)+'GTM Funnel'!G70 -> 2.8061554 | H7: =G7*Assumptions!$J$60^(1/4)+'GTM Funnel'!H70 -> 3.8678611 | I7: =H7*Assumptions!$J$60^(1/4)+'GTM Funnel'!I70 -> 5.1221897 | J7: =I7*Assumptions!$J$60^(1/4)+'GTM Funnel'!J70 -> 6.8750429 | K7: =J7*Assumptions!$J$60^(1/4)+'GTM Funnel'!K70 -> 9.0721291 | ... N7: =M7*Assumptions!$J$60^(1/4)+'GTM Funnel'!N70 -> 15.170152 | P7: =F7 -> 1.9575219 | Q7: =J7 -> 6.8750429 | R7: =N7 -> 15.170152 | S7: =R7 -> 15.170152
A8: Customers — Enterprise | B8: customers | C8: =0*Assumptions!$J$61^(1/4)+'GTM Funnel'!C71 -> 0 | D8: =C8*Assumptions!$J$61^(1/4)+'GTM Funnel'!D71 -> 0 | E8: =D8*Assumptions!$J$61^(1/4)+'GTM Funnel'!E71 -> 0.071275681 | F8: =E8*Assumptions!$J$61^(1/4)+'GTM Funnel'!F71 -> 0.19197739 | G8: =F8*Assumptions!$J$61^(1/4)+'GTM Funnel'!G71 -> 0.3228231 | H8: =G8*Assumptions!$J$61^(1/4)+'GTM Funnel'!H71 -> 0.46386262 | I8: =H8*Assumptions!$J$61^(1/4)+'GTM Funnel'!I71 -> 0.62855328 | J8: =I8*Assumptions!$J$61^(1/4)+'GTM Funnel'!J71 -> 0.81506857 | K8: =J8*Assumptions!$J$61^(1/4)+'GTM Funnel'!K71 -> 1.0636097 | ... N8: =M8*Assumptions!$J$61^(1/4)+'GTM Funnel'!N71 -> 1.9556183 | P8: =F8 -> 0.19197739 | Q8: =J8 -> 0.81506857 | R8: =N8 -> 1.9556183 | S8: =R8 -> 1.9556183
A9: Customers — total | B9: customers | C9: =C6+C7+C8 -> 0 | D9: =D6+D7+D8 -> 1.3004614 | E9: =E6+E7+E8 -> 3.562295 | F9: =F6+F7+F8 -> 6.0391679 | G9: =G6+G7+G8 -> 8.6916321 | H9: =H6+H7+H8 -> 12.029611 | I9: =I6+I7+I8 -> 15.997619 | J9: =J6+J7+J8 -> 21.745385 | ... N9: =N6+N7+N8 -> 49.528099 | P9: =F9 -> 6.0391679 | Q9: =J9 -> 21.745385 | R9: =N9 -> 49.528099 | S9: =R9 -> 49.528099
A10: ARR — SMB | B10: $ | C10: =0*Assumptions!$J$62^(1/4)+'GTM Funnel'!C69*'GTM Funnel'!$C$18 -> 0 | D10: =C10*Assumptions!$J$62^(1/4)+'GTM Funnel'!D69*'GTM Funnel'!$C$18 -> 4636.8467 | E10: =D10*Assumptions!$J$62^(1/4)+'GTM Funnel'!E69*'GTM Funnel'!$C$18 -> 12584.765 | F10: =E10*Assumptions!$J$62^(1/4)+'GTM Funnel'!F69*'GTM Funnel'!$C$18 -> 21354.592 | G10: =F10*Assumptions!$J$62^(1/4)+'GTM Funnel'!G69*'GTM Funnel'!$C$18 -> 30963.182 | H10: =G10*Assumptions!$J$62^(1/4)+'GTM Funnel'!H69*'GTM Funnel'!$C$18 -> 43327.355 | I10: =H10*Assumptions!$J$62^(1/4)+'GTM Funnel'!I69*'GTM Funnel'!$C$18 -> 58265.379 | J10: =I10*Assumptions!$J$62^(1/4)+'GTM Funnel'!J69*'GTM Funnel'!$C$18 -> 80372.849 | K10: =J10*Assumptions!$J$62^(1/4)+'GTM Funnel'!K69*'GTM Funnel'!$C$18 -> 108969.43 | ... N10: =M10*Assumptions!$J$62^(1/4)+'GTM Funnel'!N69*'GTM Funnel'!$C$18 -> 192869.73 | P10: =F10 -> 21354.592 | Q10: =J10 -> 80372.849 | R10: =N10 -> 192869.73 | S10: =R10 -> 192869.73
A11: ARR — Mid-Market | B11: $ | C11: =0*Assumptions!$J$63^(1/4)+'GTM Funnel'!C70*'GTM Funnel'!$C$19 -> 0 | D11: =C11*Assumptions!$J$63^(1/4)+'GTM Funnel'!D70*'GTM Funnel'!$C$19 -> 4239.5865 | E11: =D11*Assumptions!$J$63^(1/4)+'GTM Funnel'!E70*'GTM Funnel'!$C$19 -> 11568.781 | F11: =E11*Assumptions!$J$63^(1/4)+'GTM Funnel'!F70*'GTM Funnel'!$C$19 -> 19757.014 | G11: =F11*Assumptions!$J$63^(1/4)+'GTM Funnel'!G70*'GTM Funnel'!$C$19 -> 28832.303 | H11: =G11*Assumptions!$J$63^(1/4)+'GTM Funnel'!H70*'GTM Funnel'!$C$19 -> 40337.243 | I11: =H11*Assumptions!$J$63^(1/4)+'GTM Funnel'!I70*'GTM Funnel'!$C$19 -> 54161.865 | J11: =I11*Assumptions!$J$63^(1/4)+'GTM Funnel'!J70*'GTM Funnel'!$C$19 -> 73376.768 | K11: =J11*Assumptions!$J$63^(1/4)+'GTM Funnel'!K70*'GTM Funnel'!$C$19 -> 97657.375 | ... N11: =M11*Assumptions!$J$63^(1/4)+'GTM Funnel'!N70*'GTM Funnel'!$C$19 -> 171121.91 | P11: =F11 -> 19757.014 | Q11: =J11 -> 73376.768 | R11: =N11 -> 171121.91 | S11: =R11 -> 171121.91
A12: ARR — Enterprise | B12: $ | C12: =0*Assumptions!$J$64^(1/4)+'GTM Funnel'!C71*'GTM Funnel'!$C$20 -> 0 | D12: =C12*Assumptions!$J$64^(1/4)+'GTM Funnel'!D71*'GTM Funnel'!$C$20 -> 0 | E12: =D12*Assumptions!$J$64^(1/4)+'GTM Funnel'!E71*'GTM Funnel'!$C$20 -> 4403.2873 | F12: =E12*Assumptions!$J$64^(1/4)+'GTM Funnel'!F71*'GTM Funnel'!$C$20 -> 12107.439 | G12: =F12*Assumptions!$J$64^(1/4)+'GTM Funnel'!G71*'GTM Funnel'!$C$20 -> 20866.044 | H12: =G12*Assumptions!$J$64^(1/4)+'GTM Funnel'!H71*'GTM Funnel'!$C$20 -> 30732.603 | I12: =H12*Assumptions!$J$64^(1/4)+'GTM Funnel'!I71*'GTM Funnel'!$C$20 -> 42590.872 | J12: =I12*Assumptions!$J$64^(1/4)+'GTM Funnel'!J71*'GTM Funnel'!$C$20 -> 56428.979 | K12: =J12*Assumptions!$J$64^(1/4)+'GTM Funnel'!K71*'GTM Funnel'!$C$20 -> 74828.695 | ... N12: =M12*Assumptions!$J$64^(1/4)+'GTM Funnel'!N71*'GTM Funnel'!$C$20 -> 145621.09 | P12: =F12 -> 12107.439 | Q12: =J12 -> 56428.979 | R12: =N12 -> 145621.09 | S12: =R12 -> 145621.09
A13: ARR — total (end of quarter) | B13: $ | C13: =C10+C11+C12 -> 0 | D13: =D10+D11+D12 -> 8876.4332 | E13: =E10+E11+E12 -> 28556.833 | F13: =F10+F11+F12 -> 53219.045 | G13: =G10+G11+G12 -> 80661.528 | H13: =H10+H11+H12 -> 114397.2 | I13: =I10+I11+I12 -> 155018.12 | J13: =J10+J11+J12 -> 210178.6 | ... N13: =N10+N11+N12 -> 509612.73 | P13: =F13 -> 53219.045 | Q13: =J13 -> 210178.6 | R13: =N13 -> 509612.73 | S13: =R13 -> 509612.73
A14: New ARR booked (first-year ACV) | B14: $ | C14: ='GTM Funnel'!C69*'GTM Funnel'!$C$18+'GTM Funnel'!C70*'GTM Funnel'!$C$19+'GTM Funnel'!C71*'GTM Funnel'!$C$20 -> 0 | D14: ='GTM Funnel'!D69*'GTM Funnel'!$C$18+'GTM Funnel'!D70*'GTM Funnel'!$C$19+'GTM Funnel'!D71*'GTM Funnel'!$C$20 -> 8876.4332 | E14: ='GTM Funnel'!E69*'GTM Funnel'!$C$18+'GTM Funnel'!E70*'GTM Funnel'!$C$19+'GTM Funnel'!E71*'GTM Funnel'!$C$20 -> 19618.189 | F14: ='GTM Funnel'!F69*'GTM Funnel'!$C$18+'GTM Funnel'!F70*'GTM Funnel'!$C$19+'GTM Funnel'!F71*'GTM Funnel'!$C$20 -> 24335.881 | G14: ='GTM Funnel'!G69*'GTM Funnel'!$C$18+'GTM Funnel'!G70*'GTM Funnel'!$C$19+'GTM Funnel'!G71*'GTM Funnel'!$C$20 -> 26722.055 | H14: ='GTM Funnel'!H69*'GTM Funnel'!$C$18+'GTM Funnel'!H70*'GTM Funnel'!$C$19+'GTM Funnel'!H71*'GTM Funnel'!$C$20 -> 32570.635 | I14: ='GTM Funnel'!I69*'GTM Funnel'!$C$18+'GTM Funnel'!I70*'GTM Funnel'!$C$19+'GTM Funnel'!I71*'GTM Funnel'!$C$20 -> 38936.221 | J14: ='GTM Funnel'!J69*'GTM Funnel'!$C$18+'GTM Funnel'!J70*'GTM Funnel'!$C$19+'GTM Funnel'!J71*'GTM Funnel'!$C$20 -> 52851.267 | ... N14: ='GTM Funnel'!N69*'GTM Funnel'!$C$18+'GTM Funnel'!N70*'GTM Funnel'!$C$19+'GTM Funnel'!N71*'GTM Funnel'!$C$20 -> 68944.23 | P14: =SUM(C14:F14) -> 52830.503 | Q14: =SUM(G14:J14) -> 151080.18 | R14: =SUM(K14:N14) -> 280508.08 | S14: =SUM(P14:R14) -> 484418.76
A15: Recognized revenue (average ARR ÷ 4) | B15: $ | C15: =(0+C13)/8 -> 0 | D15: =(C13+D13)/8 -> 1109.5541 | E15: =(D13+E13)/8 -> 4679.1583 | F15: =(E13+F13)/8 -> 10221.985 | G15: =(F13+G13)/8 -> 16735.072 | H15: =(G13+H13)/8 -> 24382.341 | I15: =(H13+I13)/8 -> 33676.915 | J15: =(I13+J13)/8 -> 45649.589 | K15: =(J13+K13)/8 -> 61454.262 | ... N15: =(M13+N13)/8 -> 117975.42 | P15: =SUM(C15:F15) -> 16010.697 | Q15: =SUM(G15:J15) -> 120443.92 | R15: =SUM(K15:N15) -> 358369.17 | S15: =SUM(P15:R15) -> 494823.78
A16: Gross profit | B16: $ | C16: =C15*Assumptions!$J$76 -> 0 | D16: =D15*Assumptions!$J$76 -> 721.2102 | E16: =E15*Assumptions!$J$76 -> 3041.4529 | F16: =F15*Assumptions!$J$76 -> 6644.2901 | G16: =G15*Assumptions!$J$76 -> 10877.797 | H16: =H15*Assumptions!$J$76 -> 15848.522 | I16: =I15*Assumptions!$J$76 -> 21889.994 | J16: =J15*Assumptions!$J$76 -> 29672.233 | ... N16: =N15*Assumptions!$J$76 -> 76684.024 | P16: =SUM(C16:F16) -> 10406.953 | Q16: =SUM(G16:J16) -> 78288.546 | R16: =SUM(K16:N16) -> 232939.96 | S16: =SUM(P16:R16) -> 321635.46

Sheet Unit Economics
A1: Unit Economics — cost, P&L, NPV and Option 0
A2: Incremental cost only. NPV discounts quarterly at the hurdle rate and haircuts gross profit for wins that would have happened anyway. Option 0 redeploys the same non-CS spend into Clay's core motion.
A3: ="Live run: "&Assumptions!$E$5&" · "&Assumptions!$E$4&" · "&Assumptions!$E$6 -> Live run: Industrial distribution · Base · Lean partner-led pilot
A5: Incremental program cost | B5: Unit / note | C5: Q1 2027 | D5: Q2 2027 | E5: Q3 2027 | F5: Q4 2027 | G5: Q1 2028 | H5: Q2 2028 | I5: Q3 2028 | J5: Q4 2028 | K5: Q1 2029 | L5: Q2 2029 | M5: Q3 2029 | N5: Q4 2029 | P5: 2027 | Q5: 2028 | R5: 2029 | S5: 2027–29
A6: FTE — vertical lead | B6: FTE | C6: =Assumptions!$J$97*'GTM Funnel'!C28 -> 1 | D6: =Assumptions!$J$97*'GTM Funnel'!D28 -> 1 | E6: =Assumptions!$J$97*'GTM Funnel'!E28 -> 1 | F6: =Assumptions!$J$97*'GTM Funnel'!F28 -> 1 | G6: =Assumptions!$J$97*'GTM Funnel'!G28 -> 1 | H6: =Assumptions!$J$97*'GTM Funnel'!H28 -> 1 | I6: =Assumptions!$J$97*'GTM Funnel'!I28 -> 1 | J6: =Assumptions!$J$97*'GTM Funnel'!J28 -> 1 | ... N6: =Assumptions!$J$97*'GTM Funnel'!N28 -> 1 | P6: =AVERAGE(C6:F6) -> 1 | Q6: =AVERAGE(G6:J6) -> 1 | R6: =AVERAGE(K6:N6) -> 1
A7: FTE — dedicated AEs | B7: FTE | C7: ='GTM Funnel'!C41*'GTM Funnel'!C28 -> 0 | D7: ='GTM Funnel'!D41*'GTM Funnel'!D28 -> 0 | E7: ='GTM Funnel'!E41*'GTM Funnel'!E28 -> 0 | F7: ='GTM Funnel'!F41*'GTM Funnel'!F28 -> 0 | G7: ='GTM Funnel'!G41*'GTM Funnel'!G28 -> 0 | H7: ='GTM Funnel'!H41*'GTM Funnel'!H28 -> 0 | I7: ='GTM Funnel'!I41*'GTM Funnel'!I28 -> 0 | J7: ='GTM Funnel'!J41*'GTM Funnel'!J28 -> 0 | ... N7: ='GTM Funnel'!N41*'GTM Funnel'!N28 -> 0 | P7: =AVERAGE(C7:F7) -> 0 | Q7: =AVERAGE(G7:J7) -> 0 | R7: =AVERAGE(K7:N7) -> 0
A8: FTE — partner managers | B8: FTE | C8: =IF('GTM Funnel'!C27<=4,Assumptions!$J$98,Assumptions!$J$99)*'GTM Funnel'!C28 -> 0 | D8: =IF('GTM Funnel'!D27<=4,Assumptions!$J$98,Assumptions!$J$99)*'GTM Funnel'!D28 -> 0 | E8: =IF('GTM Funnel'!E27<=4,Assumptions!$J$98,Assumptions!$J$99)*'GTM Funnel'!E28 -> 0 | F8: =IF('GTM Funnel'!F27<=4,Assumptions!$J$98,Assumptions!$J$99)*'GTM Funnel'!F28 -> 0 | G8: =IF('GTM Funnel'!G27<=4,Assumptions!$J$98,Assumptions!$J$99)*'GTM Funnel'!G28 -> 0.5 | H8: =IF('GTM Funnel'!H27<=4,Assumptions!$J$98,Assumptions!$J$99)*'GTM Funnel'!H28 -> 0.5 | I8: =IF('GTM Funnel'!I27<=4,Assumptions!$J$98,Assumptions!$J$99)*'GTM Funnel'!I28 -> 0.5 | J8: =IF('GTM Funnel'!J27<=4,Assumptions!$J$98,Assumptions!$J$99)*'GTM Funnel'!J28 -> 0.5 | ... N8: =IF('GTM Funnel'!N27<=4,Assumptions!$J$98,Assumptions!$J$99)*'GTM Funnel'!N28 -> 0.5 | P8: =AVERAGE(C8:F8) -> 0 | Q8: =AVERAGE(G8:J8) -> 0.5 | R8: =AVERAGE(K8:N8) -> 0.5
A9: FTE — GTM / solutions engineers | B9: FTE | C9: =IF('GTM Funnel'!C27<=4,Assumptions!$J$100,Assumptions!$J$101)*'GTM Funnel'!C28 -> 1 | D9: =IF('GTM Funnel'!D27<=4,Assumptions!$J$100,Assumptions!$J$101)*'GTM Funnel'!D28 -> 1 | E9: =IF('GTM Funnel'!E27<=4,Assumptions!$J$100,Assumptions!$J$101)*'GTM Funnel'!E28 -> 1 | F9: =IF('GTM Funnel'!F27<=4,Assumptions!$J$100,Assumptions!$J$101)*'GTM Funnel'!F28 -> 1 | G9: =IF('GTM Funnel'!G27<=4,Assumptions!$J$100,Assumptions!$J$101)*'GTM Funnel'!G28 -> 0.5 | H9: =IF('GTM Funnel'!H27<=4,Assumptions!$J$100,Assumptions!$J$101)*'GTM Funnel'!H28 -> 0.5 | I9: =IF('GTM Funnel'!I27<=4,Assumptions!$J$100,Assumptions!$J$101)*'GTM Funnel'!I28 -> 0.5 | J9: =IF('GTM Funnel'!J27<=4,Assumptions!$J$100,Assumptions!$J$101)*'GTM Funnel'!J28 -> 0.5 | ... N9: =IF('GTM Funnel'!N27<=4,Assumptions!$J$100,Assumptions!$J$101)*'GTM Funnel'!N28 -> 0.5 | P9: =AVERAGE(C9:F9) -> 1 | Q9: =AVERAGE(G9:J9) -> 0.5 | R9: =AVERAGE(K9:N9) -> 0.5
A10: FTE — product marketing | B10: FTE | C10: =Assumptions!$J$102*'GTM Funnel'!C28 -> 0.25 | D10: =Assumptions!$J$102*'GTM Funnel'!D28 -> 0.25 | E10: =Assumptions!$J$102*'GTM Funnel'!E28 -> 0.25 | F10: =Assumptions!$J$102*'GTM Funnel'!F28 -> 0.25 | G10: =Assumptions!$J$102*'GTM Funnel'!G28 -> 0.25 | H10: =Assumptions!$J$102*'GTM Funnel'!H28 -> 0.25 | I10: =Assumptions!$J$102*'GTM Funnel'!I28 -> 0.25 | J10: =Assumptions!$J$102*'GTM Funnel'!J28 -> 0.25 | ... N10: =Assumptions!$J$102*'GTM Funnel'!N28 -> 0.25 | P10: =AVERAGE(C10:F10) -> 0.25 | Q10: =AVERAGE(G10:J10) -> 0.25 | R10: =AVERAGE(K10:N10) -> 0.25
A11: FTE — customer success | B11: FTE | C11: =('Revenue Model'!C7+'Revenue Model'!C8)/Assumptions!$J$74+'Revenue Model'!C6/Assumptions!$J$75 -> 0 | D11: =('Revenue Model'!D7+'Revenue Model'!D8)/Assumptions!$J$74+'Revenue Model'!D6/Assumptions!$J$75 -> 0.01431763 | E11: =('Revenue Model'!E7+'Revenue Model'!E8)/Assumptions!$J$74+'Revenue Model'!E6/Assumptions!$J$75 -> 0.040249946 | F11: =('Revenue Model'!F7+'Revenue Model'!F8)/Assumptions!$J$74+'Revenue Model'!F6/Assumptions!$J$75 -> 0.069296157 | G11: =('Revenue Model'!G7+'Revenue Model'!G8)/Assumptions!$J$74+'Revenue Model'!G6/Assumptions!$J$75 -> 0.10047508 | H11: =('Revenue Model'!H7+'Revenue Model'!H8)/Assumptions!$J$74+'Revenue Model'!H6/Assumptions!$J$75 -> 0.13908464 | I11: =('Revenue Model'!I7+'Revenue Model'!I8)/Assumptions!$J$74+'Revenue Model'!I6/Assumptions!$J$75 -> 0.18475608 | J11: =('Revenue Model'!J7+'Revenue Model'!J8)/Assumptions!$J$74+'Revenue Model'!J6/Assumptions!$J$75 -> 0.24847388 | ... N11: =('Revenue Model'!N7+'Revenue Model'!N8)/Assumptions!$J$74+'Revenue Model'!N6/Assumptions!$J$75 -> 0.55775357 | P11: =AVERAGE(C11:F11) -> 0.030965933 | Q11: =AVERAGE(G11:J11) -> 0.16819742 | R11: =AVERAGE(K11:N11) -> 0.44574486
A12: Cost — vertical lead + partner managers | B12: $ | C12: =(C6+C8)*Assumptions!$J$70/Assumptions!$J$69/4 -> 66753.571 | D12: =(D6+D8)*Assumptions!$J$70/Assumptions!$J$69/4 -> 66753.571 | E12: =(E6+E8)*Assumptions!$J$70/Assumptions!$J$69/4 -> 66753.571 | F12: =(F6+F8)*Assumptions!$J$70/Assumptions!$J$69/4 -> 66753.571 | G12: =(G6+G8)*Assumptions!$J$70/Assumptions!$J$69/4 -> 100130.36 | H12: =(H6+H8)*Assumptions!$J$70/Assumptions!$J$69/4 -> 100130.36 | I12: =(I6+I8)*Assumptions!$J$70/Assumptions!$J$69/4 -> 100130.36 | J12: =(J6+J8)*Assumptions!$J$70/Assumptions!$J$69/4 -> 100130.36 | ... N12: =(N6+N8)*Assumptions!$J$70/Assumptions!$J$69/4 -> 100130.36 | P12: =SUM(C12:F12) -> 267014.29 | Q12: =SUM(G12:J12) -> 400521.43 | R12: =SUM(K12:N12) -> 400521.43 | S12: =SUM(P12:R12) -> 1068057.1
A13: Cost — dedicated AEs | B13: $ | C13: =C7*'GTM Funnel'!$C$22/4 -> 0 | D13: =D7*'GTM Funnel'!$C$22/4 -> 0 | E13: =E7*'GTM Funnel'!$C$22/4 -> 0 | F13: =F7*'GTM Funnel'!$C$22/4 -> 0 | G13: =G7*'GTM Funnel'!$C$22/4 -> 0 | H13: =H7*'GTM Funnel'!$C$22/4 -> 0 | I13: =I7*'GTM Funnel'!$C$22/4 -> 0 | J13: =J7*'GTM Funnel'!$C$22/4 -> 0 | ... N13: =N7*'GTM Funnel'!$C$22/4 -> 0 | P13: =SUM(C13:F13) -> 0 | Q13: =SUM(G13:J13) -> 0 | R13: =SUM(K13:N13) -> 0 | S13: =SUM(P13:R13) -> 0
A14: Cost — variable AE cost (shared capacity) | B14: $ | C14: =MAX(0,('Revenue Model'!C14-'GTM Funnel'!C63*'GTM Funnel'!$C$18)-'GTM Funnel'!C42*'GTM Funnel'!$C$23)*'GTM Funnel'!$C$24*Assumptions!$J$105 -> 0 | D14: =MAX(0,('Revenue Model'!D14-'GTM Funnel'!D63*'GTM Funnel'!$C$18)-'GTM Funnel'!D42*'GTM Funnel'!$C$23)*'GTM Funnel'!$C$24*Assumptions!$J$105 -> 3491.7221 | E14: =MAX(0,('Revenue Model'!E14-'GTM Funnel'!E63*'GTM Funnel'!$C$18)-'GTM Funnel'!E42*'GTM Funnel'!$C$23)*'GTM Funnel'!$C$24*Assumptions!$J$105 -> 8039.0965 | F14: =MAX(0,('Revenue Model'!F14-'GTM Funnel'!F63*'GTM Funnel'!$C$18)-'GTM Funnel'!F42*'GTM Funnel'!$C$23)*'GTM Funnel'!$C$24*Assumptions!$J$105 -> 10124.75 | G14: =MAX(0,('Revenue Model'!G14-'GTM Funnel'!G63*'GTM Funnel'!$C$18)-'GTM Funnel'!G42*'GTM Funnel'!$C$23)*'GTM Funnel'!$C$24*Assumptions!$J$105 -> 11120.456 | H14: =MAX(0,('Revenue Model'!H14-'GTM Funnel'!H63*'GTM Funnel'!$C$18)-'GTM Funnel'!H42*'GTM Funnel'!$C$23)*'GTM Funnel'!$C$24*Assumptions!$J$105 -> 13463.036 | I14: =MAX(0,('Revenue Model'!I14-'GTM Funnel'!I63*'GTM Funnel'!$C$18)-'GTM Funnel'!I42*'GTM Funnel'!$C$23)*'GTM Funnel'!$C$24*Assumptions!$J$105 -> 16072.216 | J14: =MAX(0,('Revenue Model'!J14-'GTM Funnel'!J63*'GTM Funnel'!$C$18)-'GTM Funnel'!J42*'GTM Funnel'!$C$23)*'GTM Funnel'!$C$24*Assumptions!$J$105 -> 21559.896 | ... N14: =MAX(0,('Revenue Model'!N14-'GTM Funnel'!N63*'GTM Funnel'!$C$18)-'GTM Funnel'!N42*'GTM Funnel'!$C$23)*'GTM Funnel'!$C$24*Assumptions!$J$105 -> 28360.671 | P14: =SUM(C14:F14) -> 21655.569 | Q14: =SUM(G14:J14) -> 62215.604 | R14: =SUM(K14:N14) -> 115106.25 | S14: =SUM(P14:R14) -> 198977.42
A15: Cost — product marketing | B15: $ | C15: =C10*Assumptions!$J$71/Assumptions!$J$69/4 -> 18475.893 | D15: =D10*Assumptions!$J$71/Assumptions!$J$69/4 -> 18475.893 | E15: =E10*Assumptions!$J$71/Assumptions!$J$69/4 -> 18475.893 | F15: =F10*Assumptions!$J$71/Assumptions!$J$69/4 -> 18475.893 | G15: =G10*Assumptions!$J$71/Assumptions!$J$69/4 -> 18475.893 | H15: =H10*Assumptions!$J$71/Assumptions!$J$69/4 -> 18475.893 | I15: =I10*Assumptions!$J$71/Assumptions!$J$69/4 -> 18475.893 | J15: =J10*Assumptions!$J$71/Assumptions!$J$69/4 -> 18475.893 | ... N15: =N10*Assumptions!$J$71/Assumptions!$J$69/4 -> 18475.893 | P15: =SUM(C15:F15) -> 73903.571 | Q15: =SUM(G15:J15) -> 73903.571 | R15: =SUM(K15:N15) -> 73903.571 | S15: =SUM(P15:R15) -> 221710.71
A16: Cost — programs and launches | B16: $ | C16: =(Assumptions!$J$103+Assumptions!$J$77*(('GTM Funnel'!C27=Assumptions!$J$13)+('GTM Funnel'!C27=Assumptions!$J$14)+('GTM Funnel'!C27=Assumptions!$J$15)))*'GTM Funnel'!C28 -> 65000 | D16: =(Assumptions!$J$103+Assumptions!$J$77*(('GTM Funnel'!D27=Assumptions!$J$13)+('GTM Funnel'!D27=Assumptions!$J$14)+('GTM Funnel'!D27=Assumptions!$J$15)))*'GTM Funnel'!D28 -> 25000 | E16: =(Assumptions!$J$103+Assumptions!$J$77*(('GTM Funnel'!E27=Assumptions!$J$13)+('GTM Funnel'!E27=Assumptions!$J$14)+('GTM Funnel'!E27=Assumptions!$J$15)))*'GTM Funnel'!E28 -> 25000 | F16: =(Assumptions!$J$103+Assumptions!$J$77*(('GTM Funnel'!F27=Assumptions!$J$13)+('GTM Funnel'!F27=Assumptions!$J$14)+('GTM Funnel'!F27=Assumptions!$J$15)))*'GTM Funnel'!F28 -> 25000 | G16: =(Assumptions!$J$103+Assumptions!$J$77*(('GTM Funnel'!G27=Assumptions!$J$13)+('GTM Funnel'!G27=Assumptions!$J$14)+('GTM Funnel'!G27=Assumptions!$J$15)))*'GTM Funnel'!G28 -> 65000 | H16: =(Assumptions!$J$103+Assumptions!$J$77*(('GTM Funnel'!H27=Assumptions!$J$13)+('GTM Funnel'!H27=Assumptions!$J$14)+('GTM Funnel'!H27=Assumptions!$J$15)))*'GTM Funnel'!H28 -> 25000 | I16: =(Assumptions!$J$103+Assumptions!$J$77*(('GTM Funnel'!I27=Assumptions!$J$13)+('GTM Funnel'!I27=Assumptions!$J$14)+('GTM Funnel'!I27=Assumptions!$J$15)))*'GTM Funnel'!I28 -> 65000 | J16: =(Assumptions!$J$103+Assumptions!$J$77*(('GTM Funnel'!J27=Assumptions!$J$13)+('GTM Funnel'!J27=Assumptions!$J$14)+('GTM Funnel'!J27=Assumptions!$J$15)))*'GTM Funnel'!J28 -> 25000 | ... N16: =(Assumptions!$J$103+Assumptions!$J$77*(('GTM Funnel'!N27=Assumptions!$J$13)+('GTM Funnel'!N27=Assumptions!$J$14)+('GTM Funnel'!N27=Assumptions!$J$15)))*'GTM Funnel'!N28 -> 25000 | P16: =SUM(C16:F16) -> 140000 | Q16: =SUM(G16:J16) -> 180000 | R16: =SUM(K16:N16) -> 100000 | S16: =SUM(P16:R16) -> 420000
A17: Cost — partner fees | B17: $ | C17: ='Revenue Model'!C14*'GTM Funnel'!C62*Assumptions!$J$79 -> 0 | D17: ='Revenue Model'!D14*'GTM Funnel'!D62*Assumptions!$J$79 -> 815.33887 | E17: ='Revenue Model'!E14*'GTM Funnel'!E62*Assumptions!$J$79 -> 1576.9545 | F17: ='Revenue Model'!F14*'GTM Funnel'!F62*Assumptions!$J$79 -> 2363.7876 | G17: ='Revenue Model'!G14*'GTM Funnel'!G62*Assumptions!$J$79 -> 2961.2332 | H17: ='Revenue Model'!H14*'GTM Funnel'!H62*Assumptions!$J$79 -> 3401.8567 | I17: ='Revenue Model'!I14*'GTM Funnel'!I62*Assumptions!$J$79 -> 3951.441 | J17: ='Revenue Model'!J14*'GTM Funnel'!J62*Assumptions!$J$79 -> 4240.176 | ... N17: ='Revenue Model'!N14*'GTM Funnel'!N62*Assumptions!$J$79 -> 5685.062 | P17: =SUM(C17:F17) -> 4756.081 | Q17: =SUM(G17:J17) -> 14554.707 | R17: =SUM(K17:N17) -> 21805.256 | S17: =SUM(P17:R17) -> 41116.044
A18: Cost — partner enablement | B18: $ | C18: ='GTM Funnel'!C47*Assumptions!$J$80 -> 4000 | D18: ='GTM Funnel'!D47*Assumptions!$J$80 -> 6000 | E18: ='GTM Funnel'!E47*Assumptions!$J$80 -> 8000 | F18: ='GTM Funnel'!F47*Assumptions!$J$80 -> 10000 | G18: ='GTM Funnel'!G47*Assumptions!$J$80 -> 12000 | H18: ='GTM Funnel'!H47*Assumptions!$J$80 -> 14000 | I18: ='GTM Funnel'!I47*Assumptions!$J$80 -> 16000 | J18: ='GTM Funnel'!J47*Assumptions!$J$80 -> 18000 | ... N18: ='GTM Funnel'!N47*Assumptions!$J$80 -> 20000 | P18: =SUM(C18:F18) -> 28000 | Q18: =SUM(G18:J18) -> 60000 | R18: =SUM(K18:N18) -> 80000 | S18: =SUM(P18:R18) -> 168000
A19: Cost — onboarding subsidy (MM & Ent) | B19: $ | C19: =('GTM Funnel'!C70*'GTM Funnel'!$C$19+'GTM Funnel'!C71*'GTM Funnel'!$C$20)*Assumptions!$J$81 -> 0 | D19: =('GTM Funnel'!D70*'GTM Funnel'!$C$19+'GTM Funnel'!D71*'GTM Funnel'!$C$20)*Assumptions!$J$81 -> 635.93797 | E19: =('GTM Funnel'!E70*'GTM Funnel'!$C$19+'GTM Funnel'!E71*'GTM Funnel'!$C$20)*Assumptions!$J$81 -> 1750.5406 | F19: =('GTM Funnel'!F70*'GTM Funnel'!$C$19+'GTM Funnel'!F71*'GTM Funnel'!$C$20)*Assumptions!$J$81 -> 2334.9081 | G19: =('GTM Funnel'!G70*'GTM Funnel'!$C$19+'GTM Funnel'!G71*'GTM Funnel'!$C$20)*Assumptions!$J$81 -> 2567.0198 | H19: =('GTM Funnel'!H70*'GTM Funnel'!$C$19+'GTM Funnel'!H71*'GTM Funnel'!$C$20)*Assumptions!$J$81 -> 3030.9692 | I19: =('GTM Funnel'!I70*'GTM Funnel'!$C$19+'GTM Funnel'!I71*'GTM Funnel'!$C$20)*Assumptions!$J$81 -> 3599.7295 | J19: =('GTM Funnel'!J70*'GTM Funnel'!$C$19+'GTM Funnel'!J71*'GTM Funnel'!$C$20)*Assumptions!$J$81 -> 4611.5697 | ... N19: =('GTM Funnel'!N70*'GTM Funnel'!$C$19+'GTM Funnel'!N71*'GTM Funnel'!$C$20)*Assumptions!$J$81 -> 6268.6132 | P19: =SUM(C19:F19) -> 4721.3866 | Q19: =SUM(G19:J19) -> 13809.288 | R19: =SUM(K19:N19) -> 25201.68 | S19: =SUM(P19:R19) -> 43732.355
A20: Sales & marketing cost (CAC basis) | B20: $ | C20: =C12+C13+C14+C15+C16+C17+C18+C19 -> 154229.46 | D20: =D12+D13+D14+D15+D16+D17+D18+D19 -> 121172.46 | E20: =E12+E13+E14+E15+E16+E17+E18+E19 -> 129596.06 | F20: =F12+F13+F14+F15+F16+F17+F18+F19 -> 135052.91 | G20: =G12+G13+G14+G15+G16+G17+G18+G19 -> 212254.96 | H20: =H12+H13+H14+H15+H16+H17+H18+H19 -> 177502.11 | I20: =I12+I13+I14+I15+I16+I17+I18+I19 -> 223229.64 | J20: =J12+J13+J14+J15+J16+J17+J18+J19 -> 192017.89 | ... N20: =N12+N13+N14+N15+N16+N17+N18+N19 -> 203920.6 | P20: =SUM(C20:F20) -> 540050.89 | Q20: =SUM(G20:J20) -> 805004.6 | R20: =SUM(K20:N20) -> 816538.18 | S20: =SUM(P20:R20) -> 2161593.7
A21: Cost — GTM / solutions engineers | B21: $ | C21: =C9*Assumptions!$J$72/Assumptions!$J$69/4 -> 56535.714 | D21: =D9*Assumptions!$J$72/Assumptions!$J$69/4 -> 56535.714 | E21: =E9*Assumptions!$J$72/Assumptions!$J$69/4 -> 56535.714 | F21: =F9*Assumptions!$J$72/Assumptions!$J$69/4 -> 56535.714 | G21: =G9*Assumptions!$J$72/Assumptions!$J$69/4 -> 28267.857 | H21: =H9*Assumptions!$J$72/Assumptions!$J$69/4 -> 28267.857 | I21: =I9*Assumptions!$J$72/Assumptions!$J$69/4 -> 28267.857 | J21: =J9*Assumptions!$J$72/Assumptions!$J$69/4 -> 28267.857 | ... N21: =N9*Assumptions!$J$72/Assumptions!$J$69/4 -> 28267.857 | P21: =SUM(C21:F21) -> 226142.86 | Q21: =SUM(G21:J21) -> 113071.43 | R21: =SUM(K21:N21) -> 113071.43 | S21: =SUM(P21:R21) -> 452285.71
A22: Cost — template & connector build | B22: $ | C22: =IF('GTM Funnel'!C27<=Assumptions!$J$83,Assumptions!$J$82*Assumptions!$J$108/Assumptions!$J$83,0) -> 62500 | D22: =IF('GTM Funnel'!D27<=Assumptions!$J$83,Assumptions!$J$82*Assumptions!$J$108/Assumptions!$J$83,0) -> 62500 | E22: =IF('GTM Funnel'!E27<=Assumptions!$J$83,Assumptions!$J$82*Assumptions!$J$108/Assumptions!$J$83,0) -> 62500 | F22: =IF('GTM Funnel'!F27<=Assumptions!$J$83,Assumptions!$J$82*Assumptions!$J$108/Assumptions!$J$83,0) -> 62500 | G22: =IF('GTM Funnel'!G27<=Assumptions!$J$83,Assumptions!$J$82*Assumptions!$J$108/Assumptions!$J$83,0) -> 0 | H22: =IF('GTM Funnel'!H27<=Assumptions!$J$83,Assumptions!$J$82*Assumptions!$J$108/Assumptions!$J$83,0) -> 0 | I22: =IF('GTM Funnel'!I27<=Assumptions!$J$83,Assumptions!$J$82*Assumptions!$J$108/Assumptions!$J$83,0) -> 0 | J22: =IF('GTM Funnel'!J27<=Assumptions!$J$83,Assumptions!$J$82*Assumptions!$J$108/Assumptions!$J$83,0) -> 0 | ... N22: =IF('GTM Funnel'!N27<=Assumptions!$J$83,Assumptions!$J$82*Assumptions!$J$108/Assumptions!$J$83,0) -> 0 | P22: =SUM(C22:F22) -> 250000 | Q22: =SUM(G22:J22) -> 0 | R22: =SUM(K22:N22) -> 0 | S22: =SUM(P22:R22) -> 250000
A23: Cost — customer success | B23: $ | C23: =C11*Assumptions!$J$73/Assumptions!$J$69/4 -> 0 | D23: =D11*Assumptions!$J$73/Assumptions!$J$69/4 -> 575.31306 | E23: =E11*Assumptions!$J$73/Assumptions!$J$69/4 -> 1617.3291 | F23: =F11*Assumptions!$J$73/Assumptions!$J$69/4 -> 2784.4681 | G23: =G11*Assumptions!$J$73/Assumptions!$J$69/4 -> 4037.3039 | H23: =H11*Assumptions!$J$73/Assumptions!$J$69/4 -> 5588.719 | I23: =I11*Assumptions!$J$73/Assumptions!$J$69/4 -> 7423.8952 | J23: =J11*Assumptions!$J$73/Assumptions!$J$69/4 -> 9984.213 | ... N23: =N11*Assumptions!$J$73/Assumptions!$J$69/4 -> 22411.734 | P23: =SUM(C23:F23) -> 4977.1102 | Q23: =SUM(G23:J23) -> 27034.131 | R23: =SUM(K23:N23) -> 71643.934 | S23: =SUM(P23:R23) -> 103655.18
A24: Total incremental program cost | B24: $ | C24: =C20+C21+C22+C23 -> 273265.18 | D24: =D20+D21+D22+D23 -> 240783.49 | E24: =E20+E21+E22+E23 -> 250249.1 | F24: =F20+F21+F22+F23 -> 256873.09 | G24: =G20+G21+G22+G23 -> 244560.12 | H24: =H20+H21+H22+H23 -> 211358.69 | I24: =I20+I21+I22+I23 -> 258921.39 | J24: =J20+J21+J22+J23 -> 230269.96 | ... N24: =N20+N21+N22+N23 -> 254600.19 | P24: =SUM(C24:F24) -> 1021170.9 | Q24: =SUM(G24:J24) -> 945110.16 | R24: =SUM(K24:N24) -> 1001253.5 | S24: =SUM(P24:R24) -> 2967534.6
A25: Program P&L, NPV and the Option 0 benchmark | B25: Unit / note | C25: Q1 2027 | D25: Q2 2027 | E25: Q3 2027 | F25: Q4 2027 | G25: Q1 2028 | H25: Q2 2028 | I25: Q3 2028 | J25: Q4 2028 | K25: Q1 2029 | L25: Q2 2029 | M25: Q3 2029 | N25: Q4 2029 | P25: 2027 | Q25: 2028 | R25: 2029 | S25: 2027–29
A26: Program P&L (gross profit − incremental cost) | B26: $ | C26: ='Revenue Model'!C16-C24 -> -273265.18 | D26: ='Revenue Model'!D16-D24 -> -240062.28 | E26: ='Revenue Model'!E16-E24 -> -247207.65 | F26: ='Revenue Model'!F16-F24 -> -250228.8 | G26: ='Revenue Model'!G16-G24 -> -233682.32 | H26: ='Revenue Model'!H16-H24 -> -195510.17 | I26: ='Revenue Model'!I16-I24 -> -237031.39 | J26: ='Revenue Model'!J16-J24 -> -200597.73 | ... N26: ='Revenue Model'!N16-N24 -> -177916.16 | P26: =SUM(C26:F26) -> -1010763.9 | Q26: =SUM(G26:J26) -> -866821.61 | R26: =SUM(K26:N26) -> -768313.58 | S26: =SUM(P26:R26) -> -2645899.1
A27: Cumulative program P&L | B27: $ | C27: =0+C26 -> -273265.18 | D27: =C27+D26 -> -513327.46 | E27: =D27+E26 -> -760535.11 | F27: =E27+F26 -> -1010763.9 | G27: =F27+G26 -> -1244446.2 | H27: =G27+H26 -> -1439956.4 | I27: =H27+I26 -> -1676987.8 | J27: =I27+J26 -> -1877585.5 | K27: =J27+K26 -> -2081296.7 | ... N27: =M27+N26 -> -2645899.1 | P27: =F27 -> -1010763.9 | Q27: =J27 -> -1877585.5 | R27: =N27 -> -2645899.1 | S27: =R27 -> -2645899.1
A28: Discount factor (end of quarter) | B28: x | C28: =1/(1+Assumptions!$J$87)^('GTM Funnel'!C27/4) -> 0.97206542 | D28: =1/(1+Assumptions!$J$87)^('GTM Funnel'!D27/4) -> 0.94491118 | E28: =1/(1+Assumptions!$J$87)^('GTM Funnel'!E27/4) -> 0.91851549 | F28: =1/(1+Assumptions!$J$87)^('GTM Funnel'!F27/4) -> 0.89285714 | G28: =1/(1+Assumptions!$J$87)^('GTM Funnel'!G27/4) -> 0.86791555 | H28: =1/(1+Assumptions!$J$87)^('GTM Funnel'!H27/4) -> 0.8436707 | I28: =1/(1+Assumptions!$J$87)^('GTM Funnel'!I27/4) -> 0.82010311 | J28: =1/(1+Assumptions!$J$87)^('GTM Funnel'!J27/4) -> 0.79719388 | ... N28: =1/(1+Assumptions!$J$87)^('GTM Funnel'!N27/4) -> 0.71178025
A29: PV of incremental P&L (gross profit × (1 − haircut) − cost) | B29: $ | C29: =('Revenue Model'!C16*(1-Assumptions!$J$88)-C24)*C28 -> -265631.63 | D29: =('Revenue Model'!D16*(1-Assumptions!$J$88)-D24)*D28 -> -226973.83 | E29: =('Revenue Model'!E16*(1-Assumptions!$J$88)-E24)*E28 -> -227622.78 | F29: =('Revenue Model'!F16*(1-Assumptions!$J$88)-F24)*F28 -> -224605.05 | G29: =('Revenue Model'!G16*(1-Assumptions!$J$88)-G24)*G28 -> -204704.73 | H29: =('Revenue Model'!H16*(1-Assumptions!$J$88)-H24)*H28 -> -167620.39 | I29: =('Revenue Model'!I16*(1-Assumptions!$J$88)-I24)*I28 -> -197980.6 | J29: =('Revenue Model'!J16*(1-Assumptions!$J$88)-J24)*J28 -> -164646.19 | ... N29: =('Revenue Model'!N16*(1-Assumptions!$J$88)-N24)*N28 -> -137553.65 | P29: =SUM(C29:F29) -> -944833.29 | Q29: =SUM(G29:J29) -> -734951.89 | R29: =SUM(K29:N29) -> -606175.15 | S29: =SUM(P29:R29) -> -2285960.3
A30: Option 0: core ARR bought with the same non-CS spend | B30: $ | C30: =(C24-C23)*12/(Assumptions!$J$89*Assumptions!$J$76)*Assumptions!$J$90 -> 189183.59 | D30: =(D24-D23)*12/(Assumptions!$J$89*Assumptions!$J$76)*Assumptions!$J$90 -> 166297.97 | E30: =(E24-E23)*12/(Assumptions!$J$89*Assumptions!$J$76)*Assumptions!$J$90 -> 172129.69 | F30: =(F24-F23)*12/(Assumptions!$J$89*Assumptions!$J$76)*Assumptions!$J$90 -> 175907.51 | G30: =(G24-G23)*12/(Assumptions!$J$89*Assumptions!$J$76)*Assumptions!$J$90 -> 166515.8 | H30: =(H24-H23)*12/(Assumptions!$J$89*Assumptions!$J$76)*Assumptions!$J$90 -> 142456.13 | I30: =(I24-I23)*12/(Assumptions!$J$89*Assumptions!$J$76)*Assumptions!$J$90 -> 174113.65 | J30: =(J24-J23)*12/(Assumptions!$J$89*Assumptions!$J$76)*Assumptions!$J$90 -> 152505.52 | ... N30: =(N24-N23)*12/(Assumptions!$J$89*Assumptions!$J$76)*Assumptions!$J$90 -> 160745.85 | P30: =SUM(C30:F30) -> 703518.75 | Q30: =SUM(G30:J30) -> 635591.1 | R30: =SUM(K30:N30) -> 643575.88 | S30: =SUM(P30:R30) -> 1982685.7
A31: Option 0: core ARR (end of quarter) | B31: $ | C31: =0*Assumptions!$J$92^(1/4)+C30 -> 189183.59 | D31: =C31*Assumptions!$J$92^(1/4)+D30 -> 355952.75 | E31: =D31*Assumptions!$J$92^(1/4)+E30 -> 528969 | F31: =E31*Assumptions!$J$92^(1/4)+F30 -> 706194 | G31: =F31*Assumptions!$J$92^(1/4)+G30 -> 874468.7 | H31: =G31*Assumptions!$J$92^(1/4)+H30 -> 1019102.9 | I31: =H31*Assumptions!$J$92^(1/4)+I30 -> 1195754.8 | J31: =I31*Assumptions!$J$92^(1/4)+J30 -> 1351238.5 | K31: =J31*Assumptions!$J$92^(1/4)+K30 -> 1514130.9 | ... N31: =M31*Assumptions!$J$92^(1/4)+N30 -> 2010731.1 | P31: =F31 -> 706194 | Q31: =J31 -> 1351238.5 | R31: =N31 -> 2010731.1 | S31: =R31 -> 2010731.1
A32: Option 0: P&L (gross profit − spend − CS) | B32: $ | C32: =(0+C31)/8*Assumptions!$J$76-(C24-C23)-C31*Assumptions!$J$93/4 -> -260258.81 | D32: =(C31+D31)/8*Assumptions!$J$76-(D24-D23)-D31*Assumptions!$J$93/4 -> -200365.26 | E32: =(D31+E31)/8*Assumptions!$J$76-(E24-E23)-E31*Assumptions!$J$93/4 -> -183343.99 | F32: =(E31+F31)/8*Assumptions!$J$76-(F24-F23)-F31*Assumptions!$J$93/4 -> -162559.06 | G32: =(F31+G31)/8*Assumptions!$J$76-(G24-G23)-G31*Assumptions!$J$93/4 -> -123024.83 | H32: =(G31+H31)/8*Assumptions!$J$76-(H24-H23)-H31*Assumptions!$J$93/4 -> -64656.066 | I32: =(H31+I31)/8*Assumptions!$J$76-(I24-I23)-I31*Assumptions!$J$93/4 -> -86487.247 | J32: =(I31+J31)/8*Assumptions!$J$76-(J24-J23)-J31*Assumptions!$J$93/4 -> -30233.026 | K32: =(J31+K31)/8*Assumptions!$J$76-(K24-K23)-K31*Assumptions!$J$93/4 -> -16543.113 | ... N32: =(M31+N31)/8*Assumptions!$J$76-(N24-N23)-N31*Assumptions!$J$93/4 -> 55987.165 | P32: =SUM(C32:F32) -> -806527.11 | Q32: =SUM(G32:J32) -> -304401.17 | R32: =SUM(K32:N32) -> 74306.245 | S32: =SUM(P32:R32) -> -1036622
A33: Option 0: PV of P&L | B33: $ | C33: =C32*C28 -> -252988.59 | D33: =D32*D28 -> -189327.37 | E33: =E32*E28 -> -168404.29 | F33: =F32*F28 -> -145142.01 | G33: =G32*G28 -> -106775.16 | H33: =H32*H28 -> -54548.428 | I33: =I32*I28 -> -70928.461 | J33: =J32*J28 -> -24101.583 | ... N33: =N32*N28 -> 39850.558 | P33: =SUM(C33:F33) -> -755862.27 | Q33: =SUM(G33:J33) -> -256353.64 | R33: =SUM(K33:N33) -> 52657.75 | S33: =SUM(P33:R33) -> -959558.16
A34: ARR-weighted GRR of new customers | C34: =IFERROR(('GTM Funnel'!S69*'GTM Funnel'!$C$18*Assumptions!$J$59+'GTM Funnel'!S70*'GTM Funnel'!$C$19*Assumptions!$J$60+'GTM Funnel'!S71*'GTM Funnel'!$C$20*Assumptions!$J$61)/('GTM Funnel'!S69*'GTM Funnel'!$C$18+'GTM Funnel'!S70*'GTM Funnel'!$C$19+'GTM Funnel'!S71*'GTM Funnel'!$C$20),0.9) -> 0.89737218
A35: CS cost as % of ARR at exit | C35: =IFERROR(N23*4/'Revenue Model'!N13,0) -> 0.17591188
A36: grr ÷ (1 + discount rate) | C36: =$C$34/(1+Assumptions!$J$87) -> 0.80122516
A37: Option 0: grr0 ÷ (1 + discount rate) | C37: =Assumptions!$J$91/(1+Assumptions!$J$87) -> 0.80357143
A38: Key outputs of this run | B38: Unit / note | C38: Q1 2027 | D38: Q2 2027 | E38: Q3 2027 | F38: Q4 2027 | G38: Q1 2028 | H38: Q2 2028 | I38: Q3 2028 | J38: Q4 2028 | K38: Q1 2029 | L38: Q2 2029 | M38: Q3 2029 | N38: Q4 2029 | P38: 2027 | Q38: 2028 | R38: 2029 | S38: 2027–29
A39: Exit ARR, Q4 2029 | C39: ='Revenue Model'!N13 -> 509612.73
A40: Customers, Q4 2029 | C40: ='Revenue Model'!N9 -> 49.528099
A41: New customers 2027–29 | C41: ='GTM Funnel'!S72 -> 54.749119
A42: Recognized revenue 2027–29 | C42: ='Revenue Model'!S15 -> 494823.78
A43: Average first-year ACV | C43: =IFERROR('Revenue Model'!S14/'GTM Funnel'!S72,0) -> 8847.9735
A44: CAC, fully loaded (S&M ÷ new customers) | C44: =IFERROR(S20/'GTM Funnel'!S72,0) -> 39481.798
A45: CAC, marginal (variable AE, programs, partner costs, subsidies) | C45: =IFERROR((S14+S16+S17+S18+S19)/'GTM Funnel'!S72,0) -> 15924.015
A46: CAC payback, 2027–29 (months) | C46: =IFERROR('Unit Economics'!$C$44/('Unit Economics'!$C$43*Assumptions!$J$76/12),0) -> 82.37985
A47: CAC payback, 2029 cohort (months) | C47: =IFERROR((R20/'GTM Funnel'!R72)/(('Revenue Model'!R14/'GTM Funnel'!R72)*Assumptions!$J$76/12),0) -> 53.740167
A48: Total incremental cost 2027–29 | C48: =S24 -> 2967534.6
A49: Cumulative program P&L 2027–29 (undiscounted, gross) | C49: =N27 -> -2645899.1
A50: Peak investment (lowest cumulative P&L) | C50: =MIN($C$27:$N$27) -> -2645899.1
A51: Undiscounted post-2029 value of the 2029 ARR base (gross) | C51: ='Revenue Model'!N13*(Assumptions!$J$76-$C$35)*$C$34*(1-$C$34^Assumptions!$J$85)/(1-$C$34) -> 883215.35
A52: PV of post-2029 value, after incrementality haircut | C52: ='Revenue Model'!N13*(Assumptions!$J$76-$C$35)*(1-Assumptions!$J$88)/(1+Assumptions!$J$87)^2.5*$C$36*(1-$C$36^Assumptions!$J$85)/(1-$C$36) -> 393083.34
A53: NPV of the program (incremental, at hurdle rate) | C53: =SUM($C$29:$N$29)+'Unit Economics'!$C$52 -> -1892877
A54: NPV of Option 0 (same spend in the core motion) | C54: =SUM($C$33:$N$33)+N31*(Assumptions!$J$76-Assumptions!$J$93)/(1+Assumptions!$J$87)^2.5*$C$37*(1-$C$37^Assumptions!$J$85)/(1-$C$37) -> 1512522
A55: NPV advantage over Option 0 (program NPV − Option 0 NPV) | C55: ='Unit Economics'!$C$53-'Unit Economics'!$C$54 -> -3405399
A56: First-year ACV lost to capacity, 2027–29 | C56: ='GTM Funnel'!S68 -> 0
A57: Gate metric: opportunities created in 2027 | C57: ='GTM Funnel'!P52 -> 43.618872
A58: Gate metric: new customers in 2027 | C58: ='GTM Funnel'!P72 -> 6.182609
A59: Gate metric: partner introductions in 2027 | C59: ='GTM Funnel'!P48 -> 42
A60: Gate metric: average first-year ACV, 2027 | C60: =IFERROR('Revenue Model'!P14/'GTM Funnel'!P72,0) -> 8545.0175

Sheet Scenarios
A1: Scenarios — options compared on one engine (deterministic Downside / Base / Upside)
A2: Every figure links to a full run on 'Engine Runs'. NPV at the hurdle rate, after the incrementality haircut. Illustrative scenario outputs — not Clay forecasts.
A4: Output | B4: Unit | C4: Dist · Lean partner-led pilot · Downside | D4: Dist · Lean partner-led pilot · Base | E4: Dist · Lean partner-led pilot · Upside | F4: Dist · Sales-led vertical team · Downside | G4: Dist · Sales-led vertical team · Base | H4: Dist · Sales-led vertical team · Upside | I4: Dist · Solution play · Downside | J4: Dist · Solution play · Base | K4: Dist · Solution play · Upside | L4: PS · Lean partner-led pilot · Downside | M4: PS · Lean partner-led pilot · Base | N4: PS · Lean partner-led pilot · Upside | O4: PS · Sales-led vertical team · Downside | P4: PS · Sales-led vertical team · Base | Q4: PS · Sales-led vertical team · Upside | R4: PS · Solution play · Downside | S4: PS · Solution play · Base | T4: PS · Solution play · Upside
A5: NPV of the program at hurdle rate | B5: $ | C5: ='Engine Runs'!$C$133 -> -2099751.5 | D5: ='Engine Runs'!$C$272 -> -1892877 | E5: ='Engine Runs'!$C$411 -> 1527389.1 | F5: ='Engine Runs'!$C$830 -> -6046208.1 | G5: ='Engine Runs'!$C$969 -> -5438648.7 | H5: ='Engine Runs'!$C$1108 -> 821457.73 | I5: ='Engine Runs'!$C$1247 -> -625495.41 | J5: ='Engine Runs'!$C$1386 -> -544641.96 | K5: ='Engine Runs'!$C$1525 -> 1114412.4 | L5: ='Engine Runs'!$C$1664 -> -2148114.9 | M5: ='Engine Runs'!$C$1803 -> -2044076.8 | N5: ='Engine Runs'!$C$1942 -> -249190.25 | O5: ='Engine Runs'!$C$2361 -> -6093023.6 | P5: ='Engine Runs'!$C$2500 -> -5731151.9 | Q5: ='Engine Runs'!$C$2639 -> -2873027.5 | R5: ='Engine Runs'!$C$2778 -> -648617.85 | S5: ='Engine Runs'!$C$2917 -> -620644.16 | T5: ='Engine Runs'!$C$3056 -> 223947.77
A6: NPV of Option 0 (same spend in core) | B6: $ | C6: ='Engine Runs'!$C$134 -> 1320322.3 | D6: ='Engine Runs'!$C$273 -> 1512522 | E6: ='Engine Runs'!$C$412 -> 1983119.3 | F6: ='Engine Runs'!$C$831 -> 3498435.9 | G6: ='Engine Runs'!$C$970 -> 3736306.3 | H6: ='Engine Runs'!$C$1109 -> 4014084.7 | I6: ='Engine Runs'!$C$1248 -> 431297.34 | J6: ='Engine Runs'!$C$1387 -> 527863.09 | K6: ='Engine Runs'!$C$1526 -> 756148.16 | L6: ='Engine Runs'!$C$1665 -> 1339667.8 | M6: ='Engine Runs'!$C$1804 -> 1525400.9 | N6: ='Engine Runs'!$C$1943 -> 1804748.7 | O6: ='Engine Runs'!$C$2362 -> 3508194.6 | P6: ='Engine Runs'!$C$2501 -> 3726855.8 | Q6: ='Engine Runs'!$C$2640 -> 3902325.9 | R6: ='Engine Runs'!$C$2779 -> 440304.35 | S6: ='Engine Runs'!$C$2918 -> 532589.31 | T6: ='Engine Runs'!$C$3057 -> 665333.92
A7: NPV advantage over Option 0 | B7: $ | C7: ='Engine Runs'!$C$135 -> -3420073.8 | D7: ='Engine Runs'!$C$274 -> -3405399 | E7: ='Engine Runs'!$C$413 -> -455730.12 | F7: ='Engine Runs'!$C$832 -> -9544644 | G7: ='Engine Runs'!$C$971 -> -9174954.9 | H7: ='Engine Runs'!$C$1110 -> -3192627 | I7: ='Engine Runs'!$C$1249 -> -1056792.8 | J7: ='Engine Runs'!$C$1388 -> -1072505.1 | K7: ='Engine Runs'!$C$1527 -> 358264.27 | L7: ='Engine Runs'!$C$1666 -> -3487782.7 | M7: ='Engine Runs'!$C$1805 -> -3569477.8 | N7: ='Engine Runs'!$C$1944 -> -2053938.9 | O7: ='Engine Runs'!$C$2363 -> -9601218.2 | P7: ='Engine Runs'!$C$2502 -> -9458007.8 | Q7: ='Engine Runs'!$C$2641 -> -6775353.4 | R7: ='Engine Runs'!$C$2780 -> -1088922.2 | S7: ='Engine Runs'!$C$2919 -> -1153233.5 | T7: ='Engine Runs'!$C$3058 -> -441386.15
A8: Exit ARR, Q4 2029 | B8: $ | C8: ='Engine Runs'!$C$119 -> 62906.156 | D8: ='Engine Runs'!$C$258 -> 509612.73 | E8: ='Engine Runs'!$C$397 -> 3013219.5 | F8: ='Engine Runs'!$C$816 -> 113881.56 | G8: ='Engine Runs'!$C$955 -> 820721.59 | H8: ='Engine Runs'!$C$1094 -> 4711541.7 | I8: ='Engine Runs'!$C$1233 -> 30663.055 | J8: ='Engine Runs'!$C$1372 -> 246156.7 | K8: ='Engine Runs'!$C$1511 -> 1463066.3 | L8: ='Engine Runs'!$C$1650 -> 110994.42 | M8: ='Engine Runs'!$C$1789 -> 680163.89 | N8: ='Engine Runs'!$C$1928 -> 2609610.8 | O8: ='Engine Runs'!$C$2347 -> 161375.75 | P8: ='Engine Runs'!$C$2486 -> 914355.66 | Q8: ='Engine Runs'!$C$2625 -> 3491416.3 | R8: ='Engine Runs'!$C$2764 -> 51399.292 | S8: ='Engine Runs'!$C$2903 -> 317295.3 | T8: ='Engine Runs'!$C$3042 -> 1231458.7
A9: Customers, Q4 2029 | B9: # | C9: ='Engine Runs'!$C$120 -> 7.6148187 | D9: ='Engine Runs'!$C$259 -> 49.528099 | E9: ='Engine Runs'!$C$398 -> 194.70381 | F9: ='Engine Runs'!$C$817 -> 13.807501 | G9: ='Engine Runs'!$C$956 -> 79.321885 | H9: ='Engine Runs'!$C$1095 -> 305.19879 | I9: ='Engine Runs'!$C$1234 -> 3.7106394 | J9: ='Engine Runs'!$C$1373 -> 23.904285 | K9: ='Engine Runs'!$C$1512 -> 94.460333 | L9: ='Engine Runs'!$C$1651 -> 15.331819 | M9: ='Engine Runs'!$C$1790 -> 85.142263 | N9: ='Engine Runs'!$C$1929 -> 289.21088 | O9: ='Engine Runs'!$C$2348 -> 22.206244 | P9: ='Engine Runs'!$C$2487 -> 113.80418 | Q9: ='Engine Runs'!$C$2626 -> 386.27114 | R9: ='Engine Runs'!$C$2765 -> 7.0921192 | S9: ='Engine Runs'!$C$2904 -> 39.679914 | T9: ='Engine Runs'!$C$3043 -> 136.35761
A10: New customers 2027–29 | B10: # | C10: ='Engine Runs'!$C$121 -> 8.9506283 | D10: ='Engine Runs'!$C$260 -> 54.749119 | E10: ='Engine Runs'!$C$399 -> 210.07522 | F10: ='Engine Runs'!$C$818 -> 16.212819 | G10: ='Engine Runs'!$C$957 -> 87.892356 | H10: ='Engine Runs'!$C$1096 -> 329.14414 | I10: ='Engine Runs'!$C$1235 -> 4.3625547 | J10: ='Engine Runs'!$C$1374 -> 26.432602 | K10: ='Engine Runs'!$C$1513 -> 101.93558 | L10: ='Engine Runs'!$C$1652 -> 17.962941 | M10: ='Engine Runs'!$C$1791 -> 94.880434 | N10: ='Engine Runs'!$C$1930 -> 313.72193 | O10: ='Engine Runs'!$C$2349 -> 26.123696 | P10: ='Engine Runs'!$C$2488 -> 127.25016 | Q10: ='Engine Runs'!$C$2627 -> 419.28639 | R10: ='Engine Runs'!$C$2766 -> 8.3173922 | S10: ='Engine Runs'!$C$2905 -> 44.240234 | T10: ='Engine Runs'!$C$3044 -> 147.95161
A11: Average first-year ACV | B11: $ | C11: ='Engine Runs'!$C$123 -> 7293.9174 | D11: ='Engine Runs'!$C$262 -> 8847.9735 | E11: ='Engine Runs'!$C$401 -> 12338.488 | F11: ='Engine Runs'!$C$820 -> 7288.4625 | G11: ='Engine Runs'!$C$959 -> 8863.8206 | H11: ='Engine Runs'!$C$1098 -> 12322.66 | I11: ='Engine Runs'!$C$1237 -> 7294.8044 | J11: ='Engine Runs'!$C$1376 -> 8850.6126 | K11: ='Engine Runs'!$C$1515 -> 12341.847 | L11: ='Engine Runs'!$C$1654 -> 6452.5659 | M11: ='Engine Runs'!$C$1793 -> 6863.9789 | N11: ='Engine Runs'!$C$1932 -> 7290.9339 | O11: ='Engine Runs'!$C$2351 -> 6457.0882 | P11: ='Engine Runs'!$C$2490 -> 6868.9908 | Q11: ='Engine Runs'!$C$2629 -> 7288.0518 | R11: ='Engine Runs'!$C$2768 -> 6454.7347 | S11: ='Engine Runs'!$C$2907 -> 6865.7947 | T11: ='Engine Runs'!$C$3046 -> 7292.3236
A12: CAC, fully loaded | B12: $ | C12: ='Engine Runs'!$C$124 -> 203613.49 | D12: ='Engine Runs'!$C$263 -> 39481.798 | E12: ='Engine Runs'!$C$402 -> 15314.798 | F12: ='Engine Runs'!$C$821 -> 412144.85 | G12: ='Engine Runs'!$C$960 -> 78270.45 | H12: ='Engine Runs'!$C$1099 -> 22265.268 | I12: ='Engine Runs'!$C$1238 -> 83551.668 | J12: ='Engine Runs'!$C$1377 -> 20825.556 | K12: ='Engine Runs'!$C$1516 -> 10465.925 | L12: ='Engine Runs'!$C$1655 -> 103832.31 | M12: ='Engine Runs'!$C$1794 -> 22952.931 | N12: ='Engine Runs'!$C$1933 -> 8756.1533 | O12: ='Engine Runs'!$C$2352 -> 256488.67 | P12: ='Engine Runs'!$C$2491 -> 53777.12 | Q12: ='Engine Runs'!$C$2630 -> 16777.621 | R12: ='Engine Runs'!$C$2769 -> 46179.305 | S12: ='Engine Runs'!$C$2908 -> 12526.636 | T12: ='Engine Runs'!$C$3047 -> 5596.9127
A13: CAC, marginal | B13: $ | C13: ='Engine Runs'!$C$125 -> 59515.469 | D13: ='Engine Runs'!$C$264 -> 15924.015 | E13: ='Engine Runs'!$C$403 -> 9175.2454 | F13: ='Engine Runs'!$C$822 -> 56883.204 | G13: ='Engine Runs'!$C$961 -> 12738.098 | H13: ='Engine Runs'!$C$1100 -> 4765.9659 | I13: ='Engine Runs'!$C$1239 -> 63223.147 | J13: ='Engine Runs'!$C$1378 -> 17470.446 | K13: ='Engine Runs'!$C$1517 -> 9595.9213 | L13: ='Engine Runs'!$C$1656 -> 32030.715 | M13: ='Engine Runs'!$C$1795 -> 9359.318 | N13: ='Engine Runs'!$C$1934 -> 4644.9716 | O13: ='Engine Runs'!$C$2353 -> 36007.12 | P13: ='Engine Runs'!$C$2492 -> 8513.5784 | Q13: ='Engine Runs'!$C$2631 -> 3040.4884 | R13: ='Engine Runs'!$C$2770 -> 35516.794 | S13: ='Engine Runs'!$C$2909 -> 10522.029 | T13: ='Engine Runs'!$C$3048 -> 4997.4986
A14: CAC payback, 2029 cohort | B14: months | C14: ='Engine Runs'!$C$127 -> 474.3179 | D14: ='Engine Runs'!$C$266 -> 53.740167 | E14: ='Engine Runs'!$C$405 -> 16.190358 | F14: ='Engine Runs'!$C$824 -> 1086.7431 | G14: ='Engine Runs'!$C$963 -> 117.74997 | H14: ='Engine Runs'!$C$1102 -> 22.927529 | I14: ='Engine Runs'!$C$1241 -> 154.68713 | J14: ='Engine Runs'!$C$1380 -> 25.70966 | K14: ='Engine Runs'!$C$1519 -> 11.115368 | L14: ='Engine Runs'!$C$1658 -> 254.83256 | M14: ='Engine Runs'!$C$1797 -> 42.271735 | N14: ='Engine Runs'!$C$1936 -> 15.509346 | O14: ='Engine Runs'!$C$2355 -> 745.19772 | P14: ='Engine Runs'!$C$2494 -> 110.90519 | Q14: ='Engine Runs'!$C$2633 -> 30.717649 | R14: ='Engine Runs'!$C$2772 -> 92.513266 | S14: ='Engine Runs'!$C$2911 -> 20.487621 | T14: ='Engine Runs'!$C$3050 -> 9.5141976
A15: Total incremental cost 2027–29 | B15: $ | C15: ='Engine Runs'!$C$128 -> 2544131.1 | D15: ='Engine Runs'!$C$267 -> 2967534.6 | E15: ='Engine Runs'!$C$406 -> 4341614.2 | F15: ='Engine Runs'!$C$825 -> 7419246.7 | G15: ='Engine Runs'!$C$964 -> 7751157.4 | H15: ='Engine Runs'!$C$1103 -> 8689214.6 | I15: ='Engine Runs'!$C$1242 -> 750095.63 | J15: ='Engine Runs'!$C$1381 -> 976784.12 | K15: ='Engine Runs'!$C$1520 -> 1648174.3 | L15: ='Engine Runs'!$C$1659 -> 2602606.7 | M15: ='Engine Runs'!$C$1798 -> 3060744.9 | N15: ='Engine Runs'!$C$1937 -> 4086357.2 | O15: ='Engine Runs'!$C$2356 -> 7454859.7 | P15: ='Engine Runs'!$C$2495 -> 7793222.1 | Q15: ='Engine Runs'!$C$2634 -> 8593401.4 | R15: ='Engine Runs'!$C$2773 -> 776601.24 | S15: ='Engine Runs'!$C$2912 -> 1014849.5 | T15: ='Engine Runs'!$C$3051 -> 1505362.6
A16: Cumulative P&L 2027–29 (undiscounted) | B16: $ | C16: ='Engine Runs'!$C$129 -> -2502939.8 | D16: ='Engine Runs'!$C$268 -> -2645899.1 | E16: ='Engine Runs'!$C$407 -> -2248566.3 | F16: ='Engine Runs'!$C$826 -> -7345026.3 | G16: ='Engine Runs'!$C$965 -> -7222893 | H16: ='Engine Runs'!$C$1104 -> -5428876.5 | I16: ='Engine Runs'!$C$1243 -> -729995.02 | J16: ='Engine Runs'!$C$1382 -> -821017.4 | K16: ='Engine Runs'!$C$1521 -> -630042.27 | L16: ='Engine Runs'!$C$1660 -> -2531336 | M16: ='Engine Runs'!$C$1799 -> -2610408.3 | N16: ='Engine Runs'!$C$1938 -> -2187763.1 | O16: ='Engine Runs'!$C$2357 -> -7348790.2 | P16: ='Engine Runs'!$C$2496 -> -7171119.1 | Q16: ='Engine Runs'!$C$2635 -> -6032936.8 | R16: ='Engine Runs'!$C$2774 -> -743420.54 | S16: ='Engine Runs'!$C$2913 -> -803970.51 | T16: ='Engine Runs'!$C$3052 -> -607226.14
A17: Peak investment | B17: $ | C17: ='Engine Runs'!$C$130 -> -2502939.8 | D17: ='Engine Runs'!$C$269 -> -2645899.1 | E17: ='Engine Runs'!$C$408 -> -2299054.8 | F17: ='Engine Runs'!$C$827 -> -7345026.3 | G17: ='Engine Runs'!$C$966 -> -7222893 | H17: ='Engine Runs'!$C$1105 -> -5428876.5 | I17: ='Engine Runs'!$C$1244 -> -729995.02 | J17: ='Engine Runs'!$C$1383 -> -821017.4 | K17: ='Engine Runs'!$C$1522 -> -755671.44 | L17: ='Engine Runs'!$C$1661 -> -2531336 | M17: ='Engine Runs'!$C$1800 -> -2610408.3 | N17: ='Engine Runs'!$C$1939 -> -2199485.2 | O17: ='Engine Runs'!$C$2358 -> -7348790.2 | P17: ='Engine Runs'!$C$2497 -> -7171119.1 | Q17: ='Engine Runs'!$C$2636 -> -6032936.8 | R17: ='Engine Runs'!$C$2775 -> -743420.54 | S17: ='Engine Runs'!$C$2914 -> -803970.51 | T17: ='Engine Runs'!$C$3053 -> -698430.34
A18: ACV lost to capacity | B18: $ | C18: ='Engine Runs'!$C$136 -> 0 | D18: ='Engine Runs'!$C$275 -> 0 | E18: ='Engine Runs'!$C$414 -> 0 | F18: ='Engine Runs'!$C$833 -> 0 | G18: ='Engine Runs'!$C$972 -> 0 | H18: ='Engine Runs'!$C$1111 -> 0 | I18: ='Engine Runs'!$C$1250 -> 0 | J18: ='Engine Runs'!$C$1389 -> 0 | K18: ='Engine Runs'!$C$1528 -> 0 | L18: ='Engine Runs'!$C$1667 -> 0 | M18: ='Engine Runs'!$C$1806 -> 0 | N18: ='Engine Runs'!$C$1945 -> 0 | O18: ='Engine Runs'!$C$2364 -> 0 | P18: ='Engine Runs'!$C$2503 -> 0 | Q18: ='Engine Runs'!$C$2642 -> 0 | R18: ='Engine Runs'!$C$2781 -> 0 | S18: ='Engine Runs'!$C$2920 -> 0 | T18: ='Engine Runs'!$C$3059 -> 0
A19: Gate metric: 2027 opportunities | B19: # | C19: ='Engine Runs'!$C$137 -> 15.567034 | D19: ='Engine Runs'!$C$276 -> 43.618872 | E19: ='Engine Runs'!$C$415 -> 116.59177 | F19: ='Engine Runs'!$C$834 -> 28.501749 | G19: ='Engine Runs'!$C$973 -> 73.646584 | H19: ='Engine Runs'!$C$1112 -> 184.11473 | I19: ='Engine Runs'!$C$1251 -> 7.5903564 | J19: ='Engine Runs'!$C$1390 -> 21.191322 | K19: ='Engine Runs'!$C$1529 -> 56.892413 | L19: ='Engine Runs'!$C$1668 -> 36.373486 | M19: ='Engine Runs'!$C$1807 -> 98.476625 | N19: ='Engine Runs'!$C$1946 -> 240.54155 | O19: ='Engine Runs'!$C$2365 -> 55.552725 | P19: ='Engine Runs'!$C$2504 -> 144.03823 | Q19: ='Engine Runs'!$C$2643 -> 336.34396 | R19: ='Engine Runs'!$C$2782 -> 16.984603 | S19: ='Engine Runs'!$C$2921 -> 46.353176 | T19: ='Engine Runs'!$C$3060 -> 114.23684
A20: Gate metric: 2027 new customers | B20: # | C20: ='Engine Runs'!$C$138 -> 1.5437247 | D20: ='Engine Runs'!$C$277 -> 6.182609 | E20: ='Engine Runs'!$C$416 -> 21.77609 | F20: ='Engine Runs'!$C$835 -> 2.858747 | G20: ='Engine Runs'!$C$974 -> 10.207899 | H20: ='Engine Runs'!$C$1113 -> 33.371943 | I20: ='Engine Runs'!$C$1252 -> 0.75147843 | J20: ='Engine Runs'!$C$1391 -> 3.0005144 | K20: ='Engine Runs'!$C$1530 -> 10.622054 | L20: ='Engine Runs'!$C$1669 -> 3.3077331 | M20: ='Engine Runs'!$C$1808 -> 12.404649 | N20: ='Engine Runs'!$C$1947 -> 37.25594 | O20: ='Engine Runs'!$C$2366 -> 5.0747727 | P20: ='Engine Runs'!$C$2505 -> 17.983403 | Q20: ='Engine Runs'!$C$2644 -> 52.215134 | R20: ='Engine Runs'!$C$2783 -> 1.5436959 | S20: ='Engine Runs'!$C$2922 -> 5.8380682 | T20: ='Engine Runs'!$C$3061 -> 17.705054
A21: Gate metric: 2027 partner introductions | B21: # | C21: ='Engine Runs'!$C$139 -> 20 | D21: ='Engine Runs'!$C$278 -> 42 | E21: ='Engine Runs'!$C$417 -> 96 | F21: ='Engine Runs'!$C$836 -> 20 | G21: ='Engine Runs'!$C$975 -> 42 | H21: ='Engine Runs'!$C$1114 -> 96 | I21: ='Engine Runs'!$C$1253 -> 10 | J21: ='Engine Runs'!$C$1392 -> 21 | K21: ='Engine Runs'!$C$1531 -> 48 | L21: ='Engine Runs'!$C$1670 -> 28 | M21: ='Engine Runs'!$C$1809 -> 54 | N21: ='Engine Runs'!$C$1948 -> 112 | O21: ='Engine Runs'!$C$2367 -> 28 | P21: ='Engine Runs'!$C$2506 -> 54 | Q21: ='Engine Runs'!$C$2645 -> 112 | R21: ='Engine Runs'!$C$2784 -> 14 | S21: ='Engine Runs'!$C$2923 -> 27 | T21: ='Engine Runs'!$C$3062 -> 56
A22: Gate metric: 2027 average ACV | B22: $ | C22: ='Engine Runs'!$C$140 -> 6891.7895 | D22: ='Engine Runs'!$C$279 -> 8545.0175 | E22: ='Engine Runs'!$C$418 -> 11723.973 | F22: ='Engine Runs'!$C$837 -> 6885.736 | G22: ='Engine Runs'!$C$976 -> 8458.4771 | H22: ='Engine Runs'!$C$1115 -> 11504.356 | I22: ='Engine Runs'!$C$1254 -> 6890.5902 | J22: ='Engine Runs'!$C$1393 -> 8544.105 | K22: ='Engine Runs'!$C$1532 -> 11720.273 | L22: ='Engine Runs'!$C$1671 -> 6128.8159 | M22: ='Engine Runs'!$C$1810 -> 6435.7047 | N22: ='Engine Runs'!$C$1949 -> 6706.7685 | O22: ='Engine Runs'!$C$2368 -> 6133.1451 | P22: ='Engine Runs'!$C$2507 -> 6420.5941 | Q22: ='Engine Runs'!$C$2646 -> 6674.2198 | R22: ='Engine Runs'!$C$2785 -> 6129.112 | S22: ='Engine Runs'!$C$2924 -> 6436.3589 | T22: ='Engine Runs'!$C$3063 -> 6706.0226
A24: Gated variants (lean pilot)
A25: Output | B25: Unit | C25: Dist · Downside stopped at Gate 1 | D25: Dist · Upside + 2 AEs after Gate 1 | E25: PS · Downside stopped at Gate 1 | F25: PS · Upside + 2 AEs after Gate 1
A26: NPV of the program at hurdle rate | B26: $ | C26: ='Engine Runs'!$C$551 -> -912381.68 | D26: ='Engine Runs'!$C$691 -> 1567837.8 | E26: ='Engine Runs'!$C$2082 -> -927042.33 | F26: ='Engine Runs'!$C$2222 -> -622652.81
A27: NPV of Option 0 (same spend in core) | B27: $ | C27: ='Engine Runs'!$C$552 -> 754060.77 | D27: ='Engine Runs'!$C$692 -> 2155594.8 | E27: ='Engine Runs'!$C$2083 -> 763015.31 | F27: ='Engine Runs'!$C$2223 -> 2040061.8
A28: NPV advantage over Option 0 | B28: $ | C28: ='Engine Runs'!$C$553 -> -1666442.5 | D28: ='Engine Runs'!$C$693 -> -587756.94 | E28: ='Engine Runs'!$C$2084 -> -1690057.6 | F28: ='Engine Runs'!$C$2224 -> -2662714.7
A29: Exit ARR, Q4 2029 | B29: $ | C29: ='Engine Runs'!$C$537 -> 10088.525 | D29: ='Engine Runs'!$C$677 -> 3262047.9 | E29: ='Engine Runs'!$C$2068 -> 19612.014 | F29: ='Engine Runs'!$C$2208 -> 2703520.7
A30: Customers, Q4 2029 | B30: # | C30: ='Engine Runs'!$C$538 -> 1.1483397 | D30: ='Engine Runs'!$C$678 -> 213.37725 | E30: ='Engine Runs'!$C$2069 -> 2.5475225 | F30: ='Engine Runs'!$C$2209 -> 300.97128
A31: New customers 2027–29 | B31: # | C31: ='Engine Runs'!$C$539 -> 1.6173835 | D31: ='Engine Runs'!$C$679 -> 229.61098 | E31: ='Engine Runs'!$C$2070 -> 3.5915321 | F31: ='Engine Runs'!$C$2210 -> 326.02475
A32: Average first-year ACV | B32: $ | C32: ='Engine Runs'!$C$541 -> 6821.6645 | D32: ='Engine Runs'!$C$681 -> 12294.591 | E32: ='Engine Runs'!$C$2072 -> 6067.4328 | F32: ='Engine Runs'!$C$2212 -> 7285.9547
A33: CAC, fully loaded | B33: $ | C33: ='Engine Runs'!$C$542 -> 314768.05 | D33: ='Engine Runs'!$C$682 -> 15645.611 | E33: ='Engine Runs'!$C$2073 -> 145096.82 | F33: ='Engine Runs'!$C$2213 -> 10180.264
A34: CAC, marginal | B34: $ | C34: ='Engine Runs'!$C$543 -> 103984.48 | D34: ='Engine Runs'!$C$683 -> 5362.1457 | E34: ='Engine Runs'!$C$2074 -> 50174.138 | F34: ='Engine Runs'!$C$2214 -> 2937.8798
A35: CAC payback, 2029 cohort | B35: months | C35: ='Engine Runs'!$C$545 -> 0 | D35: ='Engine Runs'!$C$685 -> 15.378012 | E35: ='Engine Runs'!$C$2076 -> 0 | F35: ='Engine Runs'!$C$2216 -> 17.993822
A36: Total incremental cost 2027–29 | B36: $ | C36: ='Engine Runs'!$C$546 -> 991145.19 | D36: ='Engine Runs'!$C$686 -> 4742953.1 | E36: ='Engine Runs'!$C$2077 -> 1009072.8 | F36: ='Engine Runs'!$C$2217 -> 4674894.4
A37: Cumulative P&L 2027–29 (undiscounted) | B37: $ | C37: ='Engine Runs'!$C$547 -> -977862.23 | D37: ='Engine Runs'!$C$687 -> -2542791.1 | E37: ='Engine Runs'!$C$2078 -> -983066.46 | F37: ='Engine Runs'!$C$2218 -> -2735348.1
A38: Peak investment | B38: $ | C38: ='Engine Runs'!$C$548 -> -984629.14 | D38: ='Engine Runs'!$C$688 -> -2594268.5 | E38: ='Engine Runs'!$C$2079 -> -996075.63 | F38: ='Engine Runs'!$C$2219 -> -2735348.1
A39: ACV lost to capacity | B39: $ | C39: ='Engine Runs'!$C$554 -> 6549.0346 | D39: ='Engine Runs'!$C$694 -> 0 | E39: ='Engine Runs'!$C$2085 -> 9525.7042 | F39: ='Engine Runs'!$C$2225 -> 0
A41: Reconciliation: live model vs matching engine run (should be 0)
A42: NPV difference | C42: ='Unit Economics'!$C$53-INDEX($C$5:$T$5,1,((Assumptions!$D$5-1)*9+(Assumptions!$D$6-1)*3+Assumptions!$D$4)) -> 0
A43: Exit ARR difference | C43: ='Unit Economics'!$C$39-INDEX($C$8:$T$8,1,((Assumptions!$D$5-1)*9+(Assumptions!$D$6-1)*3+Assumptions!$D$4)) -> 0
A45: ARR trajectory by quarter — distribution (for charts) | C45: Q1 2027 | D45: Q2 2027 | E45: Q3 2027 | F45: Q4 2027 | G45: Q1 2028 | H45: Q2 2028 | I45: Q3 2028 | J45: Q4 2028 | K45: Q1 2029 | L45: Q2 2029 | M45: Q3 2029 | N45: Q4 2029
A46: Lean pilot — Downside | C46: ='Engine Runs'!C81 -> 0 | D46: ='Engine Runs'!D81 -> 1795.4062 | E46: ='Engine Runs'!E81 -> 5695.7302 | F46: ='Engine Runs'!F81 -> 10546.495 | G46: ='Engine Runs'!G81 -> 16044.154 | H46: ='Engine Runs'!H81 -> 22209.898 | I46: ='Engine Runs'!I81 -> 28367.684 | J46: ='Engine Runs'!J81 -> 35119.036 | ... N46: ='Engine Runs'!N81 -> 62906.156
A47: Lean pilot — Base | C47: ='Engine Runs'!C220 -> 0 | D47: ='Engine Runs'!D220 -> 8876.4332 | E47: ='Engine Runs'!E220 -> 28556.833 | F47: ='Engine Runs'!F220 -> 53219.045 | G47: ='Engine Runs'!G220 -> 80661.528 | H47: ='Engine Runs'!H220 -> 114397.2 | I47: ='Engine Runs'!I220 -> 155018.12 | J47: ='Engine Runs'!J220 -> 210178.6 | ... N47: ='Engine Runs'!N220 -> 509612.73
A48: Lean pilot — Upside | C48: ='Engine Runs'!C359 -> 0 | D48: ='Engine Runs'!D359 -> 36090.504 | E48: ='Engine Runs'!E359 -> 130249.72 | F48: ='Engine Runs'!F359 -> 260899.81 | G48: ='Engine Runs'!G359 -> 428872.53 | H48: ='Engine Runs'!H359 -> 639714.56 | I48: ='Engine Runs'!I359 -> 924070.94 | J48: ='Engine Runs'!J359 -> 1297120.4 | ... N48: ='Engine Runs'!N359 -> 3013219.5
A49: Sales-led team — Base | C49: ='Engine Runs'!C917 -> 0 | D49: ='Engine Runs'!D917 -> 12457.995 | E49: ='Engine Runs'!E917 -> 44041.686 | F49: ='Engine Runs'!F917 -> 86916.369 | G49: ='Engine Runs'!G917 -> 135340.74 | H49: ='Engine Runs'!H917 -> 194186.65 | I49: ='Engine Runs'!I917 -> 263847.39 | J49: ='Engine Runs'!J917 -> 354092.01 | ... N49: ='Engine Runs'!N917 -> 820721.59
A50: Solution play — Base | C50: ='Engine Runs'!C1334 -> 0 | D50: ='Engine Runs'!D1334 -> 4318.2231 | E50: ='Engine Runs'!E1334 -> 13858.07 | F50: ='Engine Runs'!F1334 -> 25825.488 | G50: ='Engine Runs'!G1334 -> 39177.015 | H50: ='Engine Runs'!H1334 -> 55583.82 | I50: ='Engine Runs'!I1334 -> 75310.952 | J50: ='Engine Runs'!J1334 -> 101992.46 | ... N50: ='Engine Runs'!N1334 -> 246156.7

Sheet Sensitivity
A1: Sensitivity — distribution lean pilot, Base: what moves NPV, and what would have to be true
A2: Block A: one input at a time between its Downside and Upside values (ICP tilt and discount rate use the stated values). Block B: win rate × usage grid. Block C: can a sales-led team beat the pilot if its AEs prospect harder?
A4: Input swung | B4: Low value | C4: High value | D4: NPV @ low | E4: NPV @ high | F4: Swing (NPV) | G4: Advantage vs Option 0 @ low | H4: @ high | I4: Exit ARR @ low | J4: @ high
A5: Automated outbound coverage | B5: =Assumptions!$D$17 -> 0.3 | C5: =Assumptions!$F$17 -> 0.5 | D5: ='Engine Runs'!$C$3196 -> -1924661.9 | E5: ='Engine Runs'!$C$3336 -> -1861090.9 | F5: =ABS(E5-D5) -> 63571.018 | G5: ='Engine Runs'!$C$3198 -> -3427947.3 | H5: ='Engine Runs'!$C$3338 -> -3382849.1 | I5: ='Engine Runs'!$C$3182 -> 458210.57 | J5: ='Engine Runs'!$C$3322 -> 561014.89
A6: Meeting rate | B6: =Assumptions!$D$20 -> 0.02 | C6: =Assumptions!$F$20 -> 0.045 | D6: ='Engine Runs'!$C$3476 -> -1935256.6 | E6: ='Engine Runs'!$C$3616 -> -1829303.7 | F6: =ABS(E6-D6) -> 105952.9 | G6: ='Engine Runs'!$C$3478 -> -3435462.9 | H6: ='Engine Runs'!$C$3618 -> -3360297.5 | I6: ='Engine Runs'!$C$3462 -> 441076.51 | J6: ='Engine Runs'!$C$3602 -> 612417.05
A7: Outbound fatigue | B7: =Assumptions!$D$21 -> 0.6 | C7: =Assumptions!$F$21 -> 0.85 | D7: ='Engine Runs'!$C$3756 -> -1909683.4 | E7: ='Engine Runs'!$C$3896 -> -1881423.9 | F7: =ABS(E7-D7) -> 28259.502 | G7: ='Engine Runs'!$C$3758 -> -3417526.7 | H7: ='Engine Runs'!$C$3898 -> -3397122.4 | I7: ='Engine Runs'!$C$3742 -> 479236.78 | J7: ='Engine Runs'!$C$3882 -> 530628.27
A8: Inbound MQL rate | B8: =Assumptions!$D$22 -> 0.005 | C8: =Assumptions!$F$22 -> 0.015 | D8: ='Engine Runs'!$C$4036 -> -1918926.2 | E8: ='Engine Runs'!$C$4176 -> -1866832 | F8: =ABS(E8-D8) -> 52094.245 | G8: ='Engine Runs'!$C$4038 -> -3423949.5 | H8: ='Engine Runs'!$C$4178 -> -3386854.6 | I8: ='Engine Runs'!$C$4022 -> 466364.39 | J8: ='Engine Runs'!$C$4162 -> 552861.06
A9: Partner network (start, adds, cap, intros) | B9: =Assumptions!$D$25 -> 1 | C9: =Assumptions!$F$25 -> 3 | D9: ='Engine Runs'!$C$4316 -> -1899531.2 | E9: ='Engine Runs'!$C$4456 -> -1843742.9 | F9: =ABS(E9-D9) -> 55788.3 | G9: ='Engine Runs'!$C$4318 -> -3353493.7 | H9: ='Engine Runs'!$C$4458 -> -3479085.9 | I9: ='Engine Runs'!$C$4302 -> 381909.11 | J9: ='Engine Runs'!$C$4442 -> 777802.8
A10: Funnel conversion (meeting / intro / MQL → opp) | B10: =Assumptions!$D$29 -> 0.3 | C10: =Assumptions!$F$29 -> 0.5 | D10: ='Engine Runs'!$C$4596 -> -1965606.9 | E10: ='Engine Runs'!$C$4736 -> -1820147.9 | F10: =ABS(E10-D10) -> 145458.98 | G10: ='Engine Runs'!$C$4598 -> -3451806.8 | H10: ='Engine Runs'!$C$4738 -> -3358992.4 | I10: ='Engine Runs'!$C$4582 -> 382272.83 | J10: ='Engine Runs'!$C$4722 -> 636952.62
A11: Win rate | B11: =Assumptions!$D$32 -> 0.15 | C11: =Assumptions!$F$32 -> 0.3 | D11: ='Engine Runs'!$C$4876 -> -1974671.1 | E11: ='Engine Runs'!$C$5016 -> -1770185.9 | F11: =ABS(E11-D11) -> 204485.22 | G11: ='Engine Runs'!$C$4878 -> -3455978.6 | H11: ='Engine Runs'!$C$5018 -> -3329529.6 | I11: ='Engine Runs'!$C$4862 -> 364009.09 | J11: ='Engine Runs'!$C$5002 -> 728018.18
A12: Enterprise propensity (mix) | B12: =Assumptions!$D$34 -> 0.5 | C12: =Assumptions!$F$34 -> 0.9 | D12: ='Engine Runs'!$C$5156 -> -1924682.3 | E12: ='Engine Runs'!$C$5296 -> -1861790.4 | F12: =ABS(E12-D12) -> 62891.921 | G12: ='Engine Runs'!$C$5158 -> -3428806.4 | H12: ='Engine Runs'!$C$5298 -> -3382489.6 | I12: ='Engine Runs'!$C$5142 -> 473966.08 | J12: ='Engine Runs'!$C$5282 -> 544353.33
A13: ICP tilt to Mid-Market / Enterprise (1× ↔ 3×) | B13: 1 | C13: 3 | D13: ='Engine Runs'!$C$5436 -> -1910460.8 | E13: ='Engine Runs'!$C$5576 -> -1880823.8 | F13: =ABS(E13-D13) -> 29636.991 | G13: ='Engine Runs'!$C$5438 -> -3398575.6 | H13: ='Engine Runs'!$C$5578 -> -3410434.3 | I13: ='Engine Runs'!$C$5422 -> 424851.83 | J13: ='Engine Runs'!$C$5562 -> 569219.71
A14: Usage intensity (ACV) | B14: =Assumptions!$D$43 -> 0.75 | C14: =Assumptions!$F$43 -> 1.5 | D14: ='Engine Runs'!$C$5716 -> -1968365.4 | E14: ='Engine Runs'!$C$5856 -> -1741216 | F14: =ABS(E14-D14) -> 227149.34 | G14: ='Engine Runs'!$C$5718 -> -3461215.1 | H14: ='Engine Runs'!$C$5858 -> -3293082.7 | I14: ='Engine Runs'!$C$5702 -> 430426.98 | J14: ='Engine Runs'!$C$5842 -> 667984.23
A15: Gross revenue retention | B15: =Assumptions!$D$59 -> 0.85 | C15: =Assumptions!$F$59 -> 0.91 | D15: ='Engine Runs'!$C$5996 -> -1925003.3 | E15: ='Engine Runs'!$C$6136 -> -1863858.8 | F15: =ABS(E15-D15) -> 61144.496 | G15: ='Engine Runs'!$C$5998 -> -3437525.4 | H15: ='Engine Runs'!$C$6138 -> -3376380.9 | I15: ='Engine Runs'!$C$5982 -> 509612.73 | J15: ='Engine Runs'!$C$6122 -> 509612.73
A16: Net revenue retention | B16: =Assumptions!$D$62 -> 0.92 | C16: =Assumptions!$F$62 -> 1.06 | D16: ='Engine Runs'!$C$6276 -> -1940348.2 | E16: ='Engine Runs'!$C$6416 -> -1838891.3 | F16: =ABS(E16-D16) -> 101456.87 | G16: ='Engine Runs'!$C$6278 -> -3452870.2 | H16: ='Engine Runs'!$C$6418 -> -3351413.4 | I16: ='Engine Runs'!$C$6262 -> 473839.53 | J16: ='Engine Runs'!$C$6402 -> 550570.82
A17: Gross margin | B17: =Assumptions!$D$76 -> 0.55 | C17: =Assumptions!$F$76 -> 0.72 | D17: ='Engine Runs'!$C$6556 -> -2006021 | E17: ='Engine Runs'!$C$6696 -> -1813676.2 | F17: =ABS(E17-D17) -> 192344.87 | G17: ='Engine Runs'!$C$6558 -> -3457145.6 | H17: ='Engine Runs'!$C$6698 -> -3359028.8 | I17: ='Engine Runs'!$C$6542 -> 509612.73 | J17: ='Engine Runs'!$C$6682 -> 509612.73
A18: Wave timing | B18: =Assumptions!$D$14 -> 7 | C18: =Assumptions!$F$14 -> 4 | D18: ='Engine Runs'!$C$6836 -> -1925457.9 | E18: ='Engine Runs'!$C$6976 -> -1871449.5 | F18: =ABS(E18-D18) -> 54008.415 | G18: ='Engine Runs'!$C$6838 -> -3396542.5 | H18: ='Engine Runs'!$C$6978 -> -3396280.3 | I18: ='Engine Runs'!$C$6822 -> 383720.92 | J18: ='Engine Runs'!$C$6962 -> 540187.73
A19: Partner fee and onboarding subsidy | B19: =Assumptions!$D$79 -> 0.25 | C19: =Assumptions!$F$79 -> 0.15 | D19: ='Engine Runs'!$C$7116 -> -1912492.6 | E19: ='Engine Runs'!$C$7256 -> -1873261.4 | F19: =ABS(E19-D19) -> 39231.157 | G19: ='Engine Runs'!$C$7118 -> -3434674.1 | H19: ='Engine Runs'!$C$7258 -> -3376123.9 | I19: ='Engine Runs'!$C$7102 -> 509612.73 | J19: ='Engine Runs'!$C$7242 -> 509612.73
A20: Self-serve share of SMB | B20: =Assumptions!$D$37 -> 0.15 | C20: =Assumptions!$F$37 -> 0.4 | D20: ='Engine Runs'!$C$7396 -> -1903498.8 | E20: ='Engine Runs'!$C$7536 -> -1885795.8 | F20: =ABS(E20-D20) -> 17702.953 | G20: ='Engine Runs'!$C$7398 -> -3421186.9 | H20: ='Engine Runs'!$C$7538 -> -3394873.7 | I20: ='Engine Runs'!$C$7382 -> 509612.73 | J20: ='Engine Runs'!$C$7522 -> 509612.73
A21: Incrementality haircut | B21: =Assumptions!$D$88 -> 0.3 | C21: =Assumptions!$F$88 -> 0.1 | D21: ='Engine Runs'!$C$7676 -> -1966574.7 | E21: ='Engine Runs'!$C$7816 -> -1819179.3 | F21: =ABS(E21-D21) -> 147395.37 | G21: ='Engine Runs'!$C$7678 -> -3479096.7 | H21: ='Engine Runs'!$C$7818 -> -3331701.3 | I21: ='Engine Runs'!$C$7662 -> 509612.73 | J21: ='Engine Runs'!$C$7802 -> 509612.73
A22: Discount rate (15% ↔ 8%) | B22: 0.15 | C22: 0.08 | D22: ='Engine Runs'!$C$7956 -> -1855919.5 | E22: ='Engine Runs'!$C$8096 -> -1938627.4 | F22: =ABS(E22-D22) -> 82707.953 | G22: ='Engine Runs'!$C$7958 -> -3076924.3 | H22: ='Engine Runs'!$C$8098 -> -3931409.7 | I22: ='Engine Runs'!$C$7942 -> 509612.73 | J22: ='Engine Runs'!$C$8082 -> 509612.73
A23: Base case | D23: ='Engine Runs'!$C$272 -> -1892877 | G23: ='Engine Runs'!$C$274 -> -3405399
A26: Block B — NPV of the distribution lean pilot: win rate (rows) × usage intensity (columns), all else Base
A27: Win rate ↓ / usage → | B27: 0.75 | C27: 1 | D27: 1.5 | E27: 2.5
A28: 0.15 | B28: ='Engine Runs'!$C$8236 -> -2028591.4 | C28: ='Engine Runs'!$C$8376 -> -1974671.1 | D28: ='Engine Runs'!$C$8516 -> -1866341.8 | E28: ='Engine Runs'!$C$8656 -> -1648802.3
A29: 0.21 | B29: ='Engine Runs'!$C$8796 -> -1968365.4 | C29: ='Engine Runs'!$C$8936 -> -1892877 | D29: ='Engine Runs'!$C$9076 -> -1741216 | E29: ='Engine Runs'!$C$9216 -> -1436660.7
A30: 0.3 | B30: ='Engine Runs'!$C$9356 -> -1878026.4 | C30: ='Engine Runs'!$C$9496 -> -1770185.9 | D30: ='Engine Runs'!$C$9636 -> -1553527.4 | E30: ='Engine Runs'!$C$9776 -> -1118448.3
A31: 0.4 | B31: ='Engine Runs'!$C$9916 -> -1777649.8 | C31: ='Engine Runs'!$C$10056 -> -1633862.4 | D31: ='Engine Runs'!$C$10196 -> -1344984.4 | E31: ='Engine Runs'!$C$10336 -> -764878.92
A33: Block B2 — Same grid: NPV advantage over Option 0
A34: Win rate ↓ / usage → | B34: 0.75 | C34: 1 | D34: 1.5 | E34: 2.5
A35: 0.15 | B35: ='Engine Runs'!$C$8238 -> -3495847.3 | C35: ='Engine Runs'!$C$8378 -> -3455978.6 | D35: ='Engine Runs'!$C$8518 -> -3375752.7 | E35: ='Engine Runs'!$C$8658 -> -3214419.8
A36: 0.21 | B36: ='Engine Runs'!$C$8798 -> -3461215.1 | C36: ='Engine Runs'!$C$8938 -> -3405399 | D36: ='Engine Runs'!$C$9078 -> -3293082.7 | E36: ='Engine Runs'!$C$9218 -> -3067216.7
A37: 0.3 | B37: ='Engine Runs'!$C$9358 -> -3409266.8 | C37: ='Engine Runs'!$C$9498 -> -3329529.6 | D37: ='Engine Runs'!$C$9638 -> -3169077.7 | E37: ='Engine Runs'!$C$9778 -> -2846411.9
A38: 0.4 | B38: ='Engine Runs'!$C$9918 -> -3351546.6 | C38: ='Engine Runs'!$C$10058 -> -3245230.3 | D38: ='Engine Runs'!$C$10198 -> -3031294.4 | E38: ='Engine Runs'!$C$10338 -> -2601073.4
A41: Block C — Sales-led team (Base) with more AE prospecting vs the lean pilot (Base)
A42: Accounts each ramped AE works per quarter | B42: New customers | C42: Exit ARR | D42: NPV | E42: Lean pilot NPV | F42: Sales-led − lean
A43: 0 | B43: ='Engine Runs'!$C$10464 -> 71.65085 | C43: ='Engine Runs'!$C$10462 -> 669315.22 | D43: ='Engine Runs'!$C$10476 -> -5579880.5 | E43: ='Engine Runs'!$C$272 -> -1892877 | F43: =D43-E43 -> -3687003.5
A44: 150 | B44: ='Engine Runs'!$C$10604 -> 87.892356 | C44: ='Engine Runs'!$C$10602 -> 820721.59 | D44: ='Engine Runs'!$C$10616 -> -5438648.7 | E44: ='Engine Runs'!$C$272 -> -1892877 | F44: =D44-E44 -> -3545771.7
A45: 300 | B45: ='Engine Runs'!$C$10744 -> 103.85457 | C45: ='Engine Runs'!$C$10742 -> 969127.9 | D45: ='Engine Runs'!$C$10756 -> -5300984 | E45: ='Engine Runs'!$C$272 -> -1892877 | F45: =D45-E45 -> -3408107
A46: 600 | B46: ='Engine Runs'!$C$10884 -> 120.01236 | C46: ='Engine Runs'!$C$10882 -> 1115283.8 | D46: ='Engine Runs'!$C$10896 -> -5175235.7 | E46: ='Engine Runs'!$C$272 -> -1892877 | F46: =D46-E46 -> -3282358.7
A48: Reading (v2): the sales-led team now generates its own pipeline, so the comparison is no longer true by construction (review C1). It adds customers and ARR, but in a ~5,000-account market the extra ACV does not pay for six AEs. Block B: at Base volumes, NPV turns positive only with win rates well above the 21% benchmark and usage far above the base build.

Sheet Monte Carlo
A1: Monte Carlo and gate policy — computed by appendix/clay_engine.py (a Python mirror of this workbook)
A2: Each draw samples every non-fixed input from triangular(Downside, Base, Upside); inputs in the same group (demand, value, cost, timing) are correlated through a Gaussian copula (ρ = 0.5). Values are static; rerun build_financial_model.py to refresh.
A4: Option / policy | B4: Mean NPV | C4: P10 | D4: P50 | E4: P90 | F4: P(NPV > 0) | G4: Mean advantage vs Option 0 | H4: P(beats Option 0) | I4: Stopped at Gate 1 | J4: Scaled at Gate 1
A5: Industrial distribution — Lean pilot — run all 12 quarters (ungated) | B5: -1833461 | C5: -2031553 | D5: -1877150 | E5: -1578232 | F5: 0 | G5: -3365399 | H5: 0
A6: Industrial distribution — Lean pilot — staged: Gate 1 with observation noise | B6: -1486097 | C6: -1979643 | D6: -1688191 | E6: -868884 | F6: 0 | G6: -2791988 | H6: 0 | I6: 0.337 | J6: 0.0112
A7: Industrial distribution — Sales-led vertical team | B7: -5315702 | C7: -5740374 | D7: -5403041 | E7: -4775974 | F7: 0 | G7: -9050273 | H7: 0
A8: Industrial distribution — Solution play (no vertical team) | B8: -511201 | C8: -604824 | D8: -531596 | E8: -388453 | F8: 0.0002 | G8: -1046607 | H8: 0
A9: Professional services — Lean pilot — run all 12 quarters (ungated) | B9: -2043608 | C9: -2160317 | D9: -2060360 | E9: -1904440 | F9: 0 | G9: -3570493 | H9: 0
A10: Professional services — Lean pilot — staged: Gate 1 with observation noise | B10: -1663742 | C10: -2146572 | D10: -1968093 | E10: -897861 | F10: 0 | G10: -2969701 | H10: 0 | I10: 0.3346 | J10: 0.0184
A11: Professional services — Sales-led vertical team | B11: -5726126 | C11: -5939510 | D11: -5764742 | E11: -5456822 | F11: 0 | G11: -9442359 | H11: 0
A12: Professional services — Solution play (no vertical team) | B12: -614778 | C12: -673722 | D12: -622046 | E12: -544597 | F12: 0 | G12: -1145900 | H12: 0
A14: Robustness of P(NPV > 0), distribution lean pilot (ungated): correlation and range width (2,000 draws each)
A15: Specification | B15: Within-group ρ | C15: Cross-group γ | D15: Range × (around Base) | E15: Mean NPV | F15: P90 NPV | G15: P(NPV > 0)
A16: Base specification | B16: 0.5 | C16: 0 | D16: 1 | E16: -1829576 | F16: -1560599 | G16: 0
A17: Strong correlation | B17: 0.8 | C17: 0.5 | D17: 1 | E17: -1769212 | F17: -1307517 | G17: 0.001
A18: Near-comonotonic (≈ joint scenarios) | B18: 0.9 | C18: 0.9 | D18: 1 | E18: -1714980 | F18: -1123165 | G18: 0.008
A19: Ranges 1.5× wider | B19: 0.5 | C19: 0 | D19: 1.5 | E19: -1768241 | F19: -1303319 | G19: 0.0045
A20: Ranges 1.5× wider + strong correlation | B20: 0.8 | C20: 0.5 | D20: 1.5 | E20: -1621973 | F20: -751821 | G20: 0.038
A21: Ranges 2× wider + strong correlation | B21: 0.8 | C21: 0.5 | D21: 2 | E21: -1407074 | F21: 30430 | G21: 0.101
A23: What would have to be true — single-input break-evens (Python bisection, all else Base)
A24: Break-even | B24: Distribution lean | C24: Distribution play | D24: PS lean | E24: PS play | F24: Base value
A25: Usage intensity needed for NPV = 0 (Base) | B25: 6.3946 | C25: 4.3146 | D25: not reachable | E25: not reachable | F25: 1.00x
A26: Win rate needed for NPV = 0 (Base; capped by borrowed AE capacity) | B26: not reachable | C26: not reachable | D26: not reachable | E26: not reachable | F26: 21% / 18%
A27: Option 0 efficiency at which the program ties Option 0 (Upside) | B27: 0.5477 | C27: 0.7097 | D27: 0.3366 | E27: 0.4425 | F27: 0.60
A28: Option 0 efficiency at which the program ties Option 0 (Base) | B28: 0.0781 | C28: 0.1121 | D28: 0.0569 | E28: 0.0789 | F28: 0.60
A30: Reconciliation — Python engine vs Excel engine, scenario runs (difference should be 0)
A31: Run | B31: Python NPV | C31: Excel NPV | D31: Difference | E31: Python exit ARR | F31: Excel exit ARR | G31: Difference
A32: Industrial distribution — lean pilot — Downside | B32: -2099751.5 | C32: ='Engine Runs'!$C$133 -> -2099751.5 | D32: =ROUND(C32-B32,0) -> 0 | E32: 62906.16 | F32: ='Engine Runs'!$C$119 -> 62906.156 | G32: =ROUND(F32-E32,0) -> 0
A33: Industrial distribution — lean pilot — Base | B33: -1892877 | C33: ='Engine Runs'!$C$272 -> -1892877 | D33: =ROUND(C33-B33,0) -> 0 | E33: 509612.73 | F33: ='Engine Runs'!$C$258 -> 509612.73 | G33: =ROUND(F33-E33,0) -> 0
A34: Industrial distribution — lean pilot — Upside | B34: 1527389.1 | C34: ='Engine Runs'!$C$411 -> 1527389.1 | D34: =ROUND(C34-B34,0) -> 0 | E34: 3013219.5 | F34: ='Engine Runs'!$C$397 -> 3013219.5 | G34: =ROUND(F34-E34,0) -> 0
A35: Industrial distribution — lean pilot — Downside, stopped at Gate 1 (Q4 2027) | B35: -912381.68 | C35: ='Engine Runs'!$C$551 -> -912381.68 | D35: =ROUND(C35-B35,0) -> 0 | E35: 10088.53 | F35: ='Engine Runs'!$C$537 -> 10088.525 | G35: =ROUND(F35-E35,0) -> 0
A36: Industrial distribution — lean pilot — Upside, 2 AEs hired after Gate 1 | B36: 1567837.8 | C36: ='Engine Runs'!$C$691 -> 1567837.8 | D36: =ROUND(C36-B36,0) -> 0 | E36: 3262047.9 | F36: ='Engine Runs'!$C$677 -> 3262047.9 | G36: =ROUND(F36-E36,0) -> 0
A37: Industrial distribution — sales-led vertical team — Downside | B37: -6046208.1 | C37: ='Engine Runs'!$C$830 -> -6046208.1 | D37: =ROUND(C37-B37,0) -> 0 | E37: 113881.56 | F37: ='Engine Runs'!$C$816 -> 113881.56 | G37: =ROUND(F37-E37,0) -> 0
A38: Industrial distribution — sales-led vertical team — Base | B38: -5438648.7 | C38: ='Engine Runs'!$C$969 -> -5438648.7 | D38: =ROUND(C38-B38,0) -> 0 | E38: 820721.59 | F38: ='Engine Runs'!$C$955 -> 820721.59 | G38: =ROUND(F38-E38,0) -> 0
A39: Industrial distribution — sales-led vertical team — Upside | B39: 821457.73 | C39: ='Engine Runs'!$C$1108 -> 821457.73 | D39: =ROUND(C39-B39,0) -> 0 | E39: 4711541.7 | F39: ='Engine Runs'!$C$1094 -> 4711541.7 | G39: =ROUND(F39-E39,0) -> 0
A40: Industrial distribution — solution play — Downside | B40: -625495.41 | C40: ='Engine Runs'!$C$1247 -> -625495.41 | D40: =ROUND(C40-B40,0) -> 0 | E40: 30663.05 | F40: ='Engine Runs'!$C$1233 -> 30663.055 | G40: =ROUND(F40-E40,0) -> 0
A41: Industrial distribution — solution play — Base | B41: -544641.96 | C41: ='Engine Runs'!$C$1386 -> -544641.96 | D41: =ROUND(C41-B41,0) -> 0 | E41: 246156.7 | F41: ='Engine Runs'!$C$1372 -> 246156.7 | G41: =ROUND(F41-E41,0) -> 0
A42: Industrial distribution — solution play — Upside | B42: 1114412.4 | C42: ='Engine Runs'!$C$1525 -> 1114412.4 | D42: =ROUND(C42-B42,0) -> 0 | E42: 1463066.3 | F42: ='Engine Runs'!$C$1511 -> 1463066.3 | G42: =ROUND(F42-E42,0) -> 0
A43: Professional services — lean pilot — Downside | B43: -2148114.9 | C43: ='Engine Runs'!$C$1664 -> -2148114.9 | D43: =ROUND(C43-B43,0) -> 0 | E43: 110994.42 | F43: ='Engine Runs'!$C$1650 -> 110994.42 | G43: =ROUND(F43-E43,0) -> 0
A44: Professional services — lean pilot — Base | B44: -2044076.8 | C44: ='Engine Runs'!$C$1803 -> -2044076.8 | D44: =ROUND(C44-B44,0) -> 0 | E44: 680163.89 | F44: ='Engine Runs'!$C$1789 -> 680163.89 | G44: =ROUND(F44-E44,0) -> 0
A45: Professional services — lean pilot — Upside | B45: -249190.25 | C45: ='Engine Runs'!$C$1942 -> -249190.25 | D45: =ROUND(C45-B45,0) -> 0 | E45: 2609610.8 | F45: ='Engine Runs'!$C$1928 -> 2609610.8 | G45: =ROUND(F45-E45,0) -> 0
A46: Professional services — lean pilot — Downside, stopped at Gate 1 (Q4 2027) | B46: -927042.33 | C46: ='Engine Runs'!$C$2082 -> -927042.33 | D46: =ROUND(C46-B46,0) -> 0 | E46: 19612.01 | F46: ='Engine Runs'!$C$2068 -> 19612.014 | G46: =ROUND(F46-E46,0) -> 0
A47: Professional services — lean pilot — Upside, 2 AEs hired after Gate 1 | B47: -622652.81 | C47: ='Engine Runs'!$C$2222 -> -622652.81 | D47: =ROUND(C47-B47,0) -> 0 | E47: 2703520.7 | F47: ='Engine Runs'!$C$2208 -> 2703520.7 | G47: =ROUND(F47-E47,0) -> 0
A48: Professional services — sales-led vertical team — Downside | B48: -6093023.6 | C48: ='Engine Runs'!$C$2361 -> -6093023.6 | D48: =ROUND(C48-B48,0) -> 0 | E48: 161375.75 | F48: ='Engine Runs'!$C$2347 -> 161375.75 | G48: =ROUND(F48-E48,0) -> 0
A49: Professional services — sales-led vertical team — Base | B49: -5731151.9 | C49: ='Engine Runs'!$C$2500 -> -5731151.9 | D49: =ROUND(C49-B49,0) -> 0 | E49: 914355.66 | F49: ='Engine Runs'!$C$2486 -> 914355.66 | G49: =ROUND(F49-E49,0) -> 0
A50: Professional services — sales-led vertical team — Upside | B50: -2873027.5 | C50: ='Engine Runs'!$C$2639 -> -2873027.5 | D50: =ROUND(C50-B50,0) -> 0 | E50: 3491416.3 | F50: ='Engine Runs'!$C$2625 -> 3491416.3 | G50: =ROUND(F50-E50,0) -> 0
A51: Professional services — solution play — Downside | B51: -648617.85 | C51: ='Engine Runs'!$C$2778 -> -648617.85 | D51: =ROUND(C51-B51,0) -> 0 | E51: 51399.29 | F51: ='Engine Runs'!$C$2764 -> 51399.292 | G51: =ROUND(F51-E51,0) -> 0
A52: Professional services — solution play — Base | B52: -620644.16 | C52: ='Engine Runs'!$C$2917 -> -620644.16 | D52: =ROUND(C52-B52,0) -> 0 | E52: 317295.3 | F52: ='Engine Runs'!$C$2903 -> 317295.3 | G52: =ROUND(F52-E52,0) -> 0
A53: Professional services — solution play — Upside | B53: 223947.77 | C53: ='Engine Runs'!$C$3056 -> 223947.77 | D53: =ROUND(C53-B53,0) -> 0 | E53: 1231458.7 | F53: ='Engine Runs'!$C$3042 -> 1231458.7 | G53: =ROUND(F53-E53,0) -> 0
A54: Maximum absolute difference | D54: =MAX(MAX(D32:D53),-MIN(D32:D53)) -> 0 | G54: =MAX(MAX(G32:G53),-MIN(G32:G53)) -> 0
A56: NPV distribution — distribution segment (share of draws per $250K bin; end bins are open)
A57: NPV bin (lower edge) | B57: Lean pilot, staged | C57: Sales-led team | D57: Solution play
A58: -6500000 | B58: 0 | C58: 0 | D58: 0
A59: -6250000 | B59: 0 | C59: 0 | D59: 0
A60: -6000000 | B60: 0 | C60: 0.0908 | D60: 0
A61: -5750000 | B61: 0 | C61: 0.2934 | D61: 0
A62: -5500000 | B62: 0 | C62: 0.265 | D62: 0
A63: -5250000 | B63: 0 | C63: 0.166 | D63: 0
A64: -5000000 | B64: 0 | C64: 0.0914 | D64: 0
A65: -4750000 | B65: 0 | C65: 0.0462 | D65: 0
A66: -4500000 | B66: 0 | C66: 0.025 | D66: 0
A67: -4250000 | B67: 0 | C67: 0.0132 | D67: 0
A68: -4000000 | B68: 0 | C68: 0.006 | D68: 0
A69: -3750000 | B69: 0 | C69: 0.0016 | D69: 0
... A92: 2000000 | B92: 0 | C92: 0 | D92: 0
A94: Gate thresholds (Assumptions › Gate 1 rule) sit at the midpoints between the deterministic Downside/Base and Base/Upside 2027 paths. Observed 2027 metrics are drawn with Poisson/binomial noise, so the gate can misclassify (review C3). Staged-policy NPV includes 2027 spend even when the program is stopped.

Sheet Engine Runs
A1: Engine Runs — full copies of the model for every scenario, option and sensitivity case
A2: Generated by the same code as the live model. Each block lists its overrides; the Python engine (appendix/clay_engine.py) reproduces every scenario block (Monte Carlo › reconciliation).
A4: RUN: Industrial distribution — lean pilot — Downside
A5: Industrial distribution — lean pilot — Downside — run constants | B5: Unit / note | C5: Q1 2027 | D5: Q2 2027 | E5: Q3 2027 | F5: Q4 2027 | G5: Q1 2028 | H5: Q2 2028 | I5: Q3 2028 | J5: Q4 2028 | K5: Q1 2029 | L5: Q2 2029 | M5: Q3 2029 | N5: Q4 2029 | P5: 2027 | Q5: 2028 | R5: 2029 | S5: 2027–29
A6: SAM accounts — wave 1, S | B6: firms × filters | C6: ='Market Sizing'!$C$17*Assumptions!$D$10*Assumptions!$D$11*(1-Assumptions!$D$12) -> 843.03945
A7: SAM accounts — wave 1, M | B7: firms × filters | C7: ='Market Sizing'!$D$17*Assumptions!$D$10*Assumptions!$D$11*(1-Assumptions!$D$12) -> 211.19616
A8: SAM accounts — wave 1, E | B8: firms × filters | C8: ='Market Sizing'!$E$17*Assumptions!$D$10*Assumptions!$D$11*(1-Assumptions!$D$12) -> 49.53984
A9: SAM accounts — wave 1, total | C9: =$C$6+$C$7+$C$8 -> 1103.7754
A10: SAM accounts — wave 2, S | B10: firms × filters | C10: ='Market Sizing'!$C$18*Assumptions!$D$10*Assumptions!$D$11*(1-Assumptions!$D$12) -> 612.57707
A11: SAM accounts — wave 2, M | B11: firms × filters | C11: ='Market Sizing'!$D$18*Assumptions!$D$10*Assumptions!$D$11*(1-Assumptions!$D$12) -> 142.10112
A12: SAM accounts — wave 2, E | B12: firms × filters | C12: ='Market Sizing'!$E$18*Assumptions!$D$10*Assumptions!$D$11*(1-Assumptions!$D$12) -> 24.76992
A13: SAM accounts — wave 2, total | C13: =$C$10+$C$11+$C$12 -> 779.44811
A14: SAM accounts — wave 3, S | B14: firms × filters | C14: ='Market Sizing'!$C$19*Assumptions!$D$10*Assumptions!$D$11*(1-Assumptions!$D$12) -> 2060.773
A15: SAM accounts — wave 3, M | B15: firms × filters | C15: ='Market Sizing'!$D$19*Assumptions!$D$10*Assumptions!$D$11*(1-Assumptions!$D$12) -> 428.47616
A16: SAM accounts — wave 3, E | B16: firms × filters | C16: ='Market Sizing'!$E$19*Assumptions!$D$10*Assumptions!$D$11*(1-Assumptions!$D$12) -> 79.52448
A17: SAM accounts — wave 3, total | C17: =$C$14+$C$15+$C$16 -> 2568.7737
A18: First-year ACV — S | B18: usage build | C18: =MAX((Assumptions!$D$51+Assumptions!$D$53)*12,(((('Market Sizing'!$E$25*Assumptions!$D$41*Assumptions!$D$42*Assumptions!$D$43)*Assumptions!$D$44)*Assumptions!$D$45*Assumptions!$D$46+('Market Sizing'!$E$25*Assumptions!$D$41*Assumptions!$D$42*Assumptions!$D$43)*Assumptions!$D$47+('Market Sizing'!$E$25*Assumptions!$D$41*Assumptions!$D$42*Assumptions!$D$43)*Assumptions!$D$48*Assumptions!$D$49)*(Assumptions!$D$51*12/Assumptions!$D$52)+((('Market Sizing'!$E$25*Assumptions!$D$41*Assumptions!$D$42*Assumptions!$D$43)*Assumptions!$D$44)*Assumptions!$D$45+('Market Sizing'!$E$25*Assumptions!$D$41*Assumptions!$D$42*Assumptions!$D$43)+('Market Sizing'!$E$25*Assumptions!$D$41*Assumptions!$D$42*Assumptions!$D$43)*Assumptions!$D$48)*Assumptions!$D$50*(Assumptions!$D$53*12/Assumptions!$D$54))) -> 5352
A19: First-year ACV — M | B19: usage build | C19: =MAX((Assumptions!$D$51+Assumptions!$D$53)*12,(((('Market Sizing'!$E$26*Assumptions!$D$41*Assumptions!$D$42*Assumptions!$D$43)*Assumptions!$D$44)*Assumptions!$D$45*Assumptions!$D$46+('Market Sizing'!$E$26*Assumptions!$D$41*Assumptions!$D$42*Assumptions!$D$43)*Assumptions!$D$47+('Market Sizing'!$E$26*Assumptions!$D$41*Assumptions!$D$42*Assumptions!$D$43)*Assumptions!$D$48*Assumptions!$D$49)*(Assumptions!$D$51*12/Assumptions!$D$52)+((('Market Sizing'!$E$26*Assumptions!$D$41*Assumptions!$D$42*Assumptions!$D$43)*Assumptions!$D$44)*Assumptions!$D$45+('Market Sizing'!$E$26*Assumptions!$D$41*Assumptions!$D$42*Assumptions!$D$43)+('Market Sizing'!$E$26*Assumptions!$D$41*Assumptions!$D$42*Assumptions!$D$43)*Assumptions!$D$48)*Assumptions!$D$50*(Assumptions!$D$53*12/Assumptions!$D$54))) -> 7325.0401
A20: First-year ACV — E | B20: usage build | C20: =MAX(Assumptions!$D$55*(Assumptions!$D$51*12/Assumptions!$D$52)+Assumptions!$D$56*(Assumptions!$D$53*12/Assumptions!$D$54),(((('Market Sizing'!$E$27*Assumptions!$D$41*Assumptions!$D$42*Assumptions!$D$43)*Assumptions!$D$44)*Assumptions!$D$45*Assumptions!$D$46+('Market Sizing'!$E$27*Assumptions!$D$41*Assumptions!$D$42*Assumptions!$D$43)*Assumptions!$D$47+('Market Sizing'!$E$27*Assumptions!$D$41*Assumptions!$D$42*Assumptions!$D$43)*Assumptions!$D$48*Assumptions!$D$49)*(Assumptions!$D$51*12/Assumptions!$D$52)+((('Market Sizing'!$E$27*Assumptions!$D$41*Assumptions!$D$42*Assumptions!$D$43)*Assumptions!$D$44)*Assumptions!$D$45+('Market Sizing'!$E$27*Assumptions!$D$41*Assumptions!$D$42*Assumptions!$D$43)+('Market Sizing'!$E$27*Assumptions!$D$41*Assumptions!$D$42*Assumptions!$D$43)*Assumptions!$D$48)*Assumptions!$D$50*(Assumptions!$D$53*12/Assumptions!$D$54)))*(1-Assumptions!$D$57) -> 46333.692
A21: Automated outbound coverage per quarter | B21: coverage × motion multiplier | C21: =Assumptions!$D$17*Assumptions!$D$106 -> 0.3
A22: AE fully loaded annual cost | B22: OTE ÷ wage share | C22: =Assumptions!$D$68/Assumptions!$D$69 -> 285714.29
A23: ARR one ramped AE closes per quarter | B23: quota × productivity ÷ 4 | C23: =Assumptions!$D$66*Assumptions!$D$67/4 -> 120312.5
A24: AE cost per $ of first-year ACV closed | C24: =$C$22/Assumptions!$D$66/Assumptions!$D$67 -> 0.59369202
A25: Program spend above base, per quarter | C25: =MAX(0,Assumptions!$D$103-Assumptions!$D$78) -> 0
A26: Demand and funnel | B26: Unit / note | C26: Q1 2027 | D26: Q2 2027 | E26: Q3 2027 | F26: Q4 2027 | G26: Q1 2028 | H26: Q2 2028 | I26: Q3 2028 | J26: Q4 2028 | K26: Q1 2029 | L26: Q2 2029 | M26: Q3 2029 | N26: Q4 2029 | P26: 2027 | Q26: 2028 | R26: 2029 | S26: 2027–29
A27: Quarter number | B27: # | C27: 1 | D27: 2 | E27: 3 | F27: 4 | G27: 5 | H27: 6 | I27: 7 | J27: 8 | K27: 9 | L27: 10 | M27: 11 | N27: 12
A28: Program running (1) / stopped (0) | B28: flag | C28: =IF(C27<=Assumptions!$D$84,1,0) -> 1 | D28: =IF(D27<=Assumptions!$D$84,1,0) -> 1 | E28: =IF(E27<=Assumptions!$D$84,1,0) -> 1 | F28: =IF(F27<=Assumptions!$D$84,1,0) -> 1 | G28: =IF(G27<=Assumptions!$D$84,1,0) -> 1 | H28: =IF(H27<=Assumptions!$D$84,1,0) -> 1 | I28: =IF(I27<=Assumptions!$D$84,1,0) -> 1 | J28: =IF(J27<=Assumptions!$D$84,1,0) -> 1 | ... N28: =IF(N27<=Assumptions!$D$84,1,0) -> 1
A29: Wave 1 active (0.5 in launch quarter) | B29: factor | C29: =IF(C27=Assumptions!$D$13,0.5,IF(C27>Assumptions!$D$13,1,0)) -> 0.5 | D29: =IF(D27=Assumptions!$D$13,0.5,IF(D27>Assumptions!$D$13,1,0)) -> 1 | E29: =IF(E27=Assumptions!$D$13,0.5,IF(E27>Assumptions!$D$13,1,0)) -> 1 | F29: =IF(F27=Assumptions!$D$13,0.5,IF(F27>Assumptions!$D$13,1,0)) -> 1 | G29: =IF(G27=Assumptions!$D$13,0.5,IF(G27>Assumptions!$D$13,1,0)) -> 1 | H29: =IF(H27=Assumptions!$D$13,0.5,IF(H27>Assumptions!$D$13,1,0)) -> 1 | I29: =IF(I27=Assumptions!$D$13,0.5,IF(I27>Assumptions!$D$13,1,0)) -> 1 | J29: =IF(J27=Assumptions!$D$13,0.5,IF(J27>Assumptions!$D$13,1,0)) -> 1 | ... N29: =IF(N27=Assumptions!$D$13,0.5,IF(N27>Assumptions!$D$13,1,0)) -> 1
A30: Wave 2 active (0.5 in launch quarter) | B30: factor | C30: =IF(C27=Assumptions!$D$14,0.5,IF(C27>Assumptions!$D$14,1,0)) -> 0 | D30: =IF(D27=Assumptions!$D$14,0.5,IF(D27>Assumptions!$D$14,1,0)) -> 0 | E30: =IF(E27=Assumptions!$D$14,0.5,IF(E27>Assumptions!$D$14,1,0)) -> 0 | F30: =IF(F27=Assumptions!$D$14,0.5,IF(F27>Assumptions!$D$14,1,0)) -> 0 | G30: =IF(G27=Assumptions!$D$14,0.5,IF(G27>Assumptions!$D$14,1,0)) -> 0 | H30: =IF(H27=Assumptions!$D$14,0.5,IF(H27>Assumptions!$D$14,1,0)) -> 0 | I30: =IF(I27=Assumptions!$D$14,0.5,IF(I27>Assumptions!$D$14,1,0)) -> 0.5 | J30: =IF(J27=Assumptions!$D$14,0.5,IF(J27>Assumptions!$D$14,1,0)) -> 1 | ... N30: =IF(N27=Assumptions!$D$14,0.5,IF(N27>Assumptions!$D$14,1,0)) -> 1
A31: Wave 3 active (0.5 in launch quarter) | B31: factor | C31: =IF(C27=Assumptions!$D$15,0.5,IF(C27>Assumptions!$D$15,1,0)) -> 0 | D31: =IF(D27=Assumptions!$D$15,0.5,IF(D27>Assumptions!$D$15,1,0)) -> 0 | E31: =IF(E27=Assumptions!$D$15,0.5,IF(E27>Assumptions!$D$15,1,0)) -> 0 | F31: =IF(F27=Assumptions!$D$15,0.5,IF(F27>Assumptions!$D$15,1,0)) -> 0 | G31: =IF(G27=Assumptions!$D$15,0.5,IF(G27>Assumptions!$D$15,1,0)) -> 0 | H31: =IF(H27=Assumptions!$D$15,0.5,IF(H27>Assumptions!$D$15,1,0)) -> 0 | I31: =IF(I27=Assumptions!$D$15,0.5,IF(I27>Assumptions!$D$15,1,0)) -> 0 | J31: =IF(J27=Assumptions!$D$15,0.5,IF(J27>Assumptions!$D$15,1,0)) -> 0 | ... N31: =IF(N27=Assumptions!$D$15,0.5,IF(N27>Assumptions!$D$15,1,0)) -> 0
A32: Wave 1 outbound fatigue factor | B32: factor | C32: =Assumptions!$D$21^(MAX(0,C27-Assumptions!$D$13)/4) -> 1 | D32: =Assumptions!$D$21^(MAX(0,D27-Assumptions!$D$13)/4) -> 0.88011174 | E32: =Assumptions!$D$21^(MAX(0,E27-Assumptions!$D$13)/4) -> 0.77459667 | F32: =Assumptions!$D$21^(MAX(0,F27-Assumptions!$D$13)/4) -> 0.68173162 | G32: =Assumptions!$D$21^(MAX(0,G27-Assumptions!$D$13)/4) -> 0.6 | H32: =Assumptions!$D$21^(MAX(0,H27-Assumptions!$D$13)/4) -> 0.52806704 | I32: =Assumptions!$D$21^(MAX(0,I27-Assumptions!$D$13)/4) -> 0.464758 | J32: =Assumptions!$D$21^(MAX(0,J27-Assumptions!$D$13)/4) -> 0.40903897 | ... N32: =Assumptions!$D$21^(MAX(0,N27-Assumptions!$D$13)/4) -> 0.24542338
A33: Wave 2 outbound fatigue factor | B33: factor | C33: =Assumptions!$D$21^(MAX(0,C27-Assumptions!$D$14)/4) -> 1 | D33: =Assumptions!$D$21^(MAX(0,D27-Assumptions!$D$14)/4) -> 1 | E33: =Assumptions!$D$21^(MAX(0,E27-Assumptions!$D$14)/4) -> 1 | F33: =Assumptions!$D$21^(MAX(0,F27-Assumptions!$D$14)/4) -> 1 | G33: =Assumptions!$D$21^(MAX(0,G27-Assumptions!$D$14)/4) -> 1 | H33: =Assumptions!$D$21^(MAX(0,H27-Assumptions!$D$14)/4) -> 1 | I33: =Assumptions!$D$21^(MAX(0,I27-Assumptions!$D$14)/4) -> 1 | J33: =Assumptions!$D$21^(MAX(0,J27-Assumptions!$D$14)/4) -> 0.88011174 | ... N33: =Assumptions!$D$21^(MAX(0,N27-Assumptions!$D$14)/4) -> 0.52806704
A34: Wave 3 outbound fatigue factor | B34: factor | C34: =Assumptions!$D$21^(MAX(0,C27-Assumptions!$D$15)/4) -> 1 | D34: =Assumptions!$D$21^(MAX(0,D27-Assumptions!$D$15)/4) -> 1 | E34: =Assumptions!$D$21^(MAX(0,E27-Assumptions!$D$15)/4) -> 1 | F34: =Assumptions!$D$21^(MAX(0,F27-Assumptions!$D$15)/4) -> 1 | G34: =Assumptions!$D$21^(MAX(0,G27-Assumptions!$D$15)/4) -> 1 | H34: =Assumptions!$D$21^(MAX(0,H27-Assumptions!$D$15)/4) -> 1 | I34: =Assumptions!$D$21^(MAX(0,I27-Assumptions!$D$15)/4) -> 1 | J34: =Assumptions!$D$21^(MAX(0,J27-Assumptions!$D$15)/4) -> 1 | ... N34: =Assumptions!$D$21^(MAX(0,N27-Assumptions!$D$15)/4) -> 1
A35: Active SAM accounts — S | B35: accounts | C35: =$C$6*C29+$C$10*C30+$C$14*C31 -> 421.51972 | D35: =$C$6*D29+$C$10*D30+$C$14*D31 -> 843.03945 | E35: =$C$6*E29+$C$10*E30+$C$14*E31 -> 843.03945 | F35: =$C$6*F29+$C$10*F30+$C$14*F31 -> 843.03945 | G35: =$C$6*G29+$C$10*G30+$C$14*G31 -> 843.03945 | H35: =$C$6*H29+$C$10*H30+$C$14*H31 -> 843.03945 | I35: =$C$6*I29+$C$10*I30+$C$14*I31 -> 1149.328 | J35: =$C$6*J29+$C$10*J30+$C$14*J31 -> 1455.6165 | ... N35: =$C$6*N29+$C$10*N30+$C$14*N31 -> 1455.6165 | P35: =F35 -> 843.03945 | Q35: =J35 -> 1455.6165 | R35: =N35 -> 1455.6165 | S35: =R35 -> 1455.6165
A36: Active SAM accounts — M | B36: accounts | C36: =$C$7*C29+$C$11*C30+$C$15*C31 -> 105.59808 | D36: =$C$7*D29+$C$11*D30+$C$15*D31 -> 211.19616 | E36: =$C$7*E29+$C$11*E30+$C$15*E31 -> 211.19616 | F36: =$C$7*F29+$C$11*F30+$C$15*F31 -> 211.19616 | G36: =$C$7*G29+$C$11*G30+$C$15*G31 -> 211.19616 | H36: =$C$7*H29+$C$11*H30+$C$15*H31 -> 211.19616 | I36: =$C$7*I29+$C$11*I30+$C$15*I31 -> 282.24672 | J36: =$C$7*J29+$C$11*J30+$C$15*J31 -> 353.29728 | ... N36: =$C$7*N29+$C$11*N30+$C$15*N31 -> 353.29728 | P36: =F36 -> 211.19616 | Q36: =J36 -> 353.29728 | R36: =N36 -> 353.29728 | S36: =R36 -> 353.29728
A37: Active SAM accounts — E | B37: accounts | C37: =$C$8*C29+$C$12*C30+$C$16*C31 -> 24.76992 | D37: =$C$8*D29+$C$12*D30+$C$16*D31 -> 49.53984 | E37: =$C$8*E29+$C$12*E30+$C$16*E31 -> 49.53984 | F37: =$C$8*F29+$C$12*F30+$C$16*F31 -> 49.53984 | G37: =$C$8*G29+$C$12*G30+$C$16*G31 -> 49.53984 | H37: =$C$8*H29+$C$12*H30+$C$16*H31 -> 49.53984 | I37: =$C$8*I29+$C$12*I30+$C$16*I31 -> 61.9248 | J37: =$C$8*J29+$C$12*J30+$C$16*J31 -> 74.30976 | ... N37: =$C$8*N29+$C$12*N30+$C$16*N31 -> 74.30976 | P37: =F37 -> 49.53984 | Q37: =J37 -> 74.30976 | R37: =N37 -> 74.30976 | S37: =R37 -> 74.30976
A38: Active SAM accounts — total | B38: accounts | C38: =C35+C36+C37 -> 551.88772 | D38: =D35+D36+D37 -> 1103.7754 | E38: =E35+E36+E37 -> 1103.7754 | F38: =F35+F36+F37 -> 1103.7754 | G38: =G35+G36+G37 -> 1103.7754 | H38: =H35+H36+H37 -> 1103.7754 | I38: =I35+I36+I37 -> 1493.4995 | J38: =J35+J36+J37 -> 1883.2236 | ... N38: =N35+N36+N37 -> 1883.2236 | P38: =F38 -> 1103.7754 | Q38: =J38 -> 1883.2236 | R38: =N38 -> 1883.2236 | S38: =R38 -> 1883.2236
A39: Fatigue-weighted active accounts | B39: accounts | C39: =$C$9*C29*C32+$C$13*C30*C33+$C$17*C31*C34 -> 551.88772 | D39: =$C$9*D29*D32+$C$13*D30*D33+$C$17*D31*D34 -> 971.44573 | E39: =$C$9*E29*E32+$C$13*E30*E33+$C$17*E31*E34 -> 854.98078 | F39: =$C$9*F29*F32+$C$13*F30*F33+$C$17*F31*F34 -> 752.47862 | G39: =$C$9*G29*G32+$C$13*G30*G33+$C$17*G31*G34 -> 662.26527 | H39: =$C$9*H29*H32+$C$13*H30*H33+$C$17*H31*H34 -> 582.86744 | I39: =$C$9*I29*I32+$C$13*I30*I33+$C$17*I31*I34 -> 902.71253 | J39: =$C$9*J29*J32+$C$13*J30*J33+$C$17*J31*J34 -> 1137.4886 | ... N39: =$C$9*N29*N32+$C$13*N30*N33+$C$17*N31*N34 -> 682.49316
A40: Meetings — automated outbound | B40: meetings | C40: =$C$21*Assumptions!$D$20*C28*C39 -> 3.3113263 | D40: =$C$21*Assumptions!$D$20*D28*D39 -> 5.8286744 | E40: =$C$21*Assumptions!$D$20*E28*E39 -> 5.1298847 | F40: =$C$21*Assumptions!$D$20*F28*F39 -> 4.5148717 | G40: =$C$21*Assumptions!$D$20*G28*G39 -> 3.9735916 | H40: =$C$21*Assumptions!$D$20*H28*H39 -> 3.4972046 | I40: =$C$21*Assumptions!$D$20*I28*I39 -> 5.4162752 | J40: =$C$21*Assumptions!$D$20*J28*J39 -> 6.8249316 | ... N40: =$C$21*Assumptions!$D$20*N28*N39 -> 4.094959 | P40: =SUM(C40:F40) -> 18.784757 | Q40: =SUM(G40:J40) -> 19.712003 | R40: =SUM(K40:N40) -> 20.041002 | S40: =SUM(P40:R40) -> 58.537763
A41: Dedicated AEs (headcount) | B41: FTE | C41: =Assumptions!$D$111 -> 0 | D41: =Assumptions!$E$111 -> 0 | E41: =Assumptions!$F$111 -> 0 | F41: =Assumptions!$G$111 -> 0 | G41: =Assumptions!$H$111 -> 0 | H41: =Assumptions!$I$111 -> 0 | I41: =Assumptions!$J$111 -> 0 | J41: =Assumptions!$K$111 -> 0 | K41: =Assumptions!$L$111 -> 0 | L41: =Assumptions!$M$111 -> 0 | M41: =Assumptions!$N$111 -> 0 | N41: =Assumptions!$O$111 -> 0 | P41: =F41 -> 0 | Q41: =J41 -> 0 | R41: =N41 -> 0 | S41: =R41 -> 0
A42: Ramped dedicated AEs (≈6-month ramp) | B42: FTE | C42: =0 -> 0 | D42: =0.5*C41 -> 0 | E42: =C41+0.5*(D41-C41) -> 0 | F42: =D41+0.5*(E41-D41) -> 0 | G42: =E41+0.5*(F41-E41) -> 0 | H42: =F41+0.5*(G41-F41) -> 0 | I42: =G41+0.5*(H41-G41) -> 0 | J42: =H41+0.5*(I41-H41) -> 0 | K42: =I41+0.5*(J41-I41) -> 0 | L42: =J41+0.5*(K41-J41) -> 0 | ... N42: =L41+0.5*(M41-L41) -> 0 | P42: =F42 -> 0 | Q42: =J42 -> 0 | R42: =N42 -> 0 | S42: =R42 -> 0
A43: Accounts worked by dedicated AEs | B43: accounts | C43: =MIN(C42*Assumptions!$D$38,C38*(1-$C$21)) -> 0 | D43: =MIN(D42*Assumptions!$D$38,D38*(1-$C$21)) -> 0 | E43: =MIN(E42*Assumptions!$D$38,E38*(1-$C$21)) -> 0 | F43: =MIN(F42*Assumptions!$D$38,F38*(1-$C$21)) -> 0 | G43: =MIN(G42*Assumptions!$D$38,G38*(1-$C$21)) -> 0 | H43: =MIN(H42*Assumptions!$D$38,H38*(1-$C$21)) -> 0 | I43: =MIN(I42*Assumptions!$D$38,I38*(1-$C$21)) -> 0 | J43: =MIN(J42*Assumptions!$D$38,J38*(1-$C$21)) -> 0 | ... N43: =MIN(N42*Assumptions!$D$38,N38*(1-$C$21)) -> 0 | P43: =SUM(C43:F43) -> 0 | Q43: =SUM(G43:J43) -> 0 | R43: =SUM(K43:N43) -> 0 | S43: =SUM(P43:R43) -> 0
A44: Meetings — AE self-sourced outreach | B44: meetings | C44: =C43*Assumptions!$D$20*Assumptions!$D$39*IF(C38>0,C39/C38,0)*C28 -> 0 | D44: =D43*Assumptions!$D$20*Assumptions!$D$39*IF(D38>0,D39/D38,0)*D28 -> 0 | E44: =E43*Assumptions!$D$20*Assumptions!$D$39*IF(E38>0,E39/E38,0)*E28 -> 0 | F44: =F43*Assumptions!$D$20*Assumptions!$D$39*IF(F38>0,F39/F38,0)*F28 -> 0 | G44: =G43*Assumptions!$D$20*Assumptions!$D$39*IF(G38>0,G39/G38,0)*G28 -> 0 | H44: =H43*Assumptions!$D$20*Assumptions!$D$39*IF(H38>0,H39/H38,0)*H28 -> 0 | I44: =I43*Assumptions!$D$20*Assumptions!$D$39*IF(I38>0,I39/I38,0)*I28 -> 0 | J44: =J43*Assumptions!$D$20*Assumptions!$D$39*IF(J38>0,J39/J38,0)*J28 -> 0 | ... N44: =N43*Assumptions!$D$20*Assumptions!$D$39*IF(N38>0,N39/N38,0)*N28 -> 0 | P44: =SUM(C44:F44) -> 0 | Q44: =SUM(G44:J44) -> 0 | R44: =SUM(K44:N44) -> 0 | S44: =SUM(P44:R44) -> 0
A45: Extra MQLs bought by program spend above base | B45: MQLs | C45: =IF(AND(C38>0,$C$25>0),C38*Assumptions!$D$24*(1-EXP(-$C$25/(Assumptions!$D$23*C38*Assumptions!$D$24))),0) -> 0 | D45: =IF(AND(D38>0,$C$25>0),D38*Assumptions!$D$24*(1-EXP(-$C$25/(Assumptions!$D$23*D38*Assumptions!$D$24))),0) -> 0 | E45: =IF(AND(E38>0,$C$25>0),E38*Assumptions!$D$24*(1-EXP(-$C$25/(Assumptions!$D$23*E38*Assumptions!$D$24))),0) -> 0 | F45: =IF(AND(F38>0,$C$25>0),F38*Assumptions!$D$24*(1-EXP(-$C$25/(Assumptions!$D$23*F38*Assumptions!$D$24))),0) -> 0 | G45: =IF(AND(G38>0,$C$25>0),G38*Assumptions!$D$24*(1-EXP(-$C$25/(Assumptions!$D$23*G38*Assumptions!$D$24))),0) -> 0 | H45: =IF(AND(H38>0,$C$25>0),H38*Assumptions!$D$24*(1-EXP(-$C$25/(Assumptions!$D$23*H38*Assumptions!$D$24))),0) -> 0 | I45: =IF(AND(I38>0,$C$25>0),I38*Assumptions!$D$24*(1-EXP(-$C$25/(Assumptions!$D$23*I38*Assumptions!$D$24))),0) -> 0 | J45: =IF(AND(J38>0,$C$25>0),J38*Assumptions!$D$24*(1-EXP(-$C$25/(Assumptions!$D$23*J38*Assumptions!$D$24))),0) -> 0 | ... N45: =IF(AND(N38>0,$C$25>0),N38*Assumptions!$D$24*(1-EXP(-$C$25/(Assumptions!$D$23*N38*Assumptions!$D$24))),0) -> 0 | P45: =SUM(C45:F45) -> 0 | Q45: =SUM(G45:J45) -> 0 | R45: =SUM(K45:N45) -> 0 | S45: =SUM(P45:R45) -> 0
A46: MQLs — inbound / templates | B46: MQLs | C46: =(C38*Assumptions!$D$22*MIN(1,Assumptions!$D$103/Assumptions!$D$78)+C45)*C28 -> 2.7594386 | D46: =(D38*Assumptions!$D$22*MIN(1,Assumptions!$D$103/Assumptions!$D$78)+D45)*D28 -> 5.5188772 | E46: =(E38*Assumptions!$D$22*MIN(1,Assumptions!$D$103/Assumptions!$D$78)+E45)*E28 -> 5.5188772 | F46: =(F38*Assumptions!$D$22*MIN(1,Assumptions!$D$103/Assumptions!$D$78)+F45)*F28 -> 5.5188772 | G46: =(G38*Assumptions!$D$22*MIN(1,Assumptions!$D$103/Assumptions!$D$78)+G45)*G28 -> 5.5188772 | H46: =(H38*Assumptions!$D$22*MIN(1,Assumptions!$D$103/Assumptions!$D$78)+H45)*H28 -> 5.5188772 | I46: =(I38*Assumptions!$D$22*MIN(1,Assumptions!$D$103/Assumptions!$D$78)+I45)*I28 -> 7.4674975 | J46: =(J38*Assumptions!$D$22*MIN(1,Assumptions!$D$103/Assumptions!$D$78)+J45)*J28 -> 9.4161178 | ... N46: =(N38*Assumptions!$D$22*MIN(1,Assumptions!$D$103/Assumptions!$D$78)+N45)*N28 -> 9.4161178 | P46: =SUM(C46:F46) -> 19.31607 | Q46: =SUM(G46:J46) -> 27.92137 | R46: =SUM(K46:N46) -> 37.664471 | S46: =SUM(P46:R46) -> 84.901911
A47: Active partners | B47: partners | C47: =C28*MIN(Assumptions!$D$27,Assumptions!$D$25+Assumptions!$D$26*(C27-1))*Assumptions!$D$107 -> 1 | D47: =D28*MIN(Assumptions!$D$27,Assumptions!$D$25+Assumptions!$D$26*(D27-1))*Assumptions!$D$107 -> 2 | E47: =E28*MIN(Assumptions!$D$27,Assumptions!$D$25+Assumptions!$D$26*(E27-1))*Assumptions!$D$107 -> 3 | F47: =F28*MIN(Assumptions!$D$27,Assumptions!$D$25+Assumptions!$D$26*(F27-1))*Assumptions!$D$107 -> 4 | G47: =G28*MIN(Assumptions!$D$27,Assumptions!$D$25+Assumptions!$D$26*(G27-1))*Assumptions!$D$107 -> 5 | H47: =H28*MIN(Assumptions!$D$27,Assumptions!$D$25+Assumptions!$D$26*(H27-1))*Assumptions!$D$107 -> 5 | I47: =I28*MIN(Assumptions!$D$27,Assumptions!$D$25+Assumptions!$D$26*(I27-1))*Assumptions!$D$107 -> 5 | J47: =J28*MIN(Assumptions!$D$27,Assumptions!$D$25+Assumptions!$D$26*(J27-1))*Assumptions!$D$107 -> 5 | ... N47: =N28*MIN(Assumptions!$D$27,Assumptions!$D$25+Assumptions!$D$26*(N27-1))*Assumptions!$D$107 -> 5 | P47: =F47 -> 4 | Q47: =J47 -> 5 | R47: =N47 -> 5 | S47: =R47 -> 5
A48: Partner introductions | B48: intros | C48: =C47*Assumptions!$D$28 -> 2 | D48: =D47*Assumptions!$D$28 -> 4 | E48: =E47*Assumptions!$D$28 -> 6 | F48: =F47*Assumptions!$D$28 -> 8 | G48: =G47*Assumptions!$D$28 -> 10 | H48: =H47*Assumptions!$D$28 -> 10 | I48: =I47*Assumptions!$D$28 -> 10 | J48: =J47*Assumptions!$D$28 -> 10 | ... N48: =N47*Assumptions!$D$28 -> 10 | P48: =SUM(C48:F48) -> 20 | Q48: =SUM(G48:J48) -> 40 | R48: =SUM(K48:N48) -> 40 | S48: =SUM(P48:R48) -> 100
A49: Opportunities — outbound (automated + AE) | B49: opps | C49: =(C40+C44)*Assumptions!$D$29 -> 0.9933979 | D49: =(D40+D44)*Assumptions!$D$29 -> 1.7486023 | E49: =(E40+E44)*Assumptions!$D$29 -> 1.5389654 | F49: =(F40+F44)*Assumptions!$D$29 -> 1.3544615 | G49: =(G40+G44)*Assumptions!$D$29 -> 1.1920775 | H49: =(H40+H44)*Assumptions!$D$29 -> 1.0491614 | I49: =(I40+I44)*Assumptions!$D$29 -> 1.6248825 | J49: =(J40+J44)*Assumptions!$D$29 -> 2.0474795 | ... N49: =(N40+N44)*Assumptions!$D$29 -> 1.2284877 | P49: =SUM(C49:F49) -> 5.6354271 | Q49: =SUM(G49:J49) -> 5.9136009 | R49: =SUM(K49:N49) -> 6.0123007 | S49: =SUM(P49:R49) -> 17.561329
A50: Opportunities — inbound | B50: opps | C50: =C46*Assumptions!$D$31 -> 0.27594386 | D50: =D46*Assumptions!$D$31 -> 0.55188772 | E50: =E46*Assumptions!$D$31 -> 0.55188772 | F50: =F46*Assumptions!$D$31 -> 0.55188772 | G50: =G46*Assumptions!$D$31 -> 0.55188772 | H50: =H46*Assumptions!$D$31 -> 0.55188772 | I50: =I46*Assumptions!$D$31 -> 0.74674975 | J50: =J46*Assumptions!$D$31 -> 0.94161178 | ... N50: =N46*Assumptions!$D$31 -> 0.94161178 | P50: =SUM(C50:F50) -> 1.931607 | Q50: =SUM(G50:J50) -> 2.792137 | R50: =SUM(K50:N50) -> 3.7664471 | S50: =SUM(P50:R50) -> 8.4901911
A51: Opportunities — partner | B51: opps | C51: =C48*Assumptions!$D$30 -> 0.8 | D51: =D48*Assumptions!$D$30 -> 1.6 | E51: =E48*Assumptions!$D$30 -> 2.4 | F51: =F48*Assumptions!$D$30 -> 3.2 | G51: =G48*Assumptions!$D$30 -> 4 | H51: =H48*Assumptions!$D$30 -> 4 | I51: =I48*Assumptions!$D$30 -> 4 | J51: =J48*Assumptions!$D$30 -> 4 | ... N51: =N48*Assumptions!$D$30 -> 4 | P51: =SUM(C51:F51) -> 8 | Q51: =SUM(G51:J51) -> 16 | R51: =SUM(K51:N51) -> 16 | S51: =SUM(P51:R51) -> 40
A52: Opportunities — total | B52: opps | C52: =C49+C50+C51 -> 2.0693418 | D52: =D49+D50+D51 -> 3.90049 | E52: =E49+E50+E51 -> 4.4908531 | F52: =F49+F50+F51 -> 5.1063492 | G52: =G49+G50+G51 -> 5.7439652 | H52: =H49+H50+H51 -> 5.6010491 | I52: =I49+I50+I51 -> 6.3716323 | J52: =J49+J50+J51 -> 6.9890913 | ... N52: =N49+N50+N51 -> 6.1700995 | P52: =SUM(C52:F52) -> 15.567034 | Q52: =SUM(G52:J52) -> 24.705738 | R52: =SUM(K52:N52) -> 25.778748 | S52: =SUM(P52:R52) -> 66.05152
A53: Band weight — SMB (accounts) | B53: weight | C53: =C35 -> 421.51972 | D53: =D35 -> 843.03945 | E53: =E35 -> 843.03945 | F53: =F35 -> 843.03945 | G53: =G35 -> 843.03945 | H53: =H35 -> 843.03945 | I53: =I35 -> 1149.328 | J53: =J35 -> 1455.6165 | ... N53: =N35 -> 1455.6165
A54: Band weight — Mid-Market (accounts × tilt × propensity) | B54: weight | C54: =C36*Assumptions!$D$18*Assumptions!$D$33 -> 211.19616 | D54: =D36*Assumptions!$D$18*Assumptions!$D$33 -> 422.39232 | E54: =E36*Assumptions!$D$18*Assumptions!$D$33 -> 422.39232 | F54: =F36*Assumptions!$D$18*Assumptions!$D$33 -> 422.39232 | G54: =G36*Assumptions!$D$18*Assumptions!$D$33 -> 422.39232 | H54: =H36*Assumptions!$D$18*Assumptions!$D$33 -> 422.39232 | I54: =I36*Assumptions!$D$18*Assumptions!$D$33 -> 564.49344 | J54: =J36*Assumptions!$D$18*Assumptions!$D$33 -> 706.59456 | ... N54: =N36*Assumptions!$D$18*Assumptions!$D$33 -> 706.59456
A55: Band weight — Enterprise (accounts × tilt × propensity) | B55: weight | C55: =C37*Assumptions!$D$19*Assumptions!$D$34 -> 24.76992 | D55: =D37*Assumptions!$D$19*Assumptions!$D$34 -> 49.53984 | E55: =E37*Assumptions!$D$19*Assumptions!$D$34 -> 49.53984 | F55: =F37*Assumptions!$D$19*Assumptions!$D$34 -> 49.53984 | G55: =G37*Assumptions!$D$19*Assumptions!$D$34 -> 49.53984 | H55: =H37*Assumptions!$D$19*Assumptions!$D$34 -> 49.53984 | I55: =I37*Assumptions!$D$19*Assumptions!$D$34 -> 61.9248 | J55: =J37*Assumptions!$D$19*Assumptions!$D$34 -> 74.30976 | ... N55: =N37*Assumptions!$D$19*Assumptions!$D$34 -> 74.30976
A56: Opportunity mix — S (derived, not assumed) | B56: % | C56: =IFERROR(C53/(C53+C54+C55),0) -> 0.64110848 | D56: =IFERROR(D53/(D53+D54+D55),0) -> 0.64110848 | E56: =IFERROR(E53/(E53+E54+E55),0) -> 0.64110848 | F56: =IFERROR(F53/(F53+F54+F55),0) -> 0.64110848 | G56: =IFERROR(G53/(G53+G54+G55),0) -> 0.64110848 | H56: =IFERROR(H53/(H53+H54+H55),0) -> 0.64110848 | I56: =IFERROR(I53/(I53+I54+I55),0) -> 0.64723662 | J56: =IFERROR(J53/(J53+J54+J55),0) -> 0.65083968 | ... N56: =IFERROR(N53/(N53+N54+N55),0) -> 0.65083968
A57: Opportunity mix — M (derived, not assumed) | B57: % | C57: =IFERROR(C54/(C53+C54+C55),0) -> 0.32121783 | D57: =IFERROR(D54/(D53+D54+D55),0) -> 0.32121783 | E57: =IFERROR(E54/(E53+E54+E55),0) -> 0.32121783 | F57: =IFERROR(F54/(F53+F54+F55),0) -> 0.32121783 | G57: =IFERROR(G54/(G53+G54+G55),0) -> 0.32121783 | H57: =IFERROR(H54/(H53+H54+H55),0) -> 0.32121783 | I57: =IFERROR(I54/(I53+I54+I55),0) -> 0.31789083 | J57: =IFERROR(J54/(J53+J54+J55),0) -> 0.31593471 | ... N57: =IFERROR(N54/(N53+N54+N55),0) -> 0.31593471
A58: Opportunity mix — E (derived, not assumed) | B58: % | C58: =IFERROR(C55/(C53+C54+C55),0) -> 0.037673696 | D58: =IFERROR(D55/(D53+D54+D55),0) -> 0.037673696 | E58: =IFERROR(E55/(E53+E54+E55),0) -> 0.037673696 | F58: =IFERROR(F55/(F53+F54+F55),0) -> 0.037673696 | G58: =IFERROR(G55/(G53+G54+G55),0) -> 0.037673696 | H58: =IFERROR(H55/(H53+H54+H55),0) -> 0.037673696 | I58: =IFERROR(I55/(I53+I54+I55),0) -> 0.034872551 | J58: =IFERROR(J55/(J53+J54+J55),0) -> 0.033225606 | ... N58: =IFERROR(N55/(N53+N54+N55),0) -> 0.033225606
A59: Wins (demand) — SMB | B59: wins | C59: =IF(C27-Assumptions!$D$35<1,0,INDEX($C$52:$N$52,1,C27-Assumptions!$D$35)*INDEX($C$56:$N$56,1,C27-Assumptions!$D$35)*Assumptions!$D$32) -> 0 | D59: =IF(D27-Assumptions!$D$35<1,0,INDEX($C$52:$N$52,1,D27-Assumptions!$D$35)*INDEX($C$56:$N$56,1,D27-Assumptions!$D$35)*Assumptions!$D$32) -> 0.19900088 | E59: =IF(E27-Assumptions!$D$35<1,0,INDEX($C$52:$N$52,1,E27-Assumptions!$D$35)*INDEX($C$56:$N$56,1,E27-Assumptions!$D$35)*Assumptions!$D$32) -> 0.37509558 | F59: =IF(F27-Assumptions!$D$35<1,0,INDEX($C$52:$N$52,1,F27-Assumptions!$D$35)*INDEX($C$56:$N$56,1,F27-Assumptions!$D$35)*Assumptions!$D$32) -> 0.4318686 | G59: =IF(G27-Assumptions!$D$35<1,0,INDEX($C$52:$N$52,1,G27-Assumptions!$D$35)*INDEX($C$56:$N$56,1,G27-Assumptions!$D$35)*Assumptions!$D$32) -> 0.49105857 | H59: =IF(H27-Assumptions!$D$35<1,0,INDEX($C$52:$N$52,1,H27-Assumptions!$D$35)*INDEX($C$56:$N$56,1,H27-Assumptions!$D$35)*Assumptions!$D$32) -> 0.55237572 | I59: =IF(I27-Assumptions!$D$35<1,0,INDEX($C$52:$N$52,1,I27-Assumptions!$D$35)*INDEX($C$56:$N$56,1,I27-Assumptions!$D$35)*Assumptions!$D$32) -> 0.53863201 | J59: =IF(J27-Assumptions!$D$35<1,0,INDEX($C$52:$N$52,1,J27-Assumptions!$D$35)*INDEX($C$56:$N$56,1,J27-Assumptions!$D$35)*Assumptions!$D$32) -> 0.61859306 | ... N59: =IF(N27-Assumptions!$D$35<1,0,INDEX($C$52:$N$52,1,N27-Assumptions!$D$35)*INDEX($C$56:$N$56,1,N27-Assumptions!$D$35)*Assumptions!$D$32) -> 0.61869894 | P59: =SUM(C59:F59) -> 1.0059651 | Q59: =SUM(G59:J59) -> 2.2006594 | R59: =SUM(K59:N59) -> 2.5966297 | S59: =SUM(P59:R59) -> 5.8032541
A60: Wins (demand) — Mid-Market | B60: wins | C60: =IF(C27-Assumptions!$D$35<1,0,INDEX($C$52:$N$52,1,C27-Assumptions!$D$35)*INDEX($C$57:$N$57,1,C27-Assumptions!$D$35)*Assumptions!$D$32) -> 0 | D60: =IF(D27-Assumptions!$D$35<1,0,INDEX($C$52:$N$52,1,D27-Assumptions!$D$35)*INDEX($C$57:$N$57,1,D27-Assumptions!$D$35)*Assumptions!$D$32) -> 0.099706419 | E60: =IF(E27-Assumptions!$D$35<1,0,INDEX($C$52:$N$52,1,E27-Assumptions!$D$35)*INDEX($C$57:$N$57,1,E27-Assumptions!$D$35)*Assumptions!$D$32) -> 0.18793604 | F60: =IF(F27-Assumptions!$D$35<1,0,INDEX($C$52:$N$52,1,F27-Assumptions!$D$35)*INDEX($C$57:$N$57,1,F27-Assumptions!$D$35)*Assumptions!$D$32) -> 0.21638131 | G60: =IF(G27-Assumptions!$D$35<1,0,INDEX($C$52:$N$52,1,G27-Assumptions!$D$35)*INDEX($C$57:$N$57,1,G27-Assumptions!$D$35)*Assumptions!$D$32) -> 0.24603756 | H60: =IF(H27-Assumptions!$D$35<1,0,INDEX($C$52:$N$52,1,H27-Assumptions!$D$35)*INDEX($C$57:$N$57,1,H27-Assumptions!$D$35)*Assumptions!$D$32) -> 0.2767596 | I60: =IF(I27-Assumptions!$D$35<1,0,INDEX($C$52:$N$52,1,I27-Assumptions!$D$35)*INDEX($C$57:$N$57,1,I27-Assumptions!$D$35)*Assumptions!$D$32) -> 0.26987352 | J60: =IF(J27-Assumptions!$D$35<1,0,INDEX($C$52:$N$52,1,J27-Assumptions!$D$35)*INDEX($C$57:$N$57,1,J27-Assumptions!$D$35)*Assumptions!$D$32) -> 0.30382252 | ... N60: =IF(N27-Assumptions!$D$35<1,0,INDEX($C$52:$N$52,1,N27-Assumptions!$D$35)*INDEX($C$57:$N$57,1,N27-Assumptions!$D$35)*Assumptions!$D$32) -> 0.30033275 | P60: =SUM(C60:F60) -> 0.50402377 | Q60: =SUM(G60:J60) -> 1.0964932 | R60: =SUM(K60:N60) -> 1.2604724 | S60: =SUM(P60:R60) -> 2.8609893
